{"type": "FeatureCollection", "id": "http://imperium.ahlfeldt.se/places/8024", "name": "8024", "features": [{"type": "Feature", "id": "http://data.archaeology.link/data/ancientports/615", "label": "Castel Rossello & Puig Soutre, in Roussillon area, on R Tet", "dateprops": [], "properties": {"http://purl.org/dc/elements/1.1/created": ["2023"], "http://purl.org/dc/elements/1.1/creator": ["http://data.archaeology.link/data/spphaefen/arthur_de_graauw"], "http://www.ancientports.com/ont#date_min": ["-750"], "http://www.opengis.net/ont/geosparql#hasGeometry": ["http://data.archaeology.link/data/ancientports/615_geom"], "http://www.w3.org/1999/02/22-rdf-syntax-ns#type": ["http://www.ancientports.com/ont#Harbour"], "http://www.w3.org/2000/01/rdf-schema#label": ["Castel Rossello & Puig Soutre, in Roussillon area, on R Tet"], "http://www.w3.org/2004/02/skos/core#note": ["Ropiot (2003)"], "http://www.wikidata.org/prop/direct/P1584": ["http://pleiades.stoa.org/places/246348"], "http://www.wikidata.org/prop/direct/P17": ["France South"], "http://www.wikidata.org/prop/direct/P1936": ["http://imperium.ahlfeldt.se/places/8024"], "http://www.wikidata.org/prop/direct/P1958": ["https://www.trismegistos.org/place/20656"], "http://www.wikidata.org/prop/direct/P8068": ["https://topostext.org/place/427029URus"]}, "geometry": {"type": "Point", "coordinates": [2.94526, 42.70881]}}]}