{"type": "FeatureCollection", "id": "http://www.wikidata.org/entity/Q4459073", "name": "Thmuis", "features": [{"type": "Feature", "id": "http://data.archaeology.link/data/ancientports/3901", "name": "Tell Tima\u00ef", "dateprops": ["begin"], "properties": {"http://purl.org/dc/elements/1.1/creator": ["http://data.archaeology.link/data/spphaefen/arthur_de_graauw"], "http://purl.org/dc/terms/partOf": ["http://data.archaeology.link/data/ancientports/bib_deGrauw_2013_GeoDB"], "http://www.opengis.net/ont/geosparql#hasGeometry": ["http://data.archaeology.link/data/ancientports/3901_geom"], "http://www.w3.org/1999/02/22-rdf-syntax-ns#type": ["http://www.ancientports.com/ont#Harbour"], "http://www.w3.org/2000/01/rdf-schema#label": ["Tell Tima\u00ef"], "http://www.w3.org/2002/07/owl#sameAs": ["http://www.wikidata.org/entity/Q4459073"], "http://www.w3.org/2004/02/skos/core#note": ["Redford (1996)"], "http://www.w3.org/2006/time#hasTime": ["http://data.archaeology.link/data/ancientports/3901_foundation"], "http://www.wikidata.org/prop/direct/P1584": ["http://pleiades.stoa.org/places/727249"], "http://www.wikidata.org/prop/direct/P17": ["http://www.wikidata.org/entity/Q79"], "http://www.wikidata.org/prop/direct/P1936": ["http://imperium.ahlfeldt.se/places/21700"], "http://www.wikidata.org/prop/direct/P1958": ["https://www.trismegistos.org/place/2405"], "http://www.wikidata.org/prop/direct/P8068": ["https://topostext.org/place/309315UThm"], "begin": "-750"}, "geometry": {"type": "Point", "coordinates": [31.517, 30.939]}}], "numberMatched": 1, "numberReturned": 1, "bbox": [31.517, 30.939, 31.517, 30.939], "crs": "http://www.opengis.net/def/crs/EPSG/0/4326"}