{"type": "FeatureCollection", "id": "http://pleiades.stoa.org/places/648557", "name": "648557", "features": [{"type": "Feature", "id": "http://data.archaeology.link/data/ancientports/3346", "label": "Anamur", "dateprops": [], "properties": {"http://purl.org/dc/elements/1.1/created": ["2023"], "http://purl.org/dc/elements/1.1/creator": ["http://data.archaeology.link/data/spphaefen/arthur_de_graauw"], "http://www.ancientports.com/ont#date_min": ["-550"], "http://www.opengis.net/ont/geosparql#hasGeometry": ["http://data.archaeology.link/data/ancientports/3346_geom"], "http://www.w3.org/1999/02/22-rdf-syntax-ns#type": ["http://www.ancientports.com/ont#Harbour"], "http://www.w3.org/2000/01/rdf-schema#label": ["Anamur"], "http://www.w3.org/2002/07/owl#sameAs": ["http://www.wikidata.org/entity/Q529237"], "http://www.wikidata.org/prop/direct/P1584": ["http://pleiades.stoa.org/places/648557"], "http://www.wikidata.org/prop/direct/P17": ["TR: South"], "http://www.wikidata.org/prop/direct/P1936": ["http://imperium.ahlfeldt.se/places/21402"], "http://www.wikidata.org/prop/direct/P1958": ["https://www.trismegistos.org/place/8516"], "http://www.wikidata.org/prop/direct/P8068": ["https://topostext.org/place/360328PAne"]}, "geometry": {"type": "Point", "coordinates": [32.8029, 36.0223]}}]}