{"type": "FeatureCollection", "id": "http://pleiades.stoa.org/places/638817", "name": "638817", "features": [{"type": "Feature", "id": "http://data.archaeology.link/data/ancientports/3276", "name": "Inlice K\u00f6y\u00fc", "dateprops": ["begin"], "properties": {"http://purl.org/dc/elements/1.1/creator": ["http://data.archaeology.link/data/spphaefen/arthur_de_graauw"], "http://purl.org/dc/terms/partOf": ["http://data.archaeology.link/data/ancientports/bib_deGrauw_2013_GeoDB"], "http://www.opengis.net/ont/geosparql#hasGeometry": ["http://data.archaeology.link/data/ancientports/3276_geom"], "http://www.w3.org/1999/02/22-rdf-syntax-ns#type": ["http://www.ancientports.com/ont#Harbour"], "http://www.w3.org/2000/01/rdf-schema#label": ["Inlice K\u00f6y\u00fc"], "http://www.w3.org/2002/07/owl#sameAs": ["http://www.wikidata.org/entity/Q5208155"], "http://www.w3.org/2004/02/skos/core#note": ["Arnaud (2008)"], "http://www.w3.org/2006/time#hasTime": ["http://data.archaeology.link/data/ancientports/3276_foundation"], "http://www.wikidata.org/prop/direct/P1584": ["http://pleiades.stoa.org/places/638817"], "http://www.wikidata.org/prop/direct/P17": ["http://www.wikidata.org/entity/Q43"], "http://www.wikidata.org/prop/direct/P1936": ["http://imperium.ahlfeldt.se/places/22669"], "http://www.wikidata.org/prop/direct/P1958": ["https://www.trismegistos.org/place/34351"], "http://www.wikidata.org/prop/direct/P8068": ["https://topostext.org/place/368290UDai"], "begin": "-330"}, "geometry": {"type": "Point", "coordinates": [28.968, 36.729]}}], "numberMatched": 1, "numberReturned": 1, "bbox": [28.968, 36.729, 28.968, 36.729], "crs": "http://www.opengis.net/def/crs/OGC/1.3/CRS84"}