{"type": "FeatureCollection", "id": "http://www.wikidata.org/entity/Q18201614", "name": "Q18201614", "features": [{"type": "Feature", "id": "http://data.archaeology.link/data/ancientports/1829_1", "label": "Fortlet at Tripimeni Petra, near Vrasna", "properties": {"http://purl.org/dc/elements/1.1/created": ["2023"], "http://purl.org/dc/elements/1.1/creator": ["http://data.archaeology.link/data/spphaefen/arthur_de_graauw"], "http://www.ancientports.com/ont#date_min": ["-550"], "http://www.opengis.net/ont/geosparql#hasGeometry": ["http://data.archaeology.link/data/ancientports/1829_1_geom"], "http://www.w3.org/1999/02/22-rdf-syntax-ns#type": ["http://www.ancientports.com/ont#Harbour"], "http://www.w3.org/2000/01/rdf-schema#label": ["Fortlet at Tripimeni Petra, near Vrasna"], "http://www.w3.org/2002/07/owl#sameAs": ["http://www.wikidata.org/entity/Q18201614"], "http://www.wikidata.org/prop/direct/P17": ["GR: North-East"], "http://www.wikidata.org/prop/direct/P1958": ["https://www.trismegistos.org/place/33645"], "http://www.wikidata.org/prop/direct/P8068": ["https://topostext.org/place/407236FVra"]}, "geometry": {"type": "Point", "coordinates": [23.689, 40.7051]}}]}