{"type": "FeatureCollection", "id": "http://imperium.ahlfeldt.se/places/29100", "name": "29100", "features": [{"type": "Feature", "id": "http://data.archaeology.link/data/ancientports/2259", "name": "Metokhi, on the isle of Chios", "dateprops": ["begin"], "properties": {"http://purl.org/dc/elements/1.1/created": ["2023"], "http://purl.org/dc/elements/1.1/creator": ["http://data.archaeology.link/data/spphaefen/arthur_de_graauw"], "http://www.opengis.net/ont/geosparql#hasGeometry": ["http://data.archaeology.link/data/ancientports/2259_geom"], "http://www.w3.org/1999/02/22-rdf-syntax-ns#type": ["http://www.ancientports.com/ont#Harbour"], "http://www.w3.org/2000/01/rdf-schema#label": ["Metokhi, on the isle of Chios"], "http://www.w3.org/2006/time#hasTime": ["http://data.archaeology.link/data/ancientports/2259_foundation"], "http://www.wikidata.org/prop/direct/P1584": ["http://pleiades.stoa.org/places/550739"], "http://www.wikidata.org/prop/direct/P17": ["http://www.wikidata.org/entity/Q41"], "http://www.wikidata.org/prop/direct/P1936": ["http://imperium.ahlfeldt.se/places/29100"], "http://www.wikidata.org/prop/direct/P8068": ["https://topostext.org/place/384260XMet"], "begin": "-550"}, "geometry": {"type": "Point", "coordinates": [25.9589, 38.4263]}}]}