{"type": "FeatureCollection", "id": "http://pleiades.stoa.org/places/550839", "name": "550839", "features": [{"type": "Feature", "id": "http://data.archaeology.link/data/ancientports/3144", "label": "Liman Tepe, near Urla Iskele", "properties": {"http://purl.org/dc/elements/1.1/created": ["2023"], "http://purl.org/dc/elements/1.1/creator": ["http://data.archaeology.link/data/spphaefen/arthur_de_graauw"], "http://www.ancientports.com/ont#date_min": ["-3000"], "http://www.opengis.net/ont/geosparql#hasGeometry": ["http://data.archaeology.link/data/ancientports/3144_geom"], "http://www.w3.org/1999/02/22-rdf-syntax-ns#type": ["http://www.ancientports.com/ont#Harbour"], "http://www.w3.org/2000/01/rdf-schema#label": ["Liman Tepe, near Urla Iskele"], "http://www.w3.org/2002/07/owl#sameAs": ["http://www.wikidata.org/entity/Q536598"], "http://www.w3.org/2004/02/skos/core#note": ["Sahoglu (2011)"], "http://www.wikidata.org/prop/direct/P1584": ["http://pleiades.stoa.org/places/550839"], "http://www.wikidata.org/prop/direct/P17": ["TR: West"], "http://www.wikidata.org/prop/direct/P1958": ["https://www.trismegistos.org/place/34304"]}, "geometry": {"type": "Point", "coordinates": [26.77518, 38.36431]}}]}