{"type": "FeatureCollection", "id": "http://pleiades.stoa.org/places/471942", "name": "471942", "features": [{"type": "Feature", "id": "http://data.archaeology.link/data/ancientports/771", "label": "Porto Malfatano", "properties": {"http://purl.org/dc/elements/1.1/created": ["2023"], "http://purl.org/dc/elements/1.1/creator": ["http://data.archaeology.link/data/spphaefen/arthur_de_graauw"], "http://www.opengis.net/ont/geosparql#hasGeometry": ["http://data.archaeology.link/data/ancientports/771_geom"], "http://www.w3.org/1999/02/22-rdf-syntax-ns#type": ["http://www.ancientports.com/ont#Harbour"], "http://www.w3.org/2000/01/rdf-schema#label": ["Porto Malfatano"], "http://www.wikidata.org/prop/direct/P1584": ["http://pleiades.stoa.org/places/471942"], "http://www.wikidata.org/prop/direct/P17": ["Italy Sardinia"]}, "geometry": {"type": "Point", "coordinates": [8.8031, 38.89873]}}, {"type": "Feature", "id": "http://data.archaeology.link/data/ancientports/772", "label": "Porto Malfatano, submerged breakwater on NE side of Capo Malfatano", "properties": {"http://purl.org/dc/elements/1.1/created": ["2023"], "http://purl.org/dc/elements/1.1/creator": ["http://data.archaeology.link/data/spphaefen/arthur_de_graauw"], "http://www.opengis.net/ont/geosparql#hasGeometry": ["http://data.archaeology.link/data/ancientports/772_geom"], "http://www.w3.org/1999/02/22-rdf-syntax-ns#type": ["http://www.ancientports.com/ont#Harbour"], "http://www.w3.org/2000/01/rdf-schema#label": ["Porto Malfatano, submerged breakwater on NE side of Capo Malfatano"], "http://www.wikidata.org/prop/direct/P1584": ["http://pleiades.stoa.org/places/471942"], "http://www.wikidata.org/prop/direct/P17": ["Italy Sardinia"]}, "geometry": {"type": "Point", "coordinates": [8.80336, 38.88787]}}]}