{"type": "FeatureCollection", "id": "https://topostext.org/place/300326UArs", "name": "300326UArs", "features": [{"type": "Feature", "id": "http://data.archaeology.link/data/ancientports/3892_4", "label": "Mahattat al Kibrit, Kabret, near Chalouf, Shaluf, between both Bitter Lakes, 3rd stela of Darius on Nile to Red Sea canal, Ptolemy locates Arsinoe at 20' of latitude north of Clysma", "properties": {"http://purl.org/dc/elements/1.1/created": ["2023"], "http://purl.org/dc/elements/1.1/creator": ["http://data.archaeology.link/data/spphaefen/arthur_de_graauw"], "http://www.ancientports.com/ont#date_min": ["-500"], "http://www.opengis.net/ont/geosparql#hasGeometry": ["http://data.archaeology.link/data/ancientports/3892_4_geom"], "http://www.w3.org/1999/02/22-rdf-syntax-ns#type": ["http://www.ancientports.com/ont#Harbour"], "http://www.w3.org/2000/01/rdf-schema#label": ["Mahattat al Kibrit, Kabret, near Chalouf, Shaluf, between both Bitter Lakes, 3rd stela of Darius on Nile to Red Sea canal, Ptolemy locates Arsinoe at 20' of latitude north of Clysma"], "http://www.w3.org/2002/07/owl#sameAs": ["http://www.wikidata.org/entity/Q3623994"], "http://www.w3.org/2004/02/skos/core#note": ["Bruyere (1966)"], "http://www.wikidata.org/prop/direct/P1584": ["http://pleiades.stoa.org/places/727101"], "http://www.wikidata.org/prop/direct/P17": ["Egypt: Med Sea"], "http://www.wikidata.org/prop/direct/P1936": ["http://imperium.ahlfeldt.se/places/21705"], "http://www.wikidata.org/prop/direct/P1958": ["https://www.trismegistos.org/place/2794"], "http://www.wikidata.org/prop/direct/P8068": ["https://topostext.org/place/300326UArs"]}, "geometry": {"type": "Point", "coordinates": [32.501, 30.259]}}]}