{"type": "FeatureCollection", "id": "http://imperium.ahlfeldt.se/places/27941", "name": "27941", "features": [{"type": "Feature", "id": "http://data.archaeology.link/data/ancientports/2567", "label": "Mezhvodnoye", "dateprops": ["http://purl.org/dc/elements/1.1/created", "http://www.ancientports.com/ont#date_min"], "properties": {"http://purl.org/dc/elements/1.1/created": ["2023"], "http://purl.org/dc/elements/1.1/creator": ["http://data.archaeology.link/data/spphaefen/arthur_de_graauw"], "http://www.ancientports.com/ont#date_min": ["-550"], "http://www.opengis.net/ont/geosparql#hasGeometry": ["http://data.archaeology.link/data/ancientports/2567_geom"], "http://www.w3.org/1999/02/22-rdf-syntax-ns#type": ["http://www.ancientports.com/ont#Harbour"], "http://www.w3.org/2000/01/rdf-schema#label": ["Mezhvodnoye"], "http://www.w3.org/2004/02/skos/core#note": ["Tsetskhladze (1998)"], "http://www.wikidata.org/prop/direct/P1584": ["http://pleiades.stoa.org/places/226687"], "http://www.wikidata.org/prop/direct/P17": ["Ukraine Black S."], "http://www.wikidata.org/prop/direct/P1936": ["http://imperium.ahlfeldt.se/places/27941"]}, "geometry": {"type": "Point", "coordinates": [32.84, 45.58]}}]}