{"type": "FeatureCollection", "id": "http://www.wikidata.org/entity/Q2891816", "name": "Q2891816", "features": [{"type": "Feature", "id": "http://data.archaeology.link/data/ancientports/3815_1", "label": "Bardak-Siah Palace, on R Dalaki, near Borazjan, inland palace mentioned by Arrian", "dateprops": [], "properties": {"http://purl.org/dc/elements/1.1/created": ["2023"], "http://purl.org/dc/elements/1.1/creator": ["http://data.archaeology.link/data/spphaefen/arthur_de_graauw"], "http://purl.org/dc/terms/isReferencedBy": ["http://data.archaeology.link/data/ancientports/bib_Carter_2006_Bushehr", "https://en.wikipedia.org/wiki/Temukan"], "http://www.opengis.net/ont/geosparql#hasGeometry": ["http://data.archaeology.link/data/ancientports/3815_1_geom"], "http://www.w3.org/1999/02/22-rdf-syntax-ns#type": ["http://www.ancientports.com/ont#Harbour"], "http://www.w3.org/2000/01/rdf-schema#label": ["Bardak-Siah Palace, on R Dalaki, near Borazjan, inland palace mentioned by Arrian"], "http://www.w3.org/2002/07/owl#sameAs": ["http://www.wikidata.org/entity/Q2891816"], "http://www.w3.org/2004/02/skos/core#note": ["Potts (2022)"], "http://www.w3.org/2006/time#hasTime": ["http://data.archaeology.link/data/ancientports/3815_1_foundation"], "http://www.wikidata.org/prop/direct/P1584": ["http://pleiades.stoa.org/places/922626"], "http://www.wikidata.org/prop/direct/P17": ["Gulf"]}, "geometry": {"type": "Point", "coordinates": [51.1096, 29.3541]}}]}