{"type": "FeatureCollection", "id": "http://pleiades.stoa.org/places/540972", "name": "540972", "features": [{"type": "Feature", "id": "http://data.archaeology.link/data/ancientports/1595", "label": "Skaloma, near Klima Efpalio", "properties": {"http://purl.org/dc/elements/1.1/created": ["2023"], "http://purl.org/dc/elements/1.1/creator": ["http://data.archaeology.link/data/spphaefen/arthur_de_graauw"], "http://www.ancientports.com/ont#date_min": ["-550"], "http://www.opengis.net/ont/geosparql#hasGeometry": ["http://data.archaeology.link/data/ancientports/1595_geom"], "http://www.w3.org/1999/02/22-rdf-syntax-ns#type": ["http://www.ancientports.com/ont#Harbour"], "http://www.w3.org/2000/01/rdf-schema#label": ["Skaloma, near Klima Efpalio"], "http://www.w3.org/2002/07/owl#sameAs": ["http://www.wikidata.org/entity/Q11939252"], "http://www.wikidata.org/prop/direct/P1584": ["http://pleiades.stoa.org/places/540972"], "http://www.wikidata.org/prop/direct/P17": ["GR: North-West"]}, "geometry": {"type": "Point", "coordinates": [21.9936, 38.4003]}}]}