{"type": "FeatureCollection", "id": "https://topostext.org/place/365306PPha", "name": "365306PPha", "features": [{"type": "Feature", "id": "http://data.archaeology.link/data/ancientports/3314", "label": "Fasilis Harabeleri, near Tekirova", "dateprops": ["http://purl.org/dc/elements/1.1/created"], "properties": {"http://purl.org/dc/elements/1.1/created": ["2023"], "http://purl.org/dc/elements/1.1/creator": ["http://data.archaeology.link/data/spphaefen/arthur_de_graauw"], "http://www.opengis.net/ont/geosparql#hasGeometry": ["http://data.archaeology.link/data/ancientports/3314_geom"], "http://www.w3.org/1999/02/22-rdf-syntax-ns#type": ["http://www.ancientports.com/ont#Quay", "http://www.ancientports.com/ont#Warehouse"], "http://www.w3.org/2000/01/rdf-schema#label": ["Fasilis Harabeleri, near Tekirova"], "http://www.w3.org/2002/07/owl#sameAs": ["http://www.wikidata.org/entity/Q595329"], "http://www.w3.org/2004/02/skos/core#note": ["Arslan (2015)"], "http://www.w3.org/2006/time#hasTime": ["http://data.archaeology.link/data/ancientports/3314_foundation"], "http://www.wikidata.org/prop/direct/P1584": ["http://pleiades.stoa.org/places/639051"], "http://www.wikidata.org/prop/direct/P17": ["TR: South"], "http://www.wikidata.org/prop/direct/P1936": ["http://imperium.ahlfeldt.se/places/21436"], "http://www.wikidata.org/prop/direct/P1958": ["https://www.trismegistos.org/place/1753"], "http://www.wikidata.org/prop/direct/P8068": ["https://topostext.org/place/365306PPha"]}, "geometry": {"type": "Point", "coordinates": [30.5531, 36.5251]}}]}