{"type": "FeatureCollection", "id": "http://www.wikidata.org/entity/Q987304", "name": "Port-en-Bessin-Huppain", "features": [{"type": "Feature", "id": "http://data.archaeology.link/data/ancientports/534", "name": "Port-en-Bessin-Huppain", "dateprops": [], "properties": {"http://purl.org/dc/elements/1.1/creator": ["http://data.archaeology.link/data/spphaefen/arthur_de_graauw"], "http://purl.org/dc/terms/isReferencedBy": ["http://www.inrap.fr/archeologie-preventive/Actualites/Communiques-de-presse/p-16145-Le-passe-antique-de-Port-en-Bessin-Huppain-revele-par-une-fouille-archeologique.htm"], "http://purl.org/dc/terms/partOf": ["http://data.archaeology.link/data/ancientports/bib_deGrauw_2013_GeoDB"], "http://www.opengis.net/ont/geosparql#hasGeometry": ["http://data.archaeology.link/data/ancientports/534_geom"], "http://www.w3.org/1999/02/22-rdf-syntax-ns#type": ["http://www.ancientports.com/ont#Harbour"], "http://www.w3.org/2000/01/rdf-schema#label": ["Port-en-Bessin-Huppain"], "http://www.w3.org/2002/07/owl#sameAs": ["http://www.wikidata.org/entity/Q987304"], "http://www.wikidata.org/prop/direct/P17": ["http://www.wikidata.org/entity/Q142"], "begin": ""}, "geometry": {"type": "Point", "coordinates": [-0.76, 49.34]}}]}