{"type": "FeatureCollection", "id": "https://www.trismegistos.org/place/2134", "name": "2134", "features": [{"type": "Feature", "id": "http://data.archaeology.link/data/ancientports/3458", "label": "Sa\u00efda, isle of Zire, with several quarries", "properties": {"http://purl.org/dc/elements/1.1/created": ["2023"], "http://purl.org/dc/elements/1.1/creator": ["http://data.archaeology.link/data/spphaefen/arthur_de_graauw"], "http://www.ancientports.com/ont#date_min": ["-750"], "http://www.opengis.net/ont/geosparql#hasGeometry": ["http://data.archaeology.link/data/ancientports/3458_geom"], "http://www.w3.org/1999/02/22-rdf-syntax-ns#type": ["http://www.ancientports.com/ont#Harbour"], "http://www.w3.org/2000/01/rdf-schema#label": ["Sa\u00efda, isle of Zire, with several quarries"], "http://www.w3.org/2002/07/owl#sameAs": ["http://www.wikidata.org/entity/Q163490"], "http://www.wikidata.org/prop/direct/P1584": ["http://pleiades.stoa.org/places/678393"], "http://www.wikidata.org/prop/direct/P17": ["Lebanon"], "http://www.wikidata.org/prop/direct/P1958": ["https://www.trismegistos.org/place/2134"]}, "geometry": {"type": "Point", "coordinates": [35.36802, 33.57276]}}, {"type": "Feature", "id": "http://data.archaeology.link/data/ancientports/3459", "label": "Sa\u00efda, Saida", "properties": {"http://purl.org/dc/elements/1.1/created": ["2023"], "http://purl.org/dc/elements/1.1/creator": ["http://data.archaeology.link/data/spphaefen/arthur_de_graauw"], "http://www.ancientports.com/ont#date_min": ["-3000"], "http://www.opengis.net/ont/geosparql#hasGeometry": ["http://data.archaeology.link/data/ancientports/3459_geom"], "http://www.w3.org/1999/02/22-rdf-syntax-ns#type": ["http://www.ancientports.com/ont#Harbour"], "http://www.w3.org/2000/01/rdf-schema#label": ["Sa\u00efda, Saida"], "http://www.w3.org/2002/07/owl#sameAs": ["http://www.wikidata.org/entity/Q163490"], "http://www.wikidata.org/prop/direct/P1584": ["http://pleiades.stoa.org/places/678393"], "http://www.wikidata.org/prop/direct/P17": ["Lebanon"], "http://www.wikidata.org/prop/direct/P1958": ["https://www.trismegistos.org/place/2134"]}, "geometry": {"type": "Point", "coordinates": [35.36828, 33.5645]}}, {"type": "Feature", "id": "http://data.archaeology.link/data/ancientports/3460", "label": "Sa\u00efda, quarry on rocky spit on western seafront of the port", "properties": {"http://purl.org/dc/elements/1.1/created": ["2023"], "http://purl.org/dc/elements/1.1/creator": ["http://data.archaeology.link/data/spphaefen/arthur_de_graauw"], "http://www.ancientports.com/ont#date_min": ["-750"], "http://www.opengis.net/ont/geosparql#hasGeometry": ["http://data.archaeology.link/data/ancientports/3460_geom"], "http://www.w3.org/1999/02/22-rdf-syntax-ns#type": ["http://www.ancientports.com/ont#Harbour"], "http://www.w3.org/2000/01/rdf-schema#label": ["Sa\u00efda, quarry on rocky spit on western seafront of the port"], "http://www.w3.org/2002/07/owl#sameAs": ["http://www.wikidata.org/entity/Q163490"], "http://www.wikidata.org/prop/direct/P1584": ["http://pleiades.stoa.org/places/678393"], "http://www.wikidata.org/prop/direct/P17": ["Lebanon"], "http://www.wikidata.org/prop/direct/P1958": ["https://www.trismegistos.org/place/2134"]}, "geometry": {"type": "Point", "coordinates": [35.36688, 33.56439]}}]}