{"type": "FeatureCollection", "id": "https://pleiades.stoa.org/places/471971", "name": "471971", "features": [{"type": "Feature", "id": "http://data.archaeology.link/data/ancientports/781", "label": "Temple of Antas, near Fluminimaggiore, Iglesiente mining area with possible export at Portixeddu", "dateprops": [], "properties": {"http://purl.org/dc/elements/1.1/created": ["2023"], "http://purl.org/dc/elements/1.1/creator": ["http://data.archaeology.link/data/spphaefen/arthur_de_graauw"], "http://www.ancientports.com/ont#date_min": ["-500"], "http://www.opengis.net/ont/geosparql#hasGeometry": ["http://data.archaeology.link/data/ancientports/781_geom"], "http://www.w3.org/1999/02/22-rdf-syntax-ns#type": ["http://www.ancientports.com/ont#Harbour"], "http://www.w3.org/2000/01/rdf-schema#label": ["Temple of Antas, near Fluminimaggiore, Iglesiente mining area with possible export at Portixeddu"], "http://www.w3.org/2002/07/owl#sameAs": ["http://www.wikidata.org/entity/Q689104"], "http://www.w3.org/2004/02/skos/core#note": ["Moscati (1969)"], "http://www.wikidata.org/prop/direct/P1584": ["https://pleiades.stoa.org/places/471971"], "http://www.wikidata.org/prop/direct/P17": ["Italy Sardinia"]}, "geometry": {"type": "Point", "coordinates": [8.5002, 39.394]}}]}