{"type": "FeatureCollection", "id": "http://pleiades.stoa.org/places/599983", "name": "599983", "features": [{"type": "Feature", "id": "http://data.archaeology.link/data/ancientports/3247", "label": "S\u00f6g\u00fct Kisseb\u00fck\u00fc", "dateprops": [], "properties": {"http://purl.org/dc/elements/1.1/created": ["2023"], "http://purl.org/dc/elements/1.1/creator": ["http://data.archaeology.link/data/spphaefen/arthur_de_graauw"], "http://www.ancientports.com/ont#date_min": ["-330"], "http://www.opengis.net/ont/geosparql#hasGeometry": ["http://data.archaeology.link/data/ancientports/3247_geom"], "http://www.w3.org/1999/02/22-rdf-syntax-ns#type": ["http://www.ancientports.com/ont#Harbour"], "http://www.w3.org/2000/01/rdf-schema#label": ["S\u00f6g\u00fct Kisseb\u00fck\u00fc"], "http://www.w3.org/2002/07/owl#sameAs": ["http://www.wikidata.org/entity/Q65066088"], "http://www.w3.org/2004/02/skos/core#note": ["Arnaud (2008)", "Held (2021)"], "http://www.wikidata.org/prop/direct/P1584": ["http://pleiades.stoa.org/places/599983"], "http://www.wikidata.org/prop/direct/P17": ["TR: South"], "http://www.wikidata.org/prop/direct/P1936": ["http://imperium.ahlfeldt.se/places/30808"], "http://www.wikidata.org/prop/direct/P1958": ["https://www.trismegistos.org/place/34234"], "http://www.wikidata.org/prop/direct/P8068": ["https://topostext.org/place/366281UThy"]}, "geometry": {"type": "Point", "coordinates": [28.0781, 36.6599]}}, {"type": "Feature", "id": "http://data.archaeology.link/data/ancientports/3247_1", "label": "S\u00f6g\u00fct Saranda", "dateprops": [], "properties": {"http://purl.org/dc/elements/1.1/created": ["2023"], "http://purl.org/dc/elements/1.1/creator": ["http://data.archaeology.link/data/spphaefen/arthur_de_graauw"], "http://www.opengis.net/ont/geosparql#hasGeometry": ["http://data.archaeology.link/data/ancientports/3247_1_geom"], "http://www.w3.org/1999/02/22-rdf-syntax-ns#type": ["http://www.ancientports.com/ont#Harbour"], "http://www.w3.org/2000/01/rdf-schema#label": ["S\u00f6g\u00fct Saranda"], "http://www.w3.org/2002/07/owl#sameAs": ["http://www.wikidata.org/entity/Q65066088"], "http://www.w3.org/2004/02/skos/core#note": ["Held (2021)", "\u00d6ztas (2020)"], "http://www.wikidata.org/prop/direct/P1584": ["http://pleiades.stoa.org/places/599983"], "http://www.wikidata.org/prop/direct/P17": ["TR: South"], "http://www.wikidata.org/prop/direct/P1936": ["http://imperium.ahlfeldt.se/places/30808"], "http://www.wikidata.org/prop/direct/P1958": ["https://www.trismegistos.org/place/34234"], "http://www.wikidata.org/prop/direct/P8068": ["https://topostext.org/place/366281UThy"]}, "geometry": {"type": "Point", "coordinates": [28.0907, 36.6508]}}]}