{"type": "FeatureCollection", "id": "http://pleiades.stoa.org/places/373916", "name": "373916", "features": [{"type": "Feature", "id": "http://data.archaeology.link/data/ancientports/3996", "name": "Ras Bu Meddad, Emilia resort, 8 km west of Derna", "dateprops": [], "properties": {"http://purl.org/dc/elements/1.1/created": ["2023"], "http://purl.org/dc/elements/1.1/creator": ["http://data.archaeology.link/data/spphaefen/arthur_de_graauw"], "http://www.opengis.net/ont/geosparql#hasGeometry": ["http://data.archaeology.link/data/ancientports/3996_geom"], "http://www.w3.org/1999/02/22-rdf-syntax-ns#type": ["http://www.ancientports.com/ont#Harbour"], "http://www.w3.org/2000/01/rdf-schema#label": ["Ras Bu Meddad, Emilia resort, 8 km west of Derna"], "http://www.wikidata.org/prop/direct/P1584": ["http://pleiades.stoa.org/places/373916"], "http://www.wikidata.org/prop/direct/P17": ["http://www.wikidata.org/entity/Q1016"], "http://www.wikidata.org/prop/direct/P1936": ["http://imperium.ahlfeldt.se/places/41001"], "begin": ""}, "geometry": {"type": "Point", "coordinates": [22.564, 32.7933]}}]}