{"type": "FeatureCollection", "id": "http://imperium.ahlfeldt.se/places/30440", "name": "30440", "features": [{"type": "Feature", "id": "http://data.archaeology.link/data/ancientports/1078", "label": "Le Castella ", "dateprops": ["http://purl.org/dc/elements/1.1/created", "http://www.ancientports.com/ont#date_min"], "properties": {"http://purl.org/dc/elements/1.1/created": ["2023"], "http://purl.org/dc/elements/1.1/creator": ["http://data.archaeology.link/data/spphaefen/arthur_de_graauw"], "http://www.ancientports.com/ont#date_min": ["-330"], "http://www.opengis.net/ont/geosparql#hasGeometry": ["http://data.archaeology.link/data/ancientports/1078_geom"], "http://www.w3.org/1999/02/22-rdf-syntax-ns#type": ["http://www.ancientports.com/ont#Harbour"], "http://www.w3.org/2000/01/rdf-schema#label": ["Le Castella "], "http://www.wikidata.org/prop/direct/P1584": ["http://pleiades.stoa.org/places/452289"], "http://www.wikidata.org/prop/direct/P17": ["Italy West"], "http://www.wikidata.org/prop/direct/P1936": ["http://imperium.ahlfeldt.se/places/30440"]}, "geometry": {"type": "Point", "coordinates": [17.02369, 38.9034]}}]}