{"type": "FeatureCollection", "id": "https://www.trismegistos.org/place/1662", "name": "1662", "features": [{"type": "Feature", "id": "http://data.archaeology.link/data/ancientports/3872", "label": "Tell el-Farama", "properties": {"http://purl.org/dc/elements/1.1/created": ["2023"], "http://purl.org/dc/elements/1.1/creator": ["http://data.archaeology.link/data/spphaefen/arthur_de_graauw"], "http://www.ancientports.com/ont#date_min": ["-750"], "http://www.opengis.net/ont/geosparql#hasGeometry": ["http://data.archaeology.link/data/ancientports/3872_geom"], "http://www.w3.org/1999/02/22-rdf-syntax-ns#type": ["http://www.ancientports.com/ont#Harbour"], "http://www.w3.org/2000/01/rdf-schema#label": ["Tell el-Farama"], "http://www.w3.org/2002/07/owl#sameAs": ["http://www.wikidata.org/entity/Q1145715"], "http://www.wikidata.org/prop/direct/P1584": ["http://pleiades.stoa.org/places/727192"], "http://www.wikidata.org/prop/direct/P17": ["Egypt: Med Sea"], "http://www.wikidata.org/prop/direct/P1958": ["https://www.trismegistos.org/place/1662"]}, "geometry": {"type": "Point", "coordinates": [32.5496, 31.0377]}}]}