{"type": "FeatureCollection", "id": "http://pleiades.stoa.org/places/639166", "name": "639166", "features": [{"type": "Feature", "id": "http://data.archaeology.link/data/ancientports/3288", "label": "possibly south of Letoon, at ancient outlet of R Esin Cayi", "properties": {"http://purl.org/dc/elements/1.1/created": ["2023"], "http://purl.org/dc/elements/1.1/creator": ["http://data.archaeology.link/data/spphaefen/arthur_de_graauw"], "http://www.ancientports.com/ont#date_min": ["-550"], "http://www.opengis.net/ont/geosparql#hasGeometry": ["http://data.archaeology.link/data/ancientports/3288_geom"], "http://www.w3.org/1999/02/22-rdf-syntax-ns#type": ["http://www.ancientports.com/ont#Harbour"], "http://www.w3.org/2000/01/rdf-schema#label": ["possibly south of Letoon, at ancient outlet of R Esin Cayi"], "http://www.w3.org/2002/07/owl#sameAs": ["http://www.wikidata.org/entity/Q464936"], "http://www.w3.org/2004/02/skos/core#note": ["Arnaud (2008)"], "http://www.wikidata.org/prop/direct/P1584": ["http://pleiades.stoa.org/places/639166"], "http://www.wikidata.org/prop/direct/P17": ["TR: South"], "http://www.wikidata.org/prop/direct/P1936": ["http://imperium.ahlfeldt.se/places/21462"], "http://www.wikidata.org/prop/direct/P1958": ["https://www.trismegistos.org/place/2504"], "http://www.wikidata.org/prop/direct/P8068": ["https://topostext.org/place/364293PXan"]}, "geometry": {"type": "Point", "coordinates": [29.285, 36.31]}}]}