{"type": "FeatureCollection", "id": "http://www.wikidata.org/entity/Q1806812", "name": "Q1806812", "features": [{"type": "Feature", "id": "http://data.archaeology.link/data/ancientports/638", "label": "Lattes, on R Lez, with ancient lighthouse", "properties": {"http://purl.org/dc/elements/1.1/created": ["2023"], "http://purl.org/dc/elements/1.1/creator": ["http://data.archaeology.link/data/spphaefen/arthur_de_graauw"], "http://www.ancientports.com/ont#date_min": ["-550"], "http://www.opengis.net/ont/geosparql#hasGeometry": ["http://data.archaeology.link/data/ancientports/638_geom"], "http://www.w3.org/1999/02/22-rdf-syntax-ns#type": ["http://www.ancientports.com/ont#Quay", "http://www.ancientports.com/ont#Lighthouse", "http://www.ancientports.com/ont#Warehouse"], "http://www.w3.org/2000/01/rdf-schema#label": ["Lattes, on R Lez, with ancient lighthouse"], "http://www.w3.org/2002/07/owl#sameAs": ["http://www.wikidata.org/entity/Q1806812"], "http://www.w3.org/2004/02/skos/core#note": ["Piques (2021)"], "http://www.wikidata.org/prop/direct/P1584": ["http://pleiades.stoa.org/places/148107"], "http://www.wikidata.org/prop/direct/P17": ["France South"], "http://www.wikidata.org/prop/direct/P1936": ["http://imperium.ahlfeldt.se/places/17516"], "http://www.wikidata.org/prop/direct/P1958": ["https://www.trismegistos.org/place/21494"]}, "geometry": {"type": "Point", "coordinates": [3.907, 43.56462]}}]}