{"type": "FeatureCollection", "id": "http://imperium.ahlfeldt.se/places/31379", "name": "31379", "features": [{"type": "Feature", "id": "http://data.archaeology.link/data/ancientports/2389", "label": "Degirmenalti ", "dateprops": [], "properties": {"http://purl.org/dc/elements/1.1/created": ["2023"], "http://purl.org/dc/elements/1.1/creator": ["http://data.archaeology.link/data/spphaefen/arthur_de_graauw"], "http://www.ancientports.com/ont#date_min": ["-750"], "http://www.opengis.net/ont/geosparql#hasGeometry": ["http://data.archaeology.link/data/ancientports/2389_geom"], "http://www.w3.org/1999/02/22-rdf-syntax-ns#type": ["http://www.ancientports.com/ont#Harbour"], "http://www.w3.org/2000/01/rdf-schema#label": ["Degirmenalti "], "http://www.w3.org/2004/02/skos/core#note": ["K\u00fclzer (2011)"], "http://www.wikidata.org/prop/direct/P1584": ["http://pleiades.stoa.org/places/511228"], "http://www.wikidata.org/prop/direct/P17": ["TR: Marmara N"], "http://www.wikidata.org/prop/direct/P1936": ["http://imperium.ahlfeldt.se/places/31379"]}, "geometry": {"type": "Point", "coordinates": [27.56231, 40.97798]}}]}