{"type": "FeatureCollection", "id": "http://pleiades.stoa.org/places/314845", "name": "314845", "features": [{"type": "Feature", "id": "http://data.archaeology.link/data/ancientports/4171", "label": "near Hammam Lif", "dateprops": ["http://purl.org/dc/elements/1.1/created"], "properties": {"http://purl.org/dc/elements/1.1/created": ["2023"], "http://purl.org/dc/elements/1.1/creator": ["http://data.archaeology.link/data/spphaefen/arthur_de_graauw"], "http://www.opengis.net/ont/geosparql#hasGeometry": ["http://data.archaeology.link/data/ancientports/4171_geom"], "http://www.w3.org/1999/02/22-rdf-syntax-ns#type": ["http://www.ancientports.com/ont#Harbour"], "http://www.w3.org/2000/01/rdf-schema#label": ["near Hammam Lif"], "http://www.w3.org/2002/07/owl#sameAs": ["http://www.wikidata.org/entity/Q1573684"], "http://www.w3.org/2006/time#hasTime": ["http://data.archaeology.link/data/ancientports/4171_foundation"], "http://www.wikidata.org/prop/direct/P1584": ["http://pleiades.stoa.org/places/314845"], "http://www.wikidata.org/prop/direct/P17": ["http://www.wikidata.org/entity/Q948"], "http://www.wikidata.org/prop/direct/P1936": ["http://imperium.ahlfeldt.se/places/22086"]}, "geometry": {"type": "Point", "coordinates": [10.3464, 36.7323]}}]}