{"type": "FeatureCollection", "id": "http://pleiades.stoa.org/places/599771", "name": "599771", "features": [{"type": "Feature", "id": "http://data.archaeology.link/data/ancientports/2152", "label": "Livadi, on the isle of Astypalaia, Stampalia ", "dateprops": ["http://purl.org/dc/elements/1.1/created", "http://www.ancientports.com/ont#date_min"], "properties": {"http://purl.org/dc/elements/1.1/created": ["2023"], "http://purl.org/dc/elements/1.1/creator": ["http://data.archaeology.link/data/spphaefen/arthur_de_graauw"], "http://www.ancientports.com/ont#date_min": ["3001"], "http://www.opengis.net/ont/geosparql#hasGeometry": ["http://data.archaeology.link/data/ancientports/2152_geom"], "http://www.w3.org/1999/02/22-rdf-syntax-ns#type": ["http://www.ancientports.com/ont#Harbour"], "http://www.w3.org/2000/01/rdf-schema#label": ["Livadi, on the isle of Astypalaia, Stampalia "], "http://www.wikidata.org/prop/direct/P1584": ["http://pleiades.stoa.org/places/599771"], "http://www.wikidata.org/prop/direct/P17": ["GR: Cyclades Isl."], "http://www.wikidata.org/prop/direct/P1936": ["http://imperium.ahlfeldt.se/places/28998"]}, "geometry": {"type": "Point", "coordinates": [26.34539, 36.53945]}}]}