{"type": "FeatureCollection", "id": "https://topostext.org/place/377240FShS", "name": "377240FShS", "features": [{"type": "Feature", "id": "http://data.archaeology.link/data/ancientports/1642", "name": "Sounion, most southerly point of the Attic, with steep slipway", "dateprops": ["begin"], "properties": {"http://purl.org/dc/elements/1.1/creator": ["http://data.archaeology.link/data/spphaefen/arthur_de_graauw"], "http://purl.org/dc/terms/partOf": ["http://data.archaeology.link/data/ancientports/bib_deGrauw_2013_GeoDB"], "http://www.opengis.net/ont/geosparql#hasGeometry": ["http://data.archaeology.link/data/ancientports/1642_geom"], "http://www.w3.org/1999/02/22-rdf-syntax-ns#type": ["http://www.ancientports.com/ont#Shipshed", "http://www.ancientports.com/ont#Slipway"], "http://www.w3.org/2000/01/rdf-schema#label": ["Sounion, most southerly point of the Attic, with steep slipway"], "http://www.w3.org/2002/07/owl#sameAs": ["http://www.wikidata.org/entity/Q1136637"], "http://www.w3.org/2004/02/skos/core#note": ["Laoupi (2007)"], "http://www.w3.org/2006/time#hasTime": ["http://data.archaeology.link/data/ancientports/1642_foundation"], "http://www.wikidata.org/prop/direct/P1584": ["http://pleiades.stoa.org/places/599943"], "http://www.wikidata.org/prop/direct/P17": ["http://www.wikidata.org/entity/Q41"], "http://www.wikidata.org/prop/direct/P1936": ["http://imperium.ahlfeldt.se/places/41362"], "http://www.wikidata.org/prop/direct/P1958": ["https://www.trismegistos.org/place/37804"], "http://www.wikidata.org/prop/direct/P8068": ["https://topostext.org/place/377240FShS"], "begin": "-3000"}, "geometry": {"type": "Point", "coordinates": [24.0227, 37.6524]}}]}