{"type": "FeatureCollection", "id": "https://topostext.org/place/363293BPaL", "name": "363293BPaL", "features": [{"type": "Feature", "id": "http://data.archaeology.link/data/ancientports/3289", "label": "Tepecik hill, near Gelemis, with ancient lighthouse", "properties": {"http://purl.org/dc/elements/1.1/created": ["2023"], "http://purl.org/dc/elements/1.1/creator": ["http://data.archaeology.link/data/spphaefen/arthur_de_graauw"], "http://www.ancientports.com/ont#date_min": ["-550"], "http://www.opengis.net/ont/geosparql#hasGeometry": ["http://data.archaeology.link/data/ancientports/3289_geom"], "http://www.w3.org/1999/02/22-rdf-syntax-ns#type": ["http://www.ancientports.com/ont#Lighthouse", "http://www.ancientports.com/ont#Quay", "http://www.ancientports.com/ont#Warehouse"], "http://www.w3.org/2000/01/rdf-schema#label": ["Tepecik hill, near Gelemis, with ancient lighthouse"], "http://www.w3.org/2002/07/owl#sameAs": ["http://www.wikidata.org/entity/Q233121"], "http://www.w3.org/2004/02/skos/core#note": ["Arnaud (2008)"], "http://www.wikidata.org/prop/direct/P1584": ["http://pleiades.stoa.org/places/639042"], "http://www.wikidata.org/prop/direct/P17": ["TR: South"], "http://www.wikidata.org/prop/direct/P1936": ["http://imperium.ahlfeldt.se/places/21460"], "http://www.wikidata.org/prop/direct/P1958": ["https://www.trismegistos.org/place/1625"], "http://www.wikidata.org/prop/direct/P8068": ["https://topostext.org/place/363293BPaL"]}, "geometry": {"type": "Point", "coordinates": [29.315, 36.265]}}]}