{"type": "FeatureCollection", "id": "http://pleiades.stoa.org/places/857291", "name": "857291", "features": [{"type": "Feature", "id": "http://data.archaeology.link/data/ancientports/2726", "name": "Arakli, on R Karadere, near Canayer", "dateprops": ["begin"], "properties": {"http://purl.org/dc/elements/1.1/created": ["2023"], "http://purl.org/dc/elements/1.1/creator": ["http://data.archaeology.link/data/spphaefen/arthur_de_graauw"], "http://www.opengis.net/ont/geosparql#hasGeometry": ["http://data.archaeology.link/data/ancientports/2726_geom"], "http://www.w3.org/1999/02/22-rdf-syntax-ns#type": ["http://www.ancientports.com/ont#Harbour"], "http://www.w3.org/2000/01/rdf-schema#label": ["Arakli, on R Karadere, near Canayer"], "http://www.w3.org/2002/07/owl#sameAs": ["http://www.wikidata.org/entity/Q764830"], "http://www.w3.org/2006/time#hasTime": ["http://data.archaeology.link/data/ancientports/2726_foundation"], "http://www.wikidata.org/prop/direct/P1584": ["http://pleiades.stoa.org/places/857291"], "http://www.wikidata.org/prop/direct/P17": ["http://www.wikidata.org/entity/Q43"], "http://www.wikidata.org/prop/direct/P1936": ["http://imperium.ahlfeldt.se/places/36169"], "begin": "-550"}, "geometry": {"type": "Point", "coordinates": [40.06825, 40.94234]}}, {"type": "Feature", "id": "http://data.archaeology.link/data/ancientports/2725", "name": "S\u00fcrmene, on R Manahoz Deresi", "dateprops": [], "properties": {"http://purl.org/dc/elements/1.1/created": ["2023"], "http://purl.org/dc/elements/1.1/creator": ["http://data.archaeology.link/data/spphaefen/arthur_de_graauw"], "http://www.opengis.net/ont/geosparql#hasGeometry": ["http://data.archaeology.link/data/ancientports/2725_geom"], "http://www.w3.org/1999/02/22-rdf-syntax-ns#type": ["http://www.ancientports.com/ont#Harbour"], "http://www.w3.org/2000/01/rdf-schema#label": ["S\u00fcrmene, on R Manahoz Deresi"], "http://www.w3.org/2002/07/owl#sameAs": ["http://www.wikidata.org/entity/Q1011964"], "http://www.wikidata.org/prop/direct/P1584": ["http://pleiades.stoa.org/places/857291"], "http://www.wikidata.org/prop/direct/P17": ["http://www.wikidata.org/entity/Q43"], "begin": ""}, "geometry": {"type": "Point", "coordinates": [40.1129, 40.91819]}}]}