{"type": "FeatureCollection", "id": "http://www.wikidata.org/entity/Q3298444", "name": "Q3298444", "features": [{"type": "Feature", "id": "http://data.archaeology.link/data/ancientports/1372_2", "label": "Pical, San Eleuterio, near Materada Maj, with submerged BA settlement", "properties": {"http://purl.org/dc/elements/1.1/created": ["2023"], "http://purl.org/dc/elements/1.1/creator": ["http://data.archaeology.link/data/spphaefen/arthur_de_graauw"], "http://purl.org/dc/terms/isReferencedBy": ["http://baza.iarh.hr/public/locality/detail/7518", "http://splashcos-viewer.eu/"], "http://www.opengis.net/ont/geosparql#hasGeometry": ["http://data.archaeology.link/data/ancientports/1372_2_geom"], "http://www.w3.org/1999/02/22-rdf-syntax-ns#type": ["http://www.ancientports.com/ont#Harbour"], "http://www.w3.org/2000/01/rdf-schema#label": ["Pical, San Eleuterio, near Materada Maj, with submerged BA settlement"], "http://www.w3.org/2002/07/owl#sameAs": ["http://www.wikidata.org/entity/Q3298444"], "http://www.w3.org/2004/02/skos/core#note": ["Degrassi (1955)"], "http://www.wikidata.org/prop/direct/P17": ["http://www.wikidata.org/entity/Q224"]}, "geometry": {"type": "Point", "coordinates": [13.596, 45.239]}}]}