{"type": "FeatureCollection", "id": "http://www.wikidata.org/entity/Q992270", "name": "Q992270", "features": [{"type": "Feature", "id": "http://data.archaeology.link/data/ancientports/2212", "label": "Sigri, on the isle of Lesbos, Lesvos", "dateprops": [], "properties": {"http://purl.org/dc/elements/1.1/created": ["2023"], "http://purl.org/dc/elements/1.1/creator": ["http://data.archaeology.link/data/spphaefen/arthur_de_graauw"], "http://www.opengis.net/ont/geosparql#hasGeometry": ["http://data.archaeology.link/data/ancientports/2212_geom"], "http://www.w3.org/1999/02/22-rdf-syntax-ns#type": ["http://www.ancientports.com/ont#Harbour"], "http://www.w3.org/2000/01/rdf-schema#label": ["Sigri, on the isle of Lesbos, Lesvos"], "http://www.w3.org/2002/07/owl#sameAs": ["http://www.wikidata.org/entity/Q992270"], "http://www.w3.org/2006/time#hasTime": ["http://data.archaeology.link/data/ancientports/2212_foundation"], "http://www.wikidata.org/prop/direct/P1584": ["http://pleiades.stoa.org/places/550880"], "http://www.wikidata.org/prop/direct/P17": ["GR: Eastern Isl."], "http://www.wikidata.org/prop/direct/P1936": ["http://imperium.ahlfeldt.se/places/27360"], "http://www.wikidata.org/prop/direct/P8068": ["https://topostext.org/place/392259USig"]}, "geometry": {"type": "Point", "coordinates": [25.8565, 39.2128]}}]}