{"type": "FeatureCollection", "id": "http://pleiades.stoa.org/places/226656", "name": "226656", "features": [{"type": "Feature", "id": "http://data.archaeology.link/data/ancientports/2572", "label": "Kipchak bay, port of Kastel", "dateprops": ["http://purl.org/dc/elements/1.1/created", "http://www.ancientports.com/ont#date_min"], "properties": {"http://purl.org/dc/elements/1.1/created": ["2023"], "http://purl.org/dc/elements/1.1/creator": ["http://data.archaeology.link/data/spphaefen/arthur_de_graauw"], "http://www.ancientports.com/ont#date_min": ["-550"], "http://www.opengis.net/ont/geosparql#hasGeometry": ["http://data.archaeology.link/data/ancientports/2572_geom"], "http://www.w3.org/1999/02/22-rdf-syntax-ns#type": ["http://www.ancientports.com/ont#Harbour"], "http://www.w3.org/2000/01/rdf-schema#label": ["Kipchak bay, port of Kastel"], "http://www.w3.org/2004/02/skos/core#note": ["Kutaisov (2016)", "Tsetskhladze (1998)"], "http://www.wikidata.org/prop/direct/P1584": ["http://pleiades.stoa.org/places/226656"], "http://www.wikidata.org/prop/direct/P17": ["Ukraine Black S."], "http://www.wikidata.org/prop/direct/P1936": ["http://imperium.ahlfeldt.se/places/27927"]}, "geometry": {"type": "Point", "coordinates": [32.5914, 45.4812]}}]}