{"type": "FeatureCollection", "id": "https://www.trismegistos.org/place/5085", "name": "5085", "features": [{"type": "Feature", "id": "http://data.archaeology.link/data/ancientports/3885", "name": "Qantir, port is north of village, famous stables are south", "dateprops": ["begin"], "properties": {"http://purl.org/dc/elements/1.1/creator": ["http://data.archaeology.link/data/spphaefen/arthur_de_graauw"], "http://purl.org/dc/terms/partOf": ["http://data.archaeology.link/data/ancientports/bib_deGrauw_2013_GeoDB"], "http://www.opengis.net/ont/geosparql#hasGeometry": ["http://data.archaeology.link/data/ancientports/3885_geom"], "http://www.w3.org/1999/02/22-rdf-syntax-ns#type": ["http://www.ancientports.com/ont#Harbour"], "http://www.w3.org/2000/01/rdf-schema#label": ["Qantir, port is north of village, famous stables are south"], "http://www.w3.org/2002/07/owl#sameAs": ["http://www.wikidata.org/entity/Q937930"], "http://www.w3.org/2004/02/skos/core#note": ["Bietak (1996)"], "http://www.w3.org/2006/time#hasTime": ["http://data.archaeology.link/data/ancientports/3885_foundation"], "http://www.wikidata.org/prop/direct/P1584": ["http://pleiades.stoa.org/places/727080"], "http://www.wikidata.org/prop/direct/P17": ["http://www.wikidata.org/entity/Q79"], "http://www.wikidata.org/prop/direct/P1936": ["http://imperium.ahlfeldt.se/places/28474"], "http://www.wikidata.org/prop/direct/P1958": ["https://www.trismegistos.org/place/5085"], "begin": "-1300"}, "geometry": {"type": "Point", "coordinates": [31.83486, 30.80632]}}], "numberMatched": 1, "numberReturned": 1, "bbox": [31.83486, 30.80632, 31.83486, 30.80632], "crs": "http://www.opengis.net/def/crs/EPSG/0/4326"}