{"type": "FeatureCollection", "id": "http://pleiades.stoa.org/places/530933", "name": "530933", "features": [{"type": "Feature", "id": "http://data.archaeology.link/data/ancientports/2021", "label": "Alykanas, Alikes, with Neolithic settlement, on the Isle of Zakinthos", "dateprops": [], "properties": {"http://purl.org/dc/elements/1.1/created": ["2023"], "http://purl.org/dc/elements/1.1/creator": ["http://data.archaeology.link/data/spphaefen/arthur_de_graauw"], "http://www.ancientports.com/ont#date_min": ["-330"], "http://www.opengis.net/ont/geosparql#hasGeometry": ["http://data.archaeology.link/data/ancientports/2021_geom"], "http://www.w3.org/1999/02/22-rdf-syntax-ns#type": ["http://www.ancientports.com/ont#Harbour"], "http://www.w3.org/2000/01/rdf-schema#label": ["Alykanas, Alikes, with Neolithic settlement, on the Isle of Zakinthos"], "http://www.w3.org/2002/07/owl#sameAs": ["http://www.wikidata.org/entity/Q4726608"], "http://www.wikidata.org/prop/direct/P1584": ["http://pleiades.stoa.org/places/530933"], "http://www.wikidata.org/prop/direct/P17": ["GR: Ionian Isl."], "http://www.wikidata.org/prop/direct/P1936": ["http://imperium.ahlfeldt.se/places/31574"], "http://www.wikidata.org/prop/direct/P8068": ["https://topostext.org/place/378208XKat"]}, "geometry": {"type": "Point", "coordinates": [20.7875, 37.846]}}]}