{"type": "FeatureCollection", "id": "http://www.wikidata.org/entity/Q3558915", "name": "Loupian Roman villa", "features": [{"type": "Feature", "id": "http://data.archaeology.link/data/ancientports/632", "name": "", "dateprops": ["begin"], "properties": {"http://purl.org/dc/elements/1.1/creator": ["http://data.archaeology.link/data/spphaefen/arthur_de_graauw"], "http://purl.org/dc/terms/partOf": ["http://data.archaeology.link/data/ancientports/bib_deGrauw_2013_GeoDB"], "http://www.opengis.net/ont/geosparql#hasGeometry": ["http://data.archaeology.link/data/ancientports/632_geom"], "http://www.w3.org/1999/02/22-rdf-syntax-ns#type": ["http://www.ancientports.com/ont#VillaMaritima"], "http://www.w3.org/2000/01/rdf-schema#label": ["Roman villa at Loupian"], "http://www.w3.org/2002/07/owl#sameAs": ["http://www.wikidata.org/entity/Q3558915"], "http://www.w3.org/2004/02/skos/core#note": ["Garcia (1995)"], "http://www.w3.org/2006/time#hasTime": ["http://data.archaeology.link/data/ancientports/632_foundation"], "http://www.wikidata.org/prop/direct/P17": ["http://www.wikidata.org/entity/Q142"], "begin": "-600"}, "geometry": {"type": "Point", "coordinates": [3.6143, 43.4401]}}], "numberMatched": 1, "numberReturned": 1, "bbox": [3.6143, 43.4401, 3.6143, 43.4401], "crs": "http://www.opengis.net/def/crs/EPSG/0/4326"}