{"type": "FeatureCollection", "id": "http://www.wikidata.org/entity/Q2910205", "name": "Q2910205", "features": [{"type": "Feature", "id": "http://data.archaeology.link/data/ancientports/138_1", "label": "Llanfaethlu", "properties": {"http://purl.org/dc/elements/1.1/created": ["2023"], "http://purl.org/dc/elements/1.1/creator": ["http://data.archaeology.link/data/spphaefen/arthur_de_graauw"], "http://www.opengis.net/ont/geosparql#hasGeometry": ["http://data.archaeology.link/data/ancientports/138_1_geom"], "http://www.w3.org/1999/02/22-rdf-syntax-ns#type": ["http://www.ancientports.com/ont#Harbour"], "http://www.w3.org/2000/01/rdf-schema#label": ["Llanfaethlu"], "http://www.w3.org/2002/07/owl#sameAs": ["http://www.wikidata.org/entity/Q2910205"], "http://www.wikidata.org/prop/direct/P17": ["http://www.wikidata.org/entity/Q145"], "http://www.wikidata.org/prop/direct/P1958": ["https://www.trismegistos.org/place/15006"]}, "geometry": {"type": "Point", "coordinates": [-4.5371, 53.3523]}}]}