{"type": "FeatureCollection", "id": "https://topostext.org/place/395199BMor", "name": "395199BMor", "features": [{"type": "Feature", "id": "http://data.archaeology.link/data/ancientports/1979", "label": "Roman villa at Moraitika, on Corfu", "properties": {"http://purl.org/dc/elements/1.1/created": ["2023"], "http://purl.org/dc/elements/1.1/creator": ["http://data.archaeology.link/data/spphaefen/arthur_de_graauw"], "http://www.ancientports.com/ont#date_min": ["-30"], "http://www.opengis.net/ont/geosparql#hasGeometry": ["http://data.archaeology.link/data/ancientports/1979_geom"], "http://www.w3.org/1999/02/22-rdf-syntax-ns#type": ["http://www.ancientports.com/ont#Harbour"], "http://www.w3.org/2000/01/rdf-schema#label": ["Roman villa at Moraitika, on Corfu"], "http://www.wikidata.org/prop/direct/P17": ["GR: Ionian Isl."], "http://www.wikidata.org/prop/direct/P8068": ["https://topostext.org/place/395199BMor"]}, "geometry": {"type": "Point", "coordinates": [19.9243, 39.4831]}}]}