{"type": "FeatureCollection", "id": "http://www.wikidata.org/entity/Q65074842", "name": "Q65074842", "features": [{"type": "Feature", "id": "http://data.archaeology.link/data/ancientports/2929", "label": "near Kolimbari", "properties": {"http://purl.org/dc/elements/1.1/created": ["2023"], "http://purl.org/dc/elements/1.1/creator": ["http://data.archaeology.link/data/spphaefen/arthur_de_graauw"], "http://www.ancientports.com/ont#date_min": ["-750"], "http://www.opengis.net/ont/geosparql#hasGeometry": ["http://data.archaeology.link/data/ancientports/2929_geom"], "http://www.w3.org/1999/02/22-rdf-syntax-ns#type": ["http://www.ancientports.com/ont#Harbour"], "http://www.w3.org/2000/01/rdf-schema#label": ["near Kolimbari"], "http://www.w3.org/2002/07/owl#sameAs": ["http://www.wikidata.org/entity/Q65074842"], "http://www.wikidata.org/prop/direct/P1584": ["http://pleiades.stoa.org/places/589984"], "http://www.wikidata.org/prop/direct/P17": ["GR: Crete North"], "http://www.wikidata.org/prop/direct/P1936": ["http://imperium.ahlfeldt.se/places/28830"], "http://www.wikidata.org/prop/direct/P8068": ["https://topostext.org/place/355238UPer"]}, "geometry": {"type": "Point", "coordinates": [23.7732, 35.5308]}}]}