{"type": "FeatureCollection", "id": "https://www.trismegistos.org/place/33924", "name": "33924", "features": [{"type": "Feature", "id": "http://data.archaeology.link/data/ancientports/1790", "label": "Cape Pyrgos, Pirgos Sani", "dateprops": ["http://purl.org/dc/elements/1.1/created"], "properties": {"http://purl.org/dc/elements/1.1/created": ["2023"], "http://purl.org/dc/elements/1.1/creator": ["http://data.archaeology.link/data/spphaefen/arthur_de_graauw"], "http://www.opengis.net/ont/geosparql#hasGeometry": ["http://data.archaeology.link/data/ancientports/1790_geom"], "http://www.w3.org/1999/02/22-rdf-syntax-ns#type": ["http://www.ancientports.com/ont#Harbour"], "http://www.w3.org/2000/01/rdf-schema#label": ["Cape Pyrgos, Pirgos Sani"], "http://www.w3.org/2002/07/owl#sameAs": ["http://www.wikidata.org/entity/Q112484158"], "http://www.wikidata.org/prop/direct/P1584": ["http://pleiades.stoa.org/places/491715"], "http://www.wikidata.org/prop/direct/P17": ["GR: North-East"], "http://www.wikidata.org/prop/direct/P1936": ["http://imperium.ahlfeldt.se/places/32159"], "http://www.wikidata.org/prop/direct/P1958": ["https://www.trismegistos.org/place/33924"], "http://www.wikidata.org/prop/direct/P8068": ["https://topostext.org/place/401233PSan"]}, "geometry": {"type": "Point", "coordinates": [23.311, 40.0919]}}]}