{"type": "FeatureCollection", "id": "http://imperium.ahlfeldt.se/places/41511", "name": "41511", "features": [{"type": "Feature", "id": "http://data.archaeology.link/data/ancientports/749", "name": "Nonza", "dateprops": [], "properties": {"http://purl.org/dc/elements/1.1/creator": ["http://data.archaeology.link/data/spphaefen/arthur_de_graauw"], "http://purl.org/dc/terms/partOf": ["http://data.archaeology.link/data/ancientports/bib_deGrauw_2013_GeoDB"], "http://www.opengis.net/ont/geosparql#hasGeometry": ["http://data.archaeology.link/data/ancientports/749_geom"], "http://www.w3.org/1999/02/22-rdf-syntax-ns#type": ["http://www.ancientports.com/ont#Harbour"], "http://www.w3.org/2000/01/rdf-schema#label": ["Nonza"], "http://www.wikidata.org/prop/direct/P17": ["http://www.wikidata.org/entity/Q142"], "http://www.wikidata.org/prop/direct/P1936": ["http://imperium.ahlfeldt.se/places/41511"], "begin": ""}, "geometry": {"type": "Point", "coordinates": [9.343, 42.78628]}}], "numberMatched": 1, "numberReturned": 1, "bbox": [9.343, 42.78628, 9.343, 42.78628], "crs": "http://www.opengis.net/def/crs/EPSG/0/4326"}