{"type": "FeatureCollection", "id": "http://www.wikidata.org/entity/Q25247416", "name": "Sonmiani", "features": [{"type": "Feature", "id": "http://data.archaeology.link/data/ancientports/3857", "name": "unlocated anchorage in open sea in front of the shore, possibly near Sonmiani at outlet of R Porali?", "dateprops": [], "properties": {"http://purl.org/dc/elements/1.1/creator": ["http://data.archaeology.link/data/spphaefen/arthur_de_graauw"], "http://purl.org/dc/terms/isReferencedBy": ["http://data.archaeology.link/data/ancientports/bib_Eggermont_1975_Alexander"], "http://purl.org/dc/terms/partOf": ["http://data.archaeology.link/data/ancientports/bib_deGrauw_2013_GeoDB"], "http://www.opengis.net/ont/geosparql#hasGeometry": ["http://data.archaeology.link/data/ancientports/3857_geom"], "http://www.w3.org/1999/02/22-rdf-syntax-ns#type": ["http://www.ancientports.com/ont#Harbour"], "http://www.w3.org/2000/01/rdf-schema#label": ["unlocated anchorage in open sea in front of the shore, possibly near Sonmiani at outlet of R Porali?"], "http://www.w3.org/2002/07/owl#sameAs": ["http://www.wikidata.org/entity/Q25247416"], "http://www.wikidata.org/prop/direct/P1584": ["http://pleiades.stoa.org/places/60533"], "http://www.wikidata.org/prop/direct/P17": ["http://www.wikidata.org/entity/Q843"], "begin": ""}, "geometry": {"type": "Point", "coordinates": [66.547, 25.43]}}], "numberMatched": 1, "numberReturned": 1, "bbox": [66.547, 25.43, 66.547, 25.43], "crs": "http://www.opengis.net/def/crs/OGC/1.3/CRS84"}