{"type": "FeatureCollection", "id": "http://imperium.ahlfeldt.se/places/23383", "name": "23383", "features": [{"type": "Feature", "id": "http://data.archaeology.link/data/ancientports/2999", "label": "islet of Trafos at Chrysostomos 2 km east of Kaloi Limenes ; rubble mound breakwaters can be seen on Google Earth", "properties": {"http://purl.org/dc/elements/1.1/created": ["2023"], "http://purl.org/dc/elements/1.1/creator": ["http://data.archaeology.link/data/spphaefen/arthur_de_graauw"], "http://www.ancientports.com/ont#date_min": ["-3000"], "http://www.opengis.net/ont/geosparql#hasGeometry": ["http://data.archaeology.link/data/ancientports/2999_geom"], "http://www.w3.org/1999/02/22-rdf-syntax-ns#type": ["http://www.ancientports.com/ont#Harbour"], "http://www.w3.org/2000/01/rdf-schema#label": ["islet of Trafos at Chrysostomos 2 km east of Kaloi Limenes ; rubble mound breakwaters can be seen on Google Earth"], "http://www.w3.org/2002/07/owl#sameAs": ["http://www.wikidata.org/entity/Q7832593"], "http://www.w3.org/2004/02/skos/core#note": ["Uggeri (2003)"], "http://www.wikidata.org/prop/direct/P1584": ["http://pleiades.stoa.org/places/589897"], "http://www.wikidata.org/prop/direct/P17": ["GR: Crete South"], "http://www.wikidata.org/prop/direct/P1936": ["http://imperium.ahlfeldt.se/places/23383"], "http://www.wikidata.org/prop/direct/P1958": ["https://www.trismegistos.org/place/33285"], "http://www.wikidata.org/prop/direct/P8068": ["https://topostext.org/place/349248ULas"]}, "geometry": {"type": "Point", "coordinates": [24.82495, 34.9376]}}]}