{"type": "FeatureCollection", "id": "http://www.wikidata.org/entity/Q19232110", "name": "Q19232110", "features": [{"type": "Feature", "id": "http://data.archaeology.link/data/ancientports/592_1", "label": "Roman winery at Les Minimes, near La Rochelle", "properties": {"http://purl.org/dc/elements/1.1/created": ["2023"], "http://purl.org/dc/elements/1.1/creator": ["http://data.archaeology.link/data/spphaefen/arthur_de_graauw"], "http://www.ancientports.com/ont#date_min": ["7001"], "http://www.opengis.net/ont/geosparql#hasGeometry": ["http://data.archaeology.link/data/ancientports/592_1_geom"], "http://www.w3.org/1999/02/22-rdf-syntax-ns#type": ["http://www.ancientports.com/ont#Harbour"], "http://www.w3.org/2000/01/rdf-schema#label": ["Roman winery at Les Minimes, near La Rochelle"], "http://www.w3.org/2002/07/owl#sameAs": ["http://www.wikidata.org/entity/Q19232110"], "http://www.w3.org/2004/02/skos/core#note": ["Balmelle (2001)"], "http://www.wikidata.org/prop/direct/P1584": ["http://pleiades.stoa.org/places/140480"], "http://www.wikidata.org/prop/direct/P17": ["France West"], "http://www.wikidata.org/prop/direct/P1936": ["http://imperium.ahlfeldt.se/places/18558"]}, "geometry": {"type": "Point", "coordinates": [-1.16217, 46.14379]}}]}