{"type": "FeatureCollection", "id": "https://pleiades.stoa.org/places/39330", "name": "39330", "features": [{"type": "Feature", "id": "http://data.archaeology.link/data/ancientports/3646", "label": "al-Zubayr islands", "dateprops": [], "properties": {"http://purl.org/dc/elements/1.1/created": ["2023"], "http://purl.org/dc/elements/1.1/creator": ["http://data.archaeology.link/data/spphaefen/arthur_de_graauw"], "http://www.opengis.net/ont/geosparql#hasGeometry": ["http://data.archaeology.link/data/ancientports/3646_geom"], "http://www.w3.org/1999/02/22-rdf-syntax-ns#type": ["http://www.ancientports.com/ont#Harbour"], "http://www.w3.org/2000/01/rdf-schema#label": ["al-Zubayr islands"], "http://www.w3.org/2002/07/owl#sameAs": ["http://www.wikidata.org/entity/Q227496"], "http://www.wikidata.org/prop/direct/P1584": ["https://pleiades.stoa.org/places/39330"], "http://www.wikidata.org/prop/direct/P17": ["http://www.wikidata.org/entity/Q805"]}, "geometry": {"type": "Point", "coordinates": [42.17, 15.09]}}]}