{"type": "FeatureCollection", "id": "http://www.wikidata.org/entity/Q621914", "name": "Q621914", "features": [{"type": "Feature", "id": "http://data.archaeology.link/data/ancientports/2700", "label": "Roman fort at Ilori, south of Ochamchira, on R Galidzga", "properties": {"http://purl.org/dc/elements/1.1/created": ["2023"], "http://purl.org/dc/elements/1.1/creator": ["http://data.archaeology.link/data/spphaefen/arthur_de_graauw"], "http://www.ancientports.com/ont#date_min": ["-30"], "http://www.opengis.net/ont/geosparql#hasGeometry": ["http://data.archaeology.link/data/ancientports/2700_geom"], "http://www.w3.org/1999/02/22-rdf-syntax-ns#type": ["http://www.ancientports.com/ont#Harbour"], "http://www.w3.org/2000/01/rdf-schema#label": ["Roman fort at Ilori, south of Ochamchira, on R Galidzga"], "http://www.w3.org/2002/07/owl#sameAs": ["http://www.wikidata.org/entity/Q621914"], "http://www.wikidata.org/prop/direct/P1584": ["http://pleiades.stoa.org/places/857170"], "http://www.wikidata.org/prop/direct/P17": ["Abkhazia Black S."]}, "geometry": {"type": "Point", "coordinates": [41.4986, 42.6956]}}]}