{"type": "FeatureCollection", "id": "https://topostext.org/place/373265IPat", "name": "373265IPat", "features": [{"type": "Feature", "id": "http://data.archaeology.link/data/ancientports/2289", "label": "Kastelli, on the isle of Patmos ", "dateprops": [], "properties": {"http://purl.org/dc/elements/1.1/created": ["2023"], "http://purl.org/dc/elements/1.1/creator": ["http://data.archaeology.link/data/spphaefen/arthur_de_graauw"], "http://www.opengis.net/ont/geosparql#hasGeometry": ["http://data.archaeology.link/data/ancientports/2289_geom"], "http://www.w3.org/1999/02/22-rdf-syntax-ns#type": ["http://www.ancientports.com/ont#Harbour"], "http://www.w3.org/2000/01/rdf-schema#label": ["Kastelli, on the isle of Patmos "], "http://www.w3.org/2002/07/owl#sameAs": ["http://www.wikidata.org/entity/Q190053"], "http://www.w3.org/2006/time#hasTime": ["http://data.archaeology.link/data/ancientports/2289_foundation"], "http://www.wikidata.org/prop/direct/P1584": ["http://pleiades.stoa.org/places/599871"], "http://www.wikidata.org/prop/direct/P17": ["GR: Eastern Isl."], "http://www.wikidata.org/prop/direct/P1936": ["http://imperium.ahlfeldt.se/places/29028"], "http://www.wikidata.org/prop/direct/P1958": ["https://www.trismegistos.org/place/11321"], "http://www.wikidata.org/prop/direct/P8068": ["https://topostext.org/place/373265IPat"]}, "geometry": {"type": "Point", "coordinates": [26.5352, 37.326]}}]}