{"type": "FeatureCollection", "id": "http://www.wikidata.org/entity/Q213902", "name": "Q213902", "features": [{"type": "Feature", "id": "http://data.archaeology.link/data/ancientports/2141", "label": "Chora, with port at Karavostasi, on the isle of Folegandros ", "dateprops": [], "properties": {"http://purl.org/dc/elements/1.1/created": ["2023"], "http://purl.org/dc/elements/1.1/creator": ["http://data.archaeology.link/data/spphaefen/arthur_de_graauw"], "http://www.opengis.net/ont/geosparql#hasGeometry": ["http://data.archaeology.link/data/ancientports/2141_geom"], "http://www.w3.org/1999/02/22-rdf-syntax-ns#type": ["http://www.ancientports.com/ont#Harbour"], "http://www.w3.org/2000/01/rdf-schema#label": ["Chora, with port at Karavostasi, on the isle of Folegandros "], "http://www.w3.org/2002/07/owl#sameAs": ["http://www.wikidata.org/entity/Q213902"], "http://www.wikidata.org/prop/direct/P1584": ["http://pleiades.stoa.org/places/589996"], "http://www.wikidata.org/prop/direct/P17": ["GR: Cyclades Isl."], "http://www.wikidata.org/prop/direct/P1936": ["http://imperium.ahlfeldt.se/places/41353"], "http://www.wikidata.org/prop/direct/P1958": ["https://www.trismegistos.org/place/15758"], "http://www.wikidata.org/prop/direct/P8068": ["https://topostext.org/place/366249PPho"]}, "geometry": {"type": "Point", "coordinates": [24.9255, 36.6302]}}]}