{"type": "FeatureCollection", "id": "http://www.wikidata.org/entity/Q53133", "name": "Monfalcone", "features": [{"type": "Feature", "id": "http://data.archaeology.link/data/ancientports/1352", "name": "Roman villa at via Bagni nuova, Monfalcone", "dateprops": [], "properties": {"http://purl.org/dc/elements/1.1/created": ["2023"], "http://purl.org/dc/elements/1.1/creator": ["http://data.archaeology.link/data/spphaefen/arthur_de_graauw"], "http://purl.org/dc/terms/isReferencedBy": ["https://youtu.be/Z3Rm3HaZvLs", "https://ilpiccolo.gelocal.it/trieste/cronaca/2016/06/07/news/il-mosaico-impossibile-della-villa-romana-1.13619385"], "http://www.opengis.net/ont/geosparql#hasGeometry": ["http://data.archaeology.link/data/ancientports/1352_geom"], "http://www.w3.org/1999/02/22-rdf-syntax-ns#type": ["http://www.ancientports.com/ont#VillaMaritima"], "http://www.w3.org/2000/01/rdf-schema#label": ["Roman villa at via Bagni nuova, Monfalcone"], "http://www.w3.org/2002/07/owl#sameAs": ["http://www.wikidata.org/entity/Q53133"], "http://www.wikidata.org/prop/direct/P1584": ["http://pleiades.stoa.org/places/187264"], "http://www.wikidata.org/prop/direct/P17": ["http://www.wikidata.org/entity/Q38"], "http://www.wikidata.org/prop/direct/P1936": ["http://imperium.ahlfeldt.se/places/44028"], "begin": ""}, "geometry": {"type": "Point", "coordinates": [13.5266, 45.7885]}}]}