{"type": "FeatureCollection", "id": "https://topostext.org/place/378207XKam", "name": "378207XKam", "features": [{"type": "Feature", "id": "http://data.archaeology.link/data/ancientports/2024_1", "label": "Kambi, Vigla hill, on the Isle of Zakinthos", "dateprops": [], "properties": {"http://purl.org/dc/elements/1.1/created": ["2023"], "http://purl.org/dc/elements/1.1/creator": ["http://data.archaeology.link/data/spphaefen/arthur_de_graauw"], "http://www.opengis.net/ont/geosparql#hasGeometry": ["http://data.archaeology.link/data/ancientports/2024_1_geom"], "http://www.w3.org/1999/02/22-rdf-syntax-ns#type": ["http://www.ancientports.com/ont#Harbour"], "http://www.w3.org/2000/01/rdf-schema#label": ["Kambi, Vigla hill, on the Isle of Zakinthos"], "http://www.w3.org/2006/time#hasTime": ["http://data.archaeology.link/data/ancientports/2024_1_foundation"], "http://www.wikidata.org/prop/direct/P17": ["http://www.wikidata.org/entity/Q41"], "http://www.wikidata.org/prop/direct/P8068": ["https://topostext.org/place/378207XKam"]}, "geometry": {"type": "Point", "coordinates": [20.6798, 37.7789]}}]}