{"type": "FeatureCollection", "id": "http://www.wikidata.org/entity/Q12064005", "name": "Newport Roman Villa", "features": [{"type": "Feature", "id": "http://data.archaeology.link/data/ancientports/93", "name": "", "dateprops": ["begin"], "properties": {"http://purl.org/dc/elements/1.1/creator": ["http://data.archaeology.link/data/spphaefen/arthur_de_graauw"], "http://purl.org/dc/terms/isReferencedBy": ["http://data.archaeology.link/data/ancientports/bib_Wilkes_2004_Iron", "https://historicengland.org.uk/listing/the-list/list-entry/1034658"], "http://purl.org/dc/terms/partOf": ["http://data.archaeology.link/data/ancientports/bib_deGrauw_2013_GeoDB"], "http://rdfs.org/ns/void#inDataset": ["http://data.archaeology.link/data/ancientports/ap_dataset"], "http://www.opengis.net/ont/geosparql#hasGeometry": ["http://data.archaeology.link/data/ancientports/93_geom"], "http://www.w3.org/1999/02/22-rdf-syntax-ns#type": ["http://www.ancientports.com/ont#VillaMaritima"], "http://www.w3.org/2000/01/rdf-schema#label": ["Isle of Wight, probably Newport, with Roman villa on R Medina"], "http://www.w3.org/2002/07/owl#sameAs": ["http://www.wikidata.org/entity/Q12064005"], "http://www.w3.org/2006/time#hasTime": ["http://data.archaeology.link/data/ancientports/93_foundation"], "http://www.wikidata.org/prop/direct/P1584": ["http://pleiades.stoa.org/places/79731"], "http://www.wikidata.org/prop/direct/P17": ["http://www.wikidata.org/entity/Q145"], "http://www.wikidata.org/prop/direct/P1936": ["http://imperium.ahlfeldt.se/places/41704"], "http://www.wikidata.org/prop/direct/P1958": ["https://www.trismegistos.org/place/19734"], "http://www.wikidata.org/prop/direct/P8068": ["https://topostext.org/place/507000IVec"], "begin": "5001"}, "geometry": {"type": "Point", "coordinates": [-1.2918, 50.6942]}}], "numberMatched": 1, "numberReturned": 1, "bbox": [-1.2918, 50.6942, -1.2918, 50.6942], "crs": "http://www.opengis.net/def/crs/EPSG/0/4326"}