{"type": "FeatureCollection", "id": "http://pleiades.stoa.org/places/589994", "name": "589994", "features": [{"type": "Feature", "id": "http://data.archaeology.link/data/ancientports/3010", "label": "Neolithic settlement at Damnoni cave", "dateprops": [], "properties": {"http://purl.org/dc/elements/1.1/created": ["2023"], "http://purl.org/dc/elements/1.1/creator": ["http://data.archaeology.link/data/spphaefen/arthur_de_graauw"], "http://purl.org/dc/terms/isReferencedBy": ["https://mapcarta.com/N5406146975"], "http://www.opengis.net/ont/geosparql#hasGeometry": ["http://data.archaeology.link/data/ancientports/3010_geom"], "http://www.w3.org/1999/02/22-rdf-syntax-ns#type": ["http://www.ancientports.com/ont#Harbour"], "http://www.w3.org/2000/01/rdf-schema#label": ["Neolithic settlement at Damnoni cave"], "http://www.w3.org/2006/time#hasTime": ["http://data.archaeology.link/data/ancientports/3010_foundation"], "http://www.wikidata.org/prop/direct/P1584": ["http://pleiades.stoa.org/places/589994"], "http://www.wikidata.org/prop/direct/P17": ["GR: Crete South"], "http://www.wikidata.org/prop/direct/P1936": ["http://imperium.ahlfeldt.se/places/41478"], "http://www.wikidata.org/prop/direct/P8068": ["https://topostext.org/place/352243UPho"]}, "geometry": {"type": "Point", "coordinates": [24.3986, 35.1803]}}]}