{"type": "FeatureCollection", "id": "http://www.wikidata.org/entity/Q1140015", "name": "Q1140015", "features": [{"type": "Feature", "id": "http://data.archaeology.link/data/ancientports/1876", "label": "Isle of Dokos", "properties": {"http://purl.org/dc/elements/1.1/created": ["2023"], "http://purl.org/dc/elements/1.1/creator": ["http://data.archaeology.link/data/spphaefen/arthur_de_graauw"], "http://www.ancientports.com/ont#date_min": ["-3000"], "http://www.opengis.net/ont/geosparql#hasGeometry": ["http://data.archaeology.link/data/ancientports/1876_geom"], "http://www.w3.org/1999/02/22-rdf-syntax-ns#type": ["http://www.ancientports.com/ont#Harbour"], "http://www.w3.org/2000/01/rdf-schema#label": ["Isle of Dokos"], "http://www.w3.org/2002/07/owl#sameAs": ["http://www.wikidata.org/entity/Q1140015"], "http://www.wikidata.org/prop/direct/P1584": ["http://pleiades.stoa.org/places/570089"], "http://www.wikidata.org/prop/direct/P17": ["GR: Pelop"], "http://www.wikidata.org/prop/direct/P1936": ["http://imperium.ahlfeldt.se/places/43602"], "http://www.wikidata.org/prop/direct/P1958": ["https://www.trismegistos.org/place/61205"], "http://www.wikidata.org/prop/direct/P8068": ["https://topostext.org/place/373233IApe"]}, "geometry": {"type": "Point", "coordinates": [23.3249, 37.3447]}}]}