{"type": "FeatureCollection", "id": "http://imperium.ahlfeldt.se/places/17466", "name": "17466", "features": [{"type": "Feature", "id": "http://data.archaeology.link/data/ancientports/593_3", "label": "Roman villa at Le Chatelet, near Saint Agnant, on marais de Brouage, and several other villas between this one and Port des Barques", "dateprops": ["http://purl.org/dc/elements/1.1/created"], "properties": {"http://purl.org/dc/elements/1.1/created": ["2023"], "http://purl.org/dc/elements/1.1/creator": ["http://data.archaeology.link/data/spphaefen/arthur_de_graauw"], "http://purl.org/dc/terms/isReferencedBy": ["http://mediolanum-santonum.fr/villa-du-chatelet.html", "http://socgeo-rochefort.fr/archeologie.php?sub_ref=32"], "http://www.opengis.net/ont/geosparql#hasGeometry": ["http://data.archaeology.link/data/ancientports/593_3_geom"], "http://www.w3.org/1999/02/22-rdf-syntax-ns#type": ["http://www.ancientports.com/ont#VillaMaritima"], "http://www.w3.org/2000/01/rdf-schema#label": ["Roman villa at Le Chatelet, near Saint Agnant, on marais de Brouage, and several other villas between this one and Port des Barques"], "http://www.w3.org/2004/02/skos/core#note": ["Tassaux (2010)"], "http://www.w3.org/2006/time#hasTime": ["http://data.archaeology.link/data/ancientports/593_3_foundation"], "http://www.wikidata.org/prop/direct/P17": ["France West"], "http://www.wikidata.org/prop/direct/P1936": ["http://imperium.ahlfeldt.se/places/17466"]}, "geometry": {"type": "Point", "coordinates": [-0.9323, 45.8577]}}]}