{"type": "FeatureCollection", "id": "https://www.trismegistos.org/place/11714", "name": "11714", "features": [{"type": "Feature", "id": "http://data.archaeology.link/data/ancientports/3523_1", "label": "Surandala fort, near wadi Ghurundel, Gharandel", "properties": {"http://purl.org/dc/elements/1.1/created": ["2023"], "http://purl.org/dc/elements/1.1/creator": ["http://data.archaeology.link/data/spphaefen/arthur_de_graauw"], "http://www.opengis.net/ont/geosparql#hasGeometry": ["http://data.archaeology.link/data/ancientports/3523_1_geom"], "http://www.w3.org/1999/02/22-rdf-syntax-ns#type": ["http://www.ancientports.com/ont#Harbour"], "http://www.w3.org/2000/01/rdf-schema#label": ["Surandala fort, near wadi Ghurundel, Gharandel"], "http://www.w3.org/2002/07/owl#sameAs": ["http://www.wikidata.org/entity/Q22935877"], "http://www.wikidata.org/prop/direct/P1584": ["https://pleiades.stoa.org/places/746713"], "http://www.wikidata.org/prop/direct/P17": ["Egypt: G. of Suez"], "http://www.wikidata.org/prop/direct/P1958": ["https://www.trismegistos.org/place/11714"]}, "geometry": {"type": "Point", "coordinates": [32.9059, 29.2503]}}]}