{"type": "FeatureCollection", "id": "https://www.trismegistos.org/place/22316", "name": "22316", "features": [{"type": "Feature", "id": "http://data.archaeology.link/data/ancientports/1171", "label": "Mazara del Vallo, on R Mazara", "dateprops": ["http://purl.org/dc/elements/1.1/created", "http://www.ancientports.com/ont#date_min"], "properties": {"http://purl.org/dc/elements/1.1/created": ["2023"], "http://purl.org/dc/elements/1.1/creator": ["http://data.archaeology.link/data/spphaefen/arthur_de_graauw"], "http://www.ancientports.com/ont#date_min": ["-550"], "http://www.opengis.net/ont/geosparql#hasGeometry": ["http://data.archaeology.link/data/ancientports/1171_geom"], "http://www.w3.org/1999/02/22-rdf-syntax-ns#type": ["http://www.ancientports.com/ont#Quay"], "http://www.w3.org/2000/01/rdf-schema#label": ["Mazara del Vallo, on R Mazara"], "http://www.w3.org/2002/07/owl#sameAs": ["http://www.wikidata.org/entity/Q481730"], "http://www.wikidata.org/prop/direct/P1584": ["http://pleiades.stoa.org/places/462305"], "http://www.wikidata.org/prop/direct/P17": ["Italy Sicily"], "http://www.wikidata.org/prop/direct/P1936": ["http://imperium.ahlfeldt.se/places/30171"], "http://www.wikidata.org/prop/direct/P1958": ["https://www.trismegistos.org/place/22316"]}, "geometry": {"type": "Point", "coordinates": [12.58761, 37.64421]}}]}