{"type": "FeatureCollection", "id": "http://pleiades.stoa.org/places/423025", "name": "423025", "features": [{"type": "Feature", "id": "http://data.archaeology.link/data/ancientports/931", "label": "Tor di Nora and Ripetta, on left bank of R Tiber", "properties": {"http://purl.org/dc/elements/1.1/created": ["2023"], "http://purl.org/dc/elements/1.1/creator": ["http://data.archaeology.link/data/spphaefen/arthur_de_graauw"], "http://www.opengis.net/ont/geosparql#hasGeometry": ["http://data.archaeology.link/data/ancientports/931_geom"], "http://www.w3.org/1999/02/22-rdf-syntax-ns#type": ["http://www.ancientports.com/ont#Harbour"], "http://www.w3.org/2000/01/rdf-schema#label": ["Tor di Nora and Ripetta, on left bank of R Tiber"], "http://www.wikidata.org/prop/direct/P1584": ["http://pleiades.stoa.org/places/423025"], "http://www.wikidata.org/prop/direct/P17": ["Italy West"], "http://www.wikidata.org/prop/direct/P1958": ["https://www.trismegistos.org/place/2058"]}, "geometry": {"type": "Point", "coordinates": [12.46969, 41.90152]}}]}