{"type": "FeatureCollection", "id": "http://pleiades.stoa.org/places/433122", "name": "433122", "features": [{"type": "Feature", "id": "http://data.archaeology.link/data/ancientports/970", "label": "Baia Azzurra Levagnole, near Mondragone", "properties": {"http://purl.org/dc/elements/1.1/created": ["2023"], "http://purl.org/dc/elements/1.1/creator": ["http://data.archaeology.link/data/spphaefen/arthur_de_graauw"], "http://www.ancientports.com/ont#date_min": ["-550"], "http://www.opengis.net/ont/geosparql#hasGeometry": ["http://data.archaeology.link/data/ancientports/970_geom"], "http://www.w3.org/1999/02/22-rdf-syntax-ns#type": ["http://www.ancientports.com/ont#Harbour"], "http://www.w3.org/2000/01/rdf-schema#label": ["Baia Azzurra Levagnole, near Mondragone"], "http://www.w3.org/2002/07/owl#sameAs": ["http://www.wikidata.org/entity/Q1349926"], "http://www.wikidata.org/prop/direct/P1584": ["http://pleiades.stoa.org/places/433122"], "http://www.wikidata.org/prop/direct/P17": ["Italy West"], "http://www.wikidata.org/prop/direct/P1936": ["http://imperium.ahlfeldt.se/places/21310"], "http://www.wikidata.org/prop/direct/P1958": ["https://www.trismegistos.org/place/32437"], "http://www.wikidata.org/prop/direct/P8068": ["https://topostext.org/place/411139USin"]}, "geometry": {"type": "Point", "coordinates": [13.85, 41.14944]}}]}