{"type": "FeatureCollection", "id": "http://imperium.ahlfeldt.se/places/42131", "name": "42131", "features": [{"type": "Feature", "id": "http://data.archaeology.link/data/ancientports/1121", "label": "Roman fort at Castello di Aci", "dateprops": ["http://purl.org/dc/elements/1.1/created", "http://www.ancientports.com/ont#date_min"], "properties": {"http://purl.org/dc/elements/1.1/created": ["2023"], "http://purl.org/dc/elements/1.1/creator": ["http://data.archaeology.link/data/spphaefen/arthur_de_graauw"], "http://www.ancientports.com/ont#date_min": ["3001"], "http://www.opengis.net/ont/geosparql#hasGeometry": ["http://data.archaeology.link/data/ancientports/1121_geom"], "http://www.w3.org/1999/02/22-rdf-syntax-ns#type": ["http://www.ancientports.com/ont#Harbour"], "http://www.w3.org/2000/01/rdf-schema#label": ["Roman fort at Castello di Aci"], "http://www.w3.org/2002/07/owl#sameAs": ["http://www.wikidata.org/entity/Q2968035"], "http://www.wikidata.org/prop/direct/P17": ["Italy Sicily"], "http://www.wikidata.org/prop/direct/P1936": ["http://imperium.ahlfeldt.se/places/42131"]}, "geometry": {"type": "Point", "coordinates": [15.1492, 37.5542]}}]}