{"type": "FeatureCollection", "id": "http://imperium.ahlfeldt.se/places/30751", "name": "30751", "features": [{"type": "Feature", "id": "http://data.archaeology.link/data/ancientports/2645", "name": "near Glafirovka, on Yeysky liman with R Yeya", "dateprops": ["begin"], "properties": {"http://purl.org/dc/elements/1.1/creator": ["http://data.archaeology.link/data/spphaefen/arthur_de_graauw"], "http://purl.org/dc/terms/partOf": ["http://data.archaeology.link/data/ancientports/bib_deGrauw_2013_GeoDB"], "http://www.opengis.net/ont/geosparql#hasGeometry": ["http://data.archaeology.link/data/ancientports/2645_geom"], "http://www.w3.org/1999/02/22-rdf-syntax-ns#type": ["http://www.ancientports.com/ont#Harbour"], "http://www.w3.org/2000/01/rdf-schema#label": ["near Glafirovka, on Yeysky liman with R Yeya"], "http://www.w3.org/2006/time#hasTime": ["http://data.archaeology.link/data/ancientports/2645_foundation"], "http://www.wikidata.org/prop/direct/P1584": ["http://pleiades.stoa.org/places/825350"], "http://www.wikidata.org/prop/direct/P17": ["http://www.wikidata.org/entity/Q159"], "http://www.wikidata.org/prop/direct/P1936": ["http://imperium.ahlfeldt.se/places/30751"], "begin": "-30"}, "geometry": {"type": "Point", "coordinates": [38.41771, 46.74306]}}]}