{"type": "FeatureCollection", "id": "http://imperium.ahlfeldt.se/places/32319", "name": "32319", "features": [{"type": "Feature", "id": "http://data.archaeology.link/data/ancientports/2367", "label": "Ece Limani", "properties": {"http://purl.org/dc/elements/1.1/created": ["2023"], "http://purl.org/dc/elements/1.1/creator": ["http://data.archaeology.link/data/spphaefen/arthur_de_graauw"], "http://www.ancientports.com/ont#date_min": ["-550"], "http://www.opengis.net/ont/geosparql#hasGeometry": ["http://data.archaeology.link/data/ancientports/2367_geom"], "http://www.w3.org/1999/02/22-rdf-syntax-ns#type": ["http://www.ancientports.com/ont#Harbour"], "http://www.w3.org/2000/01/rdf-schema#label": ["Ece Limani"], "http://www.w3.org/2002/07/owl#sameAs": ["http://www.wikidata.org/entity/Q65119757"], "http://www.w3.org/2004/02/skos/core#note": ["K\u00f6rpe (2015)"], "http://www.wikidata.org/prop/direct/P1584": ["http://pleiades.stoa.org/places/501404"], "http://www.wikidata.org/prop/direct/P17": ["TR: Marmara N"], "http://www.wikidata.org/prop/direct/P1936": ["http://imperium.ahlfeldt.se/places/32319"], "http://www.wikidata.org/prop/direct/P1958": ["https://www.trismegistos.org/place/60989"], "http://www.wikidata.org/prop/direct/P8068": ["https://topostext.org/place/404263UDra"]}, "geometry": {"type": "Point", "coordinates": [26.32824, 40.36774]}}]}