{"type": "FeatureCollection", "id": "https://www.trismegistos.org/place/60732", "name": "60732", "features": [{"type": "Feature", "id": "http://data.archaeology.link/data/ancientports/1622_1", "label": "R Reitoi, Koumoundourou lake, near Skaramagas", "dateprops": [], "properties": {"http://purl.org/dc/elements/1.1/created": ["2023"], "http://purl.org/dc/elements/1.1/creator": ["http://data.archaeology.link/data/spphaefen/arthur_de_graauw"], "http://www.opengis.net/ont/geosparql#hasGeometry": ["http://data.archaeology.link/data/ancientports/1622_1_geom"], "http://www.w3.org/1999/02/22-rdf-syntax-ns#type": ["http://www.ancientports.com/ont#Harbour"], "http://www.w3.org/2000/01/rdf-schema#label": ["R Reitoi, Koumoundourou lake, near Skaramagas"], "http://www.w3.org/2002/07/owl#sameAs": ["http://www.wikidata.org/entity/Q3503850"], "http://www.wikidata.org/prop/direct/P1584": ["http://pleiades.stoa.org/places/580098"], "http://www.wikidata.org/prop/direct/P17": ["http://www.wikidata.org/entity/Q41"], "http://www.wikidata.org/prop/direct/P1958": ["https://www.trismegistos.org/place/60732"], "http://www.wikidata.org/prop/direct/P8068": ["https://topostext.org/place/381236WRhe"]}, "geometry": {"type": "Point", "coordinates": [23.601, 38.0235]}}]}