{"type": "FeatureCollection", "id": "http://imperium.ahlfeldt.se/places/33278", "name": "33278", "features": [{"type": "Feature", "id": "http://data.archaeology.link/data/ancientports/3484", "label": "Athlit, Atlit, with ancient lighthouse(s)", "properties": {"http://purl.org/dc/elements/1.1/created": ["2023"], "http://purl.org/dc/elements/1.1/creator": ["http://data.archaeology.link/data/spphaefen/arthur_de_graauw"], "http://www.ancientports.com/ont#date_min": ["-800"], "http://www.opengis.net/ont/geosparql#hasGeometry": ["http://data.archaeology.link/data/ancientports/3484_geom"], "http://www.w3.org/1999/02/22-rdf-syntax-ns#type": ["http://www.ancientports.com/ont#Harbour"], "http://www.w3.org/2000/01/rdf-schema#label": ["Athlit, Atlit, with ancient lighthouse(s)"], "http://www.w3.org/2002/07/owl#sameAs": ["http://www.wikidata.org/entity/Q116859775"], "http://www.w3.org/2004/02/skos/core#note": ["Haggi (2005)"], "http://www.wikidata.org/prop/direct/P1584": ["http://pleiades.stoa.org/places/678075"], "http://www.wikidata.org/prop/direct/P17": ["http://www.wikidata.org/entity/Q801"], "http://www.wikidata.org/prop/direct/P1936": ["http://imperium.ahlfeldt.se/places/33278"]}, "geometry": {"type": "Point", "coordinates": [34.93485, 32.70715]}}]}