{"type": "FeatureCollection", "id": "http://imperium.ahlfeldt.se/places/22354", "name": "22354", "features": [{"type": "Feature", "id": "http://data.archaeology.link/data/ancientports/1313", "label": "Villalta", "properties": {"http://purl.org/dc/elements/1.1/created": ["2023"], "http://purl.org/dc/elements/1.1/creator": ["http://data.archaeology.link/data/spphaefen/arthur_de_graauw"], "http://www.ancientports.com/ont#date_min": ["-30"], "http://www.opengis.net/ont/geosparql#hasGeometry": ["http://data.archaeology.link/data/ancientports/1313_geom"], "http://www.w3.org/1999/02/22-rdf-syntax-ns#type": ["http://www.ancientports.com/ont#Harbour"], "http://www.w3.org/2000/01/rdf-schema#label": ["Villalta"], "http://www.wikidata.org/prop/direct/P17": ["Italy Adriatic"], "http://www.wikidata.org/prop/direct/P1936": ["http://imperium.ahlfeldt.se/places/22354"]}, "geometry": {"type": "Point", "coordinates": [12.3542, 44.18738]}}]}