{"type": "FeatureCollection", "id": "http://www.wikidata.org/entity/Q65046689", "name": "Q65046689", "features": [{"type": "Feature", "id": "http://data.archaeology.link/data/ancientports/2818", "label": "Akcakoca", "properties": {"http://purl.org/dc/elements/1.1/created": ["2023"], "http://purl.org/dc/elements/1.1/creator": ["http://data.archaeology.link/data/spphaefen/arthur_de_graauw"], "http://www.ancientports.com/ont#date_min": ["-30"], "http://www.opengis.net/ont/geosparql#hasGeometry": ["http://data.archaeology.link/data/ancientports/2818_geom"], "http://www.w3.org/1999/02/22-rdf-syntax-ns#type": ["http://www.ancientports.com/ont#Harbour"], "http://www.w3.org/2000/01/rdf-schema#label": ["Akcakoca"], "http://www.w3.org/2002/07/owl#sameAs": ["http://www.wikidata.org/entity/Q65046689"], "http://www.wikidata.org/prop/direct/P1584": ["http://pleiades.stoa.org/places/844907"], "http://www.wikidata.org/prop/direct/P17": ["TR: Black Sea"], "http://www.wikidata.org/prop/direct/P1958": ["https://www.trismegistos.org/place/58997"]}, "geometry": {"type": "Point", "coordinates": [31.1233, 41.0924]}}]}