{"type": "FeatureCollection", "id": "https://www.trismegistos.org/place/15654", "name": "15654", "features": [{"type": "Feature", "id": "http://data.archaeology.link/data/ancientports/1131", "label": "Port of Arethuse, on Via Vittorio Veneto, on the isle of Ortigia", "properties": {"http://purl.org/dc/elements/1.1/created": ["2023"], "http://purl.org/dc/elements/1.1/creator": ["http://data.archaeology.link/data/spphaefen/arthur_de_graauw"], "http://www.opengis.net/ont/geosparql#hasGeometry": ["http://data.archaeology.link/data/ancientports/1131_geom"], "http://www.w3.org/1999/02/22-rdf-syntax-ns#type": ["http://www.ancientports.com/ont#Harbour"], "http://www.w3.org/2000/01/rdf-schema#label": ["Port of Arethuse, on Via Vittorio Veneto, on the isle of Ortigia"], "http://www.w3.org/2002/07/owl#sameAs": ["http://www.wikidata.org/entity/Q1233234"], "http://www.wikidata.org/prop/direct/P1584": ["http://pleiades.stoa.org/places/462402"], "http://www.wikidata.org/prop/direct/P17": ["Italy Sicily"], "http://www.wikidata.org/prop/direct/P1958": ["https://www.trismegistos.org/place/15654"]}, "geometry": {"type": "Point", "coordinates": [15.2943, 37.0653]}}]}