{"type": "FeatureCollection", "id": "https://www.trismegistos.org/place/24305", "name": "24305", "features": [{"type": "Feature", "id": "http://data.archaeology.link/data/ancientports/529", "label": "Vieux, south of Caen", "properties": {"http://purl.org/dc/elements/1.1/created": ["2023"], "http://purl.org/dc/elements/1.1/creator": ["http://data.archaeology.link/data/spphaefen/arthur_de_graauw"], "http://www.ancientports.com/ont#date_min": ["-30"], "http://www.opengis.net/ont/geosparql#hasGeometry": ["http://data.archaeology.link/data/ancientports/529_geom"], "http://www.w3.org/1999/02/22-rdf-syntax-ns#type": ["http://www.ancientports.com/ont#Harbour"], "http://www.w3.org/2000/01/rdf-schema#label": ["Vieux, south of Caen"], "http://www.w3.org/2002/07/owl#sameAs": ["http://www.wikidata.org/entity/Q1013514"], "http://www.w3.org/2004/02/skos/core#note": ["Grenier (1934)"], "http://www.wikidata.org/prop/direct/P1584": ["http://pleiades.stoa.org/places/69468"], "http://www.wikidata.org/prop/direct/P17": ["France West"], "http://www.wikidata.org/prop/direct/P1936": ["http://imperium.ahlfeldt.se/places/8051"], "http://www.wikidata.org/prop/direct/P1958": ["https://www.trismegistos.org/place/24305"], "http://www.wikidata.org/prop/direct/P8068": ["https://topostext.org/place/491000UAre"]}, "geometry": {"type": "Point", "coordinates": [-0.42995, 49.10664]}}]}