{"type": "FeatureCollection", "id": "http://www.wikidata.org/entity/Q106709661", "name": "Pen Dinas", "features": [{"type": "Feature", "id": "http://data.archaeology.link/data/ancientports/129_1", "name": "", "dateprops": ["begin"], "properties": {"http://purl.org/dc/elements/1.1/creator": ["http://data.archaeology.link/data/spphaefen/arthur_de_graauw"], "http://purl.org/dc/terms/isReferencedBy": ["https://www.megalithic.co.uk/article.php?sid=5931"], "http://purl.org/dc/terms/partOf": ["http://data.archaeology.link/data/ancientports/bib_deGrauw_2013_GeoDB"], "http://www.opengis.net/ont/geosparql#hasGeometry": ["http://data.archaeology.link/data/ancientports/129_1_geom"], "http://www.w3.org/1999/02/22-rdf-syntax-ns#type": ["http://www.ancientports.com/ont#Harbour"], "http://www.w3.org/2000/01/rdf-schema#label": ["Pen Dinas, Dinas Maelor oppidum, Ceredigion, on R Ystwyth"], "http://www.w3.org/2002/07/owl#sameAs": ["http://www.wikidata.org/entity/Q106709661"], "http://www.w3.org/2006/time#hasTime": ["http://data.archaeology.link/data/ancientports/129_1_foundation"], "http://www.wikidata.org/prop/direct/P17": ["http://www.wikidata.org/entity/Q145"], "begin": "-500"}, "geometry": {"type": "Point", "coordinates": [-4.082, 52.4018]}}], "numberMatched": 1, "numberReturned": 1, "bbox": [-4.082, 52.4018, -4.082, 52.4018], "crs": "http://www.opengis.net/def/crs/EPSG/0/4326"}