{"type": "FeatureCollection", "id": "http://www.wikidata.org/entity/Q312108", "name": "El Aouana", "features": [{"type": "Feature", "id": "http://data.archaeology.link/data/ancientports/4217", "name": "el-Aouana and island Cavallo?", "dateprops": [], "properties": {"http://purl.org/dc/elements/1.1/creator": ["http://data.archaeology.link/data/spphaefen/arthur_de_graauw"], "http://purl.org/dc/terms/partOf": ["http://data.archaeology.link/data/ancientports/bib_deGrauw_2013_GeoDB"], "http://www.opengis.net/ont/geosparql#hasGeometry": ["http://data.archaeology.link/data/ancientports/4217_geom"], "http://www.w3.org/1999/02/22-rdf-syntax-ns#type": ["http://www.ancientports.com/ont#Harbour"], "http://www.w3.org/2000/01/rdf-schema#label": ["el-Aouana and island Cavallo?"], "http://www.w3.org/2002/07/owl#sameAs": ["http://www.wikidata.org/entity/Q312108"], "http://www.w3.org/2004/02/skos/core#note": ["Elie de la Primaudaie (1860)"], "http://www.wikidata.org/prop/direct/P17": ["http://www.wikidata.org/entity/Q262"], "begin": ""}, "geometry": {"type": "Point", "coordinates": [5.60529, 36.78022]}}], "numberMatched": 1, "numberReturned": 1, "bbox": [5.60529, 36.78022, 5.60529, 36.78022], "crs": "http://www.opengis.net/def/crs/OGC/1.3/CRS84"}