{"type": "FeatureCollection", "id": "https://topostext.org/place/392239PIko", "name": "392239PIko", "features": [{"type": "Feature", "id": "http://data.archaeology.link/data/ancientports/2238_1", "label": "Kokkinokastro, on the isle of Alonnisos, Alonissos", "dateprops": [], "properties": {"http://purl.org/dc/elements/1.1/created": ["2023"], "http://purl.org/dc/elements/1.1/creator": ["http://data.archaeology.link/data/spphaefen/arthur_de_graauw"], "http://www.ancientports.com/ont#date_min": ["-550"], "http://www.opengis.net/ont/geosparql#hasGeometry": ["http://data.archaeology.link/data/ancientports/2238_1_geom"], "http://www.w3.org/1999/02/22-rdf-syntax-ns#type": ["http://www.ancientports.com/ont#Harbour"], "http://www.w3.org/2000/01/rdf-schema#label": ["Kokkinokastro, on the isle of Alonnisos, Alonissos"], "http://www.w3.org/2002/07/owl#sameAs": ["http://www.wikidata.org/entity/Q647941"], "http://www.wikidata.org/prop/direct/P1584": ["http://pleiades.stoa.org/places/540835"], "http://www.wikidata.org/prop/direct/P17": ["GR: Eastern Isl."], "http://www.wikidata.org/prop/direct/P1936": ["http://imperium.ahlfeldt.se/places/29364"], "http://www.wikidata.org/prop/direct/P1958": ["https://www.trismegistos.org/place/898"], "http://www.wikidata.org/prop/direct/P8068": ["https://topostext.org/place/392239PIko"]}, "geometry": {"type": "Point", "coordinates": [23.9066, 39.1633]}}]}