{"type": "FeatureCollection", "id": "http://www.wikidata.org/entity/Q3734556", "name": "Eupatoria (Pontus)", "features": [{"type": "Feature", "id": "http://data.archaeology.link/data/ancientports/2761", "name": "", "dateprops": ["begin"], "properties": {"http://purl.org/dc/elements/1.1/creator": ["http://data.archaeology.link/data/spphaefen/arthur_de_graauw"], "http://purl.org/dc/terms/partOf": ["http://data.archaeology.link/data/ancientports/bib_deGrauw_2013_GeoDB"], "http://www.opengis.net/ont/geosparql#hasGeometry": ["http://data.archaeology.link/data/ancientports/2761_geom"], "http://www.w3.org/1999/02/22-rdf-syntax-ns#type": ["http://www.ancientports.com/ont#Harbour"], "http://www.w3.org/2000/01/rdf-schema#label": ["Karasamson"], "http://www.w3.org/2002/07/owl#sameAs": ["http://www.wikidata.org/entity/Q3734556"], "http://www.w3.org/2006/time#hasTime": ["http://data.archaeology.link/data/ancientports/2761_foundation"], "http://www.wikidata.org/prop/direct/P1584": ["http://pleiades.stoa.org/places/857121"], "http://www.wikidata.org/prop/direct/P17": ["http://www.wikidata.org/entity/Q43"], "http://www.wikidata.org/prop/direct/P1936": ["http://imperium.ahlfeldt.se/places/29554"], "begin": "-330"}, "geometry": {"type": "Point", "coordinates": [36.3176, 41.3249]}}], "numberMatched": 1, "numberReturned": 1, "bbox": [36.3176, 41.3249, 36.3176, 41.3249], "crs": "http://www.opengis.net/def/crs/EPSG/0/4326"}