{"type": "FeatureCollection", "id": "http://imperium.ahlfeldt.se/places/43124", "name": "43124", "features": [{"type": "Feature", "id": "http://data.archaeology.link/data/ancientports/335", "label": "Roman villa at Puente Melchor", "properties": {"http://purl.org/dc/elements/1.1/created": ["2023"], "http://purl.org/dc/elements/1.1/creator": ["http://data.archaeology.link/data/spphaefen/arthur_de_graauw"], "http://purl.org/dc/terms/isReferencedBy": ["https://es.wikipedia.org/wiki/Puerto_Real#Prehistoria_y_Edad_Antigua"], "http://www.opengis.net/ont/geosparql#hasGeometry": ["http://data.archaeology.link/data/ancientports/335_geom"], "http://www.w3.org/1999/02/22-rdf-syntax-ns#type": ["http://www.ancientports.com/ont#VillaMaritima"], "http://www.w3.org/2000/01/rdf-schema#label": ["Roman villa at Puente Melchor"], "http://www.wikidata.org/prop/direct/P17": ["http://www.wikidata.org/entity/Q29"], "http://www.wikidata.org/prop/direct/P1936": ["http://imperium.ahlfeldt.se/places/43124"]}, "geometry": {"type": "Point", "coordinates": [-6.16274, 36.5215]}}]}