{"type": "FeatureCollection", "id": "https://topostext.org/place/378238XYps", "name": "378238XYps", "features": [{"type": "Feature", "id": "http://data.archaeology.link/data/ancientports/2035", "label": "Ypsili, on the isle of Andros", "dateprops": ["http://purl.org/dc/elements/1.1/created"], "properties": {"http://purl.org/dc/elements/1.1/created": ["2023"], "http://purl.org/dc/elements/1.1/creator": ["http://data.archaeology.link/data/spphaefen/arthur_de_graauw"], "http://www.opengis.net/ont/geosparql#hasGeometry": ["http://data.archaeology.link/data/ancientports/2035_geom"], "http://www.w3.org/1999/02/22-rdf-syntax-ns#type": ["http://www.ancientports.com/ont#Harbour"], "http://www.w3.org/2000/01/rdf-schema#label": ["Ypsili, on the isle of Andros"], "http://www.wikidata.org/prop/direct/P1584": ["http://pleiades.stoa.org/places/589811"], "http://www.wikidata.org/prop/direct/P17": ["GR: Cyclades Isl."], "http://www.wikidata.org/prop/direct/P8068": ["https://topostext.org/place/378238XYps"]}, "geometry": {"type": "Point", "coordinates": [24.7946, 37.8423]}}]}