{"type": "FeatureCollection", "id": "http://www.wikidata.org/entity/Q270737", "name": "Q270737", "features": [{"type": "Feature", "id": "http://data.archaeology.link/data/ancientports/819", "label": "Finale Ligure", "dateprops": [], "properties": {"http://purl.org/dc/elements/1.1/created": ["2023"], "http://purl.org/dc/elements/1.1/creator": ["http://data.archaeology.link/data/spphaefen/arthur_de_graauw"], "http://www.opengis.net/ont/geosparql#hasGeometry": ["http://data.archaeology.link/data/ancientports/819_geom"], "http://www.w3.org/1999/02/22-rdf-syntax-ns#type": ["http://www.ancientports.com/ont#Harbour"], "http://www.w3.org/2000/01/rdf-schema#label": ["Finale Ligure"], "http://www.w3.org/2002/07/owl#sameAs": ["http://www.wikidata.org/entity/Q270737"], "http://www.w3.org/2006/time#hasTime": ["http://data.archaeology.link/data/ancientports/819_foundation"], "http://www.wikidata.org/prop/direct/P1584": ["http://pleiades.stoa.org/places/157910"], "http://www.wikidata.org/prop/direct/P17": ["http://www.wikidata.org/entity/Q38"], "http://www.wikidata.org/prop/direct/P1936": ["http://imperium.ahlfeldt.se/places/17179"]}, "geometry": {"type": "Point", "coordinates": [8.342, 44.164]}}]}