{"type": "FeatureCollection", "id": "http://www.wikidata.org/entity/Q190777", "name": "Q190777", "features": [{"type": "Feature", "id": "http://data.archaeology.link/data/ancientports/1483", "label": "Vid, near Metkovic on R Neretva, near Hutovo Blato lake", "properties": {"http://purl.org/dc/elements/1.1/created": ["2023"], "http://purl.org/dc/elements/1.1/creator": ["http://data.archaeology.link/data/spphaefen/arthur_de_graauw"], "http://www.ancientports.com/ont#date_min": ["-30"], "http://www.opengis.net/ont/geosparql#hasGeometry": ["http://data.archaeology.link/data/ancientports/1483_geom"], "http://www.w3.org/1999/02/22-rdf-syntax-ns#type": ["http://www.ancientports.com/ont#Harbour"], "http://www.w3.org/2000/01/rdf-schema#label": ["Vid, near Metkovic on R Neretva, near Hutovo Blato lake"], "http://www.w3.org/2002/07/owl#sameAs": ["http://www.wikidata.org/entity/Q190777"], "http://www.wikidata.org/prop/direct/P1584": ["http://pleiades.stoa.org/places/197400"], "http://www.wikidata.org/prop/direct/P17": ["http://www.wikidata.org/entity/Q224"], "http://www.wikidata.org/prop/direct/P1958": ["https://www.trismegistos.org/place/16527"]}, "geometry": {"type": "Point", "coordinates": [17.6319, 43.08]}}]}