{"type": "FeatureCollection", "id": "https://www.trismegistos.org/place/16207", "name": "16207", "features": [{"type": "Feature", "id": "http://data.archaeology.link/data/ancientports/3152", "label": "Ildir, in front of Chios", "dateprops": [], "properties": {"http://purl.org/dc/elements/1.1/created": ["2023"], "http://purl.org/dc/elements/1.1/creator": ["http://data.archaeology.link/data/spphaefen/arthur_de_graauw"], "http://www.opengis.net/ont/geosparql#hasGeometry": ["http://data.archaeology.link/data/ancientports/3152_geom"], "http://www.w3.org/1999/02/22-rdf-syntax-ns#type": ["http://www.ancientports.com/ont#Harbour"], "http://www.w3.org/2000/01/rdf-schema#label": ["Ildir, in front of Chios"], "http://www.w3.org/2002/07/owl#sameAs": ["http://www.wikidata.org/entity/Q723091"], "http://www.w3.org/2006/time#hasTime": ["http://data.archaeology.link/data/ancientports/3152_foundation"], "http://www.wikidata.org/prop/direct/P1584": ["http://pleiades.stoa.org/places/550535"], "http://www.wikidata.org/prop/direct/P17": ["http://www.wikidata.org/entity/Q43"], "http://www.wikidata.org/prop/direct/P1936": ["http://imperium.ahlfeldt.se/places/21201"], "http://www.wikidata.org/prop/direct/P1958": ["https://www.trismegistos.org/place/16207"], "http://www.wikidata.org/prop/direct/P8068": ["https://topostext.org/place/384265PEry"]}, "geometry": {"type": "Point", "coordinates": [26.4811, 38.3808]}}]}