{"type": "FeatureCollection", "id": "https://topostext.org/place/435165USal", "name": "435165USal", "features": [{"type": "Feature", "id": "http://data.archaeology.link/data/ancientports/1454", "label": "Solin, near Split, on R Jadro, with submerged BA settlement at Vranjic", "properties": {"http://purl.org/dc/elements/1.1/created": ["2023"], "http://purl.org/dc/elements/1.1/creator": ["http://data.archaeology.link/data/spphaefen/arthur_de_graauw"], "http://www.ancientports.com/ont#date_min": ["-330"], "http://www.opengis.net/ont/geosparql#hasGeometry": ["http://data.archaeology.link/data/ancientports/1454_geom"], "http://www.w3.org/1999/02/22-rdf-syntax-ns#type": ["http://www.ancientports.com/ont#Shipyard"], "http://www.w3.org/2000/01/rdf-schema#label": ["Solin, near Split, on R Jadro, with submerged BA settlement at Vranjic"], "http://www.w3.org/2002/07/owl#sameAs": ["http://www.wikidata.org/entity/Q1258998"], "http://www.w3.org/2004/02/skos/core#note": ["Kurilic (2012)"], "http://www.wikidata.org/prop/direct/P1584": ["http://pleiades.stoa.org/places/197488"], "http://www.wikidata.org/prop/direct/P17": ["http://www.wikidata.org/entity/Q224"], "http://www.wikidata.org/prop/direct/P1936": ["http://imperium.ahlfeldt.se/places/10939"], "http://www.wikidata.org/prop/direct/P1958": ["https://www.trismegistos.org/place/7043"], "http://www.wikidata.org/prop/direct/P8068": ["https://topostext.org/place/435165USal"]}, "geometry": {"type": "Point", "coordinates": [16.449, 43.5363]}}]}