{"type": "FeatureCollection", "id": "http://pleiades.stoa.org/places/570579", "name": "570579", "features": [{"type": "Feature", "id": "http://data.archaeology.link/data/ancientports/1950_1", "label": "Ancient outlet of R Peneios", "properties": {"http://purl.org/dc/elements/1.1/created": ["2023"], "http://purl.org/dc/elements/1.1/creator": ["http://data.archaeology.link/data/spphaefen/arthur_de_graauw"], "http://www.ancientports.com/ont#date_min": ["-2500"], "http://www.opengis.net/ont/geosparql#hasGeometry": ["http://data.archaeology.link/data/ancientports/1950_1_geom"], "http://www.w3.org/1999/02/22-rdf-syntax-ns#type": ["http://www.ancientports.com/ont#Harbour"], "http://www.w3.org/2000/01/rdf-schema#label": ["Ancient outlet of R Peneios"], "http://www.w3.org/2002/07/owl#sameAs": ["http://www.wikidata.org/entity/Q1233866"], "http://www.wikidata.org/prop/direct/P1584": ["http://pleiades.stoa.org/places/570579"], "http://www.wikidata.org/prop/direct/P17": ["GR: Pelop"]}, "geometry": {"type": "Point", "coordinates": [21.202, 37.94]}}]}