{"type": "FeatureCollection", "id": "http://pleiades.stoa.org/places/226710", "name": "226710", "features": [{"type": "Feature", "id": "http://data.archaeology.link/data/ancientports/2569", "label": "Panskoye, in Yarylhats\u2019ka Bay", "dateprops": [], "properties": {"http://purl.org/dc/elements/1.1/created": ["2023"], "http://purl.org/dc/elements/1.1/creator": ["http://data.archaeology.link/data/spphaefen/arthur_de_graauw"], "http://www.opengis.net/ont/geosparql#hasGeometry": ["http://data.archaeology.link/data/ancientports/2569_geom"], "http://www.w3.org/1999/02/22-rdf-syntax-ns#type": ["http://www.ancientports.com/ont#Harbour"], "http://www.w3.org/2000/01/rdf-schema#label": ["Panskoye, in Yarylhats\u2019ka Bay"], "http://www.w3.org/2004/02/skos/core#note": ["Hannestad (2002)", "Tsetskhladze (1998)"], "http://www.w3.org/2006/time#hasTime": ["http://data.archaeology.link/data/ancientports/2569_foundation"], "http://www.wikidata.org/prop/direct/P1584": ["http://pleiades.stoa.org/places/226710"], "http://www.wikidata.org/prop/direct/P17": ["Ukraine Black S."], "http://www.wikidata.org/prop/direct/P1936": ["http://imperium.ahlfeldt.se/places/27949"]}, "geometry": {"type": "Point", "coordinates": [32.81367, 45.55287]}}]}