{"type": "FeatureCollection", "id": "https://topostext.org/place/388224PHer", "name": "388224PHer", "features": [{"type": "Feature", "id": "http://data.archaeology.link/data/ancientports/1685", "label": "Fort at Pyles, Thermopyles ", "dateprops": [], "properties": {"http://purl.org/dc/elements/1.1/created": ["2023"], "http://purl.org/dc/elements/1.1/creator": ["http://data.archaeology.link/data/spphaefen/arthur_de_graauw"], "http://www.opengis.net/ont/geosparql#hasGeometry": ["http://data.archaeology.link/data/ancientports/1685_geom"], "http://www.w3.org/1999/02/22-rdf-syntax-ns#type": ["http://www.ancientports.com/ont#Harbour"], "http://www.w3.org/2000/01/rdf-schema#label": ["Fort at Pyles, Thermopyles "], "http://www.w3.org/2002/07/owl#sameAs": ["http://www.wikidata.org/entity/Q131969"], "http://www.w3.org/2006/time#hasTime": ["http://data.archaeology.link/data/ancientports/1685_foundation"], "http://www.wikidata.org/prop/direct/P1584": ["http://pleiades.stoa.org/places/541140"], "http://www.wikidata.org/prop/direct/P17": ["GR: Attica +"], "http://www.wikidata.org/prop/direct/P1936": ["http://imperium.ahlfeldt.se/places/21976"], "http://www.wikidata.org/prop/direct/P1958": ["https://www.trismegistos.org/place/3614"], "http://www.wikidata.org/prop/direct/P8068": ["https://topostext.org/place/388224PHer"]}, "geometry": {"type": "Point", "coordinates": [22.5365, 38.7968]}}, {"type": "Feature", "id": "http://data.archaeology.link/data/ancientports/1686", "label": "near Iraklia, on R Asopos", "dateprops": [], "properties": {"http://purl.org/dc/elements/1.1/created": ["2023"], "http://purl.org/dc/elements/1.1/creator": ["http://data.archaeology.link/data/spphaefen/arthur_de_graauw"], "http://www.opengis.net/ont/geosparql#hasGeometry": ["http://data.archaeology.link/data/ancientports/1686_geom"], "http://www.w3.org/1999/02/22-rdf-syntax-ns#type": ["http://www.ancientports.com/ont#Shipyard"], "http://www.w3.org/2000/01/rdf-schema#label": ["near Iraklia, on R Asopos"], "http://www.w3.org/2002/07/owl#sameAs": ["http://www.wikidata.org/entity/Q1231448"], "http://www.w3.org/2006/time#hasTime": ["http://data.archaeology.link/data/ancientports/1686_foundation"], "http://www.wikidata.org/prop/direct/P1584": ["http://pleiades.stoa.org/places/541157"], "http://www.wikidata.org/prop/direct/P17": ["GR: Attica +"], "http://www.wikidata.org/prop/direct/P1936": ["http://imperium.ahlfeldt.se/places/22751"], "http://www.wikidata.org/prop/direct/P1958": ["https://www.trismegistos.org/place/11876"], "http://www.wikidata.org/prop/direct/P8068": ["https://topostext.org/place/388224PHer"]}, "geometry": {"type": "Point", "coordinates": [22.4425, 38.79077]}}]}