{"type": "FeatureCollection", "id": "http://www.wikidata.org/entity/Q868952", "name": "Q868952", "features": [{"type": "Feature", "id": "http://data.archaeology.link/data/ancientports/2953", "label": "Agios Georgios bay, on the isle of Dia", "properties": {"http://purl.org/dc/elements/1.1/created": ["2023"], "http://purl.org/dc/elements/1.1/creator": ["http://data.archaeology.link/data/spphaefen/arthur_de_graauw"], "http://www.ancientports.com/ont#date_min": ["-550"], "http://www.opengis.net/ont/geosparql#hasGeometry": ["http://data.archaeology.link/data/ancientports/2953_geom"], "http://www.w3.org/1999/02/22-rdf-syntax-ns#type": ["http://www.ancientports.com/ont#Harbour"], "http://www.w3.org/2000/01/rdf-schema#label": ["Agios Georgios bay, on the isle of Dia"], "http://www.w3.org/2002/07/owl#sameAs": ["http://www.wikidata.org/entity/Q868952"], "http://www.wikidata.org/prop/direct/P1584": ["http://pleiades.stoa.org/places/589755"], "http://www.wikidata.org/prop/direct/P17": ["GR: Crete North"]}, "geometry": {"type": "Point", "coordinates": [25.1894, 35.4407]}}]}