{"type": "FeatureCollection", "id": "http://www.wikidata.org/entity/Q65068769", "name": "Q65068769", "features": [{"type": "Feature", "id": "http://data.archaeology.link/data/ancientports/3205", "label": "Sakiz, Bodrum airport", "properties": {"http://purl.org/dc/elements/1.1/created": ["2023"], "http://purl.org/dc/elements/1.1/creator": ["http://data.archaeology.link/data/spphaefen/arthur_de_graauw"], "http://www.ancientports.com/ont#date_min": ["-30"], "http://www.opengis.net/ont/geosparql#hasGeometry": ["http://data.archaeology.link/data/ancientports/3205_geom"], "http://www.w3.org/1999/02/22-rdf-syntax-ns#type": ["http://www.ancientports.com/ont#Harbour"], "http://www.w3.org/2000/01/rdf-schema#label": ["Sakiz, Bodrum airport"], "http://www.w3.org/2002/07/owl#sameAs": ["http://www.wikidata.org/entity/Q65068769"], "http://www.wikidata.org/prop/direct/P1584": ["http://pleiades.stoa.org/places/599870"], "http://www.wikidata.org/prop/direct/P17": ["TR: West"], "http://www.wikidata.org/prop/direct/P1936": ["http://imperium.ahlfeldt.se/places/29027"], "http://www.wikidata.org/prop/direct/P1958": ["https://www.trismegistos.org/place/16154"], "http://www.wikidata.org/prop/direct/P8068": ["https://topostext.org/place/373276UPas"]}, "geometry": {"type": "Point", "coordinates": [27.65, 37.25]}}]}