{"type": "FeatureCollection", "id": "https://www.trismegistos.org/place/3371", "name": "3371", "features": [{"type": "Feature", "id": "http://data.archaeology.link/data/ancientports/428", "label": "Tarragona, quay possibly located along Carrer de Smith, near R Francoli", "properties": {"http://purl.org/dc/elements/1.1/created": ["2023"], "http://purl.org/dc/elements/1.1/creator": ["http://data.archaeology.link/data/spphaefen/arthur_de_graauw"], "http://www.ancientports.com/ont#date_min": ["-550"], "http://www.opengis.net/ont/geosparql#hasGeometry": ["http://data.archaeology.link/data/ancientports/428_geom"], "http://www.w3.org/1999/02/22-rdf-syntax-ns#type": ["http://www.ancientports.com/ont#Harbour"], "http://www.w3.org/2000/01/rdf-schema#label": ["Tarragona, quay possibly located along Carrer de Smith, near R Francoli"], "http://www.w3.org/2002/07/owl#sameAs": ["http://www.wikidata.org/entity/Q1501940"], "http://www.w3.org/2004/02/skos/core#note": ["Terrado (2019)"], "http://www.wikidata.org/prop/direct/P1584": ["http://pleiades.stoa.org/places/246349"], "http://www.wikidata.org/prop/direct/P17": ["http://www.wikidata.org/entity/Q29"], "http://www.wikidata.org/prop/direct/P1958": ["https://www.trismegistos.org/place/3371"]}, "geometry": {"type": "Point", "coordinates": [1.24534, 41.11196]}}, {"type": "Feature", "id": "http://data.archaeology.link/data/ancientports/428_1", "label": "Tarragona, Roman breakwater probably located here, with possible lighthouse el Farellon, partly demolished in 1843", "properties": {"http://purl.org/dc/elements/1.1/created": ["2023"], "http://purl.org/dc/elements/1.1/creator": ["http://data.archaeology.link/data/spphaefen/arthur_de_graauw"], "http://www.opengis.net/ont/geosparql#hasGeometry": ["http://data.archaeology.link/data/ancientports/428_1_geom"], "http://www.w3.org/1999/02/22-rdf-syntax-ns#type": ["http://www.ancientports.com/ont#Harbour"], "http://www.w3.org/2000/01/rdf-schema#label": ["Tarragona, Roman breakwater probably located here, with possible lighthouse el Farellon, partly demolished in 1843"], "http://www.w3.org/2002/07/owl#sameAs": ["http://www.wikidata.org/entity/Q1501940"], "http://www.w3.org/2004/02/skos/core#note": ["Terrado (2019)"], "http://www.wikidata.org/prop/direct/P1584": ["http://pleiades.stoa.org/places/246349"], "http://www.wikidata.org/prop/direct/P17": ["http://www.wikidata.org/entity/Q29"], "http://www.wikidata.org/prop/direct/P1958": ["https://www.trismegistos.org/place/3371"]}, "geometry": {"type": "Point", "coordinates": [1.2482, 41.1101]}}]}