{"type": "FeatureCollection", "id": "http://pleiades.stoa.org/places/275623", "name": "275623", "features": [{"type": "Feature", "id": "http://data.archaeology.link/data/ancientports/4284", "label": "Emsa, Amsa, Kubia, Cudia Tebmain, possible fish processing factory and amphora kilns", "dateprops": ["http://purl.org/dc/elements/1.1/created", "http://www.ancientports.com/ont#date_min"], "properties": {"http://purl.org/dc/elements/1.1/created": ["2023"], "http://purl.org/dc/elements/1.1/creator": ["http://data.archaeology.link/data/spphaefen/arthur_de_graauw"], "http://www.ancientports.com/ont#date_min": ["-330"], "http://www.opengis.net/ont/geosparql#hasGeometry": ["http://data.archaeology.link/data/ancientports/4284_geom"], "http://www.w3.org/1999/02/22-rdf-syntax-ns#type": ["http://www.ancientports.com/ont#Harbour"], "http://www.w3.org/2000/01/rdf-schema#label": ["Emsa, Amsa, Kubia, Cudia Tebmain, possible fish processing factory and amphora kilns"], "http://www.wikidata.org/prop/direct/P1584": ["http://pleiades.stoa.org/places/275623"], "http://www.wikidata.org/prop/direct/P17": ["http://www.wikidata.org/entity/Q1028"], "http://www.wikidata.org/prop/direct/P1936": ["http://imperium.ahlfeldt.se/places/26963"]}, "geometry": {"type": "Point", "coordinates": [-5.23162, 35.52383]}}]}