{"type": "FeatureCollection", "id": "http://imperium.ahlfeldt.se/places/29078", "name": "29078", "features": [{"type": "Feature", "id": "http://data.archaeology.link/data/ancientports/3138", "name": "Yenifoca", "dateprops": ["begin"], "properties": {"http://purl.org/dc/elements/1.1/creator": ["http://data.archaeology.link/data/spphaefen/arthur_de_graauw"], "http://purl.org/dc/terms/partOf": ["http://data.archaeology.link/data/ancientports/bib_deGrauw_2013_GeoDB"], "http://www.opengis.net/ont/geosparql#hasGeometry": ["http://data.archaeology.link/data/ancientports/3138_geom"], "http://www.w3.org/1999/02/22-rdf-syntax-ns#type": ["http://www.ancientports.com/ont#Harbour"], "http://www.w3.org/2000/01/rdf-schema#label": ["Yenifoca"], "http://www.w3.org/2002/07/owl#sameAs": ["http://www.wikidata.org/entity/Q3397466"], "http://www.w3.org/2006/time#hasTime": ["http://data.archaeology.link/data/ancientports/3138_foundation"], "http://www.wikidata.org/prop/direct/P1584": ["http://pleiades.stoa.org/places/550674"], "http://www.wikidata.org/prop/direct/P17": ["http://www.wikidata.org/entity/Q43"], "http://www.wikidata.org/prop/direct/P1936": ["http://imperium.ahlfeldt.se/places/29078"], "begin": "-550"}, "geometry": {"type": "Point", "coordinates": [26.84083, 38.74852]}}], "numberMatched": 1, "numberReturned": 1, "bbox": [26.84083, 38.74852, 26.84083, 38.74852], "crs": "http://www.opengis.net/def/crs/EPSG/0/4326"}