{"type": "FeatureCollection", "id": "http://www.wikidata.org/entity/Q292271", "name": "Q292271", "features": [{"type": "Feature", "id": "http://data.archaeology.link/data/ancientports/733", "label": "Anse de Palma, on Cavallo island, at the Bouches de Bonifacio", "dateprops": [], "properties": {"http://purl.org/dc/elements/1.1/created": ["2023"], "http://purl.org/dc/elements/1.1/creator": ["http://data.archaeology.link/data/spphaefen/arthur_de_graauw"], "http://www.opengis.net/ont/geosparql#hasGeometry": ["http://data.archaeology.link/data/ancientports/733_geom"], "http://www.w3.org/1999/02/22-rdf-syntax-ns#type": ["http://www.ancientports.com/ont#Harbour"], "http://www.w3.org/2000/01/rdf-schema#label": ["Anse de Palma, on Cavallo island, at the Bouches de Bonifacio"], "http://www.w3.org/2002/07/owl#sameAs": ["http://www.wikidata.org/entity/Q292271"], "http://www.wikidata.org/prop/direct/P1584": ["https://pleiades.stoa.org/places/471933"], "http://www.wikidata.org/prop/direct/P17": ["France Corsica"], "http://www.wikidata.org/prop/direct/P1936": ["http://imperium.ahlfeldt.se/places/41698"]}, "geometry": {"type": "Point", "coordinates": [9.2685, 41.366]}}, {"type": "Feature", "id": "http://data.archaeology.link/data/ancientports/733_1", "label": "Anse de Capisono, on Cavallo island", "dateprops": [], "properties": {"http://purl.org/dc/elements/1.1/created": ["2023"], "http://purl.org/dc/elements/1.1/creator": ["http://data.archaeology.link/data/spphaefen/arthur_de_graauw"], "http://www.opengis.net/ont/geosparql#hasGeometry": ["http://data.archaeology.link/data/ancientports/733_1_geom"], "http://www.w3.org/1999/02/22-rdf-syntax-ns#type": ["http://www.ancientports.com/ont#Harbour"], "http://www.w3.org/2000/01/rdf-schema#label": ["Anse de Capisono, on Cavallo island"], "http://www.w3.org/2002/07/owl#sameAs": ["http://www.wikidata.org/entity/Q292271"], "http://www.w3.org/2004/02/skos/core#note": ["Vidal (2014)"], "http://www.wikidata.org/prop/direct/P17": ["France Corsica"]}, "geometry": {"type": "Point", "coordinates": [9.266, 41.3648]}}, {"type": "Feature", "id": "http://data.archaeology.link/data/ancientports/733_2", "label": "San Bainzu, quarry with quay on Cavallo island", "dateprops": [], "properties": {"http://purl.org/dc/elements/1.1/created": ["2023"], "http://purl.org/dc/elements/1.1/creator": ["http://data.archaeology.link/data/spphaefen/arthur_de_graauw"], "http://www.opengis.net/ont/geosparql#hasGeometry": ["http://data.archaeology.link/data/ancientports/733_2_geom"], "http://www.w3.org/1999/02/22-rdf-syntax-ns#type": ["http://www.ancientports.com/ont#Quay"], "http://www.w3.org/2000/01/rdf-schema#label": ["San Bainzu, quarry with quay on Cavallo island"], "http://www.w3.org/2002/07/owl#sameAs": ["http://www.wikidata.org/entity/Q292271"], "http://www.w3.org/2004/02/skos/core#note": ["Brkojewitsch (2018)"], "http://www.wikidata.org/prop/direct/P17": ["France Corsica"]}, "geometry": {"type": "Point", "coordinates": [9.2612, 41.3617]}}]}