{"type": "FeatureCollection", "id": "http://www.wikidata.org/entity/Q3561270", "name": "Q3561270", "features": [{"type": "Feature", "id": "http://data.archaeology.link/data/ancientports/1613", "label": "Alyki", "dateprops": [], "properties": {"http://purl.org/dc/elements/1.1/created": ["2023"], "http://purl.org/dc/elements/1.1/creator": ["http://data.archaeology.link/data/spphaefen/arthur_de_graauw"], "http://www.opengis.net/ont/geosparql#hasGeometry": ["http://data.archaeology.link/data/ancientports/1613_geom"], "http://www.w3.org/1999/02/22-rdf-syntax-ns#type": ["http://www.ancientports.com/ont#Harbour"], "http://www.w3.org/2000/01/rdf-schema#label": ["Alyki"], "http://www.w3.org/2002/07/owl#sameAs": ["http://www.wikidata.org/entity/Q3561270"], "http://www.w3.org/2006/time#hasTime": ["http://data.archaeology.link/data/ancientports/1613_foundation"], "http://www.wikidata.org/prop/direct/P1584": ["http://pleiades.stoa.org/places/541102"], "http://www.wikidata.org/prop/direct/P17": ["GR: North-West"], "http://www.wikidata.org/prop/direct/P1936": ["http://imperium.ahlfeldt.se/places/29461"], "http://www.wikidata.org/prop/direct/P1958": ["https://www.trismegistos.org/place/33340"], "http://www.wikidata.org/prop/direct/P8068": ["https://topostext.org/place/382230PSip"]}, "geometry": {"type": "Point", "coordinates": [23.052, 38.19]}}]}