{"type": "FeatureCollection", "id": "https://topostext.org/place/347331PAma", "name": "347331PAma", "features": [{"type": "Feature", "id": "http://data.archaeology.link/data/ancientports/3058", "label": "Amathus, 10 km east of Limassol", "dateprops": [], "properties": {"http://purl.org/dc/elements/1.1/created": ["2023"], "http://purl.org/dc/elements/1.1/creator": ["http://data.archaeology.link/data/spphaefen/arthur_de_graauw"], "http://purl.org/dc/terms/isReferencedBy": ["https://www2.rgzm.de/navis2/home/frames.htm"], "http://www.ancientports.com/ont#date_min": ["-1100"], "http://www.opengis.net/ont/geosparql#hasGeometry": ["http://data.archaeology.link/data/ancientports/3058_geom"], "http://www.w3.org/1999/02/22-rdf-syntax-ns#type": ["http://www.ancientports.com/ont#Quay"], "http://www.w3.org/2000/01/rdf-schema#label": ["Amathus, 10 km east of Limassol"], "http://www.w3.org/2004/02/skos/core#note": ["Aupert (2020)", "Chabrol (2014-2018)"], "http://www.wikidata.org/prop/direct/P1584": ["http://pleiades.stoa.org/places/707462"], "http://www.wikidata.org/prop/direct/P17": ["http://www.wikidata.org/entity/Q229"], "http://www.wikidata.org/prop/direct/P1936": ["http://imperium.ahlfeldt.se/places/21564"], "http://www.wikidata.org/prop/direct/P1958": ["https://www.trismegistos.org/place/134"], "http://www.wikidata.org/prop/direct/P8068": ["https://topostext.org/place/347331PAma"]}, "geometry": {"type": "Point", "coordinates": [33.14389, 34.70958]}}]}