{"type": "FeatureCollection", "id": "http://pleiades.stoa.org/places/462283", "name": "462283", "features": [{"type": "Feature", "id": "http://data.archaeology.link/data/ancientports/1205", "label": "Sottomonastero, on the isle of Lipari", "properties": {"http://purl.org/dc/elements/1.1/created": ["2023"], "http://purl.org/dc/elements/1.1/creator": ["http://data.archaeology.link/data/spphaefen/arthur_de_graauw"], "http://www.ancientports.com/ont#date_min": ["-1500"], "http://www.opengis.net/ont/geosparql#hasGeometry": ["http://data.archaeology.link/data/ancientports/1205_geom"], "http://www.w3.org/1999/02/22-rdf-syntax-ns#type": ["http://www.ancientports.com/ont#Harbour"], "http://www.w3.org/2000/01/rdf-schema#label": ["Sottomonastero, on the isle of Lipari"], "http://www.w3.org/2002/07/owl#sameAs": ["http://www.wikidata.org/entity/Q496389"], "http://www.w3.org/2004/02/skos/core#note": ["La Rocca (2021)"], "http://www.wikidata.org/prop/direct/P1584": ["http://pleiades.stoa.org/places/462283"], "http://www.wikidata.org/prop/direct/P17": ["Italy Sicily"], "http://www.wikidata.org/prop/direct/P1958": ["https://www.trismegistos.org/place/22311"]}, "geometry": {"type": "Point", "coordinates": [14.9568, 38.4717]}}]}