{"type": "FeatureCollection", "id": "http://pleiades.stoa.org/places/570694", "name": "570694", "features": [{"type": "Feature", "id": "http://data.archaeology.link/data/ancientports/1883_1", "label": "Tuphekares", "dateprops": [], "properties": {"http://purl.org/dc/elements/1.1/created": ["2023"], "http://purl.org/dc/elements/1.1/creator": ["http://data.archaeology.link/data/spphaefen/arthur_de_graauw"], "http://www.opengis.net/ont/geosparql#hasGeometry": ["http://data.archaeology.link/data/ancientports/1883_1_geom"], "http://www.w3.org/1999/02/22-rdf-syntax-ns#type": ["http://www.ancientports.com/ont#Harbour"], "http://www.w3.org/2000/01/rdf-schema#label": ["Tuphekares"], "http://www.wikidata.org/prop/direct/P1584": ["http://pleiades.stoa.org/places/570694"], "http://www.wikidata.org/prop/direct/P17": ["GR: Pelop"], "http://www.wikidata.org/prop/direct/P1936": ["http://imperium.ahlfeldt.se/places/43598"], "http://www.wikidata.org/prop/direct/P8068": ["https://topostext.org/place/373233LStr"]}, "geometry": {"type": "Point", "coordinates": [23.008, 37.4645]}}]}