{"type": "FeatureCollection", "id": "http://www.wikidata.org/entity/Q1035742", "name": "Q1035742", "features": [{"type": "Feature", "id": "http://data.archaeology.link/data/ancientports/121", "label": "Cardiff ", "properties": {"http://purl.org/dc/elements/1.1/created": ["2023"], "http://purl.org/dc/elements/1.1/creator": ["http://data.archaeology.link/data/spphaefen/arthur_de_graauw"], "http://www.ancientports.com/ont#date_min": ["1001"], "http://www.opengis.net/ont/geosparql#hasGeometry": ["http://data.archaeology.link/data/ancientports/121_geom"], "http://www.w3.org/1999/02/22-rdf-syntax-ns#type": ["http://www.ancientports.com/ont#Harbour"], "http://www.w3.org/2000/01/rdf-schema#label": ["Cardiff "], "http://www.w3.org/2002/07/owl#sameAs": ["http://www.wikidata.org/entity/Q1035742"], "http://www.wikidata.org/prop/direct/P1584": ["http://pleiades.stoa.org/places/79706"], "http://www.wikidata.org/prop/direct/P17": ["UK"], "http://www.wikidata.org/prop/direct/P1936": ["http://imperium.ahlfeldt.se/places/23020"], "http://www.wikidata.org/prop/direct/P1958": ["https://www.trismegistos.org/place/15358"]}, "geometry": {"type": "Point", "coordinates": [-3.18095, 51.48197]}}]}