{"type": "FeatureCollection", "id": "http://www.wikidata.org/entity/Q1605692", "name": "Q1605692", "features": [{"type": "Feature", "id": "http://data.archaeology.link/data/ancientports/313", "label": "Palomares del Rio ", "dateprops": ["http://purl.org/dc/elements/1.1/created", "http://www.ancientports.com/ont#date_min"], "properties": {"http://purl.org/dc/elements/1.1/created": ["2023"], "http://purl.org/dc/elements/1.1/creator": ["http://data.archaeology.link/data/spphaefen/arthur_de_graauw"], "http://www.ancientports.com/ont#date_min": ["-30"], "http://www.opengis.net/ont/geosparql#hasGeometry": ["http://data.archaeology.link/data/ancientports/313_geom"], "http://www.w3.org/1999/02/22-rdf-syntax-ns#type": ["http://www.ancientports.com/ont#Harbour"], "http://www.w3.org/2000/01/rdf-schema#label": ["Palomares del Rio "], "http://www.w3.org/2002/07/owl#sameAs": ["http://www.wikidata.org/entity/Q1605692"], "http://www.wikidata.org/prop/direct/P1584": ["http://pleiades.stoa.org/places/256355"], "http://www.wikidata.org/prop/direct/P17": ["http://www.wikidata.org/entity/Q29"], "http://www.wikidata.org/prop/direct/P1936": ["http://imperium.ahlfeldt.se/places/31302"], "http://www.wikidata.org/prop/direct/P1958": ["https://www.trismegistos.org/place/26238"]}, "geometry": {"type": "Point", "coordinates": [-6.05819, 37.32103]}}]}