{"type": "FeatureCollection", "id": "http://imperium.ahlfeldt.se/places/21723", "name": "21723", "features": [{"type": "Feature", "id": "http://data.archaeology.link/data/ancientports/3437", "label": "Ard Artusi, on R Nahr al-Berid", "properties": {"http://purl.org/dc/elements/1.1/created": ["2023"], "http://purl.org/dc/elements/1.1/creator": ["http://data.archaeology.link/data/spphaefen/arthur_de_graauw"], "http://www.ancientports.com/ont#date_min": ["-1500"], "http://www.opengis.net/ont/geosparql#hasGeometry": ["http://data.archaeology.link/data/ancientports/3437_geom"], "http://www.w3.org/1999/02/22-rdf-syntax-ns#type": ["http://www.ancientports.com/ont#Harbour"], "http://www.w3.org/2000/01/rdf-schema#label": ["Ard Artusi, on R Nahr al-Berid"], "http://www.w3.org/2002/07/owl#sameAs": ["http://www.wikidata.org/entity/Q90309498"], "http://www.w3.org/2004/02/skos/core#note": ["Carayon (2012)"], "http://www.wikidata.org/prop/direct/P1584": ["http://pleiades.stoa.org/places/668325"], "http://www.wikidata.org/prop/direct/P17": ["http://www.wikidata.org/entity/Q822"], "http://www.wikidata.org/prop/direct/P1936": ["http://imperium.ahlfeldt.se/places/21723"], "http://www.wikidata.org/prop/direct/P1958": ["https://www.trismegistos.org/place/1516"], "http://www.wikidata.org/prop/direct/P8068": ["https://topostext.org/place/345360UOrt"]}, "geometry": {"type": "Point", "coordinates": [35.9462, 34.5077]}}]}