{"type": "FeatureCollection", "id": "https://www.trismegistos.org/place/45030", "name": "45030", "features": [{"type": "Feature", "id": "http://data.archaeology.link/data/ancientports/271", "label": "Mythical site located by Plato beyond the Pillars of Hercules and by Diodore at several days of navigation near West Afrika, but the location of this island is still much debated (perhaps somewhere between R Guadiana and R Guadalquivir in the Tartessos country, some locate it on Santorini island)", "dateprops": [], "properties": {"http://purl.org/dc/elements/1.1/created": ["2023"], "http://purl.org/dc/elements/1.1/creator": ["http://data.archaeology.link/data/spphaefen/arthur_de_graauw"], "http://purl.org/dc/terms/isReferencedBy": ["https://www.atlantis-scout.de/"], "http://www.opengis.net/ont/geosparql#hasGeometry": ["http://data.archaeology.link/data/ancientports/271_geom"], "http://www.w3.org/1999/02/22-rdf-syntax-ns#type": ["http://www.ancientports.com/ont#Shipyard"], "http://www.w3.org/2000/01/rdf-schema#label": ["Mythical site located by Plato beyond the Pillars of Hercules and by Diodore at several days of navigation near West Afrika, but the location of this island is still much debated (perhaps somewhere between R Guadiana and R Guadalquivir in the Tartessos country, some locate it on Santorini island)"], "http://www.w3.org/2002/07/owl#sameAs": ["http://www.wikidata.org/entity/Q25373"], "http://www.wikidata.org/prop/direct/P1584": ["https://pleiades.stoa.org/places/845"], "http://www.wikidata.org/prop/direct/P17": ["http://www.wikidata.org/entity/Q45"], "http://www.wikidata.org/prop/direct/P1958": ["https://www.trismegistos.org/place/45030"], "http://www.wikidata.org/prop/direct/P8068": ["https://topostext.org/place/000000IAtl"]}, "geometry": {"type": "Point", "coordinates": [-9.11912, 37.01227]}}]}