{"type": "FeatureCollection", "id": "https://topostext.org/place/406143SMin", "name": "406143SMin", "features": [{"type": "Feature", "id": "http://data.archaeology.link/data/ancientports/1008_1", "name": "Roman villa at Punta Campanella", "dateprops": ["begin"], "properties": {"http://purl.org/dc/elements/1.1/creator": ["http://data.archaeology.link/data/spphaefen/arthur_de_graauw"], "http://purl.org/dc/terms/isReferencedBy": ["http://data.archaeology.link/data/ancientports/bib_Aucelli_2016_Historical"], "http://purl.org/dc/terms/partOf": ["http://data.archaeology.link/data/ancientports/bib_deGrauw_2013_GeoDB"], "http://www.opengis.net/ont/geosparql#hasGeometry": ["http://data.archaeology.link/data/ancientports/1008_1_geom"], "http://www.w3.org/1999/02/22-rdf-syntax-ns#type": ["http://www.ancientports.com/ont#Quay"], "http://www.w3.org/2000/01/rdf-schema#label": ["Roman villa at Punta Campanella"], "http://www.w3.org/2002/07/owl#sameAs": ["http://www.wikidata.org/entity/Q28376423"], "http://www.w3.org/2006/time#hasTime": ["http://data.archaeology.link/data/ancientports/1008_1_foundation"], "http://www.wikidata.org/prop/direct/P1584": ["https://pleiades.stoa.org/places/432938"], "http://www.wikidata.org/prop/direct/P17": ["http://www.wikidata.org/entity/Q38"], "http://www.wikidata.org/prop/direct/P1936": ["http://imperium.ahlfeldt.se/places/41250"], "http://www.wikidata.org/prop/direct/P1958": ["https://www.trismegistos.org/place/49920"], "http://www.wikidata.org/prop/direct/P8068": ["https://topostext.org/place/406143SMin"], "begin": "-30"}, "geometry": {"type": "Point", "coordinates": [14.3244, 40.5692]}}]}