{"type": "FeatureCollection", "id": "https://topostext.org/place/363277IDim", "name": "363277IDim", "features": [{"type": "Feature", "id": "http://data.archaeology.link/data/ancientports/2314_1", "label": "Isle of Agios Theodoros, near Rhodes", "dateprops": [], "properties": {"http://purl.org/dc/elements/1.1/created": ["2023"], "http://purl.org/dc/elements/1.1/creator": ["http://data.archaeology.link/data/spphaefen/arthur_de_graauw"], "http://www.opengis.net/ont/geosparql#hasGeometry": ["http://data.archaeology.link/data/ancientports/2314_1_geom"], "http://www.w3.org/1999/02/22-rdf-syntax-ns#type": ["http://www.ancientports.com/ont#Harbour"], "http://www.w3.org/2000/01/rdf-schema#label": ["Isle of Agios Theodoros, near Rhodes"], "http://www.wikidata.org/prop/direct/P1584": ["http://pleiades.stoa.org/places/589761"], "http://www.wikidata.org/prop/direct/P17": ["http://www.wikidata.org/entity/Q41"], "http://www.wikidata.org/prop/direct/P1936": ["http://imperium.ahlfeldt.se/places/41165"], "http://www.wikidata.org/prop/direct/P8068": ["https://topostext.org/place/363277IDim"]}, "geometry": {"type": "Point", "coordinates": [27.655, 36.256]}}]}