{"type": "FeatureCollection", "id": "http://pleiades.stoa.org/places/590037", "name": "590037", "features": [{"type": "Feature", "id": "http://data.archaeology.link/data/ancientports/2979", "label": "Cape Sidero, but Uggeri claims it could be at Tenta bay & beach, 3.5 km SSW of this place", "dateprops": [], "properties": {"http://purl.org/dc/elements/1.1/created": ["2023"], "http://purl.org/dc/elements/1.1/creator": ["http://data.archaeology.link/data/spphaefen/arthur_de_graauw"], "http://purl.org/dc/terms/isReferencedBy": ["https://topostext.org/place/353263SAth"], "http://www.opengis.net/ont/geosparql#hasGeometry": ["http://data.archaeology.link/data/ancientports/2979_geom"], "http://www.w3.org/1999/02/22-rdf-syntax-ns#type": ["http://www.ancientports.com/ont#Harbour"], "http://www.w3.org/2000/01/rdf-schema#label": ["Cape Sidero, but Uggeri claims it could be at Tenta bay & beach, 3.5 km SSW of this place"], "http://www.w3.org/2002/07/owl#sameAs": ["http://www.wikidata.org/entity/Q2937111"], "http://www.w3.org/2004/02/skos/core#note": ["Uggeri (2003)"], "http://www.w3.org/2006/time#hasTime": ["http://data.archaeology.link/data/ancientports/2979_foundation"], "http://www.wikidata.org/prop/direct/P1584": ["http://pleiades.stoa.org/places/590037"], "http://www.wikidata.org/prop/direct/P17": ["http://www.wikidata.org/entity/Q41"], "http://www.wikidata.org/prop/direct/P1936": ["http://imperium.ahlfeldt.se/places/36683"], "http://www.wikidata.org/prop/direct/P8068": ["https://topostext.org/place/353263LSam"]}, "geometry": {"type": "Point", "coordinates": [26.3114, 35.314]}}]}