{"type": "FeatureCollection", "id": "https://www.trismegistos.org/place/14147", "name": "14147", "features": [{"type": "Feature", "id": "http://data.archaeology.link/data/ancientports/4103", "name": "el-Kantara, on the isle of Djerba", "dateprops": ["begin"], "properties": {"http://purl.org/dc/elements/1.1/creator": ["http://data.archaeology.link/data/spphaefen/arthur_de_graauw"], "http://purl.org/dc/terms/isReferencedBy": ["http://data.archaeology.link/data/ancientports/bib_Paskoff_1991_Le"], "http://purl.org/dc/terms/partOf": ["http://data.archaeology.link/data/ancientports/bib_deGrauw_2013_GeoDB"], "http://www.opengis.net/ont/geosparql#hasGeometry": ["http://data.archaeology.link/data/ancientports/4103_geom"], "http://www.w3.org/1999/02/22-rdf-syntax-ns#type": ["http://www.ancientports.com/ont#Quay"], "http://www.w3.org/2000/01/rdf-schema#label": ["el-Kantara, on the isle of Djerba"], "http://www.w3.org/2002/07/owl#sameAs": ["http://www.wikidata.org/entity/Q3306003"], "http://www.w3.org/2004/02/skos/core#note": ["Desanges (2008)", "Drine (2014)"], "http://www.w3.org/2006/time#hasTime": ["http://data.archaeology.link/data/ancientports/4103_foundation"], "http://www.wikidata.org/prop/direct/P1584": ["http://pleiades.stoa.org/places/344440"], "http://www.wikidata.org/prop/direct/P17": ["http://www.wikidata.org/entity/Q948"], "http://www.wikidata.org/prop/direct/P1936": ["http://imperium.ahlfeldt.se/places/41304"], "http://www.wikidata.org/prop/direct/P1958": ["https://www.trismegistos.org/place/14147"], "http://www.wikidata.org/prop/direct/P8068": ["https://topostext.org/place/338109IMen"], "begin": "-330"}, "geometry": {"type": "Point", "coordinates": [10.92065, 33.68295]}}], "numberMatched": 1, "numberReturned": 1}