{"type": "FeatureCollection", "id": "https://www.trismegistos.org/place/37921", "name": "37921", "features": [{"type": "Feature", "id": "http://data.archaeology.link/data/ancientports/1874", "name": "Ydra, on the isle of Idra", "dateprops": ["begin"], "properties": {"http://purl.org/dc/elements/1.1/created": ["2023"], "http://purl.org/dc/elements/1.1/creator": ["http://data.archaeology.link/data/spphaefen/arthur_de_graauw"], "http://www.opengis.net/ont/geosparql#hasGeometry": ["http://data.archaeology.link/data/ancientports/1874_geom"], "http://www.w3.org/1999/02/22-rdf-syntax-ns#type": ["http://www.ancientports.com/ont#Harbour"], "http://www.w3.org/2000/01/rdf-schema#label": ["Ydra, on the isle of Idra"], "http://www.w3.org/2002/07/owl#sameAs": ["http://www.wikidata.org/entity/Q208319"], "http://www.w3.org/2006/time#hasTime": ["http://data.archaeology.link/data/ancientports/1874_foundation"], "http://www.wikidata.org/prop/direct/P1584": ["http://pleiades.stoa.org/places/570299"], "http://www.wikidata.org/prop/direct/P17": ["http://www.wikidata.org/entity/Q41"], "http://www.wikidata.org/prop/direct/P1936": ["http://imperium.ahlfeldt.se/places/41225"], "http://www.wikidata.org/prop/direct/P1958": ["https://www.trismegistos.org/place/37921"], "http://www.wikidata.org/prop/direct/P8068": ["https://topostext.org/place/373235IHyd"], "begin": "-3000"}, "geometry": {"type": "Point", "coordinates": [23.466, 37.3504]}}, {"type": "Feature", "id": "http://data.archaeology.link/data/ancientports/1875", "name": "Mycenaean fort at Choriza, on the isle of Idra", "dateprops": ["begin"], "properties": {"http://purl.org/dc/elements/1.1/created": ["2023"], "http://purl.org/dc/elements/1.1/creator": ["http://data.archaeology.link/data/spphaefen/arthur_de_graauw"], "http://www.opengis.net/ont/geosparql#hasGeometry": ["http://data.archaeology.link/data/ancientports/1875_geom"], "http://www.w3.org/1999/02/22-rdf-syntax-ns#type": ["http://www.ancientports.com/ont#Harbour"], "http://www.w3.org/2000/01/rdf-schema#label": ["Mycenaean fort at Choriza, on the isle of Idra"], "http://www.w3.org/2006/time#hasTime": ["http://data.archaeology.link/data/ancientports/1875_foundation"], "http://www.wikidata.org/prop/direct/P17": ["http://www.wikidata.org/entity/Q41"], "http://www.wikidata.org/prop/direct/P1958": ["https://www.trismegistos.org/place/37921"], "http://www.wikidata.org/prop/direct/P8068": ["https://topostext.org/place/373234XVly"], "begin": "-3000"}, "geometry": {"type": "Point", "coordinates": [23.4496, 37.3436]}}, {"type": "Feature", "id": "http://data.archaeology.link/data/ancientports/1875_1", "name": "Port of Episkopi, on the isle of Idra", "dateprops": ["begin"], "properties": {"http://purl.org/dc/elements/1.1/created": ["2023"], "http://purl.org/dc/elements/1.1/creator": ["http://data.archaeology.link/data/spphaefen/arthur_de_graauw"], "http://www.opengis.net/ont/geosparql#hasGeometry": ["http://data.archaeology.link/data/ancientports/1875_1_geom"], "http://www.w3.org/1999/02/22-rdf-syntax-ns#type": ["http://www.ancientports.com/ont#Harbour"], "http://www.w3.org/2000/01/rdf-schema#label": ["Port of Episkopi, on the isle of Idra"], "http://www.w3.org/2006/time#hasTime": ["http://data.archaeology.link/data/ancientports/1875_1_foundation"], "http://www.wikidata.org/prop/direct/P17": ["http://www.wikidata.org/entity/Q41"], "http://www.wikidata.org/prop/direct/P1958": ["https://www.trismegistos.org/place/37921"], "http://www.wikidata.org/prop/direct/P8068": ["https://topostext.org/place/373234XEpi"], "begin": "-3000"}, "geometry": {"type": "Point", "coordinates": [23.4393, 37.3117]}}]}