{"type": "FeatureCollection", "id": "http://imperium.ahlfeldt.se/places/21216", "name": "21216", "features": [{"type": "Feature", "id": "http://data.archaeology.link/data/ancientports/2376", "label": "Akbas liman", "dateprops": [], "properties": {"http://purl.org/dc/elements/1.1/created": ["2023"], "http://purl.org/dc/elements/1.1/creator": ["http://data.archaeology.link/data/spphaefen/arthur_de_graauw"], "http://www.opengis.net/ont/geosparql#hasGeometry": ["http://data.archaeology.link/data/ancientports/2376_geom"], "http://www.w3.org/1999/02/22-rdf-syntax-ns#type": ["http://www.ancientports.com/ont#Harbour"], "http://www.w3.org/2000/01/rdf-schema#label": ["Akbas liman"], "http://www.w3.org/2002/07/owl#sameAs": ["http://www.wikidata.org/entity/Q593737"], "http://www.w3.org/2004/02/skos/core#note": ["Tsvetkova (2008)"], "http://www.w3.org/2006/time#hasTime": ["http://data.archaeology.link/data/ancientports/2376_foundation"], "http://www.wikidata.org/prop/direct/P1584": ["http://pleiades.stoa.org/places/501609"], "http://www.wikidata.org/prop/direct/P17": ["TR: Marmara N"], "http://www.wikidata.org/prop/direct/P1936": ["http://imperium.ahlfeldt.se/places/21216"], "http://www.wikidata.org/prop/direct/P1958": ["https://www.trismegistos.org/place/15966"], "http://www.wikidata.org/prop/direct/P8068": ["https://topostext.org/place/402264USes"]}, "geometry": {"type": "Point", "coordinates": [26.427, 40.2299]}}, {"type": "Feature", "id": "http://data.archaeology.link/data/ancientports/2376_1", "label": "Akbas burnu", "dateprops": [], "properties": {"http://purl.org/dc/elements/1.1/created": ["2023"], "http://purl.org/dc/elements/1.1/creator": ["http://data.archaeology.link/data/spphaefen/arthur_de_graauw"], "http://www.opengis.net/ont/geosparql#hasGeometry": ["http://data.archaeology.link/data/ancientports/2376_1_geom"], "http://www.w3.org/1999/02/22-rdf-syntax-ns#type": ["http://www.ancientports.com/ont#Harbour"], "http://www.w3.org/2000/01/rdf-schema#label": ["Akbas burnu"], "http://www.w3.org/2002/07/owl#sameAs": ["http://www.wikidata.org/entity/Q593737"], "http://www.wikidata.org/prop/direct/P1584": ["http://pleiades.stoa.org/places/501609"], "http://www.wikidata.org/prop/direct/P17": ["TR: Marmara N"], "http://www.wikidata.org/prop/direct/P1936": ["http://imperium.ahlfeldt.se/places/21216"], "http://www.wikidata.org/prop/direct/P1958": ["https://www.trismegistos.org/place/15966"], "http://www.wikidata.org/prop/direct/P8068": ["https://topostext.org/place/402264USes"]}, "geometry": {"type": "Point", "coordinates": [26.432, 40.2309]}}]}