{"type": "FeatureCollection", "id": "http://imperium.ahlfeldt.se/places/17469", "name": "17469", "features": [{"type": "Feature", "id": "http://data.archaeology.link/data/ancientports/603", "name": "Roman villa at Le Verdon sur Mer", "dateprops": ["begin"], "properties": {"http://purl.org/dc/elements/1.1/creator": ["http://data.archaeology.link/data/spphaefen/arthur_de_graauw"], "http://purl.org/dc/terms/partOf": ["http://data.archaeology.link/data/ancientports/bib_deGrauw_2013_GeoDB"], "http://www.opengis.net/ont/geosparql#hasGeometry": ["http://data.archaeology.link/data/ancientports/603_geom"], "http://www.w3.org/1999/02/22-rdf-syntax-ns#type": ["http://www.ancientports.com/ont#VillaMaritima"], "http://www.w3.org/2000/01/rdf-schema#label": ["Roman villa at Le Verdon sur Mer"], "http://www.w3.org/2002/07/owl#sameAs": ["http://www.wikidata.org/entity/Q186324"], "http://www.w3.org/2006/time#hasTime": ["http://data.archaeology.link/data/ancientports/603_foundation"], "http://www.wikidata.org/prop/direct/P1584": ["http://pleiades.stoa.org/places/138333"], "http://www.wikidata.org/prop/direct/P17": ["http://www.wikidata.org/entity/Q142"], "http://www.wikidata.org/prop/direct/P1936": ["http://imperium.ahlfeldt.se/places/17469"], "begin": "3001"}, "geometry": {"type": "Point", "coordinates": [-1.06331, 45.54341]}}], "numberMatched": 1, "numberReturned": 1, "bbox": [-1.06331, 45.54341, -1.06331, 45.54341], "crs": "http://www.opengis.net/def/crs/OGC/1.3/CRS84"}