{"type": "FeatureCollection", "id": "http://pleiades.stoa.org/places/541094", "name": "541094", "features": [{"type": "Feature", "id": "http://data.archaeology.link/data/ancientports/2236", "label": "Loutraki, on the isle of Skopelos", "dateprops": ["http://purl.org/dc/elements/1.1/created"], "properties": {"http://purl.org/dc/elements/1.1/created": ["2023"], "http://purl.org/dc/elements/1.1/creator": ["http://data.archaeology.link/data/spphaefen/arthur_de_graauw"], "http://www.opengis.net/ont/geosparql#hasGeometry": ["http://data.archaeology.link/data/ancientports/2236_geom"], "http://www.w3.org/1999/02/22-rdf-syntax-ns#type": ["http://www.ancientports.com/ont#VillaMaritima"], "http://www.w3.org/2000/01/rdf-schema#label": ["Loutraki, on the isle of Skopelos"], "http://www.w3.org/2004/02/skos/core#note": ["Ginalis (2018b)"], "http://www.w3.org/2006/time#hasTime": ["http://data.archaeology.link/data/ancientports/2236_foundation"], "http://www.wikidata.org/prop/direct/P1584": ["http://pleiades.stoa.org/places/541094"], "http://www.wikidata.org/prop/direct/P17": ["GR: Eastern Isl."], "http://www.wikidata.org/prop/direct/P1936": ["http://imperium.ahlfeldt.se/places/29460"], "http://www.wikidata.org/prop/direct/P1958": ["https://www.trismegistos.org/place/33248"], "http://www.wikidata.org/prop/direct/P8068": ["https://topostext.org/place/392236USel"]}, "geometry": {"type": "Point", "coordinates": [23.6122, 39.1708]}}]}