{"type": "FeatureCollection", "id": "http://www.wikidata.org/entity/Q1724240", "name": "Norman%27s Law", "features": [{"type": "Feature", "id": "http://data.archaeology.link/data/ancientports/44_1", "name": "", "dateprops": ["begin"], "properties": {"http://purl.org/dc/elements/1.1/creator": ["http://data.archaeology.link/data/spphaefen/arthur_de_graauw"], "http://purl.org/dc/terms/isReferencedBy": ["https://ancientmonuments.uk/124864"], "http://purl.org/dc/terms/partOf": ["http://data.archaeology.link/data/ancientports/bib_deGrauw_2013_GeoDB"], "http://rdfs.org/ns/void#inDataset": ["http://data.archaeology.link/data/ancientports/dataset"], "http://www.opengis.net/ont/geosparql#hasGeometry": ["http://data.archaeology.link/data/ancientports/44_1_geom"], "http://www.w3.org/1999/02/22-rdf-syntax-ns#type": ["http://www.ancientports.com/ont#Harbour"], "http://www.w3.org/2000/01/rdf-schema#label": ["Norman's Law oppidum on Firth of Tay"], "http://www.w3.org/2002/07/owl#sameAs": ["http://www.wikidata.org/entity/Q1724240"], "http://www.w3.org/2006/time#hasTime": ["http://data.archaeology.link/data/ancientports/44_1_foundation"], "http://www.wikidata.org/prop/direct/P17": ["http://www.wikidata.org/entity/Q145"], "begin": "-500"}, "geometry": {"type": "Point", "coordinates": [-3.1262, 56.3691]}}], "numberMatched": 1, "numberReturned": 1, "bbox": [-3.1262, 56.3691, -3.1262, 56.3691], "crs": "http://www.opengis.net/def/crs/EPSG/0/4326"}