{"type": "FeatureCollection", "id": "http://pleiades.stoa.org/places/599813", "name": "599813", "features": [{"type": "Feature", "id": "http://data.archaeology.link/data/ancientports/3189", "label": "near Afsar", "properties": {"http://purl.org/dc/elements/1.1/created": ["2023"], "http://purl.org/dc/elements/1.1/creator": ["http://data.archaeology.link/data/spphaefen/arthur_de_graauw"], "http://www.ancientports.com/ont#date_min": ["-550"], "http://www.opengis.net/ont/geosparql#hasGeometry": ["http://data.archaeology.link/data/ancientports/3189_geom"], "http://www.w3.org/1999/02/22-rdf-syntax-ns#type": ["http://www.ancientports.com/ont#Harbour"], "http://www.w3.org/2000/01/rdf-schema#label": ["near Afsar"], "http://www.w3.org/2002/07/owl#sameAs": ["http://www.wikidata.org/entity/Q1195800"], "http://www.w3.org/2004/02/skos/core#note": ["Brueckner (2017)"], "http://www.wikidata.org/prop/direct/P1584": ["http://pleiades.stoa.org/places/599813"], "http://www.wikidata.org/prop/direct/P17": ["TR: West"], "http://www.wikidata.org/prop/direct/P1958": ["https://www.trismegistos.org/place/1403"]}, "geometry": {"type": "Point", "coordinates": [27.4286, 37.5966]}}]}