{"type": "FeatureCollection", "id": "http://imperium.ahlfeldt.se/places/21690", "name": "21690", "features": [{"type": "Feature", "id": "http://data.archaeology.link/data/ancientports/3508", "label": "Blakhiyah, Khirbet Teda NW of Gaza City", "dateprops": ["http://purl.org/dc/elements/1.1/created", "http://www.ancientports.com/ont#date_min"], "properties": {"http://purl.org/dc/elements/1.1/created": ["2023"], "http://purl.org/dc/elements/1.1/creator": ["http://data.archaeology.link/data/spphaefen/arthur_de_graauw"], "http://purl.org/dc/terms/isReferencedBy": ["http://data.archaeology.link/data/ancientports/bib_Andreou_2022_Exploring"], "http://www.ancientports.com/ont#date_min": ["-1000"], "http://www.opengis.net/ont/geosparql#hasGeometry": ["http://data.archaeology.link/data/ancientports/3508_geom"], "http://www.w3.org/1999/02/22-rdf-syntax-ns#type": ["http://www.ancientports.com/ont#Harbour"], "http://www.w3.org/2000/01/rdf-schema#label": ["Blakhiyah, Khirbet Teda NW of Gaza City"], "http://www.w3.org/2002/07/owl#sameAs": ["http://www.wikidata.org/entity/Q2377463"], "http://www.w3.org/2004/02/skos/core#note": ["Nabulsi (2010)"], "http://www.wikidata.org/prop/direct/P1584": ["http://pleiades.stoa.org/places/687826"], "http://www.wikidata.org/prop/direct/P17": ["Gaza"], "http://www.wikidata.org/prop/direct/P1936": ["http://imperium.ahlfeldt.se/places/21690"], "http://www.wikidata.org/prop/direct/P1958": ["https://www.trismegistos.org/place/11116"], "http://www.wikidata.org/prop/direct/P8068": ["https://topostext.org/place/316345UAnt"]}, "geometry": {"type": "Point", "coordinates": [34.4594, 31.5423]}}]}