{"type": "FeatureCollection", "id": "https://www.trismegistos.org/place/22304", "name": "22304", "features": [{"type": "Feature", "id": "http://data.archaeology.link/data/ancientports/1234", "label": "Roman villa at Ramla bay, with breakwater, on the isle of Gozo, near famous Neolithic Ggantija temple", "properties": {"http://purl.org/dc/elements/1.1/created": ["2023"], "http://purl.org/dc/elements/1.1/creator": ["http://data.archaeology.link/data/spphaefen/arthur_de_graauw"], "http://www.ancientports.com/ont#date_min": ["-3500"], "http://www.opengis.net/ont/geosparql#hasGeometry": ["http://data.archaeology.link/data/ancientports/1234_geom"], "http://www.w3.org/1999/02/22-rdf-syntax-ns#type": ["http://www.ancientports.com/ont#Harbour"], "http://www.w3.org/2000/01/rdf-schema#label": ["Roman villa at Ramla bay, with breakwater, on the isle of Gozo, near famous Neolithic Ggantija temple"], "http://www.w3.org/2002/07/owl#sameAs": ["http://www.wikidata.org/entity/Q28040391"], "http://www.wikidata.org/prop/direct/P1584": ["https://pleiades.stoa.org/places/170572802"], "http://www.wikidata.org/prop/direct/P17": ["Malta: Gozo"], "http://www.wikidata.org/prop/direct/P1958": ["https://www.trismegistos.org/place/22304"]}, "geometry": {"type": "Point", "coordinates": [14.2826, 36.06215]}}]}