{"type": "FeatureCollection", "id": "http://imperium.ahlfeldt.se/places/42397", "name": "42397", "features": [{"type": "Feature", "id": "http://data.archaeology.link/data/ancientports/4183", "name": "Quarry at Ras et Tarf, Cape Farina", "dateprops": [], "properties": {"http://purl.org/dc/elements/1.1/created": ["2023"], "http://purl.org/dc/elements/1.1/creator": ["http://data.archaeology.link/data/spphaefen/arthur_de_graauw"], "http://www.opengis.net/ont/geosparql#hasGeometry": ["http://data.archaeology.link/data/ancientports/4183_geom"], "http://www.w3.org/1999/02/22-rdf-syntax-ns#type": ["http://www.ancientports.com/ont#Harbour"], "http://www.w3.org/2000/01/rdf-schema#label": ["Quarry at Ras et Tarf, Cape Farina"], "http://www.wikidata.org/prop/direct/P1584": ["http://pleiades.stoa.org/places/315132"], "http://www.wikidata.org/prop/direct/P17": ["http://www.wikidata.org/entity/Q948"], "http://www.wikidata.org/prop/direct/P1936": ["http://imperium.ahlfeldt.se/places/42397"], "begin": ""}, "geometry": {"type": "Point", "coordinates": [10.2799, 37.1802]}}]}