{"type": "FeatureCollection", "id": "https://www.trismegistos.org/place/58914", "name": "58914", "features": [{"type": "Feature", "id": "http://data.archaeology.link/data/ancientports/1801", "label": "near Ormylia", "properties": {"http://purl.org/dc/elements/1.1/created": ["2023"], "http://purl.org/dc/elements/1.1/creator": ["http://data.archaeology.link/data/spphaefen/arthur_de_graauw"], "http://www.ancientports.com/ont#date_min": ["-550"], "http://www.opengis.net/ont/geosparql#hasGeometry": ["http://data.archaeology.link/data/ancientports/1801_geom"], "http://www.w3.org/1999/02/22-rdf-syntax-ns#type": ["http://www.ancientports.com/ont#Harbour"], "http://www.w3.org/2000/01/rdf-schema#label": ["near Ormylia"], "http://www.w3.org/2002/07/owl#sameAs": ["http://www.wikidata.org/entity/Q16743303"], "http://www.wikidata.org/prop/direct/P1584": ["http://pleiades.stoa.org/places/501605"], "http://www.wikidata.org/prop/direct/P17": ["GR: North-East"], "http://www.wikidata.org/prop/direct/P1958": ["https://www.trismegistos.org/place/58914"]}, "geometry": {"type": "Point", "coordinates": [23.518, 40.2596]}}]}