{"type": "FeatureCollection", "id": "https://www.trismegistos.org/place/60127", "name": "60127", "features": [{"type": "Feature", "id": "http://data.archaeology.link/data/ancientports/2335", "label": "Creek behind Cape Prasonisi, on the isle of Rhodes", "properties": {"http://purl.org/dc/elements/1.1/created": ["2023"], "http://purl.org/dc/elements/1.1/creator": ["http://data.archaeology.link/data/spphaefen/arthur_de_graauw"], "http://www.opengis.net/ont/geosparql#hasGeometry": ["http://data.archaeology.link/data/ancientports/2335_geom"], "http://www.w3.org/1999/02/22-rdf-syntax-ns#type": ["http://www.ancientports.com/ont#Harbour"], "http://www.w3.org/2000/01/rdf-schema#label": ["Creek behind Cape Prasonisi, on the isle of Rhodes"], "http://www.wikidata.org/prop/direct/P1584": ["http://pleiades.stoa.org/places/590093"], "http://www.wikidata.org/prop/direct/P17": ["GR: Eastern Isl."], "http://www.wikidata.org/prop/direct/P1958": ["https://www.trismegistos.org/place/60127"]}, "geometry": {"type": "Point", "coordinates": [27.7645, 35.895]}}]}