{"type": "FeatureCollection", "id": "https://www.trismegistos.org/place/29820", "name": "29820", "features": [{"type": "Feature", "id": "http://data.archaeology.link/data/ancientports/2471", "label": "Balchik, Balcik", "properties": {"http://purl.org/dc/elements/1.1/created": ["2023"], "http://purl.org/dc/elements/1.1/creator": ["http://data.archaeology.link/data/spphaefen/arthur_de_graauw"], "http://www.ancientports.com/ont#date_min": ["-550"], "http://www.opengis.net/ont/geosparql#hasGeometry": ["http://data.archaeology.link/data/ancientports/2471_geom"], "http://www.w3.org/1999/02/22-rdf-syntax-ns#type": ["http://www.ancientports.com/ont#Harbour"], "http://www.w3.org/2000/01/rdf-schema#label": ["Balchik, Balcik"], "http://www.w3.org/2002/07/owl#sameAs": ["http://www.wikidata.org/entity/Q329437"], "http://www.wikidata.org/prop/direct/P1584": ["http://pleiades.stoa.org/places/216793"], "http://www.wikidata.org/prop/direct/P17": ["Bulgaria Black S."], "http://www.wikidata.org/prop/direct/P1936": ["http://imperium.ahlfeldt.se/places/21392"], "http://www.wikidata.org/prop/direct/P1958": ["https://www.trismegistos.org/place/29820"], "http://www.wikidata.org/prop/direct/P8068": ["https://topostext.org/place/434282UDio"]}, "geometry": {"type": "Point", "coordinates": [28.16441, 43.40392]}}]}