{"type": "FeatureCollection", "id": "http://imperium.ahlfeldt.se/places/13869", "name": "13869", "features": [{"type": "Feature", "id": "http://data.archaeology.link/data/ancientports/1417_1", "name": "Starigrad kod Paklenice, on R Paklenica", "dateprops": ["begin"], "properties": {"http://purl.org/dc/elements/1.1/creator": ["http://data.archaeology.link/data/spphaefen/arthur_de_graauw"], "http://purl.org/dc/terms/isReferencedBy": ["http://baza.iarh.hr/public/locality/detail/2621"], "http://purl.org/dc/terms/partOf": ["http://data.archaeology.link/data/ancientports/bib_deGrauw_2013_GeoDB"], "http://www.opengis.net/ont/geosparql#hasGeometry": ["http://data.archaeology.link/data/ancientports/1417_1_geom"], "http://www.w3.org/1999/02/22-rdf-syntax-ns#type": ["http://www.ancientports.com/ont#Harbour"], "http://www.w3.org/2000/01/rdf-schema#label": ["Starigrad kod Paklenice, on R Paklenica"], "http://www.w3.org/2002/07/owl#sameAs": ["http://www.wikidata.org/entity/Q856390"], "http://www.w3.org/2006/time#hasTime": ["http://data.archaeology.link/data/ancientports/1417_1_foundation"], "http://www.wikidata.org/prop/direct/P1584": ["http://pleiades.stoa.org/places/197139"], "http://www.wikidata.org/prop/direct/P17": ["http://www.wikidata.org/entity/Q224"], "http://www.wikidata.org/prop/direct/P1936": ["http://imperium.ahlfeldt.se/places/13869"], "http://www.wikidata.org/prop/direct/P1958": ["https://www.trismegistos.org/place/29375"], "begin": "-330"}, "geometry": {"type": "Point", "coordinates": [15.4544, 44.281]}}], "numberMatched": 1, "numberReturned": 1, "bbox": [15.4544, 44.281, 15.4544, 44.281], "crs": "http://www.opengis.net/def/crs/EPSG/0/4326"}