{"type": "FeatureCollection", "id": "https://topostext.org/place/393267UHer", "name": "393267UHer", "features": [{"type": "Feature", "id": "http://data.archaeology.link/data/ancientports/3120", "label": "Ayvalik", "dateprops": [], "properties": {"http://purl.org/dc/elements/1.1/created": ["2023"], "http://purl.org/dc/elements/1.1/creator": ["http://data.archaeology.link/data/spphaefen/arthur_de_graauw"], "http://www.ancientports.com/ont#date_min": ["-330"], "http://www.opengis.net/ont/geosparql#hasGeometry": ["http://data.archaeology.link/data/ancientports/3120_geom"], "http://www.w3.org/1999/02/22-rdf-syntax-ns#type": ["http://www.ancientports.com/ont#Harbour"], "http://www.w3.org/2000/01/rdf-schema#label": ["Ayvalik"], "http://www.w3.org/2002/07/owl#sameAs": ["http://www.wikidata.org/entity/Q17121842"], "http://www.w3.org/2004/02/skos/core#note": ["K\u00fclzer (2021)"], "http://www.wikidata.org/prop/direct/P1584": ["http://pleiades.stoa.org/places/550571"], "http://www.wikidata.org/prop/direct/P17": ["TR: West"], "http://www.wikidata.org/prop/direct/P1936": ["http://imperium.ahlfeldt.se/places/29044"], "http://www.wikidata.org/prop/direct/P1958": ["https://www.trismegistos.org/place/41972"], "http://www.wikidata.org/prop/direct/P8068": ["https://topostext.org/place/393267UHer"]}, "geometry": {"type": "Point", "coordinates": [26.6863, 39.3123]}}]}