{"type": "FeatureCollection", "id": "http://imperium.ahlfeldt.se/places/16892", "name": "16892", "features": [{"type": "Feature", "id": "http://data.archaeology.link/data/ancientports/723", "label": "La Canonica, near Lucciana, Marais de Tanghiccia, at the outlet of R Golo", "dateprops": ["http://purl.org/dc/elements/1.1/created"], "properties": {"http://purl.org/dc/elements/1.1/created": ["2023"], "http://purl.org/dc/elements/1.1/creator": ["http://data.archaeology.link/data/spphaefen/arthur_de_graauw"], "http://purl.org/dc/terms/isReferencedBy": ["https://en.wikipedia.org/wiki/Al%C3%A9ria#Pre-Roman"], "http://www.opengis.net/ont/geosparql#hasGeometry": ["http://data.archaeology.link/data/ancientports/723_geom"], "http://www.w3.org/1999/02/22-rdf-syntax-ns#type": ["http://www.ancientports.com/ont#Harbour"], "http://www.w3.org/2000/01/rdf-schema#label": ["La Canonica, near Lucciana, Marais de Tanghiccia, at the outlet of R Golo"], "http://www.w3.org/2002/07/owl#sameAs": ["http://www.wikidata.org/entity/Q507251"], "http://www.w3.org/2004/02/skos/core#note": ["Mattei (2001)"], "http://www.w3.org/2006/time#hasTime": ["http://data.archaeology.link/data/ancientports/723_foundation"], "http://www.wikidata.org/prop/direct/P1584": ["http://pleiades.stoa.org/places/472096"], "http://www.wikidata.org/prop/direct/P17": ["France Corsica"], "http://www.wikidata.org/prop/direct/P1936": ["http://imperium.ahlfeldt.se/places/16892"], "http://www.wikidata.org/prop/direct/P1958": ["https://www.trismegistos.org/place/22068"], "http://www.wikidata.org/prop/direct/P8068": ["https://topostext.org/place/425950UMar"]}, "geometry": {"type": "Point", "coordinates": [9.4958, 42.539]}}]}