{"type": "FeatureCollection", "id": "http://www.wikidata.org/entity/Q842570", "name": "Santianes, Pravia", "features": [{"type": "Feature", "id": "http://data.archaeology.link/data/ancientports/190", "name": "Santianes, Pravia", "dateprops": ["begin"], "properties": {"http://purl.org/dc/elements/1.1/created": ["2023"], "http://purl.org/dc/elements/1.1/creator": ["http://data.archaeology.link/data/spphaefen/arthur_de_graauw"], "http://www.opengis.net/ont/geosparql#hasGeometry": ["http://data.archaeology.link/data/ancientports/190_geom"], "http://www.w3.org/1999/02/22-rdf-syntax-ns#type": ["http://www.ancientports.com/ont#Harbour"], "http://www.w3.org/2000/01/rdf-schema#label": ["Santianes, Pravia"], "http://www.w3.org/2002/07/owl#sameAs": ["http://www.wikidata.org/entity/Q842570"], "http://www.w3.org/2006/time#hasTime": ["http://data.archaeology.link/data/ancientports/190_foundation"], "http://www.wikidata.org/prop/direct/P1584": ["http://pleiades.stoa.org/places/236464"], "http://www.wikidata.org/prop/direct/P17": ["http://www.wikidata.org/entity/Q29"], "http://www.wikidata.org/prop/direct/P1936": ["http://imperium.ahlfeldt.se/places/18355"], "http://www.wikidata.org/prop/direct/P1958": ["https://www.trismegistos.org/place/26728"], "http://www.wikidata.org/prop/direct/P8068": ["https://topostext.org/place/435000UFla"], "begin": "-30"}, "geometry": {"type": "Point", "coordinates": [-6.09723, 43.50531]}}]}