{"type": "FeatureCollection", "id": "http://www.wikidata.org/entity/Q5699", "name": "Q5699", "features": [{"type": "Feature", "id": "http://data.archaeology.link/data/ancientports/3806_1", "label": "Tell el-Muqayyar, with 'two off-river basins enclosed within the walls of Ur' acc. to Blackman (1982, p92)", "properties": {"http://purl.org/dc/elements/1.1/created": ["2023"], "http://purl.org/dc/elements/1.1/creator": ["http://data.archaeology.link/data/spphaefen/arthur_de_graauw"], "http://www.ancientports.com/ont#date_min": ["-6000"], "http://www.opengis.net/ont/geosparql#hasGeometry": ["http://data.archaeology.link/data/ancientports/3806_1_geom"], "http://www.w3.org/1999/02/22-rdf-syntax-ns#type": ["http://www.ancientports.com/ont#Harbour"], "http://www.w3.org/2000/01/rdf-schema#label": ["Tell el-Muqayyar, with 'two off-river basins enclosed within the walls of Ur' acc. to Blackman (1982, p92)"], "http://www.w3.org/2002/07/owl#sameAs": ["http://www.wikidata.org/entity/Q5699"], "http://www.wikidata.org/prop/direct/P1584": ["http://pleiades.stoa.org/places/912985"], "http://www.wikidata.org/prop/direct/P17": ["Gulf"], "http://www.wikidata.org/prop/direct/P1958": ["https://www.trismegistos.org/place/51203"]}, "geometry": {"type": "Point", "coordinates": [46.1027, 30.96]}}, {"type": "Feature", "id": "http://data.archaeology.link/data/ancientports/3806", "label": "Tell el-Muqayyar, with 'two off-river basins enclosed within the walls of Ur' acc. to Blackman (1982, p92)", "properties": {"http://purl.org/dc/elements/1.1/created": ["2023"], "http://purl.org/dc/elements/1.1/creator": ["http://data.archaeology.link/data/spphaefen/arthur_de_graauw"], "http://www.ancientports.com/ont#date_min": ["-6000"], "http://www.opengis.net/ont/geosparql#hasGeometry": ["http://data.archaeology.link/data/ancientports/3806_geom"], "http://www.w3.org/1999/02/22-rdf-syntax-ns#type": ["http://www.ancientports.com/ont#Harbour"], "http://www.w3.org/2000/01/rdf-schema#label": ["Tell el-Muqayyar, with 'two off-river basins enclosed within the walls of Ur' acc. to Blackman (1982, p92)"], "http://www.w3.org/2002/07/owl#sameAs": ["http://www.wikidata.org/entity/Q5699"], "http://www.wikidata.org/prop/direct/P1584": ["http://pleiades.stoa.org/places/912985"], "http://www.wikidata.org/prop/direct/P17": ["Gulf"], "http://www.wikidata.org/prop/direct/P1958": ["https://www.trismegistos.org/place/51203"]}, "geometry": {"type": "Point", "coordinates": [46.10306, 30.9625]}}]}