{"type": "FeatureCollection", "id": "https://pleiades.stoa.org/places/638859", "name": "638859", "features": [{"type": "Feature", "id": "http://data.archaeology.link/data/ancientports/3285_1", "label": "K\u00f6t\u00fc Burun, Yedi Burun", "properties": {"http://purl.org/dc/elements/1.1/created": ["2023"], "http://purl.org/dc/elements/1.1/creator": ["http://data.archaeology.link/data/spphaefen/arthur_de_graauw"], "http://www.opengis.net/ont/geosparql#hasGeometry": ["http://data.archaeology.link/data/ancientports/3285_1_geom"], "http://www.w3.org/1999/02/22-rdf-syntax-ns#type": ["http://www.ancientports.com/ont#Harbour"], "http://www.w3.org/2000/01/rdf-schema#label": ["K\u00f6t\u00fc Burun, Yedi Burun"], "http://www.wikidata.org/prop/direct/P1584": ["https://pleiades.stoa.org/places/638859"], "http://www.wikidata.org/prop/direct/P17": ["TR: South"]}, "geometry": {"type": "Point", "coordinates": [29.116, 36.39]}}]}