{"type": "FeatureCollection", "id": "https://www.trismegistos.org/place/20384", "name": "20384", "features": [{"type": "Feature", "id": "http://data.archaeology.link/data/ancientports/4206", "label": "bay of Takouch NW of Annaba: Chetaibi", "properties": {"http://purl.org/dc/elements/1.1/created": ["2023"], "http://purl.org/dc/elements/1.1/creator": ["http://data.archaeology.link/data/spphaefen/arthur_de_graauw"], "http://www.ancientports.com/ont#date_min": ["-330"], "http://www.opengis.net/ont/geosparql#hasGeometry": ["http://data.archaeology.link/data/ancientports/4206_geom"], "http://www.w3.org/1999/02/22-rdf-syntax-ns#type": ["http://www.ancientports.com/ont#Harbour"], "http://www.w3.org/2000/01/rdf-schema#label": ["bay of Takouch NW of Annaba: Chetaibi"], "http://www.wikidata.org/prop/direct/P1584": ["http://pleiades.stoa.org/places/305160"], "http://www.wikidata.org/prop/direct/P17": ["Algeria"], "http://www.wikidata.org/prop/direct/P1936": ["http://imperium.ahlfeldt.se/places/23764"], "http://www.wikidata.org/prop/direct/P1958": ["https://www.trismegistos.org/place/20384"]}, "geometry": {"type": "Point", "coordinates": [7.3856, 37.06659]}}]}