{"type": "FeatureCollection", "id": "https://topostext.org/place/437104UPis", "name": "437104UPis", "features": [{"type": "Feature", "id": "http://data.archaeology.link/data/ancientports/851", "name": "Stazione Ferroviaria Pisa-San Rossore, near Pisa on R Arno", "dateprops": ["begin"], "properties": {"http://purl.org/dc/elements/1.1/creator": ["http://data.archaeology.link/data/spphaefen/arthur_de_graauw"], "http://purl.org/dc/terms/isReferencedBy": ["https://www2.rgzm.de/navis2/home/frames.htm"], "http://purl.org/dc/terms/partOf": ["http://data.archaeology.link/data/ancientports/bib_deGrauw_2013_GeoDB"], "http://www.opengis.net/ont/geosparql#hasGeometry": ["http://data.archaeology.link/data/ancientports/851_geom"], "http://www.w3.org/1999/02/22-rdf-syntax-ns#type": ["http://www.ancientports.com/ont#Quay"], "http://www.w3.org/2000/01/rdf-schema#label": ["Stazione Ferroviaria Pisa-San Rossore, near Pisa on R Arno"], "http://www.w3.org/2002/07/owl#sameAs": ["http://www.wikidata.org/entity/Q13375"], "http://www.w3.org/2004/02/skos/core#note": ["Camilli (2004)", "Camilli (2005)"], "http://www.w3.org/2006/time#hasTime": ["http://data.archaeology.link/data/ancientports/851_foundation"], "http://www.wikidata.org/prop/direct/P1584": ["http://pleiades.stoa.org/places/403253"], "http://www.wikidata.org/prop/direct/P17": ["http://www.wikidata.org/entity/Q38"], "http://www.wikidata.org/prop/direct/P1936": ["http://imperium.ahlfeldt.se/places/10595"], "http://www.wikidata.org/prop/direct/P1958": ["https://www.trismegistos.org/place/11855"], "http://www.wikidata.org/prop/direct/P8068": ["https://topostext.org/place/437104UPis"], "begin": "-550"}, "geometry": {"type": "Point", "coordinates": [10.3823, 43.722]}}], "numberMatched": 1, "numberReturned": 1, "bbox": [10.3823, 43.722, 10.3823, 43.722], "crs": "http://www.opengis.net/def/crs/EPSG/0/4326"}