{"type": "FeatureCollection", "id": "https://topostext.org/place/380137UThe", "name": "380137UThe", "features": [{"type": "Feature", "id": "http://data.archaeology.link/data/ancientports/1191", "name": "Termini Imerese, on R San Leonardo", "dateprops": ["begin"], "properties": {"http://purl.org/dc/elements/1.1/creator": ["http://data.archaeology.link/data/spphaefen/arthur_de_graauw"], "http://purl.org/dc/terms/partOf": ["http://data.archaeology.link/data/ancientports/bib_deGrauw_2013_GeoDB"], "http://www.opengis.net/ont/geosparql#hasGeometry": ["http://data.archaeology.link/data/ancientports/1191_geom"], "http://www.w3.org/1999/02/22-rdf-syntax-ns#type": ["http://www.ancientports.com/ont#Harbour"], "http://www.w3.org/2000/01/rdf-schema#label": ["Termini Imerese, on R San Leonardo"], "http://www.w3.org/2002/07/owl#sameAs": ["http://www.wikidata.org/entity/Q490851"], "http://www.w3.org/2006/time#hasTime": ["http://data.archaeology.link/data/ancientports/1191_foundation"], "http://www.wikidata.org/prop/direct/P1584": ["http://pleiades.stoa.org/places/462513"], "http://www.wikidata.org/prop/direct/P17": ["http://www.wikidata.org/entity/Q38"], "http://www.wikidata.org/prop/direct/P1936": ["http://imperium.ahlfeldt.se/places/16878"], "http://www.wikidata.org/prop/direct/P1958": ["https://www.trismegistos.org/place/22348"], "http://www.wikidata.org/prop/direct/P8068": ["https://topostext.org/place/380137UThe"], "begin": "-550"}, "geometry": {"type": "Point", "coordinates": [13.69039, 37.99399]}}], "numberMatched": 1, "numberReturned": 1, "bbox": [13.69039, 37.99399, 13.69039, 37.99399], "crs": "http://www.opengis.net/def/crs/OGC/1.3/CRS84"}