{"type": "FeatureCollection", "id": "http://imperium.ahlfeldt.se/places/46648", "name": "46648", "features": [{"type": "Feature", "id": "http://data.archaeology.link/data/ancientports/2036", "label": "Gavrion, on the isle of Andros", "dateprops": ["http://purl.org/dc/elements/1.1/created", "http://www.ancientports.com/ont#date_min"], "properties": {"http://purl.org/dc/elements/1.1/created": ["2023"], "http://purl.org/dc/elements/1.1/creator": ["http://data.archaeology.link/data/spphaefen/arthur_de_graauw"], "http://www.ancientports.com/ont#date_min": ["-3000"], "http://www.opengis.net/ont/geosparql#hasGeometry": ["http://data.archaeology.link/data/ancientports/2036_geom"], "http://www.w3.org/1999/02/22-rdf-syntax-ns#type": ["http://www.ancientports.com/ont#Harbour"], "http://www.w3.org/2000/01/rdf-schema#label": ["Gavrion, on the isle of Andros"], "http://www.w3.org/2002/07/owl#sameAs": ["http://www.wikidata.org/entity/Q65081758"], "http://www.wikidata.org/prop/direct/P1584": ["http://pleiades.stoa.org/places/589791"], "http://www.wikidata.org/prop/direct/P17": ["GR: Cyclades Isl."], "http://www.wikidata.org/prop/direct/P1936": ["http://imperium.ahlfeldt.se/places/46648"], "http://www.wikidata.org/prop/direct/P8068": ["https://topostext.org/place/379247UGau"]}, "geometry": {"type": "Point", "coordinates": [24.736, 37.8853]}}]}