{"type": "FeatureCollection", "id": "https://pleiades.stoa.org/places/40178", "name": "40178", "features": [{"type": "Feature", "id": "http://data.archaeology.link/data/ancientports/3728", "label": "Habo, Xabo, Abot fort? on Khor Filuk", "properties": {"http://purl.org/dc/elements/1.1/created": ["2023"], "http://purl.org/dc/elements/1.1/creator": ["http://data.archaeology.link/data/spphaefen/arthur_de_graauw"], "http://www.opengis.net/ont/geosparql#hasGeometry": ["http://data.archaeology.link/data/ancientports/3728_geom"], "http://www.w3.org/1999/02/22-rdf-syntax-ns#type": ["http://www.ancientports.com/ont#Harbour"], "http://www.w3.org/2000/01/rdf-schema#label": ["Habo, Xabo, Abot fort? on Khor Filuk"], "http://www.wikidata.org/prop/direct/P1584": ["https://pleiades.stoa.org/places/40178"], "http://www.wikidata.org/prop/direct/P17": ["Somalia"]}, "geometry": {"type": "Point", "coordinates": [50.52087, 11.79413]}}]}