{"type": "FeatureCollection", "id": "http://imperium.ahlfeldt.se/places/25617", "name": "25617", "features": [{"type": "Feature", "id": "http://data.archaeology.link/data/ancientports/116_2", "label": "Roman temple and oppidum at Brean Down, near outlet of R Axe", "properties": {"http://purl.org/dc/elements/1.1/created": ["2023"], "http://purl.org/dc/elements/1.1/creator": ["http://data.archaeology.link/data/spphaefen/arthur_de_graauw"], "http://www.ancientports.com/ont#date_min": ["-500"], "http://www.opengis.net/ont/geosparql#hasGeometry": ["http://data.archaeology.link/data/ancientports/116_2_geom"], "http://www.w3.org/1999/02/22-rdf-syntax-ns#type": ["http://www.ancientports.com/ont#Harbour"], "http://www.w3.org/2000/01/rdf-schema#label": ["Roman temple and oppidum at Brean Down, near outlet of R Axe"], "http://www.w3.org/2002/07/owl#sameAs": ["http://www.wikidata.org/entity/Q3403788"], "http://www.wikidata.org/prop/direct/P1584": ["http://pleiades.stoa.org/places/79351"], "http://www.wikidata.org/prop/direct/P17": ["UK"], "http://www.wikidata.org/prop/direct/P1936": ["http://imperium.ahlfeldt.se/places/25617"]}, "geometry": {"type": "Point", "coordinates": [-3.0267, 51.3255]}}]}