{"type": "FeatureCollection", "id": "http://www.wikidata.org/entity/Q1003322", "name": "Q1003322", "features": [{"type": "Feature", "id": "http://data.archaeology.link/data/ancientports/2409", "label": "Bukoleon Sarayi, probably built by Justinian I in the 6th century, beneath the Palace of Bucoleon built by Theodosius II in the 5th century", "properties": {"http://purl.org/dc/elements/1.1/created": ["2023"], "http://purl.org/dc/elements/1.1/creator": ["http://data.archaeology.link/data/spphaefen/arthur_de_graauw"], "http://www.opengis.net/ont/geosparql#hasGeometry": ["http://data.archaeology.link/data/ancientports/2409_geom"], "http://www.w3.org/1999/02/22-rdf-syntax-ns#type": ["http://www.ancientports.com/ont#Lighthouse"], "http://www.w3.org/2000/01/rdf-schema#label": ["Bukoleon Sarayi, probably built by Justinian I in the 6th century, beneath the Palace of Bucoleon built by Theodosius II in the 5th century"], "http://www.w3.org/2002/07/owl#sameAs": ["http://www.wikidata.org/entity/Q1003322"], "http://www.wikidata.org/prop/direct/P17": ["TR: Bosph N"]}, "geometry": {"type": "Point", "coordinates": [28.9763, 41.00235]}}]}