{"type": "FeatureCollection", "id": "http://www.wikidata.org/entity/Q1263995", "name": "Q1263995", "features": [{"type": "Feature", "id": "http://data.archaeology.link/data/ancientports/1478", "label": "Isle of Svetac", "properties": {"http://purl.org/dc/elements/1.1/created": ["2023"], "http://purl.org/dc/elements/1.1/creator": ["http://data.archaeology.link/data/spphaefen/arthur_de_graauw"], "http://purl.org/dc/terms/isReferencedBy": ["http://baza.iarh.hr/public/locality/detail/1705"], "http://www.ancientports.com/ont#date_min": ["3001"], "http://www.opengis.net/ont/geosparql#hasGeometry": ["http://data.archaeology.link/data/ancientports/1478_geom"], "http://www.w3.org/1999/02/22-rdf-syntax-ns#type": ["http://www.ancientports.com/ont#Harbour"], "http://www.w3.org/2000/01/rdf-schema#label": ["Isle of Svetac"], "http://www.w3.org/2002/07/owl#sameAs": ["http://www.wikidata.org/entity/Q1263995"], "http://www.w3.org/2004/02/skos/core#note": ["http://baza.iarh.hr/public/locality/detail/1705"], "http://www.wikidata.org/prop/direct/P17": ["http://www.wikidata.org/entity/Q224"]}, "geometry": {"type": "Point", "coordinates": [15.7536, 43.0342]}}]}