{"type": "FeatureCollection", "id": "https://topostext.org/place/383213IArt", "name": "383213IArt", "features": [{"type": "Feature", "id": "http://data.archaeology.link/data/ancientports/1581_1", "name": "", "dateprops": ["begin"], "properties": {"http://purl.org/dc/elements/1.1/creator": ["http://data.archaeology.link/data/spphaefen/arthur_de_graauw"], "http://purl.org/dc/terms/isReferencedBy": ["https://topostext.org/place/383211WAch"], "http://purl.org/dc/terms/partOf": ["http://data.archaeology.link/data/ancientports/bib_deGrauw_2013_GeoDB"], "http://www.opengis.net/ont/geosparql#hasGeometry": ["http://data.archaeology.link/data/ancientports/1581_1_geom"], "http://www.w3.org/1999/02/22-rdf-syntax-ns#type": ["http://www.ancientports.com/ont#Harbour"], "http://www.w3.org/2000/01/rdf-schema#label": ["Khounovina, near outlet of  R Achelous"], "http://www.w3.org/2002/07/owl#sameAs": ["http://www.wikidata.org/entity/Q203923"], "http://www.w3.org/2006/time#hasTime": ["http://data.archaeology.link/data/ancientports/1581_1_foundation"], "http://www.wikidata.org/prop/direct/P1584": ["http://pleiades.stoa.org/places/530812"], "http://www.wikidata.org/prop/direct/P17": ["http://www.wikidata.org/entity/Q41"], "http://www.wikidata.org/prop/direct/P1936": ["http://dare.ht.lu.se/places/44931"], "http://www.wikidata.org/prop/direct/P8068": ["https://topostext.org/place/383213IArt"], "begin": "-330"}, "geometry": {"type": "Point", "coordinates": [21.0955, 38.3717]}}], "numberMatched": 1, "numberReturned": 1, "bbox": [21.0955, 38.3717, 21.0955, 38.3717], "crs": "http://www.opengis.net/def/crs/EPSG/0/4326"}