{"type": "FeatureCollection", "id": "http://imperium.ahlfeldt.se/places/26217", "name": "26217", "features": [{"type": "Feature", "id": "http://data.archaeology.link/data/ancientports/132", "label": "Roman villa at Tremadoc, on R Dwyryd", "properties": {"http://purl.org/dc/elements/1.1/created": ["2023"], "http://purl.org/dc/elements/1.1/creator": ["http://data.archaeology.link/data/spphaefen/arthur_de_graauw"], "http://www.ancientports.com/ont#date_min": ["1001"], "http://www.opengis.net/ont/geosparql#hasGeometry": ["http://data.archaeology.link/data/ancientports/132_geom"], "http://www.w3.org/1999/02/22-rdf-syntax-ns#type": ["http://www.ancientports.com/ont#VillaMaritima"], "http://www.w3.org/2000/01/rdf-schema#label": ["Roman villa at Tremadoc, on R Dwyryd"], "http://www.w3.org/2002/07/owl#sameAs": ["http://www.wikidata.org/entity/Q2035368"], "http://www.wikidata.org/prop/direct/P17": ["http://www.wikidata.org/entity/Q145"], "http://www.wikidata.org/prop/direct/P1936": ["http://imperium.ahlfeldt.se/places/26217"], "http://www.wikidata.org/prop/direct/P1958": ["https://www.trismegistos.org/place/14863"]}, "geometry": {"type": "Point", "coordinates": [-4.14817, 52.9392]}}]}