{"type": "FeatureCollection", "id": "http://www.wikidata.org/entity/Q2021739", "name": "Q2021739", "features": [{"type": "Feature", "id": "http://data.archaeology.link/data/ancientports/1626", "label": "Bay of Ambelaki, on the isle of Salamis", "properties": {"http://purl.org/dc/elements/1.1/created": ["2023"], "http://purl.org/dc/elements/1.1/creator": ["http://data.archaeology.link/data/spphaefen/arthur_de_graauw"], "http://www.ancientports.com/ont#date_min": ["-550"], "http://www.opengis.net/ont/geosparql#hasGeometry": ["http://data.archaeology.link/data/ancientports/1626_geom"], "http://www.w3.org/1999/02/22-rdf-syntax-ns#type": ["http://www.ancientports.com/ont#Harbour"], "http://www.w3.org/2000/01/rdf-schema#label": ["Bay of Ambelaki, on the isle of Salamis"], "http://www.w3.org/2002/07/owl#sameAs": ["http://www.wikidata.org/entity/Q2021739"], "http://www.wikidata.org/prop/direct/P1584": ["http://pleiades.stoa.org/places/580100"], "http://www.wikidata.org/prop/direct/P17": ["GR: Attica +"], "http://www.wikidata.org/prop/direct/P1958": ["https://www.trismegistos.org/place/37803"]}, "geometry": {"type": "Point", "coordinates": [23.5387, 37.95016]}}]}