{"type": "FeatureCollection", "id": "http://www.wikidata.org/entity/Q65066291", "name": "Kasara (Caria)", "features": [{"type": "Feature", "id": "http://data.archaeology.link/data/ancientports/3248", "name": "Asardibi, in front of Taslica Adasi Island", "dateprops": ["begin"], "properties": {"http://purl.org/dc/elements/1.1/creator": ["http://data.archaeology.link/data/spphaefen/arthur_de_graauw"], "http://purl.org/dc/terms/partOf": ["http://data.archaeology.link/data/ancientports/bib_deGrauw_2013_GeoDB"], "http://www.opengis.net/ont/geosparql#hasGeometry": ["http://data.archaeology.link/data/ancientports/3248_geom"], "http://www.w3.org/1999/02/22-rdf-syntax-ns#type": ["http://www.ancientports.com/ont#Harbour"], "http://www.w3.org/2000/01/rdf-schema#label": ["Asardibi, in front of Taslica Adasi Island"], "http://www.w3.org/2002/07/owl#sameAs": ["http://www.wikidata.org/entity/Q65066291"], "http://www.w3.org/2004/02/skos/core#note": ["Atauz (1997)"], "http://www.w3.org/2006/time#hasTime": ["http://data.archaeology.link/data/ancientports/3248_foundation"], "http://www.wikidata.org/prop/direct/P1584": ["http://pleiades.stoa.org/places/599696"], "http://www.wikidata.org/prop/direct/P17": ["http://www.wikidata.org/entity/Q43"], "http://www.wikidata.org/prop/direct/P1936": ["http://imperium.ahlfeldt.se/places/28973"], "http://www.wikidata.org/prop/direct/P1958": ["https://www.trismegistos.org/place/57182"], "http://www.wikidata.org/prop/direct/P8068": ["https://topostext.org/place/366281UKas"], "begin": "-550"}, "geometry": {"type": "Point", "coordinates": [28.0564, 36.6054]}}]}