{"type": "FeatureCollection", "id": "https://www.trismegistos.org/place/27238", "name": "27238", "features": [{"type": "Feature", "id": "http://data.archaeology.link/data/ancientports/438", "label": "Mataro", "dateprops": [], "properties": {"http://purl.org/dc/elements/1.1/created": ["2023"], "http://purl.org/dc/elements/1.1/creator": ["http://data.archaeology.link/data/spphaefen/arthur_de_graauw"], "http://www.opengis.net/ont/geosparql#hasGeometry": ["http://data.archaeology.link/data/ancientports/438_geom"], "http://www.w3.org/1999/02/22-rdf-syntax-ns#type": ["http://www.ancientports.com/ont#Harbour"], "http://www.w3.org/2000/01/rdf-schema#label": ["Mataro"], "http://www.w3.org/2002/07/owl#sameAs": ["http://www.wikidata.org/entity/Q11492"], "http://www.w3.org/2006/time#hasTime": ["http://data.archaeology.link/data/ancientports/438_foundation"], "http://www.wikidata.org/prop/direct/P1584": ["http://pleiades.stoa.org/places/246436"], "http://www.wikidata.org/prop/direct/P17": ["http://www.wikidata.org/entity/Q29"], "http://www.wikidata.org/prop/direct/P1936": ["http://imperium.ahlfeldt.se/places/18293"], "http://www.wikidata.org/prop/direct/P1958": ["https://www.trismegistos.org/place/27238"], "http://www.wikidata.org/prop/direct/P8068": ["https://topostext.org/place/415024UIlu"]}, "geometry": {"type": "Point", "coordinates": [2.44787, 41.53952]}}]}