{"type": "FeatureCollection", "id": "https://www.trismegistos.org/place/41745", "name": "41745", "features": [{"type": "Feature", "id": "http://data.archaeology.link/data/ancientports/4092", "label": "Mellita, near oil terminal", "properties": {"http://purl.org/dc/elements/1.1/created": ["2023"], "http://purl.org/dc/elements/1.1/creator": ["http://data.archaeology.link/data/spphaefen/arthur_de_graauw"], "http://www.ancientports.com/ont#date_min": ["-330"], "http://www.opengis.net/ont/geosparql#hasGeometry": ["http://data.archaeology.link/data/ancientports/4092_geom"], "http://www.w3.org/1999/02/22-rdf-syntax-ns#type": ["http://www.ancientports.com/ont#Harbour"], "http://www.w3.org/2000/01/rdf-schema#label": ["Mellita, near oil terminal"], "http://www.wikidata.org/prop/direct/P1584": ["http://pleiades.stoa.org/places/344284"], "http://www.wikidata.org/prop/direct/P17": ["Libya"], "http://www.wikidata.org/prop/direct/P1958": ["https://www.trismegistos.org/place/41745"]}, "geometry": {"type": "Point", "coordinates": [12.2697, 32.849]}}]}