{"type": "FeatureCollection", "id": "http://www.wikidata.org/entity/Q16010710", "name": "Antium", "features": [{"type": "Feature", "id": "http://data.archaeology.link/data/ancientports/943", "name": "Anzio, with Nero's Roman villa and several others", "dateprops": ["begin"], "properties": {"http://purl.org/dc/elements/1.1/created": ["2023"], "http://purl.org/dc/elements/1.1/creator": ["http://data.archaeology.link/data/spphaefen/arthur_de_graauw"], "http://www.opengis.net/ont/geosparql#hasGeometry": ["http://data.archaeology.link/data/ancientports/943_geom"], "http://www.w3.org/1999/02/22-rdf-syntax-ns#type": ["http://www.ancientports.com/ont#VillaMaritima"], "http://www.w3.org/2000/01/rdf-schema#label": ["Anzio, with Nero's Roman villa and several others"], "http://www.w3.org/2002/07/owl#sameAs": ["http://www.wikidata.org/entity/Q16010710"], "http://www.w3.org/2004/02/skos/core#note": ["Felici (1993)", "Felici (2002)"], "http://www.w3.org/2006/time#hasTime": ["http://data.archaeology.link/data/ancientports/943_foundation"], "http://www.wikidata.org/prop/direct/P1584": ["http://pleiades.stoa.org/places/422837"], "http://www.wikidata.org/prop/direct/P17": ["http://www.wikidata.org/entity/Q38"], "http://www.wikidata.org/prop/direct/P1936": ["http://imperium.ahlfeldt.se/places/16711"], "http://www.wikidata.org/prop/direct/P1958": ["https://www.trismegistos.org/place/32374"], "http://www.wikidata.org/prop/direct/P8068": ["https://topostext.org/place/415126UAnt"], "begin": "-750"}, "geometry": {"type": "Point", "coordinates": [12.62839, 41.4427]}}, {"type": "Feature", "id": "http://data.archaeology.link/data/ancientports/946", "name": "Castello di San Gallo at Nettuno, on R Loricina", "dateprops": ["begin"], "properties": {"http://purl.org/dc/elements/1.1/created": ["2023"], "http://purl.org/dc/elements/1.1/creator": ["http://data.archaeology.link/data/spphaefen/arthur_de_graauw"], "http://www.opengis.net/ont/geosparql#hasGeometry": ["http://data.archaeology.link/data/ancientports/946_geom"], "http://www.w3.org/1999/02/22-rdf-syntax-ns#type": ["http://www.ancientports.com/ont#Harbour"], "http://www.w3.org/2000/01/rdf-schema#label": ["Castello di San Gallo at Nettuno, on R Loricina"], "http://www.w3.org/2002/07/owl#sameAs": ["http://www.wikidata.org/entity/Q16010710"], "http://www.w3.org/2004/02/skos/core#note": ["Attema (2010)"], "http://www.w3.org/2006/time#hasTime": ["http://data.archaeology.link/data/ancientports/946_foundation"], "http://www.wikidata.org/prop/direct/P1584": ["http://pleiades.stoa.org/places/422985"], "http://www.wikidata.org/prop/direct/P17": ["http://www.wikidata.org/entity/Q38"], "http://www.wikidata.org/prop/direct/P1936": ["http://imperium.ahlfeldt.se/places/26600"], "begin": "-30"}, "geometry": {"type": "Point", "coordinates": [12.66064, 41.45612]}}]}