{"type": "FeatureCollection", "id": "http://imperium.ahlfeldt.se/places/26210", "name": "26210", "features": [{"type": "Feature", "id": "http://data.archaeology.link/data/ancientports/131", "label": "Birthdir Roman fort, on R Mawddach ", "dateprops": [], "properties": {"http://purl.org/dc/elements/1.1/created": ["2023"], "http://purl.org/dc/elements/1.1/creator": ["http://data.archaeology.link/data/spphaefen/arthur_de_graauw"], "http://www.opengis.net/ont/geosparql#hasGeometry": ["http://data.archaeology.link/data/ancientports/131_geom"], "http://www.w3.org/1999/02/22-rdf-syntax-ns#type": ["http://www.ancientports.com/ont#Harbour"], "http://www.w3.org/2000/01/rdf-schema#label": ["Birthdir Roman fort, on R Mawddach "], "http://www.w3.org/2002/07/owl#sameAs": ["http://www.wikidata.org/entity/Q4969344"], "http://www.w3.org/2006/time#hasTime": ["http://data.archaeology.link/data/ancientports/131_foundation"], "http://www.wikidata.org/prop/direct/P17": ["http://www.wikidata.org/entity/Q145"], "http://www.wikidata.org/prop/direct/P1936": ["http://imperium.ahlfeldt.se/places/26210"]}, "geometry": {"type": "Point", "coordinates": [-3.82089, 52.75336]}}]}