{"type": "FeatureCollection", "id": "https://topostext.org/place/309324UMag", "name": "309324UMag", "features": [{"type": "Feature", "id": "http://data.archaeology.link/data/ancientports/3874", "name": "", "dateprops": ["begin"], "properties": {"http://purl.org/dc/elements/1.1/creator": ["http://data.archaeology.link/data/spphaefen/arthur_de_graauw"], "http://purl.org/dc/terms/partOf": ["http://data.archaeology.link/data/ancientports/bib_deGrauw_2013_GeoDB"], "http://rdfs.org/ns/void#inDataset": ["http://data.archaeology.link/data/ancientports/dataset"], "http://www.opengis.net/ont/geosparql#hasGeometry": ["http://data.archaeology.link/data/ancientports/3874_geom"], "http://www.w3.org/1999/02/22-rdf-syntax-ns#type": ["http://www.ancientports.com/ont#Harbour"], "http://www.w3.org/2000/01/rdf-schema#label": ["Tell Kedua, Kedwa, Oren's T-21"], "http://www.w3.org/2004/02/skos/core#note": ["Chartier-Raymond (1993)"], "http://www.w3.org/2006/time#hasTime": ["http://data.archaeology.link/data/ancientports/3874_foundation"], "http://www.wikidata.org/prop/direct/P1584": ["http://pleiades.stoa.org/places/727152"], "http://www.wikidata.org/prop/direct/P17": ["http://www.wikidata.org/entity/Q79"], "http://www.wikidata.org/prop/direct/P1936": ["http://imperium.ahlfeldt.se/places/28491"], "http://www.wikidata.org/prop/direct/P1958": ["https://www.trismegistos.org/place/2698"], "http://www.wikidata.org/prop/direct/P8068": ["https://topostext.org/place/309324UMag"], "begin": "-750"}, "geometry": {"type": "Point", "coordinates": [32.4755, 30.9833]}}, {"type": "Feature", "id": "http://data.archaeology.link/data/ancientports/3875", "name": "", "dateprops": ["begin"], "properties": {"http://purl.org/dc/elements/1.1/creator": ["http://data.archaeology.link/data/spphaefen/arthur_de_graauw"], "http://purl.org/dc/terms/partOf": ["http://data.archaeology.link/data/ancientports/bib_deGrauw_2013_GeoDB"], "http://rdfs.org/ns/void#inDataset": ["http://data.archaeology.link/data/ancientports/dataset"], "http://www.opengis.net/ont/geosparql#hasGeometry": ["http://data.archaeology.link/data/ancientports/3875_geom"], "http://www.w3.org/1999/02/22-rdf-syntax-ns#type": ["http://www.ancientports.com/ont#Harbour"], "http://www.w3.org/2000/01/rdf-schema#label": ["Tell el-Herr, el-Heir"], "http://www.w3.org/2002/07/owl#sameAs": ["http://www.wikidata.org/entity/Q193850"], "http://www.w3.org/2004/02/skos/core#note": ["Oren (1984)", "Valbelle (1998)"], "http://www.w3.org/2006/time#hasTime": ["http://data.archaeology.link/data/ancientports/3875_foundation"], "http://www.wikidata.org/prop/direct/P1584": ["http://pleiades.stoa.org/places/727152"], "http://www.wikidata.org/prop/direct/P17": ["http://www.wikidata.org/entity/Q79"], "http://www.wikidata.org/prop/direct/P1936": ["http://imperium.ahlfeldt.se/places/28491"], "http://www.wikidata.org/prop/direct/P1958": ["https://www.trismegistos.org/place/2698"], "http://www.wikidata.org/prop/direct/P8068": ["https://topostext.org/place/309324UMag"], "begin": "-500"}, "geometry": {"type": "Point", "coordinates": [32.4929, 30.9672]}}], "numberMatched": 2, "numberReturned": 2, "bbox": [32.4755, 30.9672, 32.4929, 30.9833], "crs": "http://www.opengis.net/def/crs/EPSG/0/4326"}