{"type": "FeatureCollection", "id": "http://www.wikidata.org/entity/Q85971904", "name": "Karanl%C4%B1k Kap%C4%B1", "features": [{"type": "Feature", "id": "http://data.archaeology.link/data/ancientports/3394", "name": "", "dateprops": ["begin"], "properties": {"http://purl.org/dc/elements/1.1/creator": ["http://data.archaeology.link/data/spphaefen/arthur_de_graauw"], "http://purl.org/dc/terms/isReferencedBy": ["http://data.archaeology.link/data/ancientports/bib_Akpinar_2004_Hellenistic"], "http://purl.org/dc/terms/partOf": ["http://data.archaeology.link/data/ancientports/bib_deGrauw_2013_GeoDB"], "http://rdfs.org/ns/void#inDataset": ["http://data.archaeology.link/data/ancientports/ap_dataset"], "http://www.opengis.net/ont/geosparql#hasGeometry": ["http://data.archaeology.link/data/ancientports/3394_geom"], "http://www.w3.org/1999/02/22-rdf-syntax-ns#type": ["http://www.ancientports.com/ont#Harbour"], "http://www.w3.org/2000/01/rdf-schema#label": ["Muttalip, Mutlubake, Karanlik Kapi, near Issos Harabeleri and Deli Halil settlements"], "http://www.w3.org/2002/07/owl#sameAs": ["http://www.wikidata.org/entity/Q85971904"], "http://www.w3.org/2006/time#hasTime": ["http://data.archaeology.link/data/ancientports/3394_foundation"], "http://www.wikidata.org/prop/direct/P1584": ["https://pleiades.stoa.org/places/658375"], "http://www.wikidata.org/prop/direct/P17": ["http://www.wikidata.org/entity/Q43"], "begin": "-330"}, "geometry": {"type": "Point", "coordinates": [35.9715, 36.9176]}}], "numberMatched": 1, "numberReturned": 1, "bbox": [35.9715, 36.9176, 35.9715, 36.9176], "crs": "http://www.opengis.net/def/crs/EPSG/0/4326"}