{"type": "FeatureCollection", "id": "http://www.wikidata.org/entity/Q65051540", "name": "Q65051540", "features": [{"type": "Feature", "id": "http://data.archaeology.link/data/ancientports/2421", "label": "Bebek", "properties": {"http://purl.org/dc/elements/1.1/created": ["2023"], "http://purl.org/dc/elements/1.1/creator": ["http://data.archaeology.link/data/spphaefen/arthur_de_graauw"], "http://www.ancientports.com/ont#date_min": ["-30"], "http://www.opengis.net/ont/geosparql#hasGeometry": ["http://data.archaeology.link/data/ancientports/2421_geom"], "http://www.w3.org/1999/02/22-rdf-syntax-ns#type": ["http://www.ancientports.com/ont#Harbour"], "http://www.w3.org/2000/01/rdf-schema#label": ["Bebek"], "http://www.w3.org/2002/07/owl#sameAs": ["http://www.wikidata.org/entity/Q65051540"], "http://www.w3.org/2004/02/skos/core#note": ["K\u00fclzer (2011)"], "http://www.wikidata.org/prop/direct/P1584": ["http://pleiades.stoa.org/places/520992"], "http://www.wikidata.org/prop/direct/P17": ["TR: Bosph N"]}, "geometry": {"type": "Point", "coordinates": [29.043, 41.077]}}]}