{"type": "FeatureCollection", "id": "http://pleiades.stoa.org/places/716635", "name": "716635", "features": [{"type": "Feature", "id": "http://data.archaeology.link/data/ancientports/3966", "label": "Marsa el-Asi, Aasi", "properties": {"http://purl.org/dc/elements/1.1/created": ["2023"], "http://purl.org/dc/elements/1.1/creator": ["http://data.archaeology.link/data/spphaefen/arthur_de_graauw"], "http://www.ancientports.com/ont#date_min": ["-330"], "http://www.opengis.net/ont/geosparql#hasGeometry": ["http://data.archaeology.link/data/ancientports/3966_geom"], "http://www.w3.org/1999/02/22-rdf-syntax-ns#type": ["http://www.ancientports.com/ont#Harbour"], "http://www.w3.org/2000/01/rdf-schema#label": ["Marsa el-Asi, Aasi"], "http://www.wikidata.org/prop/direct/P1584": ["http://pleiades.stoa.org/places/716635"], "http://www.wikidata.org/prop/direct/P17": ["Egypt: Med Sea"], "http://www.wikidata.org/prop/direct/P1936": ["http://imperium.ahlfeldt.se/places/36217"], "http://www.wikidata.org/prop/direct/P1958": ["https://www.trismegistos.org/place/7101"]}, "geometry": {"type": "Point", "coordinates": [26.7837, 31.4649]}}]}