{"type": "FeatureCollection", "id": "http://imperium.ahlfeldt.se/places/27148", "name": "27148", "features": [{"type": "Feature", "id": "http://data.archaeology.link/data/ancientports/3794", "label": "Tell Khazneh & Tell Sa\u2019ad & Tell Sa'aid, on the isle of Failaka, Koweith", "dateprops": [], "properties": {"http://purl.org/dc/elements/1.1/created": ["2023"], "http://purl.org/dc/elements/1.1/creator": ["http://data.archaeology.link/data/spphaefen/arthur_de_graauw"], "http://purl.org/dc/terms/isReferencedBy": ["https://pcma.uw.edu.pl/en/2019/03/26/failaka-archaeological-survey/", "http://data.archaeology.link/data/ancientports/bib_Pawlicki_2015_Preliminary", "http://data.archaeology.link/data/ancientports/bib_Connan_2007_Geochemical"], "http://www.opengis.net/ont/geosparql#hasGeometry": ["http://data.archaeology.link/data/ancientports/3794_geom"], "http://www.w3.org/1999/02/22-rdf-syntax-ns#type": ["http://www.ancientports.com/ont#Harbour"], "http://www.w3.org/2000/01/rdf-schema#label": ["Tell Khazneh & Tell Sa\u2019ad & Tell Sa'aid, on the isle of Failaka, Koweith"], "http://www.w3.org/2002/07/owl#sameAs": ["http://www.wikidata.org/entity/Q748846"], "http://www.w3.org/2006/time#hasTime": ["http://data.archaeology.link/data/ancientports/3794_foundation"], "http://www.wikidata.org/prop/direct/P1584": ["http://pleiades.stoa.org/places/912851"], "http://www.wikidata.org/prop/direct/P17": ["Gulf"], "http://www.wikidata.org/prop/direct/P1936": ["http://imperium.ahlfeldt.se/places/27148"], "http://www.wikidata.org/prop/direct/P1958": ["https://www.trismegistos.org/place/37188"], "http://www.wikidata.org/prop/direct/P8068": ["https://topostext.org/place/294483IIka"]}, "geometry": {"type": "Point", "coordinates": [48.276, 29.4294]}}]}