{"type": "FeatureCollection", "id": "http://www.wikidata.org/entity/Q118642", "name": "Q118642", "features": [{"type": "Feature", "id": "http://data.archaeology.link/data/ancientports/1286", "label": "Termoli", "dateprops": ["http://purl.org/dc/elements/1.1/created"], "properties": {"http://purl.org/dc/elements/1.1/created": ["2023"], "http://purl.org/dc/elements/1.1/creator": ["http://data.archaeology.link/data/spphaefen/arthur_de_graauw"], "http://purl.org/dc/terms/isReferencedBy": ["http://toponomastica.altervista.org/dovera-buca/"], "http://www.opengis.net/ont/geosparql#hasGeometry": ["http://data.archaeology.link/data/ancientports/1286_geom"], "http://www.w3.org/1999/02/22-rdf-syntax-ns#type": ["http://www.ancientports.com/ont#Harbour"], "http://www.w3.org/2000/01/rdf-schema#label": ["Termoli"], "http://www.w3.org/2002/07/owl#sameAs": ["http://www.wikidata.org/entity/Q118642"], "http://www.w3.org/2006/time#hasTime": ["http://data.archaeology.link/data/ancientports/1286_foundation"], "http://www.wikidata.org/prop/direct/P1584": ["http://pleiades.stoa.org/places/432727"], "http://www.wikidata.org/prop/direct/P17": ["Italy Adriatic"], "http://www.wikidata.org/prop/direct/P1936": ["http://imperium.ahlfeldt.se/places/29123"], "http://www.wikidata.org/prop/direct/P1958": ["https://www.trismegistos.org/place/45826"]}, "geometry": {"type": "Point", "coordinates": [14.9976, 42.0066]}}]}