{"type": "FeatureCollection", "id": "http://pleiades.stoa.org/places/599523", "name": "599523", "features": [{"type": "Feature", "id": "http://data.archaeology.link/data/ancientports/2290", "label": "Ormos Partheni,  on the isle of Leros ", "dateprops": [], "properties": {"http://purl.org/dc/elements/1.1/created": ["2023"], "http://purl.org/dc/elements/1.1/creator": ["http://data.archaeology.link/data/spphaefen/arthur_de_graauw"], "http://www.ancientports.com/ont#date_min": ["-750"], "http://www.opengis.net/ont/geosparql#hasGeometry": ["http://data.archaeology.link/data/ancientports/2290_geom"], "http://www.w3.org/1999/02/22-rdf-syntax-ns#type": ["http://www.ancientports.com/ont#Harbour"], "http://www.w3.org/2000/01/rdf-schema#label": ["Ormos Partheni,  on the isle of Leros "], "http://www.wikidata.org/prop/direct/P1584": ["http://pleiades.stoa.org/places/599523"], "http://www.wikidata.org/prop/direct/P17": ["GR: Eastern Isl."], "http://www.wikidata.org/prop/direct/P1936": ["http://imperium.ahlfeldt.se/places/36697"], "http://www.wikidata.org/prop/direct/P8068": ["https://topostext.org/place/372268SArt"]}, "geometry": {"type": "Point", "coordinates": [26.8004, 37.1814]}}]}