{"type": "FeatureCollection", "id": "https://www.trismegistos.org/place/33241", "name": "33241", "features": [{"type": "Feature", "id": "http://data.archaeology.link/data/ancientports/2053", "label": "Isle of Gyaros", "properties": {"http://purl.org/dc/elements/1.1/created": ["2023"], "http://purl.org/dc/elements/1.1/creator": ["http://data.archaeology.link/data/spphaefen/arthur_de_graauw"], "http://www.opengis.net/ont/geosparql#hasGeometry": ["http://data.archaeology.link/data/ancientports/2053_geom"], "http://www.w3.org/1999/02/22-rdf-syntax-ns#type": ["http://www.ancientports.com/ont#Harbour"], "http://www.w3.org/2000/01/rdf-schema#label": ["Isle of Gyaros"], "http://www.w3.org/2002/07/owl#sameAs": ["http://www.wikidata.org/entity/Q1147663"], "http://www.wikidata.org/prop/direct/P1584": ["http://pleiades.stoa.org/places/589797"], "http://www.wikidata.org/prop/direct/P17": ["GR: Cyclades Isl."], "http://www.wikidata.org/prop/direct/P1958": ["https://www.trismegistos.org/place/33241"]}, "geometry": {"type": "Point", "coordinates": [24.71273, 37.60729]}}]}