{"type": "FeatureCollection", "id": "http://pleiades.stoa.org/places/707544", "name": "707544", "features": [{"type": "Feature", "id": "http://data.archaeology.link/data/ancientports/3057", "name": "Tochni Lakkia, port of Kalavasos-Tenta copper mines?", "dateprops": ["begin"], "properties": {"http://purl.org/dc/elements/1.1/creator": ["http://data.archaeology.link/data/spphaefen/arthur_de_graauw"], "http://purl.org/dc/terms/isReferencedBy": ["http://data.archaeology.link/data/ancientports/bib_Sabatini_2016_Revisiting"], "http://purl.org/dc/terms/partOf": ["http://data.archaeology.link/data/ancientports/bib_deGrauw_2013_GeoDB"], "http://www.opengis.net/ont/geosparql#hasGeometry": ["http://data.archaeology.link/data/ancientports/3057_geom"], "http://www.w3.org/1999/02/22-rdf-syntax-ns#type": ["http://www.ancientports.com/ont#Harbour"], "http://www.w3.org/2000/01/rdf-schema#label": ["Tochni Lakkia, port of Kalavasos-Tenta copper mines?"], "http://www.w3.org/2002/07/owl#sameAs": ["http://www.wikidata.org/entity/Q1404714"], "http://www.w3.org/2004/02/skos/core#note": ["Andreou (2014)"], "http://www.w3.org/2006/time#hasTime": ["http://data.archaeology.link/data/ancientports/3057_foundation"], "http://www.wikidata.org/prop/direct/P1584": ["http://pleiades.stoa.org/places/707544"], "http://www.wikidata.org/prop/direct/P17": ["http://www.wikidata.org/entity/Q229"], "http://www.wikidata.org/prop/direct/P1936": ["http://imperium.ahlfeldt.se/places/28427"], "begin": "-1250"}, "geometry": {"type": "Point", "coordinates": [33.327, 34.7191]}}, {"type": "Feature", "id": "http://data.archaeology.link/data/ancientports/3056", "name": "Zygi-Petrini, port of Kalavasos-Kopetra & Kalavasos-Tenta copper mines? Roman amphora kiln", "dateprops": [], "properties": {"http://purl.org/dc/elements/1.1/creator": ["http://data.archaeology.link/data/spphaefen/arthur_de_graauw"], "http://purl.org/dc/terms/isReferencedBy": ["http://data.archaeology.link/data/ancientports/bib_Sabatini_2016_Revisiting"], "http://purl.org/dc/terms/partOf": ["http://data.archaeology.link/data/ancientports/bib_deGrauw_2013_GeoDB"], "http://www.opengis.net/ont/geosparql#hasGeometry": ["http://data.archaeology.link/data/ancientports/3056_geom"], "http://www.w3.org/1999/02/22-rdf-syntax-ns#type": ["http://www.ancientports.com/ont#Harbour"], "http://www.w3.org/2000/01/rdf-schema#label": ["Zygi-Petrini, port of Kalavasos-Kopetra & Kalavasos-Tenta copper mines? Roman amphora kiln"], "http://www.w3.org/2002/07/owl#sameAs": ["http://www.wikidata.org/entity/Q1404714"], "http://www.w3.org/2004/02/skos/core#note": ["Manning (2000)"], "http://www.wikidata.org/prop/direct/P1584": ["http://pleiades.stoa.org/places/707544"], "http://www.wikidata.org/prop/direct/P17": ["http://www.wikidata.org/entity/Q229"], "http://www.wikidata.org/prop/direct/P1936": ["http://imperium.ahlfeldt.se/places/28427"], "http://www.wikidata.org/prop/direct/P1958": ["https://www.trismegistos.org/place/57656"], "http://www.wikidata.org/prop/direct/P8068": ["https://topostext.org/place/347333XTen"], "begin": ""}, "geometry": {"type": "Point", "coordinates": [33.3324, 34.7242]}}], "numberMatched": 2, "numberReturned": 2, "bbox": [33.327, 34.7191, 33.3324, 34.7242], "crs": "http://www.opengis.net/def/crs/OGC/1.3/CRS84"}