{"type": "FeatureCollection", "id": "https://topostext.org/place/382204UPal", "name": "382204UPal", "features": [{"type": "Feature", "id": "http://data.archaeology.link/data/ancientports/2017", "label": "near Lixouri, on the isle of Cephalonia", "dateprops": ["http://purl.org/dc/elements/1.1/created"], "properties": {"http://purl.org/dc/elements/1.1/created": ["2023"], "http://purl.org/dc/elements/1.1/creator": ["http://data.archaeology.link/data/spphaefen/arthur_de_graauw"], "http://www.opengis.net/ont/geosparql#hasGeometry": ["http://data.archaeology.link/data/ancientports/2017_geom"], "http://www.w3.org/1999/02/22-rdf-syntax-ns#type": ["http://www.ancientports.com/ont#Harbour"], "http://www.w3.org/2000/01/rdf-schema#label": ["near Lixouri, on the isle of Cephalonia"], "http://www.w3.org/2002/07/owl#sameAs": ["http://www.wikidata.org/entity/Q2047660"], "http://www.w3.org/2006/time#hasTime": ["http://data.archaeology.link/data/ancientports/2017_foundation"], "http://www.wikidata.org/prop/direct/P1584": ["http://pleiades.stoa.org/places/531036"], "http://www.wikidata.org/prop/direct/P17": ["GR: Ionian Isl."], "http://www.wikidata.org/prop/direct/P1936": ["http://imperium.ahlfeldt.se/places/31619"], "http://www.wikidata.org/prop/direct/P1958": ["https://www.trismegistos.org/place/37944"], "http://www.wikidata.org/prop/direct/P8068": ["https://topostext.org/place/382204UPal"]}, "geometry": {"type": "Point", "coordinates": [20.4375, 38.2226]}}]}