{"type": "FeatureCollection", "id": "http://imperium.ahlfeldt.se/places/22749", "name": "22749", "features": [{"type": "Feature", "id": "http://data.archaeology.link/data/ancientports/1725", "label": "Oraioi, with 900 m (?) breakwater acc. to Lehmann-Hartleben", "properties": {"http://purl.org/dc/elements/1.1/created": ["2023"], "http://purl.org/dc/elements/1.1/creator": ["http://data.archaeology.link/data/spphaefen/arthur_de_graauw"], "http://www.ancientports.com/ont#date_min": ["-750"], "http://www.opengis.net/ont/geosparql#hasGeometry": ["http://data.archaeology.link/data/ancientports/1725_geom"], "http://www.w3.org/1999/02/22-rdf-syntax-ns#type": ["http://www.ancientports.com/ont#Harbour"], "http://www.w3.org/2000/01/rdf-schema#label": ["Oraioi, with 900 m (?) breakwater acc. to Lehmann-Hartleben"], "http://www.wikidata.org/prop/direct/P1584": ["http://pleiades.stoa.org/places/540817"], "http://www.wikidata.org/prop/direct/P17": ["GR: Evia"], "http://www.wikidata.org/prop/direct/P1936": ["http://imperium.ahlfeldt.se/places/22749"], "http://www.wikidata.org/prop/direct/P1958": ["https://www.trismegistos.org/place/856"], "http://www.wikidata.org/prop/direct/P8068": ["https://topostext.org/place/389231PHis"]}, "geometry": {"type": "Point", "coordinates": [23.087, 38.9485]}}]}