{"type": "FeatureCollection", "id": "https://topostext.org/place/384226XSte", "name": "384226XSte", "features": [{"type": "Feature", "id": "http://data.archaeology.link/data/ancientports/1605_1", "label": "Steno", "dateprops": ["http://purl.org/dc/elements/1.1/created"], "properties": {"http://purl.org/dc/elements/1.1/created": ["2023"], "http://purl.org/dc/elements/1.1/creator": ["http://data.archaeology.link/data/spphaefen/arthur_de_graauw"], "http://www.opengis.net/ont/geosparql#hasGeometry": ["http://data.archaeology.link/data/ancientports/1605_1_geom"], "http://www.w3.org/1999/02/22-rdf-syntax-ns#type": ["http://www.ancientports.com/ont#Harbour"], "http://www.w3.org/2000/01/rdf-schema#label": ["Steno"], "http://www.w3.org/2006/time#hasTime": ["http://data.archaeology.link/data/ancientports/1605_1_foundation"], "http://www.wikidata.org/prop/direct/P17": ["GR: North-West"], "http://www.wikidata.org/prop/direct/P8068": ["https://topostext.org/place/384226XSte"]}, "geometry": {"type": "Point", "coordinates": [22.6058, 38.3608]}}]}