{"type": "FeatureCollection", "id": "http://imperium.ahlfeldt.se/places/35476", "name": "35476", "features": [{"type": "Feature", "id": "http://data.archaeology.link/data/ancientports/2136", "label": "Roman villa at Probatas, on the isle of Milos, Melos, Degirmenlik ", "dateprops": ["http://purl.org/dc/elements/1.1/created", "http://www.ancientports.com/ont#date_min"], "properties": {"http://purl.org/dc/elements/1.1/created": ["2023"], "http://purl.org/dc/elements/1.1/creator": ["http://data.archaeology.link/data/spphaefen/arthur_de_graauw"], "http://www.ancientports.com/ont#date_min": ["-750"], "http://www.opengis.net/ont/geosparql#hasGeometry": ["http://data.archaeology.link/data/ancientports/2136_geom"], "http://www.w3.org/1999/02/22-rdf-syntax-ns#type": ["http://www.ancientports.com/ont#VillaMaritima"], "http://www.w3.org/2000/01/rdf-schema#label": ["Roman villa at Probatas, on the isle of Milos, Melos, Degirmenlik "], "http://www.wikidata.org/prop/direct/P1584": ["http://pleiades.stoa.org/places/570632"], "http://www.wikidata.org/prop/direct/P17": ["GR: Cyclades Isl."], "http://www.wikidata.org/prop/direct/P1936": ["http://imperium.ahlfeldt.se/places/35476"], "http://www.wikidata.org/prop/direct/P8068": ["https://topostext.org/place/367244VPro"]}, "geometry": {"type": "Point", "coordinates": [24.4398, 36.6715]}}]}