{"type": "FeatureCollection", "id": "http://www.wikidata.org/entity/Q2671391", "name": "Q2671391", "features": [{"type": "Feature", "id": "http://data.archaeology.link/data/ancientports/2711", "label": "Roman fort at Batumistsikhe, on R Korolis Tskali", "properties": {"http://purl.org/dc/elements/1.1/created": ["2023"], "http://purl.org/dc/elements/1.1/creator": ["http://data.archaeology.link/data/spphaefen/arthur_de_graauw"], "http://www.ancientports.com/ont#date_min": ["-750"], "http://www.opengis.net/ont/geosparql#hasGeometry": ["http://data.archaeology.link/data/ancientports/2711_geom"], "http://www.w3.org/1999/02/22-rdf-syntax-ns#type": ["http://www.ancientports.com/ont#Harbour"], "http://www.w3.org/2000/01/rdf-schema#label": ["Roman fort at Batumistsikhe, on R Korolis Tskali"], "http://www.w3.org/2002/07/owl#sameAs": ["http://www.wikidata.org/entity/Q2671391"], "http://www.wikidata.org/prop/direct/P1584": ["http://pleiades.stoa.org/places/857060"], "http://www.wikidata.org/prop/direct/P17": ["Georgia Black S."], "http://www.wikidata.org/prop/direct/P1936": ["http://imperium.ahlfeldt.se/places/29546"]}, "geometry": {"type": "Point", "coordinates": [41.65023, 41.65612]}}]}