{"type": "FeatureCollection", "id": "http://www.wikidata.org/entity/Q20978066", "name": "La Fosca", "features": [{"type": "Feature", "id": "http://data.archaeology.link/data/ancientports/444", "name": "Roman villa at Punta de Sant Esteve de La Fosca, near Palamos", "dateprops": [], "properties": {"http://purl.org/dc/elements/1.1/creator": ["http://data.archaeology.link/data/spphaefen/arthur_de_graauw"], "http://purl.org/dc/terms/partOf": ["http://data.archaeology.link/data/ancientports/bib_deGrauw_2013_GeoDB"], "http://www.opengis.net/ont/geosparql#hasGeometry": ["http://data.archaeology.link/data/ancientports/444_geom"], "http://www.w3.org/1999/02/22-rdf-syntax-ns#type": ["http://www.ancientports.com/ont#VillaMaritima"], "http://www.w3.org/2000/01/rdf-schema#label": ["Roman villa at Punta de Sant Esteve de La Fosca, near Palamos"], "http://www.w3.org/2002/07/owl#sameAs": ["http://www.wikidata.org/entity/Q20978066"], "http://www.w3.org/2004/02/skos/core#note": ["de Graauw pictures (2019)"], "http://www.wikidata.org/prop/direct/P17": ["http://www.wikidata.org/entity/Q29"], "begin": ""}, "geometry": {"type": "Point", "coordinates": [3.1475, 41.8583]}}, {"type": "Feature", "id": "http://data.archaeology.link/data/ancientports/444_1", "name": "Punta del Castell de La Fosca, near Palamos", "dateprops": ["begin"], "properties": {"http://purl.org/dc/elements/1.1/creator": ["http://data.archaeology.link/data/spphaefen/arthur_de_graauw"], "http://purl.org/dc/terms/partOf": ["http://data.archaeology.link/data/ancientports/bib_deGrauw_2013_GeoDB"], "http://www.opengis.net/ont/geosparql#hasGeometry": ["http://data.archaeology.link/data/ancientports/444_1_geom"], "http://www.w3.org/1999/02/22-rdf-syntax-ns#type": ["http://www.ancientports.com/ont#Harbour"], "http://www.w3.org/2000/01/rdf-schema#label": ["Punta del Castell de La Fosca, near Palamos"], "http://www.w3.org/2002/07/owl#sameAs": ["http://www.wikidata.org/entity/Q20978066"], "http://www.w3.org/2004/02/skos/core#note": ["DeFer (1705)"], "http://www.w3.org/2006/time#hasTime": ["http://data.archaeology.link/data/ancientports/444_1_foundation"], "http://www.wikidata.org/prop/direct/P1584": ["http://pleiades.stoa.org/places/246305"], "http://www.wikidata.org/prop/direct/P17": ["http://www.wikidata.org/entity/Q29"], "http://www.wikidata.org/prop/direct/P1936": ["http://imperium.ahlfeldt.se/places/18296"], "begin": "-330"}, "geometry": {"type": "Point", "coordinates": [3.15836, 41.86066]}}], "numberMatched": 2, "numberReturned": 2, "bbox": [3.1475, 41.8583, 3.15836, 41.86066], "crs": "http://www.opengis.net/def/crs/OGC/1.3/CRS84"}