{"type": "FeatureCollection", "id": "http://pleiades.stoa.org/places/157836", "name": "157836", "features": [{"type": "Feature", "id": "http://data.archaeology.link/data/ancientports/704", "label": "Roman naval base at Frejus, with one lighthouse at the Butte St Antoine and 3 landmarks: the Lanterne d'Auguste, the Triton Monument and the Lion de Mer islet in front of St Raphael", "dateprops": [], "properties": {"http://purl.org/dc/elements/1.1/created": ["2023"], "http://purl.org/dc/elements/1.1/creator": ["http://data.archaeology.link/data/spphaefen/arthur_de_graauw"], "http://www.opengis.net/ont/geosparql#hasGeometry": ["http://data.archaeology.link/data/ancientports/704_geom"], "http://www.w3.org/1999/02/22-rdf-syntax-ns#type": ["http://www.ancientports.com/ont#Warehouse", "http://www.ancientports.com/ont#Quay", "http://www.ancientports.com/ont#Lighthouse", "http://www.ancientports.com/ont#Pila", "http://www.ancientports.com/ont#VillaMaritima"], "http://www.w3.org/2000/01/rdf-schema#label": ["Roman naval base at Frejus, with one lighthouse at the Butte St Antoine and 3 landmarks: the Lanterne d'Auguste, the Triton Monument and the Lion de Mer islet in front of St Raphael"], "http://www.w3.org/2002/07/owl#sameAs": ["http://www.wikidata.org/entity/Q215155"], "http://www.w3.org/2004/02/skos/core#note": ["Gebera (2010)", "Bertoncello (2011)", "Excoffon (2021)"], "http://www.wikidata.org/prop/direct/P1584": ["http://pleiades.stoa.org/places/157836"], "http://www.wikidata.org/prop/direct/P17": ["http://www.wikidata.org/entity/Q142"], "http://www.wikidata.org/prop/direct/P1936": ["http://imperium.ahlfeldt.se/places/184"], "http://www.wikidata.org/prop/direct/P1958": ["https://www.trismegistos.org/place/20682"], "http://www.wikidata.org/prop/direct/P8068": ["https://topostext.org/place/434067UFIo"]}, "geometry": {"type": "Point", "coordinates": [6.7405, 43.43132]}}]}