{"type": "FeatureCollection", "id": "https://pleiades.stoa.org/places/50308", "name": "50308", "features": [{"type": "Feature", "id": "http://data.archaeology.link/data/ancientports/3863_6", "label": "Devgad Fort, at outlet of R Devgad", "properties": {"http://purl.org/dc/elements/1.1/created": ["2023"], "http://purl.org/dc/elements/1.1/creator": ["http://data.archaeology.link/data/spphaefen/arthur_de_graauw"], "http://www.opengis.net/ont/geosparql#hasGeometry": ["http://data.archaeology.link/data/ancientports/3863_6_geom"], "http://www.w3.org/1999/02/22-rdf-syntax-ns#type": ["http://www.ancientports.com/ont#Harbour"], "http://www.w3.org/2000/01/rdf-schema#label": ["Devgad Fort, at outlet of R Devgad"], "http://www.w3.org/2002/07/owl#sameAs": ["http://www.wikidata.org/entity/Q85756615"], "http://www.wikidata.org/prop/direct/P1584": ["https://pleiades.stoa.org/places/50308"], "http://www.wikidata.org/prop/direct/P17": ["India"]}, "geometry": {"type": "Point", "coordinates": [73.355, 16.387]}}]}