{"type": "FeatureCollection", "id": "http://imperium.ahlfeldt.se/places/22483", "name": "22483", "features": [{"type": "Feature", "id": "http://data.archaeology.link/data/ancientports/305", "name": "Castro Marim, on R Guadiana, navigable up to at least Mertola", "dateprops": ["begin"], "properties": {"http://purl.org/dc/elements/1.1/creator": ["http://data.archaeology.link/data/spphaefen/arthur_de_graauw"], "http://purl.org/dc/terms/isReferencedBy": ["http://data.archaeology.link/data/ancientports/bib_Wachsmann_2009_Palaeo"], "http://purl.org/dc/terms/partOf": ["http://data.archaeology.link/data/ancientports/bib_deGrauw_2013_GeoDB"], "http://www.opengis.net/ont/geosparql#hasGeometry": ["http://data.archaeology.link/data/ancientports/305_geom"], "http://www.w3.org/1999/02/22-rdf-syntax-ns#type": ["http://www.ancientports.com/ont#Harbour"], "http://www.w3.org/2000/01/rdf-schema#label": ["Castro Marim, on R Guadiana, navigable up to at least Mertola"], "http://www.w3.org/2002/07/owl#sameAs": ["http://www.wikidata.org/entity/Q5050374"], "http://www.w3.org/2004/02/skos/core#note": ["Arruda (1997)"], "http://www.w3.org/2006/time#hasTime": ["http://data.archaeology.link/data/ancientports/305_foundation"], "http://www.wikidata.org/prop/direct/P1584": ["http://pleiades.stoa.org/places/256008"], "http://www.wikidata.org/prop/direct/P17": ["http://www.wikidata.org/entity/Q45"], "http://www.wikidata.org/prop/direct/P1936": ["http://imperium.ahlfeldt.se/places/22483"], "http://www.wikidata.org/prop/direct/P1958": ["https://www.trismegistos.org/place/25812"], "http://www.wikidata.org/prop/direct/P8068": ["https://topostext.org/place/372000UBae"], "begin": "-1000"}, "geometry": {"type": "Point", "coordinates": [-7.4415, 37.21891]}}]}