{"type": "FeatureCollection", "id": "http://imperium.ahlfeldt.se/places/26972", "name": "26972", "features": [{"type": "Feature", "id": "http://data.archaeology.link/data/ancientports/4319", "label": "Sidi Abderahim ", "properties": {"http://purl.org/dc/elements/1.1/created": ["2023"], "http://purl.org/dc/elements/1.1/creator": ["http://data.archaeology.link/data/spphaefen/arthur_de_graauw"], "http://www.ancientports.com/ont#date_min": ["-30"], "http://www.opengis.net/ont/geosparql#hasGeometry": ["http://data.archaeology.link/data/ancientports/4319_geom"], "http://www.w3.org/1999/02/22-rdf-syntax-ns#type": ["http://www.ancientports.com/ont#Harbour"], "http://www.w3.org/2000/01/rdf-schema#label": ["Sidi Abderahim "], "http://www.wikidata.org/prop/direct/P1584": ["http://pleiades.stoa.org/places/275705"], "http://www.wikidata.org/prop/direct/P17": ["Morocco"], "http://www.wikidata.org/prop/direct/P1936": ["http://imperium.ahlfeldt.se/places/26972"]}, "geometry": {"type": "Point", "coordinates": [-6.1525, 35.2102]}}]}