{"type": "FeatureCollection", "id": "http://www.wikidata.org/entity/Q393975", "name": "Agios Nikolaos, Chalkidiki", "features": [{"type": "Feature", "id": "http://data.archaeology.link/data/ancientports/1810", "name": "", "dateprops": [], "properties": {"http://purl.org/dc/elements/1.1/creator": ["http://data.archaeology.link/data/spphaefen/arthur_de_graauw"], "http://purl.org/dc/terms/partOf": ["http://data.archaeology.link/data/ancientports/bib_deGrauw_2013_GeoDB"], "http://rdfs.org/ns/void#inDataset": ["http://data.archaeology.link/data/ancientports/ap_dataset"], "http://www.opengis.net/ont/geosparql#hasGeometry": ["http://data.archaeology.link/data/ancientports/1810_geom"], "http://www.w3.org/1999/02/22-rdf-syntax-ns#type": ["http://www.ancientports.com/ont#Harbour", "http://www.ancientports.com/ont#PotentialHarbour"], "http://www.w3.org/2000/01/rdf-schema#label": ["Ormos Dhimitriaki"], "http://www.w3.org/2002/07/owl#sameAs": ["http://www.wikidata.org/entity/Q393975"], "http://www.wikidata.org/prop/direct/P17": ["http://www.wikidata.org/entity/Q41"], "begin": ""}, "geometry": {"type": "Point", "coordinates": [23.75319, 40.22677]}}], "numberMatched": 1, "numberReturned": 1, "bbox": [23.75319, 40.22677, 23.75319, 40.22677], "crs": "http://www.opengis.net/def/crs/EPSG/0/4326"}