{"type": "FeatureCollection", "id": "http://pleiades.stoa.org/places/540804", "name": "540804", "features": [{"type": "Feature", "id": "http://data.archaeology.link/data/ancientports/1736", "label": "Port Surbi, near Almiros", "properties": {"http://purl.org/dc/elements/1.1/created": ["2023"], "http://purl.org/dc/elements/1.1/creator": ["http://data.archaeology.link/data/spphaefen/arthur_de_graauw"], "http://www.ancientports.com/ont#date_min": ["-302"], "http://www.opengis.net/ont/geosparql#hasGeometry": ["http://data.archaeology.link/data/ancientports/1736_geom"], "http://www.w3.org/1999/02/22-rdf-syntax-ns#type": ["http://www.ancientports.com/ont#Harbour"], "http://www.w3.org/2000/01/rdf-schema#label": ["Port Surbi, near Almiros"], "http://www.w3.org/2002/07/owl#sameAs": ["http://www.wikidata.org/entity/Q55623"], "http://www.wikidata.org/prop/direct/P1584": ["http://pleiades.stoa.org/places/540804"], "http://www.wikidata.org/prop/direct/P17": ["GR: North-East"], "http://www.wikidata.org/prop/direct/P1958": ["https://www.trismegistos.org/place/33382"]}, "geometry": {"type": "Point", "coordinates": [22.842, 39.16188]}}]}