{"type": "FeatureCollection", "id": "http://imperium.ahlfeldt.se/places/14185", "name": "14185", "features": [{"type": "Feature", "id": "http://data.archaeology.link/data/ancientports/559", "label": "Landerneau, on R Elorn", "dateprops": ["http://purl.org/dc/elements/1.1/created"], "properties": {"http://purl.org/dc/elements/1.1/created": ["2023"], "http://purl.org/dc/elements/1.1/creator": ["http://data.archaeology.link/data/spphaefen/arthur_de_graauw"], "http://www.opengis.net/ont/geosparql#hasGeometry": ["http://data.archaeology.link/data/ancientports/559_geom"], "http://www.w3.org/1999/02/22-rdf-syntax-ns#type": ["http://www.ancientports.com/ont#Harbour"], "http://www.w3.org/2000/01/rdf-schema#label": ["Landerneau, on R Elorn"], "http://www.w3.org/2002/07/owl#sameAs": ["http://www.wikidata.org/entity/Q325946"], "http://www.w3.org/2006/time#hasTime": ["http://data.archaeology.link/data/ancientports/559_foundation"], "http://www.wikidata.org/prop/direct/P1584": ["http://pleiades.stoa.org/places/69524"], "http://www.wikidata.org/prop/direct/P17": ["France West"], "http://www.wikidata.org/prop/direct/P1936": ["http://imperium.ahlfeldt.se/places/14185"]}, "geometry": {"type": "Point", "coordinates": [-4.25, 48.45]}}]}