{"type": "FeatureCollection", "id": "http://www.wikidata.org/entity/Q1394400", "name": "Porto Ercole", "features": [{"type": "Feature", "id": "http://data.archaeology.link/data/ancientports/886", "name": "Porto Ercole, on the peninsula of Argentario", "dateprops": ["begin"], "properties": {"http://purl.org/dc/elements/1.1/creator": ["http://data.archaeology.link/data/spphaefen/arthur_de_graauw"], "http://purl.org/dc/terms/partOf": ["http://data.archaeology.link/data/ancientports/bib_deGrauw_2013_GeoDB"], "http://www.opengis.net/ont/geosparql#hasGeometry": ["http://data.archaeology.link/data/ancientports/886_geom"], "http://www.w3.org/1999/02/22-rdf-syntax-ns#type": ["http://www.ancientports.com/ont#Harbour"], "http://www.w3.org/2000/01/rdf-schema#label": ["Porto Ercole, on the peninsula of Argentario"], "http://www.w3.org/2002/07/owl#sameAs": ["http://www.wikidata.org/entity/Q1394400"], "http://www.w3.org/2004/02/skos/core#note": ["Camilli (2005)"], "http://www.w3.org/2006/time#hasTime": ["http://data.archaeology.link/data/ancientports/886_foundation"], "http://www.wikidata.org/prop/direct/P1584": ["http://pleiades.stoa.org/places/403260"], "http://www.wikidata.org/prop/direct/P17": ["http://www.wikidata.org/entity/Q38"], "http://www.wikidata.org/prop/direct/P1936": ["http://imperium.ahlfeldt.se/places/23143"], "begin": "-330"}, "geometry": {"type": "Point", "coordinates": [11.2086, 42.3912]}}], "numberMatched": 1, "numberReturned": 1, "bbox": [11.2086, 42.3912, 11.2086, 42.3912], "crs": "http://www.opengis.net/def/crs/OGC/1.3/CRS84"}