{"type": "FeatureCollection", "id": "http://pleiades.stoa.org/places/707526", "name": "707526", "features": [{"type": "Feature", "id": "http://data.archaeology.link/data/ancientports/3098", "name": "Agios Philon, near Rizokarpaso, Dipkarpaz", "dateprops": ["begin"], "properties": {"http://purl.org/dc/elements/1.1/created": ["2023"], "http://purl.org/dc/elements/1.1/creator": ["http://data.archaeology.link/data/spphaefen/arthur_de_graauw"], "http://purl.org/dc/terms/isReferencedBy": ["http://www.whatson-northcyprus.com/interest/dipkarpaz/philon.htm"], "http://www.opengis.net/ont/geosparql#hasGeometry": ["http://data.archaeology.link/data/ancientports/3098_geom"], "http://www.w3.org/1999/02/22-rdf-syntax-ns#type": ["http://www.ancientports.com/ont#Harbour"], "http://www.w3.org/2000/01/rdf-schema#label": ["Agios Philon, near Rizokarpaso, Dipkarpaz"], "http://www.w3.org/2002/07/owl#sameAs": ["http://www.wikidata.org/entity/Q1734309"], "http://www.w3.org/2006/time#hasTime": ["http://data.archaeology.link/data/ancientports/3098_foundation"], "http://www.wikidata.org/prop/direct/P1584": ["http://pleiades.stoa.org/places/707526"], "http://www.wikidata.org/prop/direct/P17": ["http://www.wikidata.org/entity/Q229"], "http://www.wikidata.org/prop/direct/P1936": ["http://imperium.ahlfeldt.se/places/21561"], "http://www.wikidata.org/prop/direct/P1958": ["https://www.trismegistos.org/place/1011"], "http://www.wikidata.org/prop/direct/P8068": ["https://topostext.org/place/356344PKar"], "begin": "-750"}, "geometry": {"type": "Point", "coordinates": [34.372, 35.63]}}]}