{"type": "FeatureCollection", "id": "http://pleiades.stoa.org/places/857029", "name": "857029", "features": [{"type": "Feature", "id": "http://data.archaeology.link/data/ancientports/2757", "label": "at the outlet of R Yesilmak", "properties": {"http://purl.org/dc/elements/1.1/created": ["2023"], "http://purl.org/dc/elements/1.1/creator": ["http://data.archaeology.link/data/spphaefen/arthur_de_graauw"], "http://purl.org/dc/terms/isReferencedBy": ["https://topostext.org/place/412367WIri"], "http://www.ancientports.com/ont#date_min": ["-330"], "http://www.opengis.net/ont/geosparql#hasGeometry": ["http://data.archaeology.link/data/ancientports/2757_geom"], "http://www.w3.org/1999/02/22-rdf-syntax-ns#type": ["http://www.ancientports.com/ont#Harbour"], "http://www.w3.org/2000/01/rdf-schema#label": ["at the outlet of R Yesilmak"], "http://www.w3.org/2002/07/owl#sameAs": ["http://www.wikidata.org/entity/Q65048820"], "http://www.w3.org/2004/02/skos/core#note": ["https://topostext.org/place/412367WIri"], "http://www.wikidata.org/prop/direct/P1584": ["http://pleiades.stoa.org/places/857029"], "http://www.wikidata.org/prop/direct/P17": ["TR: Black Sea"], "http://www.wikidata.org/prop/direct/P1936": ["http://imperium.ahlfeldt.se/places/36254"], "http://www.wikidata.org/prop/direct/P1958": ["https://www.trismegistos.org/place/42083"]}, "geometry": {"type": "Point", "coordinates": [36.66, 41.383]}}]}