{"type": "FeatureCollection", "id": "http://imperium.ahlfeldt.se/places/36481", "name": "36481", "features": [{"type": "Feature", "id": "http://data.archaeology.link/data/ancientports/803", "name": "Porto Pozzo, ca. 12 km west of Capo d'Orso with famous Roccia dell' Orso landmark", "dateprops": ["begin"], "properties": {"http://purl.org/dc/elements/1.1/creator": ["http://data.archaeology.link/data/spphaefen/arthur_de_graauw"], "http://purl.org/dc/terms/partOf": ["http://data.archaeology.link/data/ancientports/bib_deGrauw_2013_GeoDB"], "http://www.opengis.net/ont/geosparql#hasGeometry": ["http://data.archaeology.link/data/ancientports/803_geom"], "http://www.w3.org/1999/02/22-rdf-syntax-ns#type": ["http://www.ancientports.com/ont#Harbour"], "http://www.w3.org/2000/01/rdf-schema#label": ["Porto Pozzo, ca. 12 km west of Capo d'Orso with famous Roccia dell' Orso landmark"], "http://www.w3.org/2002/07/owl#sameAs": ["http://www.wikidata.org/entity/Q55082163"], "http://www.w3.org/2006/time#hasTime": ["http://data.archaeology.link/data/ancientports/803_foundation"], "http://www.wikidata.org/prop/direct/P1584": ["http://pleiades.stoa.org/places/472036"], "http://www.wikidata.org/prop/direct/P17": ["http://www.wikidata.org/entity/Q38"], "http://www.wikidata.org/prop/direct/P1936": ["http://imperium.ahlfeldt.se/places/36481"], "begin": "-1500"}, "geometry": {"type": "Point", "coordinates": [9.27569, 41.19914]}}], "numberMatched": 1, "numberReturned": 1, "bbox": [9.27569, 41.19914, 9.27569, 41.19914], "crs": "http://www.opengis.net/def/crs/OGC/1.3/CRS84"}