{"type": "FeatureCollection", "id": "http://www.wikidata.org/entity/Q19232110", "name": "Site des Minimes", "features": [{"type": "Feature", "id": "http://data.archaeology.link/data/ancientports/592_1", "name": "Roman winery at Les Minimes, near La Rochelle", "dateprops": ["begin"], "properties": {"http://purl.org/dc/elements/1.1/creator": ["http://data.archaeology.link/data/spphaefen/arthur_de_graauw"], "http://purl.org/dc/terms/isReferencedBy": ["http://data.archaeology.link/data/ancientports/bib_Balmelle_2001_Viticulture"], "http://purl.org/dc/terms/partOf": ["http://data.archaeology.link/data/ancientports/bib_deGrauw_2013_GeoDB"], "http://www.opengis.net/ont/geosparql#hasGeometry": ["http://data.archaeology.link/data/ancientports/592_1_geom"], "http://www.w3.org/1999/02/22-rdf-syntax-ns#type": ["http://www.ancientports.com/ont#VillaMaritima"], "http://www.w3.org/2000/01/rdf-schema#label": ["Roman winery at Les Minimes, near La Rochelle"], "http://www.w3.org/2002/07/owl#sameAs": ["http://www.wikidata.org/entity/Q19232110"], "http://www.w3.org/2006/time#hasTime": ["http://data.archaeology.link/data/ancientports/592_1_foundation"], "http://www.wikidata.org/prop/direct/P1584": ["http://pleiades.stoa.org/places/140480"], "http://www.wikidata.org/prop/direct/P17": ["http://www.wikidata.org/entity/Q142"], "http://www.wikidata.org/prop/direct/P1936": ["http://imperium.ahlfeldt.se/places/18558"], "begin": "7001"}, "geometry": {"type": "Point", "coordinates": [-1.16217, 46.14379]}}], "numberMatched": 1, "numberReturned": 1, "bbox": [-1.16217, 46.14379, -1.16217, 46.14379], "crs": "http://www.opengis.net/def/crs/OGC/1.3/CRS84"}