{"type": "FeatureCollection", "id": "https://www.trismegistos.org/place/31995", "name": "31995", "features": [{"type": "Feature", "id": "http://data.archaeology.link/data/ancientports/908", "name": "Roman villa Torre Flavia", "dateprops": ["begin"], "properties": {"http://purl.org/dc/elements/1.1/created": ["2023"], "http://purl.org/dc/elements/1.1/creator": ["http://data.archaeology.link/data/spphaefen/arthur_de_graauw"], "http://www.opengis.net/ont/geosparql#hasGeometry": ["http://data.archaeology.link/data/ancientports/908_geom"], "http://www.w3.org/1999/02/22-rdf-syntax-ns#type": ["http://www.ancientports.com/ont#VillaMaritima"], "http://www.w3.org/2000/01/rdf-schema#label": ["Roman villa Torre Flavia"], "http://www.w3.org/2006/time#hasTime": ["http://data.archaeology.link/data/ancientports/908_foundation"], "http://www.wikidata.org/prop/direct/P1584": ["http://pleiades.stoa.org/places/422953"], "http://www.wikidata.org/prop/direct/P17": ["http://www.wikidata.org/entity/Q38"], "http://www.wikidata.org/prop/direct/P1936": ["http://imperium.ahlfeldt.se/places/35785"], "http://www.wikidata.org/prop/direct/P1958": ["https://www.trismegistos.org/place/31995"], "begin": "-30"}, "geometry": {"type": "Point", "coordinates": [12.0493, 41.9555]}}]}