{"type": "FeatureCollection", "id": "http://pleiades.stoa.org/places/716575", "name": "716575", "features": [{"type": "Feature", "id": "http://data.archaeology.link/data/ancientports/3960", "label": "Ras Hawala, Almaza Beach Resort", "dateprops": ["http://purl.org/dc/elements/1.1/created"], "properties": {"http://purl.org/dc/elements/1.1/created": ["2023"], "http://purl.org/dc/elements/1.1/creator": ["http://data.archaeology.link/data/spphaefen/arthur_de_graauw"], "http://www.opengis.net/ont/geosparql#hasGeometry": ["http://data.archaeology.link/data/ancientports/3960_geom"], "http://www.w3.org/1999/02/22-rdf-syntax-ns#type": ["http://www.ancientports.com/ont#Harbour"], "http://www.w3.org/2000/01/rdf-schema#label": ["Ras Hawala, Almaza Beach Resort"], "http://www.w3.org/2006/time#hasTime": ["http://data.archaeology.link/data/ancientports/3960_foundation"], "http://www.wikidata.org/prop/direct/P1584": ["http://pleiades.stoa.org/places/716575"], "http://www.wikidata.org/prop/direct/P17": ["Egypt: Med Sea"], "http://www.wikidata.org/prop/direct/P1936": ["http://imperium.ahlfeldt.se/places/36210"], "http://www.wikidata.org/prop/direct/P1958": ["https://www.trismegistos.org/place/11127"], "http://www.wikidata.org/prop/direct/P8068": ["https://topostext.org/place/315275LKal"]}, "geometry": {"type": "Point", "coordinates": [27.56585, 31.203]}}]}