{"type": "FeatureCollection", "id": "http://www.wikidata.org/entity/Q51450", "name": "Giulianova", "features": [{"type": "Feature", "id": "http://data.archaeology.link/data/ancientports/1296", "name": "Giulianova, on R Tordino", "dateprops": ["begin"], "properties": {"http://purl.org/dc/elements/1.1/creator": ["http://data.archaeology.link/data/spphaefen/arthur_de_graauw"], "http://purl.org/dc/terms/partOf": ["http://data.archaeology.link/data/ancientports/bib_deGrauw_2013_GeoDB"], "http://www.opengis.net/ont/geosparql#hasGeometry": ["http://data.archaeology.link/data/ancientports/1296_geom"], "http://www.w3.org/1999/02/22-rdf-syntax-ns#type": ["http://www.ancientports.com/ont#Harbour"], "http://www.w3.org/2000/01/rdf-schema#label": ["Giulianova, on R Tordino"], "http://www.w3.org/2002/07/owl#sameAs": ["http://www.wikidata.org/entity/Q51450"], "http://www.w3.org/2004/02/skos/core#note": ["Staffa (2001)"], "http://www.w3.org/2006/time#hasTime": ["http://data.archaeology.link/data/ancientports/1296_foundation"], "http://www.wikidata.org/prop/direct/P1584": ["http://pleiades.stoa.org/places/413073"], "http://www.wikidata.org/prop/direct/P17": ["http://www.wikidata.org/entity/Q38"], "http://www.wikidata.org/prop/direct/P1936": ["http://imperium.ahlfeldt.se/places/18731"], "http://www.wikidata.org/prop/direct/P1958": ["https://www.trismegistos.org/place/14411"], "http://www.wikidata.org/prop/direct/P8068": ["https://topostext.org/place/427140UCNo"], "begin": "-330"}, "geometry": {"type": "Point", "coordinates": [13.971, 42.7356]}}], "numberMatched": 1, "numberReturned": 1, "bbox": [13.971, 42.7356, 13.971, 42.7356], "crs": "http://www.opengis.net/def/crs/EPSG/0/4326"}