{"type": "FeatureCollection", "id": "http://www.wikidata.org/entity/Q339503", "name": "Q339503", "features": [{"type": "Feature", "id": "http://data.archaeology.link/data/ancientports/171_21", "label": "Newgrange, Neolithic settlement, on R Boyne", "dateprops": ["http://purl.org/dc/elements/1.1/created"], "properties": {"http://purl.org/dc/elements/1.1/created": ["2023"], "http://purl.org/dc/elements/1.1/creator": ["http://data.archaeology.link/data/spphaefen/arthur_de_graauw"], "http://purl.org/dc/terms/isReferencedBy": ["http://hillforts.arch.ox.ac.uk/records/IR1086.html"], "http://www.opengis.net/ont/geosparql#hasGeometry": ["http://data.archaeology.link/data/ancientports/171_21_geom"], "http://www.w3.org/1999/02/22-rdf-syntax-ns#type": ["http://www.ancientports.com/ont#Harbour"], "http://www.w3.org/2000/01/rdf-schema#label": ["Newgrange, Neolithic settlement, on R Boyne"], "http://www.w3.org/2002/07/owl#sameAs": ["http://www.wikidata.org/entity/Q339503"], "http://www.w3.org/2006/time#hasTime": ["http://data.archaeology.link/data/ancientports/171_21_foundation"], "http://www.wikidata.org/prop/direct/P17": ["http://www.wikidata.org/entity/Q27"]}, "geometry": {"type": "Point", "coordinates": [-6.4756, 53.6947]}}]}