{"type": "FeatureCollection", "id": "https://www.trismegistos.org/place/14762", "name": "14762", "features": [{"type": "Feature", "id": "http://data.archaeology.link/data/ancientports/85", "label": "Southwick? possibly at outlet of R Adur, with a Roman villa", "dateprops": [], "properties": {"http://purl.org/dc/elements/1.1/created": ["2023"], "http://purl.org/dc/elements/1.1/creator": ["http://data.archaeology.link/data/spphaefen/arthur_de_graauw"], "http://purl.org/dc/terms/isReferencedBy": ["https://historicengland.org.uk/listing/the-list/list-entry/1015122"], "http://www.opengis.net/ont/geosparql#hasGeometry": ["http://data.archaeology.link/data/ancientports/85_geom"], "http://www.w3.org/1999/02/22-rdf-syntax-ns#type": ["http://www.ancientports.com/ont#VillaMaritima"], "http://www.w3.org/2000/01/rdf-schema#label": ["Southwick? possibly at outlet of R Adur, with a Roman villa"], "http://www.w3.org/2002/07/owl#sameAs": ["http://www.wikidata.org/entity/Q3965637"], "http://www.w3.org/2006/time#hasTime": ["http://data.archaeology.link/data/ancientports/85_foundation"], "http://www.wikidata.org/prop/direct/P1584": ["http://pleiades.stoa.org/places/79690"], "http://www.wikidata.org/prop/direct/P17": ["http://www.wikidata.org/entity/Q145"], "http://www.wikidata.org/prop/direct/P1936": ["http://imperium.ahlfeldt.se/places/25766"], "http://www.wikidata.org/prop/direct/P1958": ["https://www.trismegistos.org/place/14762"]}, "geometry": {"type": "Point", "coordinates": [-0.2476, 50.8276]}}]}