{"type": "FeatureCollection", "id": "http://pleiades.stoa.org/places/39270", "name": "39270", "features": [{"type": "Feature", "id": "http://data.archaeology.link/data/ancientports/3645", "label": "al-Hodeidah, Hudaydah, near outlet of wadi Siham", "dateprops": ["http://purl.org/dc/elements/1.1/created", "http://www.ancientports.com/ont#date_min"], "properties": {"http://purl.org/dc/elements/1.1/created": ["2023"], "http://purl.org/dc/elements/1.1/creator": ["http://data.archaeology.link/data/spphaefen/arthur_de_graauw"], "http://purl.org/dc/terms/isReferencedBy": ["http://data.archaeology.link/data/ancientports/bib_Bukharin_2012_The"], "http://www.ancientports.com/ont#date_min": ["-30"], "http://www.opengis.net/ont/geosparql#hasGeometry": ["http://data.archaeology.link/data/ancientports/3645_geom"], "http://www.w3.org/1999/02/22-rdf-syntax-ns#type": ["http://www.ancientports.com/ont#Harbour"], "http://www.w3.org/2000/01/rdf-schema#label": ["al-Hodeidah, Hudaydah, near outlet of wadi Siham"], "http://www.w3.org/2002/07/owl#sameAs": ["http://www.wikidata.org/entity/Q270041"], "http://www.wikidata.org/prop/direct/P1584": ["http://pleiades.stoa.org/places/39270"], "http://www.wikidata.org/prop/direct/P17": ["Yemen: Red Sea"], "http://www.wikidata.org/prop/direct/P1936": ["http://imperium.ahlfeldt.se/places/27290"]}, "geometry": {"type": "Point", "coordinates": [42.931, 14.816]}}]}