{"type": "FeatureCollection", "id": "https://pleiades.stoa.org/places/39405", "name": "39405", "features": [{"type": "Feature", "id": "http://data.archaeology.link/data/ancientports/3746_1", "name": "Geziret Sikha island, mentioned by PME 27", "dateprops": [], "properties": {"http://purl.org/dc/elements/1.1/created": ["2023"], "http://purl.org/dc/elements/1.1/creator": ["http://data.archaeology.link/data/spphaefen/arthur_de_graauw"], "http://www.opengis.net/ont/geosparql#hasGeometry": ["http://data.archaeology.link/data/ancientports/3746_1_geom"], "http://www.w3.org/1999/02/22-rdf-syntax-ns#type": ["http://www.ancientports.com/ont#Harbour"], "http://www.w3.org/2000/01/rdf-schema#label": ["Geziret Sikha island, mentioned by PME 27"], "http://www.wikidata.org/prop/direct/P1584": ["https://pleiades.stoa.org/places/39405"], "http://www.wikidata.org/prop/direct/P17": ["Yemen Ind Oc."], "http://www.wikidata.org/prop/direct/P1958": ["https://www.trismegistos.org/place/56809"], "begin": ""}, "geometry": {"type": "Point", "coordinates": [48.387, 13.934]}}]}