{"type": "FeatureCollection", "id": "http://www.wikidata.org/entity/Q173096", "name": "Q173096", "features": [{"type": "Feature", "id": "http://data.archaeology.link/data/ancientports/1692", "label": "Isle of Eubea, Evia", "properties": {"http://purl.org/dc/elements/1.1/created": ["2023"], "http://purl.org/dc/elements/1.1/creator": ["http://data.archaeology.link/data/spphaefen/arthur_de_graauw"], "http://www.opengis.net/ont/geosparql#hasGeometry": ["http://data.archaeology.link/data/ancientports/1692_geom"], "http://www.w3.org/1999/02/22-rdf-syntax-ns#type": ["http://www.ancientports.com/ont#Harbour"], "http://www.w3.org/2000/01/rdf-schema#label": ["Isle of Eubea, Evia"], "http://www.w3.org/2002/07/owl#sameAs": ["http://www.wikidata.org/entity/Q173096"], "http://www.wikidata.org/prop/direct/P1584": ["http://pleiades.stoa.org/places/540775"], "http://www.wikidata.org/prop/direct/P17": ["GR: Evia"], "http://www.wikidata.org/prop/direct/P1958": ["https://www.trismegistos.org/place/672"]}, "geometry": {"type": "Point", "coordinates": [23.76936, 38.57249]}}]}