{"type": "FeatureCollection", "id": "https://topostext.org/place/407228PSin", "name": "407228PSin", "features": [{"type": "Feature", "id": "http://data.archaeology.link/data/ancientports/1777", "label": "Sindos, on R Gallikos", "dateprops": [], "properties": {"http://purl.org/dc/elements/1.1/created": ["2023"], "http://purl.org/dc/elements/1.1/creator": ["http://data.archaeology.link/data/spphaefen/arthur_de_graauw"], "http://www.ancientports.com/ont#date_min": ["-750"], "http://www.opengis.net/ont/geosparql#hasGeometry": ["http://data.archaeology.link/data/ancientports/1777_geom"], "http://www.w3.org/1999/02/22-rdf-syntax-ns#type": ["http://www.ancientports.com/ont#Harbour"], "http://www.w3.org/2000/01/rdf-schema#label": ["Sindos, on R Gallikos"], "http://www.w3.org/2002/07/owl#sameAs": ["http://www.wikidata.org/entity/Q3392954"], "http://www.wikidata.org/prop/direct/P1584": ["http://pleiades.stoa.org/places/491717"], "http://www.wikidata.org/prop/direct/P17": ["GR: North-East"], "http://www.wikidata.org/prop/direct/P1936": ["http://imperium.ahlfeldt.se/places/32160"], "http://www.wikidata.org/prop/direct/P1958": ["https://www.trismegistos.org/place/29917"], "http://www.wikidata.org/prop/direct/P8068": ["https://topostext.org/place/407228PSin"]}, "geometry": {"type": "Point", "coordinates": [22.80006, 40.66996]}}]}