{"type": "FeatureCollection", "id": "http://pleiades.stoa.org/places/433111", "name": "433111", "features": [{"type": "Feature", "id": "http://data.archaeology.link/data/ancientports/967", "label": "Roman villa at Scauri ", "properties": {"http://purl.org/dc/elements/1.1/created": ["2023"], "http://purl.org/dc/elements/1.1/creator": ["http://data.archaeology.link/data/spphaefen/arthur_de_graauw"], "http://www.ancientports.com/ont#date_min": ["-330"], "http://www.opengis.net/ont/geosparql#hasGeometry": ["http://data.archaeology.link/data/ancientports/967_geom"], "http://www.w3.org/1999/02/22-rdf-syntax-ns#type": ["http://www.ancientports.com/ont#Harbour"], "http://www.w3.org/2000/01/rdf-schema#label": ["Roman villa at Scauri "], "http://www.w3.org/2002/07/owl#sameAs": ["http://www.wikidata.org/entity/Q128105"], "http://www.wikidata.org/prop/direct/P1584": ["http://pleiades.stoa.org/places/433111"], "http://www.wikidata.org/prop/direct/P17": ["Italy West"]}, "geometry": {"type": "Point", "coordinates": [13.70368, 41.25066]}}]}