{"type": "FeatureCollection", "id": "http://pleiades.stoa.org/places/845017", "name": "845017", "features": [{"type": "Feature", "id": "http://data.archaeology.link/data/ancientports/2809", "label": "K\u00f6seagzi near Bali", "dateprops": ["http://purl.org/dc/elements/1.1/created"], "properties": {"http://purl.org/dc/elements/1.1/created": ["2023"], "http://purl.org/dc/elements/1.1/creator": ["http://data.archaeology.link/data/spphaefen/arthur_de_graauw"], "http://www.opengis.net/ont/geosparql#hasGeometry": ["http://data.archaeology.link/data/ancientports/2809_geom"], "http://www.w3.org/1999/02/22-rdf-syntax-ns#type": ["http://www.ancientports.com/ont#Harbour"], "http://www.w3.org/2000/01/rdf-schema#label": ["K\u00f6seagzi near Bali"], "http://www.w3.org/2002/07/owl#sameAs": ["http://www.wikidata.org/entity/Q65046773"], "http://www.w3.org/2006/time#hasTime": ["http://data.archaeology.link/data/ancientports/2809_foundation"], "http://www.wikidata.org/prop/direct/P1584": ["http://pleiades.stoa.org/places/845017"], "http://www.wikidata.org/prop/direct/P17": ["TR: Black Sea"], "http://www.wikidata.org/prop/direct/P1936": ["http://imperium.ahlfeldt.se/places/27520"]}, "geometry": {"type": "Point", "coordinates": [31.46439, 41.33123]}}]}