{"type": "FeatureCollection", "id": "http://pleiades.stoa.org/places/462138", "name": "462138", "features": [{"type": "Feature", "id": "http://data.archaeology.link/data/ancientports/1160", "name": "Spiaggia di Malerba: port of Castellazzo di Palma di Montechiaro and Narasette?", "dateprops": ["begin"], "properties": {"http://purl.org/dc/elements/1.1/created": ["2023"], "http://purl.org/dc/elements/1.1/creator": ["http://data.archaeology.link/data/spphaefen/arthur_de_graauw"], "http://www.opengis.net/ont/geosparql#hasGeometry": ["http://data.archaeology.link/data/ancientports/1160_geom"], "http://www.w3.org/1999/02/22-rdf-syntax-ns#type": ["http://www.ancientports.com/ont#Harbour"], "http://www.w3.org/2000/01/rdf-schema#label": ["Spiaggia di Malerba: port of Castellazzo di Palma di Montechiaro and Narasette?"], "http://www.w3.org/2006/time#hasTime": ["http://data.archaeology.link/data/ancientports/1160_foundation"], "http://www.wikidata.org/prop/direct/P1584": ["http://pleiades.stoa.org/places/462138"], "http://www.wikidata.org/prop/direct/P17": ["http://www.wikidata.org/entity/Q38"], "http://www.wikidata.org/prop/direct/P1936": ["http://imperium.ahlfeldt.se/places/30510"], "begin": "-750"}, "geometry": {"type": "Point", "coordinates": [13.78002, 37.14449]}}]}