{"type": "FeatureCollection", "id": "https://topostext.org/place/407245XSSo", "name": "407245XSSo", "features": [{"type": "Feature", "id": "http://data.archaeology.link/data/ancientports/2169", "label": "Skala Sotiros, near St Prophet Elijah Orthodox Church, on the isle of Thassos", "dateprops": [], "properties": {"http://purl.org/dc/elements/1.1/created": ["2023"], "http://purl.org/dc/elements/1.1/creator": ["http://data.archaeology.link/data/spphaefen/arthur_de_graauw"], "http://purl.org/dc/terms/isReferencedBy": ["http://www.yppo.gr/5/g5111.jsp?obj_id=1382", "http://antiquatedantiquarian.blogspot.fr/2015/04/the-minoans-international-trade.html"], "http://www.opengis.net/ont/geosparql#hasGeometry": ["http://data.archaeology.link/data/ancientports/2169_geom"], "http://www.w3.org/1999/02/22-rdf-syntax-ns#type": ["http://www.ancientports.com/ont#Harbour"], "http://www.w3.org/2000/01/rdf-schema#label": ["Skala Sotiros, near St Prophet Elijah Orthodox Church, on the isle of Thassos"], "http://www.w3.org/2004/02/skos/core#note": ["Matsas (1995)"], "http://www.w3.org/2006/time#hasTime": ["http://data.archaeology.link/data/ancientports/2169_foundation"], "http://www.wikidata.org/prop/direct/P17": ["http://www.wikidata.org/entity/Q41"], "http://www.wikidata.org/prop/direct/P8068": ["https://topostext.org/place/407245XSSo"]}, "geometry": {"type": "Point", "coordinates": [24.5491, 40.7302]}}]}