{"type": "FeatureCollection", "id": "http://www.wikidata.org/entity/Q5070979", "name": "Q5070979", "features": [{"type": "Feature", "id": "http://data.archaeology.link/data/ancientports/2491", "label": "Enisala", "properties": {"http://purl.org/dc/elements/1.1/created": ["2023"], "http://purl.org/dc/elements/1.1/creator": ["http://data.archaeology.link/data/spphaefen/arthur_de_graauw"], "http://www.ancientports.com/ont#date_min": ["-30"], "http://www.opengis.net/ont/geosparql#hasGeometry": ["http://data.archaeology.link/data/ancientports/2491_geom"], "http://www.w3.org/1999/02/22-rdf-syntax-ns#type": ["http://www.ancientports.com/ont#Harbour"], "http://www.w3.org/2000/01/rdf-schema#label": ["Enisala"], "http://www.w3.org/2002/07/owl#sameAs": ["http://www.wikidata.org/entity/Q5070979"], "http://www.w3.org/2004/02/skos/core#note": ["Bivolaru (2017)"], "http://www.wikidata.org/prop/direct/P1584": ["http://pleiades.stoa.org/places/216805"], "http://www.wikidata.org/prop/direct/P17": ["Romania Black S."], "http://www.wikidata.org/prop/direct/P1936": ["http://imperium.ahlfeldt.se/places/21784"]}, "geometry": {"type": "Point", "coordinates": [28.8351, 44.88375]}}, {"type": "Feature", "id": "http://data.archaeology.link/data/ancientports/2494", "label": "Sarichoi", "properties": {"http://purl.org/dc/elements/1.1/created": ["2023"], "http://purl.org/dc/elements/1.1/creator": ["http://data.archaeology.link/data/spphaefen/arthur_de_graauw"], "http://www.opengis.net/ont/geosparql#hasGeometry": ["http://data.archaeology.link/data/ancientports/2494_geom"], "http://www.w3.org/1999/02/22-rdf-syntax-ns#type": ["http://www.ancientports.com/ont#Harbour"], "http://www.w3.org/2000/01/rdf-schema#label": ["Sarichoi"], "http://www.w3.org/2002/07/owl#sameAs": ["http://www.wikidata.org/entity/Q5070979"], "http://www.w3.org/2004/02/skos/core#note": ["Avram (2004)"], "http://www.wikidata.org/prop/direct/P17": ["Romania Black S."]}, "geometry": {"type": "Point", "coordinates": [28.86171, 44.94785]}}]}