{"type": "FeatureCollection", "id": "http://www.wikidata.org/entity/Q192483", "name": "Q192483", "features": [{"type": "Feature", "id": "http://data.archaeology.link/data/ancientports/2174", "label": "Isle of Limnos", "dateprops": [], "properties": {"http://purl.org/dc/elements/1.1/created": ["2023"], "http://purl.org/dc/elements/1.1/creator": ["http://data.archaeology.link/data/spphaefen/arthur_de_graauw"], "http://www.opengis.net/ont/geosparql#hasGeometry": ["http://data.archaeology.link/data/ancientports/2174_geom"], "http://www.w3.org/1999/02/22-rdf-syntax-ns#type": ["http://www.ancientports.com/ont#Harbour"], "http://www.w3.org/2000/01/rdf-schema#label": ["Isle of Limnos"], "http://www.w3.org/2002/07/owl#sameAs": ["http://www.wikidata.org/entity/Q192483"], "http://www.wikidata.org/prop/direct/P1584": ["http://pleiades.stoa.org/places/550693"], "http://www.wikidata.org/prop/direct/P17": ["GR: Eastern Isl."], "http://www.wikidata.org/prop/direct/P1936": ["http://imperium.ahlfeldt.se/places/41115"], "http://www.wikidata.org/prop/direct/P1958": ["https://www.trismegistos.org/place/1231"], "http://www.wikidata.org/prop/direct/P8068": ["https://topostext.org/place/399253ILem"]}, "geometry": {"type": "Point", "coordinates": [25.182, 39.92179]}}]}