{"type": "FeatureCollection", "id": "http://www.wikidata.org/entity/Q747679", "name": "Battle of Artemisium", "features": [{"type": "Feature", "id": "http://data.archaeology.link/data/ancientports/1758", "name": "Chorefto beach, is the only beach between Sepias and Castanea as described by Herodotus", "dateprops": ["begin"], "properties": {"http://purl.org/dc/elements/1.1/created": ["2023"], "http://purl.org/dc/elements/1.1/creator": ["http://data.archaeology.link/data/spphaefen/arthur_de_graauw"], "http://www.opengis.net/ont/geosparql#hasGeometry": ["http://data.archaeology.link/data/ancientports/1758_geom"], "http://www.w3.org/1999/02/22-rdf-syntax-ns#type": ["http://www.ancientports.com/ont#Harbour"], "http://www.w3.org/2000/01/rdf-schema#label": ["Chorefto beach, is the only beach between Sepias and Castanea as described by Herodotus"], "http://www.w3.org/2002/07/owl#sameAs": ["http://www.wikidata.org/entity/Q747679"], "http://www.w3.org/2006/time#hasTime": ["http://data.archaeology.link/data/ancientports/1758_foundation"], "http://www.wikidata.org/prop/direct/P17": ["http://www.wikidata.org/entity/Q41"], "begin": "-480"}, "geometry": {"type": "Point", "coordinates": [23.125, 39.454]}}]}