{"type": "FeatureCollection", "id": "http://www.wikidata.org/entity/Q471886", "name": "Q471886", "features": [{"type": "Feature", "id": "http://data.archaeology.link/data/ancientports/3494", "label": "Giv\u2019at Olga", "dateprops": [], "properties": {"http://purl.org/dc/elements/1.1/created": ["2023"], "http://purl.org/dc/elements/1.1/creator": ["http://data.archaeology.link/data/spphaefen/arthur_de_graauw"], "http://www.opengis.net/ont/geosparql#hasGeometry": ["http://data.archaeology.link/data/ancientports/3494_geom"], "http://www.w3.org/1999/02/22-rdf-syntax-ns#type": ["http://www.ancientports.com/ont#Harbour"], "http://www.w3.org/2000/01/rdf-schema#label": ["Giv\u2019at Olga"], "http://www.w3.org/2002/07/owl#sameAs": ["http://www.wikidata.org/entity/Q471886"], "http://www.w3.org/2006/time#hasTime": ["http://data.archaeology.link/data/ancientports/3494_foundation"], "http://www.wikidata.org/prop/direct/P1584": ["http://pleiades.stoa.org/places/678166"], "http://www.wikidata.org/prop/direct/P17": ["http://www.wikidata.org/entity/Q801"], "http://www.wikidata.org/prop/direct/P1936": ["http://imperium.ahlfeldt.se/places/33308"]}, "geometry": {"type": "Point", "coordinates": [34.87633, 32.44435]}}]}