{"type": "FeatureCollection", "id": "https://www.trismegistos.org/place/40552", "name": "40552", "features": [{"type": "Feature", "id": "http://data.archaeology.link/data/ancientports/2398_2", "label": "1.3 km south of Neolithic settlement at Yar\u0131mburgaz Magarasi cave, on R Sazlidere", "properties": {"http://purl.org/dc/elements/1.1/created": ["2023"], "http://purl.org/dc/elements/1.1/creator": ["http://data.archaeology.link/data/spphaefen/arthur_de_graauw"], "http://www.ancientports.com/ont#date_min": ["3001"], "http://www.opengis.net/ont/geosparql#hasGeometry": ["http://data.archaeology.link/data/ancientports/2398_2_geom"], "http://www.w3.org/1999/02/22-rdf-syntax-ns#type": ["http://www.ancientports.com/ont#Harbour"], "http://www.w3.org/2000/01/rdf-schema#label": ["1.3 km south of Neolithic settlement at Yar\u0131mburgaz Magarasi cave, on R Sazlidere"], "http://www.w3.org/2002/07/owl#sameAs": ["http://www.wikidata.org/entity/Q38251618"], "http://www.wikidata.org/prop/direct/P1584": ["https://pleiades.stoa.org/places/511315"], "http://www.wikidata.org/prop/direct/P17": ["TR: Marmara N"], "http://www.wikidata.org/prop/direct/P1936": ["http://imperium.ahlfeldt.se/places/22280"], "http://www.wikidata.org/prop/direct/P1958": ["https://www.trismegistos.org/place/40552"]}, "geometry": {"type": "Point", "coordinates": [28.7486, 41.0628]}}]}