{"type": "FeatureCollection", "id": "http://imperium.ahlfeldt.se/places/22690", "name": "22690", "features": [{"type": "Feature", "id": "http://data.archaeology.link/data/ancientports/2928", "label": "Menies bay, near Cape Spatha, on Rodopou peninsula", "dateprops": ["http://purl.org/dc/elements/1.1/created"], "properties": {"http://purl.org/dc/elements/1.1/created": ["2023"], "http://purl.org/dc/elements/1.1/creator": ["http://data.archaeology.link/data/spphaefen/arthur_de_graauw"], "http://www.opengis.net/ont/geosparql#hasGeometry": ["http://data.archaeology.link/data/ancientports/2928_geom"], "http://www.w3.org/1999/02/22-rdf-syntax-ns#type": ["http://www.ancientports.com/ont#Harbour"], "http://www.w3.org/2000/01/rdf-schema#label": ["Menies bay, near Cape Spatha, on Rodopou peninsula"], "http://www.w3.org/2004/02/skos/core#note": ["Uggeri (2003)"], "http://www.w3.org/2006/time#hasTime": ["http://data.archaeology.link/data/ancientports/2928_foundation"], "http://www.wikidata.org/prop/direct/P1584": ["http://pleiades.stoa.org/places/589760"], "http://www.wikidata.org/prop/direct/P17": ["GR: Crete North"], "http://www.wikidata.org/prop/direct/P1936": ["http://imperium.ahlfeldt.se/places/22690"], "http://www.wikidata.org/prop/direct/P1958": ["https://www.trismegistos.org/place/16077"], "http://www.wikidata.org/prop/direct/P8068": ["https://topostext.org/place/357238SDik"]}, "geometry": {"type": "Point", "coordinates": [23.7683, 35.6639]}}]}