{"type": "FeatureCollection", "id": "http://www.wikidata.org/entity/Q867592", "name": "Taba, Egypt", "features": [{"type": "Feature", "id": "http://data.archaeology.link/data/ancientports/3706", "name": "Marsa al-Marakh, Fjord bay Taba, 5 km NE of the Taba resort, near wadi Tuweiba", "dateprops": [], "properties": {"http://purl.org/dc/elements/1.1/creator": ["http://data.archaeology.link/data/spphaefen/arthur_de_graauw"], "http://purl.org/dc/terms/partOf": ["http://data.archaeology.link/data/ancientports/bib_deGrauw_2013_GeoDB"], "http://www.opengis.net/ont/geosparql#hasGeometry": ["http://data.archaeology.link/data/ancientports/3706_geom"], "http://www.w3.org/1999/02/22-rdf-syntax-ns#type": ["http://www.ancientports.com/ont#Harbour"], "http://www.w3.org/2000/01/rdf-schema#label": ["Marsa al-Marakh, Fjord bay Taba, 5 km NE of the Taba resort, near wadi Tuweiba"], "http://www.w3.org/2002/07/owl#sameAs": ["http://www.wikidata.org/entity/Q867592"], "http://www.wikidata.org/prop/direct/P17": ["Gulf of Aqaba "], "begin": ""}, "geometry": {"type": "Point", "coordinates": [34.8303, 29.4288]}}]}