{"type": "FeatureCollection", "id": "http://pleiades.stoa.org/places/256416", "name": "256416", "features": [{"type": "Feature", "id": "http://data.archaeology.link/data/ancientports/355_1", "name": "El Torreon, on R Guadalmansa", "dateprops": ["begin"], "properties": {"http://purl.org/dc/elements/1.1/creator": ["http://data.archaeology.link/data/spphaefen/arthur_de_graauw"], "http://purl.org/dc/terms/partOf": ["http://data.archaeology.link/data/ancientports/bib_deGrauw_2013_GeoDB"], "http://www.opengis.net/ont/geosparql#hasGeometry": ["http://data.archaeology.link/data/ancientports/355_1_geom"], "http://www.w3.org/1999/02/22-rdf-syntax-ns#type": ["http://www.ancientports.com/ont#Harbour"], "http://www.w3.org/2000/01/rdf-schema#label": ["El Torreon, on R Guadalmansa"], "http://www.w3.org/2006/time#hasTime": ["http://data.archaeology.link/data/ancientports/355_1_foundation"], "http://www.wikidata.org/prop/direct/P1584": ["http://pleiades.stoa.org/places/256416"], "http://www.wikidata.org/prop/direct/P17": ["http://www.wikidata.org/entity/Q29"], "http://www.wikidata.org/prop/direct/P1936": ["http://dare.ht.lu.se/places/22425"], "http://www.wikidata.org/prop/direct/P8068": ["https://topostext.org/place/365000USal"], "begin": "-750"}, "geometry": {"type": "Point", "coordinates": [-5.0625, 36.457]}}], "numberMatched": 1, "numberReturned": 1, "bbox": [-5.0625, 36.457, -5.0625, 36.457], "crs": "http://www.opengis.net/def/crs/OGC/1.3/CRS84"}