{"type": "FeatureCollection", "id": "http://www.wikidata.org/entity/Q947051", "name": "Q947051", "features": [{"type": "Feature", "id": "http://data.archaeology.link/data/ancientports/3238", "label": "Datca, Burgaz, northern harbour basin (L4)", "properties": {"http://purl.org/dc/elements/1.1/created": ["2023"], "http://purl.org/dc/elements/1.1/creator": ["http://data.archaeology.link/data/spphaefen/arthur_de_graauw"], "http://www.ancientports.com/ont#date_min": ["-330"], "http://www.opengis.net/ont/geosparql#hasGeometry": ["http://data.archaeology.link/data/ancientports/3238_geom"], "http://www.w3.org/1999/02/22-rdf-syntax-ns#type": ["http://www.ancientports.com/ont#Harbour"], "http://www.w3.org/2000/01/rdf-schema#label": ["Datca, Burgaz, northern harbour basin (L4)"], "http://www.w3.org/2002/07/owl#sameAs": ["http://www.wikidata.org/entity/Q947051"], "http://www.w3.org/2004/02/skos/core#note": ["Tuna (2012)"], "http://www.wikidata.org/prop/direct/P1584": ["http://pleiades.stoa.org/places/599576"], "http://www.wikidata.org/prop/direct/P17": ["TR: South"], "http://www.wikidata.org/prop/direct/P1936": ["http://imperium.ahlfeldt.se/places/25172"]}, "geometry": {"type": "Point", "coordinates": [27.70207, 36.73955]}}, {"type": "Feature", "id": "http://data.archaeology.link/data/ancientports/3237", "label": "Datca, Burgaz, central harbour basin (L1)", "properties": {"http://purl.org/dc/elements/1.1/created": ["2023"], "http://purl.org/dc/elements/1.1/creator": ["http://data.archaeology.link/data/spphaefen/arthur_de_graauw"], "http://www.ancientports.com/ont#date_min": ["-750"], "http://www.opengis.net/ont/geosparql#hasGeometry": ["http://data.archaeology.link/data/ancientports/3237_geom"], "http://www.w3.org/1999/02/22-rdf-syntax-ns#type": ["http://www.ancientports.com/ont#Harbour"], "http://www.w3.org/2000/01/rdf-schema#label": ["Datca, Burgaz, central harbour basin (L1)"], "http://www.w3.org/2002/07/owl#sameAs": ["http://www.wikidata.org/entity/Q947051"], "http://www.w3.org/2004/02/skos/core#note": ["Tuna (2012)"], "http://www.wikidata.org/prop/direct/P1584": ["http://pleiades.stoa.org/places/599576"], "http://www.wikidata.org/prop/direct/P17": ["TR: South"], "http://www.wikidata.org/prop/direct/P1936": ["http://imperium.ahlfeldt.se/places/25172"]}, "geometry": {"type": "Point", "coordinates": [27.70037, 36.7362]}}, {"type": "Feature", "id": "http://data.archaeology.link/data/ancientports/3236", "label": "Datca, Burgaz, 2 southern harbour basins (L2 & L3)", "properties": {"http://purl.org/dc/elements/1.1/created": ["2023"], "http://purl.org/dc/elements/1.1/creator": ["http://data.archaeology.link/data/spphaefen/arthur_de_graauw"], "http://www.ancientports.com/ont#date_min": ["-400"], "http://www.opengis.net/ont/geosparql#hasGeometry": ["http://data.archaeology.link/data/ancientports/3236_geom"], "http://www.w3.org/1999/02/22-rdf-syntax-ns#type": ["http://www.ancientports.com/ont#Quay"], "http://www.w3.org/2000/01/rdf-schema#label": ["Datca, Burgaz, 2 southern harbour basins (L2 & L3)"], "http://www.w3.org/2002/07/owl#sameAs": ["http://www.wikidata.org/entity/Q947051"], "http://www.w3.org/2004/02/skos/core#note": ["Tuna (2012)"], "http://www.wikidata.org/prop/direct/P1584": ["http://pleiades.stoa.org/places/599576"], "http://www.wikidata.org/prop/direct/P17": ["TR: South"], "http://www.wikidata.org/prop/direct/P1936": ["http://imperium.ahlfeldt.se/places/25172"]}, "geometry": {"type": "Point", "coordinates": [27.6949, 36.7312]}}]}