{"type": "FeatureCollection", "id": "http://pleiades.stoa.org/places/540633", "name": "540633", "features": [{"type": "Feature", "id": "http://data.archaeology.link/data/ancientports/1674", "label": "Isle of Mitrou, near Tragana, with BA settlement", "dateprops": ["http://purl.org/dc/elements/1.1/created", "http://www.ancientports.com/ont#date_min"], "properties": {"http://purl.org/dc/elements/1.1/created": ["2023"], "http://purl.org/dc/elements/1.1/creator": ["http://data.archaeology.link/data/spphaefen/arthur_de_graauw"], "http://www.ancientports.com/ont#date_min": ["-2000"], "http://www.opengis.net/ont/geosparql#hasGeometry": ["http://data.archaeology.link/data/ancientports/1674_geom"], "http://www.w3.org/1999/02/22-rdf-syntax-ns#type": ["http://www.ancientports.com/ont#Harbour"], "http://www.w3.org/2000/01/rdf-schema#label": ["Isle of Mitrou, near Tragana, with BA settlement"], "http://www.w3.org/2002/07/owl#sameAs": ["http://www.wikidata.org/entity/Q6882940"], "http://www.w3.org/2004/02/skos/core#note": ["Kramer-Hajos (2008)"], "http://www.wikidata.org/prop/direct/P1584": ["http://pleiades.stoa.org/places/540633"], "http://www.wikidata.org/prop/direct/P17": ["GR: Attica +"], "http://www.wikidata.org/prop/direct/P1936": ["http://imperium.ahlfeldt.se/places/29299"], "http://www.wikidata.org/prop/direct/P8068": ["https://topostext.org/place/386231UAna"]}, "geometry": {"type": "Point", "coordinates": [23.1235, 38.6354]}}]}