{"type": "FeatureCollection", "id": "http://imperium.ahlfeldt.se/places/35826", "name": "35826", "features": [{"type": "Feature", "id": "http://data.archaeology.link/data/ancientports/236", "label": "Nossa Senhora do Desterro", "dateprops": ["http://purl.org/dc/elements/1.1/created", "http://www.ancientports.com/ont#date_min"], "properties": {"http://purl.org/dc/elements/1.1/created": ["2023"], "http://purl.org/dc/elements/1.1/creator": ["http://data.archaeology.link/data/spphaefen/arthur_de_graauw"], "http://www.ancientports.com/ont#date_min": ["-30"], "http://www.opengis.net/ont/geosparql#hasGeometry": ["http://data.archaeology.link/data/ancientports/236_geom"], "http://www.w3.org/1999/02/22-rdf-syntax-ns#type": ["http://www.ancientports.com/ont#Harbour"], "http://www.w3.org/2000/01/rdf-schema#label": ["Nossa Senhora do Desterro"], "http://www.wikidata.org/prop/direct/P1584": ["http://pleiades.stoa.org/places/236572"], "http://www.wikidata.org/prop/direct/P17": ["http://www.wikidata.org/entity/Q45"], "http://www.wikidata.org/prop/direct/P1936": ["http://imperium.ahlfeldt.se/places/35826"]}, "geometry": {"type": "Point", "coordinates": [-8.68366, 40.17534]}}]}