{"type": "FeatureCollection", "id": "https://topostext.org/place/363277INar", "name": "363277INar", "features": [{"type": "Feature", "id": "http://data.archaeology.link/data/ancientports/2314_2", "name": "Isle of Sfyrna, near Rhodes", "dateprops": [], "properties": {"http://purl.org/dc/elements/1.1/creator": ["http://data.archaeology.link/data/spphaefen/arthur_de_graauw"], "http://purl.org/dc/terms/partOf": ["http://data.archaeology.link/data/ancientports/bib_deGrauw_2013_GeoDB"], "http://www.opengis.net/ont/geosparql#hasGeometry": ["http://data.archaeology.link/data/ancientports/2314_2_geom"], "http://www.w3.org/1999/02/22-rdf-syntax-ns#type": ["http://www.ancientports.com/ont#Harbour"], "http://www.w3.org/2000/01/rdf-schema#label": ["Isle of Sfyrna, near Rhodes"], "http://www.wikidata.org/prop/direct/P1584": ["http://pleiades.stoa.org/places/589952"], "http://www.wikidata.org/prop/direct/P17": ["http://www.wikidata.org/entity/Q41"], "http://www.wikidata.org/prop/direct/P1936": ["http://imperium.ahlfeldt.se/places/41164"], "http://www.wikidata.org/prop/direct/P8068": ["https://topostext.org/place/363277INar"], "begin": ""}, "geometry": {"type": "Point", "coordinates": [27.677, 36.264]}}], "numberMatched": 1, "numberReturned": 1, "bbox": [27.677, 36.264, 27.677, 36.264], "crs": "http://www.opengis.net/def/crs/OGC/1.3/CRS84"}