{"type": "FeatureCollection", "id": "http://pleiades.stoa.org/places/432788", "name": "432788", "features": [{"type": "Feature", "id": "http://data.archaeology.link/data/ancientports/950", "label": "Lago di Fogliano, near Latina", "dateprops": ["http://purl.org/dc/elements/1.1/created"], "properties": {"http://purl.org/dc/elements/1.1/created": ["2023"], "http://purl.org/dc/elements/1.1/creator": ["http://data.archaeology.link/data/spphaefen/arthur_de_graauw"], "http://www.opengis.net/ont/geosparql#hasGeometry": ["http://data.archaeology.link/data/ancientports/950_geom"], "http://www.w3.org/1999/02/22-rdf-syntax-ns#type": ["http://www.ancientports.com/ont#Harbour"], "http://www.w3.org/2000/01/rdf-schema#label": ["Lago di Fogliano, near Latina"], "http://www.w3.org/2006/time#hasTime": ["http://data.archaeology.link/data/ancientports/950_foundation"], "http://www.wikidata.org/prop/direct/P1584": ["http://pleiades.stoa.org/places/432788"], "http://www.wikidata.org/prop/direct/P17": ["Italy West"], "http://www.wikidata.org/prop/direct/P1936": ["http://imperium.ahlfeldt.se/places/23147"], "http://www.wikidata.org/prop/direct/P1958": ["https://www.trismegistos.org/place/32443"]}, "geometry": {"type": "Point", "coordinates": [12.86842, 41.40192]}}]}