{"type": "FeatureCollection", "id": "http://pleiades.stoa.org/places/403258", "name": "403258", "features": [{"type": "Feature", "id": "http://data.archaeology.link/data/ancientports/850", "name": "Porto delle Conche, near R Serchio", "dateprops": ["begin"], "properties": {"http://purl.org/dc/elements/1.1/creator": ["http://data.archaeology.link/data/spphaefen/arthur_de_graauw"], "http://purl.org/dc/terms/partOf": ["http://data.archaeology.link/data/ancientports/bib_deGrauw_2013_GeoDB"], "http://www.opengis.net/ont/geosparql#hasGeometry": ["http://data.archaeology.link/data/ancientports/850_geom"], "http://www.w3.org/1999/02/22-rdf-syntax-ns#type": ["http://www.ancientports.com/ont#Harbour"], "http://www.w3.org/2000/01/rdf-schema#label": ["Porto delle Conche, near R Serchio"], "http://www.w3.org/2004/02/skos/core#note": ["Camilli (2005)"], "http://www.w3.org/2006/time#hasTime": ["http://data.archaeology.link/data/ancientports/850_foundation"], "http://www.wikidata.org/prop/direct/P1584": ["http://pleiades.stoa.org/places/403258"], "http://www.wikidata.org/prop/direct/P17": ["http://www.wikidata.org/entity/Q38"], "http://www.wikidata.org/prop/direct/P1936": ["http://imperium.ahlfeldt.se/places/33588"], "begin": "-750"}, "geometry": {"type": "Point", "coordinates": [10.33555, 43.73476]}}]}