{"type": "FeatureCollection", "id": "http://imperium.ahlfeldt.se/places/43290", "name": "43290", "features": [{"type": "Feature", "id": "http://data.archaeology.link/data/ancientports/3347", "label": "Mamure Castle, on Anamur Cayi", "properties": {"http://purl.org/dc/elements/1.1/created": ["2023"], "http://purl.org/dc/elements/1.1/creator": ["http://data.archaeology.link/data/spphaefen/arthur_de_graauw"], "http://www.ancientports.com/ont#date_min": ["-30"], "http://www.opengis.net/ont/geosparql#hasGeometry": ["http://data.archaeology.link/data/ancientports/3347_geom"], "http://www.w3.org/1999/02/22-rdf-syntax-ns#type": ["http://www.ancientports.com/ont#Harbour"], "http://www.w3.org/2000/01/rdf-schema#label": ["Mamure Castle, on Anamur Cayi"], "http://www.w3.org/2002/07/owl#sameAs": ["http://www.wikidata.org/entity/Q85798255"], "http://www.wikidata.org/prop/direct/P1584": ["http://pleiades.stoa.org/places/648759"], "http://www.wikidata.org/prop/direct/P17": ["TR: South"], "http://www.wikidata.org/prop/direct/P1936": ["http://imperium.ahlfeldt.se/places/43290"]}, "geometry": {"type": "Point", "coordinates": [32.8945, 36.081]}}]}