{"type": "FeatureCollection", "id": "http://pleiades.stoa.org/places/573361", "name": "573361", "features": [{"type": "Feature", "id": "http://data.archaeology.link/data/ancientports/1947_2", "label": "near Epitalio", "dateprops": ["http://purl.org/dc/elements/1.1/created"], "properties": {"http://purl.org/dc/elements/1.1/created": ["2023"], "http://purl.org/dc/elements/1.1/creator": ["http://data.archaeology.link/data/spphaefen/arthur_de_graauw"], "http://www.opengis.net/ont/geosparql#hasGeometry": ["http://data.archaeology.link/data/ancientports/1947_2_geom"], "http://www.w3.org/1999/02/22-rdf-syntax-ns#type": ["http://www.ancientports.com/ont#Harbour"], "http://www.w3.org/2000/01/rdf-schema#label": ["near Epitalio"], "http://www.w3.org/2002/07/owl#sameAs": ["http://www.wikidata.org/entity/Q16185816"], "http://www.w3.org/2006/time#hasTime": ["http://data.archaeology.link/data/ancientports/1947_2_foundation"], "http://www.wikidata.org/prop/direct/P1584": ["http://pleiades.stoa.org/places/573361"], "http://www.wikidata.org/prop/direct/P17": ["GR: Pelop"], "http://www.wikidata.org/prop/direct/P1936": ["http://imperium.ahlfeldt.se/places/46272"], "http://www.wikidata.org/prop/direct/P8068": ["https://topostext.org/place/376215UMar"]}, "geometry": {"type": "Point", "coordinates": [21.48, 37.66]}}]}