{"type": "FeatureCollection", "id": "https://www.trismegistos.org/place/3356", "name": "3356", "features": [{"type": "Feature", "id": "http://data.archaeology.link/data/ancientports/2027", "name": "Mikri Dragonera, Antidragonera, is probably not a port but just a wreckage area!", "dateprops": [], "properties": {"http://purl.org/dc/elements/1.1/created": ["2023"], "http://purl.org/dc/elements/1.1/creator": ["http://data.archaeology.link/data/spphaefen/arthur_de_graauw"], "http://www.opengis.net/ont/geosparql#hasGeometry": ["http://data.archaeology.link/data/ancientports/2027_geom"], "http://www.w3.org/1999/02/22-rdf-syntax-ns#type": ["http://www.ancientports.com/ont#Harbour"], "http://www.w3.org/2000/01/rdf-schema#label": ["Mikri Dragonera, Antidragonera, is probably not a port but just a wreckage area!"], "http://www.w3.org/2004/02/skos/core#note": ["Kourkoumelis (1998)"], "http://www.wikidata.org/prop/direct/P17": ["http://www.wikidata.org/entity/Q41"], "http://www.wikidata.org/prop/direct/P1936": ["http://imperium.ahlfeldt.se/places/46292"], "http://www.wikidata.org/prop/direct/P1958": ["https://www.trismegistos.org/place/3356"], "http://www.wikidata.org/prop/direct/P8068": ["https://topostext.org/place/362231SDra"], "begin": ""}, "geometry": {"type": "Point", "coordinates": [23.07553, 36.26709]}}, {"type": "Feature", "id": "http://data.archaeology.link/data/ancientports/2027_1", "name": "Fort at Avlemonas", "dateprops": [], "properties": {"http://purl.org/dc/elements/1.1/created": ["2023"], "http://purl.org/dc/elements/1.1/creator": ["http://data.archaeology.link/data/spphaefen/arthur_de_graauw"], "http://www.opengis.net/ont/geosparql#hasGeometry": ["http://data.archaeology.link/data/ancientports/2027_1_geom"], "http://www.w3.org/1999/02/22-rdf-syntax-ns#type": ["http://www.ancientports.com/ont#Harbour"], "http://www.w3.org/2000/01/rdf-schema#label": ["Fort at Avlemonas"], "http://www.wikidata.org/prop/direct/P17": ["http://www.wikidata.org/entity/Q41"], "http://www.wikidata.org/prop/direct/P1958": ["https://www.trismegistos.org/place/3356"], "http://www.wikidata.org/prop/direct/P8068": ["https://topostext.org/place/362230FAvl"], "begin": ""}, "geometry": {"type": "Point", "coordinates": [23.0807, 36.2253]}}, {"type": "Feature", "id": "http://data.archaeology.link/data/ancientports/2026", "name": "Cave at Diakofti, on the isle of Cythera", "dateprops": ["begin"], "properties": {"http://purl.org/dc/elements/1.1/created": ["2023"], "http://purl.org/dc/elements/1.1/creator": ["http://data.archaeology.link/data/spphaefen/arthur_de_graauw"], "http://www.opengis.net/ont/geosparql#hasGeometry": ["http://data.archaeology.link/data/ancientports/2026_geom"], "http://www.w3.org/1999/02/22-rdf-syntax-ns#type": ["http://www.ancientports.com/ont#Harbour"], "http://www.w3.org/2000/01/rdf-schema#label": ["Cave at Diakofti, on the isle of Cythera"], "http://www.w3.org/2006/time#hasTime": ["http://data.archaeology.link/data/ancientports/2026_foundation"], "http://www.wikidata.org/prop/direct/P17": ["http://www.wikidata.org/entity/Q41"], "http://www.wikidata.org/prop/direct/P1936": ["http://imperium.ahlfeldt.se/places/46294"], "http://www.wikidata.org/prop/direct/P1958": ["https://www.trismegistos.org/place/3356"], "http://www.wikidata.org/prop/direct/P8068": ["https://topostext.org/place/363231CCho"], "begin": "-550"}, "geometry": {"type": "Point", "coordinates": [23.079, 36.2582]}}]}