{"type": "FeatureCollection", "id": "http://imperium.ahlfeldt.se/places/1523", "name": "1523", "features": [{"type": "Feature", "id": "http://data.archaeology.link/data/ancientports/1018", "label": "Salerno", "properties": {"http://purl.org/dc/elements/1.1/created": ["2023"], "http://purl.org/dc/elements/1.1/creator": ["http://data.archaeology.link/data/spphaefen/arthur_de_graauw"], "http://www.opengis.net/ont/geosparql#hasGeometry": ["http://data.archaeology.link/data/ancientports/1018_geom"], "http://www.w3.org/1999/02/22-rdf-syntax-ns#type": ["http://www.ancientports.com/ont#Harbour"], "http://www.w3.org/2000/01/rdf-schema#label": ["Salerno"], "http://www.w3.org/2002/07/owl#sameAs": ["http://www.wikidata.org/entity/Q1083"], "http://www.wikidata.org/prop/direct/P1584": ["http://pleiades.stoa.org/places/433075"], "http://www.wikidata.org/prop/direct/P17": ["Italy West"], "http://www.wikidata.org/prop/direct/P1936": ["http://imperium.ahlfeldt.se/places/1523"], "http://www.wikidata.org/prop/direct/P1958": ["https://www.trismegistos.org/place/14450"], "http://www.wikidata.org/prop/direct/P8068": ["https://topostext.org/place/407148USal"]}, "geometry": {"type": "Point", "coordinates": [14.7611, 40.67095]}}]}