{"type": "FeatureCollection", "id": "https://topostext.org/place/350257PHie", "name": "350257PHie", "features": [{"type": "Feature", "id": "http://data.archaeology.link/data/ancientports/2988", "label": "Ierapetra", "dateprops": [], "properties": {"http://purl.org/dc/elements/1.1/created": ["2023"], "http://purl.org/dc/elements/1.1/creator": ["http://data.archaeology.link/data/spphaefen/arthur_de_graauw"], "http://www.opengis.net/ont/geosparql#hasGeometry": ["http://data.archaeology.link/data/ancientports/2988_geom"], "http://www.w3.org/1999/02/22-rdf-syntax-ns#type": ["http://www.ancientports.com/ont#Harbour"], "http://www.w3.org/2000/01/rdf-schema#label": ["Ierapetra"], "http://www.w3.org/2002/07/owl#sameAs": ["http://www.wikidata.org/entity/Q17322269"], "http://www.w3.org/2004/02/skos/core#note": ["Mourtzas (2017)", "Uggeri (2003)"], "http://www.w3.org/2006/time#hasTime": ["http://data.archaeology.link/data/ancientports/2988_foundation"], "http://www.wikidata.org/prop/direct/P1584": ["http://pleiades.stoa.org/places/589807"], "http://www.wikidata.org/prop/direct/P17": ["http://www.wikidata.org/entity/Q41"], "http://www.wikidata.org/prop/direct/P1936": ["http://imperium.ahlfeldt.se/places/23386"], "http://www.wikidata.org/prop/direct/P1958": ["https://www.trismegistos.org/place/849"], "http://www.wikidata.org/prop/direct/P8068": ["https://topostext.org/place/350257PHie"]}, "geometry": {"type": "Point", "coordinates": [25.7406, 35.00585]}}]}