{"type": "FeatureCollection", "id": "https://topostext.org/place/371245FAsp", "name": "371245FAsp", "features": [{"type": "Feature", "id": "http://data.archaeology.link/data/ancientports/2074_1", "name": "Aspropyrgos, near Ganema, on the isle of Seriphos", "dateprops": ["begin"], "properties": {"http://purl.org/dc/elements/1.1/created": ["2023"], "http://purl.org/dc/elements/1.1/creator": ["http://data.archaeology.link/data/spphaefen/arthur_de_graauw"], "http://www.opengis.net/ont/geosparql#hasGeometry": ["http://data.archaeology.link/data/ancientports/2074_1_geom"], "http://www.w3.org/1999/02/22-rdf-syntax-ns#type": ["http://www.ancientports.com/ont#Harbour"], "http://www.w3.org/2000/01/rdf-schema#label": ["Aspropyrgos, near Ganema, on the isle of Seriphos"], "http://www.w3.org/2006/time#hasTime": ["http://data.archaeology.link/data/ancientports/2074_1_foundation"], "http://www.wikidata.org/prop/direct/P17": ["http://www.wikidata.org/entity/Q41"], "http://www.wikidata.org/prop/direct/P1958": ["https://www.trismegistos.org/place/58687"], "http://www.wikidata.org/prop/direct/P8068": ["https://topostext.org/place/371245FAsp"], "begin": "-400"}, "geometry": {"type": "Point", "coordinates": [24.452, 37.1473]}}]}