{"type": "FeatureCollection", "id": "https://topostext.org/place/313343URap", "name": "313343URap", "features": [{"type": "Feature", "id": "http://data.archaeology.link/data/ancientports/3519", "label": "Tell Rafah, Rafia", "dateprops": [], "properties": {"http://purl.org/dc/elements/1.1/created": ["2023"], "http://purl.org/dc/elements/1.1/creator": ["http://data.archaeology.link/data/spphaefen/arthur_de_graauw"], "http://www.ancientports.com/ont#date_min": ["-330"], "http://www.opengis.net/ont/geosparql#hasGeometry": ["http://data.archaeology.link/data/ancientports/3519_geom"], "http://www.w3.org/1999/02/22-rdf-syntax-ns#type": ["http://www.ancientports.com/ont#Harbour"], "http://www.w3.org/2000/01/rdf-schema#label": ["Tell Rafah, Rafia"], "http://www.w3.org/2002/07/owl#sameAs": ["http://www.wikidata.org/entity/Q172343"], "http://www.w3.org/2004/02/skos/core#note": ["Andreou (2022)"], "http://www.wikidata.org/prop/direct/P1584": ["http://pleiades.stoa.org/places/688015"], "http://www.wikidata.org/prop/direct/P17": ["Gaza"], "http://www.wikidata.org/prop/direct/P1936": ["http://imperium.ahlfeldt.se/places/21693"], "http://www.wikidata.org/prop/direct/P1958": ["https://www.trismegistos.org/place/2044"], "http://www.wikidata.org/prop/direct/P8068": ["https://topostext.org/place/313343URap"]}, "geometry": {"type": "Point", "coordinates": [34.2194, 31.3233]}}]}