{"type": "FeatureCollection", "id": "http://www.wikidata.org/entity/Q1411652", "name": "Q1411652", "features": [{"type": "Feature", "id": "http://data.archaeology.link/data/ancientports/2904", "label": "Kemer", "dateprops": ["http://purl.org/dc/elements/1.1/created"], "properties": {"http://purl.org/dc/elements/1.1/created": ["2023"], "http://purl.org/dc/elements/1.1/creator": ["http://data.archaeology.link/data/spphaefen/arthur_de_graauw"], "http://www.opengis.net/ont/geosparql#hasGeometry": ["http://data.archaeology.link/data/ancientports/2904_geom"], "http://www.w3.org/1999/02/22-rdf-syntax-ns#type": ["http://www.ancientports.com/ont#Harbour"], "http://www.w3.org/2000/01/rdf-schema#label": ["Kemer"], "http://www.w3.org/2002/07/owl#sameAs": ["http://www.wikidata.org/entity/Q1411652"], "http://www.w3.org/2006/time#hasTime": ["http://data.archaeology.link/data/ancientports/2904_foundation"], "http://www.wikidata.org/prop/direct/P1584": ["http://pleiades.stoa.org/places/511354"], "http://www.wikidata.org/prop/direct/P17": ["TR: Marmara S"], "http://www.wikidata.org/prop/direct/P1936": ["http://imperium.ahlfeldt.se/places/21426"], "http://www.wikidata.org/prop/direct/P1958": ["https://www.trismegistos.org/place/1611"], "http://www.wikidata.org/prop/direct/P8068": ["https://topostext.org/place/404271UPar"]}, "geometry": {"type": "Point", "coordinates": [27.0674, 40.4257]}}]}