{"type": "FeatureCollection", "id": "http://www.wikidata.org/entity/Q858775", "name": "Dartford", "features": [{"type": "Feature", "id": "http://data.archaeology.link/data/ancientports/74_1", "name": "Roman villa at Tenters Hill Field, Dartford", "dateprops": ["begin"], "properties": {"http://purl.org/dc/elements/1.1/creator": ["http://data.archaeology.link/data/spphaefen/arthur_de_graauw"], "http://purl.org/dc/terms/partOf": ["http://data.archaeology.link/data/ancientports/bib_deGrauw_2013_GeoDB"], "http://www.opengis.net/ont/geosparql#hasGeometry": ["http://data.archaeology.link/data/ancientports/74_1_geom"], "http://www.w3.org/1999/02/22-rdf-syntax-ns#type": ["http://www.ancientports.com/ont#VillaMaritima"], "http://www.w3.org/2000/01/rdf-schema#label": ["Roman villa at Tenters Hill Field, Dartford"], "http://www.w3.org/2002/07/owl#sameAs": ["http://www.wikidata.org/entity/Q858775"], "http://www.w3.org/2006/time#hasTime": ["http://data.archaeology.link/data/ancientports/74_1_foundation"], "http://www.wikidata.org/prop/direct/P17": ["http://www.wikidata.org/entity/Q145"], "http://www.wikidata.org/prop/direct/P1936": ["http://imperium.ahlfeldt.se/places/25940"], "begin": "5001"}, "geometry": {"type": "Point", "coordinates": [0.2235, 51.4389]}}, {"type": "Feature", "id": "http://data.archaeology.link/data/ancientports/74_2", "name": "Roman villa at Wilmington, Dartford", "dateprops": ["begin"], "properties": {"http://purl.org/dc/elements/1.1/creator": ["http://data.archaeology.link/data/spphaefen/arthur_de_graauw"], "http://purl.org/dc/terms/partOf": ["http://data.archaeology.link/data/ancientports/bib_deGrauw_2013_GeoDB"], "http://www.opengis.net/ont/geosparql#hasGeometry": ["http://data.archaeology.link/data/ancientports/74_2_geom"], "http://www.w3.org/1999/02/22-rdf-syntax-ns#type": ["http://www.ancientports.com/ont#VillaMaritima"], "http://www.w3.org/2000/01/rdf-schema#label": ["Roman villa at Wilmington, Dartford"], "http://www.w3.org/2002/07/owl#sameAs": ["http://www.wikidata.org/entity/Q858775"], "http://www.w3.org/2006/time#hasTime": ["http://data.archaeology.link/data/ancientports/74_2_foundation"], "http://www.wikidata.org/prop/direct/P17": ["http://www.wikidata.org/entity/Q145"], "http://www.wikidata.org/prop/direct/P1936": ["http://imperium.ahlfeldt.se/places/25939"], "begin": "5001"}, "geometry": {"type": "Point", "coordinates": [0.2166, 51.4349]}}, {"type": "Feature", "id": "http://data.archaeology.link/data/ancientports/74_3", "name": "Roman villa at Darenth, near Dartford", "dateprops": ["begin"], "properties": {"http://purl.org/dc/elements/1.1/creator": ["http://data.archaeology.link/data/spphaefen/arthur_de_graauw"], "http://purl.org/dc/terms/isReferencedBy": ["https://historicengland.org.uk/listing/the-list/list-entry/1012965"], "http://purl.org/dc/terms/partOf": ["http://data.archaeology.link/data/ancientports/bib_deGrauw_2013_GeoDB"], "http://www.opengis.net/ont/geosparql#hasGeometry": ["http://data.archaeology.link/data/ancientports/74_3_geom"], "http://www.w3.org/1999/02/22-rdf-syntax-ns#type": ["http://www.ancientports.com/ont#VillaMaritima"], "http://www.w3.org/2000/01/rdf-schema#label": ["Roman villa at Darenth, near Dartford"], "http://www.w3.org/2002/07/owl#sameAs": ["http://www.wikidata.org/entity/Q858775"], "http://www.w3.org/2006/time#hasTime": ["http://data.archaeology.link/data/ancientports/74_3_foundation"], "http://www.wikidata.org/prop/direct/P1584": ["http://pleiades.stoa.org/places/79413"], "http://www.wikidata.org/prop/direct/P17": ["http://www.wikidata.org/entity/Q145"], "http://www.wikidata.org/prop/direct/P1936": ["http://imperium.ahlfeldt.se/places/25630"], "begin": "5001"}, "geometry": {"type": "Point", "coordinates": [0.2466, 51.4133]}}], "numberMatched": 3, "numberReturned": 3}