{"type": "FeatureCollection", "id": "http://pleiades.stoa.org/places/930194", "name": "930194", "features": [{"type": "Feature", "id": "http://data.archaeology.link/data/ancientports/3820", "label": "south of Delvar", "dateprops": [], "properties": {"http://purl.org/dc/elements/1.1/created": ["2023"], "http://purl.org/dc/elements/1.1/creator": ["http://data.archaeology.link/data/spphaefen/arthur_de_graauw"], "http://www.opengis.net/ont/geosparql#hasGeometry": ["http://data.archaeology.link/data/ancientports/3820_geom"], "http://www.w3.org/1999/02/22-rdf-syntax-ns#type": ["http://www.ancientports.com/ont#Harbour"], "http://www.w3.org/2000/01/rdf-schema#label": ["south of Delvar"], "http://www.wikidata.org/prop/direct/P1584": ["http://pleiades.stoa.org/places/930194"], "http://www.wikidata.org/prop/direct/P17": ["Gulf"]}, "geometry": {"type": "Point", "coordinates": [51.03064, 28.55101]}}]}