{"type": "FeatureCollection", "id": "https://topostext.org/place/383260XLit", "name": "383260XLit", "features": [{"type": "Feature", "id": "http://data.archaeology.link/data/ancientports/2257", "label": "Lithiou, an alternative would be Salagona on the SW coast, on the isle of Chios", "dateprops": [], "properties": {"http://purl.org/dc/elements/1.1/created": ["2023"], "http://purl.org/dc/elements/1.1/creator": ["http://data.archaeology.link/data/spphaefen/arthur_de_graauw"], "http://www.opengis.net/ont/geosparql#hasGeometry": ["http://data.archaeology.link/data/ancientports/2257_geom"], "http://www.w3.org/1999/02/22-rdf-syntax-ns#type": ["http://www.ancientports.com/ont#Harbour"], "http://www.w3.org/2000/01/rdf-schema#label": ["Lithiou, an alternative would be Salagona on the SW coast, on the isle of Chios"], "http://www.w3.org/2006/time#hasTime": ["http://data.archaeology.link/data/ancientports/2257_foundation"], "http://www.wikidata.org/prop/direct/P1584": ["http://pleiades.stoa.org/places/550699"], "http://www.wikidata.org/prop/direct/P17": ["GR: Eastern Isl."], "http://www.wikidata.org/prop/direct/P1936": ["http://imperium.ahlfeldt.se/places/29089"], "http://www.wikidata.org/prop/direct/P8068": ["https://topostext.org/place/383260XLit"]}, "geometry": {"type": "Point", "coordinates": [25.9926, 38.343]}}]}