{"type": "FeatureCollection", "id": "http://imperium.ahlfeldt.se/places/41263", "name": "41263", "features": [{"type": "Feature", "id": "http://data.archaeology.link/data/ancientports/858", "label": "Isle of Capraia", "properties": {"http://purl.org/dc/elements/1.1/created": ["2023"], "http://purl.org/dc/elements/1.1/creator": ["http://data.archaeology.link/data/spphaefen/arthur_de_graauw"], "http://www.opengis.net/ont/geosparql#hasGeometry": ["http://data.archaeology.link/data/ancientports/858_geom"], "http://www.w3.org/1999/02/22-rdf-syntax-ns#type": ["http://www.ancientports.com/ont#Harbour"], "http://www.w3.org/2000/01/rdf-schema#label": ["Isle of Capraia"], "http://www.w3.org/2002/07/owl#sameAs": ["http://www.wikidata.org/entity/Q157733"], "http://www.wikidata.org/prop/direct/P1584": ["http://pleiades.stoa.org/places/403193"], "http://www.wikidata.org/prop/direct/P17": ["Italy West"], "http://www.wikidata.org/prop/direct/P1936": ["http://imperium.ahlfeldt.se/places/41263"]}, "geometry": {"type": "Point", "coordinates": [9.8389, 43.05054]}}]}