{"type": "FeatureCollection", "id": "http://www.wikidata.org/entity/Q975080", "name": "Q975080", "features": [{"type": "Feature", "id": "http://data.archaeology.link/data/ancientports/687", "label": "Roman villa on Place d'Armes, Porquerolles village", "properties": {"http://purl.org/dc/elements/1.1/created": ["2023"], "http://purl.org/dc/elements/1.1/creator": ["http://data.archaeology.link/data/spphaefen/arthur_de_graauw"], "http://www.ancientports.com/ont#date_min": ["-100"], "http://www.opengis.net/ont/geosparql#hasGeometry": ["http://data.archaeology.link/data/ancientports/687_geom"], "http://www.w3.org/1999/02/22-rdf-syntax-ns#type": ["http://www.ancientports.com/ont#Harbour"], "http://www.w3.org/2000/01/rdf-schema#label": ["Roman villa on Place d'Armes, Porquerolles village"], "http://www.w3.org/2002/07/owl#sameAs": ["http://www.wikidata.org/entity/Q975080"], "http://www.w3.org/2004/02/skos/core#note": ["Brun (1992)"], "http://www.wikidata.org/prop/direct/P17": ["France South"]}, "geometry": {"type": "Point", "coordinates": [6.203, 43.0004]}}, {"type": "Feature", "id": "http://data.archaeology.link/data/ancientports/688", "label": "Pointe du Lequin, plage Notre Dame (Porquerolles)", "properties": {"http://purl.org/dc/elements/1.1/created": ["2023"], "http://purl.org/dc/elements/1.1/creator": ["http://data.archaeology.link/data/spphaefen/arthur_de_graauw"], "http://www.opengis.net/ont/geosparql#hasGeometry": ["http://data.archaeology.link/data/ancientports/688_geom"], "http://www.w3.org/1999/02/22-rdf-syntax-ns#type": ["http://www.ancientports.com/ont#Harbour"], "http://www.w3.org/2000/01/rdf-schema#label": ["Pointe du Lequin, plage Notre Dame (Porquerolles)"], "http://www.w3.org/2002/07/owl#sameAs": ["http://www.wikidata.org/entity/Q975080"], "http://www.wikidata.org/prop/direct/P17": ["France South"]}, "geometry": {"type": "Point", "coordinates": [6.2288, 43.0105]}}, {"type": "Feature", "id": "http://data.archaeology.link/data/ancientports/689", "label": "Pointe de La Galere (Porquerolles)", "properties": {"http://purl.org/dc/elements/1.1/created": ["2023"], "http://purl.org/dc/elements/1.1/creator": ["http://data.archaeology.link/data/spphaefen/arthur_de_graauw"], "http://www.ancientports.com/ont#date_min": ["-100"], "http://www.opengis.net/ont/geosparql#hasGeometry": ["http://data.archaeology.link/data/ancientports/689_geom"], "http://www.w3.org/1999/02/22-rdf-syntax-ns#type": ["http://www.ancientports.com/ont#Harbour"], "http://www.w3.org/2000/01/rdf-schema#label": ["Pointe de La Galere (Porquerolles)"], "http://www.w3.org/2002/07/owl#sameAs": ["http://www.wikidata.org/entity/Q975080"], "http://www.w3.org/2004/02/skos/core#note": ["Brun (1992)"], "http://www.wikidata.org/prop/direct/P1584": ["http://pleiades.stoa.org/places/157857"], "http://www.wikidata.org/prop/direct/P17": ["France South"], "http://www.wikidata.org/prop/direct/P1936": ["http://imperium.ahlfeldt.se/places/17390"]}, "geometry": {"type": "Point", "coordinates": [6.25155, 43.00177]}}, {"type": "Feature", "id": "http://data.archaeology.link/data/ancientports/690", "label": "Anse du Breganconnet (Porquerolles)", "properties": {"http://purl.org/dc/elements/1.1/created": ["2023"], "http://purl.org/dc/elements/1.1/creator": ["http://data.archaeology.link/data/spphaefen/arthur_de_graauw"], "http://www.opengis.net/ont/geosparql#hasGeometry": ["http://data.archaeology.link/data/ancientports/690_geom"], "http://www.w3.org/1999/02/22-rdf-syntax-ns#type": ["http://www.ancientports.com/ont#Harbour"], "http://www.w3.org/2000/01/rdf-schema#label": ["Anse du Breganconnet (Porquerolles)"], "http://www.w3.org/2002/07/owl#sameAs": ["http://www.wikidata.org/entity/Q975080"], "http://www.wikidata.org/prop/direct/P17": ["France South"]}, "geometry": {"type": "Point", "coordinates": [6.18107, 42.9939]}}]}