{"type": "FeatureCollection", "id": "http://imperium.ahlfeldt.se/places/21218", "name": "21218", "features": [{"type": "Feature", "id": "http://data.archaeology.link/data/ancientports/2882", "name": "Kapanca", "dateprops": [], "properties": {"http://purl.org/dc/elements/1.1/created": ["2023"], "http://purl.org/dc/elements/1.1/creator": ["http://data.archaeology.link/data/spphaefen/arthur_de_graauw"], "http://www.opengis.net/ont/geosparql#hasGeometry": ["http://data.archaeology.link/data/ancientports/2882_geom"], "http://www.w3.org/1999/02/22-rdf-syntax-ns#type": ["http://www.ancientports.com/ont#Harbour"], "http://www.w3.org/2000/01/rdf-schema#label": ["Kapanca"], "http://www.w3.org/2002/07/owl#sameAs": ["http://www.wikidata.org/entity/Q5551944"], "http://www.w3.org/2004/02/skos/core#note": ["Sahin (2011)"], "http://www.wikidata.org/prop/direct/P1584": ["http://pleiades.stoa.org/places/511267"], "http://www.wikidata.org/prop/direct/P17": ["http://www.wikidata.org/entity/Q43"], "http://www.wikidata.org/prop/direct/P1936": ["http://imperium.ahlfeldt.se/places/21218"], "http://www.wikidata.org/prop/direct/P1958": ["https://www.trismegistos.org/place/16317"], "begin": ""}, "geometry": {"type": "Point", "coordinates": [28.72451, 40.37903]}}]}