{"type": "FeatureCollection", "id": "http://imperium.ahlfeldt.se/places/32503", "name": "32503", "features": [{"type": "Feature", "id": "http://data.archaeology.link/data/ancientports/4124", "label": "Bir Flaguess 2.5 km SW of the TRAPSA oil terminal", "dateprops": ["http://purl.org/dc/elements/1.1/created"], "properties": {"http://purl.org/dc/elements/1.1/created": ["2023"], "http://purl.org/dc/elements/1.1/creator": ["http://data.archaeology.link/data/spphaefen/arthur_de_graauw"], "http://www.opengis.net/ont/geosparql#hasGeometry": ["http://data.archaeology.link/data/ancientports/4124_geom"], "http://www.w3.org/1999/02/22-rdf-syntax-ns#type": ["http://www.ancientports.com/ont#Harbour"], "http://www.w3.org/2000/01/rdf-schema#label": ["Bir Flaguess 2.5 km SW of the TRAPSA oil terminal"], "http://www.w3.org/2006/time#hasTime": ["http://data.archaeology.link/data/ancientports/4124_foundation"], "http://www.wikidata.org/prop/direct/P1584": ["http://pleiades.stoa.org/places/324675"], "http://www.wikidata.org/prop/direct/P17": ["http://www.wikidata.org/entity/Q948"], "http://www.wikidata.org/prop/direct/P1936": ["http://imperium.ahlfeldt.se/places/32503"]}, "geometry": {"type": "Point", "coordinates": [10.1196, 34.31017]}}]}