{"type": "FeatureCollection", "id": "http://www.wikidata.org/entity/Q1641335", "name": "Q1641335", "features": [{"type": "Feature", "id": "http://data.archaeology.link/data/ancientports/1263_1", "label": "Hypogea of Trinitapoli, Madonna di Loreto church", "dateprops": ["http://purl.org/dc/elements/1.1/created", "http://www.ancientports.com/ont#date_min"], "properties": {"http://purl.org/dc/elements/1.1/created": ["2023"], "http://purl.org/dc/elements/1.1/creator": ["http://data.archaeology.link/data/spphaefen/arthur_de_graauw"], "http://www.ancientports.com/ont#date_min": ["-1500"], "http://www.opengis.net/ont/geosparql#hasGeometry": ["http://data.archaeology.link/data/ancientports/1263_1_geom"], "http://www.w3.org/1999/02/22-rdf-syntax-ns#type": ["http://www.ancientports.com/ont#Harbour"], "http://www.w3.org/2000/01/rdf-schema#label": ["Hypogea of Trinitapoli, Madonna di Loreto church"], "http://www.w3.org/2002/07/owl#sameAs": ["http://www.wikidata.org/entity/Q1641335"], "http://www.wikidata.org/prop/direct/P17": ["Italy Adriatic"]}, "geometry": {"type": "Point", "coordinates": [16.0811, 41.3592]}}]}