{"type": "FeatureCollection", "id": "http://pleiades.stoa.org/places/423025", "name": "423025", "features": [{"type": "Feature", "id": "http://data.archaeology.link/data/ancientports/931", "label": "Tor di Nora and Ripetta, on left bank of R Tiber", "dateprops": [], "properties": {"http://purl.org/dc/elements/1.1/created": ["2023"], "http://purl.org/dc/elements/1.1/creator": ["http://data.archaeology.link/data/spphaefen/arthur_de_graauw"], "http://www.opengis.net/ont/geosparql#hasGeometry": ["http://data.archaeology.link/data/ancientports/931_geom"], "http://www.w3.org/1999/02/22-rdf-syntax-ns#type": ["http://www.ancientports.com/ont#Shipyard", "http://www.ancientports.com/ont#Quay"], "http://www.w3.org/2000/01/rdf-schema#label": ["Tor di Nora and Ripetta, on left bank of R Tiber"], "http://www.w3.org/2004/02/skos/core#note": ["Keay (2012)"], "http://www.wikidata.org/prop/direct/P1584": ["http://pleiades.stoa.org/places/423025"], "http://www.wikidata.org/prop/direct/P17": ["http://www.wikidata.org/entity/Q38"], "http://www.wikidata.org/prop/direct/P1936": ["http://imperium.ahlfeldt.se/places/1438"], "http://www.wikidata.org/prop/direct/P1958": ["https://www.trismegistos.org/place/2058"], "http://www.wikidata.org/prop/direct/P8068": ["https://topostext.org/place/419125PRom"]}, "geometry": {"type": "Point", "coordinates": [12.46969, 41.90152]}}]}