{"type": "FeatureCollection", "id": "http://imperium.ahlfeldt.se/places/31470", "name": "31470", "features": [{"type": "Feature", "id": "http://data.archaeology.link/data/ancientports/2418", "label": "near Galatasaray university", "dateprops": [], "properties": {"http://purl.org/dc/elements/1.1/created": ["2023"], "http://purl.org/dc/elements/1.1/creator": ["http://data.archaeology.link/data/spphaefen/arthur_de_graauw"], "http://www.opengis.net/ont/geosparql#hasGeometry": ["http://data.archaeology.link/data/ancientports/2418_geom"], "http://www.w3.org/1999/02/22-rdf-syntax-ns#type": ["http://www.ancientports.com/ont#Harbour"], "http://www.w3.org/2000/01/rdf-schema#label": ["near Galatasaray university"], "http://www.w3.org/2004/02/skos/core#note": ["K\u00fclzer (2011)"], "http://www.wikidata.org/prop/direct/P1584": ["http://pleiades.stoa.org/places/521041"], "http://www.wikidata.org/prop/direct/P17": ["TR: Bosph N"], "http://www.wikidata.org/prop/direct/P1936": ["http://imperium.ahlfeldt.se/places/31470"]}, "geometry": {"type": "Point", "coordinates": [29.0203, 41.0446]}}]}