{"type": "FeatureCollection", "id": "https://www.trismegistos.org/place/14928", "name": "14928", "features": [{"type": "Feature", "id": "http://data.archaeology.link/data/ancientports/153", "label": "Parton Roman fort, near Moresby", "properties": {"http://purl.org/dc/elements/1.1/created": ["2023"], "http://purl.org/dc/elements/1.1/creator": ["http://data.archaeology.link/data/spphaefen/arthur_de_graauw"], "http://purl.org/dc/terms/isReferencedBy": ["https://historicengland.org.uk/listing/the-list/list-entry/1007179"], "http://www.ancientports.com/ont#date_min": ["1001"], "http://www.opengis.net/ont/geosparql#hasGeometry": ["http://data.archaeology.link/data/ancientports/153_geom"], "http://www.w3.org/1999/02/22-rdf-syntax-ns#type": ["http://www.ancientports.com/ont#Harbour"], "http://www.w3.org/2000/01/rdf-schema#label": ["Parton Roman fort, near Moresby"], "http://www.w3.org/2002/07/owl#sameAs": ["http://www.wikidata.org/entity/Q2195053"], "http://www.w3.org/2004/02/skos/core#note": ["https://historicengland.org.uk/listing/the-list/list-entry/1007179"], "http://www.wikidata.org/prop/direct/P1584": ["http://pleiades.stoa.org/places/89189"], "http://www.wikidata.org/prop/direct/P17": ["http://www.wikidata.org/entity/Q145"], "http://www.wikidata.org/prop/direct/P1936": ["http://imperium.ahlfeldt.se/places/23706"], "http://www.wikidata.org/prop/direct/P1958": ["https://www.trismegistos.org/place/14928"]}, "geometry": {"type": "Point", "coordinates": [-3.57565, 54.57405]}}]}