{"type": "FeatureCollection", "id": "http://imperium.ahlfeldt.se/places/35378", "name": "35378", "features": [{"type": "Feature", "id": "http://data.archaeology.link/data/ancientports/1194", "label": "Roman villa at Settefrati, near Mazzaforno", "dateprops": [], "properties": {"http://purl.org/dc/elements/1.1/created": ["2023"], "http://purl.org/dc/elements/1.1/creator": ["http://data.archaeology.link/data/spphaefen/arthur_de_graauw"], "http://www.opengis.net/ont/geosparql#hasGeometry": ["http://data.archaeology.link/data/ancientports/1194_geom"], "http://www.w3.org/1999/02/22-rdf-syntax-ns#type": ["http://www.ancientports.com/ont#VillaMaritima"], "http://www.w3.org/2000/01/rdf-schema#label": ["Roman villa at Settefrati, near Mazzaforno"], "http://www.w3.org/2006/time#hasTime": ["http://data.archaeology.link/data/ancientports/1194_foundation"], "http://www.wikidata.org/prop/direct/P1584": ["http://pleiades.stoa.org/places/462490"], "http://www.wikidata.org/prop/direct/P17": ["Italy Sicily"], "http://www.wikidata.org/prop/direct/P1936": ["http://imperium.ahlfeldt.se/places/35378"]}, "geometry": {"type": "Point", "coordinates": [13.964, 38.0319]}}]}