{"type": "FeatureCollection", "id": "http://imperium.ahlfeldt.se/places/23631", "name": "23631", "features": [{"type": "Feature", "id": "http://data.archaeology.link/data/ancientports/4100", "label": "Naoura, on the South bank of R Bahar Alaoune", "dateprops": [], "properties": {"http://purl.org/dc/elements/1.1/created": ["2023"], "http://purl.org/dc/elements/1.1/creator": ["http://data.archaeology.link/data/spphaefen/arthur_de_graauw"], "http://www.opengis.net/ont/geosparql#hasGeometry": ["http://data.archaeology.link/data/ancientports/4100_geom"], "http://www.w3.org/1999/02/22-rdf-syntax-ns#type": ["http://www.ancientports.com/ont#Harbour"], "http://www.w3.org/2000/01/rdf-schema#label": ["Naoura, on the South bank of R Bahar Alaoune"], "http://www.w3.org/2004/02/skos/core#note": ["Drine (2014)"], "http://www.w3.org/2006/time#hasTime": ["http://data.archaeology.link/data/ancientports/4100_foundation"], "http://www.wikidata.org/prop/direct/P1584": ["http://pleiades.stoa.org/places/344462"], "http://www.wikidata.org/prop/direct/P17": ["http://www.wikidata.org/entity/Q948"], "http://www.wikidata.org/prop/direct/P1936": ["http://imperium.ahlfeldt.se/places/23631"]}, "geometry": {"type": "Point", "coordinates": [11.1083, 33.35642]}}]}