{"type": "FeatureCollection", "id": "http://pleiades.stoa.org/places/481944", "name": "481944", "features": [{"type": "Feature", "id": "http://data.archaeology.link/data/ancientports/1529", "name": "Porto Palermo", "dateprops": ["begin"], "properties": {"http://purl.org/dc/elements/1.1/creator": ["http://data.archaeology.link/data/spphaefen/arthur_de_graauw"], "http://purl.org/dc/terms/partOf": ["http://data.archaeology.link/data/ancientports/bib_deGrauw_2013_GeoDB"], "http://www.opengis.net/ont/geosparql#hasGeometry": ["http://data.archaeology.link/data/ancientports/1529_geom"], "http://www.w3.org/1999/02/22-rdf-syntax-ns#type": ["http://www.ancientports.com/ont#Harbour"], "http://www.w3.org/2000/01/rdf-schema#label": ["Porto Palermo"], "http://www.w3.org/2002/07/owl#sameAs": ["http://www.wikidata.org/entity/Q7131531"], "http://www.w3.org/2006/time#hasTime": ["http://data.archaeology.link/data/ancientports/1529_foundation"], "http://www.wikidata.org/prop/direct/P1584": ["http://pleiades.stoa.org/places/481944"], "http://www.wikidata.org/prop/direct/P17": ["http://www.wikidata.org/entity/Q222"], "http://www.wikidata.org/prop/direct/P1958": ["https://www.trismegistos.org/place/61115"], "http://www.wikidata.org/prop/direct/P8068": ["https://topostext.org/place/401198HPan"], "begin": "4001"}, "geometry": {"type": "Point", "coordinates": [19.779, 40.0712]}}], "numberMatched": 1, "numberReturned": 1, "bbox": [19.779, 40.0712, 19.779, 40.0712], "crs": "http://www.opengis.net/def/crs/OGC/1.3/CRS84"}