{"type": "FeatureCollection", "id": "http://www.wikidata.org/entity/Q2021739", "name": "Ampelakia", "features": [{"type": "Feature", "id": "http://data.archaeology.link/data/ancientports/1626", "name": "", "dateprops": ["begin"], "properties": {"http://purl.org/dc/elements/1.1/creator": ["http://data.archaeology.link/data/spphaefen/arthur_de_graauw"], "http://purl.org/dc/terms/isReferencedBy": ["https://www.culture.gov.gr/el/Information/SitePages/view.aspx?nID=3731"], "http://purl.org/dc/terms/partOf": ["http://data.archaeology.link/data/ancientports/bib_deGrauw_2013_GeoDB"], "http://www.opengis.net/ont/geosparql#hasGeometry": ["http://data.archaeology.link/data/ancientports/1626_geom"], "http://www.w3.org/1999/02/22-rdf-syntax-ns#type": ["http://www.ancientports.com/ont#Quay"], "http://www.w3.org/2000/01/rdf-schema#label": ["Bay of Ambelaki, on the isle of Salamis"], "http://www.w3.org/2002/07/owl#sameAs": ["http://www.wikidata.org/entity/Q2021739"], "http://www.w3.org/2004/02/skos/core#note": ["Lolos (1989)"], "http://www.w3.org/2006/time#hasTime": ["http://data.archaeology.link/data/ancientports/1626_foundation"], "http://www.wikidata.org/prop/direct/P1584": ["http://pleiades.stoa.org/places/580100"], "http://www.wikidata.org/prop/direct/P17": ["http://www.wikidata.org/entity/Q41"], "http://www.wikidata.org/prop/direct/P1936": ["http://imperium.ahlfeldt.se/places/46604"], "http://www.wikidata.org/prop/direct/P1958": ["https://www.trismegistos.org/place/37803"], "http://www.wikidata.org/prop/direct/P8068": ["https://topostext.org/place/379235HSal"], "begin": "-550"}, "geometry": {"type": "Point", "coordinates": [23.5387, 37.95016]}}], "numberMatched": 1, "numberReturned": 1, "bbox": [23.5387, 37.95016, 23.5387, 37.95016], "crs": "http://www.opengis.net/def/crs/EPSG/0/4326"}