{"type": "FeatureCollection", "id": "http://pleiades.stoa.org/places/462184", "name": "462184", "features": [{"type": "Feature", "id": "http://data.archaeology.link/data/ancientports/1159", "label": "Rocca San Nicola", "dateprops": [], "properties": {"http://purl.org/dc/elements/1.1/created": ["2023"], "http://purl.org/dc/elements/1.1/creator": ["http://data.archaeology.link/data/spphaefen/arthur_de_graauw"], "http://www.ancientports.com/ont#date_min": ["-30"], "http://www.opengis.net/ont/geosparql#hasGeometry": ["http://data.archaeology.link/data/ancientports/1159_geom"], "http://www.w3.org/1999/02/22-rdf-syntax-ns#type": ["http://www.ancientports.com/ont#Harbour"], "http://www.w3.org/2000/01/rdf-schema#label": ["Rocca San Nicola"], "http://www.wikidata.org/prop/direct/P1584": ["http://pleiades.stoa.org/places/462184"], "http://www.wikidata.org/prop/direct/P17": ["Italy Sicily"], "http://www.wikidata.org/prop/direct/P1936": ["http://imperium.ahlfeldt.se/places/36390"]}, "geometry": {"type": "Point", "coordinates": [13.85609, 37.11483]}}]}