{"type": "FeatureCollection", "id": "http://www.wikidata.org/entity/Q1789784", "name": "Q1789784", "features": [{"type": "Feature", "id": "http://data.archaeology.link/data/ancientports/1856", "label": "near Agio Theodori", "dateprops": [], "properties": {"http://purl.org/dc/elements/1.1/created": ["2023"], "http://purl.org/dc/elements/1.1/creator": ["http://data.archaeology.link/data/spphaefen/arthur_de_graauw"], "http://www.opengis.net/ont/geosparql#hasGeometry": ["http://data.archaeology.link/data/ancientports/1856_geom"], "http://www.w3.org/1999/02/22-rdf-syntax-ns#type": ["http://www.ancientports.com/ont#Harbour"], "http://www.w3.org/2000/01/rdf-schema#label": ["near Agio Theodori"], "http://www.w3.org/2002/07/owl#sameAs": ["http://www.wikidata.org/entity/Q1789784"], "http://www.w3.org/2006/time#hasTime": ["http://data.archaeology.link/data/ancientports/1856_foundation"], "http://www.wikidata.org/prop/direct/P1584": ["http://pleiades.stoa.org/places/570386"], "http://www.wikidata.org/prop/direct/P17": ["GR: Pelop"], "http://www.wikidata.org/prop/direct/P1936": ["http://imperium.ahlfeldt.se/places/28522"], "http://www.wikidata.org/prop/direct/P1958": ["https://www.trismegistos.org/place/54411"], "http://www.wikidata.org/prop/direct/P8068": ["https://topostext.org/place/380231UKro"]}, "geometry": {"type": "Point", "coordinates": [23.14, 37.92]}}]}