{"type": "FeatureCollection", "id": "http://pleiades.stoa.org/places/452407", "name": "452407", "features": [{"type": "Feature", "id": "http://data.archaeology.link/data/ancientports/1095", "name": "Piano San Pietro ", "dateprops": ["begin"], "properties": {"http://purl.org/dc/elements/1.1/creator": ["http://data.archaeology.link/data/spphaefen/arthur_de_graauw"], "http://purl.org/dc/terms/partOf": ["http://data.archaeology.link/data/ancientports/bib_deGrauw_2013_GeoDB"], "http://www.opengis.net/ont/geosparql#hasGeometry": ["http://data.archaeology.link/data/ancientports/1095_geom"], "http://www.w3.org/1999/02/22-rdf-syntax-ns#type": ["http://www.ancientports.com/ont#Harbour"], "http://www.w3.org/2000/01/rdf-schema#label": ["Piano San Pietro "], "http://www.w3.org/2006/time#hasTime": ["http://data.archaeology.link/data/ancientports/1095_foundation"], "http://www.wikidata.org/prop/direct/P1584": ["http://pleiades.stoa.org/places/452407"], "http://www.wikidata.org/prop/direct/P17": ["http://www.wikidata.org/entity/Q38"], "http://www.wikidata.org/prop/direct/P1936": ["http://imperium.ahlfeldt.se/places/30473"], "begin": "-330"}, "geometry": {"type": "Point", "coordinates": [16.64197, 40.15955]}}], "numberMatched": 1, "numberReturned": 1, "bbox": [16.64197, 40.15955, 16.64197, 40.15955], "crs": "http://www.opengis.net/def/crs/OGC/1.3/CRS84"}