{"type": "FeatureCollection", "id": "http://pleiades.stoa.org/places/844918", "name": "844918", "features": [{"type": "Feature", "id": "http://data.archaeology.link/data/ancientports/2796", "label": "Cakraz, near Senyurt", "dateprops": [], "properties": {"http://purl.org/dc/elements/1.1/created": ["2023"], "http://purl.org/dc/elements/1.1/creator": ["http://data.archaeology.link/data/spphaefen/arthur_de_graauw"], "http://www.opengis.net/ont/geosparql#hasGeometry": ["http://data.archaeology.link/data/ancientports/2796_geom"], "http://www.w3.org/1999/02/22-rdf-syntax-ns#type": ["http://www.ancientports.com/ont#Harbour"], "http://www.w3.org/2000/01/rdf-schema#label": ["Cakraz, near Senyurt"], "http://www.w3.org/2006/time#hasTime": ["http://data.archaeology.link/data/ancientports/2796_foundation"], "http://www.wikidata.org/prop/direct/P1584": ["http://pleiades.stoa.org/places/844918"], "http://www.wikidata.org/prop/direct/P17": ["http://www.wikidata.org/entity/Q43"], "http://www.wikidata.org/prop/direct/P1936": ["http://imperium.ahlfeldt.se/places/27480"]}, "geometry": {"type": "Point", "coordinates": [32.48155, 41.78425]}}]}