{"type": "FeatureCollection", "id": "http://www.wikidata.org/entity/Q1000", "name": "Gabon", "features": [{"type": "Feature", "id": "http://data.archaeology.link/data/ancientports/4343", "name": "This bay is where Hanno decided to go back home. This bay was located at 3 sailing days south of a high mountain with fire called Theon Ochema which might be Mount Cameroon. An island with gorillas was located on a lake which was located on an island in this bay: the isle of Mbani\u00e9 is now a tiny island which might once have been part of Corisco island and its surrounding lagoon, itself located in Corisco bay (Gabon) around 200 nautical miles south of Mount Cameroon. This similarity is obviously hypothetical, but it is plausible ...\nNote that in this area trade winds and currents are North oriented, and therefore  quite adverse for navigating further South.", "dateprops": [], "properties": {"http://purl.org/dc/elements/1.1/created": ["2023"], "http://purl.org/dc/elements/1.1/creator": ["http://data.archaeology.link/data/spphaefen/arthur_de_graauw"], "http://purl.org/dc/terms/isReferencedBy": ["http://www.livius.org/articles/person/hanno-1-the-navigator/hanno-1-the-navigator-2/"], "http://www.opengis.net/ont/geosparql#hasGeometry": ["http://data.archaeology.link/data/ancientports/4343_geom"], "http://www.w3.org/1999/02/22-rdf-syntax-ns#type": ["http://www.ancientports.com/ont#Harbour"], "http://www.w3.org/2000/01/rdf-schema#label": ["This bay is where Hanno decided to go back home. This bay was located at 3 sailing days south of a high mountain with fire called Theon Ochema which might be Mount Cameroon. An island with gorillas was located on a lake which was located on an island in this bay: the isle of Mbani\u00e9 is now a tiny island which might once have been part of Corisco island and its surrounding lagoon, itself located in Corisco bay (Gabon) around 200 nautical miles south of Mount Cameroon. This similarity is obviously hypothetical, but it is plausible ...\nNote that in this area trade winds and currents are North oriented, and therefore  quite adverse for navigating further South."], "http://www.w3.org/2004/02/skos/core#note": ["Bucciantini (2012)"], "http://www.wikidata.org/prop/direct/P17": ["http://www.wikidata.org/entity/Q1000"], "http://www.wikidata.org/prop/direct/P1958": ["https://www.trismegistos.org/place/11223"], "begin": ""}, "geometry": {"type": "Point", "coordinates": [9.379, 0.81]}}]}