{"type": "FeatureCollection", "id": "http://pleiades.stoa.org/places/580100", "name": "580100", "features": [{"type": "Feature", "id": "http://data.archaeology.link/data/ancientports/1626", "label": "Bay of Ambelaki, on the isle of Salamis", "properties": {"http://purl.org/dc/elements/1.1/created": ["2023"], "http://purl.org/dc/elements/1.1/creator": ["http://data.archaeology.link/data/spphaefen/arthur_de_graauw"], "http://purl.org/dc/terms/isReferencedBy": ["https://www.culture.gov.gr/el/Information/SitePages/view.aspx?nID=3731"], "http://www.ancientports.com/ont#date_min": ["-550"], "http://www.opengis.net/ont/geosparql#hasGeometry": ["http://data.archaeology.link/data/ancientports/1626_geom"], "http://www.w3.org/1999/02/22-rdf-syntax-ns#type": ["http://www.ancientports.com/ont#Quay"], "http://www.w3.org/2000/01/rdf-schema#label": ["Bay of Ambelaki, on the isle of Salamis"], "http://www.w3.org/2002/07/owl#sameAs": ["http://www.wikidata.org/entity/Q2021739"], "http://www.w3.org/2004/02/skos/core#note": ["Lolos (1989)", "https://www.culture.gov.gr/el/Information/SitePages/view.aspx?nID=3731"], "http://www.wikidata.org/prop/direct/P1584": ["http://pleiades.stoa.org/places/580100"], "http://www.wikidata.org/prop/direct/P17": ["GR: Attica +"], "http://www.wikidata.org/prop/direct/P1936": ["http://imperium.ahlfeldt.se/places/46604"], "http://www.wikidata.org/prop/direct/P1958": ["https://www.trismegistos.org/place/37803"], "http://www.wikidata.org/prop/direct/P8068": ["https://topostext.org/place/379235HSal"]}, "geometry": {"type": "Point", "coordinates": [23.5387, 37.95016]}}]}