{"type": "FeatureCollection", "id": "https://www.trismegistos.org/place/16489", "name": "16489", "features": [{"type": "Feature", "id": "http://data.archaeology.link/data/ancientports/3340", "label": "Kale Burnu, Gazipasa Limani, on R Inceagri, Sarisu", "properties": {"http://purl.org/dc/elements/1.1/created": ["2023"], "http://purl.org/dc/elements/1.1/creator": ["http://data.archaeology.link/data/spphaefen/arthur_de_graauw"], "http://www.ancientports.com/ont#date_min": ["-750"], "http://www.opengis.net/ont/geosparql#hasGeometry": ["http://data.archaeology.link/data/ancientports/3340_geom"], "http://www.w3.org/1999/02/22-rdf-syntax-ns#type": ["http://www.ancientports.com/ont#Harbour"], "http://www.w3.org/2000/01/rdf-schema#label": ["Kale Burnu, Gazipasa Limani, on R Inceagri, Sarisu"], "http://www.w3.org/2002/07/owl#sameAs": ["http://www.wikidata.org/entity/Q1424724"], "http://www.wikidata.org/prop/direct/P1584": ["http://pleiades.stoa.org/places/648772"], "http://www.wikidata.org/prop/direct/P17": ["TR: South"], "http://www.wikidata.org/prop/direct/P1958": ["https://www.trismegistos.org/place/16489"]}, "geometry": {"type": "Point", "coordinates": [32.2828, 36.2586]}}]}