{"type": "FeatureCollection", "id": "http://www.wikidata.org/entity/Q20667612", "name": "Carussa", "features": [{"type": "Feature", "id": "http://data.archaeology.link/data/ancientports/2771", "name": "K\u00f6sk H\u00f6y\u00fck, near Gerze", "dateprops": ["begin"], "properties": {"http://purl.org/dc/elements/1.1/creator": ["http://data.archaeology.link/data/spphaefen/arthur_de_graauw"], "http://purl.org/dc/terms/partOf": ["http://data.archaeology.link/data/ancientports/bib_deGrauw_2013_GeoDB"], "http://www.opengis.net/ont/geosparql#hasGeometry": ["http://data.archaeology.link/data/ancientports/2771_geom"], "http://www.w3.org/1999/02/22-rdf-syntax-ns#type": ["http://www.ancientports.com/ont#Harbour"], "http://www.w3.org/2000/01/rdf-schema#label": ["K\u00f6sk H\u00f6y\u00fck, near Gerze"], "http://www.w3.org/2002/07/owl#sameAs": ["http://www.wikidata.org/entity/Q20667612"], "http://www.w3.org/2004/02/skos/core#note": ["Dan (2009)", "Doonan (2011)"], "http://www.w3.org/2006/time#hasTime": ["http://data.archaeology.link/data/ancientports/2771_foundation"], "http://www.wikidata.org/prop/direct/P1584": ["http://pleiades.stoa.org/places/857181"], "http://www.wikidata.org/prop/direct/P17": ["http://www.wikidata.org/entity/Q43"], "http://www.wikidata.org/prop/direct/P1936": ["http://imperium.ahlfeldt.se/places/29562"], "begin": "-1000"}, "geometry": {"type": "Point", "coordinates": [35.20145, 41.79204]}}], "numberMatched": 1, "numberReturned": 1, "bbox": [35.20145, 41.79204, 35.20145, 41.79204], "crs": "http://www.opengis.net/def/crs/EPSG/0/4326"}