{"type": "FeatureCollection", "id": "http://www.wikidata.org/entity/Q3398568", "name": "Q3398568", "features": [{"type": "Feature", "id": "http://data.archaeology.link/data/ancientports/3433", "label": "Tell Kazel, on R Nahr el-Abrash", "dateprops": [], "properties": {"http://purl.org/dc/elements/1.1/created": ["2023"], "http://purl.org/dc/elements/1.1/creator": ["http://data.archaeology.link/data/spphaefen/arthur_de_graauw"], "http://purl.org/dc/terms/isReferencedBy": ["https://en.wikipedia.org/wiki/Amarna_letters"], "http://www.ancientports.com/ont#date_min": ["-1500"], "http://www.opengis.net/ont/geosparql#hasGeometry": ["http://data.archaeology.link/data/ancientports/3433_geom"], "http://www.w3.org/1999/02/22-rdf-syntax-ns#type": ["http://www.ancientports.com/ont#Harbour"], "http://www.w3.org/2000/01/rdf-schema#label": ["Tell Kazel, on R Nahr el-Abrash"], "http://www.w3.org/2002/07/owl#sameAs": ["http://www.wikidata.org/entity/Q3398568"], "http://www.w3.org/2004/02/skos/core#note": ["Pfaelzner (2012)"], "http://www.wikidata.org/prop/direct/P1584": ["http://pleiades.stoa.org/places/668372"], "http://www.wikidata.org/prop/direct/P17": ["http://www.wikidata.org/entity/Q858"], "http://www.wikidata.org/prop/direct/P1936": ["http://imperium.ahlfeldt.se/places/33235"], "http://www.wikidata.org/prop/direct/P1958": ["https://www.trismegistos.org/place/37581"]}, "geometry": {"type": "Point", "coordinates": [35.986, 34.7085]}}]}