{"type": "FeatureCollection", "id": "http://pleiades.stoa.org/places/857242", "name": "857242", "features": [{"type": "Feature", "id": "http://data.archaeology.link/data/ancientports/2764", "name": "Liman Gol, G\u00f6l\u00fc", "dateprops": ["begin"], "properties": {"http://purl.org/dc/elements/1.1/creator": ["http://data.archaeology.link/data/spphaefen/arthur_de_graauw"], "http://purl.org/dc/terms/partOf": ["http://data.archaeology.link/data/ancientports/bib_deGrauw_2013_GeoDB"], "http://www.opengis.net/ont/geosparql#hasGeometry": ["http://data.archaeology.link/data/ancientports/2764_geom"], "http://www.w3.org/1999/02/22-rdf-syntax-ns#type": ["http://www.ancientports.com/ont#Harbour"], "http://www.w3.org/2000/01/rdf-schema#label": ["Liman Gol, G\u00f6l\u00fc"], "http://www.w3.org/2002/07/owl#sameAs": ["http://www.wikidata.org/entity/Q65047435"], "http://www.w3.org/2004/02/skos/core#note": ["Dan (2009)"], "http://www.w3.org/2006/time#hasTime": ["http://data.archaeology.link/data/ancientports/2764_foundation"], "http://www.wikidata.org/prop/direct/P1584": ["http://pleiades.stoa.org/places/857242"], "http://www.wikidata.org/prop/direct/P17": ["http://www.wikidata.org/entity/Q43"], "http://www.wikidata.org/prop/direct/P1936": ["http://imperium.ahlfeldt.se/places/23449"], "http://www.wikidata.org/prop/direct/P1958": ["https://www.trismegistos.org/place/41387"], "begin": "-30"}, "geometry": {"type": "Point", "coordinates": [36.018, 41.697]}}], "numberMatched": 1, "numberReturned": 1, "bbox": [36.018, 41.697, 36.018, 41.697], "crs": "http://www.opengis.net/def/crs/EPSG/0/4326"}