{"type": "FeatureCollection", "id": "http://pleiades.stoa.org/places/501649", "name": "501649", "features": [{"type": "Feature", "id": "http://data.archaeology.link/data/ancientports/1854", "label": "Loutra Traianopolis", "dateprops": ["http://purl.org/dc/elements/1.1/created"], "properties": {"http://purl.org/dc/elements/1.1/created": ["2023"], "http://purl.org/dc/elements/1.1/creator": ["http://data.archaeology.link/data/spphaefen/arthur_de_graauw"], "http://www.opengis.net/ont/geosparql#hasGeometry": ["http://data.archaeology.link/data/ancientports/1854_geom"], "http://www.w3.org/1999/02/22-rdf-syntax-ns#type": ["http://www.ancientports.com/ont#Harbour"], "http://www.w3.org/2000/01/rdf-schema#label": ["Loutra Traianopolis"], "http://www.w3.org/2002/07/owl#sameAs": ["http://www.wikidata.org/entity/Q2284484"], "http://www.w3.org/2006/time#hasTime": ["http://data.archaeology.link/data/ancientports/1854_foundation"], "http://www.wikidata.org/prop/direct/P1584": ["http://pleiades.stoa.org/places/501649"], "http://www.wikidata.org/prop/direct/P17": ["GR: North-East"], "http://www.wikidata.org/prop/direct/P1936": ["http://imperium.ahlfeldt.se/places/32411"], "http://www.wikidata.org/prop/direct/P1958": ["https://www.trismegistos.org/place/38413"], "http://www.wikidata.org/prop/direct/P8068": ["https://topostext.org/place/409260UTra"]}, "geometry": {"type": "Point", "coordinates": [26.033, 40.8653]}}]}