{"type": "FeatureCollection", "id": "http://imperium.ahlfeldt.se/places/30792", "name": "30792", "features": [{"type": "Feature", "id": "http://data.archaeology.link/data/ancientports/2298", "label": "Skalia, on the isle of Kalymnos ", "properties": {"http://purl.org/dc/elements/1.1/created": ["2023"], "http://purl.org/dc/elements/1.1/creator": ["http://data.archaeology.link/data/spphaefen/arthur_de_graauw"], "http://www.ancientports.com/ont#date_min": ["-550"], "http://www.opengis.net/ont/geosparql#hasGeometry": ["http://data.archaeology.link/data/ancientports/2298_geom"], "http://www.w3.org/1999/02/22-rdf-syntax-ns#type": ["http://www.ancientports.com/ont#Harbour"], "http://www.w3.org/2000/01/rdf-schema#label": ["Skalia, on the isle of Kalymnos "], "http://www.wikidata.org/prop/direct/P1584": ["http://pleiades.stoa.org/places/599938"], "http://www.wikidata.org/prop/direct/P17": ["GR: Eastern Isl."], "http://www.wikidata.org/prop/direct/P1936": ["http://imperium.ahlfeldt.se/places/30792"], "http://www.wikidata.org/prop/direct/P8068": ["https://topostext.org/place/370270XSka"]}, "geometry": {"type": "Point", "coordinates": [26.9531, 37.0375]}}]}