{"type": "FeatureCollection", "id": "http://www.wikidata.org/entity/Q12246", "name": "Q12246", "features": [{"type": "Feature", "id": "http://data.archaeology.link/data/ancientports/308", "label": "east of Plaza de las Monjas, Huelva, between R Rio Tinto & R Odiel", "dateprops": ["http://purl.org/dc/elements/1.1/created"], "properties": {"http://purl.org/dc/elements/1.1/created": ["2023"], "http://purl.org/dc/elements/1.1/creator": ["http://data.archaeology.link/data/spphaefen/arthur_de_graauw"], "http://www.opengis.net/ont/geosparql#hasGeometry": ["http://data.archaeology.link/data/ancientports/308_geom"], "http://www.w3.org/1999/02/22-rdf-syntax-ns#type": ["http://www.ancientports.com/ont#Lighthouse"], "http://www.w3.org/2000/01/rdf-schema#label": ["east of Plaza de las Monjas, Huelva, between R Rio Tinto & R Odiel"], "http://www.w3.org/2002/07/owl#sameAs": ["http://www.wikidata.org/entity/Q12246"], "http://www.w3.org/2004/02/skos/core#note": ["Gonzalez (2006)"], "http://www.w3.org/2006/time#hasTime": ["http://data.archaeology.link/data/ancientports/308_foundation"], "http://www.wikidata.org/prop/direct/P1584": ["http://pleiades.stoa.org/places/265985"], "http://www.wikidata.org/prop/direct/P17": ["http://www.wikidata.org/entity/Q29"], "http://www.wikidata.org/prop/direct/P1936": ["http://imperium.ahlfeldt.se/places/26935"], "http://www.wikidata.org/prop/direct/P1958": ["https://www.trismegistos.org/place/26027"]}, "geometry": {"type": "Point", "coordinates": [-6.9513, 37.2571]}}]}