{"type": "FeatureCollection", "id": "http://imperium.ahlfeldt.se/places/22911", "name": "22911", "features": [{"type": "Feature", "id": "http://data.archaeology.link/data/ancientports/860", "name": "Piombino", "dateprops": ["begin"], "properties": {"http://purl.org/dc/elements/1.1/created": ["2023"], "http://purl.org/dc/elements/1.1/creator": ["http://data.archaeology.link/data/spphaefen/arthur_de_graauw"], "http://www.opengis.net/ont/geosparql#hasGeometry": ["http://data.archaeology.link/data/ancientports/860_geom"], "http://www.w3.org/1999/02/22-rdf-syntax-ns#type": ["http://www.ancientports.com/ont#Harbour"], "http://www.w3.org/2000/01/rdf-schema#label": ["Piombino"], "http://www.w3.org/2002/07/owl#sameAs": ["http://www.wikidata.org/entity/Q157824"], "http://www.w3.org/2004/02/skos/core#note": ["Camilli (2005)"], "http://www.w3.org/2006/time#hasTime": ["http://data.archaeology.link/data/ancientports/860_foundation"], "http://www.wikidata.org/prop/direct/P1584": ["http://pleiades.stoa.org/places/403206"], "http://www.wikidata.org/prop/direct/P17": ["http://www.wikidata.org/entity/Q38"], "http://www.wikidata.org/prop/direct/P1936": ["http://imperium.ahlfeldt.se/places/22911"], "begin": "3001"}, "geometry": {"type": "Point", "coordinates": [10.55904, 42.9343]}}]}