{"type": "FeatureCollection", "id": "http://imperium.ahlfeldt.se/places/27831", "name": "27831", "features": [{"type": "Feature", "id": "http://data.archaeology.link/data/ancientports/2702", "name": "Pichori near R Enguri, near Anaklia", "dateprops": ["begin"], "properties": {"http://purl.org/dc/elements/1.1/creator": ["http://data.archaeology.link/data/spphaefen/arthur_de_graauw"], "http://purl.org/dc/terms/partOf": ["http://data.archaeology.link/data/ancientports/bib_deGrauw_2013_GeoDB"], "http://www.opengis.net/ont/geosparql#hasGeometry": ["http://data.archaeology.link/data/ancientports/2702_geom"], "http://www.w3.org/1999/02/22-rdf-syntax-ns#type": ["http://www.ancientports.com/ont#Harbour"], "http://www.w3.org/2000/01/rdf-schema#label": ["Pichori near R Enguri, near Anaklia"], "http://www.w3.org/2004/02/skos/core#note": ["Kvirkvelia (2005)"], "http://www.w3.org/2006/time#hasTime": ["http://data.archaeology.link/data/ancientports/2702_foundation"], "http://www.wikidata.org/prop/direct/P1584": ["http://pleiades.stoa.org/places/857280"], "http://www.wikidata.org/prop/direct/P17": ["Abkhazia Black S."], "http://www.wikidata.org/prop/direct/P1936": ["http://imperium.ahlfeldt.se/places/27831"], "begin": "-550"}, "geometry": {"type": "Point", "coordinates": [41.548, 42.3894]}}], "numberMatched": 1, "numberReturned": 1, "bbox": [41.548, 42.3894, 41.548, 42.3894], "crs": "http://www.opengis.net/def/crs/OGC/1.3/CRS84"}