{"type": "FeatureCollection", "id": "http://pleiades.stoa.org/places/541096", "name": "541096", "features": [{"type": "Feature", "id": "http://data.archaeology.link/data/ancientports/1758_1", "label": "Hellenistic fort at Cape Pouri", "properties": {"http://purl.org/dc/elements/1.1/created": ["2023"], "http://purl.org/dc/elements/1.1/creator": ["http://data.archaeology.link/data/spphaefen/arthur_de_graauw"], "http://www.ancientports.com/ont#date_min": ["-750"], "http://www.opengis.net/ont/geosparql#hasGeometry": ["http://data.archaeology.link/data/ancientports/1758_1_geom"], "http://www.w3.org/1999/02/22-rdf-syntax-ns#type": ["http://www.ancientports.com/ont#Harbour"], "http://www.w3.org/2000/01/rdf-schema#label": ["Hellenistic fort at Cape Pouri"], "http://www.wikidata.org/prop/direct/P1584": ["http://pleiades.stoa.org/places/541096"], "http://www.wikidata.org/prop/direct/P17": ["GR: North-East"], "http://www.wikidata.org/prop/direct/P1936": ["http://imperium.ahlfeldt.se/places/34368"], "http://www.wikidata.org/prop/direct/P8068": ["https://topostext.org/place/395231FSep"]}, "geometry": {"type": "Point", "coordinates": [23.0853, 39.4751]}}]}