{"type": "FeatureCollection", "id": "http://pleiades.stoa.org/places/39377", "name": "39377", "features": [{"type": "Feature", "id": "http://data.archaeology.link/data/ancientports/3650", "label": "al-Luhayyah, Loheia, other possible locations: as-Shuqaiq, 230 km further north and Mimla, 230 km further south", "dateprops": [], "properties": {"http://purl.org/dc/elements/1.1/created": ["2023"], "http://purl.org/dc/elements/1.1/creator": ["http://data.archaeology.link/data/spphaefen/arthur_de_graauw"], "http://purl.org/dc/terms/isReferencedBy": ["http://data.archaeology.link/data/ancientports/bib_Bukharin_2012_The"], "http://www.opengis.net/ont/geosparql#hasGeometry": ["http://data.archaeology.link/data/ancientports/3650_geom"], "http://www.w3.org/1999/02/22-rdf-syntax-ns#type": ["http://www.ancientports.com/ont#Harbour"], "http://www.w3.org/2000/01/rdf-schema#label": ["al-Luhayyah, Loheia, other possible locations: as-Shuqaiq, 230 km further north and Mimla, 230 km further south"], "http://www.w3.org/2002/07/owl#sameAs": ["http://www.wikidata.org/entity/Q292439"], "http://www.wikidata.org/prop/direct/P1584": ["http://pleiades.stoa.org/places/39377"], "http://www.wikidata.org/prop/direct/P17": ["http://www.wikidata.org/entity/Q805"]}, "geometry": {"type": "Point", "coordinates": [42.687, 15.695]}}]}