{"type": "FeatureCollection", "id": "http://pleiades.stoa.org/places/305111", "name": "305111", "features": [{"type": "Feature", "id": "http://data.archaeology.link/data/ancientports/4219", "name": "Andriech, at Sidi Rehane, near Cape Aokas", "dateprops": ["begin"], "properties": {"http://purl.org/dc/elements/1.1/created": ["2023"], "http://purl.org/dc/elements/1.1/creator": ["http://data.archaeology.link/data/spphaefen/arthur_de_graauw"], "http://www.opengis.net/ont/geosparql#hasGeometry": ["http://data.archaeology.link/data/ancientports/4219_geom"], "http://www.w3.org/1999/02/22-rdf-syntax-ns#type": ["http://www.ancientports.com/ont#VillaMaritima"], "http://www.w3.org/2000/01/rdf-schema#label": ["Andriech, at Sidi Rehane, near Cape Aokas"], "http://www.w3.org/2004/02/skos/core#note": ["Elie de la Primaudaie (1860) locates it at Ziama Mansouria"], "http://www.w3.org/2006/time#hasTime": ["http://data.archaeology.link/data/ancientports/4219_foundation"], "http://www.wikidata.org/prop/direct/P1584": ["http://pleiades.stoa.org/places/305111"], "http://www.wikidata.org/prop/direct/P17": ["http://www.wikidata.org/entity/Q262"], "http://www.wikidata.org/prop/direct/P1936": ["http://imperium.ahlfeldt.se/places/23759"], "begin": "-330"}, "geometry": {"type": "Point", "coordinates": [5.2616, 36.6298]}}]}