{"type": "FeatureCollection", "id": "http://pleiades.stoa.org/places/324688", "name": "324688", "features": [{"type": "Feature", "id": "http://data.archaeology.link/data/ancientports/4123", "name": "La Skhirra, ex 'Ferme Roderie' 300 m south of La Tour du Nadour", "dateprops": ["begin"], "properties": {"http://purl.org/dc/elements/1.1/creator": ["http://data.archaeology.link/data/spphaefen/arthur_de_graauw"], "http://purl.org/dc/terms/isReferencedBy": ["http://data.archaeology.link/data/ancientports/bib_Paskoff_1991_Le"], "http://purl.org/dc/terms/partOf": ["http://data.archaeology.link/data/ancientports/bib_deGrauw_2013_GeoDB"], "http://www.opengis.net/ont/geosparql#hasGeometry": ["http://data.archaeology.link/data/ancientports/4123_geom"], "http://www.w3.org/1999/02/22-rdf-syntax-ns#type": ["http://www.ancientports.com/ont#Harbour"], "http://www.w3.org/2000/01/rdf-schema#label": ["La Skhirra, ex 'Ferme Roderie' 300 m south of La Tour du Nadour"], "http://www.w3.org/2006/time#hasTime": ["http://data.archaeology.link/data/ancientports/4123_foundation"], "http://www.wikidata.org/prop/direct/P1584": ["http://pleiades.stoa.org/places/324688"], "http://www.wikidata.org/prop/direct/P17": ["http://www.wikidata.org/entity/Q948"], "http://www.wikidata.org/prop/direct/P1936": ["http://imperium.ahlfeldt.se/places/32509"], "begin": "-30"}, "geometry": {"type": "Point", "coordinates": [10.06284, 34.22828]}}], "numberMatched": 1, "numberReturned": 1, "bbox": [10.06284, 34.22828, 10.06284, 34.22828], "crs": "http://www.opengis.net/def/crs/OGC/1.3/CRS84"}