{"type": "FeatureCollection", "id": "http://www.wikidata.org/entity/Q820972", "name": "Q820972", "features": [{"type": "Feature", "id": "http://data.archaeology.link/data/ancientports/3737_1", "label": "Tadjoura", "dateprops": [], "properties": {"http://purl.org/dc/elements/1.1/created": ["2023"], "http://purl.org/dc/elements/1.1/creator": ["http://data.archaeology.link/data/spphaefen/arthur_de_graauw"], "http://www.opengis.net/ont/geosparql#hasGeometry": ["http://data.archaeology.link/data/ancientports/3737_1_geom"], "http://www.w3.org/1999/02/22-rdf-syntax-ns#type": ["http://www.ancientports.com/ont#PotentialHarbour", "http://www.ancientports.com/ont#Harbour"], "http://www.w3.org/2000/01/rdf-schema#label": ["Tadjoura"], "http://www.w3.org/2002/07/owl#sameAs": ["http://www.wikidata.org/entity/Q820972"], "http://www.wikidata.org/prop/direct/P17": ["http://www.wikidata.org/entity/Q977", "Djibouti Ind Oc."]}, "geometry": {"type": "Point", "coordinates": [42.878, 11.782]}}]}