{"type": "FeatureCollection", "id": "http://www.wikidata.org/entity/Q744317", "name": "Q744317", "features": [{"type": "Feature", "id": "http://data.archaeology.link/data/ancientports/104_5", "label": "Roman fort at Calstock, on R Tamar (export of tin)", "dateprops": ["http://purl.org/dc/elements/1.1/created"], "properties": {"http://purl.org/dc/elements/1.1/created": ["2023"], "http://purl.org/dc/elements/1.1/creator": ["http://data.archaeology.link/data/spphaefen/arthur_de_graauw"], "http://purl.org/dc/terms/isReferencedBy": ["https://historicengland.org.uk/listing/the-list/list-entry/1140252"], "http://www.opengis.net/ont/geosparql#hasGeometry": ["http://data.archaeology.link/data/ancientports/104_5_geom"], "http://www.w3.org/1999/02/22-rdf-syntax-ns#type": ["http://www.ancientports.com/ont#Harbour"], "http://www.w3.org/2000/01/rdf-schema#label": ["Roman fort at Calstock, on R Tamar (export of tin)"], "http://www.w3.org/2002/07/owl#sameAs": ["http://www.wikidata.org/entity/Q744317"], "http://www.w3.org/2004/02/skos/core#note": ["de Graauw pictures (2019)"], "http://www.w3.org/2006/time#hasTime": ["http://data.archaeology.link/data/ancientports/104_5_foundation"], "http://www.wikidata.org/prop/direct/P1584": ["https://pleiades.stoa.org/places/442808"], "http://www.wikidata.org/prop/direct/P17": ["http://www.wikidata.org/entity/Q145"], "http://www.wikidata.org/prop/direct/P1936": ["http://imperium.ahlfeldt.se/places/38988"], "http://www.wikidata.org/prop/direct/P1958": ["https://www.trismegistos.org/place/19639"]}, "geometry": {"type": "Point", "coordinates": [-4.20721, 50.50197]}}]}