{"type": "FeatureCollection", "id": "http://www.wikidata.org/entity/Q858775", "name": "Q858775", "features": [{"type": "Feature", "id": "http://data.archaeology.link/data/ancientports/74_3", "label": "Roman villa at Darenth, near Dartford", "properties": {"http://purl.org/dc/elements/1.1/created": ["2023"], "http://purl.org/dc/elements/1.1/creator": ["http://data.archaeology.link/data/spphaefen/arthur_de_graauw"], "http://purl.org/dc/terms/isReferencedBy": ["https://historicengland.org.uk/listing/the-list/list-entry/1012965"], "http://www.ancientports.com/ont#date_min": ["5001"], "http://www.opengis.net/ont/geosparql#hasGeometry": ["http://data.archaeology.link/data/ancientports/74_3_geom"], "http://www.w3.org/1999/02/22-rdf-syntax-ns#type": ["http://www.ancientports.com/ont#VillaMaritima"], "http://www.w3.org/2000/01/rdf-schema#label": ["Roman villa at Darenth, near Dartford"], "http://www.w3.org/2002/07/owl#sameAs": ["http://www.wikidata.org/entity/Q858775"], "http://www.wikidata.org/prop/direct/P1584": ["http://pleiades.stoa.org/places/79413"], "http://www.wikidata.org/prop/direct/P17": ["http://www.wikidata.org/entity/Q145"], "http://www.wikidata.org/prop/direct/P1936": ["http://imperium.ahlfeldt.se/places/25630"]}, "geometry": {"type": "Point", "coordinates": [0.2466, 51.4133]}}, {"type": "Feature", "id": "http://data.archaeology.link/data/ancientports/74_2", "label": "Roman villa at Wilmington, Dartford", "properties": {"http://purl.org/dc/elements/1.1/created": ["2023"], "http://purl.org/dc/elements/1.1/creator": ["http://data.archaeology.link/data/spphaefen/arthur_de_graauw"], "http://www.ancientports.com/ont#date_min": ["5001"], "http://www.opengis.net/ont/geosparql#hasGeometry": ["http://data.archaeology.link/data/ancientports/74_2_geom"], "http://www.w3.org/1999/02/22-rdf-syntax-ns#type": ["http://www.ancientports.com/ont#VillaMaritima"], "http://www.w3.org/2000/01/rdf-schema#label": ["Roman villa at Wilmington, Dartford"], "http://www.w3.org/2002/07/owl#sameAs": ["http://www.wikidata.org/entity/Q858775"], "http://www.wikidata.org/prop/direct/P17": ["http://www.wikidata.org/entity/Q145"], "http://www.wikidata.org/prop/direct/P1936": ["http://imperium.ahlfeldt.se/places/25939"]}, "geometry": {"type": "Point", "coordinates": [0.2166, 51.4349]}}, {"type": "Feature", "id": "http://data.archaeology.link/data/ancientports/74_1", "label": "Roman villa at Tenters Hill Field, Dartford", "properties": {"http://purl.org/dc/elements/1.1/created": ["2023"], "http://purl.org/dc/elements/1.1/creator": ["http://data.archaeology.link/data/spphaefen/arthur_de_graauw"], "http://www.ancientports.com/ont#date_min": ["5001"], "http://www.opengis.net/ont/geosparql#hasGeometry": ["http://data.archaeology.link/data/ancientports/74_1_geom"], "http://www.w3.org/1999/02/22-rdf-syntax-ns#type": ["http://www.ancientports.com/ont#VillaMaritima"], "http://www.w3.org/2000/01/rdf-schema#label": ["Roman villa at Tenters Hill Field, Dartford"], "http://www.w3.org/2002/07/owl#sameAs": ["http://www.wikidata.org/entity/Q858775"], "http://www.wikidata.org/prop/direct/P17": ["http://www.wikidata.org/entity/Q145"], "http://www.wikidata.org/prop/direct/P1936": ["http://imperium.ahlfeldt.se/places/25940"]}, "geometry": {"type": "Point", "coordinates": [0.2235, 51.4389]}}]}