{"type": "FeatureCollection", "id": "http://imperium.ahlfeldt.se/places/36872", "name": "36872", "features": [{"type": "Feature", "id": "http://data.archaeology.link/data/ancientports/3409", "name": "near Meydan?", "dateprops": ["begin"], "properties": {"http://purl.org/dc/elements/1.1/creator": ["http://data.archaeology.link/data/spphaefen/arthur_de_graauw"], "http://purl.org/dc/terms/partOf": ["http://data.archaeology.link/data/ancientports/bib_deGrauw_2013_GeoDB"], "http://www.opengis.net/ont/geosparql#hasGeometry": ["http://data.archaeology.link/data/ancientports/3409_geom"], "http://www.w3.org/1999/02/22-rdf-syntax-ns#type": ["http://www.ancientports.com/ont#Harbour"], "http://www.w3.org/2000/01/rdf-schema#label": ["near Meydan?"], "http://www.w3.org/2006/time#hasTime": ["http://data.archaeology.link/data/ancientports/3409_foundation"], "http://www.wikidata.org/prop/direct/P1584": ["http://pleiades.stoa.org/places/658552"], "http://www.wikidata.org/prop/direct/P17": ["http://www.wikidata.org/entity/Q43"], "http://www.wikidata.org/prop/direct/P1936": ["http://imperium.ahlfeldt.se/places/36872"], "begin": "3001"}, "geometry": {"type": "Point", "coordinates": [35.9974, 36.0342]}}]}