{"type": "FeatureCollection", "id": "http://www.wikidata.org/entity/Q4708853", "name": "Q4708853", "features": [{"type": "Feature", "id": "http://data.archaeology.link/data/ancientports/155", "label": "Roman fort at Maryport, with many fortlets on the Firth of Solway", "properties": {"http://purl.org/dc/elements/1.1/created": ["2023"], "http://purl.org/dc/elements/1.1/creator": ["http://data.archaeology.link/data/spphaefen/arthur_de_graauw"], "http://www.ancientports.com/ont#date_min": ["1001"], "http://www.opengis.net/ont/geosparql#hasGeometry": ["http://data.archaeology.link/data/ancientports/155_geom"], "http://www.w3.org/1999/02/22-rdf-syntax-ns#type": ["http://www.ancientports.com/ont#Harbour"], "http://www.w3.org/2000/01/rdf-schema#label": ["Roman fort at Maryport, with many fortlets on the Firth of Solway"], "http://www.w3.org/2002/07/owl#sameAs": ["http://www.wikidata.org/entity/Q4708853"], "http://www.wikidata.org/prop/direct/P1584": ["http://pleiades.stoa.org/places/89097"], "http://www.wikidata.org/prop/direct/P17": ["http://www.wikidata.org/entity/Q145"], "http://www.wikidata.org/prop/direct/P1936": ["http://imperium.ahlfeldt.se/places/23702"], "http://www.wikidata.org/prop/direct/P1958": ["https://www.trismegistos.org/place/14569"]}, "geometry": {"type": "Point", "coordinates": [-3.49393, 54.72065]}}]}