{"type": "FeatureCollection", "id": "http://pleiades.stoa.org/places/589871", "name": "589871", "features": [{"type": "Feature", "id": "http://data.archaeology.link/data/ancientports/2939", "name": "Kalami, on the South side of the entrance to the bay of Souda. There are thus two 'Kisamos' homonym sites", "dateprops": ["begin"], "properties": {"http://purl.org/dc/elements/1.1/creator": ["http://data.archaeology.link/data/spphaefen/arthur_de_graauw"], "http://purl.org/dc/terms/partOf": ["http://data.archaeology.link/data/ancientports/bib_deGrauw_2013_GeoDB"], "http://www.opengis.net/ont/geosparql#hasGeometry": ["http://data.archaeology.link/data/ancientports/2939_geom"], "http://www.w3.org/1999/02/22-rdf-syntax-ns#type": ["http://www.ancientports.com/ont#Harbour"], "http://www.w3.org/2000/01/rdf-schema#label": ["Kalami, on the South side of the entrance to the bay of Souda. There are thus two 'Kisamos' homonym sites"], "http://www.w3.org/2002/07/owl#sameAs": ["http://www.wikidata.org/entity/Q622234"], "http://www.w3.org/2004/02/skos/core#note": ["Uggeri (2003)"], "http://www.w3.org/2006/time#hasTime": ["http://data.archaeology.link/data/ancientports/2939_foundation"], "http://www.wikidata.org/prop/direct/P1584": ["http://pleiades.stoa.org/places/589871"], "http://www.wikidata.org/prop/direct/P17": ["http://www.wikidata.org/entity/Q41"], "http://www.wikidata.org/prop/direct/P1936": ["http://imperium.ahlfeldt.se/places/28800"], "http://www.wikidata.org/prop/direct/P8068": ["https://topostext.org/place/355242UKis"], "begin": "-1500"}, "geometry": {"type": "Point", "coordinates": [24.1407, 35.4702]}}, {"type": "Feature", "id": "http://data.archaeology.link/data/ancientports/2939_1", "name": "Kera beach, near Kalyves", "dateprops": [], "properties": {"http://purl.org/dc/elements/1.1/creator": ["http://data.archaeology.link/data/spphaefen/arthur_de_graauw"], "http://purl.org/dc/terms/partOf": ["http://data.archaeology.link/data/ancientports/bib_deGrauw_2013_GeoDB"], "http://www.opengis.net/ont/geosparql#hasGeometry": ["http://data.archaeology.link/data/ancientports/2939_1_geom"], "http://www.w3.org/1999/02/22-rdf-syntax-ns#type": ["http://www.ancientports.com/ont#Harbour"], "http://www.w3.org/2000/01/rdf-schema#label": ["Kera beach, near Kalyves"], "http://www.w3.org/2002/07/owl#sameAs": ["http://www.wikidata.org/entity/Q15966202"], "http://www.wikidata.org/prop/direct/P1584": ["http://pleiades.stoa.org/places/589871"], "http://www.wikidata.org/prop/direct/P17": ["http://www.wikidata.org/entity/Q41"], "http://www.wikidata.org/prop/direct/P1936": ["http://imperium.ahlfeldt.se/places/28800"], "http://www.wikidata.org/prop/direct/P1958": ["https://www.trismegistos.org/place/41978"], "http://www.wikidata.org/prop/direct/P8068": ["https://topostext.org/place/355242UKis"], "begin": ""}, "geometry": {"type": "Point", "coordinates": [24.187, 35.45]}}], "numberMatched": 2, "numberReturned": 2}