{"type": "FeatureCollection", "id": "https://topostext.org/place/353263IDio", "name": "353263IDio", "features": [{"type": "Feature", "id": "http://data.archaeology.link/data/ancientports/2978", "label": "Dionysiades islands, Dragonada, Gianisada and Paximada, South creek on the isle of Dragonada", "dateprops": [], "properties": {"http://purl.org/dc/elements/1.1/created": ["2023"], "http://purl.org/dc/elements/1.1/creator": ["http://data.archaeology.link/data/spphaefen/arthur_de_graauw"], "http://www.opengis.net/ont/geosparql#hasGeometry": ["http://data.archaeology.link/data/ancientports/2978_geom"], "http://www.w3.org/1999/02/22-rdf-syntax-ns#type": ["http://www.ancientports.com/ont#Harbour"], "http://www.w3.org/2000/01/rdf-schema#label": ["Dionysiades islands, Dragonada, Gianisada and Paximada, South creek on the isle of Dragonada"], "http://www.w3.org/2002/07/owl#sameAs": ["http://www.wikidata.org/entity/Q915908"], "http://www.w3.org/2004/02/skos/core#note": ["Uggeri (2003)"], "http://www.w3.org/2006/time#hasTime": ["http://data.archaeology.link/data/ancientports/2978_foundation"], "http://www.wikidata.org/prop/direct/P1584": ["http://pleiades.stoa.org/places/589763"], "http://www.wikidata.org/prop/direct/P17": ["http://www.wikidata.org/entity/Q41"], "http://www.wikidata.org/prop/direct/P1936": ["http://imperium.ahlfeldt.se/places/44581"], "http://www.wikidata.org/prop/direct/P8068": ["https://topostext.org/place/353263IDio"]}, "geometry": {"type": "Point", "coordinates": [26.18272, 35.33806]}}]}