{"type": "FeatureCollection", "id": "http://www.wikidata.org/entity/Q1021806", "name": "Q1021806", "features": [{"type": "Feature", "id": "http://data.archaeology.link/data/ancientports/1434", "label": "Janice, near Pakostane ", "dateprops": [], "properties": {"http://purl.org/dc/elements/1.1/created": ["2023"], "http://purl.org/dc/elements/1.1/creator": ["http://data.archaeology.link/data/spphaefen/arthur_de_graauw"], "http://purl.org/dc/terms/isReferencedBy": ["http://baza.iarh.hr/public/locality/detail/3822", "http://www.arkaeos.fr/les-operations/article/pakostane"], "http://www.opengis.net/ont/geosparql#hasGeometry": ["http://data.archaeology.link/data/ancientports/1434_geom"], "http://www.w3.org/1999/02/22-rdf-syntax-ns#type": ["http://www.ancientports.com/ont#Harbour"], "http://www.w3.org/2000/01/rdf-schema#label": ["Janice, near Pakostane "], "http://www.w3.org/2002/07/owl#sameAs": ["http://www.wikidata.org/entity/Q1021806"], "http://www.w3.org/2004/02/skos/core#note": ["Radic (2008)"], "http://www.w3.org/2006/time#hasTime": ["http://data.archaeology.link/data/ancientports/1434_foundation"], "http://www.wikidata.org/prop/direct/P17": ["http://www.wikidata.org/entity/Q224"]}, "geometry": {"type": "Point", "coordinates": [15.5124, 43.9043]}}]}