{"type": "FeatureCollection", "id": "https://topostext.org/place/353243UHyd", "name": "353243UHyd", "features": [{"type": "Feature", "id": "http://data.archaeology.link/data/ancientports/2942", "name": "Dramia, Idramon, on R Mouselas", "dateprops": ["begin"], "properties": {"http://purl.org/dc/elements/1.1/creator": ["http://data.archaeology.link/data/spphaefen/arthur_de_graauw"], "http://purl.org/dc/terms/partOf": ["http://data.archaeology.link/data/ancientports/bib_deGrauw_2013_GeoDB"], "http://www.opengis.net/ont/geosparql#hasGeometry": ["http://data.archaeology.link/data/ancientports/2942_geom"], "http://www.w3.org/1999/02/22-rdf-syntax-ns#type": ["http://www.ancientports.com/ont#Harbour"], "http://www.w3.org/2000/01/rdf-schema#label": ["Dramia, Idramon, on R Mouselas"], "http://www.w3.org/2002/07/owl#sameAs": ["http://www.wikidata.org/entity/Q65075205"], "http://www.w3.org/2004/02/skos/core#note": ["Uggeri (2003)"], "http://www.w3.org/2006/time#hasTime": ["http://data.archaeology.link/data/ancientports/2942_foundation"], "http://www.wikidata.org/prop/direct/P1584": ["http://pleiades.stoa.org/places/589810"], "http://www.wikidata.org/prop/direct/P17": ["http://www.wikidata.org/entity/Q41"], "http://www.wikidata.org/prop/direct/P1936": ["http://imperium.ahlfeldt.se/places/28780"], "http://www.wikidata.org/prop/direct/P1958": ["https://www.trismegistos.org/place/33254"], "http://www.wikidata.org/prop/direct/P8068": ["https://topostext.org/place/353243UHyd"], "begin": "-30"}, "geometry": {"type": "Point", "coordinates": [24.3174, 35.3482]}}], "numberMatched": 1, "numberReturned": 1, "bbox": [24.3174, 35.3482, 24.3174, 35.3482], "crs": "http://www.opengis.net/def/crs/EPSG/0/4326"}