{"type": "FeatureCollection", "id": "http://pleiades.stoa.org/places/187339", "name": "187339", "features": [{"type": "Feature", "id": "http://data.archaeology.link/data/ancientports/1353", "label": "Castello di Miramare, Grignano", "properties": {"http://purl.org/dc/elements/1.1/created": ["2023"], "http://purl.org/dc/elements/1.1/creator": ["http://data.archaeology.link/data/spphaefen/arthur_de_graauw"], "http://www.ancientports.com/ont#date_min": ["-30"], "http://www.opengis.net/ont/geosparql#hasGeometry": ["http://data.archaeology.link/data/ancientports/1353_geom"], "http://www.w3.org/1999/02/22-rdf-syntax-ns#type": ["http://www.ancientports.com/ont#Harbour"], "http://www.w3.org/2000/01/rdf-schema#label": ["Castello di Miramare, Grignano"], "http://www.w3.org/2004/02/skos/core#note": ["Degrassi (1955)"], "http://www.wikidata.org/prop/direct/P1584": ["http://pleiades.stoa.org/places/187339"], "http://www.wikidata.org/prop/direct/P17": ["Italy Adriatic"]}, "geometry": {"type": "Point", "coordinates": [13.70822, 45.70551]}}]}