{"type": "FeatureCollection", "id": "http://www.wikidata.org/entity/Q1986111", "name": "Q1986111", "features": [{"type": "Feature", "id": "http://data.archaeology.link/data/ancientports/1766", "label": "near Pyrgetos?", "dateprops": [], "properties": {"http://purl.org/dc/elements/1.1/created": ["2023"], "http://purl.org/dc/elements/1.1/creator": ["http://data.archaeology.link/data/spphaefen/arthur_de_graauw"], "http://www.ancientports.com/ont#date_min": ["-550"], "http://www.opengis.net/ont/geosparql#hasGeometry": ["http://data.archaeology.link/data/ancientports/1766_geom"], "http://www.w3.org/1999/02/22-rdf-syntax-ns#type": ["http://www.ancientports.com/ont#Harbour"], "http://www.w3.org/2000/01/rdf-schema#label": ["near Pyrgetos?"], "http://www.w3.org/2002/07/owl#sameAs": ["http://www.wikidata.org/entity/Q1986111"], "http://www.wikidata.org/prop/direct/P1584": ["http://pleiades.stoa.org/places/541045"], "http://www.wikidata.org/prop/direct/P17": ["GR: North-East"], "http://www.wikidata.org/prop/direct/P1936": ["http://imperium.ahlfeldt.se/places/29440"], "http://www.wikidata.org/prop/direct/P1958": ["https://www.trismegistos.org/place/34000"], "http://www.wikidata.org/prop/direct/P8068": ["https://topostext.org/place/399226UPhi"]}, "geometry": {"type": "Point", "coordinates": [22.5955, 39.91794]}}]}