{"type": "FeatureCollection", "id": "http://imperium.ahlfeldt.se/places/39719", "name": "39719", "features": [{"type": "Feature", "id": "http://data.archaeology.link/data/ancientports/364", "name": "Roman villa at La Loma de Benagalbon, Rincon de la Victoria", "dateprops": ["begin"], "properties": {"http://purl.org/dc/elements/1.1/creator": ["http://data.archaeology.link/data/spphaefen/arthur_de_graauw"], "http://purl.org/dc/terms/partOf": ["http://data.archaeology.link/data/ancientports/bib_deGrauw_2013_GeoDB"], "http://www.opengis.net/ont/geosparql#hasGeometry": ["http://data.archaeology.link/data/ancientports/364_geom"], "http://www.w3.org/1999/02/22-rdf-syntax-ns#type": ["http://www.ancientports.com/ont#VillaMaritima"], "http://www.w3.org/2000/01/rdf-schema#label": ["Roman villa at La Loma de Benagalbon, Rincon de la Victoria"], "http://www.w3.org/2006/time#hasTime": ["http://data.archaeology.link/data/ancientports/364_foundation"], "http://www.wikidata.org/prop/direct/P17": ["http://www.wikidata.org/entity/Q29"], "http://www.wikidata.org/prop/direct/P1936": ["http://imperium.ahlfeldt.se/places/39719"], "begin": "-750"}, "geometry": {"type": "Point", "coordinates": [-4.2598, 36.7135]}}], "numberMatched": 1, "numberReturned": 1, "bbox": [-4.2598, 36.7135, -4.2598, 36.7135], "crs": "http://www.opengis.net/def/crs/OGC/1.3/CRS84"}