{"type": "FeatureCollection", "id": "http://pleiades.stoa.org/places/521092", "name": "521092", "features": [{"type": "Feature", "id": "http://data.archaeology.link/data/ancientports/2857", "name": "Dragos near Maltepe", "dateprops": [], "properties": {"http://purl.org/dc/elements/1.1/creator": ["http://data.archaeology.link/data/spphaefen/arthur_de_graauw"], "http://purl.org/dc/terms/partOf": ["http://data.archaeology.link/data/ancientports/bib_deGrauw_2013_GeoDB"], "http://www.opengis.net/ont/geosparql#hasGeometry": ["http://data.archaeology.link/data/ancientports/2857_geom"], "http://www.w3.org/1999/02/22-rdf-syntax-ns#type": ["http://www.ancientports.com/ont#Harbour"], "http://www.w3.org/2000/01/rdf-schema#label": ["Dragos near Maltepe"], "http://www.wikidata.org/prop/direct/P1584": ["http://pleiades.stoa.org/places/521092"], "http://www.wikidata.org/prop/direct/P17": ["http://www.wikidata.org/entity/Q43"], "begin": ""}, "geometry": {"type": "Point", "coordinates": [29.14107, 40.89601]}}], "numberMatched": 1, "numberReturned": 1}