{"type": "FeatureCollection", "id": "http://pleiades.stoa.org/places/520988", "name": "520988", "features": [{"type": "Feature", "id": "http://data.archaeology.link/data/ancientports/2850_1", "name": "Moda iskelesi", "dateprops": ["begin"], "properties": {"http://purl.org/dc/elements/1.1/created": ["2023"], "http://purl.org/dc/elements/1.1/creator": ["http://data.archaeology.link/data/spphaefen/arthur_de_graauw"], "http://www.opengis.net/ont/geosparql#hasGeometry": ["http://data.archaeology.link/data/ancientports/2850_1_geom"], "http://www.w3.org/1999/02/22-rdf-syntax-ns#type": ["http://www.ancientports.com/ont#Harbour"], "http://www.w3.org/2000/01/rdf-schema#label": ["Moda iskelesi"], "http://www.w3.org/2002/07/owl#sameAs": ["http://www.wikidata.org/entity/Q337381"], "http://www.w3.org/2006/time#hasTime": ["http://data.archaeology.link/data/ancientports/2850_1_foundation"], "http://www.wikidata.org/prop/direct/P1584": ["http://pleiades.stoa.org/places/520988"], "http://www.wikidata.org/prop/direct/P17": ["http://www.wikidata.org/entity/Q43"], "http://www.wikidata.org/prop/direct/P1958": ["https://www.trismegistos.org/place/972"], "http://www.wikidata.org/prop/direct/P8068": ["https://topostext.org/place/410290PCha"], "begin": "5001"}, "geometry": {"type": "Point", "coordinates": [29.0254, 40.979]}}]}