{"type": "FeatureCollection", "id": "http://www.wikidata.org/entity/Q328647", "name": "Sulina", "features": [{"type": "Feature", "id": "http://data.archaeology.link/data/ancientports/2520", "name": "Sulina", "dateprops": [], "properties": {"http://purl.org/dc/elements/1.1/creator": ["http://data.archaeology.link/data/spphaefen/arthur_de_graauw"], "http://purl.org/dc/terms/partOf": ["http://data.archaeology.link/data/ancientports/bib_deGrauw_2013_GeoDB"], "http://www.opengis.net/ont/geosparql#hasGeometry": ["http://data.archaeology.link/data/ancientports/2520_geom"], "http://www.w3.org/1999/02/22-rdf-syntax-ns#type": ["http://www.ancientports.com/ont#Harbour"], "http://www.w3.org/2000/01/rdf-schema#label": ["Sulina"], "http://www.w3.org/2002/07/owl#sameAs": ["http://www.wikidata.org/entity/Q328647"], "http://www.wikidata.org/prop/direct/P17": ["http://www.wikidata.org/entity/Q218"], "begin": ""}, "geometry": {"type": "Point", "coordinates": [29.6526, 45.1566]}}]}