{"type": "FeatureCollection", "id": "https://topostext.org/place/371271PLep", "name": "371271PLep", "features": [{"type": "Feature", "id": "http://data.archaeology.link/data/ancientports/2299", "name": "", "dateprops": [], "properties": {"http://purl.org/dc/elements/1.1/creator": ["http://data.archaeology.link/data/spphaefen/arthur_de_graauw"], "http://purl.org/dc/terms/partOf": ["http://data.archaeology.link/data/ancientports/bib_deGrauw_2013_GeoDB"], "http://rdfs.org/ns/void#inDataset": ["http://data.archaeology.link/data/ancientports/ap_dataset"], "http://www.opengis.net/ont/geosparql#hasGeometry": ["http://data.archaeology.link/data/ancientports/2299_geom"], "http://www.w3.org/1999/02/22-rdf-syntax-ns#type": ["http://www.ancientports.com/ont#Harbour"], "http://www.w3.org/2000/01/rdf-schema#label": ["Isle of Kalolimnos"], "http://www.w3.org/2002/07/owl#sameAs": ["http://www.wikidata.org/entity/Q17619737"], "http://www.wikidata.org/prop/direct/P1584": ["http://pleiades.stoa.org/places/599762"], "http://www.wikidata.org/prop/direct/P17": ["http://www.wikidata.org/entity/Q41"], "http://www.wikidata.org/prop/direct/P1936": ["http://imperium.ahlfeldt.se/places/41150"], "http://www.wikidata.org/prop/direct/P1958": ["https://www.trismegistos.org/place/58966"], "http://www.wikidata.org/prop/direct/P8068": ["https://topostext.org/place/371271PLep"], "begin": ""}, "geometry": {"type": "Point", "coordinates": [27.086, 37.061]}}], "numberMatched": 1, "numberReturned": 1, "bbox": [27.086, 37.061, 27.086, 37.061], "crs": "http://www.opengis.net/def/crs/EPSG/0/4326"}