{"type": "FeatureCollection", "id": "https://pleiades.stoa.org/places/570198", "name": "570198", "features": [{"type": "Feature", "id": "http://data.archaeology.link/data/ancientports/1966_1", "name": "Posidonia", "dateprops": ["begin"], "properties": {"http://purl.org/dc/elements/1.1/creator": ["http://data.archaeology.link/data/spphaefen/arthur_de_graauw"], "http://purl.org/dc/terms/partOf": ["http://data.archaeology.link/data/ancientports/bib_deGrauw_2013_GeoDB"], "http://www.opengis.net/ont/geosparql#hasGeometry": ["http://data.archaeology.link/data/ancientports/1966_1_geom"], "http://www.w3.org/1999/02/22-rdf-syntax-ns#type": ["http://www.ancientports.com/ont#Slipway"], "http://www.w3.org/2000/01/rdf-schema#label": ["Posidonia"], "http://www.w3.org/2002/07/owl#sameAs": ["http://www.wikidata.org/entity/Q1226902"], "http://www.w3.org/2004/02/skos/core#note": ["Kolaiti (2017)"], "http://www.w3.org/2006/time#hasTime": ["http://data.archaeology.link/data/ancientports/1966_1_foundation"], "http://www.wikidata.org/prop/direct/P1584": ["https://pleiades.stoa.org/places/570198"], "http://www.wikidata.org/prop/direct/P17": ["http://www.wikidata.org/entity/Q41"], "http://www.wikidata.org/prop/direct/P8068": ["https://topostext.org/place/379230LDio"], "begin": "-750"}, "geometry": {"type": "Point", "coordinates": [22.95954, 37.95119]}}], "numberMatched": 1, "numberReturned": 1, "bbox": [22.95954, 37.95119, 22.95954, 37.95119], "crs": "http://www.opengis.net/def/crs/EPSG/0/4326"}