{"type": "FeatureCollection", "id": "http://www.wikidata.org/entity/Q649217", "name": "Santa Maria di Leuca", "features": [{"type": "Feature", "id": "http://data.archaeology.link/data/ancientports/1110", "name": "Santa Maria di Leuca, near Punta Ristola", "dateprops": ["begin"], "properties": {"http://purl.org/dc/elements/1.1/created": ["2023"], "http://purl.org/dc/elements/1.1/creator": ["http://data.archaeology.link/data/spphaefen/arthur_de_graauw"], "http://www.opengis.net/ont/geosparql#hasGeometry": ["http://data.archaeology.link/data/ancientports/1110_geom"], "http://www.w3.org/1999/02/22-rdf-syntax-ns#type": ["http://www.ancientports.com/ont#Harbour"], "http://www.w3.org/2000/01/rdf-schema#label": ["Santa Maria di Leuca, near Punta Ristola"], "http://www.w3.org/2002/07/owl#sameAs": ["http://www.wikidata.org/entity/Q649217"], "http://www.w3.org/2006/time#hasTime": ["http://data.archaeology.link/data/ancientports/1110_foundation"], "http://www.wikidata.org/prop/direct/P1584": ["http://pleiades.stoa.org/places/442632"], "http://www.wikidata.org/prop/direct/P17": ["http://www.wikidata.org/entity/Q38"], "http://www.wikidata.org/prop/direct/P1936": ["http://imperium.ahlfeldt.se/places/41276"], "http://www.wikidata.org/prop/direct/P1958": ["https://www.trismegistos.org/place/32964"], "http://www.wikidata.org/prop/direct/P8068": ["https://topostext.org/place/398183LIap"], "begin": "-750"}, "geometry": {"type": "Point", "coordinates": [18.36268, 39.79216]}}]}