{"type": "FeatureCollection", "id": "https://topostext.org/place/379125PMot", "name": "379125PMot", "features": [{"type": "Feature", "id": "http://data.archaeology.link/data/ancientports/1176", "name": "", "dateprops": ["begin"], "properties": {"http://purl.org/dc/elements/1.1/creator": ["http://data.archaeology.link/data/spphaefen/arthur_de_graauw"], "http://purl.org/dc/terms/isReferencedBy": ["https://www2.rgzm.de/navis2/home/frames.htm"], "http://purl.org/dc/terms/partOf": ["http://data.archaeology.link/data/ancientports/bib_deGrauw_2013_GeoDB"], "http://www.opengis.net/ont/geosparql#hasGeometry": ["http://data.archaeology.link/data/ancientports/1176_geom"], "http://www.w3.org/1999/02/22-rdf-syntax-ns#type": ["http://www.ancientports.com/ont#Quay"], "http://www.w3.org/2000/01/rdf-schema#label": ["Mozia, on the isle of San Pantaleo, a causeway connects the island to the continent, but the 52x37 m basin was not a port"], "http://www.w3.org/2002/07/owl#sameAs": ["http://www.wikidata.org/entity/Q962184"], "http://www.w3.org/2004/02/skos/core#note": ["Nigro (2013)"], "http://www.w3.org/2006/time#hasTime": ["http://data.archaeology.link/data/ancientports/1176_foundation"], "http://www.wikidata.org/prop/direct/P1584": ["http://pleiades.stoa.org/places/462373"], "http://www.wikidata.org/prop/direct/P17": ["http://www.wikidata.org/entity/Q38"], "http://www.wikidata.org/prop/direct/P1936": ["http://imperium.ahlfeldt.se/places/22634"], "http://www.wikidata.org/prop/direct/P1958": ["https://www.trismegistos.org/place/22326"], "http://www.wikidata.org/prop/direct/P8068": ["https://topostext.org/place/379125PMot"], "begin": "-750"}, "geometry": {"type": "Point", "coordinates": [12.466, 37.8635]}}], "numberMatched": 1, "numberReturned": 1, "bbox": [12.466, 37.8635, 12.466, 37.8635], "crs": "http://www.opengis.net/def/crs/EPSG/0/4326"}