{"type": "FeatureCollection", "id": "https://topostext.org/place/385235USal", "name": "385235USal", "features": [{"type": "Feature", "id": "http://data.archaeology.link/data/ancientports/1669", "name": "", "dateprops": ["begin"], "properties": {"http://purl.org/dc/elements/1.1/creator": ["http://data.archaeology.link/data/spphaefen/arthur_de_graauw"], "http://purl.org/dc/terms/partOf": ["http://data.archaeology.link/data/ancientports/bib_deGrauw_2013_GeoDB"], "http://rdfs.org/ns/void#inDataset": ["http://data.archaeology.link/data/ancientports/dataset"], "http://www.opengis.net/ont/geosparql#hasGeometry": ["http://data.archaeology.link/data/ancientports/1669_geom"], "http://www.w3.org/1999/02/22-rdf-syntax-ns#type": ["http://www.ancientports.com/ont#Harbour"], "http://www.w3.org/2000/01/rdf-schema#label": ["Panagitsa Drosias"], "http://www.w3.org/2002/07/owl#sameAs": ["http://www.wikidata.org/entity/Q16627937"], "http://www.w3.org/2006/time#hasTime": ["http://data.archaeology.link/data/ancientports/1669_foundation"], "http://www.wikidata.org/prop/direct/P1584": ["http://pleiades.stoa.org/places/541088"], "http://www.wikidata.org/prop/direct/P17": ["http://www.wikidata.org/entity/Q41"], "http://www.wikidata.org/prop/direct/P1936": ["http://imperium.ahlfeldt.se/places/29457"], "http://www.wikidata.org/prop/direct/P8068": ["https://topostext.org/place/385235USal"], "begin": "-550"}, "geometry": {"type": "Point", "coordinates": [23.51467, 38.48299]}}], "numberMatched": 1, "numberReturned": 1, "bbox": [23.51467, 38.48299, 23.51467, 38.48299], "crs": "http://www.opengis.net/def/crs/EPSG/0/4326"}