{"type": "FeatureCollection", "id": "http://www.wikidata.org/entity/Q393975", "name": "Q393975", "features": [{"type": "Feature", "id": "http://data.archaeology.link/data/ancientports/1810", "label": "Ormos Dhimitriaki", "properties": {"http://purl.org/dc/elements/1.1/created": ["2023"], "http://purl.org/dc/elements/1.1/creator": ["http://data.archaeology.link/data/spphaefen/arthur_de_graauw"], "http://www.opengis.net/ont/geosparql#hasGeometry": ["http://data.archaeology.link/data/ancientports/1810_geom"], "http://www.w3.org/1999/02/22-rdf-syntax-ns#type": ["http://www.ancientports.com/ont#Harbour", "http://www.ancientports.com/ont#PotentialHarbour"], "http://www.w3.org/2000/01/rdf-schema#label": ["Ormos Dhimitriaki"], "http://www.w3.org/2002/07/owl#sameAs": ["http://www.wikidata.org/entity/Q393975"], "http://www.wikidata.org/prop/direct/P17": ["GR: North-East"]}, "geometry": {"type": "Point", "coordinates": [23.75319, 40.22677]}}]}