{"type": "FeatureCollection", "id": "http://imperium.ahlfeldt.se/places/2103", "name": "2103", "features": [{"type": "Feature", "id": "http://data.archaeology.link/data/ancientports/31", "name": "submerged offshore of Oostvoorne, Brielse Meer, at outlet of R Oude Maas, Meuse", "dateprops": [], "properties": {"http://purl.org/dc/elements/1.1/creator": ["http://data.archaeology.link/data/spphaefen/arthur_de_graauw"], "http://purl.org/dc/terms/isReferencedBy": ["https://vici.org/vici/19216/"], "http://purl.org/dc/terms/partOf": ["http://data.archaeology.link/data/ancientports/bib_deGrauw_2013_GeoDB"], "http://www.opengis.net/ont/geosparql#hasGeometry": ["http://data.archaeology.link/data/ancientports/31_geom"], "http://www.w3.org/1999/02/22-rdf-syntax-ns#type": ["http://www.ancientports.com/ont#Harbour"], "http://www.w3.org/2000/01/rdf-schema#label": ["submerged offshore of Oostvoorne, Brielse Meer, at outlet of R Oude Maas, Meuse"], "http://www.w3.org/2002/07/owl#sameAs": ["http://www.wikidata.org/entity/Q1265889"], "http://www.w3.org/2004/02/skos/core#note": ["Lendering", "Zeeuws Museum (2018)"], "http://www.wikidata.org/prop/direct/P1584": ["https://pleiades.stoa.org/places/109180"], "http://www.wikidata.org/prop/direct/P17": ["http://www.wikidata.org/entity/Q55"], "http://www.wikidata.org/prop/direct/P1936": ["http://imperium.ahlfeldt.se/places/2103"], "begin": ""}, "geometry": {"type": "Point", "coordinates": [4.114, 51.931]}}], "numberMatched": 1, "numberReturned": 1, "bbox": [4.114, 51.931, 4.114, 51.931], "crs": "http://www.opengis.net/def/crs/EPSG/0/4326"}