{"type": "FeatureCollection", "id": "http://imperium.ahlfeldt.se/places/36206", "name": "36206", "features": [{"type": "Feature", "id": "http://data.archaeology.link/data/ancientports/3946", "label": "el-Kimo, about 30 km east of el-Alamein", "dateprops": [], "properties": {"http://purl.org/dc/elements/1.1/created": ["2023"], "http://purl.org/dc/elements/1.1/creator": ["http://data.archaeology.link/data/spphaefen/arthur_de_graauw"], "http://www.ancientports.com/ont#date_min": ["-330"], "http://www.opengis.net/ont/geosparql#hasGeometry": ["http://data.archaeology.link/data/ancientports/3946_geom"], "http://www.w3.org/1999/02/22-rdf-syntax-ns#type": ["http://www.ancientports.com/ont#Harbour"], "http://www.w3.org/2000/01/rdf-schema#label": ["el-Kimo, about 30 km east of el-Alamein"], "http://www.wikidata.org/prop/direct/P1584": ["http://pleiades.stoa.org/places/716544"], "http://www.wikidata.org/prop/direct/P17": ["Egypt: Med Sea"], "http://www.wikidata.org/prop/direct/P1936": ["http://imperium.ahlfeldt.se/places/36206"], "http://www.wikidata.org/prop/direct/P1958": ["https://www.trismegistos.org/place/8014"], "http://www.wikidata.org/prop/direct/P8068": ["https://topostext.org/place/308293UChe"]}, "geometry": {"type": "Point", "coordinates": [29.325, 30.877]}}]}