{"type": "FeatureCollection", "id": "http://www.wikidata.org/entity/Q46810", "name": "Campagna Lupia", "features": [{"type": "Feature", "id": "http://data.archaeology.link/data/ancientports/1330", "name": "Lova, near Campagna Lupia on R Bacchiglione", "dateprops": ["begin"], "properties": {"http://purl.org/dc/elements/1.1/created": ["2023"], "http://purl.org/dc/elements/1.1/creator": ["http://data.archaeology.link/data/spphaefen/arthur_de_graauw"], "http://www.opengis.net/ont/geosparql#hasGeometry": ["http://data.archaeology.link/data/ancientports/1330_geom"], "http://www.w3.org/1999/02/22-rdf-syntax-ns#type": ["http://www.ancientports.com/ont#Harbour"], "http://www.w3.org/2000/01/rdf-schema#label": ["Lova, near Campagna Lupia on R Bacchiglione"], "http://www.w3.org/2002/07/owl#sameAs": ["http://www.wikidata.org/entity/Q46810"], "http://www.w3.org/2006/time#hasTime": ["http://data.archaeology.link/data/ancientports/1330_foundation"], "http://www.wikidata.org/prop/direct/P1584": ["http://pleiades.stoa.org/places/393451"], "http://www.wikidata.org/prop/direct/P17": ["http://www.wikidata.org/entity/Q38"], "http://www.wikidata.org/prop/direct/P1936": ["http://imperium.ahlfeldt.se/places/23155"], "begin": "-30"}, "geometry": {"type": "Point", "coordinates": [12.09872, 45.33435]}}]}