{"type": "FeatureCollection", "id": "http://pleiades.stoa.org/places/707626", "name": "707626", "features": [{"type": "Feature", "id": "http://data.archaeology.link/data/ancientports/3069", "label": "Styllarka, at the outlet of R Xeros ", "properties": {"http://purl.org/dc/elements/1.1/created": ["2023"], "http://purl.org/dc/elements/1.1/creator": ["http://data.archaeology.link/data/spphaefen/arthur_de_graauw"], "http://www.ancientports.com/ont#date_min": ["-750"], "http://www.opengis.net/ont/geosparql#hasGeometry": ["http://data.archaeology.link/data/ancientports/3069_geom"], "http://www.w3.org/1999/02/22-rdf-syntax-ns#type": ["http://www.ancientports.com/ont#Harbour"], "http://www.w3.org/2000/01/rdf-schema#label": ["Styllarka, at the outlet of R Xeros "], "http://www.wikidata.org/prop/direct/P1584": ["http://pleiades.stoa.org/places/707626"], "http://www.wikidata.org/prop/direct/P17": ["Cyprus"]}, "geometry": {"type": "Point", "coordinates": [32.554, 34.7002]}}]}