{"type": "FeatureCollection", "id": "https://www.trismegistos.org/place/3362", "name": "3362", "features": [{"type": "Feature", "id": "http://data.archaeology.link/data/ancientports/1303", "label": "Ancona, on Lungomare Vanvitelli", "properties": {"http://purl.org/dc/elements/1.1/created": ["2023"], "http://purl.org/dc/elements/1.1/creator": ["http://data.archaeology.link/data/spphaefen/arthur_de_graauw"], "http://www.opengis.net/ont/geosparql#hasGeometry": ["http://data.archaeology.link/data/ancientports/1303_geom"], "http://www.w3.org/1999/02/22-rdf-syntax-ns#type": ["http://www.ancientports.com/ont#Harbour"], "http://www.w3.org/2000/01/rdf-schema#label": ["Ancona, on Lungomare Vanvitelli"], "http://www.w3.org/2002/07/owl#sameAs": ["http://www.wikidata.org/entity/Q3415"], "http://www.w3.org/2004/02/skos/core#note": ["Ciuccarelli (2021)"], "http://www.wikidata.org/prop/direct/P1584": ["http://pleiades.stoa.org/places/413014"], "http://www.wikidata.org/prop/direct/P17": ["Italy Adriatic"], "http://www.wikidata.org/prop/direct/P1958": ["https://www.trismegistos.org/place/3362"]}, "geometry": {"type": "Point", "coordinates": [13.5092, 43.6235]}}]}