{"type": "FeatureCollection", "id": "https://www.trismegistos.org/place/14925", "name": "14925", "features": [{"type": "Feature", "id": "http://data.archaeology.link/data/ancientports/72_1", "name": "Mucking", "dateprops": [], "properties": {"http://purl.org/dc/elements/1.1/created": ["2023"], "http://purl.org/dc/elements/1.1/creator": ["http://data.archaeology.link/data/spphaefen/arthur_de_graauw"], "http://www.opengis.net/ont/geosparql#hasGeometry": ["http://data.archaeology.link/data/ancientports/72_1_geom"], "http://www.w3.org/1999/02/22-rdf-syntax-ns#type": ["http://www.ancientports.com/ont#Harbour"], "http://www.w3.org/2000/01/rdf-schema#label": ["Mucking"], "http://www.w3.org/2002/07/owl#sameAs": ["http://www.wikidata.org/entity/Q6931178"], "http://www.wikidata.org/prop/direct/P17": ["http://www.wikidata.org/entity/Q145"], "http://www.wikidata.org/prop/direct/P1958": ["https://www.trismegistos.org/place/14925"], "begin": ""}, "geometry": {"type": "Point", "coordinates": [0.428, 51.504]}}]}