{"type": "FeatureCollection", "id": "http://pleiades.stoa.org/places/550415", "name": "550415", "features": [{"type": "Feature", "id": "http://data.archaeology.link/data/ancientports/2915", "label": "Kumkale promontory, now inland", "properties": {"http://purl.org/dc/elements/1.1/created": ["2023"], "http://purl.org/dc/elements/1.1/creator": ["http://data.archaeology.link/data/spphaefen/arthur_de_graauw"], "http://www.ancientports.com/ont#date_min": ["-30"], "http://www.opengis.net/ont/geosparql#hasGeometry": ["http://data.archaeology.link/data/ancientports/2915_geom"], "http://www.w3.org/1999/02/22-rdf-syntax-ns#type": ["http://www.ancientports.com/ont#Harbour"], "http://www.w3.org/2000/01/rdf-schema#label": ["Kumkale promontory, now inland"], "http://www.w3.org/2002/07/owl#sameAs": ["http://www.wikidata.org/entity/Q7321268"], "http://www.wikidata.org/prop/direct/P1584": ["http://pleiades.stoa.org/places/550415"], "http://www.wikidata.org/prop/direct/P17": ["TR: Marmara S"]}, "geometry": {"type": "Point", "coordinates": [26.232, 39.9815]}}]}