{"type": "FeatureCollection", "id": "http://www.wikidata.org/entity/Q923211", "name": "Q923211", "features": [{"type": "Feature", "id": "http://data.archaeology.link/data/ancientports/1585", "label": "Katoxi, Trikardo, now inland, on R Aspropotamos", "properties": {"http://purl.org/dc/elements/1.1/created": ["2023"], "http://purl.org/dc/elements/1.1/creator": ["http://data.archaeology.link/data/spphaefen/arthur_de_graauw"], "http://www.ancientports.com/ont#date_min": ["-550"], "http://www.opengis.net/ont/geosparql#hasGeometry": ["http://data.archaeology.link/data/ancientports/1585_geom"], "http://www.w3.org/1999/02/22-rdf-syntax-ns#type": ["http://www.ancientports.com/ont#Harbour"], "http://www.w3.org/2000/01/rdf-schema#label": ["Katoxi, Trikardo, now inland, on R Aspropotamos"], "http://www.w3.org/2002/07/owl#sameAs": ["http://www.wikidata.org/entity/Q923211"], "http://www.wikidata.org/prop/direct/P1584": ["http://pleiades.stoa.org/places/531016"], "http://www.wikidata.org/prop/direct/P17": ["GR: North-West"], "http://www.wikidata.org/prop/direct/P1958": ["https://www.trismegistos.org/place/37640"]}, "geometry": {"type": "Point", "coordinates": [21.20975, 38.39901]}}, {"type": "Feature", "id": "http://data.archaeology.link/data/ancientports/1584", "label": "Katoxi, Trikardo, now inland", "properties": {"http://purl.org/dc/elements/1.1/created": ["2023"], "http://purl.org/dc/elements/1.1/creator": ["http://data.archaeology.link/data/spphaefen/arthur_de_graauw"], "http://www.ancientports.com/ont#date_min": ["-550"], "http://www.opengis.net/ont/geosparql#hasGeometry": ["http://data.archaeology.link/data/ancientports/1584_geom"], "http://www.w3.org/1999/02/22-rdf-syntax-ns#type": ["http://www.ancientports.com/ont#Harbour"], "http://www.w3.org/2000/01/rdf-schema#label": ["Katoxi, Trikardo, now inland"], "http://www.w3.org/2002/07/owl#sameAs": ["http://www.wikidata.org/entity/Q923211"], "http://www.wikidata.org/prop/direct/P1584": ["http://pleiades.stoa.org/places/531016"], "http://www.wikidata.org/prop/direct/P17": ["GR: North-West"], "http://www.wikidata.org/prop/direct/P1958": ["https://www.trismegistos.org/place/37640"]}, "geometry": {"type": "Point", "coordinates": [21.19364, 38.41143]}}]}