{"type": "FeatureCollection", "id": "http://www.wikidata.org/entity/Q208587", "name": "Amorgos", "features": [{"type": "Feature", "id": "http://data.archaeology.link/data/ancientports/2110", "name": "Isle of Amorgos, Yamurgi", "dateprops": [], "properties": {"http://purl.org/dc/elements/1.1/created": ["2023"], "http://purl.org/dc/elements/1.1/creator": ["http://data.archaeology.link/data/spphaefen/arthur_de_graauw"], "http://www.opengis.net/ont/geosparql#hasGeometry": ["http://data.archaeology.link/data/ancientports/2110_geom"], "http://www.w3.org/1999/02/22-rdf-syntax-ns#type": ["http://www.ancientports.com/ont#Harbour"], "http://www.w3.org/2000/01/rdf-schema#label": ["Isle of Amorgos, Yamurgi"], "http://www.w3.org/2002/07/owl#sameAs": ["http://www.wikidata.org/entity/Q208587"], "http://www.wikidata.org/prop/direct/P1584": ["http://pleiades.stoa.org/places/599484"], "http://www.wikidata.org/prop/direct/P17": ["http://www.wikidata.org/entity/Q41"], "http://www.wikidata.org/prop/direct/P1936": ["http://imperium.ahlfeldt.se/places/41349"], "http://www.wikidata.org/prop/direct/P1958": ["https://www.trismegistos.org/place/3592"], "http://www.wikidata.org/prop/direct/P8068": ["https://topostext.org/place/368259IAmo"], "begin": ""}, "geometry": {"type": "Point", "coordinates": [25.89018, 36.83577]}}]}