{"type": "FeatureCollection", "id": "http://www.wikidata.org/entity/Q282350", "name": "Land of Punt", "features": [{"type": "Feature", "id": "http://data.archaeology.link/data/ancientports/3616", "name": "", "dateprops": [], "properties": {"http://purl.org/dc/elements/1.1/creator": ["http://data.archaeology.link/data/spphaefen/arthur_de_graauw"], "http://purl.org/dc/terms/isReferencedBy": ["http://data.archaeology.link/data/ancientports/bib_Glazer_2012_Solomon"], "http://purl.org/dc/terms/partOf": ["http://data.archaeology.link/data/ancientports/bib_deGrauw_2013_GeoDB"], "http://rdfs.org/ns/void#inDataset": ["http://data.archaeology.link/data/ancientports/dataset"], "http://www.opengis.net/ont/geosparql#hasGeometry": ["http://data.archaeology.link/data/ancientports/3616_geom"], "http://www.w3.org/1999/02/22-rdf-syntax-ns#type": ["http://www.ancientports.com/ont#Harbour"], "http://www.w3.org/2000/01/rdf-schema#label": ["Probably somewhere in East Africa, possibly in the area of the Afar people, between Adulis and Djibouti, on the location of the ancient D'mt (Da'amat) kingdom and close to the Kush kingdom and its gold mines, where they could also find silver, ivory, apes, and peacocks. Other possible locations for Punt are Mundus-Mosylium and Opone (Somalia)"], "http://www.w3.org/2002/07/owl#sameAs": ["http://www.wikidata.org/entity/Q282350"], "http://www.wikidata.org/prop/direct/P17": ["http://www.wikidata.org/entity/Q986"], "begin": ""}, "geometry": {"type": "Point", "coordinates": [39.25, 15.35]}}], "numberMatched": 1, "numberReturned": 1, "bbox": [39.25, 15.35, 39.25, 15.35], "crs": "http://www.opengis.net/def/crs/EPSG/0/4326"}