{"type": "FeatureCollection", "id": "http://www.wikidata.org/entity/Q7697545", "name": "Tell es-Sakan", "features": [{"type": "Feature", "id": "http://data.archaeology.link/data/ancientports/3510", "name": "Tell es-Sakan, near  on wadi Gaza, Ghazzeh", "dateprops": ["begin"], "properties": {"http://purl.org/dc/elements/1.1/creator": ["http://data.archaeology.link/data/spphaefen/arthur_de_graauw"], "http://purl.org/dc/terms/isReferencedBy": ["http://data.archaeology.link/data/ancientports/bib_Andreou_2022_Exploring"], "http://purl.org/dc/terms/partOf": ["http://data.archaeology.link/data/ancientports/bib_deGrauw_2013_GeoDB"], "http://www.opengis.net/ont/geosparql#hasGeometry": ["http://data.archaeology.link/data/ancientports/3510_geom"], "http://www.w3.org/1999/02/22-rdf-syntax-ns#type": ["http://www.ancientports.com/ont#Harbour"], "http://www.w3.org/2000/01/rdf-schema#label": ["Tell es-Sakan, near  on wadi Gaza, Ghazzeh"], "http://www.w3.org/2002/07/owl#sameAs": ["http://www.wikidata.org/entity/Q7697545"], "http://www.w3.org/2004/02/skos/core#note": ["Morhange (2005)"], "http://www.w3.org/2006/time#hasTime": ["http://data.archaeology.link/data/ancientports/3510_foundation"], "http://www.wikidata.org/prop/direct/P17": ["http://www.wikidata.org/entity/Q39760"], "begin": "-3000"}, "geometry": {"type": "Point", "coordinates": [34.4049, 31.4748]}}], "numberMatched": 1, "numberReturned": 1, "bbox": [34.4049, 31.4748, 34.4049, 31.4748], "crs": "http://www.opengis.net/def/crs/EPSG/0/4326"}