{"type": "FeatureCollection", "id": "http://imperium.ahlfeldt.se/places/26040", "name": "26040", "features": [{"type": "Feature", "id": "http://data.archaeology.link/data/ancientports/86", "name": "Roman villa at Sidlesham, near Pagham", "dateprops": ["begin"], "properties": {"http://purl.org/dc/elements/1.1/created": ["2023"], "http://purl.org/dc/elements/1.1/creator": ["http://data.archaeology.link/data/spphaefen/arthur_de_graauw"], "http://purl.org/dc/terms/isReferencedBy": ["http://data.archaeology.link/data/ancientports/bib_Wilkes_2004_Iron"], "http://www.opengis.net/ont/geosparql#hasGeometry": ["http://data.archaeology.link/data/ancientports/86_geom"], "http://www.w3.org/1999/02/22-rdf-syntax-ns#type": ["http://www.ancientports.com/ont#VillaMaritima"], "http://www.w3.org/2000/01/rdf-schema#label": ["Roman villa at Sidlesham, near Pagham"], "http://www.w3.org/2002/07/owl#sameAs": ["http://www.wikidata.org/entity/Q2242263"], "http://www.w3.org/2006/time#hasTime": ["http://data.archaeology.link/data/ancientports/86_foundation"], "http://www.wikidata.org/prop/direct/P17": ["http://www.wikidata.org/entity/Q145"], "http://www.wikidata.org/prop/direct/P1936": ["http://imperium.ahlfeldt.se/places/26040"], "begin": "5001"}, "geometry": {"type": "Point", "coordinates": [-0.7894, 50.7665]}}]}