{"type": "FeatureCollection", "id": "http://www.wikidata.org/entity/Q3682385", "name": "Q3682385", "features": [{"type": "Feature", "id": "http://data.archaeology.link/data/ancientports/159", "label": "Drumburgh Roman fort, on the Firth of Solway", "dateprops": [], "properties": {"http://purl.org/dc/elements/1.1/created": ["2023"], "http://purl.org/dc/elements/1.1/creator": ["http://data.archaeology.link/data/spphaefen/arthur_de_graauw"], "http://purl.org/dc/terms/isReferencedBy": ["https://historicengland.org.uk/listing/the-list/list-entry/1014699"], "http://www.opengis.net/ont/geosparql#hasGeometry": ["http://data.archaeology.link/data/ancientports/159_geom"], "http://www.w3.org/1999/02/22-rdf-syntax-ns#type": ["http://www.ancientports.com/ont#Harbour"], "http://www.w3.org/2000/01/rdf-schema#label": ["Drumburgh Roman fort, on the Firth of Solway"], "http://www.w3.org/2002/07/owl#sameAs": ["http://www.wikidata.org/entity/Q3682385"], "http://www.w3.org/2006/time#hasTime": ["http://data.archaeology.link/data/ancientports/159_foundation"], "http://www.wikidata.org/prop/direct/P1584": ["http://pleiades.stoa.org/places/89151"], "http://www.wikidata.org/prop/direct/P17": ["http://www.wikidata.org/entity/Q145"], "http://www.wikidata.org/prop/direct/P1936": ["http://imperium.ahlfeldt.se/places/23750"], "http://www.wikidata.org/prop/direct/P1958": ["https://www.trismegistos.org/place/15248"]}, "geometry": {"type": "Point", "coordinates": [-3.14894, 54.9281]}}]}