{"type": "FeatureCollection", "id": "http://www.wikidata.org/entity/Q216878", "name": "Lastovo", "features": [{"type": "Feature", "id": "http://data.archaeology.link/data/ancientports/1495_1", "name": "Barje, on the isle of Lastovo", "dateprops": ["begin"], "properties": {"http://purl.org/dc/elements/1.1/creator": ["http://data.archaeology.link/data/spphaefen/arthur_de_graauw"], "http://purl.org/dc/terms/isReferencedBy": ["http://baza.iarh.hr/public/locality/detail/1561"], "http://purl.org/dc/terms/partOf": ["http://data.archaeology.link/data/ancientports/bib_deGrauw_2013_GeoDB"], "http://www.opengis.net/ont/geosparql#hasGeometry": ["http://data.archaeology.link/data/ancientports/1495_1_geom"], "http://www.w3.org/1999/02/22-rdf-syntax-ns#type": ["http://www.ancientports.com/ont#Harbour"], "http://www.w3.org/2000/01/rdf-schema#label": ["Barje, on the isle of Lastovo"], "http://www.w3.org/2002/07/owl#sameAs": ["http://www.wikidata.org/entity/Q216878"], "http://www.w3.org/2006/time#hasTime": ["http://data.archaeology.link/data/ancientports/1495_1_foundation"], "http://www.wikidata.org/prop/direct/P17": ["http://www.wikidata.org/entity/Q224"], "begin": "3001"}, "geometry": {"type": "Point", "coordinates": [16.9374, 42.7619]}}], "numberMatched": 1, "numberReturned": 1, "bbox": [16.9374, 42.7619, 16.9374, 42.7619], "crs": "http://www.opengis.net/def/crs/OGC/1.3/CRS84"}