{"type": "FeatureCollection", "id": "http://pleiades.stoa.org/places/432839", "name": "432839", "features": [{"type": "Feature", "id": "http://data.archaeology.link/data/ancientports/965", "name": "Roman villa Comunale at Formia", "dateprops": [], "properties": {"http://purl.org/dc/elements/1.1/creator": ["http://data.archaeology.link/data/spphaefen/arthur_de_graauw"], "http://purl.org/dc/terms/partOf": ["http://data.archaeology.link/data/ancientports/bib_deGrauw_2013_GeoDB"], "http://www.opengis.net/ont/geosparql#hasGeometry": ["http://data.archaeology.link/data/ancientports/965_geom"], "http://www.w3.org/1999/02/22-rdf-syntax-ns#type": ["http://www.ancientports.com/ont#VillaMaritima"], "http://www.w3.org/2000/01/rdf-schema#label": ["Roman villa Comunale at Formia"], "http://www.w3.org/2002/07/owl#sameAs": ["http://www.wikidata.org/entity/Q128086"], "http://www.wikidata.org/prop/direct/P1584": ["http://pleiades.stoa.org/places/432839"], "http://www.wikidata.org/prop/direct/P17": ["http://www.wikidata.org/entity/Q38"], "http://www.wikidata.org/prop/direct/P1958": ["https://www.trismegistos.org/place/32462"], "http://www.wikidata.org/prop/direct/P8068": ["https://topostext.org/place/413136UFor"], "begin": ""}, "geometry": {"type": "Point", "coordinates": [13.60878, 41.25546]}}, {"type": "Feature", "id": "http://data.archaeology.link/data/ancientports/964", "name": "Roman villa Sarinola at Formia", "dateprops": ["begin"], "properties": {"http://purl.org/dc/elements/1.1/creator": ["http://data.archaeology.link/data/spphaefen/arthur_de_graauw"], "http://purl.org/dc/terms/partOf": ["http://data.archaeology.link/data/ancientports/bib_deGrauw_2013_GeoDB"], "http://www.opengis.net/ont/geosparql#hasGeometry": ["http://data.archaeology.link/data/ancientports/964_geom"], "http://www.w3.org/1999/02/22-rdf-syntax-ns#type": ["http://www.ancientports.com/ont#Quay", "http://www.ancientports.com/ont#VillaMaritima"], "http://www.w3.org/2000/01/rdf-schema#label": ["Roman villa Sarinola at Formia"], "http://www.w3.org/2002/07/owl#sameAs": ["http://www.wikidata.org/entity/Q128086"], "http://www.w3.org/2006/time#hasTime": ["http://data.archaeology.link/data/ancientports/964_foundation"], "http://www.wikidata.org/prop/direct/P1584": ["http://pleiades.stoa.org/places/432839"], "http://www.wikidata.org/prop/direct/P17": ["http://www.wikidata.org/entity/Q38"], "http://www.wikidata.org/prop/direct/P1936": ["http://imperium.ahlfeldt.se/places/16716"], "http://www.wikidata.org/prop/direct/P1958": ["https://www.trismegistos.org/place/32462"], "http://www.wikidata.org/prop/direct/P8068": ["https://topostext.org/place/413136UFor"], "begin": "-330"}, "geometry": {"type": "Point", "coordinates": [13.60604, 41.25323]}}], "numberMatched": 2, "numberReturned": 2}