{"type": "FeatureCollection", "id": "https://www.trismegistos.org/place/17560", "name": "17560", "features": [{"type": "Feature", "id": "http://data.archaeology.link/data/ancientports/4189", "label": "Bizerte, although no archaeological evidence was found, it is suggested the present fishing port is the archaic port because of Dio Cassius' story", "properties": {"http://purl.org/dc/elements/1.1/created": ["2023"], "http://purl.org/dc/elements/1.1/creator": ["http://data.archaeology.link/data/spphaefen/arthur_de_graauw"], "http://www.opengis.net/ont/geosparql#hasGeometry": ["http://data.archaeology.link/data/ancientports/4189_geom"], "http://www.w3.org/1999/02/22-rdf-syntax-ns#type": ["http://www.ancientports.com/ont#Harbour"], "http://www.w3.org/2000/01/rdf-schema#label": ["Bizerte, although no archaeological evidence was found, it is suggested the present fishing port is the archaic port because of Dio Cassius' story"], "http://www.w3.org/2002/07/owl#sameAs": ["http://www.wikidata.org/entity/Q189546"], "http://www.wikidata.org/prop/direct/P1584": ["http://pleiades.stoa.org/places/315038"], "http://www.wikidata.org/prop/direct/P17": ["Tunisia"], "http://www.wikidata.org/prop/direct/P1958": ["https://www.trismegistos.org/place/17560"]}, "geometry": {"type": "Point", "coordinates": [9.8749, 37.2773]}}]}