{"type": "FeatureCollection", "id": "http://pleiades.stoa.org/places/648719", "name": "648719", "features": [{"type": "Feature", "id": "http://data.archaeology.link/data/ancientports/3338", "label": "Cokkilise, near Seki", "dateprops": ["http://purl.org/dc/elements/1.1/created", "http://www.ancientports.com/ont#date_min"], "properties": {"http://purl.org/dc/elements/1.1/created": ["2023"], "http://purl.org/dc/elements/1.1/creator": ["http://data.archaeology.link/data/spphaefen/arthur_de_graauw"], "http://www.ancientports.com/ont#date_min": ["-30"], "http://www.opengis.net/ont/geosparql#hasGeometry": ["http://data.archaeology.link/data/ancientports/3338_geom"], "http://www.w3.org/1999/02/22-rdf-syntax-ns#type": ["http://www.ancientports.com/ont#Harbour"], "http://www.w3.org/2000/01/rdf-schema#label": ["Cokkilise, near Seki"], "http://www.w3.org/2002/07/owl#sameAs": ["http://www.wikidata.org/entity/Q65122854"], "http://www.w3.org/2004/02/skos/core#note": ["Oniz (2012)"], "http://www.wikidata.org/prop/direct/P1584": ["http://pleiades.stoa.org/places/648719"], "http://www.wikidata.org/prop/direct/P17": ["TR: South"], "http://www.wikidata.org/prop/direct/P1936": ["http://imperium.ahlfeldt.se/places/22052"], "http://www.wikidata.org/prop/direct/P1958": ["https://www.trismegistos.org/place/34273"], "http://www.wikidata.org/prop/direct/P8068": ["https://topostext.org/place/364321USye"]}, "geometry": {"type": "Point", "coordinates": [32.1442, 36.4322]}}]}