{"type": "FeatureCollection", "id": "http://imperium.ahlfeldt.se/places/41662", "name": "41662", "features": [{"type": "Feature", "id": "http://data.archaeology.link/data/ancientports/804", "label": "Cala Gavetta, on Isla La Maddalena", "dateprops": ["http://purl.org/dc/elements/1.1/created"], "properties": {"http://purl.org/dc/elements/1.1/created": ["2023"], "http://purl.org/dc/elements/1.1/creator": ["http://data.archaeology.link/data/spphaefen/arthur_de_graauw"], "http://www.opengis.net/ont/geosparql#hasGeometry": ["http://data.archaeology.link/data/ancientports/804_geom"], "http://www.w3.org/1999/02/22-rdf-syntax-ns#type": ["http://www.ancientports.com/ont#Harbour", "http://www.ancientports.com/ont#PotentialHarbour"], "http://www.w3.org/2000/01/rdf-schema#label": ["Cala Gavetta, on Isla La Maddalena"], "http://www.w3.org/2002/07/owl#sameAs": ["http://www.wikidata.org/entity/Q340757"], "http://www.wikidata.org/prop/direct/P1584": ["http://pleiades.stoa.org/places/471952"], "http://www.wikidata.org/prop/direct/P17": ["Italy Sardinia"], "http://www.wikidata.org/prop/direct/P1936": ["http://imperium.ahlfeldt.se/places/41662"]}, "geometry": {"type": "Point", "coordinates": [9.40402, 41.21205]}}]}