{"type": "FeatureCollection", "id": "http://www.wikidata.org/entity/Q922", "name": "Q922", "features": [{"type": "Feature", "id": "http://data.archaeology.link/data/ancientports/1463", "label": "Uvala Luka, on the isle of Brac", "dateprops": ["http://purl.org/dc/elements/1.1/created"], "properties": {"http://purl.org/dc/elements/1.1/created": ["2023"], "http://purl.org/dc/elements/1.1/creator": ["http://data.archaeology.link/data/spphaefen/arthur_de_graauw"], "http://purl.org/dc/terms/isReferencedBy": ["http://baza.iarh.hr/public/locality/detail/1385"], "http://www.opengis.net/ont/geosparql#hasGeometry": ["http://data.archaeology.link/data/ancientports/1463_geom"], "http://www.w3.org/1999/02/22-rdf-syntax-ns#type": ["http://www.ancientports.com/ont#Harbour"], "http://www.w3.org/2000/01/rdf-schema#label": ["Uvala Luka, on the isle of Brac"], "http://www.w3.org/2002/07/owl#sameAs": ["http://www.wikidata.org/entity/Q922"], "http://www.wikidata.org/prop/direct/P17": ["http://www.wikidata.org/entity/Q224"]}, "geometry": {"type": "Point", "coordinates": [16.79767, 43.33928]}}, {"type": "Feature", "id": "http://data.archaeology.link/data/ancientports/1462", "label": "Lovrecina, on the isle of Brac", "dateprops": ["http://purl.org/dc/elements/1.1/created"], "properties": {"http://purl.org/dc/elements/1.1/created": ["2023"], "http://purl.org/dc/elements/1.1/creator": ["http://data.archaeology.link/data/spphaefen/arthur_de_graauw"], "http://purl.org/dc/terms/isReferencedBy": ["http://baza.iarh.hr/public/locality/detail/623", "https://bestofbrac.com/brac-culture/short-history-island/"], "http://www.opengis.net/ont/geosparql#hasGeometry": ["http://data.archaeology.link/data/ancientports/1462_geom"], "http://www.w3.org/1999/02/22-rdf-syntax-ns#type": ["http://www.ancientports.com/ont#Harbour"], "http://www.w3.org/2000/01/rdf-schema#label": ["Lovrecina, on the isle of Brac"], "http://www.w3.org/2002/07/owl#sameAs": ["http://www.wikidata.org/entity/Q922"], "http://www.wikidata.org/prop/direct/P17": ["http://www.wikidata.org/entity/Q224"]}, "geometry": {"type": "Point", "coordinates": [16.66642, 43.37134]}}, {"type": "Feature", "id": "http://data.archaeology.link/data/ancientports/1465", "label": "Uvala Rasotica, on the isle of Bra\u00e7", "dateprops": ["http://purl.org/dc/elements/1.1/created"], "properties": {"http://purl.org/dc/elements/1.1/created": ["2023"], "http://purl.org/dc/elements/1.1/creator": ["http://data.archaeology.link/data/spphaefen/arthur_de_graauw"], "http://www.opengis.net/ont/geosparql#hasGeometry": ["http://data.archaeology.link/data/ancientports/1465_geom"], "http://www.w3.org/1999/02/22-rdf-syntax-ns#type": ["http://www.ancientports.com/ont#Harbour", "http://www.ancientports.com/ont#PotentialHarbour"], "http://www.w3.org/2000/01/rdf-schema#label": ["Uvala Rasotica, on the isle of Brac", "Uvala Rasotica, on the isle of Bra\u00e7"], "http://www.w3.org/2002/07/owl#sameAs": ["http://www.wikidata.org/entity/Q922"], "http://www.wikidata.org/prop/direct/P17": ["http://www.wikidata.org/entity/Q224"]}, "geometry": {"type": "Point", "coordinates": [16.88588, 43.30775]}}]}