{"type": "FeatureCollection", "id": "https://topostext.org/place/369307PAtt", "name": "369307PAtt", "features": [{"type": "Feature", "id": "http://data.archaeology.link/data/ancientports/3319", "label": "Antalya", "dateprops": [], "properties": {"http://purl.org/dc/elements/1.1/created": ["2023"], "http://purl.org/dc/elements/1.1/creator": ["http://data.archaeology.link/data/spphaefen/arthur_de_graauw"], "http://purl.org/dc/terms/isReferencedBy": ["http://www.turkeytravelplanner.com/go/med/Antalya/sights/harbor.html"], "http://www.opengis.net/ont/geosparql#hasGeometry": ["http://data.archaeology.link/data/ancientports/3319_geom"], "http://www.w3.org/1999/02/22-rdf-syntax-ns#type": ["http://www.ancientports.com/ont#Lighthouse"], "http://www.w3.org/2000/01/rdf-schema#label": ["Antalya"], "http://www.w3.org/2002/07/owl#sameAs": ["http://www.wikidata.org/entity/Q6487"], "http://www.w3.org/2006/time#hasTime": ["http://data.archaeology.link/data/ancientports/3319_foundation"], "http://www.wikidata.org/prop/direct/P1584": ["http://pleiades.stoa.org/places/638778"], "http://www.wikidata.org/prop/direct/P17": ["http://www.wikidata.org/entity/Q43"], "http://www.wikidata.org/prop/direct/P1936": ["http://imperium.ahlfeldt.se/places/21502"], "http://www.wikidata.org/prop/direct/P1958": ["https://www.trismegistos.org/place/16422"], "http://www.wikidata.org/prop/direct/P8068": ["https://topostext.org/place/369307PAtt"]}, "geometry": {"type": "Point", "coordinates": [30.7023, 36.8844]}}]}