{"type": "FeatureCollection", "id": "http://imperium.ahlfeldt.se/places/27974", "name": "27974", "features": [{"type": "Feature", "id": "http://data.archaeology.link/data/ancientports/2522", "label": "near Trapivka, near Tartarbournary", "properties": {"http://purl.org/dc/elements/1.1/created": ["2023"], "http://purl.org/dc/elements/1.1/creator": ["http://data.archaeology.link/data/spphaefen/arthur_de_graauw"], "http://www.ancientports.com/ont#date_min": ["-330"], "http://www.opengis.net/ont/geosparql#hasGeometry": ["http://data.archaeology.link/data/ancientports/2522_geom"], "http://www.w3.org/1999/02/22-rdf-syntax-ns#type": ["http://www.ancientports.com/ont#Harbour"], "http://www.w3.org/2000/01/rdf-schema#label": ["near Trapivka, near Tartarbournary"], "http://www.wikidata.org/prop/direct/P1584": ["http://pleiades.stoa.org/places/226772"], "http://www.wikidata.org/prop/direct/P17": ["Ukraine Black S."], "http://www.wikidata.org/prop/direct/P1936": ["http://imperium.ahlfeldt.se/places/27974"]}, "geometry": {"type": "Point", "coordinates": [29.68225, 45.78751]}}]}