{"type": "FeatureCollection", "id": "https://topostext.org/place/378238IPha", "name": "378238IPha", "features": [{"type": "Feature", "id": "http://data.archaeology.link/data/ancientports/1635", "label": "Isle of Fleves", "dateprops": [], "properties": {"http://purl.org/dc/elements/1.1/created": ["2023"], "http://purl.org/dc/elements/1.1/creator": ["http://data.archaeology.link/data/spphaefen/arthur_de_graauw"], "http://www.opengis.net/ont/geosparql#hasGeometry": ["http://data.archaeology.link/data/ancientports/1635_geom"], "http://www.w3.org/1999/02/22-rdf-syntax-ns#type": ["http://www.ancientports.com/ont#Harbour"], "http://www.w3.org/2000/01/rdf-schema#label": ["Isle of Fleves"], "http://www.wikidata.org/prop/direct/P1584": ["http://pleiades.stoa.org/places/580069"], "http://www.wikidata.org/prop/direct/P17": ["http://www.wikidata.org/entity/Q41"], "http://www.wikidata.org/prop/direct/P1936": ["http://imperium.ahlfeldt.se/places/41361"], "http://www.wikidata.org/prop/direct/P1958": ["https://www.trismegistos.org/place/60752"], "http://www.wikidata.org/prop/direct/P8068": ["https://topostext.org/place/378238IPha"]}, "geometry": {"type": "Point", "coordinates": [23.76264, 37.7704]}}]}