{"type": "FeatureCollection", "id": "http://imperium.ahlfeldt.se/places/18811", "name": "18811", "features": [{"type": "Feature", "id": "http://data.archaeology.link/data/ancientports/522", "label": "Camp de Cesar, Oppidum at Sandouville", "properties": {"http://purl.org/dc/elements/1.1/created": ["2023"], "http://purl.org/dc/elements/1.1/creator": ["http://data.archaeology.link/data/spphaefen/arthur_de_graauw"], "http://www.ancientports.com/ont#date_min": ["-30"], "http://www.opengis.net/ont/geosparql#hasGeometry": ["http://data.archaeology.link/data/ancientports/522_geom"], "http://www.w3.org/1999/02/22-rdf-syntax-ns#type": ["http://www.ancientports.com/ont#Harbour"], "http://www.w3.org/2000/01/rdf-schema#label": ["Camp de Cesar, Oppidum at Sandouville"], "http://www.w3.org/2002/07/owl#sameAs": ["http://www.wikidata.org/entity/Q752926"], "http://www.wikidata.org/prop/direct/P17": ["France West"], "http://www.wikidata.org/prop/direct/P1936": ["http://imperium.ahlfeldt.se/places/18811"]}, "geometry": {"type": "Point", "coordinates": [0.30773, 49.49359]}}]}