{"type": "FeatureCollection", "id": "http://pleiades.stoa.org/places/511366", "name": "511366", "features": [{"type": "Feature", "id": "http://data.archaeology.link/data/ancientports/2888", "label": "Kursunlu Manastir", "dateprops": [], "properties": {"http://purl.org/dc/elements/1.1/created": ["2023"], "http://purl.org/dc/elements/1.1/creator": ["http://data.archaeology.link/data/spphaefen/arthur_de_graauw"], "http://www.opengis.net/ont/geosparql#hasGeometry": ["http://data.archaeology.link/data/ancientports/2888_geom"], "http://www.w3.org/1999/02/22-rdf-syntax-ns#type": ["http://www.ancientports.com/ont#Harbour"], "http://www.w3.org/2000/01/rdf-schema#label": ["Kursunlu Manastir"], "http://www.w3.org/2002/07/owl#sameAs": ["http://www.wikidata.org/entity/Q17625216"], "http://www.w3.org/2004/02/skos/core#note": ["G\u00fcnd\u00fcz (2015)"], "http://www.w3.org/2006/time#hasTime": ["http://data.archaeology.link/data/ancientports/2888_foundation"], "http://www.wikidata.org/prop/direct/P1584": ["http://pleiades.stoa.org/places/511366"], "http://www.wikidata.org/prop/direct/P17": ["TR: Marmara S"], "http://www.wikidata.org/prop/direct/P1936": ["http://imperium.ahlfeldt.se/places/31417"], "http://www.wikidata.org/prop/direct/P1958": ["https://www.trismegistos.org/place/56117"], "http://www.wikidata.org/prop/direct/P8068": ["https://topostext.org/place/404283UPla"]}, "geometry": {"type": "Point", "coordinates": [28.2697, 40.4009]}}]}