{"type": "FeatureCollection", "id": "http://www.wikidata.org/entity/Q1229367", "name": "Q1229367", "features": [{"type": "Feature", "id": "http://data.archaeology.link/data/ancientports/448", "label": "Empuries, Ampurias, sheltered by Las Muscleres Grosses islets (NB: the structure on the beach is not a breakwater but a part of the ancient city wall)", "dateprops": ["http://purl.org/dc/elements/1.1/created", "http://www.ancientports.com/ont#date_min"], "properties": {"http://purl.org/dc/elements/1.1/created": ["2023"], "http://purl.org/dc/elements/1.1/creator": ["http://data.archaeology.link/data/spphaefen/arthur_de_graauw"], "http://www.ancientports.com/ont#date_min": ["-575"], "http://www.opengis.net/ont/geosparql#hasGeometry": ["http://data.archaeology.link/data/ancientports/448_geom"], "http://www.w3.org/1999/02/22-rdf-syntax-ns#type": ["http://www.ancientports.com/ont#Warehouse"], "http://www.w3.org/2000/01/rdf-schema#label": ["Empuries, Ampurias, sheltered by Las Muscleres Grosses islets (NB: the structure on the beach is not a breakwater but a part of the ancient city wall)"], "http://www.w3.org/2002/07/owl#sameAs": ["http://www.wikidata.org/entity/Q1229367"], "http://www.w3.org/2004/02/skos/core#note": ["Bony (2011)", "Castanyer (2021)"], "http://www.wikidata.org/prop/direct/P1584": ["http://pleiades.stoa.org/places/246382"], "http://www.wikidata.org/prop/direct/P17": ["http://www.wikidata.org/entity/Q29"], "http://www.wikidata.org/prop/direct/P1936": ["http://imperium.ahlfeldt.se/places/18301"], "http://www.wikidata.org/prop/direct/P1958": ["https://www.trismegistos.org/place/27282"], "http://www.wikidata.org/prop/direct/P8068": ["https://topostext.org/place/421031PEmp"]}, "geometry": {"type": "Point", "coordinates": [3.12247, 42.13594]}}]}