{"type": "FeatureCollection", "id": "https://www.trismegistos.org/place/19731", "name": "19731", "features": [{"type": "Feature", "id": "http://data.archaeology.link/data/ancientports/1", "name": "Iceland? Pliny and Strabo, who cite Pytheas (ca 325 BC?), place Thule at 6 navigation days from (Great) Britain, which may be 400-600 nautical miles. Iceland is at 450 miles north of Scotland. The mention of six months long days and nights means a position beyond the Arctic Circle, which corresponds better to Iceland than to the Shetland islands.", "dateprops": [], "properties": {"http://purl.org/dc/elements/1.1/creator": ["http://data.archaeology.link/data/spphaefen/arthur_de_graauw"], "http://purl.org/dc/terms/partOf": ["http://data.archaeology.link/data/ancientports/bib_deGrauw_2013_GeoDB"], "http://www.opengis.net/ont/geosparql#hasGeometry": ["http://data.archaeology.link/data/ancientports/1_geom"], "http://www.w3.org/1999/02/22-rdf-syntax-ns#type": ["http://www.ancientports.com/ont#Harbour"], "http://www.w3.org/2000/01/rdf-schema#label": ["Iceland? Pliny and Strabo, who cite Pytheas (ca 325 BC?), place Thule at 6 navigation days from (Great) Britain, which may be 400-600 nautical miles. Iceland is at 450 miles north of Scotland. The mention of six months long days and nights means a position beyond the Arctic Circle, which corresponds better to Iceland than to the Shetland islands."], "http://www.w3.org/2002/07/owl#sameAs": ["http://www.wikidata.org/entity/Q671008"], "http://www.w3.org/2004/02/skos/core#note": ["Journes (2000)"], "http://www.wikidata.org/prop/direct/P1584": ["https://pleiades.stoa.org/places/20624"], "http://www.wikidata.org/prop/direct/P17": ["Iceland?"], "http://www.wikidata.org/prop/direct/P1958": ["https://www.trismegistos.org/place/19731"], "http://www.wikidata.org/prop/direct/P8068": ["https://topostext.org/place/000000UThu"], "begin": ""}, "geometry": {"type": "Point", "coordinates": [-14.76131, 63.27477]}}], "numberMatched": 1, "numberReturned": 1}