{"type": "FeatureCollection", "id": "https://www.trismegistos.org/place/1358", "name": "1358", "features": [{"type": "Feature", "id": "http://data.archaeology.link/data/ancientports/3915_4", "label": "Submerged city in the bay of Abu Qir", "dateprops": [], "properties": {"http://purl.org/dc/elements/1.1/created": ["2023"], "http://purl.org/dc/elements/1.1/creator": ["http://data.archaeology.link/data/spphaefen/arthur_de_graauw"], "http://purl.org/dc/terms/isReferencedBy": ["https://www.franckgoddio.org/"], "http://www.opengis.net/ont/geosparql#hasGeometry": ["http://data.archaeology.link/data/ancientports/3915_4_geom"], "http://www.w3.org/1999/02/22-rdf-syntax-ns#type": ["http://www.ancientports.com/ont#Harbour"], "http://www.w3.org/2000/01/rdf-schema#label": ["Submerged city in the bay of Abu Qir"], "http://www.w3.org/2002/07/owl#sameAs": ["http://www.wikidata.org/entity/Q1492594"], "http://www.w3.org/2004/02/skos/core#note": ["Goddio (2015)"], "http://www.w3.org/2006/time#hasTime": ["http://data.archaeology.link/data/ancientports/3915_4_foundation"], "http://www.wikidata.org/prop/direct/P1584": ["http://pleiades.stoa.org/places/727162"], "http://www.wikidata.org/prop/direct/P17": ["http://www.wikidata.org/entity/Q79"], "http://www.wikidata.org/prop/direct/P1936": ["http://imperium.ahlfeldt.se/places/28493"], "http://www.wikidata.org/prop/direct/P1958": ["https://www.trismegistos.org/place/1358"], "http://www.wikidata.org/prop/direct/P8068": ["https://topostext.org/place/313300UMen"]}, "geometry": {"type": "Point", "coordinates": [30.088, 31.3162]}}]}