{"type": "FeatureCollection", "id": "https://www.trismegistos.org/place/33688", "name": "33688", "features": [{"type": "Feature", "id": "http://data.archaeology.link/data/ancientports/2241", "label": "Agios Petros, on the isle of Kyra Panagia, Pelagonisi", "dateprops": ["http://purl.org/dc/elements/1.1/created", "http://www.ancientports.com/ont#date_min"], "properties": {"http://purl.org/dc/elements/1.1/created": ["2023"], "http://purl.org/dc/elements/1.1/creator": ["http://data.archaeology.link/data/spphaefen/arthur_de_graauw"], "http://www.ancientports.com/ont#date_min": ["-5000"], "http://www.opengis.net/ont/geosparql#hasGeometry": ["http://data.archaeology.link/data/ancientports/2241_geom"], "http://www.w3.org/1999/02/22-rdf-syntax-ns#type": ["http://www.ancientports.com/ont#Harbour"], "http://www.w3.org/2000/01/rdf-schema#label": ["Agios Petros, on the isle of Kyra Panagia, Pelagonisi"], "http://www.w3.org/2004/02/skos/core#note": ["Carlson (2013)"], "http://www.wikidata.org/prop/direct/P17": ["GR: Eastern Isl."], "http://www.wikidata.org/prop/direct/P1958": ["https://www.trismegistos.org/place/33688"], "http://www.wikidata.org/prop/direct/P8068": ["https://topostext.org/place/393241XAPe"]}, "geometry": {"type": "Point", "coordinates": [24.0551, 39.3216]}}]}