{"type": "FeatureCollection", "id": "http://www.wikidata.org/entity/Q183405", "name": "Q183405", "features": [{"type": "Feature", "id": "http://data.archaeology.link/data/ancientports/4336", "label": "Safi", "properties": {"http://purl.org/dc/elements/1.1/created": ["2023"], "http://purl.org/dc/elements/1.1/creator": ["http://data.archaeology.link/data/spphaefen/arthur_de_graauw"], "http://www.opengis.net/ont/geosparql#hasGeometry": ["http://data.archaeology.link/data/ancientports/4336_geom"], "http://www.w3.org/1999/02/22-rdf-syntax-ns#type": ["http://www.ancientports.com/ont#Harbour"], "http://www.w3.org/2000/01/rdf-schema#label": ["Safi"], "http://www.w3.org/2002/07/owl#sameAs": ["http://www.wikidata.org/entity/Q183405"], "http://www.wikidata.org/prop/direct/P17": ["Morocco"]}, "geometry": {"type": "Point", "coordinates": [-9.25873, 32.30366]}}]}