{"type": "FeatureCollection", "id": "http://imperium.ahlfeldt.se/places/33681", "name": "33681", "features": [{"type": "Feature", "id": "http://data.archaeology.link/data/ancientports/181", "name": "Calle San Fernando, Santander (note that Juliobriga is located near Reinosa)", "dateprops": [], "properties": {"http://purl.org/dc/elements/1.1/creator": ["http://data.archaeology.link/data/spphaefen/arthur_de_graauw"], "http://purl.org/dc/terms/partOf": ["http://data.archaeology.link/data/ancientports/bib_deGrauw_2013_GeoDB"], "http://www.opengis.net/ont/geosparql#hasGeometry": ["http://data.archaeology.link/data/ancientports/181_geom"], "http://www.w3.org/1999/02/22-rdf-syntax-ns#type": ["http://www.ancientports.com/ont#Harbour"], "http://www.w3.org/2000/01/rdf-schema#label": ["Calle San Fernando, Santander (note that Juliobriga is located near Reinosa)"], "http://www.w3.org/2002/07/owl#sameAs": ["http://www.wikidata.org/entity/Q12233"], "http://www.w3.org/2004/02/skos/core#note": ["Morillo (2016)"], "http://www.wikidata.org/prop/direct/P1584": ["http://pleiades.stoa.org/places/236613"], "http://www.wikidata.org/prop/direct/P17": ["http://www.wikidata.org/entity/Q29"], "http://www.wikidata.org/prop/direct/P1936": ["http://imperium.ahlfeldt.se/places/33681"], "begin": ""}, "geometry": {"type": "Point", "coordinates": [-3.8201, 43.4602]}}], "numberMatched": 1, "numberReturned": 1, "bbox": [-3.8201, 43.4602, -3.8201, 43.4602], "crs": "http://www.opengis.net/def/crs/EPSG/0/4326"}