{"type": "FeatureCollection", "id": "http://imperium.ahlfeldt.se/places/17381", "name": "17381", "features": [{"type": "Feature", "id": "http://data.archaeology.link/data/ancientports/813", "label": "La Costa, Sanremo", "dateprops": ["http://purl.org/dc/elements/1.1/created", "http://www.ancientports.com/ont#date_min"], "properties": {"http://purl.org/dc/elements/1.1/created": ["2023"], "http://purl.org/dc/elements/1.1/creator": ["http://data.archaeology.link/data/spphaefen/arthur_de_graauw"], "http://www.ancientports.com/ont#date_min": ["-30"], "http://www.opengis.net/ont/geosparql#hasGeometry": ["http://data.archaeology.link/data/ancientports/813_geom"], "http://www.w3.org/1999/02/22-rdf-syntax-ns#type": ["http://www.ancientports.com/ont#Harbour"], "http://www.w3.org/2000/01/rdf-schema#label": ["La Costa, Sanremo"], "http://www.w3.org/2002/07/owl#sameAs": ["http://www.wikidata.org/entity/Q33962"], "http://www.wikidata.org/prop/direct/P1584": ["http://pleiades.stoa.org/places/157837"], "http://www.wikidata.org/prop/direct/P17": ["Italy West"], "http://www.wikidata.org/prop/direct/P1936": ["http://imperium.ahlfeldt.se/places/17381"]}, "geometry": {"type": "Point", "coordinates": [7.7807, 43.8147]}}]}