{"type": "FeatureCollection", "id": "http://www.wikidata.org/entity/Q975080", "name": "Porquerolles", "features": [{"type": "Feature", "id": "http://data.archaeology.link/data/ancientports/689", "name": "Pointe de La Galere (Porquerolles)", "dateprops": ["begin"], "properties": {"http://purl.org/dc/elements/1.1/creator": ["http://data.archaeology.link/data/spphaefen/arthur_de_graauw"], "http://purl.org/dc/terms/partOf": ["http://data.archaeology.link/data/ancientports/bib_deGrauw_2013_GeoDB"], "http://www.opengis.net/ont/geosparql#hasGeometry": ["http://data.archaeology.link/data/ancientports/689_geom"], "http://www.w3.org/1999/02/22-rdf-syntax-ns#type": ["http://www.ancientports.com/ont#Harbour"], "http://www.w3.org/2000/01/rdf-schema#label": ["Pointe de La Galere (Porquerolles)"], "http://www.w3.org/2002/07/owl#sameAs": ["http://www.wikidata.org/entity/Q975080"], "http://www.w3.org/2004/02/skos/core#note": ["Brun (1992)"], "http://www.w3.org/2006/time#hasTime": ["http://data.archaeology.link/data/ancientports/689_foundation"], "http://www.wikidata.org/prop/direct/P1584": ["http://pleiades.stoa.org/places/157857"], "http://www.wikidata.org/prop/direct/P17": ["http://www.wikidata.org/entity/Q142"], "http://www.wikidata.org/prop/direct/P1936": ["http://imperium.ahlfeldt.se/places/17390"], "begin": "-100"}, "geometry": {"type": "Point", "coordinates": [6.25155, 43.00177]}}, {"type": "Feature", "id": "http://data.archaeology.link/data/ancientports/690", "name": "Anse du Breganconnet (Porquerolles)", "dateprops": [], "properties": {"http://purl.org/dc/elements/1.1/creator": ["http://data.archaeology.link/data/spphaefen/arthur_de_graauw"], "http://purl.org/dc/terms/partOf": ["http://data.archaeology.link/data/ancientports/bib_deGrauw_2013_GeoDB"], "http://www.opengis.net/ont/geosparql#hasGeometry": ["http://data.archaeology.link/data/ancientports/690_geom"], "http://www.w3.org/1999/02/22-rdf-syntax-ns#type": ["http://www.ancientports.com/ont#Harbour"], "http://www.w3.org/2000/01/rdf-schema#label": ["Anse du Breganconnet (Porquerolles)"], "http://www.w3.org/2002/07/owl#sameAs": ["http://www.wikidata.org/entity/Q975080"], "http://www.wikidata.org/prop/direct/P17": ["http://www.wikidata.org/entity/Q142"], "begin": ""}, "geometry": {"type": "Point", "coordinates": [6.18107, 42.9939]}}, {"type": "Feature", "id": "http://data.archaeology.link/data/ancientports/687", "name": "Roman villa on Place d'Armes, Porquerolles village", "dateprops": ["begin"], "properties": {"http://purl.org/dc/elements/1.1/creator": ["http://data.archaeology.link/data/spphaefen/arthur_de_graauw"], "http://purl.org/dc/terms/partOf": ["http://data.archaeology.link/data/ancientports/bib_deGrauw_2013_GeoDB"], "http://www.opengis.net/ont/geosparql#hasGeometry": ["http://data.archaeology.link/data/ancientports/687_geom"], "http://www.w3.org/1999/02/22-rdf-syntax-ns#type": ["http://www.ancientports.com/ont#VillaMaritima"], "http://www.w3.org/2000/01/rdf-schema#label": ["Roman villa on Place d'Armes, Porquerolles village"], "http://www.w3.org/2002/07/owl#sameAs": ["http://www.wikidata.org/entity/Q975080"], "http://www.w3.org/2004/02/skos/core#note": ["Brun (1992)"], "http://www.w3.org/2006/time#hasTime": ["http://data.archaeology.link/data/ancientports/687_foundation"], "http://www.wikidata.org/prop/direct/P17": ["http://www.wikidata.org/entity/Q142"], "begin": "-100"}, "geometry": {"type": "Point", "coordinates": [6.203, 43.0004]}}, {"type": "Feature", "id": "http://data.archaeology.link/data/ancientports/688", "name": "Pointe du Lequin, plage Notre Dame (Porquerolles)", "dateprops": [], "properties": {"http://purl.org/dc/elements/1.1/creator": ["http://data.archaeology.link/data/spphaefen/arthur_de_graauw"], "http://purl.org/dc/terms/partOf": ["http://data.archaeology.link/data/ancientports/bib_deGrauw_2013_GeoDB"], "http://www.opengis.net/ont/geosparql#hasGeometry": ["http://data.archaeology.link/data/ancientports/688_geom"], "http://www.w3.org/1999/02/22-rdf-syntax-ns#type": ["http://www.ancientports.com/ont#Harbour"], "http://www.w3.org/2000/01/rdf-schema#label": ["Pointe du Lequin, plage Notre Dame (Porquerolles)"], "http://www.w3.org/2002/07/owl#sameAs": ["http://www.wikidata.org/entity/Q975080"], "http://www.wikidata.org/prop/direct/P17": ["http://www.wikidata.org/entity/Q142"], "begin": ""}, "geometry": {"type": "Point", "coordinates": [6.2288, 43.0105]}}]}