{"type": "FeatureCollection", "id": "http://imperium.ahlfeldt.se/places/21795", "name": "21795", "features": [{"type": "Feature", "id": "http://data.archaeology.link/data/ancientports/2706", "label": "Poti, on southern arm of R Rioni, with Roman naval base (on lake Paliastomi, which may have been just a bay in ancient times?)", "properties": {"http://purl.org/dc/elements/1.1/created": ["2023"], "http://purl.org/dc/elements/1.1/creator": ["http://data.archaeology.link/data/spphaefen/arthur_de_graauw"], "http://www.ancientports.com/ont#date_min": ["-600"], "http://www.opengis.net/ont/geosparql#hasGeometry": ["http://data.archaeology.link/data/ancientports/2706_geom"], "http://www.w3.org/1999/02/22-rdf-syntax-ns#type": ["http://www.ancientports.com/ont#Harbour"], "http://www.w3.org/2000/01/rdf-schema#label": ["Poti, on southern arm of R Rioni, with Roman naval base (on lake Paliastomi, which may have been just a bay in ancient times?)"], "http://www.w3.org/2002/07/owl#sameAs": ["http://www.wikidata.org/entity/Q378091"], "http://www.w3.org/2004/02/skos/core#note": ["Dan (2016)"], "http://www.wikidata.org/prop/direct/P1584": ["http://pleiades.stoa.org/places/857275"], "http://www.wikidata.org/prop/direct/P17": ["Georgia Black S."], "http://www.wikidata.org/prop/direct/P1936": ["http://imperium.ahlfeldt.se/places/21795"]}, "geometry": {"type": "Point", "coordinates": [41.6745, 42.1413]}}]}