{"type": "FeatureCollection", "id": "http://pleiades.stoa.org/places/246665", "name": "246665", "features": [{"type": "Feature", "id": "http://data.archaeology.link/data/ancientports/423", "label": "near Vandellos nuclear power station", "properties": {"http://purl.org/dc/elements/1.1/created": ["2023"], "http://purl.org/dc/elements/1.1/creator": ["http://data.archaeology.link/data/spphaefen/arthur_de_graauw"], "http://www.ancientports.com/ont#date_min": ["-30"], "http://www.opengis.net/ont/geosparql#hasGeometry": ["http://data.archaeology.link/data/ancientports/423_geom"], "http://www.w3.org/1999/02/22-rdf-syntax-ns#type": ["http://www.ancientports.com/ont#Harbour"], "http://www.w3.org/2000/01/rdf-schema#label": ["near Vandellos nuclear power station"], "http://www.wikidata.org/prop/direct/P1584": ["http://pleiades.stoa.org/places/246665"], "http://www.wikidata.org/prop/direct/P17": ["Spain East"], "http://www.wikidata.org/prop/direct/P1958": ["https://www.trismegistos.org/place/33176"]}, "geometry": {"type": "Point", "coordinates": [0.8829, 40.9574]}}]}