{"type": "FeatureCollection", "id": "http://pleiades.stoa.org/places/922680", "name": "922680", "features": [{"type": "Feature", "id": "http://data.archaeology.link/data/ancientports/3817", "label": "Bushir, Bushehr", "properties": {"http://purl.org/dc/elements/1.1/created": ["2023"], "http://purl.org/dc/elements/1.1/creator": ["http://data.archaeology.link/data/spphaefen/arthur_de_graauw"], "http://www.ancientports.com/ont#date_min": ["-330"], "http://www.opengis.net/ont/geosparql#hasGeometry": ["http://data.archaeology.link/data/ancientports/3817_geom"], "http://www.w3.org/1999/02/22-rdf-syntax-ns#type": ["http://www.ancientports.com/ont#Harbour"], "http://www.w3.org/2000/01/rdf-schema#label": ["Bushir, Bushehr"], "http://www.w3.org/2002/07/owl#sameAs": ["http://www.wikidata.org/entity/Q158928"], "http://www.wikidata.org/prop/direct/P1584": ["http://pleiades.stoa.org/places/922680"], "http://www.wikidata.org/prop/direct/P17": ["Gulf"]}, "geometry": {"type": "Point", "coordinates": [50.836, 28.9935]}}]}