{"type": "FeatureCollection", "id": "http://pleiades.stoa.org/places/278605", "name": "278605", "features": [{"type": "Feature", "id": "http://data.archaeology.link/data/ancientports/4282", "label": "el-Jebha", "properties": {"http://purl.org/dc/elements/1.1/created": ["2023"], "http://purl.org/dc/elements/1.1/creator": ["http://data.archaeology.link/data/spphaefen/arthur_de_graauw"], "http://www.opengis.net/ont/geosparql#hasGeometry": ["http://data.archaeology.link/data/ancientports/4282_geom"], "http://www.w3.org/1999/02/22-rdf-syntax-ns#type": ["http://www.ancientports.com/ont#Harbour"], "http://www.w3.org/2000/01/rdf-schema#label": ["el-Jebha"], "http://www.wikidata.org/prop/direct/P1584": ["http://pleiades.stoa.org/places/278605"], "http://www.wikidata.org/prop/direct/P17": ["http://www.wikidata.org/entity/Q1028"]}, "geometry": {"type": "Point", "coordinates": [-4.65763, 35.21109]}}]}