{"type": "FeatureCollection", "id": "https://topostext.org/place/329132UOea", "name": "329132UOea", "features": [{"type": "Feature", "id": "http://data.archaeology.link/data/ancientports/4085", "name": "Tripoli", "dateprops": ["begin"], "properties": {"http://purl.org/dc/elements/1.1/created": ["2023"], "http://purl.org/dc/elements/1.1/creator": ["http://data.archaeology.link/data/spphaefen/arthur_de_graauw"], "http://www.opengis.net/ont/geosparql#hasGeometry": ["http://data.archaeology.link/data/ancientports/4085_geom"], "http://www.w3.org/1999/02/22-rdf-syntax-ns#type": ["http://www.ancientports.com/ont#Quay"], "http://www.w3.org/2000/01/rdf-schema#label": ["Tripoli"], "http://www.w3.org/2002/07/owl#sameAs": ["http://www.wikidata.org/entity/Q1994812"], "http://www.w3.org/2006/time#hasTime": ["http://data.archaeology.link/data/ancientports/4085_foundation"], "http://www.wikidata.org/prop/direct/P1584": ["http://pleiades.stoa.org/places/344456"], "http://www.wikidata.org/prop/direct/P17": ["http://www.wikidata.org/entity/Q1016"], "http://www.wikidata.org/prop/direct/P1936": ["http://imperium.ahlfeldt.se/places/22283"], "http://www.wikidata.org/prop/direct/P1958": ["https://www.trismegistos.org/place/11840"], "http://www.wikidata.org/prop/direct/P8068": ["https://topostext.org/place/329132UOea"], "begin": "-750"}, "geometry": {"type": "Point", "coordinates": [13.17867, 32.90134]}}]}