{"type": "FeatureCollection", "id": "http://imperium.ahlfeldt.se/places/39162", "name": "39162", "features": [{"type": "Feature", "id": "http://data.archaeology.link/data/ancientports/139", "label": "Pen Bryn-Yr-Eglwys", "properties": {"http://purl.org/dc/elements/1.1/created": ["2023"], "http://purl.org/dc/elements/1.1/creator": ["http://data.archaeology.link/data/spphaefen/arthur_de_graauw"], "http://www.ancientports.com/ont#date_min": ["-500"], "http://www.opengis.net/ont/geosparql#hasGeometry": ["http://data.archaeology.link/data/ancientports/139_geom"], "http://www.w3.org/1999/02/22-rdf-syntax-ns#type": ["http://www.ancientports.com/ont#Harbour"], "http://www.w3.org/2000/01/rdf-schema#label": ["Pen Bryn-Yr-Eglwys"], "http://www.w3.org/2004/02/skos/core#note": ["Jones (2009)"], "http://www.wikidata.org/prop/direct/P17": ["UK"], "http://www.wikidata.org/prop/direct/P1936": ["http://imperium.ahlfeldt.se/places/39162"]}, "geometry": {"type": "Point", "coordinates": [-4.5688, 53.40165]}}]}