{"type": "FeatureCollection", "id": "http://imperium.ahlfeldt.se/places/28847", "name": "28847", "features": [{"type": "Feature", "id": "http://data.archaeology.link/data/ancientports/2976", "label": "Sitia, near R Penteles", "dateprops": [], "properties": {"http://purl.org/dc/elements/1.1/created": ["2023"], "http://purl.org/dc/elements/1.1/creator": ["http://data.archaeology.link/data/spphaefen/arthur_de_graauw"], "http://www.opengis.net/ont/geosparql#hasGeometry": ["http://data.archaeology.link/data/ancientports/2976_geom"], "http://www.w3.org/1999/02/22-rdf-syntax-ns#type": ["http://www.ancientports.com/ont#Harbour"], "http://www.w3.org/2000/01/rdf-schema#label": ["Sitia, near R Penteles"], "http://www.w3.org/2002/07/owl#sameAs": ["http://www.wikidata.org/entity/Q985549"], "http://www.w3.org/2004/02/skos/core#note": ["Cline (2011)", "Uggeri (2003)"], "http://www.w3.org/2006/time#hasTime": ["http://data.archaeology.link/data/ancientports/2976_foundation"], "http://www.wikidata.org/prop/direct/P1584": ["http://pleiades.stoa.org/places/590045"], "http://www.wikidata.org/prop/direct/P17": ["GR: Crete North"], "http://www.wikidata.org/prop/direct/P1936": ["http://imperium.ahlfeldt.se/places/28847"], "http://www.wikidata.org/prop/direct/P1958": ["https://www.trismegistos.org/place/33312"], "http://www.wikidata.org/prop/direct/P8068": ["https://topostext.org/place/352261USet"]}, "geometry": {"type": "Point", "coordinates": [26.106, 35.2085]}}]}