{"type": "FeatureCollection", "id": "http://www.wikidata.org/entity/Q7534982", "name": "Q7534982", "features": [{"type": "Feature", "id": "http://data.archaeology.link/data/ancientports/2226", "label": "Naval base at Skiathos, on the isle of Skiathos", "dateprops": ["http://purl.org/dc/elements/1.1/created", "http://www.ancientports.com/ont#date_min"], "properties": {"http://purl.org/dc/elements/1.1/created": ["2023"], "http://purl.org/dc/elements/1.1/creator": ["http://data.archaeology.link/data/spphaefen/arthur_de_graauw"], "http://www.ancientports.com/ont#date_min": ["-350"], "http://www.opengis.net/ont/geosparql#hasGeometry": ["http://data.archaeology.link/data/ancientports/2226_geom"], "http://www.w3.org/1999/02/22-rdf-syntax-ns#type": ["http://www.ancientports.com/ont#Quay"], "http://www.w3.org/2000/01/rdf-schema#label": ["Naval base at Skiathos, on the isle of Skiathos"], "http://www.w3.org/2002/07/owl#sameAs": ["http://www.wikidata.org/entity/Q7534982"], "http://www.w3.org/2004/02/skos/core#note": ["Ginalis (2018)", "Ginalis (2021)"], "http://www.wikidata.org/prop/direct/P1584": ["http://pleiades.stoa.org/places/541104"], "http://www.wikidata.org/prop/direct/P17": ["GR: Eastern Isl."], "http://www.wikidata.org/prop/direct/P1936": ["http://imperium.ahlfeldt.se/places/29462"], "http://www.wikidata.org/prop/direct/P1958": ["https://www.trismegistos.org/place/33247"], "http://www.wikidata.org/prop/direct/P8068": ["https://topostext.org/place/392235PSki"]}, "geometry": {"type": "Point", "coordinates": [23.4894, 39.1616]}}]}