{"type": "FeatureCollection", "id": "http://pleiades.stoa.org/places/265852", "name": "265852", "features": [{"type": "Feature", "id": "http://data.archaeology.link/data/ancientports/387", "label": "Roman villa at El Castillet, near Cabo de Palos, from where one could sail directly to Caesarea Mauretania", "dateprops": [], "properties": {"http://purl.org/dc/elements/1.1/created": ["2023"], "http://purl.org/dc/elements/1.1/creator": ["http://data.archaeology.link/data/spphaefen/arthur_de_graauw"], "http://www.opengis.net/ont/geosparql#hasGeometry": ["http://data.archaeology.link/data/ancientports/387_geom"], "http://www.w3.org/1999/02/22-rdf-syntax-ns#type": ["http://www.ancientports.com/ont#VillaMaritima"], "http://www.w3.org/2000/01/rdf-schema#label": ["Roman villa at El Castillet, near Cabo de Palos, from where one could sail directly to Caesarea Mauretania"], "http://www.w3.org/2002/07/owl#sameAs": ["http://www.wikidata.org/entity/Q731315"], "http://www.w3.org/2006/time#hasTime": ["http://data.archaeology.link/data/ancientports/387_foundation"], "http://www.wikidata.org/prop/direct/P1584": ["http://pleiades.stoa.org/places/265852"], "http://www.wikidata.org/prop/direct/P17": ["http://www.wikidata.org/entity/Q29"], "http://www.wikidata.org/prop/direct/P1936": ["http://imperium.ahlfeldt.se/places/35556"]}, "geometry": {"type": "Point", "coordinates": [-0.6997, 37.6322]}}]}