{"type": "FeatureCollection", "id": "https://topostext.org/place/408225PPel", "name": "408225PPel", "features": [{"type": "Feature", "id": "http://data.archaeology.link/data/ancientports/1774", "label": "Pella, river port in the gulf of Salonika", "dateprops": [], "properties": {"http://purl.org/dc/elements/1.1/created": ["2023"], "http://purl.org/dc/elements/1.1/creator": ["http://data.archaeology.link/data/spphaefen/arthur_de_graauw"], "http://www.ancientports.com/ont#date_min": ["-750"], "http://www.opengis.net/ont/geosparql#hasGeometry": ["http://data.archaeology.link/data/ancientports/1774_geom"], "http://www.w3.org/1999/02/22-rdf-syntax-ns#type": ["http://www.ancientports.com/ont#Harbour"], "http://www.w3.org/2000/01/rdf-schema#label": ["Pella, river port in the gulf of Salonika"], "http://www.w3.org/2002/07/owl#sameAs": ["http://www.wikidata.org/entity/Q213679"], "http://www.wikidata.org/prop/direct/P1584": ["http://pleiades.stoa.org/places/491687"], "http://www.wikidata.org/prop/direct/P17": ["GR: North-East"], "http://www.wikidata.org/prop/direct/P1936": ["http://imperium.ahlfeldt.se/places/21891"], "http://www.wikidata.org/prop/direct/P1958": ["https://www.trismegistos.org/place/1657"], "http://www.wikidata.org/prop/direct/P8068": ["https://topostext.org/place/408225PPel"]}, "geometry": {"type": "Point", "coordinates": [22.5186, 40.7558]}}]}