{"type": "FeatureCollection", "id": "http://www.wikidata.org/entity/Q28721809", "name": "Q28721809", "features": [{"type": "Feature", "id": "http://data.archaeology.link/data/ancientports/2116", "label": "Tholaria, on the isle of Amorgos", "dateprops": [], "properties": {"http://purl.org/dc/elements/1.1/created": ["2023"], "http://purl.org/dc/elements/1.1/creator": ["http://data.archaeology.link/data/spphaefen/arthur_de_graauw"], "http://purl.org/dc/terms/isReferencedBy": ["https://amorgos.gr/explore-amorgos/ancient-aegiali-vigla/"], "http://www.ancientports.com/ont#date_min": ["-1000"], "http://www.opengis.net/ont/geosparql#hasGeometry": ["http://data.archaeology.link/data/ancientports/2116_geom"], "http://www.w3.org/1999/02/22-rdf-syntax-ns#type": ["http://www.ancientports.com/ont#Harbour"], "http://www.w3.org/2000/01/rdf-schema#label": ["Tholaria, on the isle of Amorgos"], "http://www.w3.org/2002/07/owl#sameAs": ["http://www.wikidata.org/entity/Q28721809"], "http://www.wikidata.org/prop/direct/P1584": ["http://pleiades.stoa.org/places/599476"], "http://www.wikidata.org/prop/direct/P17": ["GR: Cyclades Isl."], "http://www.wikidata.org/prop/direct/P1936": ["http://imperium.ahlfeldt.se/places/28925"], "http://www.wikidata.org/prop/direct/P1958": ["https://www.trismegistos.org/place/34064"], "http://www.wikidata.org/prop/direct/P8068": ["https://topostext.org/place/369260PAig"]}, "geometry": {"type": "Point", "coordinates": [25.9803, 36.9193]}}]}