{"type": "FeatureCollection", "id": "http://pleiades.stoa.org/places/452457", "name": "452457", "features": [{"type": "Feature", "id": "http://data.archaeology.link/data/ancientports/1090", "name": "Laghi di Sibari, Francavilla Marittima, on R Crati", "dateprops": ["begin"], "properties": {"http://purl.org/dc/elements/1.1/created": ["2023"], "http://purl.org/dc/elements/1.1/creator": ["http://data.archaeology.link/data/spphaefen/arthur_de_graauw"], "http://purl.org/dc/terms/isReferencedBy": ["https://topostext.org/place/397164PTho"], "http://www.opengis.net/ont/geosparql#hasGeometry": ["http://data.archaeology.link/data/ancientports/1090_geom"], "http://www.w3.org/1999/02/22-rdf-syntax-ns#type": ["http://www.ancientports.com/ont#Slipway"], "http://www.w3.org/2000/01/rdf-schema#label": ["Laghi di Sibari, Francavilla Marittima, on R Crati"], "http://www.w3.org/2002/07/owl#sameAs": ["http://www.wikidata.org/entity/Q220583"], "http://www.w3.org/2004/02/skos/core#note": ["Vella (2021)"], "http://www.w3.org/2006/time#hasTime": ["http://data.archaeology.link/data/ancientports/1090_foundation"], "http://www.wikidata.org/prop/direct/P1584": ["http://pleiades.stoa.org/places/452457"], "http://www.wikidata.org/prop/direct/P17": ["http://www.wikidata.org/entity/Q38"], "http://www.wikidata.org/prop/direct/P1936": ["http://imperium.ahlfeldt.se/places/16740"], "http://www.wikidata.org/prop/direct/P1958": ["https://www.trismegistos.org/place/14503"], "http://www.wikidata.org/prop/direct/P8068": ["https://topostext.org/place/397165PSyb"], "begin": "-720"}, "geometry": {"type": "Point", "coordinates": [16.49119, 39.71704]}}]}