{"type": "FeatureCollection", "id": "http://www.wikidata.org/entity/Q922", "name": "Bra%C4%8D", "features": [{"type": "Feature", "id": "http://data.archaeology.link/data/ancientports/1465", "name": "Uvala Rasotica, on the isle of Bra\u00e7", "dateprops": [], "properties": {"http://purl.org/dc/elements/1.1/creator": ["http://data.archaeology.link/data/spphaefen/arthur_de_graauw"], "http://purl.org/dc/terms/partOf": ["http://data.archaeology.link/data/ancientports/bib_deGrauw_2013_GeoDB"], "http://www.opengis.net/ont/geosparql#hasGeometry": ["http://data.archaeology.link/data/ancientports/1465_geom"], "http://www.w3.org/1999/02/22-rdf-syntax-ns#type": ["http://www.ancientports.com/ont#Harbour", "http://www.ancientports.com/ont#PotentialHarbour"], "http://www.w3.org/2000/01/rdf-schema#label": ["Uvala Rasotica, on the isle of Brac", "Uvala Rasotica, on the isle of Bra\u00e7"], "http://www.w3.org/2002/07/owl#sameAs": ["http://www.wikidata.org/entity/Q922"], "http://www.wikidata.org/prop/direct/P17": ["http://www.wikidata.org/entity/Q224"], "begin": ""}, "geometry": {"type": "Point", "coordinates": [16.88588, 43.30775]}}, {"type": "Feature", "id": "http://data.archaeology.link/data/ancientports/1463", "name": "Uvala Luka, on the isle of Brac", "dateprops": [], "properties": {"http://purl.org/dc/elements/1.1/creator": ["http://data.archaeology.link/data/spphaefen/arthur_de_graauw"], "http://purl.org/dc/terms/isReferencedBy": ["http://baza.iarh.hr/public/locality/detail/1385"], "http://purl.org/dc/terms/partOf": ["http://data.archaeology.link/data/ancientports/bib_deGrauw_2013_GeoDB"], "http://www.opengis.net/ont/geosparql#hasGeometry": ["http://data.archaeology.link/data/ancientports/1463_geom"], "http://www.w3.org/1999/02/22-rdf-syntax-ns#type": ["http://www.ancientports.com/ont#Harbour"], "http://www.w3.org/2000/01/rdf-schema#label": ["Uvala Luka, on the isle of Brac"], "http://www.w3.org/2002/07/owl#sameAs": ["http://www.wikidata.org/entity/Q922"], "http://www.wikidata.org/prop/direct/P17": ["http://www.wikidata.org/entity/Q224"], "begin": ""}, "geometry": {"type": "Point", "coordinates": [16.79767, 43.33928]}}, {"type": "Feature", "id": "http://data.archaeology.link/data/ancientports/1462", "name": "Lovrecina, on the isle of Brac", "dateprops": [], "properties": {"http://purl.org/dc/elements/1.1/creator": ["http://data.archaeology.link/data/spphaefen/arthur_de_graauw"], "http://purl.org/dc/terms/isReferencedBy": ["http://baza.iarh.hr/public/locality/detail/623", "https://bestofbrac.com/brac-culture/short-history-island/"], "http://purl.org/dc/terms/partOf": ["http://data.archaeology.link/data/ancientports/bib_deGrauw_2013_GeoDB"], "http://www.opengis.net/ont/geosparql#hasGeometry": ["http://data.archaeology.link/data/ancientports/1462_geom"], "http://www.w3.org/1999/02/22-rdf-syntax-ns#type": ["http://www.ancientports.com/ont#Harbour"], "http://www.w3.org/2000/01/rdf-schema#label": ["Lovrecina, on the isle of Brac"], "http://www.w3.org/2002/07/owl#sameAs": ["http://www.wikidata.org/entity/Q922"], "http://www.wikidata.org/prop/direct/P17": ["http://www.wikidata.org/entity/Q224"], "begin": ""}, "geometry": {"type": "Point", "coordinates": [16.66642, 43.37134]}}], "numberMatched": 3, "numberReturned": 3, "bbox": [16.66642, 43.30775, 16.88588, 43.37134], "crs": "http://www.opengis.net/def/crs/EPSG/0/4326"}