{"type": "FeatureCollection", "id": "http://pleiades.stoa.org/places/113312", "name": "113312", "features": [{"type": "Feature", "id": "http://data.archaeology.link/data/ancientports/22", "label": "Xanten, Arch\u00e4ologischen Park, on R Rhein", "dateprops": [], "properties": {"http://purl.org/dc/elements/1.1/created": ["2023"], "http://purl.org/dc/elements/1.1/creator": ["http://data.archaeology.link/data/spphaefen/arthur_de_graauw"], "http://purl.org/dc/terms/isReferencedBy": ["https://www2.rgzm.de/navis2/home/frames.htm", "http://data.archaeology.link/data/ancientports/bib_Seinen_2014_Late"], "http://www.opengis.net/ont/geosparql#hasGeometry": ["http://data.archaeology.link/data/ancientports/22_geom"], "http://www.w3.org/1999/02/22-rdf-syntax-ns#type": ["http://www.ancientports.com/ont#Quay"], "http://www.w3.org/2000/01/rdf-schema#label": ["Xanten, Arch\u00e4ologischen Park, on R Rhein"], "http://www.w3.org/2002/07/owl#sameAs": ["http://www.wikidata.org/entity/Q1265889"], "http://www.w3.org/2004/02/skos/core#note": ["Dempwolff (2019)"], "http://www.wikidata.org/prop/direct/P1584": ["http://pleiades.stoa.org/places/113312"], "http://www.wikidata.org/prop/direct/P17": ["http://www.wikidata.org/entity/Q183"]}, "geometry": {"type": "Point", "coordinates": [6.4467, 51.6698]}}]}