{"type": "FeatureCollection", "id": "http://pleiades.stoa.org/places/550721", "name": "550721", "features": [{"type": "Feature", "id": "http://data.archaeology.link/data/ancientports/3145_2", "label": "Yassica Ada island", "dateprops": ["http://purl.org/dc/elements/1.1/created"], "properties": {"http://purl.org/dc/elements/1.1/created": ["2023"], "http://purl.org/dc/elements/1.1/creator": ["http://data.archaeology.link/data/spphaefen/arthur_de_graauw"], "http://www.opengis.net/ont/geosparql#hasGeometry": ["http://data.archaeology.link/data/ancientports/3145_2_geom"], "http://www.w3.org/1999/02/22-rdf-syntax-ns#type": ["http://www.ancientports.com/ont#Harbour"], "http://www.w3.org/2000/01/rdf-schema#label": ["Yassica Ada island"], "http://www.wikidata.org/prop/direct/P1584": ["http://pleiades.stoa.org/places/550721"], "http://www.wikidata.org/prop/direct/P17": ["TR: West"], "http://www.wikidata.org/prop/direct/P1936": ["http://imperium.ahlfeldt.se/places/43488"]}, "geometry": {"type": "Point", "coordinates": [26.7955, 38.406]}}]}