{"type": "FeatureCollection", "id": "http://www.wikidata.org/entity/Q1106404", "name": "Q1106404", "features": [{"type": "Feature", "id": "http://data.archaeology.link/data/ancientports/449", "label": "Sant Marti d\u2019Empuries", "dateprops": ["http://purl.org/dc/elements/1.1/created"], "properties": {"http://purl.org/dc/elements/1.1/created": ["2023"], "http://purl.org/dc/elements/1.1/creator": ["http://data.archaeology.link/data/spphaefen/arthur_de_graauw"], "http://www.opengis.net/ont/geosparql#hasGeometry": ["http://data.archaeology.link/data/ancientports/449_geom"], "http://www.w3.org/1999/02/22-rdf-syntax-ns#type": ["http://www.ancientports.com/ont#Harbour"], "http://www.w3.org/2000/01/rdf-schema#label": ["Sant Marti d\u2019Empuries"], "http://www.w3.org/2002/07/owl#sameAs": ["http://www.wikidata.org/entity/Q1106404"], "http://www.w3.org/2004/02/skos/core#note": ["Bony (2011)", "Castanyer (2021)"], "http://www.w3.org/2006/time#hasTime": ["http://data.archaeology.link/data/ancientports/449_foundation"], "http://www.wikidata.org/prop/direct/P1584": ["http://pleiades.stoa.org/places/246382"], "http://www.wikidata.org/prop/direct/P17": ["http://www.wikidata.org/entity/Q29"], "http://www.wikidata.org/prop/direct/P1936": ["http://imperium.ahlfeldt.se/places/18301"], "http://www.wikidata.org/prop/direct/P1958": ["https://www.trismegistos.org/place/27282"], "http://www.wikidata.org/prop/direct/P8068": ["https://topostext.org/place/421031PEmp"]}, "geometry": {"type": "Point", "coordinates": [3.1166, 42.1382]}}]}