{"type": "FeatureCollection", "id": "http://pleiades.stoa.org/places/465897", "name": "465897", "features": [{"type": "Feature", "id": "http://data.archaeology.link/data/ancientports/1241", "label": "Lampedusa, on the isle of Lampedusa", "properties": {"http://purl.org/dc/elements/1.1/created": ["2023"], "http://purl.org/dc/elements/1.1/creator": ["http://data.archaeology.link/data/spphaefen/arthur_de_graauw"], "http://www.opengis.net/ont/geosparql#hasGeometry": ["http://data.archaeology.link/data/ancientports/1241_geom"], "http://www.w3.org/1999/02/22-rdf-syntax-ns#type": ["http://www.ancientports.com/ont#Harbour"], "http://www.w3.org/2000/01/rdf-schema#label": ["Lampedusa, on the isle of Lampedusa"], "http://www.w3.org/2002/07/owl#sameAs": ["http://www.wikidata.org/entity/Q107338"], "http://www.wikidata.org/prop/direct/P1584": ["http://pleiades.stoa.org/places/465897"], "http://www.wikidata.org/prop/direct/P17": ["Italy Lampedusa"], "http://www.wikidata.org/prop/direct/P1936": ["http://imperium.ahlfeldt.se/places/41240"], "http://www.wikidata.org/prop/direct/P1958": ["https://www.trismegistos.org/place/61078"], "http://www.wikidata.org/prop/direct/P8068": ["https://topostext.org/place/355126ILop"]}, "geometry": {"type": "Point", "coordinates": [12.605, 35.5013]}}]}