{"type": "FeatureCollection", "id": "http://pleiades.stoa.org/places/462142", "name": "462142", "features": [{"type": "Feature", "id": "http://data.archaeology.link/data/ancientports/1161", "label": "Castello di Palma di Montechiaro ", "properties": {"http://purl.org/dc/elements/1.1/created": ["2023"], "http://purl.org/dc/elements/1.1/creator": ["http://data.archaeology.link/data/spphaefen/arthur_de_graauw"], "http://www.ancientports.com/ont#date_min": ["-550"], "http://www.opengis.net/ont/geosparql#hasGeometry": ["http://data.archaeology.link/data/ancientports/1161_geom"], "http://www.w3.org/1999/02/22-rdf-syntax-ns#type": ["http://www.ancientports.com/ont#Harbour"], "http://www.w3.org/2000/01/rdf-schema#label": ["Castello di Palma di Montechiaro "], "http://www.wikidata.org/prop/direct/P1584": ["http://pleiades.stoa.org/places/462142"], "http://www.wikidata.org/prop/direct/P17": ["Italy Sicily"], "http://www.wikidata.org/prop/direct/P1936": ["http://imperium.ahlfeldt.se/places/34445"]}, "geometry": {"type": "Point", "coordinates": [13.69534, 37.17957]}}]}