{"type": "FeatureCollection", "id": "http://pleiades.stoa.org/places/658508", "name": "658508", "features": [{"type": "Feature", "id": "http://data.archaeology.link/data/ancientports/3399", "label": "\u201cPillars of Jonas\u201d, Sariseki Kalesi ", "properties": {"http://purl.org/dc/elements/1.1/created": ["2023"], "http://purl.org/dc/elements/1.1/creator": ["http://data.archaeology.link/data/spphaefen/arthur_de_graauw"], "http://www.ancientports.com/ont#date_min": ["-550"], "http://www.opengis.net/ont/geosparql#hasGeometry": ["http://data.archaeology.link/data/ancientports/3399_geom"], "http://www.w3.org/1999/02/22-rdf-syntax-ns#type": ["http://www.ancientports.com/ont#Harbour"], "http://www.w3.org/2000/01/rdf-schema#label": ["\u201cPillars of Jonas\u201d, Sariseki Kalesi "], "http://www.w3.org/2004/02/skos/core#note": ["Seton-Williams (1954)"], "http://www.wikidata.org/prop/direct/P1584": ["http://pleiades.stoa.org/places/658508"], "http://www.wikidata.org/prop/direct/P17": ["TR: South"], "http://www.wikidata.org/prop/direct/P1936": ["http://imperium.ahlfeldt.se/places/38532"]}, "geometry": {"type": "Point", "coordinates": [36.2202, 36.6592]}}]}