{"type": "FeatureCollection", "id": "https://topostext.org/place/445288PHis", "name": "445288PHis", "features": [{"type": "Feature", "id": "http://data.archaeology.link/data/ancientports/2487", "label": "Istria", "dateprops": ["http://purl.org/dc/elements/1.1/created"], "properties": {"http://purl.org/dc/elements/1.1/created": ["2023"], "http://purl.org/dc/elements/1.1/creator": ["http://data.archaeology.link/data/spphaefen/arthur_de_graauw"], "http://www.opengis.net/ont/geosparql#hasGeometry": ["http://data.archaeology.link/data/ancientports/2487_geom"], "http://www.w3.org/1999/02/22-rdf-syntax-ns#type": ["http://www.ancientports.com/ont#Harbour"], "http://www.w3.org/2000/01/rdf-schema#label": ["Istria"], "http://www.w3.org/2002/07/owl#sameAs": ["http://www.wikidata.org/entity/Q1164460"], "http://www.w3.org/2004/02/skos/core#note": ["Angelescu (2018)", "Avram (2004)", "Bivolaru (2021)"], "http://www.w3.org/2006/time#hasTime": ["http://data.archaeology.link/data/ancientports/2487_foundation"], "http://www.wikidata.org/prop/direct/P1584": ["http://pleiades.stoa.org/places/216839"], "http://www.wikidata.org/prop/direct/P17": ["Romania Black S."], "http://www.wikidata.org/prop/direct/P1936": ["http://imperium.ahlfeldt.se/places/21423"], "http://www.wikidata.org/prop/direct/P1958": ["https://www.trismegistos.org/place/1068"], "http://www.wikidata.org/prop/direct/P8068": ["https://topostext.org/place/445288PHis"]}, "geometry": {"type": "Point", "coordinates": [28.7703, 44.5482]}}]}