{"type": "FeatureCollection", "id": "https://pleiades.stoa.org/places/50278", "name": "50278", "features": [{"type": "Feature", "id": "http://data.archaeology.link/data/ancientports/3867_4", "name": "Mamallapuram, Mahabalipuram, with submerged settlement offshore", "dateprops": [], "properties": {"http://purl.org/dc/elements/1.1/creator": ["http://data.archaeology.link/data/spphaefen/arthur_de_graauw"], "http://purl.org/dc/terms/isReferencedBy": ["https://en.wikipedia.org/wiki/Mamallapuram"], "http://purl.org/dc/terms/partOf": ["http://data.archaeology.link/data/ancientports/bib_deGrauw_2013_GeoDB"], "http://www.opengis.net/ont/geosparql#hasGeometry": ["http://data.archaeology.link/data/ancientports/3867_4_geom"], "http://www.w3.org/1999/02/22-rdf-syntax-ns#type": ["http://www.ancientports.com/ont#Harbour"], "http://www.w3.org/2000/01/rdf-schema#label": ["Mamallapuram, Mahabalipuram, with submerged settlement offshore"], "http://www.w3.org/2002/07/owl#sameAs": ["http://www.wikidata.org/entity/Q2554778"], "http://www.w3.org/2004/02/skos/core#note": ["Sundaresh (2011)"], "http://www.wikidata.org/prop/direct/P1584": ["https://pleiades.stoa.org/places/50278"], "http://www.wikidata.org/prop/direct/P17": ["http://www.wikidata.org/entity/Q668"], "begin": ""}, "geometry": {"type": "Point", "coordinates": [80.2024, 12.6141]}}], "numberMatched": 1, "numberReturned": 1}