{"type": "FeatureCollection", "id": "http://pleiades.stoa.org/places/256414", "name": "256414", "features": [{"type": "Feature", "id": "http://data.archaeology.link/data/ancientports/267", "label": "Alcacer do Sal, upstream of Setubal on R Sado", "properties": {"http://purl.org/dc/elements/1.1/created": ["2023"], "http://purl.org/dc/elements/1.1/creator": ["http://data.archaeology.link/data/spphaefen/arthur_de_graauw"], "http://www.ancientports.com/ont#date_min": ["-750"], "http://www.opengis.net/ont/geosparql#hasGeometry": ["http://data.archaeology.link/data/ancientports/267_geom"], "http://www.w3.org/1999/02/22-rdf-syntax-ns#type": ["http://www.ancientports.com/ont#Harbour"], "http://www.w3.org/2000/01/rdf-schema#label": ["Alcacer do Sal, upstream of Setubal on R Sado"], "http://www.w3.org/2002/07/owl#sameAs": ["http://www.wikidata.org/entity/Q850697"], "http://www.wikidata.org/prop/direct/P1584": ["http://pleiades.stoa.org/places/256414"], "http://www.wikidata.org/prop/direct/P17": ["http://www.wikidata.org/entity/Q45"], "http://www.wikidata.org/prop/direct/P1936": ["http://imperium.ahlfeldt.se/places/18348"], "http://www.wikidata.org/prop/direct/P1958": ["https://www.trismegistos.org/place/25726"], "http://www.wikidata.org/prop/direct/P8068": ["https://topostext.org/place/384000USal"]}, "geometry": {"type": "Point", "coordinates": [-8.51426, 38.36787]}}]}