{"type": "FeatureCollection", "id": "https://topostext.org/place/378248PAnd", "name": "378248PAnd", "features": [{"type": "Feature", "id": "http://data.archaeology.link/data/ancientports/2034", "name": "Paleopolis, on the isle of Andros", "dateprops": ["begin"], "properties": {"http://purl.org/dc/elements/1.1/creator": ["http://data.archaeology.link/data/spphaefen/arthur_de_graauw"], "http://purl.org/dc/terms/partOf": ["http://data.archaeology.link/data/ancientports/bib_deGrauw_2013_GeoDB"], "http://www.opengis.net/ont/geosparql#hasGeometry": ["http://data.archaeology.link/data/ancientports/2034_geom"], "http://www.w3.org/1999/02/22-rdf-syntax-ns#type": ["http://www.ancientports.com/ont#Harbour"], "http://www.w3.org/2000/01/rdf-schema#label": ["Paleopolis, on the isle of Andros"], "http://www.w3.org/2002/07/owl#sameAs": ["http://www.wikidata.org/entity/Q12882633"], "http://www.w3.org/2004/02/skos/core#note": ["Kolaiti (2020)"], "http://www.w3.org/2006/time#hasTime": ["http://data.archaeology.link/data/ancientports/2034_foundation"], "http://www.wikidata.org/prop/direct/P1584": ["http://pleiades.stoa.org/places/589692"], "http://www.wikidata.org/prop/direct/P17": ["http://www.wikidata.org/entity/Q41"], "http://www.wikidata.org/prop/direct/P1936": ["http://imperium.ahlfeldt.se/places/39550"], "http://www.wikidata.org/prop/direct/P1958": ["https://www.trismegistos.org/place/15755"], "http://www.wikidata.org/prop/direct/P8068": ["https://topostext.org/place/378248PAnd"], "begin": "-550"}, "geometry": {"type": "Point", "coordinates": [24.82498, 37.81434]}}]}