{"type": "FeatureCollection", "id": "https://topostext.org/place/378234PAig", "name": "378234PAig", "features": [{"type": "Feature", "id": "http://data.archaeology.link/data/ancientports/1867", "label": "Modern marina, on Isle of Egina", "properties": {"http://purl.org/dc/elements/1.1/created": ["2023"], "http://purl.org/dc/elements/1.1/creator": ["http://data.archaeology.link/data/spphaefen/arthur_de_graauw"], "http://www.ancientports.com/ont#date_min": ["-750"], "http://www.opengis.net/ont/geosparql#hasGeometry": ["http://data.archaeology.link/data/ancientports/1867_geom"], "http://www.w3.org/1999/02/22-rdf-syntax-ns#type": ["http://www.ancientports.com/ont#Harbour"], "http://www.w3.org/2000/01/rdf-schema#label": ["Modern marina, on Isle of Egina"], "http://www.w3.org/2004/02/skos/core#note": ["Knoblauch (1973)"], "http://www.wikidata.org/prop/direct/P1584": ["http://pleiades.stoa.org/places/579853"], "http://www.wikidata.org/prop/direct/P17": ["GR: Pelop"], "http://www.wikidata.org/prop/direct/P1936": ["http://imperium.ahlfeldt.se/places/21936"], "http://www.wikidata.org/prop/direct/P1958": ["https://www.trismegistos.org/place/77"], "http://www.wikidata.org/prop/direct/P8068": ["https://topostext.org/place/378234PAig"]}, "geometry": {"type": "Point", "coordinates": [23.4279, 37.745]}}]}