{"type": "FeatureCollection", "id": "http://pleiades.stoa.org/places/79588", "name": "79588", "features": [{"type": "Feature", "id": "http://data.archaeology.link/data/ancientports/108_4", "label": "Roman villa at Magor Farm, Illogan", "properties": {"http://purl.org/dc/elements/1.1/created": ["2023"], "http://purl.org/dc/elements/1.1/creator": ["http://data.archaeology.link/data/spphaefen/arthur_de_graauw"], "http://purl.org/dc/terms/isReferencedBy": ["https://historicengland.org.uk/listing/the-list/list-entry/1003111"], "http://www.ancientports.com/ont#date_min": ["1001"], "http://www.opengis.net/ont/geosparql#hasGeometry": ["http://data.archaeology.link/data/ancientports/108_4_geom"], "http://www.w3.org/1999/02/22-rdf-syntax-ns#type": ["http://www.ancientports.com/ont#VillaMaritima"], "http://www.w3.org/2000/01/rdf-schema#label": ["Roman villa at Magor Farm, Illogan"], "http://www.w3.org/2002/07/owl#sameAs": ["http://www.wikidata.org/entity/Q681695"], "http://www.w3.org/2004/02/skos/core#note": ["https://historicengland.org.uk/listing/the-list/list-entry/1003111"], "http://www.wikidata.org/prop/direct/P1584": ["http://pleiades.stoa.org/places/79588"], "http://www.wikidata.org/prop/direct/P17": ["http://www.wikidata.org/entity/Q145"], "http://www.wikidata.org/prop/direct/P1936": ["http://imperium.ahlfeldt.se/places/26022"]}, "geometry": {"type": "Point", "coordinates": [-5.3155, 50.234]}}]}