{"type": "FeatureCollection", "id": "http://imperium.ahlfeldt.se/places/29319", "name": "29319", "features": [{"type": "Feature", "id": "http://data.archaeology.link/data/ancientports/1668", "label": "near Agios Minas", "dateprops": [], "properties": {"http://purl.org/dc/elements/1.1/created": ["2023"], "http://purl.org/dc/elements/1.1/creator": ["http://data.archaeology.link/data/spphaefen/arthur_de_graauw"], "http://www.ancientports.com/ont#date_min": ["-750"], "http://www.opengis.net/ont/geosparql#hasGeometry": ["http://data.archaeology.link/data/ancientports/1668_geom"], "http://www.w3.org/1999/02/22-rdf-syntax-ns#type": ["http://www.ancientports.com/ont#Harbour"], "http://www.w3.org/2000/01/rdf-schema#label": ["near Agios Minas"], "http://www.wikidata.org/prop/direct/P1584": ["http://pleiades.stoa.org/places/540705"], "http://www.wikidata.org/prop/direct/P17": ["GR: Attica +"], "http://www.wikidata.org/prop/direct/P1936": ["http://imperium.ahlfeldt.se/places/29319"], "http://www.wikidata.org/prop/direct/P8068": ["https://topostext.org/place/385236UCha"]}, "geometry": {"type": "Point", "coordinates": [23.57612, 38.48578]}}]}