{"type": "FeatureCollection", "id": "http://pleiades.stoa.org/places/511227", "name": "511227", "features": [{"type": "Feature", "id": "http://data.archaeology.link/data/ancientports/2394_1", "label": "Kinalik\u00f6pr\u00fc", "dateprops": [], "properties": {"http://purl.org/dc/elements/1.1/created": ["2023"], "http://purl.org/dc/elements/1.1/creator": ["http://data.archaeology.link/data/spphaefen/arthur_de_graauw"], "http://www.opengis.net/ont/geosparql#hasGeometry": ["http://data.archaeology.link/data/ancientports/2394_1_geom"], "http://www.w3.org/1999/02/22-rdf-syntax-ns#type": ["http://www.ancientports.com/ont#Harbour"], "http://www.w3.org/2000/01/rdf-schema#label": ["Kinalik\u00f6pr\u00fc"], "http://www.w3.org/2002/07/owl#sameAs": ["http://www.wikidata.org/entity/Q5212553"], "http://www.w3.org/2004/02/skos/core#note": ["K\u00fclzer (2011)"], "http://www.wikidata.org/prop/direct/P1584": ["http://pleiades.stoa.org/places/511227"], "http://www.wikidata.org/prop/direct/P17": ["http://www.wikidata.org/entity/Q43"], "http://www.wikidata.org/prop/direct/P1936": ["http://imperium.ahlfeldt.se/places/31378"], "http://www.wikidata.org/prop/direct/P1958": ["https://www.trismegistos.org/place/61001"], "http://www.wikidata.org/prop/direct/P8068": ["https://topostext.org/place/411280UDau"]}, "geometry": {"type": "Point", "coordinates": [28.119, 41.061]}}]}