{"type": "FeatureCollection", "id": "http://pleiades.stoa.org/places/648555", "name": "648555", "features": [{"type": "Feature", "id": "http://data.archaeology.link/data/ancientports/3378", "label": "Yumuktepe, near Mersin, on R M\u00fcft\u00fc, R Efrenk", "dateprops": [], "properties": {"http://purl.org/dc/elements/1.1/created": ["2023"], "http://purl.org/dc/elements/1.1/creator": ["http://data.archaeology.link/data/spphaefen/arthur_de_graauw"], "http://www.ancientports.com/ont#date_min": ["-6000"], "http://www.opengis.net/ont/geosparql#hasGeometry": ["http://data.archaeology.link/data/ancientports/3378_geom"], "http://www.w3.org/1999/02/22-rdf-syntax-ns#type": ["http://www.ancientports.com/ont#Harbour"], "http://www.w3.org/2000/01/rdf-schema#label": ["Yumuktepe, near Mersin, on R M\u00fcft\u00fc, R Efrenk"], "http://www.w3.org/2002/07/owl#sameAs": ["http://www.wikidata.org/entity/Q4818905"], "http://www.w3.org/2004/02/skos/core#note": ["Oruc (2013)"], "http://www.wikidata.org/prop/direct/P1584": ["http://pleiades.stoa.org/places/648555"], "http://www.wikidata.org/prop/direct/P17": ["TR: South"], "http://www.wikidata.org/prop/direct/P1936": ["http://imperium.ahlfeldt.se/places/30268"], "http://www.wikidata.org/prop/direct/P1958": ["https://www.trismegistos.org/place/58777"], "http://www.wikidata.org/prop/direct/P8068": ["https://topostext.org/place/368346UAnc"]}, "geometry": {"type": "Point", "coordinates": [34.6041, 36.8013]}}]}