{"type": "FeatureCollection", "id": "http://www.wikidata.org/entity/Q7230819", "name": "Port Navas Creek", "features": [{"type": "Feature", "id": "http://data.archaeology.link/data/ancientports/106_1", "name": "", "dateprops": ["begin"], "properties": {"http://purl.org/dc/elements/1.1/creator": ["http://data.archaeology.link/data/spphaefen/arthur_de_graauw"], "http://purl.org/dc/terms/isReferencedBy": ["http://data.archaeology.link/data/ancientports/bib_Wilkes_2004_Iron", "https://historicengland.org.uk/listing/the-list/list-entry/1159524"], "http://purl.org/dc/terms/partOf": ["http://data.archaeology.link/data/ancientports/bib_deGrauw_2013_GeoDB"], "http://www.opengis.net/ont/geosparql#hasGeometry": ["http://data.archaeology.link/data/ancientports/106_1_geom"], "http://www.w3.org/1999/02/22-rdf-syntax-ns#type": ["http://www.ancientports.com/ont#Harbour"], "http://www.w3.org/2000/01/rdf-schema#label": ["Port Navas, near Gweek, on R Helford (export of tin?)"], "http://www.w3.org/2002/07/owl#sameAs": ["http://www.wikidata.org/entity/Q7230819"], "http://www.w3.org/2006/time#hasTime": ["http://data.archaeology.link/data/ancientports/106_1_foundation"], "http://www.wikidata.org/prop/direct/P17": ["http://www.wikidata.org/entity/Q145"], "begin": "5001"}, "geometry": {"type": "Point", "coordinates": [-5.1408, 50.1055]}}], "numberMatched": 1, "numberReturned": 1, "bbox": [-5.1408, 50.1055, -5.1408, 50.1055], "crs": "http://www.opengis.net/def/crs/EPSG/0/4326"}