{"type": "FeatureCollection", "id": "http://www.wikidata.org/entity/Q6984309", "name": "Neapolis (Thrace)", "features": [{"type": "Feature", "id": "http://data.archaeology.link/data/ancientports/1839", "name": "Kavala, in Macedonia", "dateprops": ["begin"], "properties": {"http://purl.org/dc/elements/1.1/created": ["2023"], "http://purl.org/dc/elements/1.1/creator": ["http://data.archaeology.link/data/spphaefen/arthur_de_graauw"], "http://www.opengis.net/ont/geosparql#hasGeometry": ["http://data.archaeology.link/data/ancientports/1839_geom"], "http://www.w3.org/1999/02/22-rdf-syntax-ns#type": ["http://www.ancientports.com/ont#Harbour"], "http://www.w3.org/2000/01/rdf-schema#label": ["Kavala, in Macedonia"], "http://www.w3.org/2002/07/owl#sameAs": ["http://www.wikidata.org/entity/Q6984309"], "http://www.w3.org/2006/time#hasTime": ["http://data.archaeology.link/data/ancientports/1839_foundation"], "http://www.wikidata.org/prop/direct/P1584": ["http://pleiades.stoa.org/places/501523"], "http://www.wikidata.org/prop/direct/P17": ["http://www.wikidata.org/entity/Q41"], "http://www.wikidata.org/prop/direct/P1936": ["http://imperium.ahlfeldt.se/places/21896"], "http://www.wikidata.org/prop/direct/P1958": ["https://www.trismegistos.org/place/12081"], "http://www.wikidata.org/prop/direct/P8068": ["https://topostext.org/place/409244PNea"], "begin": "-750"}, "geometry": {"type": "Point", "coordinates": [24.4109, 40.9349]}}]}