{"type": "FeatureCollection", "id": "http://www.wikidata.org/entity/Q641189", "name": "Sinoe Lake", "features": [{"type": "Feature", "id": "http://data.archaeology.link/data/ancientports/2487_1", "name": "", "dateprops": [], "properties": {"http://purl.org/dc/elements/1.1/creator": ["http://data.archaeology.link/data/spphaefen/arthur_de_graauw"], "http://purl.org/dc/terms/partOf": ["http://data.archaeology.link/data/ancientports/bib_deGrauw_2013_GeoDB"], "http://www.opengis.net/ont/geosparql#hasGeometry": ["http://data.archaeology.link/data/ancientports/2487_1_geom"], "http://www.w3.org/1999/02/22-rdf-syntax-ns#type": ["http://www.ancientports.com/ont#Harbour"], "http://www.w3.org/2000/01/rdf-schema#label": ["Sinoe"], "http://www.w3.org/2002/07/owl#sameAs": ["http://www.wikidata.org/entity/Q641189"], "http://www.w3.org/2004/02/skos/core#note": ["Avram (2004)"], "http://www.wikidata.org/prop/direct/P17": ["http://www.wikidata.org/entity/Q218"], "begin": ""}, "geometry": {"type": "Point", "coordinates": [28.80284, 44.62329]}}], "numberMatched": 1, "numberReturned": 1, "bbox": [28.80284, 44.62329, 28.80284, 44.62329], "crs": "http://www.opengis.net/def/crs/EPSG/0/4326"}