{"type": "FeatureCollection", "id": "http://www.wikidata.org/entity/Q43018", "name": "Q43018", "features": [{"type": "Feature", "id": "http://data.archaeology.link/data/ancientports/3170", "label": "Ayasoluk hill, near Selcuk, on R K\u00fcc\u00fck Menderes", "properties": {"http://purl.org/dc/elements/1.1/created": ["2023"], "http://purl.org/dc/elements/1.1/creator": ["http://data.archaeology.link/data/spphaefen/arthur_de_graauw"], "http://www.ancientports.com/ont#date_min": ["-1500"], "http://www.opengis.net/ont/geosparql#hasGeometry": ["http://data.archaeology.link/data/ancientports/3170_geom"], "http://www.w3.org/1999/02/22-rdf-syntax-ns#type": ["http://www.ancientports.com/ont#Harbour"], "http://www.w3.org/2000/01/rdf-schema#label": ["Ayasoluk hill, near Selcuk, on R K\u00fcc\u00fck Menderes"], "http://www.w3.org/2002/07/owl#sameAs": ["http://www.wikidata.org/entity/Q43018"], "http://www.wikidata.org/prop/direct/P1584": ["http://pleiades.stoa.org/places/873985034"], "http://www.wikidata.org/prop/direct/P17": ["TR: West"], "http://www.wikidata.org/prop/direct/P1958": ["https://www.trismegistos.org/place/51942"]}, "geometry": {"type": "Point", "coordinates": [27.3644, 37.95]}}]}