{"type": "FeatureCollection", "id": "https://www.trismegistos.org/place/369", "name": "369", "features": [{"type": "Feature", "id": "http://data.archaeology.link/data/ancientports/3908", "name": "Tell el-Atrib, near Benha", "dateprops": ["begin"], "properties": {"http://purl.org/dc/elements/1.1/creator": ["http://data.archaeology.link/data/spphaefen/arthur_de_graauw"], "http://purl.org/dc/terms/partOf": ["http://data.archaeology.link/data/ancientports/bib_deGrauw_2013_GeoDB"], "http://www.opengis.net/ont/geosparql#hasGeometry": ["http://data.archaeology.link/data/ancientports/3908_geom"], "http://www.w3.org/1999/02/22-rdf-syntax-ns#type": ["http://www.ancientports.com/ont#Harbour"], "http://www.w3.org/2000/01/rdf-schema#label": ["Tell el-Atrib, near Benha"], "http://www.w3.org/2002/07/owl#sameAs": ["http://www.wikidata.org/entity/Q755734"], "http://www.w3.org/2006/time#hasTime": ["http://data.archaeology.link/data/ancientports/3908_foundation"], "http://www.wikidata.org/prop/direct/P1584": ["http://pleiades.stoa.org/places/727078"], "http://www.wikidata.org/prop/direct/P17": ["http://www.wikidata.org/entity/Q79"], "http://www.wikidata.org/prop/direct/P1936": ["http://imperium.ahlfeldt.se/places/21704"], "http://www.wikidata.org/prop/direct/P1958": ["https://www.trismegistos.org/place/369"], "http://www.wikidata.org/prop/direct/P8068": ["https://topostext.org/place/304311UAth"], "begin": "-750"}, "geometry": {"type": "Point", "coordinates": [31.188, 30.4706]}}], "numberMatched": 1, "numberReturned": 1, "bbox": [31.188, 30.4706, 31.188, 30.4706], "crs": "http://www.opengis.net/def/crs/OGC/1.3/CRS84"}