{"type": "FeatureCollection", "id": "http://www.wikidata.org/entity/Q12062109", "name": "Q12062109", "features": [{"type": "Feature", "id": "http://data.archaeology.link/data/ancientports/84_3", "label": "The Caburn oppidum", "properties": {"http://purl.org/dc/elements/1.1/created": ["2023"], "http://purl.org/dc/elements/1.1/creator": ["http://data.archaeology.link/data/spphaefen/arthur_de_graauw"], "http://purl.org/dc/terms/isReferencedBy": ["https://historicengland.org.uk/listing/the-list/list-entry/1014527"], "http://www.ancientports.com/ont#date_min": ["-500"], "http://www.opengis.net/ont/geosparql#hasGeometry": ["http://data.archaeology.link/data/ancientports/84_3_geom"], "http://www.w3.org/1999/02/22-rdf-syntax-ns#type": ["http://www.ancientports.com/ont#Harbour"], "http://www.w3.org/2000/01/rdf-schema#label": ["The Caburn oppidum"], "http://www.w3.org/2002/07/owl#sameAs": ["http://www.wikidata.org/entity/Q12062109"], "http://www.w3.org/2004/02/skos/core#note": ["https://historicengland.org.uk/listing/the-list/list-entry/1014527"], "http://www.wikidata.org/prop/direct/P1584": ["https://pleiades.stoa.org/places/187989738"], "http://www.wikidata.org/prop/direct/P17": ["http://www.wikidata.org/entity/Q145"]}, "geometry": {"type": "Point", "coordinates": [0.051, 50.8617]}}]}