{"type": "FeatureCollection", "id": "http://www.wikidata.org/entity/Q3083368", "name": "Q3083368", "features": [{"type": "Feature", "id": "http://data.archaeology.link/data/ancientports/2896", "label": "Pasalimani, on the isle of Pasalimani Adasi", "properties": {"http://purl.org/dc/elements/1.1/created": ["2023"], "http://purl.org/dc/elements/1.1/creator": ["http://data.archaeology.link/data/spphaefen/arthur_de_graauw"], "http://www.ancientports.com/ont#date_min": ["-30"], "http://www.opengis.net/ont/geosparql#hasGeometry": ["http://data.archaeology.link/data/ancientports/2896_geom"], "http://www.w3.org/1999/02/22-rdf-syntax-ns#type": ["http://www.ancientports.com/ont#Harbour"], "http://www.w3.org/2000/01/rdf-schema#label": ["Pasalimani, on the isle of Pasalimani Adasi"], "http://www.w3.org/2002/07/owl#sameAs": ["http://www.wikidata.org/entity/Q3083368"], "http://www.wikidata.org/prop/direct/P1584": ["http://pleiades.stoa.org/places/511262"], "http://www.wikidata.org/prop/direct/P17": ["TR: Marmara S"], "http://www.wikidata.org/prop/direct/P1958": ["https://www.trismegistos.org/place/56105"]}, "geometry": {"type": "Point", "coordinates": [27.6034, 40.48719]}}]}