{"type": "FeatureCollection", "id": "http://www.wikidata.org/entity/Q31117838", "name": "Hollingbury Castle", "features": [{"type": "Feature", "id": "http://data.archaeology.link/data/ancientports/84_6", "name": "", "dateprops": ["begin"], "properties": {"http://purl.org/dc/elements/1.1/creator": ["http://data.archaeology.link/data/spphaefen/arthur_de_graauw"], "http://purl.org/dc/terms/isReferencedBy": ["https://historicengland.org.uk/listing/the-list/list-entry/1014526"], "http://purl.org/dc/terms/partOf": ["http://data.archaeology.link/data/ancientports/bib_deGrauw_2013_GeoDB"], "http://www.opengis.net/ont/geosparql#hasGeometry": ["http://data.archaeology.link/data/ancientports/84_6_geom"], "http://www.w3.org/1999/02/22-rdf-syntax-ns#type": ["http://www.ancientports.com/ont#Harbour"], "http://www.w3.org/2000/01/rdf-schema#label": ["Hollingbury Castle oppidum, Brighton"], "http://www.w3.org/2002/07/owl#sameAs": ["http://www.wikidata.org/entity/Q31117838"], "http://www.w3.org/2006/time#hasTime": ["http://data.archaeology.link/data/ancientports/84_6_foundation"], "http://www.wikidata.org/prop/direct/P17": ["http://www.wikidata.org/entity/Q145"], "begin": "-500"}, "geometry": {"type": "Point", "coordinates": [-0.123, 50.8553]}}], "numberMatched": 1, "numberReturned": 1, "bbox": [-0.123, 50.8553, -0.123, 50.8553], "crs": "http://www.opengis.net/def/crs/EPSG/0/4326"}