{"type": "FeatureCollection", "id": "https://www.trismegistos.org/place/23247", "name": "23247", "features": [{"type": "Feature", "id": "http://data.archaeology.link/data/ancientports/594", "label": "Roman villa at Pepiron, near Mauzac, and several other villas on the ridge north of R Seudre", "properties": {"http://purl.org/dc/elements/1.1/created": ["2023"], "http://purl.org/dc/elements/1.1/creator": ["http://data.archaeology.link/data/spphaefen/arthur_de_graauw"], "http://www.ancientports.com/ont#date_min": ["-200"], "http://www.opengis.net/ont/geosparql#hasGeometry": ["http://data.archaeology.link/data/ancientports/594_geom"], "http://www.w3.org/1999/02/22-rdf-syntax-ns#type": ["http://www.ancientports.com/ont#Harbour"], "http://www.w3.org/2000/01/rdf-schema#label": ["Roman villa at Pepiron, near Mauzac, and several other villas on the ridge north of R Seudre"], "http://www.w3.org/2004/02/skos/core#note": ["Tassaux (2010)"], "http://www.wikidata.org/prop/direct/P1584": ["http://pleiades.stoa.org/places/140481"], "http://www.wikidata.org/prop/direct/P17": ["France West"], "http://www.wikidata.org/prop/direct/P1936": ["http://imperium.ahlfeldt.se/places/20147"], "http://www.wikidata.org/prop/direct/P1958": ["https://www.trismegistos.org/place/23247"]}, "geometry": {"type": "Point", "coordinates": [-1.0631, 45.8049]}}]}