{"type": "FeatureCollection", "id": "http://pleiades.stoa.org/places/501515", "name": "501515", "features": [{"type": "Feature", "id": "http://data.archaeology.link/data/ancientports/1792", "name": "Kalandra", "dateprops": ["begin"], "properties": {"http://purl.org/dc/elements/1.1/creator": ["http://data.archaeology.link/data/spphaefen/arthur_de_graauw"], "http://purl.org/dc/terms/partOf": ["http://data.archaeology.link/data/ancientports/bib_deGrauw_2013_GeoDB"], "http://www.opengis.net/ont/geosparql#hasGeometry": ["http://data.archaeology.link/data/ancientports/1792_geom"], "http://www.w3.org/1999/02/22-rdf-syntax-ns#type": ["http://www.ancientports.com/ont#Harbour"], "http://www.w3.org/2000/01/rdf-schema#label": ["Kalandra"], "http://www.w3.org/2002/07/owl#sameAs": ["http://www.wikidata.org/entity/Q3305786"], "http://www.w3.org/2006/time#hasTime": ["http://data.archaeology.link/data/ancientports/1792_foundation"], "http://www.wikidata.org/prop/direct/P1584": ["http://pleiades.stoa.org/places/501515"], "http://www.wikidata.org/prop/direct/P17": ["http://www.wikidata.org/entity/Q41"], "http://www.wikidata.org/prop/direct/P1936": ["http://imperium.ahlfeldt.se/places/22701"], "http://www.wikidata.org/prop/direct/P1958": ["https://www.trismegistos.org/place/1349"], "http://www.wikidata.org/prop/direct/P8068": ["https://topostext.org/place/400234PMen"], "begin": "-750"}, "geometry": {"type": "Point", "coordinates": [23.4267, 39.96652]}}], "numberMatched": 1, "numberReturned": 1, "bbox": [23.4267, 39.96652, 23.4267, 39.96652], "crs": "http://www.opengis.net/def/crs/OGC/1.3/CRS84"}