{"type": "FeatureCollection", "id": "https://www.trismegistos.org/place/60810", "name": "60810", "features": [{"type": "Feature", "id": "http://data.archaeology.link/data/ancientports/4002", "label": "El-Hamamah, with many fish tanks and where submerged remains have been reported", "dateprops": ["http://purl.org/dc/elements/1.1/created", "http://www.ancientports.com/ont#date_min"], "properties": {"http://purl.org/dc/elements/1.1/created": ["2023"], "http://purl.org/dc/elements/1.1/creator": ["http://data.archaeology.link/data/spphaefen/arthur_de_graauw"], "http://www.ancientports.com/ont#date_min": ["-330"], "http://www.opengis.net/ont/geosparql#hasGeometry": ["http://data.archaeology.link/data/ancientports/4002_geom"], "http://www.w3.org/1999/02/22-rdf-syntax-ns#type": ["http://www.ancientports.com/ont#Lighthouse", "http://www.ancientports.com/ont#Quay"], "http://www.w3.org/2000/01/rdf-schema#label": ["El-Hamamah, with many fish tanks and where submerged remains have been reported"], "http://www.w3.org/2004/02/skos/core#note": ["Yorke (1972)"], "http://www.wikidata.org/prop/direct/P1584": ["http://pleiades.stoa.org/places/373872"], "http://www.wikidata.org/prop/direct/P17": ["http://www.wikidata.org/entity/Q1016"], "http://www.wikidata.org/prop/direct/P1936": ["http://imperium.ahlfeldt.se/places/27257"], "http://www.wikidata.org/prop/direct/P1958": ["https://www.trismegistos.org/place/60810"], "http://www.wikidata.org/prop/direct/P8068": ["https://topostext.org/place/329216HPhy"]}, "geometry": {"type": "Point", "coordinates": [21.6321, 32.9259]}}]}