{"type": "FeatureCollection", "id": "https://topostext.org/place/326349UDor", "name": "326349UDor", "features": [{"type": "Feature", "id": "http://data.archaeology.link/data/ancientports/3486_1", "name": "Dor, Dora, Moshav Bay, North Bay", "dateprops": ["begin"], "properties": {"http://purl.org/dc/elements/1.1/created": ["2023"], "http://purl.org/dc/elements/1.1/creator": ["http://data.archaeology.link/data/spphaefen/arthur_de_graauw"], "http://www.opengis.net/ont/geosparql#hasGeometry": ["http://data.archaeology.link/data/ancientports/3486_1_geom"], "http://www.w3.org/1999/02/22-rdf-syntax-ns#type": ["http://www.ancientports.com/ont#Harbour"], "http://www.w3.org/2000/01/rdf-schema#label": ["Dor, Dora, Moshav Bay, North Bay"], "http://www.w3.org/2002/07/owl#sameAs": ["http://www.wikidata.org/entity/Q2777560"], "http://www.w3.org/2004/02/skos/core#note": ["Marcus (1998)"], "http://www.w3.org/2006/time#hasTime": ["http://data.archaeology.link/data/ancientports/3486_1_foundation"], "http://www.wikidata.org/prop/direct/P1584": ["http://pleiades.stoa.org/places/678121"], "http://www.wikidata.org/prop/direct/P17": ["http://www.wikidata.org/entity/Q801"], "http://www.wikidata.org/prop/direct/P1936": ["http://imperium.ahlfeldt.se/places/21661"], "http://www.wikidata.org/prop/direct/P1958": ["https://www.trismegistos.org/place/587"], "http://www.wikidata.org/prop/direct/P8068": ["https://topostext.org/place/326349UDor"], "begin": "-2000"}, "geometry": {"type": "Point", "coordinates": [34.91774, 32.62058]}}, {"type": "Feature", "id": "http://data.archaeology.link/data/ancientports/3487", "name": "Dor, Dora, Love Bay", "dateprops": ["begin"], "properties": {"http://purl.org/dc/elements/1.1/created": ["2023"], "http://purl.org/dc/elements/1.1/creator": ["http://data.archaeology.link/data/spphaefen/arthur_de_graauw"], "http://www.opengis.net/ont/geosparql#hasGeometry": ["http://data.archaeology.link/data/ancientports/3487_geom"], "http://www.w3.org/1999/02/22-rdf-syntax-ns#type": ["http://www.ancientports.com/ont#Quay", "http://www.ancientports.com/ont#Slipway"], "http://www.w3.org/2000/01/rdf-schema#label": ["Dor, Dora, Love Bay"], "http://www.w3.org/2002/07/owl#sameAs": ["http://www.wikidata.org/entity/Q2777560"], "http://www.w3.org/2004/02/skos/core#note": ["Gambash (2017)", "Galili (2018)"], "http://www.w3.org/2006/time#hasTime": ["http://data.archaeology.link/data/ancientports/3487_foundation"], "http://www.wikidata.org/prop/direct/P1584": ["http://pleiades.stoa.org/places/678121"], "http://www.wikidata.org/prop/direct/P17": ["http://www.wikidata.org/entity/Q801"], "http://www.wikidata.org/prop/direct/P1936": ["http://imperium.ahlfeldt.se/places/21661"], "http://www.wikidata.org/prop/direct/P1958": ["https://www.trismegistos.org/place/587"], "http://www.wikidata.org/prop/direct/P8068": ["https://topostext.org/place/326349UDor"], "begin": "-750"}, "geometry": {"type": "Point", "coordinates": [34.91652, 32.6182]}}, {"type": "Feature", "id": "http://data.archaeology.link/data/ancientports/3488", "name": "Dor, Dora, Nahsholim Bay, South Bay", "dateprops": ["begin"], "properties": {"http://purl.org/dc/elements/1.1/created": ["2023"], "http://purl.org/dc/elements/1.1/creator": ["http://data.archaeology.link/data/spphaefen/arthur_de_graauw"], "http://purl.org/dc/terms/isReferencedBy": ["https://www2.rgzm.de/navis2/home/frames.htm"], "http://www.opengis.net/ont/geosparql#hasGeometry": ["http://data.archaeology.link/data/ancientports/3488_geom"], "http://www.w3.org/1999/02/22-rdf-syntax-ns#type": ["http://www.ancientports.com/ont#Warehouse", "http://www.ancientports.com/ont#Quay"], "http://www.w3.org/2000/01/rdf-schema#label": ["Dor, Dora, Nahsholim Bay, South Bay"], "http://www.w3.org/2002/07/owl#sameAs": ["http://www.wikidata.org/entity/Q2777560"], "http://www.w3.org/2004/02/skos/core#note": ["Gilboa (2015)", "Arkin Shalev (2019a)"], "http://www.w3.org/2006/time#hasTime": ["http://data.archaeology.link/data/ancientports/3488_foundation"], "http://www.wikidata.org/prop/direct/P1584": ["http://pleiades.stoa.org/places/678121"], "http://www.wikidata.org/prop/direct/P17": ["http://www.wikidata.org/entity/Q801"], "http://www.wikidata.org/prop/direct/P1936": ["http://imperium.ahlfeldt.se/places/21661"], "http://www.wikidata.org/prop/direct/P1958": ["https://www.trismegistos.org/place/587"], "http://www.wikidata.org/prop/direct/P8068": ["https://topostext.org/place/326349UDor"], "begin": "-1200"}, "geometry": {"type": "Point", "coordinates": [34.91683, 32.61595]}}]}