{"type": "FeatureCollection", "id": "http://imperium.ahlfeldt.se/places/25168", "name": "25168", "features": [{"type": "Feature", "id": "http://data.archaeology.link/data/ancientports/2963", "label": "Poros isthmus to Kalydon-Spinalonga peninsula, at the south end of large Elounda bay", "dateprops": ["http://purl.org/dc/elements/1.1/created", "http://www.ancientports.com/ont#date_min"], "properties": {"http://purl.org/dc/elements/1.1/created": ["2023"], "http://purl.org/dc/elements/1.1/creator": ["http://data.archaeology.link/data/spphaefen/arthur_de_graauw"], "http://purl.org/dc/terms/isReferencedBy": ["https://www.tornosnews.gr/en/greek-news/culture/38942-submerged-buildings-found-in-ancient-city-and-modern-luxury-resort-of-crete.html"], "http://www.ancientports.com/ont#date_min": ["-1500"], "http://www.opengis.net/ont/geosparql#hasGeometry": ["http://data.archaeology.link/data/ancientports/2963_geom"], "http://www.w3.org/1999/02/22-rdf-syntax-ns#type": ["http://www.ancientports.com/ont#Harbour"], "http://www.w3.org/2000/01/rdf-schema#label": ["Poros isthmus to Kalydon-Spinalonga peninsula, at the south end of large Elounda bay"], "http://www.w3.org/2002/07/owl#sameAs": ["http://www.wikidata.org/entity/Q2215268"], "http://www.w3.org/2004/02/skos/core#note": ["Mourtzas (2022)", "Theodoulou (2015b)"], "http://www.wikidata.org/prop/direct/P1584": ["http://pleiades.stoa.org/places/589959"], "http://www.wikidata.org/prop/direct/P17": ["GR: Crete North"], "http://www.wikidata.org/prop/direct/P1936": ["http://imperium.ahlfeldt.se/places/25168"], "http://www.wikidata.org/prop/direct/P1958": ["https://www.trismegistos.org/place/1493"], "http://www.wikidata.org/prop/direct/P8068": ["https://topostext.org/place/353257POlo"]}, "geometry": {"type": "Point", "coordinates": [25.73583, 35.25577]}}]}