{"type": "FeatureCollection", "id": "https://www.trismegistos.org/place/2267", "name": "2267", "features": [{"type": "Feature", "id": "http://data.archaeology.link/data/ancientports/1100", "name": "Tarento, Taranto, Scoglio del Tonno", "dateprops": ["begin"], "properties": {"http://purl.org/dc/elements/1.1/created": ["2023"], "http://purl.org/dc/elements/1.1/creator": ["http://data.archaeology.link/data/spphaefen/arthur_de_graauw"], "http://www.opengis.net/ont/geosparql#hasGeometry": ["http://data.archaeology.link/data/ancientports/1100_geom"], "http://www.w3.org/1999/02/22-rdf-syntax-ns#type": ["http://www.ancientports.com/ont#Harbour"], "http://www.w3.org/2000/01/rdf-schema#label": ["Tarento, Taranto, Scoglio del Tonno"], "http://www.w3.org/2002/07/owl#sameAs": ["http://www.wikidata.org/entity/Q13498"], "http://www.w3.org/2006/time#hasTime": ["http://data.archaeology.link/data/ancientports/1100_foundation"], "http://www.wikidata.org/prop/direct/P1584": ["http://pleiades.stoa.org/places/442810"], "http://www.wikidata.org/prop/direct/P17": ["http://www.wikidata.org/entity/Q38"], "http://www.wikidata.org/prop/direct/P1936": ["http://imperium.ahlfeldt.se/places/16562"], "http://www.wikidata.org/prop/direct/P1958": ["https://www.trismegistos.org/place/2267"], "http://www.wikidata.org/prop/direct/P8068": ["https://topostext.org/place/405172PTar"], "begin": "-750"}, "geometry": {"type": "Point", "coordinates": [17.22814, 40.47203]}}]}