{"type": "FeatureCollection", "id": "http://www.wikidata.org/entity/Q5732573", "name": "Q5732573", "features": [{"type": "Feature", "id": "http://data.archaeology.link/data/ancientports/1565", "label": "Vonitsa, Bonditza", "dateprops": ["http://purl.org/dc/elements/1.1/created"], "properties": {"http://purl.org/dc/elements/1.1/created": ["2023"], "http://purl.org/dc/elements/1.1/creator": ["http://data.archaeology.link/data/spphaefen/arthur_de_graauw"], "http://www.opengis.net/ont/geosparql#hasGeometry": ["http://data.archaeology.link/data/ancientports/1565_geom"], "http://www.w3.org/1999/02/22-rdf-syntax-ns#type": ["http://www.ancientports.com/ont#Harbour"], "http://www.w3.org/2000/01/rdf-schema#label": ["Vonitsa, Bonditza"], "http://www.w3.org/2002/07/owl#sameAs": ["http://www.wikidata.org/entity/Q5732573"], "http://www.wikidata.org/prop/direct/P17": ["GR: North-West"], "http://www.wikidata.org/prop/direct/P1936": ["http://dare.ht.lu.se/places/31559"], "http://www.wikidata.org/prop/direct/P8068": ["https://topostext.org/place/389209PHer"]}, "geometry": {"type": "Point", "coordinates": [20.8946, 38.9204]}}]}