{"type": "FeatureCollection", "id": "https://www.trismegistos.org/place/40992", "name": "40992", "features": [{"type": "Feature", "id": "http://data.archaeology.link/data/ancientports/4056", "label": "Bir Usaylah, Red Valley ", "dateprops": ["http://purl.org/dc/elements/1.1/created"], "properties": {"http://purl.org/dc/elements/1.1/created": ["2023"], "http://purl.org/dc/elements/1.1/creator": ["http://data.archaeology.link/data/spphaefen/arthur_de_graauw"], "http://www.opengis.net/ont/geosparql#hasGeometry": ["http://data.archaeology.link/data/ancientports/4056_geom"], "http://www.w3.org/1999/02/22-rdf-syntax-ns#type": ["http://www.ancientports.com/ont#Harbour"], "http://www.w3.org/2000/01/rdf-schema#label": ["Bir Usaylah, Red Valley "], "http://www.w3.org/2006/time#hasTime": ["http://data.archaeology.link/data/ancientports/4056_foundation"], "http://www.wikidata.org/prop/direct/P1584": ["http://pleiades.stoa.org/places/363930"], "http://www.wikidata.org/prop/direct/P17": ["http://www.wikidata.org/entity/Q1016"], "http://www.wikidata.org/prop/direct/P1936": ["http://imperium.ahlfeldt.se/places/23615"], "http://www.wikidata.org/prop/direct/P1958": ["https://www.trismegistos.org/place/40992"]}, "geometry": {"type": "Point", "coordinates": [17.4397, 31.0447]}}]}