{"type": "FeatureCollection", "id": "http://pleiades.stoa.org/places/363978", "name": "363978", "features": [{"type": "Feature", "id": "http://data.archaeology.link/data/ancientports/4061", "label": "Several Roman villas near Jabiat Escout ", "dateprops": ["http://purl.org/dc/elements/1.1/created"], "properties": {"http://purl.org/dc/elements/1.1/created": ["2023"], "http://purl.org/dc/elements/1.1/creator": ["http://data.archaeology.link/data/spphaefen/arthur_de_graauw"], "http://www.opengis.net/ont/geosparql#hasGeometry": ["http://data.archaeology.link/data/ancientports/4061_geom"], "http://www.w3.org/1999/02/22-rdf-syntax-ns#type": ["http://www.ancientports.com/ont#VillaMaritima"], "http://www.w3.org/2000/01/rdf-schema#label": ["Several Roman villas near Jabiat Escout "], "http://www.w3.org/2006/time#hasTime": ["http://data.archaeology.link/data/ancientports/4061_foundation"], "http://www.wikidata.org/prop/direct/P1584": ["http://pleiades.stoa.org/places/363978"], "http://www.wikidata.org/prop/direct/P17": ["http://www.wikidata.org/entity/Q1016"], "http://www.wikidata.org/prop/direct/P1936": ["http://imperium.ahlfeldt.se/places/27209"]}, "geometry": {"type": "Point", "coordinates": [16.77199, 31.21318]}}]}