{"type": "FeatureCollection", "id": "http://imperium.ahlfeldt.se/places/27215", "name": "27215", "features": [{"type": "Feature", "id": "http://data.archaeology.link/data/ancientports/4015", "name": "Ain Zeina, near Kuwayfiyah ", "dateprops": ["begin"], "properties": {"http://purl.org/dc/elements/1.1/created": ["2023"], "http://purl.org/dc/elements/1.1/creator": ["http://data.archaeology.link/data/spphaefen/arthur_de_graauw"], "http://www.opengis.net/ont/geosparql#hasGeometry": ["http://data.archaeology.link/data/ancientports/4015_geom"], "http://www.w3.org/1999/02/22-rdf-syntax-ns#type": ["http://www.ancientports.com/ont#Harbour"], "http://www.w3.org/2000/01/rdf-schema#label": ["Ain Zeina, near Kuwayfiyah "], "http://www.w3.org/2006/time#hasTime": ["http://data.archaeology.link/data/ancientports/4015_foundation"], "http://www.wikidata.org/prop/direct/P1584": ["http://pleiades.stoa.org/places/373728"], "http://www.wikidata.org/prop/direct/P17": ["http://www.wikidata.org/entity/Q1016"], "http://www.wikidata.org/prop/direct/P1936": ["http://imperium.ahlfeldt.se/places/27215"], "begin": "-30"}, "geometry": {"type": "Point", "coordinates": [20.1447, 32.2194]}}]}