{"type": "FeatureCollection", "id": "http://www.wikidata.org/entity/Q21484003", "name": "Dium (Chalcidice)", "features": [{"type": "Feature", "id": "http://data.archaeology.link/data/ancientports/1825", "name": "Ormos Plati", "dateprops": ["begin"], "properties": {"http://purl.org/dc/elements/1.1/created": ["2023"], "http://purl.org/dc/elements/1.1/creator": ["http://data.archaeology.link/data/spphaefen/arthur_de_graauw"], "http://www.opengis.net/ont/geosparql#hasGeometry": ["http://data.archaeology.link/data/ancientports/1825_geom"], "http://www.w3.org/1999/02/22-rdf-syntax-ns#type": ["http://www.ancientports.com/ont#Harbour"], "http://www.w3.org/2000/01/rdf-schema#label": ["Ormos Plati"], "http://www.w3.org/2002/07/owl#sameAs": ["http://www.wikidata.org/entity/Q21484003"], "http://www.w3.org/2006/time#hasTime": ["http://data.archaeology.link/data/ancientports/1825_foundation"], "http://www.wikidata.org/prop/direct/P1584": ["http://pleiades.stoa.org/places/501400"], "http://www.wikidata.org/prop/direct/P17": ["http://www.wikidata.org/entity/Q41"], "http://www.wikidata.org/prop/direct/P1936": ["http://imperium.ahlfeldt.se/places/32317"], "http://www.wikidata.org/prop/direct/P8068": ["https://topostext.org/place/404242PDio"], "begin": "-550"}, "geometry": {"type": "Point", "coordinates": [24.1533, 40.3576]}}]}