{"type": "FeatureCollection", "id": "http://www.wikidata.org/entity/Q2933591", "name": "Calanque d%27En-Vau", "features": [{"type": "Feature", "id": "http://data.archaeology.link/data/ancientports/673", "name": "Calanque d'En-vau", "dateprops": [], "properties": {"http://purl.org/dc/elements/1.1/created": ["2023"], "http://purl.org/dc/elements/1.1/creator": ["http://data.archaeology.link/data/spphaefen/arthur_de_graauw"], "http://www.opengis.net/ont/geosparql#hasGeometry": ["http://data.archaeology.link/data/ancientports/673_geom"], "http://www.w3.org/1999/02/22-rdf-syntax-ns#type": ["http://www.ancientports.com/ont#Harbour"], "http://www.w3.org/2000/01/rdf-schema#label": ["Calanque d'En-vau"], "http://www.w3.org/2002/07/owl#sameAs": ["http://www.wikidata.org/entity/Q2933591"], "http://www.w3.org/2004/02/skos/core#note": ["Arnaud (2004)"], "http://www.wikidata.org/prop/direct/P17": ["http://www.wikidata.org/entity/Q142"], "begin": ""}, "geometry": {"type": "Point", "coordinates": [5.49784, 43.20237]}}]}