{"type": "FeatureCollection", "id": "http://imperium.ahlfeldt.se/places/21893", "name": "21893", "features": [{"type": "Feature", "id": "http://data.archaeology.link/data/ancientports/1773_2", "label": "Aigeai, Vergina", "dateprops": ["http://purl.org/dc/elements/1.1/created"], "properties": {"http://purl.org/dc/elements/1.1/created": ["2023"], "http://purl.org/dc/elements/1.1/creator": ["http://data.archaeology.link/data/spphaefen/arthur_de_graauw"], "http://purl.org/dc/terms/isReferencedBy": ["https://en.wikipedia.org/wiki/Vergina"], "http://www.opengis.net/ont/geosparql#hasGeometry": ["http://data.archaeology.link/data/ancientports/1773_2_geom"], "http://www.w3.org/1999/02/22-rdf-syntax-ns#type": ["http://www.ancientports.com/ont#Harbour"], "http://www.w3.org/2000/01/rdf-schema#label": ["Aigeai, Vergina"], "http://www.w3.org/2002/07/owl#sameAs": ["http://www.wikidata.org/entity/Q16963755"], "http://www.w3.org/2006/time#hasTime": ["http://data.archaeology.link/data/ancientports/1773_2_foundation"], "http://www.wikidata.org/prop/direct/P1584": ["http://pleiades.stoa.org/places/491512"], "http://www.wikidata.org/prop/direct/P17": ["GR: North-East"], "http://www.wikidata.org/prop/direct/P1936": ["http://imperium.ahlfeldt.se/places/21893"], "http://www.wikidata.org/prop/direct/P1958": ["https://www.trismegistos.org/place/30329"], "http://www.wikidata.org/prop/direct/P8068": ["https://topostext.org/place/405223PAig"]}, "geometry": {"type": "Point", "coordinates": [22.3223, 40.4779]}}]}