{"type": "FeatureCollection", "id": "https://topostext.org/place/317250UPet", "name": "317250UPet", "features": [{"type": "Feature", "id": "http://data.archaeology.link/data/ancientports/3976", "name": "Bardia", "dateprops": ["begin"], "properties": {"http://purl.org/dc/elements/1.1/creator": ["http://data.archaeology.link/data/spphaefen/arthur_de_graauw"], "http://purl.org/dc/terms/isReferencedBy": ["http://data.archaeology.link/data/ancientports/bib_Laronde_1992_Aspects"], "http://purl.org/dc/terms/partOf": ["http://data.archaeology.link/data/ancientports/bib_deGrauw_2013_GeoDB"], "http://www.opengis.net/ont/geosparql#hasGeometry": ["http://data.archaeology.link/data/ancientports/3976_geom"], "http://www.w3.org/1999/02/22-rdf-syntax-ns#type": ["http://www.ancientports.com/ont#Harbour"], "http://www.w3.org/2000/01/rdf-schema#label": ["Bardia"], "http://www.w3.org/2002/07/owl#sameAs": ["http://www.wikidata.org/entity/Q141687"], "http://www.w3.org/2006/time#hasTime": ["http://data.archaeology.link/data/ancientports/3976_foundation"], "http://www.wikidata.org/prop/direct/P1584": ["http://pleiades.stoa.org/places/716619"], "http://www.wikidata.org/prop/direct/P17": ["http://www.wikidata.org/entity/Q1016"], "http://www.wikidata.org/prop/direct/P1936": ["http://imperium.ahlfeldt.se/places/41004"], "http://www.wikidata.org/prop/direct/P1958": ["https://www.trismegistos.org/place/11124"], "http://www.wikidata.org/prop/direct/P8068": ["https://topostext.org/place/317250UPet"], "begin": "-330"}, "geometry": {"type": "Point", "coordinates": [25.10202, 31.75919]}}]}