{"type": "FeatureCollection", "id": "http://imperium.ahlfeldt.se/places/22696", "name": "22696", "features": [{"type": "Feature", "id": "http://data.archaeology.link/data/ancientports/2848", "label": "Area between Yeni Valide Mosque and Mihrimah Mosque at \u00dcsk\u00fcdar, at outlet of former rivers R Cavus and R B\u00fclb\u00fcl", "dateprops": ["http://purl.org/dc/elements/1.1/created"], "properties": {"http://purl.org/dc/elements/1.1/created": ["2023"], "http://purl.org/dc/elements/1.1/creator": ["http://data.archaeology.link/data/spphaefen/arthur_de_graauw"], "http://www.opengis.net/ont/geosparql#hasGeometry": ["http://data.archaeology.link/data/ancientports/2848_geom"], "http://www.w3.org/1999/02/22-rdf-syntax-ns#type": ["http://www.ancientports.com/ont#Harbour"], "http://www.w3.org/2000/01/rdf-schema#label": ["Area between Yeni Valide Mosque and Mihrimah Mosque at \u00dcsk\u00fcdar, at outlet of former rivers R Cavus and R B\u00fclb\u00fcl"], "http://www.w3.org/2002/07/owl#sameAs": ["http://www.wikidata.org/entity/Q326339"], "http://www.w3.org/2004/02/skos/core#note": ["K\u00fclzer (2011)"], "http://www.w3.org/2006/time#hasTime": ["http://data.archaeology.link/data/ancientports/2848_foundation"], "http://www.wikidata.org/prop/direct/P1584": ["http://pleiades.stoa.org/places/521001"], "http://www.wikidata.org/prop/direct/P17": ["TR: Bosph S"], "http://www.wikidata.org/prop/direct/P1936": ["http://imperium.ahlfeldt.se/places/22696"], "http://www.wikidata.org/prop/direct/P1958": ["https://www.trismegistos.org/place/41365"], "http://www.wikidata.org/prop/direct/P8068": ["https://topostext.org/place/410290UChr"]}, "geometry": {"type": "Point", "coordinates": [29.0155, 41.0259]}}]}