{"type": "FeatureCollection", "id": "https://pleiades.stoa.org/places/39280", "name": "39280", "features": [{"type": "Feature", "id": "http://data.archaeology.link/data/ancientports/3651", "label": "Near Zamzam? Jizan?", "properties": {"http://purl.org/dc/elements/1.1/created": ["2023"], "http://purl.org/dc/elements/1.1/creator": ["http://data.archaeology.link/data/spphaefen/arthur_de_graauw"], "http://www.opengis.net/ont/geosparql#hasGeometry": ["http://data.archaeology.link/data/ancientports/3651_geom"], "http://www.w3.org/1999/02/22-rdf-syntax-ns#type": ["http://www.ancientports.com/ont#Harbour"], "http://www.w3.org/2000/01/rdf-schema#label": ["Near Zamzam? Jizan?"], "http://www.wikidata.org/prop/direct/P1584": ["https://pleiades.stoa.org/places/39280"], "http://www.wikidata.org/prop/direct/P17": ["Saudi Arabia: Red Sea"]}, "geometry": {"type": "Point", "coordinates": [42.739, 16.457]}}]}