{"type": "FeatureCollection", "id": "https://www.trismegistos.org/place/26217", "name": "26217", "features": [{"type": "Feature", "id": "http://data.archaeology.link/data/ancientports/319", "label": "Torre de los Herberos, at Dos Hermanas", "properties": {"http://purl.org/dc/elements/1.1/created": ["2023"], "http://purl.org/dc/elements/1.1/creator": ["http://data.archaeology.link/data/spphaefen/arthur_de_graauw"], "http://www.ancientports.com/ont#date_min": ["-330"], "http://www.opengis.net/ont/geosparql#hasGeometry": ["http://data.archaeology.link/data/ancientports/319_geom"], "http://www.w3.org/1999/02/22-rdf-syntax-ns#type": ["http://www.ancientports.com/ont#Harbour"], "http://www.w3.org/2000/01/rdf-schema#label": ["Torre de los Herberos, at Dos Hermanas"], "http://www.w3.org/2002/07/owl#sameAs": ["http://www.wikidata.org/entity/Q489205"], "http://www.wikidata.org/prop/direct/P1584": ["http://pleiades.stoa.org/places/256343"], "http://www.wikidata.org/prop/direct/P17": ["http://www.wikidata.org/entity/Q29"], "http://www.wikidata.org/prop/direct/P1958": ["https://www.trismegistos.org/place/26217"]}, "geometry": {"type": "Point", "coordinates": [-6.0043, 37.27413]}}]}