{"type": "FeatureCollection", "id": "http://pleiades.stoa.org/places/409239", "name": "409239", "features": [{"type": "Feature", "id": "http://data.archaeology.link/data/ancientports/852", "label": "Roman villa at San Piero a Grado, near Pisa on R Arno", "properties": {"http://purl.org/dc/elements/1.1/created": ["2023"], "http://purl.org/dc/elements/1.1/creator": ["http://data.archaeology.link/data/spphaefen/arthur_de_graauw"], "http://purl.org/dc/terms/isReferencedBy": ["https://www2.rgzm.de/navis2/home/frames.htm"], "http://www.ancientports.com/ont#date_min": ["-30"], "http://www.opengis.net/ont/geosparql#hasGeometry": ["http://data.archaeology.link/data/ancientports/852_geom"], "http://www.w3.org/1999/02/22-rdf-syntax-ns#type": ["http://www.ancientports.com/ont#VillaMaritima"], "http://www.w3.org/2000/01/rdf-schema#label": ["Roman villa at San Piero a Grado, near Pisa on R Arno"], "http://www.w3.org/2002/07/owl#sameAs": ["http://www.wikidata.org/entity/Q810100"], "http://www.w3.org/2004/02/skos/core#note": ["Camilli (2004)", "Camilli (2005)", "https://www2.rgzm.de/navis2/home/frames.htm"], "http://www.wikidata.org/prop/direct/P1584": ["http://pleiades.stoa.org/places/409239"], "http://www.wikidata.org/prop/direct/P17": ["Italy West"], "http://www.wikidata.org/prop/direct/P1936": ["http://imperium.ahlfeldt.se/places/22570"]}, "geometry": {"type": "Point", "coordinates": [10.346, 43.68]}}]}