{"type": "FeatureCollection", "id": "http://pleiades.stoa.org/places/599755", "name": "599755", "features": [{"type": "Feature", "id": "http://data.archaeology.link/data/ancientports/2118", "label": "Ormos Levitha, on the isle of Levitha", "properties": {"http://purl.org/dc/elements/1.1/created": ["2023"], "http://purl.org/dc/elements/1.1/creator": ["http://data.archaeology.link/data/spphaefen/arthur_de_graauw"], "http://www.opengis.net/ont/geosparql#hasGeometry": ["http://data.archaeology.link/data/ancientports/2118_geom"], "http://www.w3.org/1999/02/22-rdf-syntax-ns#type": ["http://www.ancientports.com/ont#Harbour"], "http://www.w3.org/2000/01/rdf-schema#label": ["Ormos Levitha, on the isle of Levitha"], "http://www.w3.org/2002/07/owl#sameAs": ["http://www.wikidata.org/entity/Q1756721"], "http://www.wikidata.org/prop/direct/P1584": ["http://pleiades.stoa.org/places/599755"], "http://www.wikidata.org/prop/direct/P17": ["GR: Cyclades Isl."]}, "geometry": {"type": "Point", "coordinates": [26.47055, 37.0022]}}]}