{"type": "FeatureCollection", "id": "http://pleiades.stoa.org/places/550697", "name": "550697", "features": [{"type": "Feature", "id": "http://data.archaeology.link/data/ancientports/3141", "label": "island Kus Cenneti, at Uc Tepeler, now connected to the continent, on R Gediz", "properties": {"http://purl.org/dc/elements/1.1/created": ["2023"], "http://purl.org/dc/elements/1.1/creator": ["http://data.archaeology.link/data/spphaefen/arthur_de_graauw"], "http://www.ancientports.com/ont#date_min": ["-550"], "http://www.opengis.net/ont/geosparql#hasGeometry": ["http://data.archaeology.link/data/ancientports/3141_geom"], "http://www.w3.org/1999/02/22-rdf-syntax-ns#type": ["http://www.ancientports.com/ont#Harbour"], "http://www.w3.org/2000/01/rdf-schema#label": ["island Kus Cenneti, at Uc Tepeler, now connected to the continent, on R Gediz"], "http://www.w3.org/2002/07/owl#sameAs": ["http://www.wikidata.org/entity/Q1743491"], "http://www.wikidata.org/prop/direct/P1584": ["http://pleiades.stoa.org/places/550697"], "http://www.wikidata.org/prop/direct/P17": ["TR: West"], "http://www.wikidata.org/prop/direct/P1958": ["https://www.trismegistos.org/place/16237"]}, "geometry": {"type": "Point", "coordinates": [26.856, 38.5466]}}]}