{"type": "FeatureCollection", "id": "http://www.wikidata.org/entity/Q1010891", "name": "Aizier", "features": [{"type": "Feature", "id": "http://data.archaeology.link/data/ancientports/525_4", "name": "Aizier, on R Seine", "dateprops": [], "properties": {"http://purl.org/dc/elements/1.1/created": ["2023"], "http://purl.org/dc/elements/1.1/creator": ["http://data.archaeology.link/data/spphaefen/arthur_de_graauw"], "http://www.opengis.net/ont/geosparql#hasGeometry": ["http://data.archaeology.link/data/ancientports/525_4_geom"], "http://www.w3.org/1999/02/22-rdf-syntax-ns#type": ["http://www.ancientports.com/ont#Harbour"], "http://www.w3.org/2000/01/rdf-schema#label": ["Aizier, on R Seine"], "http://www.w3.org/2002/07/owl#sameAs": ["http://www.wikidata.org/entity/Q1010891"], "http://www.w3.org/2004/02/skos/core#note": ["Arthuis (2010)", "Mouchard (2021)"], "http://www.wikidata.org/prop/direct/P17": ["http://www.wikidata.org/entity/Q142"], "begin": ""}, "geometry": {"type": "Point", "coordinates": [0.6249, 49.4308]}}]}