{"type": "FeatureCollection", "id": "http://imperium.ahlfeldt.se/places/27964", "name": "27964", "features": [{"type": "Feature", "id": "http://data.archaeology.link/data/ancientports/2557", "name": "Rybal'chye", "dateprops": ["begin"], "properties": {"http://purl.org/dc/elements/1.1/created": ["2023"], "http://purl.org/dc/elements/1.1/creator": ["http://data.archaeology.link/data/spphaefen/arthur_de_graauw"], "http://www.opengis.net/ont/geosparql#hasGeometry": ["http://data.archaeology.link/data/ancientports/2557_geom"], "http://www.w3.org/1999/02/22-rdf-syntax-ns#type": ["http://www.ancientports.com/ont#Harbour"], "http://www.w3.org/2000/01/rdf-schema#label": ["Rybal'chye"], "http://www.w3.org/2006/time#hasTime": ["http://data.archaeology.link/data/ancientports/2557_foundation"], "http://www.wikidata.org/prop/direct/P1584": ["http://pleiades.stoa.org/places/226743"], "http://www.wikidata.org/prop/direct/P17": ["Ukraine Black S."], "http://www.wikidata.org/prop/direct/P1936": ["http://imperium.ahlfeldt.se/places/27964"], "begin": "-550"}, "geometry": {"type": "Point", "coordinates": [32.2345, 46.4809]}}]}