{"type": "FeatureCollection", "id": "http://www.wikidata.org/entity/Q461426", "name": "Lo%C5%A1inj", "features": [{"type": "Feature", "id": "http://data.archaeology.link/data/ancientports/1411", "name": "", "dateprops": [], "properties": {"http://purl.org/dc/elements/1.1/creator": ["http://data.archaeology.link/data/spphaefen/arthur_de_graauw"], "http://purl.org/dc/terms/partOf": ["http://data.archaeology.link/data/ancientports/bib_deGrauw_2013_GeoDB"], "http://www.opengis.net/ont/geosparql#hasGeometry": ["http://data.archaeology.link/data/ancientports/1411_geom"], "http://www.w3.org/1999/02/22-rdf-syntax-ns#type": ["http://www.ancientports.com/ont#Harbour", "http://www.ancientports.com/ont#PotentialHarbour"], "http://www.w3.org/2000/01/rdf-schema#label": ["Luka Krivica, on the isle of Losinj"], "http://www.w3.org/2002/07/owl#sameAs": ["http://www.wikidata.org/entity/Q461426"], "http://www.wikidata.org/prop/direct/P17": ["http://www.wikidata.org/entity/Q224"], "begin": ""}, "geometry": {"type": "Point", "coordinates": [14.49522, 44.50067]}}], "numberMatched": 1, "numberReturned": 1, "bbox": [14.49522, 44.50067, 14.49522, 44.50067], "crs": "http://www.opengis.net/def/crs/EPSG/0/4326"}