{"type": "FeatureCollection", "id": "http://pleiades.stoa.org/places/570724", "name": "570724", "features": [{"type": "Feature", "id": "http://data.archaeology.link/data/ancientports/1877", "label": "Thermisia", "dateprops": ["http://purl.org/dc/elements/1.1/created", "http://www.ancientports.com/ont#date_min"], "properties": {"http://purl.org/dc/elements/1.1/created": ["2023"], "http://purl.org/dc/elements/1.1/creator": ["http://data.archaeology.link/data/spphaefen/arthur_de_graauw"], "http://www.ancientports.com/ont#date_min": ["-550"], "http://www.opengis.net/ont/geosparql#hasGeometry": ["http://data.archaeology.link/data/ancientports/1877_geom"], "http://www.w3.org/1999/02/22-rdf-syntax-ns#type": ["http://www.ancientports.com/ont#Harbour"], "http://www.w3.org/2000/01/rdf-schema#label": ["Thermisia"], "http://www.wikidata.org/prop/direct/P1584": ["http://pleiades.stoa.org/places/570724"], "http://www.wikidata.org/prop/direct/P17": ["GR: Pelop"], "http://www.wikidata.org/prop/direct/P1936": ["http://imperium.ahlfeldt.se/places/31083"], "http://www.wikidata.org/prop/direct/P8068": ["https://topostext.org/place/374233UThe"]}, "geometry": {"type": "Point", "coordinates": [23.3259, 37.4089]}}]}