{"type": "FeatureCollection", "id": "http://www.wikidata.org/entity/Q45301", "name": "Trabzon", "features": [{"type": "Feature", "id": "http://data.archaeology.link/data/ancientports/2727", "name": "Trabzon, on R Degirmendere, note Stephanus mentions 'Sidarus Trapezuntius' ", "dateprops": ["begin"], "properties": {"http://purl.org/dc/elements/1.1/creator": ["http://data.archaeology.link/data/spphaefen/arthur_de_graauw"], "http://purl.org/dc/terms/isReferencedBy": ["https://pontosworld.com/index.php/pontus/places/206-pyxites-river-degirmendere"], "http://purl.org/dc/terms/partOf": ["http://data.archaeology.link/data/ancientports/bib_deGrauw_2013_GeoDB"], "http://www.opengis.net/ont/geosparql#hasGeometry": ["http://data.archaeology.link/data/ancientports/2727_geom"], "http://www.w3.org/1999/02/22-rdf-syntax-ns#type": ["http://www.ancientports.com/ont#Harbour"], "http://www.w3.org/2000/01/rdf-schema#label": ["Trabzon, on R Degirmendere, note Stephanus mentions 'Sidarus Trapezuntius' "], "http://www.w3.org/2002/07/owl#sameAs": ["http://www.wikidata.org/entity/Q45301"], "http://www.w3.org/2004/02/skos/core#note": ["Saprykin (2017)"], "http://www.w3.org/2006/time#hasTime": ["http://data.archaeology.link/data/ancientports/2727_foundation"], "http://www.wikidata.org/prop/direct/P1584": ["http://pleiades.stoa.org/places/857359"], "http://www.wikidata.org/prop/direct/P17": ["http://www.wikidata.org/entity/Q43"], "http://www.wikidata.org/prop/direct/P1936": ["http://imperium.ahlfeldt.se/places/21165"], "http://www.wikidata.org/prop/direct/P1958": ["https://www.trismegistos.org/place/12808"], "http://www.wikidata.org/prop/direct/P8068": ["https://topostext.org/place/410397PTra"], "begin": "-750"}, "geometry": {"type": "Point", "coordinates": [39.73909, 41.00491]}}], "numberMatched": 1, "numberReturned": 1, "bbox": [39.73909, 41.00491, 39.73909, 41.00491], "crs": "http://www.opengis.net/def/crs/EPSG/0/4326"}