{"type": "FeatureCollection", "id": "http://www.wikidata.org/entity/Q10313", "name": "Q10313", "features": [{"type": "Feature", "id": "http://data.archaeology.link/data/ancientports/172_2", "label": "San Sebastien", "properties": {"http://purl.org/dc/elements/1.1/created": ["2023"], "http://purl.org/dc/elements/1.1/creator": ["http://data.archaeology.link/data/spphaefen/arthur_de_graauw"], "http://www.opengis.net/ont/geosparql#hasGeometry": ["http://data.archaeology.link/data/ancientports/172_2_geom"], "http://www.w3.org/1999/02/22-rdf-syntax-ns#type": ["http://www.ancientports.com/ont#Harbour"], "http://www.w3.org/2000/01/rdf-schema#label": ["San Sebastien"], "http://www.w3.org/2002/07/owl#sameAs": ["http://www.wikidata.org/entity/Q10313"], "http://www.wikidata.org/prop/direct/P17": ["Spain North"]}, "geometry": {"type": "Point", "coordinates": [-1.991, 43.317]}}]}