{"type": "FeatureCollection", "id": "http://pleiades.stoa.org/places/668216", "name": "668216", "features": [{"type": "Feature", "id": "http://data.archaeology.link/data/ancientports/3451", "label": "Jbeil, bay of Jouret Osman, north of bay of el-Skhiny, near outlet of R Nahr Qassouba", "properties": {"http://purl.org/dc/elements/1.1/created": ["2023"], "http://purl.org/dc/elements/1.1/creator": ["http://data.archaeology.link/data/spphaefen/arthur_de_graauw"], "http://www.ancientports.com/ont#date_min": ["-550"], "http://www.opengis.net/ont/geosparql#hasGeometry": ["http://data.archaeology.link/data/ancientports/3451_geom"], "http://www.w3.org/1999/02/22-rdf-syntax-ns#type": ["http://www.ancientports.com/ont#Harbour"], "http://www.w3.org/2000/01/rdf-schema#label": ["Jbeil, bay of Jouret Osman, north of bay of el-Skhiny, near outlet of R Nahr Qassouba"], "http://www.w3.org/2002/07/owl#sameAs": ["http://www.wikidata.org/entity/Q173532"], "http://www.wikidata.org/prop/direct/P1584": ["http://pleiades.stoa.org/places/668216"], "http://www.wikidata.org/prop/direct/P17": ["Lebanon"], "http://www.wikidata.org/prop/direct/P1958": ["https://www.trismegistos.org/place/3820"]}, "geometry": {"type": "Point", "coordinates": [35.647, 34.117]}}, {"type": "Feature", "id": "http://data.archaeology.link/data/ancientports/3450", "label": "Jbeil, bay of Chamiye", "properties": {"http://purl.org/dc/elements/1.1/created": ["2023"], "http://purl.org/dc/elements/1.1/creator": ["http://data.archaeology.link/data/spphaefen/arthur_de_graauw"], "http://www.ancientports.com/ont#date_min": ["-550"], "http://www.opengis.net/ont/geosparql#hasGeometry": ["http://data.archaeology.link/data/ancientports/3450_geom"], "http://www.w3.org/1999/02/22-rdf-syntax-ns#type": ["http://www.ancientports.com/ont#Harbour"], "http://www.w3.org/2000/01/rdf-schema#label": ["Jbeil, bay of Chamiye"], "http://www.w3.org/2002/07/owl#sameAs": ["http://www.wikidata.org/entity/Q173532"], "http://www.wikidata.org/prop/direct/P1584": ["http://pleiades.stoa.org/places/668216"], "http://www.wikidata.org/prop/direct/P17": ["Lebanon"], "http://www.wikidata.org/prop/direct/P1958": ["https://www.trismegistos.org/place/3820"]}, "geometry": {"type": "Point", "coordinates": [35.64361, 34.11948]}}, {"type": "Feature", "id": "http://data.archaeology.link/data/ancientports/3449", "label": "Jbeil, Medieval port", "properties": {"http://purl.org/dc/elements/1.1/created": ["2023"], "http://purl.org/dc/elements/1.1/creator": ["http://data.archaeology.link/data/spphaefen/arthur_de_graauw"], "http://www.ancientports.com/ont#date_min": ["-6000"], "http://www.opengis.net/ont/geosparql#hasGeometry": ["http://data.archaeology.link/data/ancientports/3449_geom"], "http://www.w3.org/1999/02/22-rdf-syntax-ns#type": ["http://www.ancientports.com/ont#Harbour"], "http://www.w3.org/2000/01/rdf-schema#label": ["Jbeil, Medieval port"], "http://www.w3.org/2002/07/owl#sameAs": ["http://www.wikidata.org/entity/Q173532"], "http://www.wikidata.org/prop/direct/P1584": ["http://pleiades.stoa.org/places/668216"], "http://www.wikidata.org/prop/direct/P17": ["Lebanon"], "http://www.wikidata.org/prop/direct/P1958": ["https://www.trismegistos.org/place/3820"]}, "geometry": {"type": "Point", "coordinates": [35.6433, 34.12148]}}]}