{"type": "FeatureCollection", "id": "http://www.wikidata.org/entity/Q5070979", "name": "Sarichioi", "features": [{"type": "Feature", "id": "http://data.archaeology.link/data/ancientports/2491", "name": "Enisala", "dateprops": ["begin"], "properties": {"http://purl.org/dc/elements/1.1/creator": ["http://data.archaeology.link/data/spphaefen/arthur_de_graauw"], "http://purl.org/dc/terms/partOf": ["http://data.archaeology.link/data/ancientports/bib_deGrauw_2013_GeoDB"], "http://www.opengis.net/ont/geosparql#hasGeometry": ["http://data.archaeology.link/data/ancientports/2491_geom"], "http://www.w3.org/1999/02/22-rdf-syntax-ns#type": ["http://www.ancientports.com/ont#Harbour"], "http://www.w3.org/2000/01/rdf-schema#label": ["Enisala"], "http://www.w3.org/2002/07/owl#sameAs": ["http://www.wikidata.org/entity/Q5070979"], "http://www.w3.org/2004/02/skos/core#note": ["Bivolaru (2017)"], "http://www.w3.org/2006/time#hasTime": ["http://data.archaeology.link/data/ancientports/2491_foundation"], "http://www.wikidata.org/prop/direct/P1584": ["http://pleiades.stoa.org/places/216805"], "http://www.wikidata.org/prop/direct/P17": ["http://www.wikidata.org/entity/Q218"], "http://www.wikidata.org/prop/direct/P1936": ["http://imperium.ahlfeldt.se/places/21784"], "begin": "-30"}, "geometry": {"type": "Point", "coordinates": [28.8351, 44.88375]}}, {"type": "Feature", "id": "http://data.archaeology.link/data/ancientports/2494", "name": "Sarichoi", "dateprops": [], "properties": {"http://purl.org/dc/elements/1.1/creator": ["http://data.archaeology.link/data/spphaefen/arthur_de_graauw"], "http://purl.org/dc/terms/partOf": ["http://data.archaeology.link/data/ancientports/bib_deGrauw_2013_GeoDB"], "http://www.opengis.net/ont/geosparql#hasGeometry": ["http://data.archaeology.link/data/ancientports/2494_geom"], "http://www.w3.org/1999/02/22-rdf-syntax-ns#type": ["http://www.ancientports.com/ont#Harbour"], "http://www.w3.org/2000/01/rdf-schema#label": ["Sarichoi"], "http://www.w3.org/2002/07/owl#sameAs": ["http://www.wikidata.org/entity/Q5070979"], "http://www.w3.org/2004/02/skos/core#note": ["Avram (2004)"], "http://www.wikidata.org/prop/direct/P17": ["http://www.wikidata.org/entity/Q218"], "begin": ""}, "geometry": {"type": "Point", "coordinates": [28.86171, 44.94785]}}]}