{"type": "FeatureCollection", "id": "http://pleiades.stoa.org/places/658535", "name": "658535", "features": [{"type": "Feature", "id": "http://data.archaeology.link/data/ancientports/3407", "label": "Al-Mina, at the outlet of R Oronte, R Asi, near Antakya", "properties": {"http://purl.org/dc/elements/1.1/created": ["2023"], "http://purl.org/dc/elements/1.1/creator": ["http://data.archaeology.link/data/spphaefen/arthur_de_graauw"], "http://www.ancientports.com/ont#date_min": ["-1500"], "http://www.opengis.net/ont/geosparql#hasGeometry": ["http://data.archaeology.link/data/ancientports/3407_geom"], "http://www.w3.org/1999/02/22-rdf-syntax-ns#type": ["http://www.ancientports.com/ont#Harbour"], "http://www.w3.org/2000/01/rdf-schema#label": ["Al-Mina, at the outlet of R Oronte, R Asi, near Antakya"], "http://www.w3.org/2002/07/owl#sameAs": ["http://www.wikidata.org/entity/Q200441"], "http://www.wikidata.org/prop/direct/P1584": ["http://pleiades.stoa.org/places/658535"], "http://www.wikidata.org/prop/direct/P17": ["TR: South"], "http://www.wikidata.org/prop/direct/P1958": ["https://www.trismegistos.org/place/37509"]}, "geometry": {"type": "Point", "coordinates": [35.9741, 36.0616]}}]}