{"type": "FeatureCollection", "id": "https://topostext.org/place/434137UPot", "name": "434137UPot", "features": [{"type": "Feature", "id": "http://data.archaeology.link/data/ancientports/1301", "label": "Porto Potenza, near outlet of R Potenza", "properties": {"http://purl.org/dc/elements/1.1/created": ["2023"], "http://purl.org/dc/elements/1.1/creator": ["http://data.archaeology.link/data/spphaefen/arthur_de_graauw"], "http://purl.org/dc/terms/isReferencedBy": ["https://mapcarta.com/W32393250"], "http://www.ancientports.com/ont#date_min": ["-330"], "http://www.opengis.net/ont/geosparql#hasGeometry": ["http://data.archaeology.link/data/ancientports/1301_geom"], "http://www.w3.org/1999/02/22-rdf-syntax-ns#type": ["http://www.ancientports.com/ont#Harbour"], "http://www.w3.org/2000/01/rdf-schema#label": ["Porto Potenza, near outlet of R Potenza"], "http://www.w3.org/2002/07/owl#sameAs": ["http://www.wikidata.org/entity/Q2106396"], "http://www.w3.org/2004/02/skos/core#note": ["Vermeulen (2014)"], "http://www.wikidata.org/prop/direct/P1584": ["http://pleiades.stoa.org/places/413272"], "http://www.wikidata.org/prop/direct/P17": ["Italy Adriatic"], "http://www.wikidata.org/prop/direct/P1936": ["http://imperium.ahlfeldt.se/places/22713"], "http://www.wikidata.org/prop/direct/P1958": ["https://www.trismegistos.org/place/32688"], "http://www.wikidata.org/prop/direct/P8068": ["https://topostext.org/place/434137UPot"]}, "geometry": {"type": "Point", "coordinates": [13.6711, 43.4142]}}]}