{"type": "FeatureCollection", "id": "http://imperium.ahlfeldt.se/places/17857", "name": "17857", "features": [{"type": "Feature", "id": "http://data.archaeology.link/data/ancientports/675", "label": "Cassis", "dateprops": ["http://purl.org/dc/elements/1.1/created", "http://www.ancientports.com/ont#date_min"], "properties": {"http://purl.org/dc/elements/1.1/created": ["2023"], "http://purl.org/dc/elements/1.1/creator": ["http://data.archaeology.link/data/spphaefen/arthur_de_graauw"], "http://www.ancientports.com/ont#date_min": ["-30"], "http://www.opengis.net/ont/geosparql#hasGeometry": ["http://data.archaeology.link/data/ancientports/675_geom"], "http://www.w3.org/1999/02/22-rdf-syntax-ns#type": ["http://www.ancientports.com/ont#Quay"], "http://www.w3.org/2000/01/rdf-schema#label": ["Cassis"], "http://www.w3.org/2002/07/owl#sameAs": ["http://www.wikidata.org/entity/Q243002"], "http://www.w3.org/2004/02/skos/core#note": ["Arnaud (2004)"], "http://www.wikidata.org/prop/direct/P1584": ["http://pleiades.stoa.org/places/148037"], "http://www.wikidata.org/prop/direct/P17": ["France South"], "http://www.wikidata.org/prop/direct/P1936": ["http://imperium.ahlfeldt.se/places/17857"]}, "geometry": {"type": "Point", "coordinates": [5.53902, 43.21411]}}]}