{"type": "FeatureCollection", "id": "http://pleiades.stoa.org/places/507393", "name": "507393", "features": [{"type": "Feature", "id": "http://data.archaeology.link/data/ancientports/1842", "label": "Chrysopouli, in R Nestos delta", "properties": {"http://purl.org/dc/elements/1.1/created": ["2023"], "http://purl.org/dc/elements/1.1/creator": ["http://data.archaeology.link/data/spphaefen/arthur_de_graauw"], "http://www.ancientports.com/ont#date_min": ["-750"], "http://www.opengis.net/ont/geosparql#hasGeometry": ["http://data.archaeology.link/data/ancientports/1842_geom"], "http://www.w3.org/1999/02/22-rdf-syntax-ns#type": ["http://www.ancientports.com/ont#Harbour"], "http://www.w3.org/2000/01/rdf-schema#label": ["Chrysopouli, in R Nestos delta"], "http://www.w3.org/2002/07/owl#sameAs": ["http://www.wikidata.org/entity/Q5227719"], "http://www.wikidata.org/prop/direct/P1584": ["http://pleiades.stoa.org/places/507393"], "http://www.wikidata.org/prop/direct/P17": ["GR: North-East"], "http://www.wikidata.org/prop/direct/P1958": ["https://www.trismegistos.org/place/61222"]}, "geometry": {"type": "Point", "coordinates": [24.69, 40.99]}}]}