{"type": "FeatureCollection", "id": "http://www.wikidata.org/entity/Q9676", "name": "Q9676", "features": [{"type": "Feature", "id": "http://data.archaeology.link/data/ancientports/150", "label": "Isle of Man", "properties": {"http://purl.org/dc/elements/1.1/created": ["2023"], "http://purl.org/dc/elements/1.1/creator": ["http://data.archaeology.link/data/spphaefen/arthur_de_graauw"], "http://www.opengis.net/ont/geosparql#hasGeometry": ["http://data.archaeology.link/data/ancientports/150_geom"], "http://www.w3.org/1999/02/22-rdf-syntax-ns#type": ["http://www.ancientports.com/ont#Harbour"], "http://www.w3.org/2000/01/rdf-schema#label": ["Isle of Man"], "http://www.w3.org/2002/07/owl#sameAs": ["http://www.wikidata.org/entity/Q9676"], "http://www.wikidata.org/prop/direct/P1584": ["http://pleiades.stoa.org/places/89242"], "http://www.wikidata.org/prop/direct/P17": ["UK"], "http://www.wikidata.org/prop/direct/P1958": ["https://www.trismegistos.org/place/19059"]}, "geometry": {"type": "Point", "coordinates": [-4.525, 54.177]}}]}