{"type": "FeatureCollection", "id": "http://pleiades.stoa.org/places/452455", "name": "452455", "features": [{"type": "Feature", "id": "http://data.archaeology.link/data/ancientports/1209", "name": "beach of San Vincenzo, on the isle of Stromboli", "dateprops": ["begin"], "properties": {"http://purl.org/dc/elements/1.1/creator": ["http://data.archaeology.link/data/spphaefen/arthur_de_graauw"], "http://purl.org/dc/terms/partOf": ["http://data.archaeology.link/data/ancientports/bib_deGrauw_2013_GeoDB"], "http://www.opengis.net/ont/geosparql#hasGeometry": ["http://data.archaeology.link/data/ancientports/1209_geom"], "http://www.w3.org/1999/02/22-rdf-syntax-ns#type": ["http://www.ancientports.com/ont#Harbour"], "http://www.w3.org/2000/01/rdf-schema#label": ["beach of San Vincenzo, on the isle of Stromboli"], "http://www.w3.org/2002/07/owl#sameAs": ["http://www.wikidata.org/entity/Q131148"], "http://www.w3.org/2006/time#hasTime": ["http://data.archaeology.link/data/ancientports/1209_foundation"], "http://www.wikidata.org/prop/direct/P1584": ["http://pleiades.stoa.org/places/452455"], "http://www.wikidata.org/prop/direct/P17": ["http://www.wikidata.org/entity/Q38"], "http://www.wikidata.org/prop/direct/P1936": ["http://imperium.ahlfeldt.se/places/41245"], "http://www.wikidata.org/prop/direct/P1958": ["https://www.trismegistos.org/place/42514"], "http://www.wikidata.org/prop/direct/P8068": ["https://topostext.org/place/388152IStr"], "begin": "-1500"}, "geometry": {"type": "Point", "coordinates": [15.24421, 38.79746]}}], "numberMatched": 1, "numberReturned": 1, "bbox": [15.24421, 38.79746, 15.24421, 38.79746], "crs": "http://www.opengis.net/def/crs/OGC/1.3/CRS84"}