{"type": "FeatureCollection", "id": "https://www.trismegistos.org/place/14695", "name": "14695", "features": [{"type": "Feature", "id": "http://data.archaeology.link/data/ancientports/141_4", "name": "Towyn", "dateprops": [], "properties": {"http://purl.org/dc/elements/1.1/created": ["2023"], "http://purl.org/dc/elements/1.1/creator": ["http://data.archaeology.link/data/spphaefen/arthur_de_graauw"], "http://www.opengis.net/ont/geosparql#hasGeometry": ["http://data.archaeology.link/data/ancientports/141_4_geom"], "http://www.w3.org/1999/02/22-rdf-syntax-ns#type": ["http://www.ancientports.com/ont#Harbour"], "http://www.w3.org/2000/01/rdf-schema#label": ["Towyn"], "http://www.w3.org/2002/07/owl#sameAs": ["http://www.wikidata.org/entity/Q7830339"], "http://www.wikidata.org/prop/direct/P17": ["http://www.wikidata.org/entity/Q145"], "http://www.wikidata.org/prop/direct/P1958": ["https://www.trismegistos.org/place/14695"], "begin": ""}, "geometry": {"type": "Point", "coordinates": [-3.5398, 53.3017]}}]}