{"type": "FeatureCollection", "id": "https://www.trismegistos.org/place/32481", "name": "32481", "features": [{"type": "Feature", "id": "http://data.archaeology.link/data/ancientports/974", "label": "Lago di Patria", "properties": {"http://purl.org/dc/elements/1.1/created": ["2023"], "http://purl.org/dc/elements/1.1/creator": ["http://data.archaeology.link/data/spphaefen/arthur_de_graauw"], "http://www.ancientports.com/ont#date_min": ["-330"], "http://www.opengis.net/ont/geosparql#hasGeometry": ["http://data.archaeology.link/data/ancientports/974_geom"], "http://www.w3.org/1999/02/22-rdf-syntax-ns#type": ["http://www.ancientports.com/ont#Harbour"], "http://www.w3.org/2000/01/rdf-schema#label": ["Lago di Patria"], "http://www.w3.org/2002/07/owl#sameAs": ["http://www.wikidata.org/entity/Q898417"], "http://www.wikidata.org/prop/direct/P1584": ["http://pleiades.stoa.org/places/432911"], "http://www.wikidata.org/prop/direct/P17": ["Italy West"], "http://www.wikidata.org/prop/direct/P1958": ["https://www.trismegistos.org/place/32481"]}, "geometry": {"type": "Point", "coordinates": [14.0299, 40.92133]}}]}