{"type": "FeatureCollection", "id": "http://www.wikidata.org/entity/Q3040241", "name": "Q3040241", "features": [{"type": "Feature", "id": "http://data.archaeology.link/data/ancientports/1181", "label": "Trapani", "properties": {"http://purl.org/dc/elements/1.1/created": ["2023"], "http://purl.org/dc/elements/1.1/creator": ["http://data.archaeology.link/data/spphaefen/arthur_de_graauw"], "http://www.ancientports.com/ont#date_min": ["-330"], "http://www.opengis.net/ont/geosparql#hasGeometry": ["http://data.archaeology.link/data/ancientports/1181_geom"], "http://www.w3.org/1999/02/22-rdf-syntax-ns#type": ["http://www.ancientports.com/ont#Harbour"], "http://www.w3.org/2000/01/rdf-schema#label": ["Trapani"], "http://www.w3.org/2002/07/owl#sameAs": ["http://www.wikidata.org/entity/Q3040241"], "http://www.wikidata.org/prop/direct/P1584": ["http://pleiades.stoa.org/places/462187"], "http://www.wikidata.org/prop/direct/P17": ["Italy Sicily"], "http://www.wikidata.org/prop/direct/P1958": ["https://www.trismegistos.org/place/22351"]}, "geometry": {"type": "Point", "coordinates": [12.50219, 38.00796]}}]}