{"type": "FeatureCollection", "id": "https://topostext.org/place/392236FSin", "name": "392236FSin", "features": [{"type": "Feature", "id": "http://data.archaeology.link/data/ancientports/2237", "label": "4 Roman forts: Mauragani, Hellinikon, Priounos, Sindouka probably sharing one port, possibly near Sindouka?", "dateprops": ["http://purl.org/dc/elements/1.1/created", "http://www.ancientports.com/ont#date_min"], "properties": {"http://purl.org/dc/elements/1.1/created": ["2023"], "http://purl.org/dc/elements/1.1/creator": ["http://data.archaeology.link/data/spphaefen/arthur_de_graauw"], "http://www.ancientports.com/ont#date_min": ["-550"], "http://www.opengis.net/ont/geosparql#hasGeometry": ["http://data.archaeology.link/data/ancientports/2237_geom"], "http://www.w3.org/1999/02/22-rdf-syntax-ns#type": ["http://www.ancientports.com/ont#Harbour"], "http://www.w3.org/2000/01/rdf-schema#label": ["4 Roman forts: Mauragani, Hellinikon, Priounos, Sindouka probably sharing one port, possibly near Sindouka?"], "http://www.wikidata.org/prop/direct/P1584": ["http://pleiades.stoa.org/places/541101"], "http://www.wikidata.org/prop/direct/P17": ["GR: Eastern Isl."], "http://www.wikidata.org/prop/direct/P1936": ["http://imperium.ahlfeldt.se/places/34370"], "http://www.wikidata.org/prop/direct/P8068": ["https://topostext.org/place/392236FSin"]}, "geometry": {"type": "Point", "coordinates": [23.6159, 39.1987]}}]}