{"type": "FeatureCollection", "id": "http://imperium.ahlfeldt.se/places/27105", "name": "27105", "features": [{"type": "Feature", "id": "http://data.archaeology.link/data/ancientports/3768", "label": "Muscat, Mascate", "dateprops": ["http://purl.org/dc/elements/1.1/created"], "properties": {"http://purl.org/dc/elements/1.1/created": ["2023"], "http://purl.org/dc/elements/1.1/creator": ["http://data.archaeology.link/data/spphaefen/arthur_de_graauw"], "http://purl.org/dc/terms/isReferencedBy": ["http://data.archaeology.link/data/ancientports/bib_Bhacker_1997_Digging"], "http://www.opengis.net/ont/geosparql#hasGeometry": ["http://data.archaeology.link/data/ancientports/3768_geom"], "http://www.w3.org/1999/02/22-rdf-syntax-ns#type": ["http://www.ancientports.com/ont#Harbour"], "http://www.w3.org/2000/01/rdf-schema#label": ["Muscat, Mascate"], "http://www.w3.org/2002/07/owl#sameAs": ["http://www.wikidata.org/entity/Q3826"], "http://www.w3.org/2006/time#hasTime": ["http://data.archaeology.link/data/ancientports/3768_foundation"], "http://www.wikidata.org/prop/direct/P1584": ["http://pleiades.stoa.org/places/29635"], "http://www.wikidata.org/prop/direct/P17": ["http://www.wikidata.org/entity/Q842"], "http://www.wikidata.org/prop/direct/P1936": ["http://imperium.ahlfeldt.se/places/27105"]}, "geometry": {"type": "Point", "coordinates": [58.57417, 23.62206]}}]}