{"type": "FeatureCollection", "id": "http://imperium.ahlfeldt.se/places/27984", "name": "27984", "features": [{"type": "Feature", "id": "http://data.archaeology.link/data/ancientports/2542", "label": "Zhevakhova hora mount", "dateprops": [], "properties": {"http://purl.org/dc/elements/1.1/created": ["2023"], "http://purl.org/dc/elements/1.1/creator": ["http://data.archaeology.link/data/spphaefen/arthur_de_graauw"], "http://www.opengis.net/ont/geosparql#hasGeometry": ["http://data.archaeology.link/data/ancientports/2542_geom"], "http://www.w3.org/1999/02/22-rdf-syntax-ns#type": ["http://www.ancientports.com/ont#Harbour"], "http://www.w3.org/2000/01/rdf-schema#label": ["Zhevakhova hora mount"], "http://www.w3.org/2004/02/skos/core#note": ["Kozlovskaya (2017)"], "http://www.w3.org/2006/time#hasTime": ["http://data.archaeology.link/data/ancientports/2542_foundation"], "http://www.wikidata.org/prop/direct/P1584": ["http://pleiades.stoa.org/places/226828"], "http://www.wikidata.org/prop/direct/P17": ["Ukraine Black S."], "http://www.wikidata.org/prop/direct/P1936": ["http://imperium.ahlfeldt.se/places/27984"]}, "geometry": {"type": "Point", "coordinates": [30.7354, 46.5454]}}]}