{"type": "FeatureCollection", "id": "http://imperium.ahlfeldt.se/places/34341", "name": "34341", "features": [{"type": "Feature", "id": "http://data.archaeology.link/data/ancientports/2208", "label": "Roman fort at Makara, on the isle of Lesbos, Lesvos ", "dateprops": ["http://purl.org/dc/elements/1.1/created", "http://www.ancientports.com/ont#date_min"], "properties": {"http://purl.org/dc/elements/1.1/created": ["2023"], "http://purl.org/dc/elements/1.1/creator": ["http://data.archaeology.link/data/spphaefen/arthur_de_graauw"], "http://www.ancientports.com/ont#date_min": ["-750"], "http://www.opengis.net/ont/geosparql#hasGeometry": ["http://data.archaeology.link/data/ancientports/2208_geom"], "http://www.w3.org/1999/02/22-rdf-syntax-ns#type": ["http://www.ancientports.com/ont#Harbour"], "http://www.w3.org/2000/01/rdf-schema#label": ["Roman fort at Makara, on the isle of Lesbos, Lesvos "], "http://www.wikidata.org/prop/direct/P1584": ["http://pleiades.stoa.org/places/550711"], "http://www.wikidata.org/prop/direct/P17": ["GR: Eastern Isl."], "http://www.wikidata.org/prop/direct/P1936": ["http://imperium.ahlfeldt.se/places/34341"], "http://www.wikidata.org/prop/direct/P8068": ["https://topostext.org/place/391261FMak"]}, "geometry": {"type": "Point", "coordinates": [26.0663, 39.0952]}}]}