{"type": "FeatureCollection", "id": "http://pleiades.stoa.org/places/707523", "name": "707523", "features": [{"type": "Feature", "id": "http://data.archaeology.link/data/ancientports/3043", "label": "Roman villa at Kalogiannis", "dateprops": [], "properties": {"http://purl.org/dc/elements/1.1/created": ["2023"], "http://purl.org/dc/elements/1.1/creator": ["http://data.archaeology.link/data/spphaefen/arthur_de_graauw"], "http://www.opengis.net/ont/geosparql#hasGeometry": ["http://data.archaeology.link/data/ancientports/3043_geom"], "http://www.w3.org/1999/02/22-rdf-syntax-ns#type": ["http://www.ancientports.com/ont#VillaMaritima"], "http://www.w3.org/2000/01/rdf-schema#label": ["Roman villa at Kalogiannis"], "http://www.w3.org/2006/time#hasTime": ["http://data.archaeology.link/data/ancientports/3043_foundation"], "http://www.wikidata.org/prop/direct/P1584": ["http://pleiades.stoa.org/places/707523"], "http://www.wikidata.org/prop/direct/P17": ["http://www.wikidata.org/entity/Q229"], "http://www.wikidata.org/prop/direct/P1936": ["http://imperium.ahlfeldt.se/places/35093"], "http://www.wikidata.org/prop/direct/P1958": ["https://www.trismegistos.org/place/60850"], "http://www.wikidata.org/prop/direct/P8068": ["https://topostext.org/place/350341VKal"]}, "geometry": {"type": "Point", "coordinates": [34.0655, 34.96278]}}]}