{"type": "FeatureCollection", "id": "https://www.trismegistos.org/place/37640", "name": "37640", "features": [{"type": "Feature", "id": "http://data.archaeology.link/data/ancientports/1584", "label": "Katoxi, Trikardo, now inland", "dateprops": [], "properties": {"http://purl.org/dc/elements/1.1/created": ["2023"], "http://purl.org/dc/elements/1.1/creator": ["http://data.archaeology.link/data/spphaefen/arthur_de_graauw"], "http://purl.org/dc/terms/isReferencedBy": ["https://mapcarta.com/N7062718612"], "http://www.opengis.net/ont/geosparql#hasGeometry": ["http://data.archaeology.link/data/ancientports/1584_geom"], "http://www.w3.org/1999/02/22-rdf-syntax-ns#type": ["http://www.ancientports.com/ont#Slipway", "http://www.ancientports.com/ont#Shipshed"], "http://www.w3.org/2000/01/rdf-schema#label": ["Katoxi, Trikardo, now inland"], "http://www.w3.org/2002/07/owl#sameAs": ["http://www.wikidata.org/entity/Q923211"], "http://www.w3.org/2006/time#hasTime": ["http://data.archaeology.link/data/ancientports/1584_foundation"], "http://www.wikidata.org/prop/direct/P1584": ["http://pleiades.stoa.org/places/531016"], "http://www.wikidata.org/prop/direct/P17": ["http://www.wikidata.org/entity/Q41"], "http://www.wikidata.org/prop/direct/P1936": ["http://imperium.ahlfeldt.se/places/21993"], "http://www.wikidata.org/prop/direct/P1958": ["https://www.trismegistos.org/place/37640"], "http://www.wikidata.org/prop/direct/P8068": ["https://topostext.org/place/384212HOin"]}, "geometry": {"type": "Point", "coordinates": [21.19364, 38.41143]}}, {"type": "Feature", "id": "http://data.archaeology.link/data/ancientports/1585", "label": "Katoxi, Trikardo, now inland, on R Aspropotamos", "dateprops": [], "properties": {"http://purl.org/dc/elements/1.1/created": ["2023"], "http://purl.org/dc/elements/1.1/creator": ["http://data.archaeology.link/data/spphaefen/arthur_de_graauw"], "http://www.opengis.net/ont/geosparql#hasGeometry": ["http://data.archaeology.link/data/ancientports/1585_geom"], "http://www.w3.org/1999/02/22-rdf-syntax-ns#type": ["http://www.ancientports.com/ont#Harbour"], "http://www.w3.org/2000/01/rdf-schema#label": ["Katoxi, Trikardo, now inland, on R Aspropotamos"], "http://www.w3.org/2002/07/owl#sameAs": ["http://www.wikidata.org/entity/Q923211"], "http://www.w3.org/2004/02/skos/core#note": ["V\u00f6tt (2004)"], "http://www.w3.org/2006/time#hasTime": ["http://data.archaeology.link/data/ancientports/1585_foundation"], "http://www.wikidata.org/prop/direct/P1584": ["http://pleiades.stoa.org/places/531016"], "http://www.wikidata.org/prop/direct/P17": ["http://www.wikidata.org/entity/Q41"], "http://www.wikidata.org/prop/direct/P1936": ["http://imperium.ahlfeldt.se/places/21993"], "http://www.wikidata.org/prop/direct/P1958": ["https://www.trismegistos.org/place/37640"]}, "geometry": {"type": "Point", "coordinates": [21.20975, 38.39901]}}]}