{"type": "FeatureCollection", "id": "http://pleiades.stoa.org/places/511169", "name": "511169", "features": [{"type": "Feature", "id": "http://data.archaeology.link/data/ancientports/2866", "label": "Izmit South, with Trajan's projected connection to lake Sapanca by a canal", "dateprops": [], "properties": {"http://purl.org/dc/elements/1.1/created": ["2023"], "http://purl.org/dc/elements/1.1/creator": ["http://data.archaeology.link/data/spphaefen/arthur_de_graauw"], "http://www.opengis.net/ont/geosparql#hasGeometry": ["http://data.archaeology.link/data/ancientports/2866_geom"], "http://www.w3.org/1999/02/22-rdf-syntax-ns#type": ["http://www.ancientports.com/ont#Harbour"], "http://www.w3.org/2000/01/rdf-schema#label": ["Izmit South, with Trajan's projected connection to lake Sapanca by a canal"], "http://www.w3.org/2002/07/owl#sameAs": ["http://www.wikidata.org/entity/Q868012"], "http://www.w3.org/2004/02/skos/core#note": ["Texier (1839)"], "http://www.w3.org/2006/time#hasTime": ["http://data.archaeology.link/data/ancientports/2866_foundation"], "http://www.wikidata.org/prop/direct/P1584": ["http://pleiades.stoa.org/places/511169"], "http://www.wikidata.org/prop/direct/P17": ["TR: Marmara S"], "http://www.wikidata.org/prop/direct/P1936": ["http://imperium.ahlfeldt.se/places/31363"], "http://www.wikidata.org/prop/direct/P1958": ["https://www.trismegistos.org/place/58869"], "http://www.wikidata.org/prop/direct/P8068": ["https://topostext.org/place/407299UAst"]}, "geometry": {"type": "Point", "coordinates": [29.929, 40.714]}}]}