{"type": "FeatureCollection", "id": "http://www.wikidata.org/entity/Q11304", "name": "L%27Escala", "features": [{"type": "Feature", "id": "http://data.archaeology.link/data/ancientports/447", "name": "Cala Montgo? Near L\u2019Escala", "dateprops": ["begin"], "properties": {"http://purl.org/dc/elements/1.1/creator": ["http://data.archaeology.link/data/spphaefen/arthur_de_graauw"], "http://purl.org/dc/terms/partOf": ["http://data.archaeology.link/data/ancientports/bib_deGrauw_2013_GeoDB"], "http://www.opengis.net/ont/geosparql#hasGeometry": ["http://data.archaeology.link/data/ancientports/447_geom"], "http://www.w3.org/1999/02/22-rdf-syntax-ns#type": ["http://www.ancientports.com/ont#Harbour"], "http://www.w3.org/2000/01/rdf-schema#label": ["Cala Montgo? Near L\u2019Escala"], "http://www.w3.org/2002/07/owl#sameAs": ["http://www.wikidata.org/entity/Q11304"], "http://www.w3.org/2006/time#hasTime": ["http://data.archaeology.link/data/ancientports/447_foundation"], "http://www.wikidata.org/prop/direct/P1584": ["http://pleiades.stoa.org/places/246441"], "http://www.wikidata.org/prop/direct/P17": ["http://www.wikidata.org/entity/Q29"], "http://www.wikidata.org/prop/direct/P1936": ["http://imperium.ahlfeldt.se/places/18300"], "begin": "-550"}, "geometry": {"type": "Point", "coordinates": [3.17, 42.1067]}}, {"type": "Feature", "id": "http://data.archaeology.link/data/ancientports/447_1", "name": "Riells-La Clota, at La Escala", "dateprops": [], "properties": {"http://purl.org/dc/elements/1.1/creator": ["http://data.archaeology.link/data/spphaefen/arthur_de_graauw"], "http://purl.org/dc/terms/partOf": ["http://data.archaeology.link/data/ancientports/bib_deGrauw_2013_GeoDB"], "http://www.opengis.net/ont/geosparql#hasGeometry": ["http://data.archaeology.link/data/ancientports/447_1_geom"], "http://www.w3.org/1999/02/22-rdf-syntax-ns#type": ["http://www.ancientports.com/ont#Harbour"], "http://www.w3.org/2000/01/rdf-schema#label": ["Riells-La Clota, at La Escala"], "http://www.w3.org/2002/07/owl#sameAs": ["http://www.wikidata.org/entity/Q11304"], "http://www.w3.org/2004/02/skos/core#note": ["Camiade (2008)"], "http://www.wikidata.org/prop/direct/P17": ["http://www.wikidata.org/entity/Q29"], "begin": ""}, "geometry": {"type": "Point", "coordinates": [3.1486, 42.117]}}], "numberMatched": 2, "numberReturned": 2}