{"type": "FeatureCollection", "id": "http://pleiades.stoa.org/places/599713", "name": "599713", "features": [{"type": "Feature", "id": "http://data.archaeology.link/data/ancientports/2279", "label": "Khrysomilia, on the isle of Fournoi", "properties": {"http://purl.org/dc/elements/1.1/created": ["2023"], "http://purl.org/dc/elements/1.1/creator": ["http://data.archaeology.link/data/spphaefen/arthur_de_graauw"], "http://www.ancientports.com/ont#date_min": ["-330"], "http://www.opengis.net/ont/geosparql#hasGeometry": ["http://data.archaeology.link/data/ancientports/2279_geom"], "http://www.w3.org/1999/02/22-rdf-syntax-ns#type": ["http://www.ancientports.com/ont#Harbour"], "http://www.w3.org/2000/01/rdf-schema#label": ["Khrysomilia, on the isle of Fournoi"], "http://www.wikidata.org/prop/direct/P1584": ["http://pleiades.stoa.org/places/599713"], "http://www.wikidata.org/prop/direct/P17": ["GR: Eastern Isl."], "http://www.wikidata.org/prop/direct/P1958": ["https://www.trismegistos.org/place/61273"]}, "geometry": {"type": "Point", "coordinates": [26.5121, 37.626]}}]}