{"type": "FeatureCollection", "id": "http://imperium.ahlfeldt.se/places/21796", "name": "21796", "features": [{"type": "Feature", "id": "http://data.archaeology.link/data/ancientports/2713", "label": "Roman fort & naval base at Fort of Gonio, 10 km south of Batumi", "dateprops": [], "properties": {"http://purl.org/dc/elements/1.1/created": ["2023"], "http://purl.org/dc/elements/1.1/creator": ["http://data.archaeology.link/data/spphaefen/arthur_de_graauw"], "http://purl.org/dc/terms/isReferencedBy": ["https://pcma.uw.edu.pl/en/2019/03/18/gonio-apsaros-2/"], "http://www.ancientports.com/ont#date_min": ["-330"], "http://www.opengis.net/ont/geosparql#hasGeometry": ["http://data.archaeology.link/data/ancientports/2713_geom"], "http://www.w3.org/1999/02/22-rdf-syntax-ns#type": ["http://www.ancientports.com/ont#Harbour"], "http://www.w3.org/2000/01/rdf-schema#label": ["Roman fort & naval base at Fort of Gonio, 10 km south of Batumi"], "http://www.w3.org/2002/07/owl#sameAs": ["http://www.wikidata.org/entity/Q944813"], "http://www.w3.org/2004/02/skos/core#note": ["Karasiewicz (2016)"], "http://www.wikidata.org/prop/direct/P1584": ["http://pleiades.stoa.org/places/857032"], "http://www.wikidata.org/prop/direct/P17": ["Georgia Black S."], "http://www.wikidata.org/prop/direct/P1936": ["http://imperium.ahlfeldt.se/places/21796"], "http://www.wikidata.org/prop/direct/P1958": ["https://www.trismegistos.org/place/16526"], "http://www.wikidata.org/prop/direct/P8068": ["https://topostext.org/place/416416UAps"]}, "geometry": {"type": "Point", "coordinates": [41.57374, 41.57311]}}]}