{"type": "FeatureCollection", "id": "https://www.trismegistos.org/place/54481", "name": "54481", "features": [{"type": "Feature", "id": "http://data.archaeology.link/data/ancientports/3455", "label": "Khalde, with Neolithic settlements", "properties": {"http://purl.org/dc/elements/1.1/created": ["2023"], "http://purl.org/dc/elements/1.1/creator": ["http://data.archaeology.link/data/spphaefen/arthur_de_graauw"], "http://purl.org/dc/terms/isReferencedBy": ["https://pcma.uw.edu.pl/en/2019/03/04/khalde-2/"], "http://www.ancientports.com/ont#date_min": ["-750"], "http://www.opengis.net/ont/geosparql#hasGeometry": ["http://data.archaeology.link/data/ancientports/3455_geom"], "http://www.w3.org/1999/02/22-rdf-syntax-ns#type": ["http://www.ancientports.com/ont#Harbour"], "http://www.w3.org/2000/01/rdf-schema#label": ["Khalde, with Neolithic settlements"], "http://www.w3.org/2002/07/owl#sameAs": ["http://www.wikidata.org/entity/Q7416913"], "http://www.w3.org/2004/02/skos/core#note": ["Carayon (2012)", "https://pcma.uw.edu.pl/en/2019/03/04/khalde-2/"], "http://www.wikidata.org/prop/direct/P1584": ["http://pleiades.stoa.org/places/678177"], "http://www.wikidata.org/prop/direct/P17": ["http://www.wikidata.org/entity/Q822"], "http://www.wikidata.org/prop/direct/P1936": ["http://imperium.ahlfeldt.se/places/36495"], "http://www.wikidata.org/prop/direct/P1958": ["https://www.trismegistos.org/place/54481"]}, "geometry": {"type": "Point", "coordinates": [35.4811, 33.808]}}]}