{"type": "FeatureCollection", "id": "http://imperium.ahlfeldt.se/places/23130", "name": "23130", "features": [{"type": "Feature", "id": "http://data.archaeology.link/data/ancientports/74", "label": "Dartford", "properties": {"http://purl.org/dc/elements/1.1/created": ["2023"], "http://purl.org/dc/elements/1.1/creator": ["http://data.archaeology.link/data/spphaefen/arthur_de_graauw"], "http://www.ancientports.com/ont#date_min": ["5001"], "http://www.opengis.net/ont/geosparql#hasGeometry": ["http://data.archaeology.link/data/ancientports/74_geom"], "http://www.w3.org/1999/02/22-rdf-syntax-ns#type": ["http://www.ancientports.com/ont#Harbour"], "http://www.w3.org/2000/01/rdf-schema#label": ["Dartford"], "http://www.w3.org/2002/07/owl#sameAs": ["http://www.wikidata.org/entity/Q20713640"], "http://www.wikidata.org/prop/direct/P1584": ["http://pleiades.stoa.org/places/79623"], "http://www.wikidata.org/prop/direct/P17": ["UK"], "http://www.wikidata.org/prop/direct/P1936": ["http://imperium.ahlfeldt.se/places/23130"], "http://www.wikidata.org/prop/direct/P1958": ["https://www.trismegistos.org/place/18974"], "http://www.wikidata.org/prop/direct/P8068": ["https://topostext.org/place/515002UNov"]}, "geometry": {"type": "Point", "coordinates": [0.178, 51.451]}}]}