{"type": "FeatureCollection", "id": "http://pleiades.stoa.org/places/197420", "name": "197420", "features": [{"type": "Feature", "id": "http://data.archaeology.link/data/ancientports/1409", "label": "Stinica", "properties": {"http://purl.org/dc/elements/1.1/created": ["2023"], "http://purl.org/dc/elements/1.1/creator": ["http://data.archaeology.link/data/spphaefen/arthur_de_graauw"], "http://www.ancientports.com/ont#date_min": ["-330"], "http://www.opengis.net/ont/geosparql#hasGeometry": ["http://data.archaeology.link/data/ancientports/1409_geom"], "http://www.w3.org/1999/02/22-rdf-syntax-ns#type": ["http://www.ancientports.com/ont#Harbour"], "http://www.w3.org/2000/01/rdf-schema#label": ["Stinica"], "http://www.wikidata.org/prop/direct/P1584": ["http://pleiades.stoa.org/places/197420"], "http://www.wikidata.org/prop/direct/P17": ["http://www.wikidata.org/entity/Q224"], "http://www.wikidata.org/prop/direct/P1936": ["http://imperium.ahlfeldt.se/places/13865"]}, "geometry": {"type": "Point", "coordinates": [14.894, 44.724]}}]}