{"type": "FeatureCollection", "id": "http://imperium.ahlfeldt.se/places/16693", "name": "16693", "features": [{"type": "Feature", "id": "http://data.archaeology.link/data/ancientports/859", "name": "Baratti, near Populonia", "dateprops": ["begin"], "properties": {"http://purl.org/dc/elements/1.1/created": ["2023"], "http://purl.org/dc/elements/1.1/creator": ["http://data.archaeology.link/data/spphaefen/arthur_de_graauw"], "http://www.opengis.net/ont/geosparql#hasGeometry": ["http://data.archaeology.link/data/ancientports/859_geom"], "http://www.w3.org/1999/02/22-rdf-syntax-ns#type": ["http://www.ancientports.com/ont#Shipshed", "http://www.ancientports.com/ont#Shipyard", "http://www.ancientports.com/ont#Slipway"], "http://www.w3.org/2000/01/rdf-schema#label": ["Baratti, near Populonia"], "http://www.w3.org/2002/07/owl#sameAs": ["http://www.wikidata.org/entity/Q1172685"], "http://www.w3.org/2004/02/skos/core#note": ["Camilli (2005)"], "http://www.w3.org/2006/time#hasTime": ["http://data.archaeology.link/data/ancientports/859_foundation"], "http://www.wikidata.org/prop/direct/P1584": ["http://pleiades.stoa.org/places/403212"], "http://www.wikidata.org/prop/direct/P17": ["http://www.wikidata.org/entity/Q38"], "http://www.wikidata.org/prop/direct/P1936": ["http://imperium.ahlfeldt.se/places/16693"], "http://www.wikidata.org/prop/direct/P1958": ["https://www.trismegistos.org/place/14356"], "http://www.wikidata.org/prop/direct/P8068": ["https://topostext.org/place/430105UPop"], "begin": "-750"}, "geometry": {"type": "Point", "coordinates": [10.5014, 42.9924]}}]}