{"type": "FeatureCollection", "id": "http://imperium.ahlfeldt.se/places/31039", "name": "31039", "features": [{"type": "Feature", "id": "http://data.archaeology.link/data/ancientports/1927", "label": "near Agios Dimitrios", "dateprops": [], "properties": {"http://purl.org/dc/elements/1.1/created": ["2023"], "http://purl.org/dc/elements/1.1/creator": ["http://data.archaeology.link/data/spphaefen/arthur_de_graauw"], "http://www.opengis.net/ont/geosparql#hasGeometry": ["http://data.archaeology.link/data/ancientports/1927_geom"], "http://www.w3.org/1999/02/22-rdf-syntax-ns#type": ["http://www.ancientports.com/ont#Harbour"], "http://www.w3.org/2000/01/rdf-schema#label": ["near Agios Dimitrios"], "http://www.w3.org/2002/07/owl#sameAs": ["http://www.wikidata.org/entity/Q16617755"], "http://www.w3.org/2006/time#hasTime": ["http://data.archaeology.link/data/ancientports/1927_foundation"], "http://www.wikidata.org/prop/direct/P1584": ["http://pleiades.stoa.org/places/570581"], "http://www.wikidata.org/prop/direct/P17": ["GR: Pelop"], "http://www.wikidata.org/prop/direct/P1936": ["http://imperium.ahlfeldt.se/places/31039"], "http://www.wikidata.org/prop/direct/P8068": ["https://topostext.org/place/368223UPep"]}, "geometry": {"type": "Point", "coordinates": [22.2957, 36.8101]}}]}