{"type": "FeatureCollection", "id": "https://www.trismegistos.org/place/54760", "name": "54760", "features": [{"type": "Feature", "id": "http://data.archaeology.link/data/ancientports/3587_2", "label": "Abu Ramad, Ramatte, east of Ras Abu Fatma", "dateprops": [], "properties": {"http://purl.org/dc/elements/1.1/created": ["2023"], "http://purl.org/dc/elements/1.1/creator": ["http://data.archaeology.link/data/spphaefen/arthur_de_graauw"], "http://www.opengis.net/ont/geosparql#hasGeometry": ["http://data.archaeology.link/data/ancientports/3587_2_geom"], "http://www.w3.org/1999/02/22-rdf-syntax-ns#type": ["http://www.ancientports.com/ont#Harbour"], "http://www.w3.org/2000/01/rdf-schema#label": ["Abu Ramad, Ramatte, east of Ras Abu Fatma"], "http://www.w3.org/2004/02/skos/core#note": ["Hinkel (1992)"], "http://www.wikidata.org/prop/direct/P17": ["Egypt: Red Sea"], "http://www.wikidata.org/prop/direct/P1958": ["https://www.trismegistos.org/place/54760"]}, "geometry": {"type": "Point", "coordinates": [36.4222, 22.4125]}}]}