{"type": "FeatureCollection", "id": "http://pleiades.stoa.org/places/344448", "name": "344448", "features": [{"type": "Feature", "id": "http://data.archaeology.link/data/ancientports/4076", "label": "Leptis Magna, Lepcis Magna, with ancient lighthouse, on wadi Lebda", "properties": {"http://purl.org/dc/elements/1.1/created": ["2023"], "http://purl.org/dc/elements/1.1/creator": ["http://data.archaeology.link/data/spphaefen/arthur_de_graauw"], "http://www.ancientports.com/ont#date_min": ["2001"], "http://www.opengis.net/ont/geosparql#hasGeometry": ["http://data.archaeology.link/data/ancientports/4076_geom"], "http://www.w3.org/1999/02/22-rdf-syntax-ns#type": ["http://www.ancientports.com/ont#Harbour"], "http://www.w3.org/2000/01/rdf-schema#label": ["Leptis Magna, Lepcis Magna, with ancient lighthouse, on wadi Lebda"], "http://www.w3.org/2002/07/owl#sameAs": ["http://www.wikidata.org/entity/Q191504"], "http://www.wikidata.org/prop/direct/P1584": ["http://pleiades.stoa.org/places/344448"], "http://www.wikidata.org/prop/direct/P17": ["Libya"], "http://www.wikidata.org/prop/direct/P1958": ["https://www.trismegistos.org/place/11836"]}, "geometry": {"type": "Point", "coordinates": [14.3008, 32.6376]}}, {"type": "Feature", "id": "http://data.archaeology.link/data/ancientports/4078", "label": "not yet 'Magna'", "properties": {"http://purl.org/dc/elements/1.1/created": ["2023"], "http://purl.org/dc/elements/1.1/creator": ["http://data.archaeology.link/data/spphaefen/arthur_de_graauw"], "http://www.ancientports.com/ont#date_min": ["-500"], "http://www.opengis.net/ont/geosparql#hasGeometry": ["http://data.archaeology.link/data/ancientports/4078_geom"], "http://www.w3.org/1999/02/22-rdf-syntax-ns#type": ["http://www.ancientports.com/ont#Harbour"], "http://www.w3.org/2000/01/rdf-schema#label": ["not yet 'Magna'"], "http://www.w3.org/2002/07/owl#sameAs": ["http://www.wikidata.org/entity/Q191504"], "http://www.wikidata.org/prop/direct/P1584": ["http://pleiades.stoa.org/places/344448"], "http://www.wikidata.org/prop/direct/P17": ["Libya"], "http://www.wikidata.org/prop/direct/P1958": ["https://www.trismegistos.org/place/11836"]}, "geometry": {"type": "Point", "coordinates": [14.294, 32.6404]}}]}