{"type": "FeatureCollection", "id": "http://www.wikidata.org/entity/Q157816", "name": "Olba (Cilicie)", "features": [{"type": "Feature", "id": "http://data.archaeology.link/data/ancientports/3370", "name": "Yaprak K\u00f6y\u00fc", "dateprops": ["begin"], "properties": {"http://purl.org/dc/elements/1.1/created": ["2023"], "http://purl.org/dc/elements/1.1/creator": ["http://data.archaeology.link/data/spphaefen/arthur_de_graauw"], "http://www.opengis.net/ont/geosparql#hasGeometry": ["http://data.archaeology.link/data/ancientports/3370_geom"], "http://www.w3.org/1999/02/22-rdf-syntax-ns#type": ["http://www.ancientports.com/ont#Harbour"], "http://www.w3.org/2000/01/rdf-schema#label": ["Yaprak K\u00f6y\u00fc"], "http://www.w3.org/2002/07/owl#sameAs": ["http://www.wikidata.org/entity/Q157816"], "http://www.w3.org/2004/02/skos/core#note": ["Arnaud (2020)"], "http://www.w3.org/2006/time#hasTime": ["http://data.archaeology.link/data/ancientports/3370_foundation"], "http://www.wikidata.org/prop/direct/P1584": ["http://pleiades.stoa.org/places/648679"], "http://www.wikidata.org/prop/direct/P17": ["http://www.wikidata.org/entity/Q43"], "http://www.wikidata.org/prop/direct/P1936": ["http://imperium.ahlfeldt.se/places/30296"], "http://www.wikidata.org/prop/direct/P1958": ["https://www.trismegistos.org/place/57194"], "begin": "-30"}, "geometry": {"type": "Point", "coordinates": [34.0885, 36.4192]}}]}