{"type": "FeatureCollection", "id": "http://imperium.ahlfeldt.se/places/27711", "name": "27711", "features": [{"type": "Feature", "id": "http://data.archaeology.link/data/ancientports/3335", "label": "SE of Elikezik", "dateprops": ["http://purl.org/dc/elements/1.1/created"], "properties": {"http://purl.org/dc/elements/1.1/created": ["2023"], "http://purl.org/dc/elements/1.1/creator": ["http://data.archaeology.link/data/spphaefen/arthur_de_graauw"], "http://purl.org/dc/terms/isReferencedBy": ["https://vici.org/vici/61637/"], "http://www.opengis.net/ont/geosparql#hasGeometry": ["http://data.archaeology.link/data/ancientports/3335_geom"], "http://www.w3.org/1999/02/22-rdf-syntax-ns#type": ["http://www.ancientports.com/ont#Quay"], "http://www.w3.org/2000/01/rdf-schema#label": ["SE of Elikezik"], "http://www.w3.org/2002/07/owl#sameAs": ["http://www.wikidata.org/entity/Q65053244"], "http://www.w3.org/2006/time#hasTime": ["http://data.archaeology.link/data/ancientports/3335_foundation"], "http://www.wikidata.org/prop/direct/P1584": ["http://pleiades.stoa.org/places/638785"], "http://www.wikidata.org/prop/direct/P17": ["TR: South"], "http://www.wikidata.org/prop/direct/P1936": ["http://imperium.ahlfeldt.se/places/27711"]}, "geometry": {"type": "Point", "coordinates": [31.9205, 36.5603]}}]}