{"type": "FeatureCollection", "id": "https://www.trismegistos.org/place/14147", "name": "14147", "features": [{"type": "Feature", "id": "http://data.archaeology.link/data/ancientports/4103", "label": "el-Kantara, on the isle of Djerba", "properties": {"http://purl.org/dc/elements/1.1/created": ["2023"], "http://purl.org/dc/elements/1.1/creator": ["http://data.archaeology.link/data/spphaefen/arthur_de_graauw"], "http://www.ancientports.com/ont#date_min": ["-330"], "http://www.opengis.net/ont/geosparql#hasGeometry": ["http://data.archaeology.link/data/ancientports/4103_geom"], "http://www.w3.org/1999/02/22-rdf-syntax-ns#type": ["http://www.ancientports.com/ont#Harbour"], "http://www.w3.org/2000/01/rdf-schema#label": ["el-Kantara, on the isle of Djerba"], "http://www.w3.org/2002/07/owl#sameAs": ["http://www.wikidata.org/entity/Q3306003"], "http://www.wikidata.org/prop/direct/P1584": ["http://pleiades.stoa.org/places/344440"], "http://www.wikidata.org/prop/direct/P17": ["Tunisia"], "http://www.wikidata.org/prop/direct/P1958": ["https://www.trismegistos.org/place/14147"]}, "geometry": {"type": "Point", "coordinates": [10.92065, 33.68295]}}]}