{"type": "FeatureCollection", "id": "http://pleiades.stoa.org/places/531074", "name": "531074", "features": [{"type": "Feature", "id": "http://data.archaeology.link/data/ancientports/2014", "label": "Poros, near Elio-Proni, Tomb of Odysseus near Tzannata?, on the isle of Cephalonia", "dateprops": [], "properties": {"http://purl.org/dc/elements/1.1/created": ["2023"], "http://purl.org/dc/elements/1.1/creator": ["http://data.archaeology.link/data/spphaefen/arthur_de_graauw"], "http://purl.org/dc/terms/isReferencedBy": ["http://homericithaca.blogspot.fr/2014/10/la-tombe-tholos-de-tzannata.html"], "http://www.opengis.net/ont/geosparql#hasGeometry": ["http://data.archaeology.link/data/ancientports/2014_geom"], "http://www.w3.org/1999/02/22-rdf-syntax-ns#type": ["http://www.ancientports.com/ont#Harbour"], "http://www.w3.org/2000/01/rdf-schema#label": ["Poros, near Elio-Proni, Tomb of Odysseus near Tzannata?, on the isle of Cephalonia"], "http://www.w3.org/2002/07/owl#sameAs": ["http://www.wikidata.org/entity/Q7249936"], "http://www.w3.org/2006/time#hasTime": ["http://data.archaeology.link/data/ancientports/2014_foundation"], "http://www.wikidata.org/prop/direct/P1584": ["http://pleiades.stoa.org/places/531074"], "http://www.wikidata.org/prop/direct/P17": ["http://www.wikidata.org/entity/Q41"], "http://www.wikidata.org/prop/direct/P1936": ["http://imperium.ahlfeldt.se/places/31635"], "http://www.wikidata.org/prop/direct/P1958": ["https://www.trismegistos.org/place/37945"], "http://www.wikidata.org/prop/direct/P8068": ["https://topostext.org/place/381208PPro"]}, "geometry": {"type": "Point", "coordinates": [20.7806, 38.1467]}}]}