{"type": "FeatureCollection", "id": "http://imperium.ahlfeldt.se/places/27114", "name": "27114", "features": [{"type": "Feature", "id": "http://data.archaeology.link/data/ancientports/3824", "label": "Bandar Siraf, near R Kunarak", "properties": {"http://purl.org/dc/elements/1.1/created": ["2023"], "http://purl.org/dc/elements/1.1/creator": ["http://data.archaeology.link/data/spphaefen/arthur_de_graauw"], "http://purl.org/dc/terms/isReferencedBy": ["https://www.tehrantimes.com/news/473819/Torpedo-tip-jars-discovered-in-ancient-Iranian-port"], "http://www.ancientports.com/ont#date_min": ["2001"], "http://www.opengis.net/ont/geosparql#hasGeometry": ["http://data.archaeology.link/data/ancientports/3824_geom"], "http://www.w3.org/1999/02/22-rdf-syntax-ns#type": ["http://www.ancientports.com/ont#Harbour"], "http://www.w3.org/2000/01/rdf-schema#label": ["Bandar Siraf, near R Kunarak"], "http://www.w3.org/2002/07/owl#sameAs": ["http://www.wikidata.org/entity/Q168056"], "http://www.w3.org/2004/02/skos/core#note": ["Khakzad (2015)", "Priestman (2013)", "https://www.tehrantimes.com/news/473819/Torpedo-tip-jars-discovered-in-ancient-Iranian-port"], "http://www.wikidata.org/prop/direct/P1584": ["http://pleiades.stoa.org/places/29762"], "http://www.wikidata.org/prop/direct/P17": ["Gulf"], "http://www.wikidata.org/prop/direct/P1936": ["http://imperium.ahlfeldt.se/places/27114"]}, "geometry": {"type": "Point", "coordinates": [52.321, 27.666]}}]}