{"type": "FeatureCollection", "id": "http://pleiades.stoa.org/places/590081", "name": "590081", "features": [{"type": "Feature", "id": "http://data.archaeology.link/data/ancientports/2927", "label": "Akra Nisi, Agios Paulos, on Rodopou peninsula", "dateprops": ["http://purl.org/dc/elements/1.1/created", "http://www.ancientports.com/ont#date_min"], "properties": {"http://purl.org/dc/elements/1.1/created": ["2023"], "http://purl.org/dc/elements/1.1/creator": ["http://data.archaeology.link/data/spphaefen/arthur_de_graauw"], "http://www.ancientports.com/ont#date_min": ["-330"], "http://www.opengis.net/ont/geosparql#hasGeometry": ["http://data.archaeology.link/data/ancientports/2927_geom"], "http://www.w3.org/1999/02/22-rdf-syntax-ns#type": ["http://www.ancientports.com/ont#Harbour"], "http://www.w3.org/2000/01/rdf-schema#label": ["Akra Nisi, Agios Paulos, on Rodopou peninsula"], "http://www.w3.org/2002/07/owl#sameAs": ["http://www.wikidata.org/entity/Q1674880"], "http://www.w3.org/2004/02/skos/core#note": ["Uggeri (2003)"], "http://www.wikidata.org/prop/direct/P1584": ["http://pleiades.stoa.org/places/590081"], "http://www.wikidata.org/prop/direct/P17": ["GR: Crete North"], "http://www.wikidata.org/prop/direct/P1936": ["http://imperium.ahlfeldt.se/places/41892"], "http://www.wikidata.org/prop/direct/P8068": ["https://topostext.org/place/358238LTit"]}, "geometry": {"type": "Point", "coordinates": [23.7106, 35.599]}}]}