{"type": "FeatureCollection", "id": "http://www.wikidata.org/entity/Q65046266", "name": "Proochthoi", "features": [{"type": "Feature", "id": "http://data.archaeology.link/data/ancientports/2844", "name": "Vanik\u00f6y", "dateprops": [], "properties": {"http://purl.org/dc/elements/1.1/creator": ["http://data.archaeology.link/data/spphaefen/arthur_de_graauw"], "http://purl.org/dc/terms/isReferencedBy": ["http://pleiades.stoa.org/places/521129"], "http://purl.org/dc/terms/partOf": ["http://data.archaeology.link/data/ancientports/bib_deGrauw_2013_GeoDB"], "http://www.opengis.net/ont/geosparql#hasGeometry": ["http://data.archaeology.link/data/ancientports/2844_geom"], "http://www.w3.org/1999/02/22-rdf-syntax-ns#type": ["http://www.ancientports.com/ont#Harbour"], "http://www.w3.org/2000/01/rdf-schema#label": ["Vanik\u00f6y"], "http://www.w3.org/2002/07/owl#sameAs": ["http://www.wikidata.org/entity/Q65046266"], "http://www.wikidata.org/prop/direct/P1584": ["http://pleiades.stoa.org/places/523223"], "http://www.wikidata.org/prop/direct/P17": ["http://www.wikidata.org/entity/Q43"], "http://www.wikidata.org/prop/direct/P1936": ["http://imperium.ahlfeldt.se/places/31498"], "begin": ""}, "geometry": {"type": "Point", "coordinates": [29.05524, 41.06775]}}], "numberMatched": 1, "numberReturned": 1}