{"type": "FeatureCollection", "id": "http://imperium.ahlfeldt.se/places/21682", "name": "21682", "features": [{"type": "Feature", "id": "http://data.archaeology.link/data/ancientports/3498", "name": "Tell Arsuf, anchorage south of Crusader castle", "dateprops": ["begin"], "properties": {"http://purl.org/dc/elements/1.1/creator": ["http://data.archaeology.link/data/spphaefen/arthur_de_graauw"], "http://purl.org/dc/terms/partOf": ["http://data.archaeology.link/data/ancientports/bib_deGrauw_2013_GeoDB"], "http://www.opengis.net/ont/geosparql#hasGeometry": ["http://data.archaeology.link/data/ancientports/3498_geom"], "http://www.w3.org/1999/02/22-rdf-syntax-ns#type": ["http://www.ancientports.com/ont#Pila"], "http://www.w3.org/2000/01/rdf-schema#label": ["Tell Arsuf, anchorage south of Crusader castle"], "http://www.w3.org/2004/02/skos/core#note": ["Galili (2019)"], "http://www.w3.org/2006/time#hasTime": ["http://data.archaeology.link/data/ancientports/3498_foundation"], "http://www.wikidata.org/prop/direct/P1584": ["http://pleiades.stoa.org/places/678025"], "http://www.wikidata.org/prop/direct/P17": ["http://www.wikidata.org/entity/Q801"], "http://www.wikidata.org/prop/direct/P1936": ["http://imperium.ahlfeldt.se/places/21682"], "http://www.wikidata.org/prop/direct/P1958": ["https://www.trismegistos.org/place/12032"], "http://www.wikidata.org/prop/direct/P8068": ["https://topostext.org/place/322348UApo"], "begin": "-1500"}, "geometry": {"type": "Point", "coordinates": [34.8036, 32.1903]}}], "numberMatched": 1, "numberReturned": 1}