{"type": "FeatureCollection", "id": "http://imperium.ahlfeldt.se/places/45238", "name": "45238", "features": [{"type": "Feature", "id": "http://data.archaeology.link/data/ancientports/402", "label": "Roman villa at L'Albir", "properties": {"http://purl.org/dc/elements/1.1/created": ["2023"], "http://purl.org/dc/elements/1.1/creator": ["http://data.archaeology.link/data/spphaefen/arthur_de_graauw"], "http://www.opengis.net/ont/geosparql#hasGeometry": ["http://data.archaeology.link/data/ancientports/402_geom"], "http://www.w3.org/1999/02/22-rdf-syntax-ns#type": ["http://www.ancientports.com/ont#VillaMaritima"], "http://www.w3.org/2000/01/rdf-schema#label": ["Roman villa at L'Albir"], "http://www.wikidata.org/prop/direct/P17": ["http://www.wikidata.org/entity/Q29"], "http://www.wikidata.org/prop/direct/P1936": ["http://imperium.ahlfeldt.se/places/45238"]}, "geometry": {"type": "Point", "coordinates": [-0.0666, 38.57355]}}]}