{"type": "FeatureCollection", "id": "https://topostext.org/place/362337UAph", "name": "362337UAph", "features": [{"type": "Feature", "id": "http://data.archaeology.link/data/ancientports/3360", "name": "Tisan K\u00f6y\u00fc, Ovacik Adasi, north of cape B\u00f6l\u00fckada Burnu", "dateprops": ["begin"], "properties": {"http://purl.org/dc/elements/1.1/creator": ["http://data.archaeology.link/data/spphaefen/arthur_de_graauw"], "http://purl.org/dc/terms/partOf": ["http://data.archaeology.link/data/ancientports/bib_deGrauw_2013_GeoDB"], "http://www.opengis.net/ont/geosparql#hasGeometry": ["http://data.archaeology.link/data/ancientports/3360_geom"], "http://www.w3.org/1999/02/22-rdf-syntax-ns#type": ["http://www.ancientports.com/ont#Harbour"], "http://www.w3.org/2000/01/rdf-schema#label": ["Tisan K\u00f6y\u00fc, Ovacik Adasi, north of cape B\u00f6l\u00fckada Burnu"], "http://www.w3.org/2002/07/owl#sameAs": ["http://www.wikidata.org/entity/Q4779720"], "http://www.w3.org/2006/time#hasTime": ["http://data.archaeology.link/data/ancientports/3360_foundation"], "http://www.wikidata.org/prop/direct/P1584": ["http://pleiades.stoa.org/places/648565"], "http://www.wikidata.org/prop/direct/P17": ["http://www.wikidata.org/entity/Q43"], "http://www.wikidata.org/prop/direct/P1936": ["http://imperium.ahlfeldt.se/places/43302"], "http://www.wikidata.org/prop/direct/P1958": ["https://www.trismegistos.org/place/3587"], "http://www.wikidata.org/prop/direct/P8068": ["https://topostext.org/place/362337UAph"], "begin": "-330"}, "geometry": {"type": "Point", "coordinates": [33.6858, 33.6898]}}], "numberMatched": 1, "numberReturned": 1, "bbox": [33.6858, 33.6898, 33.6858, 33.6898], "crs": "http://www.opengis.net/def/crs/EPSG/0/4326"}