{"type": "FeatureCollection", "id": "http://imperium.ahlfeldt.se/places/29254", "name": "29254", "features": [{"type": "Feature", "id": "http://data.archaeology.link/data/ancientports/1271", "label": "Monte Saraceno, near Mattinata", "properties": {"http://purl.org/dc/elements/1.1/created": ["2023"], "http://purl.org/dc/elements/1.1/creator": ["http://data.archaeology.link/data/spphaefen/arthur_de_graauw"], "http://www.ancientports.com/ont#date_min": ["-750"], "http://www.opengis.net/ont/geosparql#hasGeometry": ["http://data.archaeology.link/data/ancientports/1271_geom"], "http://www.w3.org/1999/02/22-rdf-syntax-ns#type": ["http://www.ancientports.com/ont#Harbour"], "http://www.w3.org/2000/01/rdf-schema#label": ["Monte Saraceno, near Mattinata"], "http://www.wikidata.org/prop/direct/P1584": ["http://pleiades.stoa.org/places/442677"], "http://www.wikidata.org/prop/direct/P17": ["Italy Adriatic"], "http://www.wikidata.org/prop/direct/P1936": ["http://imperium.ahlfeldt.se/places/29254"]}, "geometry": {"type": "Point", "coordinates": [16.06038, 41.69375]}}]}