{"type": "FeatureCollection", "id": "http://imperium.ahlfeldt.se/places/8023", "name": "8023", "features": [{"type": "Feature", "id": "http://data.archaeology.link/data/ancientports/616", "label": "Salses le Ch\u00e2teau", "dateprops": [], "properties": {"http://purl.org/dc/elements/1.1/created": ["2023"], "http://purl.org/dc/elements/1.1/creator": ["http://data.archaeology.link/data/spphaefen/arthur_de_graauw"], "http://www.ancientports.com/ont#date_min": ["-330"], "http://www.opengis.net/ont/geosparql#hasGeometry": ["http://data.archaeology.link/data/ancientports/616_geom"], "http://www.w3.org/1999/02/22-rdf-syntax-ns#type": ["http://www.ancientports.com/ont#Harbour"], "http://www.w3.org/2000/01/rdf-schema#label": ["Salses le Ch\u00e2teau"], "http://www.w3.org/2002/07/owl#sameAs": ["http://www.wikidata.org/entity/Q821246"], "http://www.wikidata.org/prop/direct/P1584": ["http://pleiades.stoa.org/places/246611"], "http://www.wikidata.org/prop/direct/P17": ["France South"], "http://www.wikidata.org/prop/direct/P1936": ["http://imperium.ahlfeldt.se/places/8023"], "http://www.wikidata.org/prop/direct/P1958": ["https://www.trismegistos.org/place/21908"]}, "geometry": {"type": "Point", "coordinates": [2.966, 42.839]}}]}