{"type": "FeatureCollection", "id": "http://www.wikidata.org/entity/Q3358045", "name": "Oued Miliane", "features": [{"type": "Feature", "id": "http://data.archaeology.link/data/ancientports/4172", "name": "Wadi Miliane? near Hammam Lif", "dateprops": ["begin"], "properties": {"http://purl.org/dc/elements/1.1/created": ["2023"], "http://purl.org/dc/elements/1.1/creator": ["http://data.archaeology.link/data/spphaefen/arthur_de_graauw"], "http://www.opengis.net/ont/geosparql#hasGeometry": ["http://data.archaeology.link/data/ancientports/4172_geom"], "http://www.w3.org/1999/02/22-rdf-syntax-ns#type": ["http://www.ancientports.com/ont#Harbour"], "http://www.w3.org/2000/01/rdf-schema#label": ["Wadi Miliane? near Hammam Lif"], "http://www.w3.org/2002/07/owl#sameAs": ["http://www.wikidata.org/entity/Q3358045"], "http://www.w3.org/2006/time#hasTime": ["http://data.archaeology.link/data/ancientports/4172_foundation"], "http://www.wikidata.org/prop/direct/P1584": ["http://pleiades.stoa.org/places/315092"], "http://www.wikidata.org/prop/direct/P17": ["http://www.wikidata.org/entity/Q948"], "http://www.wikidata.org/prop/direct/P1936": ["http://imperium.ahlfeldt.se/places/28153"], "http://www.wikidata.org/prop/direct/P1958": ["https://www.trismegistos.org/place/17141"], "begin": "-30"}, "geometry": {"type": "Point", "coordinates": [10.305, 36.767]}}]}