{"type": "FeatureCollection", "id": "http://pleiades.stoa.org/places/438710", "name": "438710", "features": [{"type": "Feature", "id": "http://data.archaeology.link/data/ancientports/938", "label": "Tor San Lorenzo, at Porto Rutulo", "properties": {"http://purl.org/dc/elements/1.1/created": ["2023"], "http://purl.org/dc/elements/1.1/creator": ["http://data.archaeology.link/data/spphaefen/arthur_de_graauw"], "http://www.ancientports.com/ont#date_min": ["-750"], "http://www.opengis.net/ont/geosparql#hasGeometry": ["http://data.archaeology.link/data/ancientports/938_geom"], "http://www.w3.org/1999/02/22-rdf-syntax-ns#type": ["http://www.ancientports.com/ont#Harbour"], "http://www.w3.org/2000/01/rdf-schema#label": ["Tor San Lorenzo, at Porto Rutulo"], "http://www.w3.org/2002/07/owl#sameAs": ["http://www.wikidata.org/entity/Q241733"], "http://www.wikidata.org/prop/direct/P1584": ["http://pleiades.stoa.org/places/438710"], "http://www.wikidata.org/prop/direct/P17": ["Italy West"], "http://www.wikidata.org/prop/direct/P1936": ["http://imperium.ahlfeldt.se/places/41381"], "http://www.wikidata.org/prop/direct/P1958": ["https://www.trismegistos.org/place/61099"], "http://www.wikidata.org/prop/direct/P8068": ["https://topostext.org/place/416125UCaI"]}, "geometry": {"type": "Point", "coordinates": [12.5113, 41.5803]}}]}