{"type": "FeatureCollection", "id": "https://topostext.org/place/391171PCro", "name": "391171PCro", "features": [{"type": "Feature", "id": "http://data.archaeology.link/data/ancientports/1082", "label": "Crotone, on R Esaro", "dateprops": ["http://purl.org/dc/elements/1.1/created", "http://www.ancientports.com/ont#date_min"], "properties": {"http://purl.org/dc/elements/1.1/created": ["2023"], "http://purl.org/dc/elements/1.1/creator": ["http://data.archaeology.link/data/spphaefen/arthur_de_graauw"], "http://www.ancientports.com/ont#date_min": ["-750"], "http://www.opengis.net/ont/geosparql#hasGeometry": ["http://data.archaeology.link/data/ancientports/1082_geom"], "http://www.w3.org/1999/02/22-rdf-syntax-ns#type": ["http://www.ancientports.com/ont#Harbour"], "http://www.w3.org/2000/01/rdf-schema#label": ["Crotone, on R Esaro"], "http://www.w3.org/2002/07/owl#sameAs": ["http://www.wikidata.org/entity/Q6681"], "http://www.wikidata.org/prop/direct/P1584": ["http://pleiades.stoa.org/places/452317"], "http://www.wikidata.org/prop/direct/P17": ["Italy West"], "http://www.wikidata.org/prop/direct/P1936": ["http://imperium.ahlfeldt.se/places/16739"], "http://www.wikidata.org/prop/direct/P1958": ["https://www.trismegistos.org/place/33075"], "http://www.wikidata.org/prop/direct/P8068": ["https://topostext.org/place/391171PCro"]}, "geometry": {"type": "Point", "coordinates": [17.12635, 39.08554]}}]}