{"type": "FeatureCollection", "id": "http://www.wikidata.org/entity/Q690575", "name": "Q690575", "features": [{"type": "Feature", "id": "http://data.archaeology.link/data/ancientports/3235", "label": "Cnide East, former isle of Triopion now connected to mainland, Cape Kriou, with possible ancient lighthouse", "properties": {"http://purl.org/dc/elements/1.1/created": ["2023"], "http://purl.org/dc/elements/1.1/creator": ["http://data.archaeology.link/data/spphaefen/arthur_de_graauw"], "http://www.ancientports.com/ont#date_min": ["-330"], "http://www.opengis.net/ont/geosparql#hasGeometry": ["http://data.archaeology.link/data/ancientports/3235_geom"], "http://www.w3.org/1999/02/22-rdf-syntax-ns#type": ["http://www.ancientports.com/ont#Harbour"], "http://www.w3.org/2000/01/rdf-schema#label": ["Cnide East, former isle of Triopion now connected to mainland, Cape Kriou, with possible ancient lighthouse"], "http://www.w3.org/2002/07/owl#sameAs": ["http://www.wikidata.org/entity/Q690575"], "http://www.wikidata.org/prop/direct/P1584": ["http://pleiades.stoa.org/places/599576"], "http://www.wikidata.org/prop/direct/P17": ["TR: South"], "http://www.wikidata.org/prop/direct/P1936": ["http://imperium.ahlfeldt.se/places/21190"], "http://www.wikidata.org/prop/direct/P1958": ["https://www.trismegistos.org/place/1121"], "http://www.wikidata.org/prop/direct/P8068": ["https://topostext.org/place/367274PKni"]}, "geometry": {"type": "Point", "coordinates": [27.37643, 36.68371]}}, {"type": "Feature", "id": "http://data.archaeology.link/data/ancientports/3234", "label": "Cnide West, former isle of Triopion now connected to mainland, Cape Kriou", "properties": {"http://purl.org/dc/elements/1.1/created": ["2023"], "http://purl.org/dc/elements/1.1/creator": ["http://data.archaeology.link/data/spphaefen/arthur_de_graauw"], "http://www.ancientports.com/ont#date_min": ["-330"], "http://www.opengis.net/ont/geosparql#hasGeometry": ["http://data.archaeology.link/data/ancientports/3234_geom"], "http://www.w3.org/1999/02/22-rdf-syntax-ns#type": ["http://www.ancientports.com/ont#Shipyard", "http://www.ancientports.com/ont#Slipway", "http://www.ancientports.com/ont#Quay"], "http://www.w3.org/2000/01/rdf-schema#label": ["Cnide West, former isle of Triopion now connected to mainland, Cape Kriou"], "http://www.w3.org/2002/07/owl#sameAs": ["http://www.wikidata.org/entity/Q690575"], "http://www.w3.org/2004/02/skos/core#note": ["Mauro (2022)"], "http://www.wikidata.org/prop/direct/P1584": ["http://pleiades.stoa.org/places/599576"], "http://www.wikidata.org/prop/direct/P17": ["TR: West"], "http://www.wikidata.org/prop/direct/P1936": ["http://imperium.ahlfeldt.se/places/21190"], "http://www.wikidata.org/prop/direct/P1958": ["https://www.trismegistos.org/place/1121"], "http://www.wikidata.org/prop/direct/P8068": ["https://topostext.org/place/367274PKni"]}, "geometry": {"type": "Point", "coordinates": [27.37182, 36.68629]}}]}