{"type": "FeatureCollection", "id": "http://www.wikidata.org/entity/Q455657", "name": "Fos-sur-Mer", "features": [{"type": "Feature", "id": "http://data.archaeology.link/data/ancientports/653", "name": "Fos marina, Anse St Gervais near Fos and etang de l\u2019Estomac and digue de la Marronede", "dateprops": ["begin"], "properties": {"http://purl.org/dc/elements/1.1/creator": ["http://data.archaeology.link/data/spphaefen/arthur_de_graauw"], "http://purl.org/dc/terms/isReferencedBy": ["http://www.arkaeos.fr/?digue-de-la-marronede-golfe-de-fos"], "http://purl.org/dc/terms/partOf": ["http://data.archaeology.link/data/ancientports/bib_deGrauw_2013_GeoDB"], "http://www.opengis.net/ont/geosparql#hasGeometry": ["http://data.archaeology.link/data/ancientports/653_geom"], "http://www.w3.org/1999/02/22-rdf-syntax-ns#type": ["http://www.ancientports.com/ont#Harbour"], "http://www.w3.org/2000/01/rdf-schema#label": ["Fos marina, Anse St Gervais near Fos and etang de l\u2019Estomac and digue de la Marronede"], "http://www.w3.org/2002/07/owl#sameAs": ["http://www.wikidata.org/entity/Q455657"], "http://www.w3.org/2004/02/skos/core#note": ["Fontaine (2016)", "Marty (2019)"], "http://www.w3.org/2006/time#hasTime": ["http://data.archaeology.link/data/ancientports/653_foundation"], "http://www.wikidata.org/prop/direct/P1584": ["http://pleiades.stoa.org/places/148085"], "http://www.wikidata.org/prop/direct/P17": ["http://www.wikidata.org/entity/Q142"], "http://www.wikidata.org/prop/direct/P1936": ["http://imperium.ahlfeldt.se/places/6586"], "begin": "-330"}, "geometry": {"type": "Point", "coordinates": [4.9342, 43.429]}}]}