{"type": "FeatureCollection", "id": "http://imperium.ahlfeldt.se/places/27561", "name": "27561", "features": [{"type": "Feature", "id": "http://data.archaeology.link/data/ancientports/2621", "name": "Semenovka", "dateprops": ["begin"], "properties": {"http://purl.org/dc/elements/1.1/created": ["2023"], "http://purl.org/dc/elements/1.1/creator": ["http://data.archaeology.link/data/spphaefen/arthur_de_graauw"], "http://www.opengis.net/ont/geosparql#hasGeometry": ["http://data.archaeology.link/data/ancientports/2621_geom"], "http://www.w3.org/1999/02/22-rdf-syntax-ns#type": ["http://www.ancientports.com/ont#Harbour"], "http://www.w3.org/2000/01/rdf-schema#label": ["Semenovka"], "http://www.w3.org/2006/time#hasTime": ["http://data.archaeology.link/data/ancientports/2621_foundation"], "http://www.wikidata.org/prop/direct/P1584": ["http://pleiades.stoa.org/places/854734"], "http://www.wikidata.org/prop/direct/P17": ["http://www.wikidata.org/entity/Q212"], "http://www.wikidata.org/prop/direct/P1936": ["http://imperium.ahlfeldt.se/places/27561"], "begin": "-330"}, "geometry": {"type": "Point", "coordinates": [35.7607, 45.3812]}}]}