{"type": "FeatureCollection", "id": "http://pleiades.stoa.org/places/550905", "name": "550905", "features": [{"type": "Feature", "id": "http://data.archaeology.link/data/ancientports/2196", "name": "Quarry at Tarti, on the isle of Lesbos, Lesvos", "dateprops": ["begin"], "properties": {"http://purl.org/dc/elements/1.1/created": ["2023"], "http://purl.org/dc/elements/1.1/creator": ["http://data.archaeology.link/data/spphaefen/arthur_de_graauw"], "http://www.opengis.net/ont/geosparql#hasGeometry": ["http://data.archaeology.link/data/ancientports/2196_geom"], "http://www.w3.org/1999/02/22-rdf-syntax-ns#type": ["http://www.ancientports.com/ont#Harbour"], "http://www.w3.org/2000/01/rdf-schema#label": ["Quarry at Tarti, on the isle of Lesbos, Lesvos"], "http://www.w3.org/2006/time#hasTime": ["http://data.archaeology.link/data/ancientports/2196_foundation"], "http://www.wikidata.org/prop/direct/P1584": ["http://pleiades.stoa.org/places/550905"], "http://www.wikidata.org/prop/direct/P17": ["http://www.wikidata.org/entity/Q41"], "http://www.wikidata.org/prop/direct/P1936": ["http://imperium.ahlfeldt.se/places/37981"], "http://www.wikidata.org/prop/direct/P8068": ["https://topostext.org/place/390265QTar"], "begin": "-550"}, "geometry": {"type": "Point", "coordinates": [26.4936, 38.9772]}}]}