{"type": "FeatureCollection", "id": "https://www.trismegistos.org/place/33898", "name": "33898", "features": [{"type": "Feature", "id": "http://data.archaeology.link/data/ancientports/1821", "name": "near Megisti Lavra monastry", "dateprops": ["begin"], "properties": {"http://purl.org/dc/elements/1.1/creator": ["http://data.archaeology.link/data/spphaefen/arthur_de_graauw"], "http://purl.org/dc/terms/partOf": ["http://data.archaeology.link/data/ancientports/bib_deGrauw_2013_GeoDB"], "http://www.opengis.net/ont/geosparql#hasGeometry": ["http://data.archaeology.link/data/ancientports/1821_geom"], "http://www.w3.org/1999/02/22-rdf-syntax-ns#type": ["http://www.ancientports.com/ont#Harbour"], "http://www.w3.org/2000/01/rdf-schema#label": ["near Megisti Lavra monastry"], "http://www.w3.org/2002/07/owl#sameAs": ["http://www.wikidata.org/entity/Q17620105"], "http://www.w3.org/2006/time#hasTime": ["http://data.archaeology.link/data/ancientports/1821_foundation"], "http://www.wikidata.org/prop/direct/P1584": ["http://pleiades.stoa.org/places/501343"], "http://www.wikidata.org/prop/direct/P17": ["http://www.wikidata.org/entity/Q41"], "http://www.wikidata.org/prop/direct/P1936": ["http://imperium.ahlfeldt.se/places/32294"], "http://www.wikidata.org/prop/direct/P1958": ["https://www.trismegistos.org/place/33898"], "http://www.wikidata.org/prop/direct/P8068": ["https://topostext.org/place/402243PAkr"], "begin": "-550"}, "geometry": {"type": "Point", "coordinates": [24.391, 40.171]}}], "numberMatched": 1, "numberReturned": 1, "bbox": [24.391, 40.171, 24.391, 40.171], "crs": "http://www.opengis.net/def/crs/OGC/1.3/CRS84"}