{"type": "FeatureCollection", "id": "https://www.trismegistos.org/place/906", "name": "906", "features": [{"type": "Feature", "id": "http://data.archaeology.link/data/ancientports/2119", "label": "Isle of Ios, Aniye", "properties": {"http://purl.org/dc/elements/1.1/created": ["2023"], "http://purl.org/dc/elements/1.1/creator": ["http://data.archaeology.link/data/spphaefen/arthur_de_graauw"], "http://www.opengis.net/ont/geosparql#hasGeometry": ["http://data.archaeology.link/data/ancientports/2119_geom"], "http://www.w3.org/1999/02/22-rdf-syntax-ns#type": ["http://www.ancientports.com/ont#Harbour"], "http://www.w3.org/2000/01/rdf-schema#label": ["Isle of Ios, Aniye"], "http://www.w3.org/2002/07/owl#sameAs": ["http://www.wikidata.org/entity/Q216993"], "http://www.wikidata.org/prop/direct/P1584": ["http://pleiades.stoa.org/places/599673"], "http://www.wikidata.org/prop/direct/P17": ["GR: Cyclades Isl."], "http://www.wikidata.org/prop/direct/P1936": ["http://imperium.ahlfeldt.se/places/41350"], "http://www.wikidata.org/prop/direct/P1958": ["https://www.trismegistos.org/place/906"]}, "geometry": {"type": "Point", "coordinates": [25.32905, 36.7227]}}, {"type": "Feature", "id": "http://data.archaeology.link/data/ancientports/2120", "label": "Ios, on the isle of Ios", "properties": {"http://purl.org/dc/elements/1.1/created": ["2023"], "http://purl.org/dc/elements/1.1/creator": ["http://data.archaeology.link/data/spphaefen/arthur_de_graauw"], "http://www.opengis.net/ont/geosparql#hasGeometry": ["http://data.archaeology.link/data/ancientports/2120_geom"], "http://www.w3.org/1999/02/22-rdf-syntax-ns#type": ["http://www.ancientports.com/ont#Harbour"], "http://www.w3.org/2000/01/rdf-schema#label": ["Ios, on the isle of Ios"], "http://www.w3.org/2002/07/owl#sameAs": ["http://www.wikidata.org/entity/Q216993"], "http://www.w3.org/2004/02/skos/core#note": ["Marthari (2009)"], "http://www.wikidata.org/prop/direct/P1584": ["http://pleiades.stoa.org/places/599672"], "http://www.wikidata.org/prop/direct/P17": ["GR: Cyclades Isl."], "http://www.wikidata.org/prop/direct/P1936": ["http://imperium.ahlfeldt.se/places/23505"], "http://www.wikidata.org/prop/direct/P1958": ["https://www.trismegistos.org/place/906"], "http://www.wikidata.org/prop/direct/P8068": ["https://topostext.org/place/367253PIos"]}, "geometry": {"type": "Point", "coordinates": [25.2822, 36.7233]}}]}