{"type": "FeatureCollection", "id": "http://www.wikidata.org/entity/Q23725", "name": "Q23725", "features": [{"type": "Feature", "id": "http://data.archaeology.link/data/ancientports/2405", "label": "Istanbul", "properties": {"http://purl.org/dc/elements/1.1/created": ["2023"], "http://purl.org/dc/elements/1.1/creator": ["http://data.archaeology.link/data/spphaefen/arthur_de_graauw"], "http://www.ancientports.com/ont#date_min": ["-659"], "http://www.opengis.net/ont/geosparql#hasGeometry": ["http://data.archaeology.link/data/ancientports/2405_geom"], "http://www.w3.org/1999/02/22-rdf-syntax-ns#type": ["http://www.ancientports.com/ont#Harbour"], "http://www.w3.org/2000/01/rdf-schema#label": ["Istanbul"], "http://www.w3.org/2002/07/owl#sameAs": ["http://www.wikidata.org/entity/Q23725"], "http://www.wikidata.org/prop/direct/P1584": ["http://pleiades.stoa.org/places/520985"], "http://www.wikidata.org/prop/direct/P17": ["TR: Bosph N"], "http://www.wikidata.org/prop/direct/P1958": ["https://www.trismegistos.org/place/478"]}, "geometry": {"type": "Point", "coordinates": [28.95894, 40.98873]}}]}