{"type": "FeatureCollection", "id": "http://imperium.ahlfeldt.se/places/18294", "name": "18294", "features": [{"type": "Feature", "id": "http://data.archaeology.link/data/ancientports/440", "label": "Blanes", "properties": {"http://purl.org/dc/elements/1.1/created": ["2023"], "http://purl.org/dc/elements/1.1/creator": ["http://data.archaeology.link/data/spphaefen/arthur_de_graauw"], "http://www.ancientports.com/ont#date_min": ["-30"], "http://www.opengis.net/ont/geosparql#hasGeometry": ["http://data.archaeology.link/data/ancientports/440_geom"], "http://www.w3.org/1999/02/22-rdf-syntax-ns#type": ["http://www.ancientports.com/ont#Harbour"], "http://www.w3.org/2000/01/rdf-schema#label": ["Blanes"], "http://www.w3.org/2002/07/owl#sameAs": ["http://www.wikidata.org/entity/Q12991"], "http://www.wikidata.org/prop/direct/P1584": ["http://pleiades.stoa.org/places/246251"], "http://www.wikidata.org/prop/direct/P17": ["http://www.wikidata.org/entity/Q29"], "http://www.wikidata.org/prop/direct/P1936": ["http://imperium.ahlfeldt.se/places/18294"], "http://www.wikidata.org/prop/direct/P1958": ["https://www.trismegistos.org/place/39403"], "http://www.wikidata.org/prop/direct/P8068": ["https://topostext.org/place/417027UBla"]}, "geometry": {"type": "Point", "coordinates": [2.79565, 41.6703]}}]}