{"type": "FeatureCollection", "id": "http://www.wikidata.org/entity/Q82859", "name": "Q82859", "features": [{"type": "Feature", "id": "http://data.archaeology.link/data/ancientports/3722_1", "label": "Hoq cave on Socotra island, with many inscriptions and a drawing of a ship", "properties": {"http://purl.org/dc/elements/1.1/created": ["2023"], "http://purl.org/dc/elements/1.1/creator": ["http://data.archaeology.link/data/spphaefen/arthur_de_graauw"], "http://www.opengis.net/ont/geosparql#hasGeometry": ["http://data.archaeology.link/data/ancientports/3722_1_geom"], "http://www.w3.org/1999/02/22-rdf-syntax-ns#type": ["http://www.ancientports.com/ont#Harbour"], "http://www.w3.org/2000/01/rdf-schema#label": ["Hoq cave on Socotra island, with many inscriptions and a drawing of a ship"], "http://www.w3.org/2002/07/owl#sameAs": ["http://www.wikidata.org/entity/Q82859"], "http://www.w3.org/2004/02/skos/core#note": ["Robin (2002)", "Strauch (2016)"], "http://www.wikidata.org/prop/direct/P17": ["Yemen: Socotra"]}, "geometry": {"type": "Point", "coordinates": [54.3542, 12.5879]}}, {"type": "Feature", "id": "http://data.archaeology.link/data/ancientports/3722", "label": "Isle of Socotra, Suqutra", "properties": {"http://purl.org/dc/elements/1.1/created": ["2023"], "http://purl.org/dc/elements/1.1/creator": ["http://data.archaeology.link/data/spphaefen/arthur_de_graauw"], "http://purl.org/dc/terms/isReferencedBy": ["https://pleiades.stoa.org/places/39362"], "http://www.opengis.net/ont/geosparql#hasGeometry": ["http://data.archaeology.link/data/ancientports/3722_geom"], "http://www.w3.org/1999/02/22-rdf-syntax-ns#type": ["http://www.ancientports.com/ont#Harbour"], "http://www.w3.org/2000/01/rdf-schema#label": ["Isle of Socotra, Suqutra"], "http://www.w3.org/2002/07/owl#sameAs": ["http://www.wikidata.org/entity/Q82859"], "http://www.w3.org/2004/02/skos/core#note": ["Marcotte (2017)", "https://pleiades.stoa.org/places/39362"], "http://www.wikidata.org/prop/direct/P1584": ["http://pleiades.stoa.org/places/39338"], "http://www.wikidata.org/prop/direct/P17": ["Yemen: Socotra"]}, "geometry": {"type": "Point", "coordinates": [53.76735, 12.45581]}}]}