{"type": "FeatureCollection", "id": "http://pleiades.stoa.org/places/433006", "name": "433006", "features": [{"type": "Feature", "id": "http://data.archaeology.link/data/ancientports/1010", "name": "Palazzo a Mare, near Marina Grande on the isle of Capri", "dateprops": ["begin"], "properties": {"http://purl.org/dc/elements/1.1/created": ["2023"], "http://purl.org/dc/elements/1.1/creator": ["http://data.archaeology.link/data/spphaefen/arthur_de_graauw"], "http://www.opengis.net/ont/geosparql#hasGeometry": ["http://data.archaeology.link/data/ancientports/1010_geom"], "http://www.w3.org/1999/02/22-rdf-syntax-ns#type": ["http://www.ancientports.com/ont#Quay", "http://www.ancientports.com/ont#Pila"], "http://www.w3.org/2000/01/rdf-schema#label": ["Palazzo a Mare, near Marina Grande on the isle of Capri"], "http://www.w3.org/2002/07/owl#sameAs": ["http://www.wikidata.org/entity/Q3891134"], "http://www.w3.org/2006/time#hasTime": ["http://data.archaeology.link/data/ancientports/1010_foundation"], "http://www.wikidata.org/prop/direct/P1584": ["http://pleiades.stoa.org/places/433006"], "http://www.wikidata.org/prop/direct/P17": ["http://www.wikidata.org/entity/Q38"], "http://www.wikidata.org/prop/direct/P1936": ["http://imperium.ahlfeldt.se/places/22398"], "begin": "-30"}, "geometry": {"type": "Point", "coordinates": [14.2288, 40.5596]}}]}