{"type": "FeatureCollection", "id": "http://www.wikidata.org/entity/Q459673", "name": "Q459673", "features": [{"type": "Feature", "id": "http://data.archaeology.link/data/ancientports/617", "label": "Leucate", "dateprops": ["http://purl.org/dc/elements/1.1/created"], "properties": {"http://purl.org/dc/elements/1.1/created": ["2023"], "http://purl.org/dc/elements/1.1/creator": ["http://data.archaeology.link/data/spphaefen/arthur_de_graauw"], "http://www.opengis.net/ont/geosparql#hasGeometry": ["http://data.archaeology.link/data/ancientports/617_geom"], "http://www.w3.org/1999/02/22-rdf-syntax-ns#type": ["http://www.ancientports.com/ont#Harbour"], "http://www.w3.org/2000/01/rdf-schema#label": ["Leucate"], "http://www.w3.org/2002/07/owl#sameAs": ["http://www.wikidata.org/entity/Q459673"], "http://www.wikidata.org/prop/direct/P17": ["France South"]}, "geometry": {"type": "Point", "coordinates": [3.02008, 42.88395]}}]}