{"type": "FeatureCollection", "id": "https://www.trismegistos.org/place/1220", "name": "1220", "features": [{"type": "Feature", "id": "http://data.archaeology.link/data/ancientports/1689", "label": "Lamia ", "dateprops": [], "properties": {"http://purl.org/dc/elements/1.1/created": ["2023"], "http://purl.org/dc/elements/1.1/creator": ["http://data.archaeology.link/data/spphaefen/arthur_de_graauw"], "http://www.ancientports.com/ont#date_min": ["-550"], "http://www.opengis.net/ont/geosparql#hasGeometry": ["http://data.archaeology.link/data/ancientports/1689_geom"], "http://www.w3.org/1999/02/22-rdf-syntax-ns#type": ["http://www.ancientports.com/ont#Harbour"], "http://www.w3.org/2000/01/rdf-schema#label": ["Lamia "], "http://www.w3.org/2002/07/owl#sameAs": ["http://www.wikidata.org/entity/Q192980"], "http://www.wikidata.org/prop/direct/P1584": ["http://pleiades.stoa.org/places/540902"], "http://www.wikidata.org/prop/direct/P17": ["GR: Attica +"], "http://www.wikidata.org/prop/direct/P1936": ["http://imperium.ahlfeldt.se/places/22750"], "http://www.wikidata.org/prop/direct/P1958": ["https://www.trismegistos.org/place/1220"], "http://www.wikidata.org/prop/direct/P8068": ["https://topostext.org/place/389224PLam"]}, "geometry": {"type": "Point", "coordinates": [22.4351, 38.9045]}}]}