{"type": "FeatureCollection", "id": "http://imperium.ahlfeldt.se/places/42399", "name": "42399", "features": [{"type": "Feature", "id": "http://data.archaeology.link/data/ancientports/4265", "name": "Isles of Habibas north of Bouzedjar", "dateprops": [], "properties": {"http://purl.org/dc/elements/1.1/creator": ["http://data.archaeology.link/data/spphaefen/arthur_de_graauw"], "http://purl.org/dc/terms/partOf": ["http://data.archaeology.link/data/ancientports/bib_deGrauw_2013_GeoDB"], "http://www.opengis.net/ont/geosparql#hasGeometry": ["http://data.archaeology.link/data/ancientports/4265_geom"], "http://www.w3.org/1999/02/22-rdf-syntax-ns#type": ["http://www.ancientports.com/ont#Harbour"], "http://www.w3.org/2000/01/rdf-schema#label": ["Isles of Habibas north of Bouzedjar"], "http://www.wikidata.org/prop/direct/P1584": ["http://pleiades.stoa.org/places/285531"], "http://www.wikidata.org/prop/direct/P17": ["http://www.wikidata.org/entity/Q262"], "http://www.wikidata.org/prop/direct/P1936": ["http://imperium.ahlfeldt.se/places/42399"], "begin": ""}, "geometry": {"type": "Point", "coordinates": [-1.13152, 35.72413]}}], "numberMatched": 1, "numberReturned": 1}