{"type": "FeatureCollection", "id": "http://pleiades.stoa.org/places/462084", "name": "462084", "features": [{"type": "Feature", "id": "http://data.archaeology.link/data/ancientports/1178", "label": "La Collina Torretta-Navetta, on the isle of Favignana", "properties": {"http://purl.org/dc/elements/1.1/created": ["2023"], "http://purl.org/dc/elements/1.1/creator": ["http://data.archaeology.link/data/spphaefen/arthur_de_graauw"], "http://www.opengis.net/ont/geosparql#hasGeometry": ["http://data.archaeology.link/data/ancientports/1178_geom"], "http://www.w3.org/1999/02/22-rdf-syntax-ns#type": ["http://www.ancientports.com/ont#Harbour"], "http://www.w3.org/2000/01/rdf-schema#label": ["La Collina Torretta-Navetta, on the isle of Favignana"], "http://www.w3.org/2002/07/owl#sameAs": ["http://www.wikidata.org/entity/Q216799"], "http://www.wikidata.org/prop/direct/P1584": ["http://pleiades.stoa.org/places/462084"], "http://www.wikidata.org/prop/direct/P17": ["Italy Sicily"], "http://www.wikidata.org/prop/direct/P1958": ["https://www.trismegistos.org/place/42873"]}, "geometry": {"type": "Point", "coordinates": [12.36386, 37.92499]}}, {"type": "Feature", "id": "http://data.archaeology.link/data/ancientports/1177", "label": "Favignana, on the isle of Favignana, the largest of the Egadi islands (Cuisenier mentions this site with two other possible sites: Faraglioni and Nisida, the latter clearly providing the best shelter as described by Homer)", "properties": {"http://purl.org/dc/elements/1.1/created": ["2023"], "http://purl.org/dc/elements/1.1/creator": ["http://data.archaeology.link/data/spphaefen/arthur_de_graauw"], "http://www.ancientports.com/ont#date_min": ["-750"], "http://www.opengis.net/ont/geosparql#hasGeometry": ["http://data.archaeology.link/data/ancientports/1177_geom"], "http://www.w3.org/1999/02/22-rdf-syntax-ns#type": ["http://www.ancientports.com/ont#Harbour"], "http://www.w3.org/2000/01/rdf-schema#label": ["Favignana, on the isle of Favignana, the largest of the Egadi islands (Cuisenier mentions this site with two other possible sites: Faraglioni and Nisida, the latter clearly providing the best shelter as described by Homer)"], "http://www.w3.org/2002/07/owl#sameAs": ["http://www.wikidata.org/entity/Q216799"], "http://www.wikidata.org/prop/direct/P1584": ["http://pleiades.stoa.org/places/462084"], "http://www.wikidata.org/prop/direct/P17": ["Italy Sicily"], "http://www.wikidata.org/prop/direct/P1958": ["https://www.trismegistos.org/place/42873"]}, "geometry": {"type": "Point", "coordinates": [12.32249, 37.93404]}}]}