{"type": "FeatureCollection", "id": "http://www.wikidata.org/entity/Q849330", "name": "Q849330", "features": [{"type": "Feature", "id": "http://data.archaeology.link/data/ancientports/173", "label": "Guetaria", "properties": {"http://purl.org/dc/elements/1.1/created": ["2023"], "http://purl.org/dc/elements/1.1/creator": ["http://data.archaeology.link/data/spphaefen/arthur_de_graauw"], "http://www.opengis.net/ont/geosparql#hasGeometry": ["http://data.archaeology.link/data/ancientports/173_geom"], "http://www.w3.org/1999/02/22-rdf-syntax-ns#type": ["http://www.ancientports.com/ont#Harbour"], "http://www.w3.org/2000/01/rdf-schema#label": ["Guetaria"], "http://www.w3.org/2002/07/owl#sameAs": ["http://www.wikidata.org/entity/Q849330"], "http://www.wikidata.org/prop/direct/P1584": ["https://pleiades.stoa.org/places/252216"], "http://www.wikidata.org/prop/direct/P17": ["Spain North"]}, "geometry": {"type": "Point", "coordinates": [-2.1987, 43.3011]}}]}