{"type": "FeatureCollection", "id": "http://pleiades.stoa.org/places/246441", "name": "246441", "features": [{"type": "Feature", "id": "http://data.archaeology.link/data/ancientports/447", "label": "Cala Montgo? Near L\u2019Escala", "dateprops": [], "properties": {"http://purl.org/dc/elements/1.1/created": ["2023"], "http://purl.org/dc/elements/1.1/creator": ["http://data.archaeology.link/data/spphaefen/arthur_de_graauw"], "http://www.ancientports.com/ont#date_min": ["-550"], "http://www.opengis.net/ont/geosparql#hasGeometry": ["http://data.archaeology.link/data/ancientports/447_geom"], "http://www.w3.org/1999/02/22-rdf-syntax-ns#type": ["http://www.ancientports.com/ont#Harbour"], "http://www.w3.org/2000/01/rdf-schema#label": ["Cala Montgo? Near L\u2019Escala"], "http://www.w3.org/2002/07/owl#sameAs": ["http://www.wikidata.org/entity/Q11304"], "http://www.wikidata.org/prop/direct/P1584": ["http://pleiades.stoa.org/places/246441"], "http://www.wikidata.org/prop/direct/P17": ["http://www.wikidata.org/entity/Q29"], "http://www.wikidata.org/prop/direct/P1936": ["http://imperium.ahlfeldt.se/places/18300"]}, "geometry": {"type": "Point", "coordinates": [3.17, 42.1067]}}]}