{"type": "FeatureCollection", "id": "http://pleiades.stoa.org/places/511225", "name": "511225", "features": [{"type": "Feature", "id": "http://data.archaeology.link/data/ancientports/2889", "label": "Ergili on Lake Manyas G\u00f6l\u00fc, near Muslucesme Neolithic settlement", "dateprops": [], "properties": {"http://purl.org/dc/elements/1.1/created": ["2023"], "http://purl.org/dc/elements/1.1/creator": ["http://data.archaeology.link/data/spphaefen/arthur_de_graauw"], "http://www.ancientports.com/ont#date_min": ["-750"], "http://www.opengis.net/ont/geosparql#hasGeometry": ["http://data.archaeology.link/data/ancientports/2889_geom"], "http://www.w3.org/1999/02/22-rdf-syntax-ns#type": ["http://www.ancientports.com/ont#Harbour"], "http://www.w3.org/2000/01/rdf-schema#label": ["Ergili on Lake Manyas G\u00f6l\u00fc, near Muslucesme Neolithic settlement"], "http://www.w3.org/2002/07/owl#sameAs": ["http://www.wikidata.org/entity/Q1171924"], "http://www.w3.org/2004/02/skos/core#note": ["Krauss (2017)"], "http://www.wikidata.org/prop/direct/P1584": ["http://pleiades.stoa.org/places/511225"], "http://www.wikidata.org/prop/direct/P17": ["TR: Marmara S"], "http://www.wikidata.org/prop/direct/P1936": ["http://imperium.ahlfeldt.se/places/21538"], "http://www.wikidata.org/prop/direct/P1958": ["https://www.trismegistos.org/place/16145"], "http://www.wikidata.org/prop/direct/P8068": ["https://topostext.org/place/401281PDas"]}, "geometry": {"type": "Point", "coordinates": [28.05039, 40.13224]}}]}