{"type": "FeatureCollection", "id": "http://imperium.ahlfeldt.se/places/36587", "name": "36587", "features": [{"type": "Feature", "id": "http://data.archaeology.link/data/ancientports/2256", "label": "Kato Phana, Fana, on the isle of Chios", "dateprops": [], "properties": {"http://purl.org/dc/elements/1.1/created": ["2023"], "http://purl.org/dc/elements/1.1/creator": ["http://data.archaeology.link/data/spphaefen/arthur_de_graauw"], "http://www.ancientports.com/ont#date_min": ["-750"], "http://www.opengis.net/ont/geosparql#hasGeometry": ["http://data.archaeology.link/data/ancientports/2256_geom"], "http://www.w3.org/1999/02/22-rdf-syntax-ns#type": ["http://www.ancientports.com/ont#Harbour"], "http://www.w3.org/2000/01/rdf-schema#label": ["Kato Phana, Fana, on the isle of Chios"], "http://www.wikidata.org/prop/direct/P1584": ["http://pleiades.stoa.org/places/550819"], "http://www.wikidata.org/prop/direct/P17": ["GR: Eastern Isl."], "http://www.wikidata.org/prop/direct/P1936": ["http://imperium.ahlfeldt.se/places/36587"], "http://www.wikidata.org/prop/direct/P1958": ["https://www.trismegistos.org/place/61256"], "http://www.wikidata.org/prop/direct/P8068": ["https://topostext.org/place/382259SPha"]}, "geometry": {"type": "Point", "coordinates": [25.9306, 38.207]}}]}