{"type": "FeatureCollection", "id": "http://www.wikidata.org/entity/Q65045277", "name": "Diolkides", "features": [{"type": "Feature", "id": "http://data.archaeology.link/data/ancientports/2867", "name": "near G\u00f6lc\u00fck", "dateprops": ["begin"], "properties": {"http://purl.org/dc/elements/1.1/created": ["2023"], "http://purl.org/dc/elements/1.1/creator": ["http://data.archaeology.link/data/spphaefen/arthur_de_graauw"], "http://www.opengis.net/ont/geosparql#hasGeometry": ["http://data.archaeology.link/data/ancientports/2867_geom"], "http://www.w3.org/1999/02/22-rdf-syntax-ns#type": ["http://www.ancientports.com/ont#Harbour"], "http://www.w3.org/2000/01/rdf-schema#label": ["near G\u00f6lc\u00fck"], "http://www.w3.org/2002/07/owl#sameAs": ["http://www.wikidata.org/entity/Q65045277"], "http://www.w3.org/2006/time#hasTime": ["http://data.archaeology.link/data/ancientports/2867_foundation"], "http://www.wikidata.org/prop/direct/P1584": ["http://pleiades.stoa.org/places/511237"], "http://www.wikidata.org/prop/direct/P17": ["http://www.wikidata.org/entity/Q43"], "http://www.wikidata.org/prop/direct/P1936": ["http://imperium.ahlfeldt.se/places/31382"], "begin": "3001"}, "geometry": {"type": "Point", "coordinates": [29.8602, 40.7227]}}]}