{"type": "FeatureCollection", "id": "http://www.wikidata.org/entity/Q949970", "name": "Povlja", "features": [{"type": "Feature", "id": "http://data.archaeology.link/data/ancientports/1464", "name": "Povlja, on the isle of Brac", "dateprops": ["begin"], "properties": {"http://purl.org/dc/elements/1.1/creator": ["http://data.archaeology.link/data/spphaefen/arthur_de_graauw"], "http://purl.org/dc/terms/isReferencedBy": ["http://baza.iarh.hr/public/locality/detail/1007"], "http://purl.org/dc/terms/partOf": ["http://data.archaeology.link/data/ancientports/bib_deGrauw_2013_GeoDB"], "http://www.opengis.net/ont/geosparql#hasGeometry": ["http://data.archaeology.link/data/ancientports/1464_geom"], "http://www.w3.org/1999/02/22-rdf-syntax-ns#type": ["http://www.ancientports.com/ont#Harbour"], "http://www.w3.org/2000/01/rdf-schema#label": ["Povlja, on the isle of Brac"], "http://www.w3.org/2002/07/owl#sameAs": ["http://www.wikidata.org/entity/Q949970"], "http://www.w3.org/2006/time#hasTime": ["http://data.archaeology.link/data/ancientports/1464_foundation"], "http://www.wikidata.org/prop/direct/P17": ["http://www.wikidata.org/entity/Q224"], "begin": "5001"}, "geometry": {"type": "Point", "coordinates": [16.836, 43.33356]}}], "numberMatched": 1, "numberReturned": 1}