{"type": "FeatureCollection", "id": "https://www.trismegistos.org/place/15347", "name": "15347", "features": [{"type": "Feature", "id": "http://data.archaeology.link/data/ancientports/45_2", "label": "Carriden House, at the eastern end of Antonine's wall, on Firth of Forth", "dateprops": [], "properties": {"http://purl.org/dc/elements/1.1/created": ["2023"], "http://purl.org/dc/elements/1.1/creator": ["http://data.archaeology.link/data/spphaefen/arthur_de_graauw"], "http://purl.org/dc/terms/isReferencedBy": ["https://ancientmonuments.uk/126859"], "http://www.opengis.net/ont/geosparql#hasGeometry": ["http://data.archaeology.link/data/ancientports/45_2_geom"], "http://www.w3.org/1999/02/22-rdf-syntax-ns#type": ["http://www.ancientports.com/ont#Harbour"], "http://www.w3.org/2000/01/rdf-schema#label": ["Carriden House, at the eastern end of Antonine's wall, on Firth of Forth"], "http://www.w3.org/2002/07/owl#sameAs": ["http://www.wikidata.org/entity/Q896424"], "http://www.w3.org/2006/time#hasTime": ["http://data.archaeology.link/data/ancientports/45_2_foundation"], "http://www.wikidata.org/prop/direct/P1584": ["http://pleiades.stoa.org/places/89309"], "http://www.wikidata.org/prop/direct/P17": ["http://www.wikidata.org/entity/Q145"], "http://www.wikidata.org/prop/direct/P1936": ["http://imperium.ahlfeldt.se/places/23499"], "http://www.wikidata.org/prop/direct/P1958": ["https://www.trismegistos.org/place/15347"]}, "geometry": {"type": "Point", "coordinates": [-3.5608, 56.0095]}}]}