{"type": "FeatureCollection", "id": "http://pleiades.stoa.org/places/295255", "name": "295255", "features": [{"type": "Feature", "id": "http://data.archaeology.link/data/ancientports/4227", "name": "Dar Mendil, on wadi Isser, Yusr", "dateprops": ["begin"], "properties": {"http://purl.org/dc/elements/1.1/creator": ["http://data.archaeology.link/data/spphaefen/arthur_de_graauw"], "http://purl.org/dc/terms/isReferencedBy": ["https://pleiades.stoa.org/places/295338"], "http://purl.org/dc/terms/partOf": ["http://data.archaeology.link/data/ancientports/bib_deGrauw_2013_GeoDB"], "http://www.opengis.net/ont/geosparql#hasGeometry": ["http://data.archaeology.link/data/ancientports/4227_geom"], "http://www.w3.org/1999/02/22-rdf-syntax-ns#type": ["http://www.ancientports.com/ont#Harbour"], "http://www.w3.org/2000/01/rdf-schema#label": ["Dar Mendil, on wadi Isser, Yusr"], "http://www.w3.org/2006/time#hasTime": ["http://data.archaeology.link/data/ancientports/4227_foundation"], "http://www.wikidata.org/prop/direct/P1584": ["http://pleiades.stoa.org/places/295255"], "http://www.wikidata.org/prop/direct/P17": ["http://www.wikidata.org/entity/Q262"], "http://www.wikidata.org/prop/direct/P1936": ["http://imperium.ahlfeldt.se/places/27058"], "begin": "-30"}, "geometry": {"type": "Point", "coordinates": [3.6724, 36.8349]}}]}