{"type": "FeatureCollection", "id": "https://topostext.org/place/353333PKer", "name": "353333PKer", "features": [{"type": "Feature", "id": "http://data.archaeology.link/data/ancientports/3092", "label": "Kyrenia, Girne, with an undated chain closure", "dateprops": [], "properties": {"http://purl.org/dc/elements/1.1/created": ["2023"], "http://purl.org/dc/elements/1.1/creator": ["http://data.archaeology.link/data/spphaefen/arthur_de_graauw"], "http://purl.org/dc/terms/isReferencedBy": ["https://www2.rgzm.de/navis2/home/frames.htm"], "http://www.opengis.net/ont/geosparql#hasGeometry": ["http://data.archaeology.link/data/ancientports/3092_geom"], "http://www.w3.org/1999/02/22-rdf-syntax-ns#type": ["http://www.ancientports.com/ont#Harbour"], "http://www.w3.org/2000/01/rdf-schema#label": ["Kyrenia, Girne, with an undated chain closure"], "http://www.w3.org/2002/07/owl#sameAs": ["http://www.wikidata.org/entity/Q206760"], "http://www.w3.org/2004/02/skos/core#note": ["Camiz (2020)"], "http://www.w3.org/2006/time#hasTime": ["http://data.archaeology.link/data/ancientports/3092_foundation"], "http://www.wikidata.org/prop/direct/P1584": ["http://pleiades.stoa.org/places/707531"], "http://www.wikidata.org/prop/direct/P17": ["http://www.wikidata.org/entity/Q229"], "http://www.wikidata.org/prop/direct/P1936": ["http://imperium.ahlfeldt.se/places/22726"], "http://www.wikidata.org/prop/direct/P1958": ["https://www.trismegistos.org/place/3665"], "http://www.wikidata.org/prop/direct/P8068": ["https://topostext.org/place/353333PKer"]}, "geometry": {"type": "Point", "coordinates": [33.3233, 35.34383]}}]}