{"type": "FeatureCollection", "id": "http://pleiades.stoa.org/places/315062", "name": "315062", "features": [{"type": "Feature", "id": "http://data.archaeology.link/data/ancientports/4160", "label": "El-Haouaria, near Cap Bon", "properties": {"http://purl.org/dc/elements/1.1/created": ["2023"], "http://purl.org/dc/elements/1.1/creator": ["http://data.archaeology.link/data/spphaefen/arthur_de_graauw"], "http://www.ancientports.com/ont#date_min": ["-330"], "http://www.opengis.net/ont/geosparql#hasGeometry": ["http://data.archaeology.link/data/ancientports/4160_geom"], "http://www.w3.org/1999/02/22-rdf-syntax-ns#type": ["http://www.ancientports.com/ont#Harbour"], "http://www.w3.org/2000/01/rdf-schema#label": ["El-Haouaria, near Cap Bon"], "http://www.w3.org/2002/07/owl#sameAs": ["http://www.wikidata.org/entity/Q849879"], "http://www.wikidata.org/prop/direct/P1584": ["http://pleiades.stoa.org/places/315062"], "http://www.wikidata.org/prop/direct/P17": ["Tunisia"], "http://www.wikidata.org/prop/direct/P1936": ["http://imperium.ahlfeldt.se/places/28141"], "http://www.wikidata.org/prop/direct/P1958": ["https://www.trismegistos.org/place/17688"], "http://www.wikidata.org/prop/direct/P8068": ["https://topostext.org/place/371110LHer"]}, "geometry": {"type": "Point", "coordinates": [10.9958, 37.0596]}}]}