{"type": "FeatureCollection", "id": "http://www.wikidata.org/entity/Q173096", "name": "Euboea", "features": [{"type": "Feature", "id": "http://data.archaeology.link/data/ancientports/1692", "name": "Isle of Eubea, Evia", "dateprops": [], "properties": {"http://purl.org/dc/elements/1.1/creator": ["http://data.archaeology.link/data/spphaefen/arthur_de_graauw"], "http://purl.org/dc/terms/partOf": ["http://data.archaeology.link/data/ancientports/bib_deGrauw_2013_GeoDB"], "http://www.opengis.net/ont/geosparql#hasGeometry": ["http://data.archaeology.link/data/ancientports/1692_geom"], "http://www.w3.org/1999/02/22-rdf-syntax-ns#type": ["http://www.ancientports.com/ont#Harbour"], "http://www.w3.org/2000/01/rdf-schema#label": ["Isle of Eubea, Evia"], "http://www.w3.org/2002/07/owl#sameAs": ["http://www.wikidata.org/entity/Q173096"], "http://www.wikidata.org/prop/direct/P1584": ["http://pleiades.stoa.org/places/540775"], "http://www.wikidata.org/prop/direct/P17": ["http://www.wikidata.org/entity/Q41"], "http://www.wikidata.org/prop/direct/P1936": ["http://imperium.ahlfeldt.se/places/41413"], "http://www.wikidata.org/prop/direct/P1958": ["https://www.trismegistos.org/place/672"], "http://www.wikidata.org/prop/direct/P8068": ["https://topostext.org/place/385239IEub"], "begin": ""}, "geometry": {"type": "Point", "coordinates": [23.76936, 38.57249]}}]}