{"type": "FeatureCollection", "id": "https://www.trismegistos.org/place/61152", "name": "61152", "features": [{"type": "Feature", "id": "http://data.archaeology.link/data/ancientports/593_6", "label": "Roman winery at Pontheziere, near Saint Georges d'Oleron", "dateprops": ["http://purl.org/dc/elements/1.1/created"], "properties": {"http://purl.org/dc/elements/1.1/created": ["2023"], "http://purl.org/dc/elements/1.1/creator": ["http://data.archaeology.link/data/spphaefen/arthur_de_graauw"], "http://www.opengis.net/ont/geosparql#hasGeometry": ["http://data.archaeology.link/data/ancientports/593_6_geom"], "http://www.w3.org/1999/02/22-rdf-syntax-ns#type": ["http://www.ancientports.com/ont#VillaMaritima"], "http://www.w3.org/2000/01/rdf-schema#label": ["Roman winery at Pontheziere, near Saint Georges d'Oleron"], "http://www.w3.org/2002/07/owl#sameAs": ["http://www.wikidata.org/entity/Q292568"], "http://www.w3.org/2004/02/skos/core#note": ["Balmelle (2001)"], "http://www.wikidata.org/prop/direct/P1584": ["http://pleiades.stoa.org/places/138632"], "http://www.wikidata.org/prop/direct/P17": ["France West"], "http://www.wikidata.org/prop/direct/P1936": ["http://dare.ht.lu.se/places/18559"], "http://www.wikidata.org/prop/direct/P1958": ["https://www.trismegistos.org/place/61152"], "http://www.wikidata.org/prop/direct/P8068": ["https://topostext.org/place/459000IUli"]}, "geometry": {"type": "Point", "coordinates": [-1.393, 45.9535]}}]}