{"type": "FeatureCollection", "id": "http://pleiades.stoa.org/places/59857", "name": "59857", "features": [{"type": "Feature", "id": "http://data.archaeology.link/data/ancientports/3852", "label": "Khor Kalmat, near Sokhta Koh", "properties": {"http://purl.org/dc/elements/1.1/created": ["2023"], "http://purl.org/dc/elements/1.1/creator": ["http://data.archaeology.link/data/spphaefen/arthur_de_graauw"], "http://www.opengis.net/ont/geosparql#hasGeometry": ["http://data.archaeology.link/data/ancientports/3852_geom"], "http://www.w3.org/1999/02/22-rdf-syntax-ns#type": ["http://www.ancientports.com/ont#Harbour"], "http://www.w3.org/2000/01/rdf-schema#label": ["Khor Kalmat, near Sokhta Koh"], "http://www.w3.org/2002/07/owl#sameAs": ["http://www.wikidata.org/entity/Q6402306"], "http://www.wikidata.org/prop/direct/P1584": ["http://pleiades.stoa.org/places/59857"], "http://www.wikidata.org/prop/direct/P17": ["Pakistan"]}, "geometry": {"type": "Point", "coordinates": [64.07, 25.41]}}]}