{"type": "FeatureCollection", "id": "https://topostext.org/place/365000USal", "name": "365000USal", "features": [{"type": "Feature", "id": "http://data.archaeology.link/data/ancientports/355_1", "label": "El Torreon, on R Guadalmansa", "dateprops": ["http://purl.org/dc/elements/1.1/created", "http://www.ancientports.com/ont#date_min"], "properties": {"http://purl.org/dc/elements/1.1/created": ["2023"], "http://purl.org/dc/elements/1.1/creator": ["http://data.archaeology.link/data/spphaefen/arthur_de_graauw"], "http://www.ancientports.com/ont#date_min": ["-750"], "http://www.opengis.net/ont/geosparql#hasGeometry": ["http://data.archaeology.link/data/ancientports/355_1_geom"], "http://www.w3.org/1999/02/22-rdf-syntax-ns#type": ["http://www.ancientports.com/ont#Harbour"], "http://www.w3.org/2000/01/rdf-schema#label": ["El Torreon, on R Guadalmansa"], "http://www.wikidata.org/prop/direct/P1584": ["http://pleiades.stoa.org/places/256416"], "http://www.wikidata.org/prop/direct/P17": ["http://www.wikidata.org/entity/Q29"], "http://www.wikidata.org/prop/direct/P1936": ["http://dare.ht.lu.se/places/22425"], "http://www.wikidata.org/prop/direct/P8068": ["https://topostext.org/place/365000USal"]}, "geometry": {"type": "Point", "coordinates": [-5.0625, 36.457]}}]}