{"type": "FeatureCollection", "id": "https://pleiades.stoa.org/places/50755", "name": "50755", "features": [{"type": "Feature", "id": "http://data.archaeology.link/data/ancientports/3866_2", "name": "Lankapattana? on Sri Lanka island", "dateprops": [], "properties": {"http://purl.org/dc/elements/1.1/creator": ["http://data.archaeology.link/data/spphaefen/arthur_de_graauw"], "http://purl.org/dc/terms/partOf": ["http://data.archaeology.link/data/ancientports/bib_deGrauw_2013_GeoDB"], "http://www.opengis.net/ont/geosparql#hasGeometry": ["http://data.archaeology.link/data/ancientports/3866_2_geom"], "http://www.w3.org/1999/02/22-rdf-syntax-ns#type": ["http://www.ancientports.com/ont#Harbour"], "http://www.w3.org/2000/01/rdf-schema#label": ["Lankapattana? on Sri Lanka island"], "http://www.w3.org/2004/02/skos/core#note": ["Gunawardana (2015)"], "http://www.wikidata.org/prop/direct/P1584": ["https://pleiades.stoa.org/places/50755"], "http://www.wikidata.org/prop/direct/P17": ["http://www.wikidata.org/entity/Q854"], "begin": ""}, "geometry": {"type": "Point", "coordinates": [81.395, 8.354]}}]}