{"type": "FeatureCollection", "id": "https://www.trismegistos.org/place/37721", "name": "37721", "features": [{"type": "Feature", "id": "http://data.archaeology.link/data/ancientports/1633", "name": "near Glifadha", "dateprops": ["begin"], "properties": {"http://purl.org/dc/elements/1.1/created": ["2023"], "http://purl.org/dc/elements/1.1/creator": ["http://data.archaeology.link/data/spphaefen/arthur_de_graauw"], "http://www.opengis.net/ont/geosparql#hasGeometry": ["http://data.archaeology.link/data/ancientports/1633_geom"], "http://www.w3.org/1999/02/22-rdf-syntax-ns#type": ["http://www.ancientports.com/ont#Harbour"], "http://www.w3.org/2000/01/rdf-schema#label": ["near Glifadha"], "http://www.w3.org/2002/07/owl#sameAs": ["http://www.wikidata.org/entity/Q13424322"], "http://www.w3.org/2006/time#hasTime": ["http://data.archaeology.link/data/ancientports/1633_foundation"], "http://www.wikidata.org/prop/direct/P1584": ["http://pleiades.stoa.org/places/579855"], "http://www.wikidata.org/prop/direct/P17": ["http://www.wikidata.org/entity/Q41"], "http://www.wikidata.org/prop/direct/P1936": ["http://imperium.ahlfeldt.se/places/22756"], "http://www.wikidata.org/prop/direct/P1958": ["https://www.trismegistos.org/place/37721"], "http://www.wikidata.org/prop/direct/P8068": ["https://topostext.org/place/379238DAix"], "begin": "-3000"}, "geometry": {"type": "Point", "coordinates": [23.7476, 37.8571]}}]}