{"type": "FeatureCollection", "id": "https://topostext.org/place/368-62UHas", "name": "368-62UHas", "features": [{"type": "Feature", "id": "http://data.archaeology.link/data/ancientports/326", "name": "", "dateprops": ["begin"], "properties": {"http://purl.org/dc/elements/1.1/creator": ["http://data.archaeology.link/data/spphaefen/arthur_de_graauw"], "http://purl.org/dc/terms/partOf": ["http://data.archaeology.link/data/ancientports/bib_deGrauw_2013_GeoDB"], "http://www.opengis.net/ont/geosparql#hasGeometry": ["http://data.archaeology.link/data/ancientports/326_geom"], "http://www.w3.org/1999/02/22-rdf-syntax-ns#type": ["http://www.ancientports.com/ont#Quay"], "http://www.w3.org/2000/01/rdf-schema#label": ["Cortijo el Rosario, Mesas de Asta, with a causeway and quay at El Muelle"], "http://www.w3.org/2002/07/owl#sameAs": ["http://www.wikidata.org/entity/Q5709588"], "http://www.w3.org/2004/02/skos/core#note": ["Alonso&Menanteau (2010)", "Caro Bellido (1985)"], "http://www.w3.org/2006/time#hasTime": ["http://data.archaeology.link/data/ancientports/326_foundation"], "http://www.wikidata.org/prop/direct/P1584": ["http://pleiades.stoa.org/places/256193"], "http://www.wikidata.org/prop/direct/P17": ["http://www.wikidata.org/entity/Q29"], "http://www.wikidata.org/prop/direct/P1936": ["http://imperium.ahlfeldt.se/places/25198"], "http://www.wikidata.org/prop/direct/P1958": ["https://www.trismegistos.org/place/25992"], "http://www.wikidata.org/prop/direct/P8068": ["https://topostext.org/place/368-62UHas"], "begin": "-1200"}, "geometry": {"type": "Point", "coordinates": [-6.1547, 36.7893]}}], "numberMatched": 1, "numberReturned": 1, "bbox": [-6.1547, 36.7893, -6.1547, 36.7893], "crs": "http://www.opengis.net/def/crs/EPSG/0/4326"}