{"type": "FeatureCollection", "id": "http://www.wikidata.org/entity/Q3674186", "name": "Q3674186", "features": [{"type": "Feature", "id": "http://data.archaeology.link/data/ancientports/922", "label": "Santa Passera, on left bank of R Tiber, south of Rome", "dateprops": ["http://purl.org/dc/elements/1.1/created", "http://www.ancientports.com/ont#date_min"], "properties": {"http://purl.org/dc/elements/1.1/created": ["2023"], "http://purl.org/dc/elements/1.1/creator": ["http://data.archaeology.link/data/spphaefen/arthur_de_graauw"], "http://purl.org/dc/terms/isReferencedBy": ["https://www2.rgzm.de/navis2/home/frames.htm"], "http://www.ancientports.com/ont#date_min": ["-330"], "http://www.opengis.net/ont/geosparql#hasGeometry": ["http://data.archaeology.link/data/ancientports/922_geom"], "http://www.w3.org/1999/02/22-rdf-syntax-ns#type": ["http://www.ancientports.com/ont#Quay"], "http://www.w3.org/2000/01/rdf-schema#label": ["Santa Passera, on left bank of R Tiber, south of Rome"], "http://www.w3.org/2002/07/owl#sameAs": ["http://www.wikidata.org/entity/Q3674186"], "http://www.wikidata.org/prop/direct/P1584": ["http://pleiades.stoa.org/places/423120"], "http://www.wikidata.org/prop/direct/P17": ["Italy West"], "http://www.wikidata.org/prop/direct/P1936": ["http://imperium.ahlfeldt.se/places/29118"]}, "geometry": {"type": "Point", "coordinates": [12.47144, 41.84739]}}, {"type": "Feature", "id": "http://data.archaeology.link/data/ancientports/923", "label": "Santa Passera, on right bank of R Tiber", "dateprops": ["http://purl.org/dc/elements/1.1/created"], "properties": {"http://purl.org/dc/elements/1.1/created": ["2023"], "http://purl.org/dc/elements/1.1/creator": ["http://data.archaeology.link/data/spphaefen/arthur_de_graauw"], "http://purl.org/dc/terms/isReferencedBy": ["https://www2.rgzm.de/navis2/home/frames.htm"], "http://www.opengis.net/ont/geosparql#hasGeometry": ["http://data.archaeology.link/data/ancientports/923_geom"], "http://www.w3.org/1999/02/22-rdf-syntax-ns#type": ["http://www.ancientports.com/ont#Quay"], "http://www.w3.org/2000/01/rdf-schema#label": ["Santa Passera, on right bank of R Tiber"], "http://www.w3.org/2002/07/owl#sameAs": ["http://www.wikidata.org/entity/Q3674186"], "http://www.wikidata.org/prop/direct/P1584": ["http://pleiades.stoa.org/places/423051"], "http://www.wikidata.org/prop/direct/P17": ["Italy West"]}, "geometry": {"type": "Point", "coordinates": [12.46084, 41.85644]}}]}