{"type": "FeatureCollection", "id": "http://imperium.ahlfeldt.se/places/35436", "name": "35436", "features": [{"type": "Feature", "id": "http://data.archaeology.link/data/ancientports/4107", "name": "Rhizene, near Houmt Souk, on the isle of Djerba", "dateprops": ["begin"], "properties": {"http://purl.org/dc/elements/1.1/created": ["2023"], "http://purl.org/dc/elements/1.1/creator": ["http://data.archaeology.link/data/spphaefen/arthur_de_graauw"], "http://www.opengis.net/ont/geosparql#hasGeometry": ["http://data.archaeology.link/data/ancientports/4107_geom"], "http://www.w3.org/1999/02/22-rdf-syntax-ns#type": ["http://www.ancientports.com/ont#Harbour"], "http://www.w3.org/2000/01/rdf-schema#label": ["Rhizene, near Houmt Souk, on the isle of Djerba"], "http://www.w3.org/2006/time#hasTime": ["http://data.archaeology.link/data/ancientports/4107_foundation"], "http://www.wikidata.org/prop/direct/P1584": ["http://pleiades.stoa.org/places/344400"], "http://www.wikidata.org/prop/direct/P17": ["http://www.wikidata.org/entity/Q948"], "http://www.wikidata.org/prop/direct/P1936": ["http://imperium.ahlfeldt.se/places/35436"], "begin": "-330"}, "geometry": {"type": "Point", "coordinates": [10.92133, 33.88172]}}]}