{"type": "FeatureCollection", "id": "http://www.wikidata.org/entity/Q6624788", "name": "Tel Tanninim", "features": [{"type": "Feature", "id": "http://data.archaeology.link/data/ancientports/3490", "name": "", "dateprops": ["begin"], "properties": {"http://purl.org/dc/elements/1.1/creator": ["http://data.archaeology.link/data/spphaefen/arthur_de_graauw"], "http://purl.org/dc/terms/partOf": ["http://data.archaeology.link/data/ancientports/bib_deGrauw_2013_GeoDB"], "http://www.opengis.net/ont/geosparql#hasGeometry": ["http://data.archaeology.link/data/ancientports/3490_geom"], "http://www.w3.org/1999/02/22-rdf-syntax-ns#type": ["http://www.ancientports.com/ont#Harbour"], "http://www.w3.org/2000/01/rdf-schema#label": ["Tell Taninim, near Tell Mevorach located 2400 m inland at Beit Hanania, on R Taninim"], "http://www.w3.org/2002/07/owl#sameAs": ["http://www.wikidata.org/entity/Q6624788"], "http://www.w3.org/2004/02/skos/core#note": ["Marcus (1998)"], "http://www.w3.org/2006/time#hasTime": ["http://data.archaeology.link/data/ancientports/3490_foundation"], "http://www.wikidata.org/prop/direct/P1584": ["http://pleiades.stoa.org/places/678261"], "http://www.wikidata.org/prop/direct/P17": ["http://www.wikidata.org/entity/Q801"], "http://www.wikidata.org/prop/direct/P1936": ["http://imperium.ahlfeldt.se/places/33353"], "http://www.wikidata.org/prop/direct/P1958": ["https://www.trismegistos.org/place/37424"], "begin": "-2000"}, "geometry": {"type": "Point", "coordinates": [34.9018, 32.5387]}}], "numberMatched": 1, "numberReturned": 1, "bbox": [34.9018, 32.5387, 34.9018, 32.5387], "crs": "http://www.opengis.net/def/crs/EPSG/0/4326"}