{"type": "FeatureCollection", "id": "http://www.wikidata.org/entity/Q72672", "name": "Q72672", "features": [{"type": "Feature", "id": "http://data.archaeology.link/data/ancientports/1006", "label": "Sorrento, Roman villa Agrippa Postumus at Marina Grande", "properties": {"http://purl.org/dc/elements/1.1/created": ["2023"], "http://purl.org/dc/elements/1.1/creator": ["http://data.archaeology.link/data/spphaefen/arthur_de_graauw"], "http://www.ancientports.com/ont#date_min": ["-330"], "http://www.opengis.net/ont/geosparql#hasGeometry": ["http://data.archaeology.link/data/ancientports/1006_geom"], "http://www.w3.org/1999/02/22-rdf-syntax-ns#type": ["http://www.ancientports.com/ont#VillaMaritima", "http://www.ancientports.com/ont#Quay"], "http://www.w3.org/2000/01/rdf-schema#label": ["Sorrento, Roman villa Agrippa Postumus at Marina Grande"], "http://www.w3.org/2002/07/owl#sameAs": ["http://www.wikidata.org/entity/Q72672"], "http://www.w3.org/2004/02/skos/core#note": ["Aucelli (2016)"], "http://www.wikidata.org/prop/direct/P1584": ["http://pleiades.stoa.org/places/433139"], "http://www.wikidata.org/prop/direct/P17": ["Italy West"], "http://www.wikidata.org/prop/direct/P1936": ["http://imperium.ahlfeldt.se/places/16723"], "http://www.wikidata.org/prop/direct/P1958": ["https://www.trismegistos.org/place/14448"], "http://www.wikidata.org/prop/direct/P8068": ["https://topostext.org/place/406144USur"]}, "geometry": {"type": "Point", "coordinates": [14.3698, 40.6279]}}]}