{"type": "FeatureCollection", "id": "https://topostext.org/place/367253XSka", "name": "367253XSka", "features": [{"type": "Feature", "id": "http://data.archaeology.link/data/ancientports/2120_1", "name": "Skarkos, on the isle of Ios", "dateprops": ["begin"], "properties": {"http://purl.org/dc/elements/1.1/creator": ["http://data.archaeology.link/data/spphaefen/arthur_de_graauw"], "http://purl.org/dc/terms/partOf": ["http://data.archaeology.link/data/ancientports/bib_deGrauw_2013_GeoDB"], "http://www.opengis.net/ont/geosparql#hasGeometry": ["http://data.archaeology.link/data/ancientports/2120_1_geom"], "http://www.w3.org/1999/02/22-rdf-syntax-ns#type": ["http://www.ancientports.com/ont#Harbour"], "http://www.w3.org/2000/01/rdf-schema#label": ["Skarkos, on the isle of Ios"], "http://www.w3.org/2002/07/owl#sameAs": ["http://www.wikidata.org/entity/Q1495996"], "http://www.w3.org/2006/time#hasTime": ["http://data.archaeology.link/data/ancientports/2120_1_foundation"], "http://www.wikidata.org/prop/direct/P17": ["http://www.wikidata.org/entity/Q41"], "http://www.wikidata.org/prop/direct/P8068": ["https://topostext.org/place/367253XSka"], "begin": "-3000"}, "geometry": {"type": "Point", "coordinates": [25.2829, 36.7318]}}]}