{"type": "FeatureCollection", "id": "https://topostext.org/place/371253XSte", "name": "371253XSte", "features": [{"type": "Feature", "id": "http://data.archaeology.link/data/ancientports/2102", "name": "", "dateprops": ["begin"], "properties": {"http://purl.org/dc/elements/1.1/creator": ["http://data.archaeology.link/data/spphaefen/arthur_de_graauw"], "http://purl.org/dc/terms/isReferencedBy": ["https://www.naxos.gr/prehistoric-era/?lang=en"], "http://purl.org/dc/terms/partOf": ["http://data.archaeology.link/data/ancientports/bib_deGrauw_2013_GeoDB"], "http://rdfs.org/ns/void#inDataset": ["http://data.archaeology.link/data/ancientports/ap_dataset"], "http://www.opengis.net/ont/geosparql#hasGeometry": ["http://data.archaeology.link/data/ancientports/2102_geom"], "http://www.w3.org/1999/02/22-rdf-syntax-ns#type": ["http://www.ancientports.com/ont#Harbour"], "http://www.w3.org/2000/01/rdf-schema#label": ["Stelida, Mesolithic settlement, on the isle of Naxos, Naksa"], "http://www.w3.org/2002/07/owl#sameAs": ["http://www.wikidata.org/entity/Q2586345"], "http://www.w3.org/2004/02/skos/core#note": ["Carter (2019)"], "http://www.w3.org/2006/time#hasTime": ["http://data.archaeology.link/data/ancientports/2102_foundation"], "http://www.wikidata.org/prop/direct/P17": ["http://www.wikidata.org/entity/Q41"], "http://www.wikidata.org/prop/direct/P8068": ["https://topostext.org/place/371253XSte"], "begin": "-10000"}, "geometry": {"type": "Point", "coordinates": [25.345, 37.0869]}}], "numberMatched": 1, "numberReturned": 1, "bbox": [25.345, 37.0869, 25.345, 37.0869], "crs": "http://www.opengis.net/def/crs/EPSG/0/4326"}