{"type": "FeatureCollection", "id": "http://pleiades.stoa.org/places/462379", "name": "462379", "features": [{"type": "Feature", "id": "http://data.archaeology.link/data/ancientports/1212", "label": "Milazzo", "properties": {"http://purl.org/dc/elements/1.1/created": ["2023"], "http://purl.org/dc/elements/1.1/creator": ["http://data.archaeology.link/data/spphaefen/arthur_de_graauw"], "http://www.ancientports.com/ont#date_min": ["-750"], "http://www.opengis.net/ont/geosparql#hasGeometry": ["http://data.archaeology.link/data/ancientports/1212_geom"], "http://www.w3.org/1999/02/22-rdf-syntax-ns#type": ["http://www.ancientports.com/ont#Harbour"], "http://www.w3.org/2000/01/rdf-schema#label": ["Milazzo"], "http://www.w3.org/2002/07/owl#sameAs": ["http://www.wikidata.org/entity/Q487929"], "http://www.wikidata.org/prop/direct/P1584": ["http://pleiades.stoa.org/places/462379"], "http://www.wikidata.org/prop/direct/P17": ["Italy Sicily"], "http://www.wikidata.org/prop/direct/P1936": ["http://imperium.ahlfeldt.se/places/16877"], "http://www.wikidata.org/prop/direct/P1958": ["https://www.trismegistos.org/place/61073"], "http://www.wikidata.org/prop/direct/P8068": ["https://topostext.org/place/382152PMyl"]}, "geometry": {"type": "Point", "coordinates": [15.2428, 38.2177]}}]}