{"type": "FeatureCollection", "id": "http://www.wikidata.org/entity/Q3038108", "name": "Q3038108", "features": [{"type": "Feature", "id": "http://data.archaeology.link/data/ancientports/1581_2", "label": "Probably Koutsilaris, a former island now connected to mainland, another option was the isle of Lefkada", "dateprops": ["http://purl.org/dc/elements/1.1/created", "http://www.ancientports.com/ont#date_min"], "properties": {"http://purl.org/dc/elements/1.1/created": ["2023"], "http://purl.org/dc/elements/1.1/creator": ["http://data.archaeology.link/data/spphaefen/arthur_de_graauw"], "http://www.ancientports.com/ont#date_min": ["-1200"], "http://www.opengis.net/ont/geosparql#hasGeometry": ["http://data.archaeology.link/data/ancientports/1581_2_geom"], "http://www.w3.org/1999/02/22-rdf-syntax-ns#type": ["http://www.ancientports.com/ont#Harbour"], "http://www.w3.org/2000/01/rdf-schema#label": ["Probably Koutsilaris, a former island now connected to mainland, another option was the isle of Lefkada"], "http://www.w3.org/2002/07/owl#sameAs": ["http://www.wikidata.org/entity/Q3038108"], "http://www.wikidata.org/prop/direct/P1584": ["https://pleiades.stoa.org/places/530845"], "http://www.wikidata.org/prop/direct/P17": ["GR: North-West"], "http://www.wikidata.org/prop/direct/P1936": ["http://dare.ht.lu.se/places/44932"]}, "geometry": {"type": "Point", "coordinates": [21.1514, 38.3216]}}, {"type": "Feature", "id": "http://data.archaeology.link/data/ancientports/1988", "label": "isle of Lefkada", "dateprops": ["http://purl.org/dc/elements/1.1/created", "http://www.ancientports.com/ont#date_min"], "properties": {"http://purl.org/dc/elements/1.1/created": ["2023"], "http://purl.org/dc/elements/1.1/creator": ["http://data.archaeology.link/data/spphaefen/arthur_de_graauw"], "http://www.ancientports.com/ont#date_min": ["-750"], "http://www.opengis.net/ont/geosparql#hasGeometry": ["http://data.archaeology.link/data/ancientports/1988_geom"], "http://www.w3.org/1999/02/22-rdf-syntax-ns#type": ["http://www.ancientports.com/ont#Harbour"], "http://www.w3.org/2000/01/rdf-schema#label": ["isle of Lefkada"], "http://www.w3.org/2002/07/owl#sameAs": ["http://www.wikidata.org/entity/Q3038108"], "http://www.wikidata.org/prop/direct/P1584": ["http://pleiades.stoa.org/places/530975"], "http://www.wikidata.org/prop/direct/P17": ["GR: Ionian Isl."], "http://www.wikidata.org/prop/direct/P1936": ["http://imperium.ahlfeldt.se/places/41196"]}, "geometry": {"type": "Point", "coordinates": [20.64, 38.7]}}]}