{"type": "FeatureCollection", "id": "http://www.wikidata.org/entity/Q272932", "name": "%C3%87ukuri%C3%A7i H%C3%B6y%C3%BCk", "features": [{"type": "Feature", "id": "http://data.archaeology.link/data/ancientports/3170_1", "name": "Cukurici H\u00f6y\u00fck, prehistoric site, near Selcuk", "dateprops": ["begin"], "properties": {"http://purl.org/dc/elements/1.1/creator": ["http://data.archaeology.link/data/spphaefen/arthur_de_graauw"], "http://purl.org/dc/terms/partOf": ["http://data.archaeology.link/data/ancientports/bib_deGrauw_2013_GeoDB"], "http://www.opengis.net/ont/geosparql#hasGeometry": ["http://data.archaeology.link/data/ancientports/3170_1_geom"], "http://www.w3.org/1999/02/22-rdf-syntax-ns#type": ["http://www.ancientports.com/ont#Harbour"], "http://www.w3.org/2000/01/rdf-schema#label": ["Cukurici H\u00f6y\u00fck, prehistoric site, near Selcuk"], "http://www.w3.org/2002/07/owl#sameAs": ["http://www.wikidata.org/entity/Q272932"], "http://www.w3.org/2004/02/skos/core#note": ["Horejs (2017)"], "http://www.w3.org/2006/time#hasTime": ["http://data.archaeology.link/data/ancientports/3170_1_foundation"], "http://www.wikidata.org/prop/direct/P17": ["http://www.wikidata.org/entity/Q43"], "begin": "-7000"}, "geometry": {"type": "Point", "coordinates": [27.35945, 37.92915]}}], "numberMatched": 1, "numberReturned": 1, "bbox": [27.35945, 37.92915, 27.35945, 37.92915], "crs": "http://www.opengis.net/def/crs/OGC/1.3/CRS84"}