{"type": "FeatureCollection", "id": "http://imperium.ahlfeldt.se/places/17226", "name": "17226", "features": [{"type": "Feature", "id": "http://data.archaeology.link/data/ancientports/1314", "label": "Castiglione di Cervia", "dateprops": ["http://purl.org/dc/elements/1.1/created", "http://www.ancientports.com/ont#date_min"], "properties": {"http://purl.org/dc/elements/1.1/created": ["2023"], "http://purl.org/dc/elements/1.1/creator": ["http://data.archaeology.link/data/spphaefen/arthur_de_graauw"], "http://www.ancientports.com/ont#date_min": ["-30"], "http://www.opengis.net/ont/geosparql#hasGeometry": ["http://data.archaeology.link/data/ancientports/1314_geom"], "http://www.w3.org/1999/02/22-rdf-syntax-ns#type": ["http://www.ancientports.com/ont#Harbour"], "http://www.w3.org/2000/01/rdf-schema#label": ["Castiglione di Cervia"], "http://www.wikidata.org/prop/direct/P17": ["Italy Adriatic"], "http://www.wikidata.org/prop/direct/P1936": ["http://imperium.ahlfeldt.se/places/17226"]}, "geometry": {"type": "Point", "coordinates": [12.2633, 44.26035]}}]}