{"type": "FeatureCollection", "id": "https://pleiades.stoa.org/places/40224", "name": "40224", "features": [{"type": "Feature", "id": "http://data.archaeology.link/data/ancientports/3589", "label": "Marsa Umbeila, on wadi Gabatit, Igidid, south of Ras Hadarba", "properties": {"http://purl.org/dc/elements/1.1/created": ["2023"], "http://purl.org/dc/elements/1.1/creator": ["http://data.archaeology.link/data/spphaefen/arthur_de_graauw"], "http://www.opengis.net/ont/geosparql#hasGeometry": ["http://data.archaeology.link/data/ancientports/3589_geom"], "http://www.w3.org/1999/02/22-rdf-syntax-ns#type": ["http://www.ancientports.com/ont#Harbour"], "http://www.w3.org/2000/01/rdf-schema#label": ["Marsa Umbeila, on wadi Gabatit, Igidid, south of Ras Hadarba"], "http://www.wikidata.org/prop/direct/P1584": ["https://pleiades.stoa.org/places/40224"], "http://www.wikidata.org/prop/direct/P17": ["http://www.wikidata.org/entity/Q1049"]}, "geometry": {"type": "Point", "coordinates": [36.864, 21.975]}}]}