{"type": "FeatureCollection", "id": "http://pleiades.stoa.org/places/814698", "name": "814698", "features": [{"type": "Feature", "id": "http://data.archaeology.link/data/ancientports/3694", "label": "al-Khuraybah in Aynunah bay, a road to Petra starts there. Some scholars locate Leuke Kome at al-Wajh, 240 km further south.", "properties": {"http://purl.org/dc/elements/1.1/created": ["2023"], "http://purl.org/dc/elements/1.1/creator": ["http://data.archaeology.link/data/spphaefen/arthur_de_graauw"], "http://www.ancientports.com/ont#date_min": ["-330"], "http://www.opengis.net/ont/geosparql#hasGeometry": ["http://data.archaeology.link/data/ancientports/3694_geom"], "http://www.w3.org/1999/02/22-rdf-syntax-ns#type": ["http://www.ancientports.com/ont#Harbour"], "http://www.w3.org/2000/01/rdf-schema#label": ["al-Khuraybah in Aynunah bay, a road to Petra starts there. Some scholars locate Leuke Kome at al-Wajh, 240 km further south."], "http://www.w3.org/2002/07/owl#sameAs": ["http://www.wikidata.org/entity/Q3237114"], "http://www.w3.org/2004/02/skos/core#note": ["Gawlikowski (2022)", "Ghabban (2011)", "Mayerson (1995)"], "http://www.wikidata.org/prop/direct/P1584": ["http://pleiades.stoa.org/places/814698"], "http://www.wikidata.org/prop/direct/P17": ["Saudi Arabia: Red Sea"], "http://www.wikidata.org/prop/direct/P1936": ["http://imperium.ahlfeldt.se/places/30690"], "http://www.wikidata.org/prop/direct/P1958": ["https://www.trismegistos.org/place/10862"]}, "geometry": {"type": "Point", "coordinates": [35.1831, 28.0867]}}]}