{"type": "FeatureCollection", "id": "https://www.trismegistos.org/place/10608", "name": "10608", "features": [{"type": "Feature", "id": "http://data.archaeology.link/data/ancientports/369", "label": "El Majuelo, Almunecar, large Roman fish processing factory", "properties": {"http://purl.org/dc/elements/1.1/created": ["2023"], "http://purl.org/dc/elements/1.1/creator": ["http://data.archaeology.link/data/spphaefen/arthur_de_graauw"], "http://www.ancientports.com/ont#date_min": ["-750"], "http://www.opengis.net/ont/geosparql#hasGeometry": ["http://data.archaeology.link/data/ancientports/369_geom"], "http://www.w3.org/1999/02/22-rdf-syntax-ns#type": ["http://www.ancientports.com/ont#Harbour"], "http://www.w3.org/2000/01/rdf-schema#label": ["El Majuelo, Almunecar, large Roman fish processing factory"], "http://www.w3.org/2002/07/owl#sameAs": ["http://www.wikidata.org/entity/Q47766735"], "http://www.wikidata.org/prop/direct/P1584": ["http://pleiades.stoa.org/places/266038"], "http://www.wikidata.org/prop/direct/P17": ["Spain South"], "http://www.wikidata.org/prop/direct/P1958": ["https://www.trismegistos.org/place/10608"]}, "geometry": {"type": "Point", "coordinates": [-3.69405, 36.732]}}]}