{"type": "FeatureCollection", "id": "https://www.trismegistos.org/place/8852", "name": "8852", "features": [{"type": "Feature", "id": "http://data.archaeology.link/data/ancientports/3708", "label": "Aqaba", "dateprops": ["http://purl.org/dc/elements/1.1/created"], "properties": {"http://purl.org/dc/elements/1.1/created": ["2023"], "http://purl.org/dc/elements/1.1/creator": ["http://data.archaeology.link/data/spphaefen/arthur_de_graauw"], "http://purl.org/dc/terms/isReferencedBy": ["http://data.archaeology.link/data/ancientports/bib_Glazer_2012_Solomon"], "http://www.opengis.net/ont/geosparql#hasGeometry": ["http://data.archaeology.link/data/ancientports/3708_geom"], "http://www.w3.org/1999/02/22-rdf-syntax-ns#type": ["http://www.ancientports.com/ont#Harbour"], "http://www.w3.org/2000/01/rdf-schema#label": ["Aqaba"], "http://www.w3.org/2002/07/owl#sameAs": ["http://www.wikidata.org/entity/Q180522"], "http://www.w3.org/2004/02/skos/core#note": ["Parker (2014)"], "http://www.w3.org/2006/time#hasTime": ["http://data.archaeology.link/data/ancientports/3708_foundation"], "http://www.wikidata.org/prop/direct/P1584": ["http://pleiades.stoa.org/places/746700"], "http://www.wikidata.org/prop/direct/P17": ["Gulf of Aqaba "], "http://www.wikidata.org/prop/direct/P1936": ["http://imperium.ahlfeldt.se/places/21749"], "http://www.wikidata.org/prop/direct/P1958": ["https://www.trismegistos.org/place/8852"], "http://www.wikidata.org/prop/direct/P8068": ["https://topostext.org/place/295350UAil"]}, "geometry": {"type": "Point", "coordinates": [34.994, 29.537]}}]}