{"type": "FeatureCollection", "id": "http://pleiades.stoa.org/places/226623", "name": "226623", "features": [{"type": "Feature", "id": "http://data.archaeology.link/data/ancientports/2555", "label": "Stanislavskoye, at the mouth of R Dniepr", "properties": {"http://purl.org/dc/elements/1.1/created": ["2023"], "http://purl.org/dc/elements/1.1/creator": ["http://data.archaeology.link/data/spphaefen/arthur_de_graauw"], "http://www.ancientports.com/ont#date_min": ["-330"], "http://www.opengis.net/ont/geosparql#hasGeometry": ["http://data.archaeology.link/data/ancientports/2555_geom"], "http://www.w3.org/1999/02/22-rdf-syntax-ns#type": ["http://www.ancientports.com/ont#Harbour"], "http://www.w3.org/2000/01/rdf-schema#label": ["Stanislavskoye, at the mouth of R Dniepr"], "http://www.wikidata.org/prop/direct/P1584": ["http://pleiades.stoa.org/places/226623"], "http://www.wikidata.org/prop/direct/P17": ["Ukraine Black S."]}, "geometry": {"type": "Point", "coordinates": [32.14782, 46.55604]}}]}