{"type": "FeatureCollection", "id": "http://pleiades.stoa.org/places/157906", "name": "157906", "features": [{"type": "Feature", "id": "http://data.archaeology.link/data/ancientports/708", "label": "Roman villa on the Isle of St Honorat in the isles of Lerins", "dateprops": [], "properties": {"http://purl.org/dc/elements/1.1/created": ["2023"], "http://purl.org/dc/elements/1.1/creator": ["http://data.archaeology.link/data/spphaefen/arthur_de_graauw"], "http://www.opengis.net/ont/geosparql#hasGeometry": ["http://data.archaeology.link/data/ancientports/708_geom"], "http://www.w3.org/1999/02/22-rdf-syntax-ns#type": ["http://www.ancientports.com/ont#VillaMaritima"], "http://www.w3.org/2000/01/rdf-schema#label": ["Roman villa on the Isle of St Honorat in the isles of Lerins"], "http://www.w3.org/2002/07/owl#sameAs": ["http://www.wikidata.org/entity/Q292642"], "http://www.wikidata.org/prop/direct/P1584": ["http://pleiades.stoa.org/places/157906"], "http://www.wikidata.org/prop/direct/P17": ["http://www.wikidata.org/entity/Q142"]}, "geometry": {"type": "Point", "coordinates": [7.04494, 43.5097]}}]}