{"type": "FeatureCollection", "id": "http://www.wikidata.org/entity/Q27029", "name": "Manora, Karachi", "features": [{"type": "Feature", "id": "http://data.archaeology.link/data/ancientports/3859", "name": "Karachi, behind Manora reef", "dateprops": [], "properties": {"http://purl.org/dc/elements/1.1/created": ["2023"], "http://purl.org/dc/elements/1.1/creator": ["http://data.archaeology.link/data/spphaefen/arthur_de_graauw"], "http://purl.org/dc/terms/isReferencedBy": ["http://data.archaeology.link/data/ancientports/bib_Eggermont_1975_Alexander"], "http://www.opengis.net/ont/geosparql#hasGeometry": ["http://data.archaeology.link/data/ancientports/3859_geom"], "http://www.w3.org/1999/02/22-rdf-syntax-ns#type": ["http://www.ancientports.com/ont#Harbour"], "http://www.w3.org/2000/01/rdf-schema#label": ["Karachi, behind Manora reef"], "http://www.w3.org/2002/07/owl#sameAs": ["http://www.wikidata.org/entity/Q27029"], "http://www.wikidata.org/prop/direct/P1584": ["http://pleiades.stoa.org/places/59831"], "http://www.wikidata.org/prop/direct/P17": ["http://www.wikidata.org/entity/Q843"], "begin": ""}, "geometry": {"type": "Point", "coordinates": [66.965, 24.798]}}]}