{"type": "FeatureCollection", "id": "http://www.wikidata.org/entity/Q188547", "name": "Q188547", "features": [{"type": "Feature", "id": "http://data.archaeology.link/data/ancientports/876", "label": "Roman villa at Paduline, Castiglione della Pescaia, on R Bruna", "properties": {"http://purl.org/dc/elements/1.1/created": ["2023"], "http://purl.org/dc/elements/1.1/creator": ["http://data.archaeology.link/data/spphaefen/arthur_de_graauw"], "http://www.opengis.net/ont/geosparql#hasGeometry": ["http://data.archaeology.link/data/ancientports/876_geom"], "http://www.w3.org/1999/02/22-rdf-syntax-ns#type": ["http://www.ancientports.com/ont#Harbour"], "http://www.w3.org/2000/01/rdf-schema#label": ["Roman villa at Paduline, Castiglione della Pescaia, on R Bruna"], "http://www.w3.org/2002/07/owl#sameAs": ["http://www.wikidata.org/entity/Q188547"], "http://www.w3.org/2004/02/skos/core#note": ["Camilli (2005)"], "http://www.wikidata.org/prop/direct/P1584": ["http://pleiades.stoa.org/places/403269"], "http://www.wikidata.org/prop/direct/P17": ["Italy West"], "http://www.wikidata.org/prop/direct/P1936": ["http://imperium.ahlfeldt.se/places/45375"], "http://www.wikidata.org/prop/direct/P1958": ["https://www.trismegistos.org/place/32134"], "http://www.wikidata.org/prop/direct/P8068": ["https://topostext.org/place/429110UVet"]}, "geometry": {"type": "Point", "coordinates": [10.8868, 42.765]}}]}