{"type": "FeatureCollection", "id": "http://pleiades.stoa.org/places/857015", "name": "857015", "features": [{"type": "Feature", "id": "http://data.archaeology.link/data/ancientports/2712", "name": "R Chorokh", "dateprops": [], "properties": {"http://purl.org/dc/elements/1.1/created": ["2023"], "http://purl.org/dc/elements/1.1/creator": ["http://data.archaeology.link/data/spphaefen/arthur_de_graauw"], "http://www.opengis.net/ont/geosparql#hasGeometry": ["http://data.archaeology.link/data/ancientports/2712_geom"], "http://www.w3.org/1999/02/22-rdf-syntax-ns#type": ["http://www.ancientports.com/ont#Harbour"], "http://www.w3.org/2000/01/rdf-schema#label": ["R Chorokh"], "http://www.w3.org/2002/07/owl#sameAs": ["http://www.wikidata.org/entity/Q70970"], "http://www.wikidata.org/prop/direct/P1584": ["http://pleiades.stoa.org/places/857015"], "http://www.wikidata.org/prop/direct/P17": ["http://www.wikidata.org/entity/Q230"], "http://www.wikidata.org/prop/direct/P1958": ["https://www.trismegistos.org/place/61169"], "http://www.wikidata.org/prop/direct/P8068": ["https://topostext.org/place/416416WAka"], "begin": ""}, "geometry": {"type": "Point", "coordinates": [41.56527, 41.60455]}}]}