{"type": "FeatureCollection", "id": "http://www.wikidata.org/entity/Q2554855", "name": "Thrippunithura", "features": [{"type": "Feature", "id": "http://data.archaeology.link/data/ancientports/3864_1", "name": "", "dateprops": [], "properties": {"http://purl.org/dc/elements/1.1/creator": ["http://data.archaeology.link/data/spphaefen/arthur_de_graauw"], "http://purl.org/dc/terms/partOf": ["http://data.archaeology.link/data/ancientports/bib_deGrauw_2013_GeoDB"], "http://rdfs.org/ns/void#inDataset": ["http://data.archaeology.link/data/ancientports/dataset"], "http://www.opengis.net/ont/geosparql#hasGeometry": ["http://data.archaeology.link/data/ancientports/3864_1_geom"], "http://www.w3.org/1999/02/22-rdf-syntax-ns#type": ["http://www.ancientports.com/ont#Harbour"], "http://www.w3.org/2000/01/rdf-schema#label": ["Tripunittura, near Cochin, Kochi"], "http://www.w3.org/2002/07/owl#sameAs": ["http://www.wikidata.org/entity/Q2554855"], "http://www.wikidata.org/prop/direct/P1584": ["https://pleiades.stoa.org/places/50311"], "http://www.wikidata.org/prop/direct/P17": ["http://www.wikidata.org/entity/Q668"], "begin": ""}, "geometry": {"type": "Point", "coordinates": [76.4829, 9.8066]}}], "numberMatched": 1, "numberReturned": 1, "bbox": [76.4829, 9.8066, 76.4829, 9.8066], "crs": "http://www.opengis.net/def/crs/EPSG/0/4326"}