{"type": "FeatureCollection", "id": "https://www.trismegistos.org/place/23247", "name": "23247", "features": [{"type": "Feature", "id": "http://data.archaeology.link/data/ancientports/594", "name": "Roman villa at Pepiron, near Mauzac, and several other villas on the ridge north of R Seudre", "dateprops": ["begin"], "properties": {"http://purl.org/dc/elements/1.1/created": ["2023"], "http://purl.org/dc/elements/1.1/creator": ["http://data.archaeology.link/data/spphaefen/arthur_de_graauw"], "http://purl.org/dc/terms/isReferencedBy": ["http://ym.piel.pagesperso-orange.fr/gallorom.html", "http://socgeo-rochefort.fr/archeologie.php?sub_ref=32"], "http://www.opengis.net/ont/geosparql#hasGeometry": ["http://data.archaeology.link/data/ancientports/594_geom"], "http://www.w3.org/1999/02/22-rdf-syntax-ns#type": ["http://www.ancientports.com/ont#VillaMaritima"], "http://www.w3.org/2000/01/rdf-schema#label": ["Roman villa at Pepiron, near Mauzac, and several other villas on the ridge north of R Seudre"], "http://www.w3.org/2004/02/skos/core#note": ["Tassaux (2010)"], "http://www.w3.org/2006/time#hasTime": ["http://data.archaeology.link/data/ancientports/594_foundation"], "http://www.wikidata.org/prop/direct/P1584": ["http://pleiades.stoa.org/places/140481"], "http://www.wikidata.org/prop/direct/P17": ["http://www.wikidata.org/entity/Q142"], "http://www.wikidata.org/prop/direct/P1936": ["http://imperium.ahlfeldt.se/places/20147"], "http://www.wikidata.org/prop/direct/P1958": ["https://www.trismegistos.org/place/23247"], "begin": "-200"}, "geometry": {"type": "Point", "coordinates": [-1.0631, 45.8049]}}]}