{"type": "FeatureCollection", "id": "http://pleiades.stoa.org/places/216815", "name": "216815", "features": [{"type": "Feature", "id": "http://data.archaeology.link/data/ancientports/2470", "label": "Kranevo, Kraneya, near R Batova", "dateprops": [], "properties": {"http://purl.org/dc/elements/1.1/created": ["2023"], "http://purl.org/dc/elements/1.1/creator": ["http://data.archaeology.link/data/spphaefen/arthur_de_graauw"], "http://www.ancientports.com/ont#date_min": ["-30"], "http://www.opengis.net/ont/geosparql#hasGeometry": ["http://data.archaeology.link/data/ancientports/2470_geom"], "http://www.w3.org/1999/02/22-rdf-syntax-ns#type": ["http://www.ancientports.com/ont#Harbour"], "http://www.w3.org/2000/01/rdf-schema#label": ["Kranevo, Kraneya, near R Batova"], "http://www.w3.org/2004/02/skos/core#note": ["Peev (2020)"], "http://www.wikidata.org/prop/direct/P1584": ["http://pleiades.stoa.org/places/216815"], "http://www.wikidata.org/prop/direct/P17": ["Bulgaria Black S."], "http://www.wikidata.org/prop/direct/P1936": ["http://imperium.ahlfeldt.se/places/27853"], "http://www.wikidata.org/prop/direct/P1958": ["https://www.trismegistos.org/place/36505"]}, "geometry": {"type": "Point", "coordinates": [28.08401, 43.35406]}}]}