{"type": "FeatureCollection", "id": "https://topostext.org/place/375234XMMa", "name": "375234XMMa", "features": [{"type": "Feature", "id": "http://data.archaeology.link/data/ancientports/1872_1", "label": "Megali Magoula, BA settlement", "dateprops": [], "properties": {"http://purl.org/dc/elements/1.1/created": ["2023"], "http://purl.org/dc/elements/1.1/creator": ["http://data.archaeology.link/data/spphaefen/arthur_de_graauw"], "http://www.ancientports.com/ont#date_min": ["-1500"], "http://www.opengis.net/ont/geosparql#hasGeometry": ["http://data.archaeology.link/data/ancientports/1872_1_geom"], "http://www.w3.org/1999/02/22-rdf-syntax-ns#type": ["http://www.ancientports.com/ont#Harbour"], "http://www.w3.org/2000/01/rdf-schema#label": ["Megali Magoula, BA settlement"], "http://www.wikidata.org/prop/direct/P17": ["GR: Pelop"], "http://www.wikidata.org/prop/direct/P8068": ["https://topostext.org/place/375234XMMa"]}, "geometry": {"type": "Point", "coordinates": [23.4232, 37.502]}}]}