{"type": "FeatureCollection", "id": "https://topostext.org/place/389208PAna", "name": "389208PAna", "features": [{"type": "Feature", "id": "http://data.archaeology.link/data/ancientports/1567", "label": "near Nea Kamarina, anchorage for Antonius' fleet at Actium", "dateprops": [], "properties": {"http://purl.org/dc/elements/1.1/created": ["2023"], "http://purl.org/dc/elements/1.1/creator": ["http://data.archaeology.link/data/spphaefen/arthur_de_graauw"], "http://www.opengis.net/ont/geosparql#hasGeometry": ["http://data.archaeology.link/data/ancientports/1567_geom"], "http://www.w3.org/1999/02/22-rdf-syntax-ns#type": ["http://www.ancientports.com/ont#Harbour"], "http://www.w3.org/2000/01/rdf-schema#label": ["near Nea Kamarina, anchorage for Antonius' fleet at Actium"], "http://www.w3.org/2002/07/owl#sameAs": ["http://www.wikidata.org/entity/Q12873561"], "http://www.w3.org/2006/time#hasTime": ["http://data.archaeology.link/data/ancientports/1567_foundation"], "http://www.wikidata.org/prop/direct/P1584": ["http://pleiades.stoa.org/places/530798"], "http://www.wikidata.org/prop/direct/P17": ["GR: North-West"], "http://www.wikidata.org/prop/direct/P1936": ["http://imperium.ahlfeldt.se/places/31521"], "http://www.wikidata.org/prop/direct/P1958": ["https://www.trismegistos.org/place/37624"], "http://www.wikidata.org/prop/direct/P8068": ["https://topostext.org/place/389208PAna"]}, "geometry": {"type": "Point", "coordinates": [20.8435, 38.9209]}}]}