{"type": "FeatureCollection", "id": "http://pleiades.stoa.org/places/344501", "name": "344501", "features": [{"type": "Feature", "id": "http://data.archaeology.link/data/ancientports/4067", "name": "Bu Retma? east of Misrata", "dateprops": [], "properties": {"http://purl.org/dc/elements/1.1/created": ["2023"], "http://purl.org/dc/elements/1.1/creator": ["http://data.archaeology.link/data/spphaefen/arthur_de_graauw"], "http://www.opengis.net/ont/geosparql#hasGeometry": ["http://data.archaeology.link/data/ancientports/4067_geom"], "http://www.w3.org/1999/02/22-rdf-syntax-ns#type": ["http://www.ancientports.com/ont#Harbour"], "http://www.w3.org/2000/01/rdf-schema#label": ["Bu Retma? east of Misrata"], "http://www.wikidata.org/prop/direct/P1584": ["http://pleiades.stoa.org/places/344501"], "http://www.wikidata.org/prop/direct/P17": ["http://www.wikidata.org/entity/Q1016"], "begin": ""}, "geometry": {"type": "Point", "coordinates": [15.45022, 31.78831]}}]}