{"type": "FeatureCollection", "id": "https://www.trismegistos.org/place/17077", "name": "17077", "features": [{"type": "Feature", "id": "http://data.archaeology.link/data/ancientports/4113", "label": "Bou Ghrara, Roman jetty with platform", "dateprops": ["http://purl.org/dc/elements/1.1/created", "http://www.ancientports.com/ont#date_min"], "properties": {"http://purl.org/dc/elements/1.1/created": ["2023"], "http://purl.org/dc/elements/1.1/creator": ["http://data.archaeology.link/data/spphaefen/arthur_de_graauw"], "http://www.ancientports.com/ont#date_min": ["-550"], "http://www.opengis.net/ont/geosparql#hasGeometry": ["http://data.archaeology.link/data/ancientports/4113_geom"], "http://www.w3.org/1999/02/22-rdf-syntax-ns#type": ["http://www.ancientports.com/ont#Quay"], "http://www.w3.org/2000/01/rdf-schema#label": ["Bou Ghrara, Roman jetty with platform"], "http://www.w3.org/2004/02/skos/core#note": ["Stone (2016)"], "http://www.wikidata.org/prop/direct/P1584": ["http://pleiades.stoa.org/places/344380"], "http://www.wikidata.org/prop/direct/P17": ["http://www.wikidata.org/entity/Q948"], "http://www.wikidata.org/prop/direct/P1936": ["http://imperium.ahlfeldt.se/places/21858"], "http://www.wikidata.org/prop/direct/P1958": ["https://www.trismegistos.org/place/17077"]}, "geometry": {"type": "Point", "coordinates": [10.68204, 33.53255]}}]}