{"type": "FeatureCollection", "id": "http://pleiades.stoa.org/places/472095", "name": "472095", "features": [{"type": "Feature", "id": "http://data.archaeology.link/data/ancientports/722", "label": "Lavasina", "dateprops": ["http://purl.org/dc/elements/1.1/created", "http://www.ancientports.com/ont#date_min"], "properties": {"http://purl.org/dc/elements/1.1/created": ["2023"], "http://purl.org/dc/elements/1.1/creator": ["http://data.archaeology.link/data/spphaefen/arthur_de_graauw"], "http://www.ancientports.com/ont#date_min": ["-330"], "http://www.opengis.net/ont/geosparql#hasGeometry": ["http://data.archaeology.link/data/ancientports/722_geom"], "http://www.w3.org/1999/02/22-rdf-syntax-ns#type": ["http://www.ancientports.com/ont#Harbour"], "http://www.w3.org/2000/01/rdf-schema#label": ["Lavasina"], "http://www.w3.org/2004/02/skos/core#note": ["Mattei (2001)"], "http://www.wikidata.org/prop/direct/P1584": ["http://pleiades.stoa.org/places/472095"], "http://www.wikidata.org/prop/direct/P17": ["France Corsica"], "http://www.wikidata.org/prop/direct/P1936": ["http://imperium.ahlfeldt.se/places/32855"]}, "geometry": {"type": "Point", "coordinates": [9.4659, 42.7575]}}]}