{"type": "FeatureCollection", "id": "http://imperium.ahlfeldt.se/places/44414", "name": "44414", "features": [{"type": "Feature", "id": "http://data.archaeology.link/data/ancientports/170_1", "label": "Dunadd, on R Add", "dateprops": ["http://purl.org/dc/elements/1.1/created", "http://www.ancientports.com/ont#date_min"], "properties": {"http://purl.org/dc/elements/1.1/created": ["2023"], "http://purl.org/dc/elements/1.1/creator": ["http://data.archaeology.link/data/spphaefen/arthur_de_graauw"], "http://purl.org/dc/terms/isReferencedBy": ["https://ancientmonuments.uk/124086"], "http://www.ancientports.com/ont#date_min": ["5001"], "http://www.opengis.net/ont/geosparql#hasGeometry": ["http://data.archaeology.link/data/ancientports/170_1_geom"], "http://www.w3.org/1999/02/22-rdf-syntax-ns#type": ["http://www.ancientports.com/ont#Harbour"], "http://www.w3.org/2000/01/rdf-schema#label": ["Dunadd, on R Add"], "http://www.w3.org/2002/07/owl#sameAs": ["http://www.wikidata.org/entity/Q233579"], "http://www.wikidata.org/prop/direct/P17": ["http://www.wikidata.org/entity/Q145"], "http://www.wikidata.org/prop/direct/P1936": ["http://imperium.ahlfeldt.se/places/44414"]}, "geometry": {"type": "Point", "coordinates": [-5.47881, 56.08567]}}]}