{"type": "FeatureCollection", "id": "http://imperium.ahlfeldt.se/places/42560", "name": "42560", "features": [{"type": "Feature", "id": "http://data.archaeology.link/data/ancientports/1101", "label": "Roman villa at Masseria Caronella, near Tarento", "dateprops": [], "properties": {"http://purl.org/dc/elements/1.1/created": ["2023"], "http://purl.org/dc/elements/1.1/creator": ["http://data.archaeology.link/data/spphaefen/arthur_de_graauw"], "http://www.opengis.net/ont/geosparql#hasGeometry": ["http://data.archaeology.link/data/ancientports/1101_geom"], "http://www.w3.org/1999/02/22-rdf-syntax-ns#type": ["http://www.ancientports.com/ont#VillaMaritima"], "http://www.w3.org/2000/01/rdf-schema#label": ["Roman villa at Masseria Caronella, near Tarento"], "http://www.wikidata.org/prop/direct/P17": ["Italy West"], "http://www.wikidata.org/prop/direct/P1936": ["http://imperium.ahlfeldt.se/places/42560"]}, "geometry": {"type": "Point", "coordinates": [17.31499, 40.50047]}}]}