{"type": "FeatureCollection", "id": "https://topostext.org/place/367253XSka", "name": "367253XSka", "features": [{"type": "Feature", "id": "http://data.archaeology.link/data/ancientports/2120_1", "label": "Skarkos, on the isle of Ios", "dateprops": [], "properties": {"http://purl.org/dc/elements/1.1/created": ["2023"], "http://purl.org/dc/elements/1.1/creator": ["http://data.archaeology.link/data/spphaefen/arthur_de_graauw"], "http://www.ancientports.com/ont#date_min": ["-3000"], "http://www.opengis.net/ont/geosparql#hasGeometry": ["http://data.archaeology.link/data/ancientports/2120_1_geom"], "http://www.w3.org/1999/02/22-rdf-syntax-ns#type": ["http://www.ancientports.com/ont#Harbour"], "http://www.w3.org/2000/01/rdf-schema#label": ["Skarkos, on the isle of Ios"], "http://www.w3.org/2002/07/owl#sameAs": ["http://www.wikidata.org/entity/Q1495996"], "http://www.wikidata.org/prop/direct/P17": ["GR: Cyclades Isl."], "http://www.wikidata.org/prop/direct/P8068": ["https://topostext.org/place/367253XSka"]}, "geometry": {"type": "Point", "coordinates": [25.2829, 36.7318]}}]}