{"type": "FeatureCollection", "id": "http://www.wikidata.org/entity/Q12878005", "name": "Thryon", "features": [{"type": "Feature", "id": "http://data.archaeology.link/data/ancientports/1947_1", "name": "Epitalio, at outlet of R Alfeios", "dateprops": ["begin"], "properties": {"http://purl.org/dc/elements/1.1/creator": ["http://data.archaeology.link/data/spphaefen/arthur_de_graauw"], "http://purl.org/dc/terms/partOf": ["http://data.archaeology.link/data/ancientports/bib_deGrauw_2013_GeoDB"], "http://www.opengis.net/ont/geosparql#hasGeometry": ["http://data.archaeology.link/data/ancientports/1947_1_geom"], "http://www.w3.org/1999/02/22-rdf-syntax-ns#type": ["http://www.ancientports.com/ont#Harbour"], "http://www.w3.org/2000/01/rdf-schema#label": ["Epitalio, at outlet of R Alfeios"], "http://www.w3.org/2002/07/owl#sameAs": ["http://www.wikidata.org/entity/Q12878005"], "http://www.w3.org/2004/02/skos/core#note": ["Kraft (2005)"], "http://www.w3.org/2006/time#hasTime": ["http://data.archaeology.link/data/ancientports/1947_1_foundation"], "http://www.wikidata.org/prop/direct/P1584": ["http://pleiades.stoa.org/places/573559"], "http://www.wikidata.org/prop/direct/P17": ["http://www.wikidata.org/entity/Q41"], "http://www.wikidata.org/prop/direct/P1936": ["http://imperium.ahlfeldt.se/places/46271"], "http://www.wikidata.org/prop/direct/P8068": ["https://topostext.org/place/380232UThr"], "begin": "-550"}, "geometry": {"type": "Point", "coordinates": [21.48, 37.64]}}], "numberMatched": 1, "numberReturned": 1, "bbox": [21.48, 37.64, 21.48, 37.64], "crs": "http://www.opengis.net/def/crs/OGC/1.3/CRS84"}