{"type": "FeatureCollection", "id": "http://www.wikidata.org/entity/Q1540236", "name": "Q1540236", "features": [{"type": "Feature", "id": "http://data.archaeology.link/data/ancientports/2969", "label": "Gournia ", "properties": {"http://purl.org/dc/elements/1.1/created": ["2023"], "http://purl.org/dc/elements/1.1/creator": ["http://data.archaeology.link/data/spphaefen/arthur_de_graauw"], "http://www.ancientports.com/ont#date_min": ["-2000"], "http://www.opengis.net/ont/geosparql#hasGeometry": ["http://data.archaeology.link/data/ancientports/2969_geom"], "http://www.w3.org/1999/02/22-rdf-syntax-ns#type": ["http://www.ancientports.com/ont#Harbour"], "http://www.w3.org/2000/01/rdf-schema#label": ["Gournia "], "http://www.w3.org/2002/07/owl#sameAs": ["http://www.wikidata.org/entity/Q1540236"], "http://www.w3.org/2004/02/skos/core#note": ["Watrous (2010)"], "http://www.wikidata.org/prop/direct/P1584": ["http://pleiades.stoa.org/places/771100776"], "http://www.wikidata.org/prop/direct/P17": ["GR: Crete North"]}, "geometry": {"type": "Point", "coordinates": [25.7907, 35.1148]}}]}