{"type": "FeatureCollection", "id": "http://www.wikidata.org/entity/Q57777690", "name": "Q57777690", "features": [{"type": "Feature", "id": "http://data.archaeology.link/data/ancientports/1969", "label": "near Agia Sotira", "dateprops": [], "properties": {"http://purl.org/dc/elements/1.1/created": ["2023"], "http://purl.org/dc/elements/1.1/creator": ["http://data.archaeology.link/data/spphaefen/arthur_de_graauw"], "http://www.ancientports.com/ont#date_min": ["-550"], "http://www.opengis.net/ont/geosparql#hasGeometry": ["http://data.archaeology.link/data/ancientports/1969_geom"], "http://www.w3.org/1999/02/22-rdf-syntax-ns#type": ["http://www.ancientports.com/ont#Harbour"], "http://www.w3.org/2000/01/rdf-schema#label": ["near Agia Sotira"], "http://www.w3.org/2002/07/owl#sameAs": ["http://www.wikidata.org/entity/Q57777690"], "http://www.wikidata.org/prop/direct/P17": ["GR: Pelop"], "http://www.wikidata.org/prop/direct/P1958": ["https://www.trismegistos.org/place/60703"], "http://www.wikidata.org/prop/direct/P8068": ["https://topostext.org/place/380230FOin"]}, "geometry": {"type": "Point", "coordinates": [23.0448, 38.0395]}}]}