{"type": "FeatureCollection", "id": "http://www.wikidata.org/entity/Q687104", "name": "Q687104", "features": [{"type": "Feature", "id": "http://data.archaeology.link/data/ancientports/1597", "label": "Nisis Trizonia", "dateprops": [], "properties": {"http://purl.org/dc/elements/1.1/created": ["2023"], "http://purl.org/dc/elements/1.1/creator": ["http://data.archaeology.link/data/spphaefen/arthur_de_graauw"], "http://www.opengis.net/ont/geosparql#hasGeometry": ["http://data.archaeology.link/data/ancientports/1597_geom"], "http://www.w3.org/1999/02/22-rdf-syntax-ns#type": ["http://www.ancientports.com/ont#Harbour", "http://www.ancientports.com/ont#PotentialHarbour"], "http://www.w3.org/2000/01/rdf-schema#label": ["Nisis Trizonia"], "http://www.w3.org/2002/07/owl#sameAs": ["http://www.wikidata.org/entity/Q687104"], "http://www.wikidata.org/prop/direct/P17": ["http://www.wikidata.org/entity/Q41"], "http://www.wikidata.org/prop/direct/P8068": ["https://topostext.org/place/384221UTri"]}, "geometry": {"type": "Point", "coordinates": [22.0756, 38.36806]}}]}