{"type": "FeatureCollection", "id": "http://www.wikidata.org/entity/Q2082231", "name": "Lake Mariout", "features": [{"type": "Feature", "id": "http://data.archaeology.link/data/ancientports/3938_1", "name": "", "dateprops": ["begin"], "properties": {"http://purl.org/dc/elements/1.1/creator": ["http://data.archaeology.link/data/spphaefen/arthur_de_graauw"], "http://purl.org/dc/terms/isReferencedBy": ["http://data.archaeology.link/data/ancientports/bib_Flaux_2017_Ancient", "https://honorfrostfoundation.org/2022/02/08/el-max-rescue-project-ongoing/"], "http://purl.org/dc/terms/partOf": ["http://data.archaeology.link/data/ancientports/bib_deGrauw_2013_GeoDB"], "http://rdfs.org/ns/void#inDataset": ["http://data.archaeology.link/data/ancientports/ap_dataset"], "http://www.opengis.net/ont/geosparql#hasGeometry": ["http://data.archaeology.link/data/ancientports/3938_1_geom"], "http://www.w3.org/1999/02/22-rdf-syntax-ns#type": ["http://www.ancientports.com/ont#Harbour"], "http://www.w3.org/2000/01/rdf-schema#label": ["Mariout lake-port connected to sea by el-Mexx canal"], "http://www.w3.org/2002/07/owl#sameAs": ["http://www.wikidata.org/entity/Q2082231"], "http://www.w3.org/2006/time#hasTime": ["http://data.archaeology.link/data/ancientports/3938_1_foundation"], "http://www.wikidata.org/prop/direct/P17": ["http://www.wikidata.org/entity/Q79"], "begin": "-30"}, "geometry": {"type": "Point", "coordinates": [29.8526, 31.146]}}, {"type": "Feature", "id": "http://data.archaeology.link/data/ancientports/3938", "name": "", "dateprops": ["begin"], "properties": {"http://purl.org/dc/elements/1.1/creator": ["http://data.archaeology.link/data/spphaefen/arthur_de_graauw"], "http://purl.org/dc/terms/isReferencedBy": ["http://data.archaeology.link/data/ancientports/bib_Flaux_2017_Ancient"], "http://purl.org/dc/terms/partOf": ["http://data.archaeology.link/data/ancientports/bib_deGrauw_2013_GeoDB"], "http://rdfs.org/ns/void#inDataset": ["http://data.archaeology.link/data/ancientports/ap_dataset"], "http://www.opengis.net/ont/geosparql#hasGeometry": ["http://data.archaeology.link/data/ancientports/3938_geom"], "http://www.w3.org/1999/02/22-rdf-syntax-ns#type": ["http://www.ancientports.com/ont#Harbour"], "http://www.w3.org/2000/01/rdf-schema#label": ["Mariout lake-port"], "http://www.w3.org/2002/07/owl#sameAs": ["http://www.wikidata.org/entity/Q2082231"], "http://www.w3.org/2004/02/skos/core#note": ["Rodziewicz (1988)"], "http://www.w3.org/2006/time#hasTime": ["http://data.archaeology.link/data/ancientports/3938_foundation"], "http://www.wikidata.org/prop/direct/P1584": ["http://pleiades.stoa.org/places/727154"], "http://www.wikidata.org/prop/direct/P17": ["http://www.wikidata.org/entity/Q79"], "http://www.wikidata.org/prop/direct/P1936": ["http://imperium.ahlfeldt.se/places/28492"], "http://www.wikidata.org/prop/direct/P1958": ["https://www.trismegistos.org/place/3431"], "http://www.wikidata.org/prop/direct/P8068": ["https://topostext.org/place/311298WMar"], "begin": "-30"}, "geometry": {"type": "Point", "coordinates": [29.90864, 31.17829]}}], "numberMatched": 2, "numberReturned": 2, "bbox": [29.8526, 31.146, 29.90864, 31.17829], "crs": "http://www.opengis.net/def/crs/EPSG/0/4326"}