{"type": "FeatureCollection", "id": "https://www.trismegistos.org/place/494", "name": "494", "features": [{"type": "Feature", "id": "http://data.archaeology.link/data/ancientports/1700", "name": "Liani Ammos, north of Chalkis, on Euripe strait, with submerged BA settlement", "dateprops": ["begin"], "properties": {"http://purl.org/dc/elements/1.1/creator": ["http://data.archaeology.link/data/spphaefen/arthur_de_graauw"], "http://purl.org/dc/terms/isReferencedBy": ["http://splashcos-viewer.eu/", "https://topostext.org/place/385236WEur"], "http://purl.org/dc/terms/partOf": ["http://data.archaeology.link/data/ancientports/bib_deGrauw_2013_GeoDB"], "http://www.opengis.net/ont/geosparql#hasGeometry": ["http://data.archaeology.link/data/ancientports/1700_geom"], "http://www.w3.org/1999/02/22-rdf-syntax-ns#type": ["http://www.ancientports.com/ont#Quay"], "http://www.w3.org/2000/01/rdf-schema#label": ["Liani Ammos, north of Chalkis, on Euripe strait, with submerged BA settlement"], "http://www.w3.org/2002/07/owl#sameAs": ["http://www.wikidata.org/entity/Q200133"], "http://www.w3.org/2006/time#hasTime": ["http://data.archaeology.link/data/ancientports/1700_foundation"], "http://www.wikidata.org/prop/direct/P1584": ["http://pleiades.stoa.org/places/540703"], "http://www.wikidata.org/prop/direct/P17": ["http://www.wikidata.org/entity/Q41"], "http://www.wikidata.org/prop/direct/P1936": ["http://imperium.ahlfeldt.se/places/21971"], "http://www.wikidata.org/prop/direct/P1958": ["https://www.trismegistos.org/place/494"], "http://www.wikidata.org/prop/direct/P8068": ["https://topostext.org/place/385236PCha"], "begin": "-3000"}, "geometry": {"type": "Point", "coordinates": [23.5917, 38.4562]}}, {"type": "Feature", "id": "http://data.archaeology.link/data/ancientports/1701", "name": "Agios Stefanos, south of Chalkis, on Euripe strait", "dateprops": ["begin"], "properties": {"http://purl.org/dc/elements/1.1/creator": ["http://data.archaeology.link/data/spphaefen/arthur_de_graauw"], "http://purl.org/dc/terms/partOf": ["http://data.archaeology.link/data/ancientports/bib_deGrauw_2013_GeoDB"], "http://www.opengis.net/ont/geosparql#hasGeometry": ["http://data.archaeology.link/data/ancientports/1701_geom"], "http://www.w3.org/1999/02/22-rdf-syntax-ns#type": ["http://www.ancientports.com/ont#Quay"], "http://www.w3.org/2000/01/rdf-schema#label": ["Agios Stefanos, south of Chalkis, on Euripe strait"], "http://www.w3.org/2002/07/owl#sameAs": ["http://www.wikidata.org/entity/Q200133"], "http://www.w3.org/2006/time#hasTime": ["http://data.archaeology.link/data/ancientports/1701_foundation"], "http://www.wikidata.org/prop/direct/P1584": ["http://pleiades.stoa.org/places/540703"], "http://www.wikidata.org/prop/direct/P17": ["http://www.wikidata.org/entity/Q41"], "http://www.wikidata.org/prop/direct/P1936": ["http://imperium.ahlfeldt.se/places/21971"], "http://www.wikidata.org/prop/direct/P1958": ["https://www.trismegistos.org/place/494"], "http://www.wikidata.org/prop/direct/P8068": ["https://topostext.org/place/385236PCha"], "begin": "-750"}, "geometry": {"type": "Point", "coordinates": [23.6098, 38.45074]}}], "numberMatched": 2, "numberReturned": 2, "bbox": [23.5917, 38.45074, 23.6098, 38.4562], "crs": "http://www.opengis.net/def/crs/EPSG/0/4326"}