{"type": "FeatureCollection", "id": "http://imperium.ahlfeldt.se/places/34370", "name": "34370", "features": [{"type": "Feature", "id": "http://data.archaeology.link/data/ancientports/2237", "name": "4 Roman forts: Mauragani, Hellinikon, Priounos, Sindouka probably sharing one port, possibly near Sindouka?", "dateprops": ["begin"], "properties": {"http://purl.org/dc/elements/1.1/created": ["2023"], "http://purl.org/dc/elements/1.1/creator": ["http://data.archaeology.link/data/spphaefen/arthur_de_graauw"], "http://www.opengis.net/ont/geosparql#hasGeometry": ["http://data.archaeology.link/data/ancientports/2237_geom"], "http://www.w3.org/1999/02/22-rdf-syntax-ns#type": ["http://www.ancientports.com/ont#Harbour"], "http://www.w3.org/2000/01/rdf-schema#label": ["4 Roman forts: Mauragani, Hellinikon, Priounos, Sindouka probably sharing one port, possibly near Sindouka?"], "http://www.w3.org/2006/time#hasTime": ["http://data.archaeology.link/data/ancientports/2237_foundation"], "http://www.wikidata.org/prop/direct/P1584": ["http://pleiades.stoa.org/places/541101"], "http://www.wikidata.org/prop/direct/P17": ["http://www.wikidata.org/entity/Q41"], "http://www.wikidata.org/prop/direct/P1936": ["http://imperium.ahlfeldt.se/places/34370"], "http://www.wikidata.org/prop/direct/P8068": ["https://topostext.org/place/392236FSin"], "begin": "-550"}, "geometry": {"type": "Point", "coordinates": [23.6159, 39.1987]}}]}