{"type": "FeatureCollection", "id": "http://www.wikidata.org/entity/Q534571", "name": "Marsaskala", "features": [{"type": "Feature", "id": "http://data.archaeology.link/data/ancientports/1225", "name": "Marsaskala ", "dateprops": [], "properties": {"http://purl.org/dc/elements/1.1/creator": ["http://data.archaeology.link/data/spphaefen/arthur_de_graauw"], "http://purl.org/dc/terms/partOf": ["http://data.archaeology.link/data/ancientports/bib_deGrauw_2013_GeoDB"], "http://www.opengis.net/ont/geosparql#hasGeometry": ["http://data.archaeology.link/data/ancientports/1225_geom"], "http://www.w3.org/1999/02/22-rdf-syntax-ns#type": ["http://www.ancientports.com/ont#Harbour"], "http://www.w3.org/2000/01/rdf-schema#label": ["Marsaskala "], "http://www.w3.org/2002/07/owl#sameAs": ["http://www.wikidata.org/entity/Q534571"], "http://www.wikidata.org/prop/direct/P17": ["http://www.wikidata.org/entity/Q233"], "begin": ""}, "geometry": {"type": "Point", "coordinates": [14.57183, 35.86492]}}], "numberMatched": 1, "numberReturned": 1, "bbox": [14.57183, 35.86492, 14.57183, 35.86492], "crs": "http://www.opengis.net/def/crs/EPSG/0/4326"}