{"type": "FeatureCollection", "id": "http://pleiades.stoa.org/places/305062", "name": "305062", "features": [{"type": "Feature", "id": "http://data.archaeology.link/data/ancientports/4218_1", "label": "Roman port at Ziama, on wadi Ziama", "properties": {"http://purl.org/dc/elements/1.1/created": ["2023"], "http://purl.org/dc/elements/1.1/creator": ["http://data.archaeology.link/data/spphaefen/arthur_de_graauw"], "http://www.ancientports.com/ont#date_min": ["-30"], "http://www.opengis.net/ont/geosparql#hasGeometry": ["http://data.archaeology.link/data/ancientports/4218_1_geom"], "http://www.w3.org/1999/02/22-rdf-syntax-ns#type": ["http://www.ancientports.com/ont#Harbour"], "http://www.w3.org/2000/01/rdf-schema#label": ["Roman port at Ziama, on wadi Ziama"], "http://www.w3.org/2002/07/owl#sameAs": ["http://www.wikidata.org/entity/Q3575466"], "http://www.wikidata.org/prop/direct/P1584": ["http://pleiades.stoa.org/places/305062"], "http://www.wikidata.org/prop/direct/P17": ["Algeria"], "http://www.wikidata.org/prop/direct/P1958": ["https://www.trismegistos.org/place/20395"]}, "geometry": {"type": "Point", "coordinates": [5.447, 36.6611]}}]}