{"type": "FeatureCollection", "id": "https://topostext.org/place/366264BTal", "name": "366264BTal", "features": [{"type": "Feature", "id": "http://data.archaeology.link/data/ancientports/2155", "label": "Roman villa & quarry at Tallara, Maltezana, on the isle of Astypalaia, Stampalia ", "dateprops": [], "properties": {"http://purl.org/dc/elements/1.1/created": ["2023"], "http://purl.org/dc/elements/1.1/creator": ["http://data.archaeology.link/data/spphaefen/arthur_de_graauw"], "http://www.opengis.net/ont/geosparql#hasGeometry": ["http://data.archaeology.link/data/ancientports/2155_geom"], "http://www.w3.org/1999/02/22-rdf-syntax-ns#type": ["http://www.ancientports.com/ont#Harbour"], "http://www.w3.org/2000/01/rdf-schema#label": ["Roman villa & quarry at Tallara, Maltezana, on the isle of Astypalaia, Stampalia "], "http://www.w3.org/2006/time#hasTime": ["http://data.archaeology.link/data/ancientports/2155_foundation"], "http://www.wikidata.org/prop/direct/P1584": ["http://pleiades.stoa.org/places/599782"], "http://www.wikidata.org/prop/direct/P17": ["http://www.wikidata.org/entity/Q41"], "http://www.wikidata.org/prop/direct/P1936": ["http://imperium.ahlfeldt.se/places/38041"], "http://www.wikidata.org/prop/direct/P8068": ["https://topostext.org/place/366264BTal"]}, "geometry": {"type": "Point", "coordinates": [26.3873, 36.576]}}]}