{"type": "FeatureCollection", "id": "http://imperium.ahlfeldt.se/places/29238", "name": "29238", "features": [{"type": "Feature", "id": "http://data.archaeology.link/data/ancientports/1275", "name": "Roman villa at Santa Maria di Merino", "dateprops": ["begin"], "properties": {"http://purl.org/dc/elements/1.1/created": ["2023"], "http://purl.org/dc/elements/1.1/creator": ["http://data.archaeology.link/data/spphaefen/arthur_de_graauw"], "http://www.opengis.net/ont/geosparql#hasGeometry": ["http://data.archaeology.link/data/ancientports/1275_geom"], "http://www.w3.org/1999/02/22-rdf-syntax-ns#type": ["http://www.ancientports.com/ont#VillaMaritima"], "http://www.w3.org/2000/01/rdf-schema#label": ["Roman villa at Santa Maria di Merino"], "http://www.w3.org/2006/time#hasTime": ["http://data.archaeology.link/data/ancientports/1275_foundation"], "http://www.wikidata.org/prop/direct/P1584": ["http://pleiades.stoa.org/places/442654"], "http://www.wikidata.org/prop/direct/P17": ["http://www.wikidata.org/entity/Q38"], "http://www.wikidata.org/prop/direct/P1936": ["http://imperium.ahlfeldt.se/places/29238"], "begin": "-30"}, "geometry": {"type": "Point", "coordinates": [16.1114, 41.915]}}]}