{"type": "FeatureCollection", "id": "http://www.wikidata.org/entity/Q194005", "name": "Q194005", "features": [{"type": "Feature", "id": "http://data.archaeology.link/data/ancientports/1125_1", "label": "Porto Megarese, Augusta", "dateprops": [], "properties": {"http://purl.org/dc/elements/1.1/created": ["2023"], "http://purl.org/dc/elements/1.1/creator": ["http://data.archaeology.link/data/spphaefen/arthur_de_graauw"], "http://www.ancientports.com/ont#date_min": ["-330"], "http://www.opengis.net/ont/geosparql#hasGeometry": ["http://data.archaeology.link/data/ancientports/1125_1_geom"], "http://www.w3.org/1999/02/22-rdf-syntax-ns#type": ["http://www.ancientports.com/ont#Harbour"], "http://www.w3.org/2000/01/rdf-schema#label": ["Porto Megarese, Augusta"], "http://www.w3.org/2002/07/owl#sameAs": ["http://www.wikidata.org/entity/Q194005"], "http://www.wikidata.org/prop/direct/P1584": ["http://pleiades.stoa.org/places/462536"], "http://www.wikidata.org/prop/direct/P17": ["Italy Sicily"], "http://www.wikidata.org/prop/direct/P1936": ["http://imperium.ahlfeldt.se/places/42107"]}, "geometry": {"type": "Point", "coordinates": [15.207, 37.234]}}]}