{"type": "FeatureCollection", "id": "https://topostext.org/place/367254XPsa", "name": "367254XPsa", "features": [{"type": "Feature", "id": "http://data.archaeology.link/data/ancientports/2122", "label": "Psathonisi, on the isle of Ios", "dateprops": ["http://purl.org/dc/elements/1.1/created"], "properties": {"http://purl.org/dc/elements/1.1/created": ["2023"], "http://purl.org/dc/elements/1.1/creator": ["http://data.archaeology.link/data/spphaefen/arthur_de_graauw"], "http://www.opengis.net/ont/geosparql#hasGeometry": ["http://data.archaeology.link/data/ancientports/2122_geom"], "http://www.w3.org/1999/02/22-rdf-syntax-ns#type": ["http://www.ancientports.com/ont#Harbour"], "http://www.w3.org/2000/01/rdf-schema#label": ["Psathonisi, on the isle of Ios"], "http://www.w3.org/2002/07/owl#sameAs": ["http://www.wikidata.org/entity/Q48816244"], "http://www.wikidata.org/prop/direct/P17": ["GR: Cyclades Isl."], "http://www.wikidata.org/prop/direct/P8068": ["https://topostext.org/place/367254XPsa"]}, "geometry": {"type": "Point", "coordinates": [25.3644, 36.7494]}}]}