{"type": "FeatureCollection", "id": "http://pleiades.stoa.org/places/814681", "name": "814681", "features": [{"type": "Feature", "id": "http://data.archaeology.link/data/ancientports/3679", "label": "al-Hawra, Haura, al-Duqm?", "dateprops": [], "properties": {"http://purl.org/dc/elements/1.1/created": ["2023"], "http://purl.org/dc/elements/1.1/creator": ["http://data.archaeology.link/data/spphaefen/arthur_de_graauw"], "http://purl.org/dc/terms/isReferencedBy": ["http://data.archaeology.link/data/ancientports/bib_Pedersen_2015_Preliminary"], "http://www.opengis.net/ont/geosparql#hasGeometry": ["http://data.archaeology.link/data/ancientports/3679_geom"], "http://www.w3.org/1999/02/22-rdf-syntax-ns#type": ["http://www.ancientports.com/ont#Harbour"], "http://www.w3.org/2000/01/rdf-schema#label": ["al-Hawra, Haura, al-Duqm?"], "http://www.w3.org/2006/time#hasTime": ["http://data.archaeology.link/data/ancientports/3679_foundation"], "http://www.wikidata.org/prop/direct/P1584": ["http://pleiades.stoa.org/places/814681"], "http://www.wikidata.org/prop/direct/P17": ["http://www.wikidata.org/entity/Q851"], "http://www.wikidata.org/prop/direct/P1936": ["http://imperium.ahlfeldt.se/places/30683"]}, "geometry": {"type": "Point", "coordinates": [37.2559, 25.0724]}}]}