{"type": "FeatureCollection", "id": "http://www.wikidata.org/entity/Q8826", "name": "Palma de Mallorca", "features": [{"type": "Feature", "id": "http://data.archaeology.link/data/ancientports/454", "name": "Palma de Mallorca ", "dateprops": ["begin"], "properties": {"http://purl.org/dc/elements/1.1/creator": ["http://data.archaeology.link/data/spphaefen/arthur_de_graauw"], "http://purl.org/dc/terms/partOf": ["http://data.archaeology.link/data/ancientports/bib_deGrauw_2013_GeoDB"], "http://www.opengis.net/ont/geosparql#hasGeometry": ["http://data.archaeology.link/data/ancientports/454_geom"], "http://www.w3.org/1999/02/22-rdf-syntax-ns#type": ["http://www.ancientports.com/ont#Harbour"], "http://www.w3.org/2000/01/rdf-schema#label": ["Palma de Mallorca "], "http://www.w3.org/2002/07/owl#sameAs": ["http://www.wikidata.org/entity/Q8826"], "http://www.w3.org/2006/time#hasTime": ["http://data.archaeology.link/data/ancientports/454_foundation"], "http://www.wikidata.org/prop/direct/P1584": ["http://pleiades.stoa.org/places/265998"], "http://www.wikidata.org/prop/direct/P17": ["http://www.wikidata.org/entity/Q8828"], "http://www.wikidata.org/prop/direct/P1936": ["http://imperium.ahlfeldt.se/places/24889"], "http://www.wikidata.org/prop/direct/P1958": ["https://www.trismegistos.org/place/27686"], "http://www.wikidata.org/prop/direct/P8068": ["https://topostext.org/place/396026UPal"], "begin": "-122"}, "geometry": {"type": "Point", "coordinates": [2.64505, 39.56152]}}], "numberMatched": 1, "numberReturned": 1, "bbox": [2.64505, 39.56152, 2.64505, 39.56152], "crs": "http://www.opengis.net/def/crs/OGC/1.3/CRS84"}