{"type": "FeatureCollection", "id": "http://pleiades.stoa.org/places/589969", "name": "589969", "features": [{"type": "Feature", "id": "http://data.archaeology.link/data/ancientports/2352", "label": "Palaiokastro, on the isle of Carpathos, Karpathos, Kerpe", "properties": {"http://purl.org/dc/elements/1.1/created": ["2023"], "http://purl.org/dc/elements/1.1/creator": ["http://data.archaeology.link/data/spphaefen/arthur_de_graauw"], "http://www.opengis.net/ont/geosparql#hasGeometry": ["http://data.archaeology.link/data/ancientports/2352_geom"], "http://www.w3.org/1999/02/22-rdf-syntax-ns#type": ["http://www.ancientports.com/ont#Harbour"], "http://www.w3.org/2000/01/rdf-schema#label": ["Palaiokastro, on the isle of Carpathos, Karpathos, Kerpe"], "http://www.wikidata.org/prop/direct/P1584": ["http://pleiades.stoa.org/places/589969"], "http://www.wikidata.org/prop/direct/P17": ["GR: Eastern Isl."]}, "geometry": {"type": "Point", "coordinates": [27.11047, 35.54393]}}]}