{"type": "FeatureCollection", "id": "http://www.wikidata.org/entity/Q275635", "name": "Q275635", "features": [{"type": "Feature", "id": "http://data.archaeology.link/data/ancientports/3615", "label": "Massawa, Ptolemy locates Saba at 50\u2019 of latitude north of Adulis, which could be Massawa at only 20 nautical miles", "properties": {"http://purl.org/dc/elements/1.1/created": ["2023"], "http://purl.org/dc/elements/1.1/creator": ["http://data.archaeology.link/data/spphaefen/arthur_de_graauw"], "http://www.opengis.net/ont/geosparql#hasGeometry": ["http://data.archaeology.link/data/ancientports/3615_geom"], "http://www.w3.org/1999/02/22-rdf-syntax-ns#type": ["http://www.ancientports.com/ont#Harbour"], "http://www.w3.org/2000/01/rdf-schema#label": ["Massawa, Ptolemy locates Saba at 50\u2019 of latitude north of Adulis, which could be Massawa at only 20 nautical miles"], "http://www.w3.org/2002/07/owl#sameAs": ["http://www.wikidata.org/entity/Q275635"], "http://www.wikidata.org/prop/direct/P17": ["Eritrea"], "http://www.wikidata.org/prop/direct/P1958": ["https://www.trismegistos.org/place/4910"]}, "geometry": {"type": "Point", "coordinates": [39.46311, 15.60981]}}]}