{"type": "FeatureCollection", "id": "https://www.trismegistos.org/place/41037", "name": "41037", "features": [{"type": "Feature", "id": "http://data.archaeology.link/data/ancientports/558", "name": "Brest, on R Penfeld", "dateprops": ["begin"], "properties": {"http://purl.org/dc/elements/1.1/creator": ["http://data.archaeology.link/data/spphaefen/arthur_de_graauw"], "http://purl.org/dc/terms/partOf": ["http://data.archaeology.link/data/ancientports/bib_deGrauw_2013_GeoDB"], "http://www.opengis.net/ont/geosparql#hasGeometry": ["http://data.archaeology.link/data/ancientports/558_geom"], "http://www.w3.org/1999/02/22-rdf-syntax-ns#type": ["http://www.ancientports.com/ont#Harbour"], "http://www.w3.org/2000/01/rdf-schema#label": ["Brest, on R Penfeld"], "http://www.w3.org/2002/07/owl#sameAs": ["http://www.wikidata.org/entity/Q12193"], "http://www.w3.org/2004/02/skos/core#note": ["DeFer (1705)"], "http://www.w3.org/2006/time#hasTime": ["http://data.archaeology.link/data/ancientports/558_foundation"], "http://www.wikidata.org/prop/direct/P1584": ["http://pleiades.stoa.org/places/69511"], "http://www.wikidata.org/prop/direct/P17": ["http://www.wikidata.org/entity/Q142"], "http://www.wikidata.org/prop/direct/P1936": ["http://imperium.ahlfeldt.se/places/8055"], "http://www.wikidata.org/prop/direct/P1958": ["https://www.trismegistos.org/place/41037"], "begin": "-330"}, "geometry": {"type": "Point", "coordinates": [-4.495, 48.378]}}], "numberMatched": 1, "numberReturned": 1, "bbox": [-4.495, 48.378, -4.495, 48.378], "crs": "http://www.opengis.net/def/crs/EPSG/0/4326"}