{"type": "FeatureCollection", "id": "http://www.wikidata.org/entity/Q1641335", "name": "Hypog%C3%A4en von Trinitapoli", "features": [{"type": "Feature", "id": "http://data.archaeology.link/data/ancientports/1263_1", "name": "", "dateprops": ["begin"], "properties": {"http://purl.org/dc/elements/1.1/creator": ["http://data.archaeology.link/data/spphaefen/arthur_de_graauw"], "http://purl.org/dc/terms/partOf": ["http://data.archaeology.link/data/ancientports/bib_deGrauw_2013_GeoDB"], "http://www.opengis.net/ont/geosparql#hasGeometry": ["http://data.archaeology.link/data/ancientports/1263_1_geom"], "http://www.w3.org/1999/02/22-rdf-syntax-ns#type": ["http://www.ancientports.com/ont#Harbour"], "http://www.w3.org/2000/01/rdf-schema#label": ["Hypogea of Trinitapoli, Madonna di Loreto church"], "http://www.w3.org/2002/07/owl#sameAs": ["http://www.wikidata.org/entity/Q1641335"], "http://www.w3.org/2006/time#hasTime": ["http://data.archaeology.link/data/ancientports/1263_1_foundation"], "http://www.wikidata.org/prop/direct/P17": ["http://www.wikidata.org/entity/Q38"], "begin": "-1500"}, "geometry": {"type": "Point", "coordinates": [16.0811, 41.3592]}}], "numberMatched": 1, "numberReturned": 1, "bbox": [16.0811, 41.3592, 16.0811, 41.3592], "crs": "http://www.opengis.net/def/crs/EPSG/0/4326"}