{"type": "FeatureCollection", "id": "http://pleiades.stoa.org/places/82300", "name": "82300", "features": [{"type": "Feature", "id": "http://data.archaeology.link/data/ancientports/141_2", "label": "Great Orme Bronze Age copper mine, near Neolithic settlement at Snail Cave", "properties": {"http://purl.org/dc/elements/1.1/created": ["2023"], "http://purl.org/dc/elements/1.1/creator": ["http://data.archaeology.link/data/spphaefen/arthur_de_graauw"], "http://www.ancientports.com/ont#date_min": ["-1500"], "http://www.opengis.net/ont/geosparql#hasGeometry": ["http://data.archaeology.link/data/ancientports/141_2_geom"], "http://www.w3.org/1999/02/22-rdf-syntax-ns#type": ["http://www.ancientports.com/ont#Harbour"], "http://www.w3.org/2000/01/rdf-schema#label": ["Great Orme Bronze Age copper mine, near Neolithic settlement at Snail Cave"], "http://www.w3.org/2002/07/owl#sameAs": ["http://www.wikidata.org/entity/Q3395318"], "http://www.w3.org/2004/02/skos/core#note": ["Williams (2018)"], "http://www.wikidata.org/prop/direct/P1584": ["http://pleiades.stoa.org/places/82300"], "http://www.wikidata.org/prop/direct/P17": ["UK"], "http://www.wikidata.org/prop/direct/P1936": ["http://imperium.ahlfeldt.se/places/40807"]}, "geometry": {"type": "Point", "coordinates": [-3.8472, 53.3303]}}]}