{"type": "FeatureCollection", "id": "https://topostext.org/place/384260XEli", "name": "384260XEli", "features": [{"type": "Feature", "id": "http://data.archaeology.link/data/ancientports/2258", "name": "Elinda, an alternative would be Apothika on the SW coast, on the isle of Chios", "dateprops": ["begin"], "properties": {"http://purl.org/dc/elements/1.1/creator": ["http://data.archaeology.link/data/spphaefen/arthur_de_graauw"], "http://purl.org/dc/terms/partOf": ["http://data.archaeology.link/data/ancientports/bib_deGrauw_2013_GeoDB"], "http://www.opengis.net/ont/geosparql#hasGeometry": ["http://data.archaeology.link/data/ancientports/2258_geom"], "http://www.w3.org/1999/02/22-rdf-syntax-ns#type": ["http://www.ancientports.com/ont#Harbour"], "http://www.w3.org/2000/01/rdf-schema#label": ["Elinda, an alternative would be Apothika on the SW coast, on the isle of Chios"], "http://www.w3.org/2006/time#hasTime": ["http://data.archaeology.link/data/ancientports/2258_foundation"], "http://www.wikidata.org/prop/direct/P1584": ["http://pleiades.stoa.org/places/550527"], "http://www.wikidata.org/prop/direct/P17": ["http://www.wikidata.org/entity/Q41"], "http://www.wikidata.org/prop/direct/P1936": ["http://imperium.ahlfeldt.se/places/29529"], "http://www.wikidata.org/prop/direct/P8068": ["https://topostext.org/place/384260XEli"], "begin": "-550"}, "geometry": {"type": "Point", "coordinates": [25.99, 38.3894]}}], "numberMatched": 1, "numberReturned": 1, "bbox": [25.99, 38.3894, 25.99, 38.3894], "crs": "http://www.opengis.net/def/crs/OGC/1.3/CRS84"}