{"type": "FeatureCollection", "id": "https://topostext.org/place/363293BPaL", "name": "363293BPaL", "features": [{"type": "Feature", "id": "http://data.archaeology.link/data/ancientports/3289", "name": "Tepecik hill, near Gelemis, with ancient lighthouse", "dateprops": ["begin"], "properties": {"http://purl.org/dc/elements/1.1/creator": ["http://data.archaeology.link/data/spphaefen/arthur_de_graauw"], "http://purl.org/dc/terms/isReferencedBy": ["https://topostext.org/place/363293WXan"], "http://purl.org/dc/terms/partOf": ["http://data.archaeology.link/data/ancientports/bib_deGrauw_2013_GeoDB"], "http://www.opengis.net/ont/geosparql#hasGeometry": ["http://data.archaeology.link/data/ancientports/3289_geom"], "http://www.w3.org/1999/02/22-rdf-syntax-ns#type": ["http://www.ancientports.com/ont#Lighthouse", "http://www.ancientports.com/ont#Quay", "http://www.ancientports.com/ont#Warehouse"], "http://www.w3.org/2000/01/rdf-schema#label": ["Tepecik hill, near Gelemis, with ancient lighthouse"], "http://www.w3.org/2002/07/owl#sameAs": ["http://www.wikidata.org/entity/Q233121"], "http://www.w3.org/2004/02/skos/core#note": ["Arnaud (2008)", "D\u00fcndar (2021)"], "http://www.w3.org/2006/time#hasTime": ["http://data.archaeology.link/data/ancientports/3289_foundation"], "http://www.wikidata.org/prop/direct/P1584": ["http://pleiades.stoa.org/places/639042"], "http://www.wikidata.org/prop/direct/P17": ["http://www.wikidata.org/entity/Q43"], "http://www.wikidata.org/prop/direct/P1936": ["http://imperium.ahlfeldt.se/places/21460"], "http://www.wikidata.org/prop/direct/P1958": ["https://www.trismegistos.org/place/1625"], "http://www.wikidata.org/prop/direct/P8068": ["https://topostext.org/place/363293BPaL"], "begin": "-550"}, "geometry": {"type": "Point", "coordinates": [29.315, 36.265]}}], "numberMatched": 1, "numberReturned": 1, "bbox": [29.315, 36.265, 29.315, 36.265], "crs": "http://www.opengis.net/def/crs/OGC/1.3/CRS84"}