{"type": "FeatureCollection", "id": "http://pleiades.stoa.org/places/30275", "name": "30275", "features": [{"type": "Feature", "id": "http://data.archaeology.link/data/ancientports/3842", "label": "Lipar, on Chabahar Pink Lake", "dateprops": [], "properties": {"http://purl.org/dc/elements/1.1/created": ["2023"], "http://purl.org/dc/elements/1.1/creator": ["http://data.archaeology.link/data/spphaefen/arthur_de_graauw"], "http://www.opengis.net/ont/geosparql#hasGeometry": ["http://data.archaeology.link/data/ancientports/3842_geom"], "http://www.w3.org/1999/02/22-rdf-syntax-ns#type": ["http://www.ancientports.com/ont#Harbour"], "http://www.w3.org/2000/01/rdf-schema#label": ["Lipar, on Chabahar Pink Lake"], "http://www.w3.org/2002/07/owl#sameAs": ["http://www.wikidata.org/entity/Q862466"], "http://www.wikidata.org/prop/direct/P1584": ["http://pleiades.stoa.org/places/30275"], "http://www.wikidata.org/prop/direct/P17": ["http://www.wikidata.org/entity/Q794"]}, "geometry": {"type": "Point", "coordinates": [60.83, 25.248]}}]}