{"type": "FeatureCollection", "id": "https://topostext.org/place/400262UIli", "name": "400262UIli", "features": [{"type": "Feature", "id": "http://data.archaeology.link/data/ancientports/2916", "name": "", "dateprops": ["begin"], "properties": {"http://purl.org/dc/elements/1.1/creator": ["http://data.archaeology.link/data/spphaefen/arthur_de_graauw"], "http://purl.org/dc/terms/partOf": ["http://data.archaeology.link/data/ancientports/bib_deGrauw_2013_GeoDB"], "http://rdfs.org/ns/void#inDataset": ["http://data.archaeology.link/data/ancientports/ap_dataset"], "http://www.opengis.net/ont/geosparql#hasGeometry": ["http://data.archaeology.link/data/ancientports/2916_geom"], "http://www.w3.org/1999/02/22-rdf-syntax-ns#type": ["http://www.ancientports.com/ont#Harbour"], "http://www.w3.org/2000/01/rdf-schema#label": ["Hisarlik, near the valleys, now silted up, of R Karamenderes and R Dumrek"], "http://www.w3.org/2002/07/owl#sameAs": ["http://www.wikidata.org/entity/Q22647"], "http://www.w3.org/2004/02/skos/core#note": ["Blum (2014)", "Kraft (2003)", "Zangger (1999)"], "http://www.w3.org/2006/time#hasTime": ["http://data.archaeology.link/data/ancientports/2916_foundation"], "http://www.wikidata.org/prop/direct/P1584": ["http://pleiades.stoa.org/places/550595"], "http://www.wikidata.org/prop/direct/P17": ["http://www.wikidata.org/entity/Q43"], "http://www.wikidata.org/prop/direct/P1936": ["http://imperium.ahlfeldt.se/places/21153"], "http://www.wikidata.org/prop/direct/P1958": ["https://www.trismegistos.org/place/3681"], "http://www.wikidata.org/prop/direct/P8068": ["https://topostext.org/place/400262UIli"], "begin": "-2900"}, "geometry": {"type": "Point", "coordinates": [26.2389, 39.9572]}}], "numberMatched": 1, "numberReturned": 1, "bbox": [26.2389, 39.9572, 26.2389, 39.9572], "crs": "http://www.opengis.net/def/crs/EPSG/0/4326"}