{"type": "FeatureCollection", "id": "http://www.wikidata.org/entity/Q4119042", "name": "Enfeh#Deir el-Natour", "features": [{"type": "Feature", "id": "http://data.archaeology.link/data/ancientports/3441_1", "name": "Deir el-Natour", "dateprops": [], "properties": {"http://purl.org/dc/elements/1.1/creator": ["http://data.archaeology.link/data/spphaefen/arthur_de_graauw"], "http://purl.org/dc/terms/isReferencedBy": ["https://honorfrostfoundation.org/2020/07/29/deir-el-natour-ongoing/"], "http://purl.org/dc/terms/partOf": ["http://data.archaeology.link/data/ancientports/bib_deGrauw_2013_GeoDB"], "http://www.opengis.net/ont/geosparql#hasGeometry": ["http://data.archaeology.link/data/ancientports/3441_1_geom"], "http://www.w3.org/1999/02/22-rdf-syntax-ns#type": ["http://www.ancientports.com/ont#Harbour"], "http://www.w3.org/2000/01/rdf-schema#label": ["Deir el-Natour"], "http://www.w3.org/2002/07/owl#sameAs": ["http://www.wikidata.org/entity/Q4119042"], "http://www.wikidata.org/prop/direct/P17": ["http://www.wikidata.org/entity/Q822"], "begin": ""}, "geometry": {"type": "Point", "coordinates": [35.738, 34.3751]}}, {"type": "Feature", "id": "http://data.archaeology.link/data/ancientports/3442", "name": "slipway at Ras al-Qalaat, Anfeh, Enfe", "dateprops": ["begin"], "properties": {"http://purl.org/dc/elements/1.1/creator": ["http://data.archaeology.link/data/spphaefen/arthur_de_graauw"], "http://purl.org/dc/terms/isReferencedBy": ["https://en.wikipedia.org/wiki/Amarna_letters", "https://honorfrostfoundation.org/2018/01/01/anfeh-lebanon/"], "http://purl.org/dc/terms/partOf": ["http://data.archaeology.link/data/ancientports/bib_deGrauw_2013_GeoDB"], "http://www.opengis.net/ont/geosparql#hasGeometry": ["http://data.archaeology.link/data/ancientports/3442_geom"], "http://www.w3.org/1999/02/22-rdf-syntax-ns#type": ["http://www.ancientports.com/ont#Slipway"], "http://www.w3.org/2000/01/rdf-schema#label": ["slipway at Ras al-Qalaat, Anfeh, Enfe"], "http://www.w3.org/2002/07/owl#sameAs": ["http://www.wikidata.org/entity/Q4119042"], "http://www.w3.org/2004/02/skos/core#note": ["Pfaelzner (2012)"], "http://www.w3.org/2006/time#hasTime": ["http://data.archaeology.link/data/ancientports/3442_foundation"], "http://www.wikidata.org/prop/direct/P17": ["http://www.wikidata.org/entity/Q822"], "begin": "-1500"}, "geometry": {"type": "Point", "coordinates": [35.72918, 34.36088]}}, {"type": "Feature", "id": "http://data.archaeology.link/data/ancientports/3443", "name": "slipway at Ras al-Qalaat, Anfeh, Enfe", "dateprops": [], "properties": {"http://purl.org/dc/elements/1.1/creator": ["http://data.archaeology.link/data/spphaefen/arthur_de_graauw"], "http://purl.org/dc/terms/isReferencedBy": ["https://honorfrostfoundation.org/2018/01/01/anfeh-lebanon/"], "http://purl.org/dc/terms/partOf": ["http://data.archaeology.link/data/ancientports/bib_deGrauw_2013_GeoDB"], "http://www.opengis.net/ont/geosparql#hasGeometry": ["http://data.archaeology.link/data/ancientports/3443_geom"], "http://www.w3.org/1999/02/22-rdf-syntax-ns#type": ["http://www.ancientports.com/ont#Slipway"], "http://www.w3.org/2000/01/rdf-schema#label": ["slipway at Ras al-Qalaat, Anfeh, Enfe"], "http://www.w3.org/2002/07/owl#sameAs": ["http://www.wikidata.org/entity/Q4119042"], "http://www.w3.org/2004/02/skos/core#note": ["Carayon (2012)"], "http://www.wikidata.org/prop/direct/P17": ["http://www.wikidata.org/entity/Q822"], "begin": ""}, "geometry": {"type": "Point", "coordinates": [35.72547, 34.36146]}}], "numberMatched": 3, "numberReturned": 3, "bbox": [35.72547, 34.36088, 35.738, 34.3751], "crs": "http://www.opengis.net/def/crs/EPSG/0/4326"}