{"type": "FeatureCollection", "id": "https://topostext.org/place/513013URut", "name": "513013URut", "features": [{"type": "Feature", "id": "http://data.archaeology.link/data/ancientports/80", "name": "", "dateprops": ["begin"], "properties": {"http://purl.org/dc/elements/1.1/creator": ["http://data.archaeology.link/data/spphaefen/arthur_de_graauw"], "http://purl.org/dc/terms/isReferencedBy": ["https://historicengland.org.uk/listing/the-list/list-entry/1014642"], "http://purl.org/dc/terms/partOf": ["http://data.archaeology.link/data/ancientports/bib_deGrauw_2013_GeoDB"], "http://www.opengis.net/ont/geosparql#hasGeometry": ["http://data.archaeology.link/data/ancientports/80_geom"], "http://www.w3.org/1999/02/22-rdf-syntax-ns#type": ["http://www.ancientports.com/ont#Lighthouse"], "http://www.w3.org/2000/01/rdf-schema#label": ["Roman naval base at Richborough, probable first landing place of Romans in 43 AD"], "http://www.w3.org/2002/07/owl#sameAs": ["http://www.wikidata.org/entity/Q1309736"], "http://www.w3.org/2004/02/skos/core#note": ["Wilmott (2018)"], "http://www.w3.org/2006/time#hasTime": ["http://data.archaeology.link/data/ancientports/80_foundation"], "http://www.wikidata.org/prop/direct/P1584": ["http://pleiades.stoa.org/places/79664"], "http://www.wikidata.org/prop/direct/P17": ["http://www.wikidata.org/entity/Q145"], "http://www.wikidata.org/prop/direct/P1936": ["http://imperium.ahlfeldt.se/places/18911"], "http://www.wikidata.org/prop/direct/P1958": ["https://www.trismegistos.org/place/14825"], "http://www.wikidata.org/prop/direct/P8068": ["https://topostext.org/place/513013URut"], "begin": "3001"}, "geometry": {"type": "Point", "coordinates": [1.33241, 51.29306]}}], "numberMatched": 1, "numberReturned": 1, "bbox": [1.33241, 51.29306, 1.33241, 51.29306], "crs": "http://www.opengis.net/def/crs/EPSG/0/4326"}