{"type": "FeatureCollection", "id": "https://topostext.org/place/375234XMMa", "name": "375234XMMa", "features": [{"type": "Feature", "id": "http://data.archaeology.link/data/ancientports/1872_1", "name": "", "dateprops": ["begin"], "properties": {"http://purl.org/dc/elements/1.1/creator": ["http://data.archaeology.link/data/spphaefen/arthur_de_graauw"], "http://purl.org/dc/terms/partOf": ["http://data.archaeology.link/data/ancientports/bib_deGrauw_2013_GeoDB"], "http://rdfs.org/ns/void#inDataset": ["http://data.archaeology.link/data/ancientports/dataset"], "http://www.opengis.net/ont/geosparql#hasGeometry": ["http://data.archaeology.link/data/ancientports/1872_1_geom"], "http://www.w3.org/1999/02/22-rdf-syntax-ns#type": ["http://www.ancientports.com/ont#Harbour"], "http://www.w3.org/2000/01/rdf-schema#label": ["Megali Magoula, BA settlement"], "http://www.w3.org/2006/time#hasTime": ["http://data.archaeology.link/data/ancientports/1872_1_foundation"], "http://www.wikidata.org/prop/direct/P17": ["http://www.wikidata.org/entity/Q41"], "http://www.wikidata.org/prop/direct/P8068": ["https://topostext.org/place/375234XMMa"], "begin": "-1500"}, "geometry": {"type": "Point", "coordinates": [23.4232, 37.502]}}], "numberMatched": 1, "numberReturned": 1, "bbox": [23.4232, 37.502, 23.4232, 37.502], "crs": "http://www.opengis.net/def/crs/EPSG/0/4326"}