{"type": "FeatureCollection", "id": "https://topostext.org/place/353253XNir", "name": "353253XNir", "features": [{"type": "Feature", "id": "http://data.archaeology.link/data/ancientports/2959", "label": "Niros, Nirou Khani, Haghioi Theodoroi, 2 km east of the temple of Zeus Thenatas ; rock-cut structure visited by several famous authors. I would favour a twin slipway 2 x 5 m wide and 46 m long (see GE picture)", "properties": {"http://purl.org/dc/elements/1.1/created": ["2023"], "http://purl.org/dc/elements/1.1/creator": ["http://data.archaeology.link/data/spphaefen/arthur_de_graauw"], "http://purl.org/dc/terms/isReferencedBy": ["http://www.ancientportsantiques.com/a-few-ports/nirou-khani/"], "http://www.ancientports.com/ont#date_min": ["-1500"], "http://www.opengis.net/ont/geosparql#hasGeometry": ["http://data.archaeology.link/data/ancientports/2959_geom"], "http://www.w3.org/1999/02/22-rdf-syntax-ns#type": ["http://www.ancientports.com/ont#Slipway", "http://www.ancientports.com/ont#VillaMaritima"], "http://www.w3.org/2000/01/rdf-schema#label": ["Niros, Nirou Khani, Haghioi Theodoroi, 2 km east of the temple of Zeus Thenatas ; rock-cut structure visited by several famous authors. I would favour a twin slipway 2 x 5 m wide and 46 m long (see GE picture)"], "http://www.w3.org/2004/02/skos/core#note": ["Google Earth picture (15/3/2011)", "Loizou (2016)"], "http://www.wikidata.org/prop/direct/P17": ["GR: Crete North"], "http://www.wikidata.org/prop/direct/P8068": ["https://topostext.org/place/353253XNir"]}, "geometry": {"type": "Point", "coordinates": [25.24323, 35.33373]}}]}