{"type": "FeatureCollection", "id": "http://imperium.ahlfeldt.se/places/23381", "name": "23381", "features": [{"type": "Feature", "id": "http://data.archaeology.link/data/ancientports/3021", "label": "Agios Kyriakos, 2 km west of Sougia", "dateprops": [], "properties": {"http://purl.org/dc/elements/1.1/created": ["2023"], "http://purl.org/dc/elements/1.1/creator": ["http://data.archaeology.link/data/spphaefen/arthur_de_graauw"], "http://www.ancientports.com/ont#date_min": ["-330"], "http://www.opengis.net/ont/geosparql#hasGeometry": ["http://data.archaeology.link/data/ancientports/3021_geom"], "http://www.w3.org/1999/02/22-rdf-syntax-ns#type": ["http://www.ancientports.com/ont#Harbour"], "http://www.w3.org/2000/01/rdf-schema#label": ["Agios Kyriakos, 2 km west of Sougia"], "http://www.w3.org/2002/07/owl#sameAs": ["http://www.wikidata.org/entity/Q266558"], "http://www.w3.org/2004/02/skos/core#note": ["Uggeri (2003)"], "http://www.wikidata.org/prop/direct/P1584": ["http://pleiades.stoa.org/places/589914"], "http://www.wikidata.org/prop/direct/P17": ["GR: Crete South"], "http://www.wikidata.org/prop/direct/P1936": ["http://imperium.ahlfeldt.se/places/23381"], "http://www.wikidata.org/prop/direct/P1958": ["https://www.trismegistos.org/place/33255"], "http://www.wikidata.org/prop/direct/P8068": ["https://topostext.org/place/352238ULis"]}, "geometry": {"type": "Point", "coordinates": [23.785, 35.244]}}]}