{"type": "FeatureCollection", "id": "http://pleiades.stoa.org/places/256391", "name": "256391", "features": [{"type": "Feature", "id": "http://data.archaeology.link/data/ancientports/297", "name": "Quinta do Marim, Quelfes, near Olhao", "dateprops": ["begin"], "properties": {"http://purl.org/dc/elements/1.1/creator": ["http://data.archaeology.link/data/spphaefen/arthur_de_graauw"], "http://purl.org/dc/terms/partOf": ["http://data.archaeology.link/data/ancientports/bib_deGrauw_2013_GeoDB"], "http://www.opengis.net/ont/geosparql#hasGeometry": ["http://data.archaeology.link/data/ancientports/297_geom"], "http://www.w3.org/1999/02/22-rdf-syntax-ns#type": ["http://www.ancientports.com/ont#Harbour"], "http://www.w3.org/2000/01/rdf-schema#label": ["Quinta do Marim, Quelfes, near Olhao"], "http://www.w3.org/2004/02/skos/core#note": ["Rodrigues (2004)"], "http://www.w3.org/2006/time#hasTime": ["http://data.archaeology.link/data/ancientports/297_foundation"], "http://www.wikidata.org/prop/direct/P1584": ["http://pleiades.stoa.org/places/256391"], "http://www.wikidata.org/prop/direct/P17": ["http://www.wikidata.org/entity/Q45"], "http://www.wikidata.org/prop/direct/P1936": ["http://imperium.ahlfeldt.se/places/22463"], "begin": "-30"}, "geometry": {"type": "Point", "coordinates": [-7.81212, 37.03345]}}]}