{"type": "FeatureCollection", "id": "http://pleiades.stoa.org/places/295331", "name": "295331", "features": [{"type": "Feature", "id": "http://data.archaeology.link/data/ancientports/4230", "label": "Cape Matifou, Tametfoust near Bordj el-Bahri, La Perouse", "properties": {"http://purl.org/dc/elements/1.1/created": ["2023"], "http://purl.org/dc/elements/1.1/creator": ["http://data.archaeology.link/data/spphaefen/arthur_de_graauw"], "http://www.ancientports.com/ont#date_min": ["-330"], "http://www.opengis.net/ont/geosparql#hasGeometry": ["http://data.archaeology.link/data/ancientports/4230_geom"], "http://www.w3.org/1999/02/22-rdf-syntax-ns#type": ["http://www.ancientports.com/ont#Harbour"], "http://www.w3.org/2000/01/rdf-schema#label": ["Cape Matifou, Tametfoust near Bordj el-Bahri, La Perouse"], "http://www.w3.org/2002/07/owl#sameAs": ["http://www.wikidata.org/entity/Q3514786"], "http://www.wikidata.org/prop/direct/P1584": ["http://pleiades.stoa.org/places/295331"], "http://www.wikidata.org/prop/direct/P17": ["Algeria"], "http://www.wikidata.org/prop/direct/P1936": ["http://imperium.ahlfeldt.se/places/22130"], "http://www.wikidata.org/prop/direct/P1958": ["https://www.trismegistos.org/place/20464"]}, "geometry": {"type": "Point", "coordinates": [3.23209, 36.80461]}}]}