{"type": "FeatureCollection", "id": "https://www.trismegistos.org/place/34245", "name": "34245", "features": [{"type": "Feature", "id": "http://data.archaeology.link/data/ancientports/3386", "label": "3 names for one single place, according to Arnaud, near Cape Karatas Fener Burnu", "dateprops": [], "properties": {"http://purl.org/dc/elements/1.1/created": ["2023"], "http://purl.org/dc/elements/1.1/creator": ["http://data.archaeology.link/data/spphaefen/arthur_de_graauw"], "http://purl.org/dc/terms/isReferencedBy": ["https://en.wikipedia.org/wiki/Mallus_(Cilicia)"], "http://www.opengis.net/ont/geosparql#hasGeometry": ["http://data.archaeology.link/data/ancientports/3386_geom"], "http://www.w3.org/1999/02/22-rdf-syntax-ns#type": ["http://www.ancientports.com/ont#Quay"], "http://www.w3.org/2000/01/rdf-schema#label": ["3 names for one single place, according to Arnaud, near Cape Karatas Fener Burnu"], "http://www.w3.org/2002/07/owl#sameAs": ["http://www.wikidata.org/entity/Q1057961"], "http://www.w3.org/2004/02/skos/core#note": ["Arnaud (2016)", "Arnaud (2020)"], "http://www.w3.org/2006/time#hasTime": ["http://data.archaeology.link/data/ancientports/3386_foundation"], "http://www.wikidata.org/prop/direct/P1584": ["http://pleiades.stoa.org/places/648701"], "http://www.wikidata.org/prop/direct/P17": ["TR: South"], "http://www.wikidata.org/prop/direct/P1936": ["http://imperium.ahlfeldt.se/places/21250"], "http://www.wikidata.org/prop/direct/P1958": ["https://www.trismegistos.org/place/34245"], "http://www.wikidata.org/prop/direct/P8068": ["https://topostext.org/place/365353UMag"]}, "geometry": {"type": "Point", "coordinates": [35.3374, 36.5427]}}]}