{"type": "FeatureCollection", "id": "http://imperium.ahlfeldt.se/places/32338", "name": "32338", "features": [{"type": "Feature", "id": "http://data.archaeology.link/data/ancientports/3864", "label": "Pattanam, near R Periyar", "dateprops": [], "properties": {"http://purl.org/dc/elements/1.1/created": ["2023"], "http://purl.org/dc/elements/1.1/creator": ["http://data.archaeology.link/data/spphaefen/arthur_de_graauw"], "http://purl.org/dc/terms/isReferencedBy": ["https://timesofindia.indiatimes.com/city/kochi/kerala-sphinx-seal-ring-recovered-from-pattanam/articleshow/78227316.cms", "https://www.newindianexpress.com/cities/kochi/2020/sep/25/new-excavations-unravelpattanams-global-trade-past-2201449.html"], "http://www.ancientports.com/ont#date_min": ["-30"], "http://www.opengis.net/ont/geosparql#hasGeometry": ["http://data.archaeology.link/data/ancientports/3864_geom"], "http://www.w3.org/1999/02/22-rdf-syntax-ns#type": ["http://www.ancientports.com/ont#Quay"], "http://www.w3.org/2000/01/rdf-schema#label": ["Pattanam, near R Periyar"], "http://www.w3.org/2002/07/owl#sameAs": ["http://www.wikidata.org/entity/Q2974112"], "http://www.w3.org/2004/02/skos/core#note": ["Dalayan (2018)"], "http://www.wikidata.org/prop/direct/P1584": ["https://pleiades.stoa.org/places/50146"], "http://www.wikidata.org/prop/direct/P17": ["http://www.wikidata.org/entity/Q668"], "http://www.wikidata.org/prop/direct/P1936": ["http://imperium.ahlfeldt.se/places/32338"], "http://www.wikidata.org/prop/direct/P1958": ["https://www.trismegistos.org/place/9229"], "http://www.wikidata.org/prop/direct/P8068": ["https://topostext.org/place/102762UPat"]}, "geometry": {"type": "Point", "coordinates": [76.2093, 10.1568]}}]}