{"type": "FeatureCollection", "id": "http://www.wikidata.org/entity/Q6593", "name": "Vannes", "features": [{"type": "Feature", "id": "http://data.archaeology.link/data/ancientports/580", "name": "Porte Saint Patern, Vannes, capital city of the Venetes", "dateprops": [], "properties": {"http://purl.org/dc/elements/1.1/created": ["2023"], "http://purl.org/dc/elements/1.1/creator": ["http://data.archaeology.link/data/spphaefen/arthur_de_graauw"], "http://www.opengis.net/ont/geosparql#hasGeometry": ["http://data.archaeology.link/data/ancientports/580_geom"], "http://www.w3.org/1999/02/22-rdf-syntax-ns#type": ["http://www.ancientports.com/ont#Harbour"], "http://www.w3.org/2000/01/rdf-schema#label": ["Porte Saint Patern, Vannes, capital city of the Venetes"], "http://www.w3.org/2002/07/owl#sameAs": ["http://www.wikidata.org/entity/Q6593"], "http://www.wikidata.org/prop/direct/P1584": ["http://pleiades.stoa.org/places/138323"], "http://www.wikidata.org/prop/direct/P17": ["http://www.wikidata.org/entity/Q142"], "http://www.wikidata.org/prop/direct/P1936": ["http://imperium.ahlfeldt.se/places/126"], "http://www.wikidata.org/prop/direct/P1958": ["https://www.trismegistos.org/place/23836"], "http://www.wikidata.org/prop/direct/P8068": ["https://topostext.org/place/477-28UVen"], "begin": ""}, "geometry": {"type": "Point", "coordinates": [-2.76225, 47.62647]}}]}