{"type": "FeatureCollection", "id": "http://pleiades.stoa.org/places/589824", "name": "589824", "features": [{"type": "Feature", "id": "http://data.archaeology.link/data/ancientports/2980", "name": "Itanos beach", "dateprops": ["begin"], "properties": {"http://purl.org/dc/elements/1.1/created": ["2023"], "http://purl.org/dc/elements/1.1/creator": ["http://data.archaeology.link/data/spphaefen/arthur_de_graauw"], "http://www.opengis.net/ont/geosparql#hasGeometry": ["http://data.archaeology.link/data/ancientports/2980_geom"], "http://www.w3.org/1999/02/22-rdf-syntax-ns#type": ["http://www.ancientports.com/ont#Harbour"], "http://www.w3.org/2000/01/rdf-schema#label": ["Itanos beach"], "http://www.w3.org/2002/07/owl#sameAs": ["http://www.wikidata.org/entity/Q6093995"], "http://www.w3.org/2006/time#hasTime": ["http://data.archaeology.link/data/ancientports/2980_foundation"], "http://www.wikidata.org/prop/direct/P1584": ["http://pleiades.stoa.org/places/589824"], "http://www.wikidata.org/prop/direct/P17": ["http://www.wikidata.org/entity/Q41"], "http://www.wikidata.org/prop/direct/P1936": ["http://imperium.ahlfeldt.se/places/22688"], "http://www.wikidata.org/prop/direct/P1958": ["https://www.trismegistos.org/place/933"], "http://www.wikidata.org/prop/direct/P8068": ["https://topostext.org/place/353263PIta"], "begin": "-750"}, "geometry": {"type": "Point", "coordinates": [26.2633, 35.2624]}}]}