{"type": "FeatureCollection", "id": "https://www.trismegistos.org/place/22117", "name": "22117", "features": [{"type": "Feature", "id": "http://data.archaeology.link/data/ancientports/770", "label": "Punta di Chia, near Domus de Maria", "dateprops": [], "properties": {"http://purl.org/dc/elements/1.1/created": ["2023"], "http://purl.org/dc/elements/1.1/creator": ["http://data.archaeology.link/data/spphaefen/arthur_de_graauw"], "http://www.opengis.net/ont/geosparql#hasGeometry": ["http://data.archaeology.link/data/ancientports/770_geom"], "http://www.w3.org/1999/02/22-rdf-syntax-ns#type": ["http://www.ancientports.com/ont#Harbour"], "http://www.w3.org/2000/01/rdf-schema#label": ["Punta di Chia, near Domus de Maria"], "http://www.w3.org/2002/07/owl#sameAs": ["http://www.wikidata.org/entity/Q2904892"], "http://www.w3.org/2004/02/skos/core#note": ["Auriemma (2009)"], "http://www.w3.org/2006/time#hasTime": ["http://data.archaeology.link/data/ancientports/770_foundation"], "http://www.wikidata.org/prop/direct/P1584": ["http://pleiades.stoa.org/places/471894"], "http://www.wikidata.org/prop/direct/P17": ["Italy Sardinia"], "http://www.wikidata.org/prop/direct/P1936": ["http://imperium.ahlfeldt.se/places/36274"], "http://www.wikidata.org/prop/direct/P1958": ["https://www.trismegistos.org/place/22117"], "http://www.wikidata.org/prop/direct/P8068": ["https://topostext.org/place/389089UBit"]}, "geometry": {"type": "Point", "coordinates": [8.8849, 38.8956]}}]}