{"type": "FeatureCollection", "id": "http://www.wikidata.org/entity/Q3469627", "name": "Salapia", "features": [{"type": "Feature", "id": "http://data.archaeology.link/data/ancientports/1265", "name": "near Trinitapoli", "dateprops": ["begin"], "properties": {"http://purl.org/dc/elements/1.1/creator": ["http://data.archaeology.link/data/spphaefen/arthur_de_graauw"], "http://purl.org/dc/terms/partOf": ["http://data.archaeology.link/data/ancientports/bib_deGrauw_2013_GeoDB"], "http://www.opengis.net/ont/geosparql#hasGeometry": ["http://data.archaeology.link/data/ancientports/1265_geom"], "http://www.w3.org/1999/02/22-rdf-syntax-ns#type": ["http://www.ancientports.com/ont#Harbour"], "http://www.w3.org/2000/01/rdf-schema#label": ["near Trinitapoli"], "http://www.w3.org/2002/07/owl#sameAs": ["http://www.wikidata.org/entity/Q3469627"], "http://www.w3.org/2006/time#hasTime": ["http://data.archaeology.link/data/ancientports/1265_foundation"], "http://www.wikidata.org/prop/direct/P1584": ["http://pleiades.stoa.org/places/442759"], "http://www.wikidata.org/prop/direct/P17": ["http://www.wikidata.org/entity/Q38"], "http://www.wikidata.org/prop/direct/P1936": ["http://imperium.ahlfeldt.se/places/23207"], "http://www.wikidata.org/prop/direct/P1958": ["https://www.trismegistos.org/place/14287"], "http://www.wikidata.org/prop/direct/P8068": ["https://topostext.org/place/414160UElp"], "begin": "-30"}, "geometry": {"type": "Point", "coordinates": [15.9965, 41.3993]}}]}