{"type": "FeatureCollection", "id": "http://pleiades.stoa.org/places/216984", "name": "216984", "features": [{"type": "Feature", "id": "http://data.archaeology.link/data/ancientports/2464", "label": "Shkorpilovtsi, at the outlet of R Kamchia ", "properties": {"http://purl.org/dc/elements/1.1/created": ["2023"], "http://purl.org/dc/elements/1.1/creator": ["http://data.archaeology.link/data/spphaefen/arthur_de_graauw"], "http://www.ancientports.com/ont#date_min": ["3001"], "http://www.opengis.net/ont/geosparql#hasGeometry": ["http://data.archaeology.link/data/ancientports/2464_geom"], "http://www.w3.org/1999/02/22-rdf-syntax-ns#type": ["http://www.ancientports.com/ont#Harbour"], "http://www.w3.org/2000/01/rdf-schema#label": ["Shkorpilovtsi, at the outlet of R Kamchia "], "http://www.w3.org/2002/07/owl#sameAs": ["http://www.wikidata.org/entity/Q2655385"], "http://www.wikidata.org/prop/direct/P1584": ["http://pleiades.stoa.org/places/216984"], "http://www.wikidata.org/prop/direct/P17": ["Bulgaria Black S."]}, "geometry": {"type": "Point", "coordinates": [27.9045, 42.9644]}}]}