{"type": "FeatureCollection", "id": "https://pleiades.stoa.org/places/668180", "name": "668180", "features": [{"type": "Feature", "id": "http://data.archaeology.link/data/ancientports/3451_1", "label": "R Nahr Ibrahim, Abraham", "dateprops": [], "properties": {"http://purl.org/dc/elements/1.1/created": ["2023"], "http://purl.org/dc/elements/1.1/creator": ["http://data.archaeology.link/data/spphaefen/arthur_de_graauw"], "http://www.opengis.net/ont/geosparql#hasGeometry": ["http://data.archaeology.link/data/ancientports/3451_1_geom"], "http://www.w3.org/1999/02/22-rdf-syntax-ns#type": ["http://www.ancientports.com/ont#Harbour"], "http://www.w3.org/2000/01/rdf-schema#label": ["R Nahr Ibrahim, Abraham"], "http://www.w3.org/2002/07/owl#sameAs": ["http://www.wikidata.org/entity/Q2399602"], "http://www.wikidata.org/prop/direct/P1584": ["https://pleiades.stoa.org/places/668180"], "http://www.wikidata.org/prop/direct/P17": ["http://www.wikidata.org/entity/Q822"], "http://www.wikidata.org/prop/direct/P1958": ["https://www.trismegistos.org/place/61450"], "http://www.wikidata.org/prop/direct/P8068": ["https://topostext.org/place/340356WAdo"]}, "geometry": {"type": "Point", "coordinates": [35.641, 34.0618]}}]}