{"type": "FeatureCollection", "id": "http://pleiades.stoa.org/places/256295", "name": "256295", "features": [{"type": "Feature", "id": "http://data.archaeology.link/data/ancientports/342", "label": "near Conil de la Frontera", "properties": {"http://purl.org/dc/elements/1.1/created": ["2023"], "http://purl.org/dc/elements/1.1/creator": ["http://data.archaeology.link/data/spphaefen/arthur_de_graauw"], "http://www.ancientports.com/ont#date_min": ["-30"], "http://www.opengis.net/ont/geosparql#hasGeometry": ["http://data.archaeology.link/data/ancientports/342_geom"], "http://www.w3.org/1999/02/22-rdf-syntax-ns#type": ["http://www.ancientports.com/ont#Harbour"], "http://www.w3.org/2000/01/rdf-schema#label": ["near Conil de la Frontera"], "http://www.wikidata.org/prop/direct/P1584": ["http://pleiades.stoa.org/places/256295"], "http://www.wikidata.org/prop/direct/P17": ["Spain South"]}, "geometry": {"type": "Point", "coordinates": [-6.11272, 36.27654]}}]}