{"type": "FeatureCollection", "id": "http://imperium.ahlfeldt.se/places/11957", "name": "11957", "features": [{"type": "Feature", "id": "http://data.archaeology.link/data/ancientports/587", "label": "Rez\u00e9, Reze, Chapelle Saint-Lupien, near Trentemoux", "properties": {"http://purl.org/dc/elements/1.1/created": ["2023"], "http://purl.org/dc/elements/1.1/creator": ["http://data.archaeology.link/data/spphaefen/arthur_de_graauw"], "http://www.ancientports.com/ont#date_min": ["-30"], "http://www.opengis.net/ont/geosparql#hasGeometry": ["http://data.archaeology.link/data/ancientports/587_geom"], "http://www.w3.org/1999/02/22-rdf-syntax-ns#type": ["http://www.ancientports.com/ont#Harbour"], "http://www.w3.org/2000/01/rdf-schema#label": ["Rez\u00e9, Reze, Chapelle Saint-Lupien, near Trentemoux"], "http://www.w3.org/2002/07/owl#sameAs": ["http://www.wikidata.org/entity/Q326453"], "http://www.w3.org/2004/02/skos/core#note": ["Arthuis (2010)"], "http://www.wikidata.org/prop/direct/P1584": ["http://pleiades.stoa.org/places/138533"], "http://www.wikidata.org/prop/direct/P17": ["France West"], "http://www.wikidata.org/prop/direct/P1936": ["http://imperium.ahlfeldt.se/places/11957"], "http://www.wikidata.org/prop/direct/P1958": ["https://www.trismegistos.org/place/14251"], "http://www.wikidata.org/prop/direct/P8068": ["https://topostext.org/place/472000UXRa"]}, "geometry": {"type": "Point", "coordinates": [-1.566, 47.1922]}}]}