{"type": "FeatureCollection", "id": "http://imperium.ahlfeldt.se/places/43409", "name": "43409", "features": [{"type": "Feature", "id": "http://data.archaeology.link/data/ancientports/3183", "name": "near Karina", "dateprops": ["begin"], "properties": {"http://purl.org/dc/elements/1.1/creator": ["http://data.archaeology.link/data/spphaefen/arthur_de_graauw"], "http://purl.org/dc/terms/partOf": ["http://data.archaeology.link/data/ancientports/bib_deGrauw_2013_GeoDB"], "http://www.opengis.net/ont/geosparql#hasGeometry": ["http://data.archaeology.link/data/ancientports/3183_geom"], "http://www.w3.org/1999/02/22-rdf-syntax-ns#type": ["http://www.ancientports.com/ont#Harbour"], "http://www.w3.org/2000/01/rdf-schema#label": ["near Karina"], "http://www.w3.org/2002/07/owl#sameAs": ["http://www.wikidata.org/entity/Q17631108"], "http://www.w3.org/2004/02/skos/core#note": ["Lohmann (2006)"], "http://www.w3.org/2006/time#hasTime": ["http://data.archaeology.link/data/ancientports/3183_foundation"], "http://www.wikidata.org/prop/direct/P1584": ["http://pleiades.stoa.org/places/599970"], "http://www.wikidata.org/prop/direct/P17": ["http://www.wikidata.org/entity/Q43"], "http://www.wikidata.org/prop/direct/P1936": ["http://imperium.ahlfeldt.se/places/43409"], "http://www.wikidata.org/prop/direct/P1958": ["https://www.trismegistos.org/place/3627"], "http://www.wikidata.org/prop/direct/P8068": ["https://topostext.org/place/376272UThe"], "begin": "-750"}, "geometry": {"type": "Point", "coordinates": [27.1438, 37.6343]}}]}