{"type": "FeatureCollection", "id": "http://www.wikidata.org/entity/Q2010377", "name": "Myrtos Pyrgos", "features": [{"type": "Feature", "id": "http://data.archaeology.link/data/ancientports/2991_2", "name": "", "dateprops": ["begin"], "properties": {"http://purl.org/dc/elements/1.1/creator": ["http://data.archaeology.link/data/spphaefen/arthur_de_graauw"], "http://purl.org/dc/terms/partOf": ["http://data.archaeology.link/data/ancientports/bib_deGrauw_2013_GeoDB"], "http://rdfs.org/ns/void#inDataset": ["http://data.archaeology.link/data/ancientports/dataset"], "http://www.opengis.net/ont/geosparql#hasGeometry": ["http://data.archaeology.link/data/ancientports/2991_2_geom"], "http://www.w3.org/1999/02/22-rdf-syntax-ns#type": ["http://www.ancientports.com/ont#Harbour"], "http://www.w3.org/2000/01/rdf-schema#label": ["Pyrgos, near Myrtos"], "http://www.w3.org/2002/07/owl#sameAs": ["http://www.wikidata.org/entity/Q2010377"], "http://www.w3.org/2006/time#hasTime": ["http://data.archaeology.link/data/ancientports/2991_2_foundation"], "http://www.wikidata.org/prop/direct/P1584": ["http://pleiades.stoa.org/places/589949"], "http://www.wikidata.org/prop/direct/P17": ["http://www.wikidata.org/entity/Q41"], "http://www.wikidata.org/prop/direct/P1936": ["http://imperium.ahlfeldt.se/places/28824"], "http://www.wikidata.org/prop/direct/P1958": ["https://www.trismegistos.org/place/34075"], "http://www.wikidata.org/prop/direct/P8068": ["https://topostext.org/place/350256XMyr"], "begin": "-2000"}, "geometry": {"type": "Point", "coordinates": [25.5907, 35.0069]}}], "numberMatched": 1, "numberReturned": 1, "bbox": [25.5907, 35.0069, 25.5907, 35.0069], "crs": "http://www.opengis.net/def/crs/EPSG/0/4326"}