{"type": "FeatureCollection", "id": "http://www.wikidata.org/entity/Q114", "name": "Kenya", "features": [{"type": "Feature", "id": "http://data.archaeology.link/data/ancientports/3715", "name": "Lamu archipelago, with Manda, Pate & Lamu islands", "dateprops": [], "properties": {"http://purl.org/dc/elements/1.1/creator": ["http://data.archaeology.link/data/spphaefen/arthur_de_graauw"], "http://purl.org/dc/terms/isReferencedBy": ["http://data.archaeology.link/data/ancientports/bib_Priestman_2013_Quantitative"], "http://purl.org/dc/terms/partOf": ["http://data.archaeology.link/data/ancientports/bib_deGrauw_2013_GeoDB"], "http://www.opengis.net/ont/geosparql#hasGeometry": ["http://data.archaeology.link/data/ancientports/3715_geom"], "http://www.w3.org/1999/02/22-rdf-syntax-ns#type": ["http://www.ancientports.com/ont#Harbour"], "http://www.w3.org/2000/01/rdf-schema#label": ["Lamu archipelago, with Manda, Pate & Lamu islands"], "http://www.w3.org/2002/07/owl#sameAs": ["http://www.wikidata.org/entity/Q618573"], "http://www.wikidata.org/prop/direct/P1584": ["http://pleiades.stoa.org/places/39410"], "http://www.wikidata.org/prop/direct/P17": ["http://www.wikidata.org/entity/Q114"], "begin": ""}, "geometry": {"type": "Point", "coordinates": [40.967, -2.227]}}], "numberMatched": 1, "numberReturned": 1, "bbox": [40.967, -2.227, 40.967, -2.227], "crs": "http://www.opengis.net/def/crs/OGC/1.3/CRS84"}