{"type": "FeatureCollection", "id": "http://imperium.ahlfeldt.se/places/29739", "name": "29739", "features": [{"type": "Feature", "id": "http://data.archaeology.link/data/ancientports/4191_2", "label": "on the SE bank of the Lake of Bizerte", "dateprops": [], "properties": {"http://purl.org/dc/elements/1.1/created": ["2023"], "http://purl.org/dc/elements/1.1/creator": ["http://data.archaeology.link/data/spphaefen/arthur_de_graauw"], "http://www.ancientports.com/ont#date_min": ["-330"], "http://www.opengis.net/ont/geosparql#hasGeometry": ["http://data.archaeology.link/data/ancientports/4191_2_geom"], "http://www.w3.org/1999/02/22-rdf-syntax-ns#type": ["http://www.ancientports.com/ont#Harbour"], "http://www.w3.org/2000/01/rdf-schema#label": ["on the SE bank of the Lake of Bizerte"], "http://www.wikidata.org/prop/direct/P1584": ["http://pleiades.stoa.org/places/208942468"], "http://www.wikidata.org/prop/direct/P17": ["http://www.wikidata.org/entity/Q948"], "http://www.wikidata.org/prop/direct/P1936": ["http://imperium.ahlfeldt.se/places/29739"]}, "geometry": {"type": "Point", "coordinates": [9.85871, 37.12491]}}]}