{"type": "FeatureCollection", "id": "https://topostext.org/place/453370UKep", "name": "453370UKep", "features": [{"type": "Feature", "id": "http://data.archaeology.link/data/ancientports/2663", "name": "near Sennoy", "dateprops": ["begin"], "properties": {"http://purl.org/dc/elements/1.1/creator": ["http://data.archaeology.link/data/spphaefen/arthur_de_graauw"], "http://purl.org/dc/terms/isReferencedBy": ["http://data.archaeology.link/data/ancientports/bib_Hojte_2005_Archaeological"], "http://purl.org/dc/terms/partOf": ["http://data.archaeology.link/data/ancientports/bib_deGrauw_2013_GeoDB"], "http://www.opengis.net/ont/geosparql#hasGeometry": ["http://data.archaeology.link/data/ancientports/2663_geom"], "http://www.w3.org/1999/02/22-rdf-syntax-ns#type": ["http://www.ancientports.com/ont#Harbour"], "http://www.w3.org/2000/01/rdf-schema#label": ["near Sennoy"], "http://www.w3.org/2002/07/owl#sameAs": ["http://www.wikidata.org/entity/Q3555347"], "http://www.w3.org/2006/time#hasTime": ["http://data.archaeology.link/data/ancientports/2663_foundation"], "http://www.wikidata.org/prop/direct/P1584": ["http://pleiades.stoa.org/places/854695"], "http://www.wikidata.org/prop/direct/P17": ["http://www.wikidata.org/entity/Q159"], "http://www.wikidata.org/prop/direct/P1936": ["http://imperium.ahlfeldt.se/places/22017"], "http://www.wikidata.org/prop/direct/P1958": ["https://www.trismegistos.org/place/38269"], "http://www.wikidata.org/prop/direct/P8068": ["https://topostext.org/place/453370UKep"], "begin": "-750"}, "geometry": {"type": "Point", "coordinates": [36.98262, 45.29498]}}], "numberMatched": 1, "numberReturned": 1, "bbox": [36.98262, 45.29498, 36.98262, 45.29498], "crs": "http://www.opengis.net/def/crs/EPSG/0/4326"}