{"type": "FeatureCollection", "id": "https://topostext.org/place/467319UOlb", "name": "467319UOlb", "features": [{"type": "Feature", "id": "http://data.archaeology.link/data/ancientports/2550", "label": "Parutino, Parutyne, on R Bug Liman, Roman naval base, now submerged at ca. 150 m from the shore", "dateprops": [], "properties": {"http://purl.org/dc/elements/1.1/created": ["2023"], "http://purl.org/dc/elements/1.1/creator": ["http://data.archaeology.link/data/spphaefen/arthur_de_graauw"], "http://www.opengis.net/ont/geosparql#hasGeometry": ["http://data.archaeology.link/data/ancientports/2550_geom"], "http://www.w3.org/1999/02/22-rdf-syntax-ns#type": ["http://www.ancientports.com/ont#Warehouse"], "http://www.w3.org/2000/01/rdf-schema#label": ["Parutino, Parutyne, on R Bug Liman, Roman naval base, now submerged at ca. 150 m from the shore"], "http://www.w3.org/2002/07/owl#sameAs": ["http://www.wikidata.org/entity/Q360404"], "http://www.w3.org/2004/02/skos/core#note": ["Hojte (2005)", "Kozlovskaya (2017)"], "http://www.w3.org/2006/time#hasTime": ["http://data.archaeology.link/data/ancientports/2550_foundation"], "http://www.wikidata.org/prop/direct/P1584": ["http://pleiades.stoa.org/places/226546"], "http://www.wikidata.org/prop/direct/P17": ["Ukraine Black S."], "http://www.wikidata.org/prop/direct/P1936": ["http://imperium.ahlfeldt.se/places/22004"], "http://www.wikidata.org/prop/direct/P1958": ["https://www.trismegistos.org/place/451"], "http://www.wikidata.org/prop/direct/P8068": ["https://topostext.org/place/467319UOlb"]}, "geometry": {"type": "Point", "coordinates": [31.9091, 46.693]}}]}