{"type": "FeatureCollection", "id": "http://imperium.ahlfeldt.se/places/30328", "name": "30328", "features": [{"type": "Feature", "id": "http://data.archaeology.link/data/ancientports/3389", "label": "Sirintilimin Cintlik, near Bebeli at the ancient outlet of R Ceyhan", "dateprops": [], "properties": {"http://purl.org/dc/elements/1.1/created": ["2023"], "http://purl.org/dc/elements/1.1/creator": ["http://data.archaeology.link/data/spphaefen/arthur_de_graauw"], "http://www.opengis.net/ont/geosparql#hasGeometry": ["http://data.archaeology.link/data/ancientports/3389_geom"], "http://www.w3.org/1999/02/22-rdf-syntax-ns#type": ["http://www.ancientports.com/ont#Harbour"], "http://www.w3.org/2000/01/rdf-schema#label": ["Sirintilimin Cintlik, near Bebeli at the ancient outlet of R Ceyhan"], "http://www.w3.org/2002/07/owl#sameAs": ["http://www.wikidata.org/entity/Q1057961"], "http://www.w3.org/2004/02/skos/core#note": ["Arnaud (2016)"], "http://www.w3.org/2006/time#hasTime": ["http://data.archaeology.link/data/ancientports/3389_foundation"], "http://www.wikidata.org/prop/direct/P1584": ["http://pleiades.stoa.org/places/648774"], "http://www.wikidata.org/prop/direct/P17": ["http://www.wikidata.org/entity/Q43"], "http://www.wikidata.org/prop/direct/P1936": ["http://imperium.ahlfeldt.se/places/30328"]}, "geometry": {"type": "Point", "coordinates": [35.482, 36.6429]}}]}