{"type": "FeatureCollection", "id": "https://topostext.org/place/369349UTar", "name": "369349UTar", "features": [{"type": "Feature", "id": "http://data.archaeology.link/data/ancientports/3381", "label": "G\u00f6zl\u00fckule, Tarsus, on R Tarsus, with Karabucak swamps south of it", "properties": {"http://purl.org/dc/elements/1.1/created": ["2023"], "http://purl.org/dc/elements/1.1/creator": ["http://data.archaeology.link/data/spphaefen/arthur_de_graauw"], "http://www.ancientports.com/ont#date_min": ["-8000"], "http://www.opengis.net/ont/geosparql#hasGeometry": ["http://data.archaeology.link/data/ancientports/3381_geom"], "http://www.w3.org/1999/02/22-rdf-syntax-ns#type": ["http://www.ancientports.com/ont#Harbour"], "http://www.w3.org/2000/01/rdf-schema#label": ["G\u00f6zl\u00fckule, Tarsus, on R Tarsus, with Karabucak swamps south of it"], "http://www.w3.org/2004/02/skos/core#note": ["Seton-Williams (1954)"], "http://www.wikidata.org/prop/direct/P1584": ["http://pleiades.stoa.org/places/648789"], "http://www.wikidata.org/prop/direct/P17": ["TR: South"], "http://www.wikidata.org/prop/direct/P1936": ["http://imperium.ahlfeldt.se/places/21245"], "http://www.wikidata.org/prop/direct/P1958": ["https://www.trismegistos.org/place/2269"], "http://www.wikidata.org/prop/direct/P8068": ["https://topostext.org/place/369349UTar"]}, "geometry": {"type": "Point", "coordinates": [34.87119, 36.88895]}}]}