{"type": "FeatureCollection", "id": "http://www.wikidata.org/entity/Q516353", "name": "Peyriac-de-Mer", "features": [{"type": "Feature", "id": "http://data.archaeology.link/data/ancientports/620", "name": "Oppidum at Castel-Illet, Moulin, near Peyriac de Mer, on Etang de Bages-Sigean", "dateprops": [], "properties": {"http://purl.org/dc/elements/1.1/created": ["2023"], "http://purl.org/dc/elements/1.1/creator": ["http://data.archaeology.link/data/spphaefen/arthur_de_graauw"], "http://www.opengis.net/ont/geosparql#hasGeometry": ["http://data.archaeology.link/data/ancientports/620_geom"], "http://www.w3.org/1999/02/22-rdf-syntax-ns#type": ["http://www.ancientports.com/ont#Harbour"], "http://www.w3.org/2000/01/rdf-schema#label": ["Oppidum at Castel-Illet, Moulin, near Peyriac de Mer, on Etang de Bages-Sigean"], "http://www.w3.org/2002/07/owl#sameAs": ["http://www.wikidata.org/entity/Q516353"], "http://www.w3.org/2004/02/skos/core#note": ["Bats (1992)"], "http://www.wikidata.org/prop/direct/P17": ["http://www.wikidata.org/entity/Q142"], "http://www.wikidata.org/prop/direct/P1936": ["http://imperium.ahlfeldt.se/places/14179"], "begin": ""}, "geometry": {"type": "Point", "coordinates": [2.9802, 43.09436]}}]}