{"type": "FeatureCollection", "id": "http://pleiades.stoa.org/places/471895", "name": "471895", "features": [{"type": "Feature", "id": "http://data.archaeology.link/data/ancientports/791", "label": "Bosa Marina, at outlet of R Temo", "properties": {"http://purl.org/dc/elements/1.1/created": ["2023"], "http://purl.org/dc/elements/1.1/creator": ["http://data.archaeology.link/data/spphaefen/arthur_de_graauw"], "http://www.ancientports.com/ont#date_min": ["-330"], "http://www.opengis.net/ont/geosparql#hasGeometry": ["http://data.archaeology.link/data/ancientports/791_geom"], "http://www.w3.org/1999/02/22-rdf-syntax-ns#type": ["http://www.ancientports.com/ont#Harbour"], "http://www.w3.org/2000/01/rdf-schema#label": ["Bosa Marina, at outlet of R Temo"], "http://www.wikidata.org/prop/direct/P1584": ["http://pleiades.stoa.org/places/471895"], "http://www.wikidata.org/prop/direct/P17": ["Italy Sardinia"], "http://www.wikidata.org/prop/direct/P1936": ["http://imperium.ahlfeldt.se/places/30259"], "http://www.wikidata.org/prop/direct/P1958": ["https://www.trismegistos.org/place/22102"]}, "geometry": {"type": "Point", "coordinates": [8.46942, 40.28454]}}]}