{"type": "FeatureCollection", "id": "http://imperium.ahlfeldt.se/places/15970", "name": "15970", "features": [{"type": "Feature", "id": "http://data.archaeology.link/data/ancientports/1302", "label": "Numana", "dateprops": [], "properties": {"http://purl.org/dc/elements/1.1/created": ["2023"], "http://purl.org/dc/elements/1.1/creator": ["http://data.archaeology.link/data/spphaefen/arthur_de_graauw"], "http://purl.org/dc/terms/isReferencedBy": ["https://mapcarta.com/W256091396"], "http://www.ancientports.com/ont#date_min": ["-750"], "http://www.opengis.net/ont/geosparql#hasGeometry": ["http://data.archaeology.link/data/ancientports/1302_geom"], "http://www.w3.org/1999/02/22-rdf-syntax-ns#type": ["http://www.ancientports.com/ont#Harbour"], "http://www.w3.org/2000/01/rdf-schema#label": ["Numana"], "http://www.w3.org/2002/07/owl#sameAs": ["http://www.wikidata.org/entity/Q124456"], "http://www.wikidata.org/prop/direct/P1584": ["http://pleiades.stoa.org/places/413228"], "http://www.wikidata.org/prop/direct/P17": ["Italy Adriatic"], "http://www.wikidata.org/prop/direct/P1936": ["http://imperium.ahlfeldt.se/places/15970"], "http://www.wikidata.org/prop/direct/P1958": ["https://www.trismegistos.org/place/32679"], "http://www.wikidata.org/prop/direct/P8068": ["https://topostext.org/place/435136UNum"]}, "geometry": {"type": "Point", "coordinates": [13.6282, 43.50729]}}]}