{"type": "FeatureCollection", "id": "http://www.wikidata.org/entity/Q485329", "name": "Ferrol", "features": [{"type": "Feature", "id": "http://data.archaeology.link/data/ancientports/197", "name": "El Ferrol (Mela's description fits best to El Ferrol)", "dateprops": [], "properties": {"http://purl.org/dc/elements/1.1/creator": ["http://data.archaeology.link/data/spphaefen/arthur_de_graauw"], "http://purl.org/dc/terms/partOf": ["http://data.archaeology.link/data/ancientports/bib_deGrauw_2013_GeoDB"], "http://www.opengis.net/ont/geosparql#hasGeometry": ["http://data.archaeology.link/data/ancientports/197_geom"], "http://www.w3.org/1999/02/22-rdf-syntax-ns#type": ["http://www.ancientports.com/ont#Harbour"], "http://www.w3.org/2000/01/rdf-schema#label": ["El Ferrol (Mela's description fits best to El Ferrol)"], "http://www.w3.org/2002/07/owl#sameAs": ["http://www.wikidata.org/entity/Q485329"], "http://www.wikidata.org/prop/direct/P17": ["http://www.wikidata.org/entity/Q29"], "begin": ""}, "geometry": {"type": "Point", "coordinates": [-8.25508, 43.47677]}}, {"type": "Feature", "id": "http://data.archaeology.link/data/ancientports/196", "name": "Castro de Lobadiz", "dateprops": [], "properties": {"http://purl.org/dc/elements/1.1/creator": ["http://data.archaeology.link/data/spphaefen/arthur_de_graauw"], "http://purl.org/dc/terms/partOf": ["http://data.archaeology.link/data/ancientports/bib_deGrauw_2013_GeoDB"], "http://www.opengis.net/ont/geosparql#hasGeometry": ["http://data.archaeology.link/data/ancientports/196_geom"], "http://www.w3.org/1999/02/22-rdf-syntax-ns#type": ["http://www.ancientports.com/ont#Harbour"], "http://www.w3.org/2000/01/rdf-schema#label": ["Castro de Lobadiz"], "http://www.w3.org/2002/07/owl#sameAs": ["http://www.wikidata.org/entity/Q485329"], "http://www.wikidata.org/prop/direct/P17": ["http://www.wikidata.org/entity/Q29"], "begin": ""}, "geometry": {"type": "Point", "coordinates": [-8.3289, 43.5086]}}]}