{"type": "FeatureCollection", "id": "https://topostext.org/place/404266UKre", "name": "404266UKre", "features": [{"type": "Feature", "id": "http://data.archaeology.link/data/ancientports/2378", "name": "Kressa ", "dateprops": ["begin"], "properties": {"http://purl.org/dc/elements/1.1/creator": ["http://data.archaeology.link/data/spphaefen/arthur_de_graauw"], "http://purl.org/dc/terms/partOf": ["http://data.archaeology.link/data/ancientports/bib_deGrauw_2013_GeoDB"], "http://www.opengis.net/ont/geosparql#hasGeometry": ["http://data.archaeology.link/data/ancientports/2378_geom"], "http://www.w3.org/1999/02/22-rdf-syntax-ns#type": ["http://www.ancientports.com/ont#Harbour"], "http://www.w3.org/2000/01/rdf-schema#label": ["Kressa "], "http://www.w3.org/2002/07/owl#sameAs": ["http://www.wikidata.org/entity/Q6436822"], "http://www.w3.org/2004/02/skos/core#note": ["Tsvetkova (2008)"], "http://www.w3.org/2006/time#hasTime": ["http://data.archaeology.link/data/ancientports/2378_foundation"], "http://www.wikidata.org/prop/direct/P1584": ["http://pleiades.stoa.org/places/501483"], "http://www.wikidata.org/prop/direct/P17": ["http://www.wikidata.org/entity/Q43"], "http://www.wikidata.org/prop/direct/P1936": ["http://imperium.ahlfeldt.se/places/32351"], "http://www.wikidata.org/prop/direct/P1958": ["https://www.trismegistos.org/place/60990"], "http://www.wikidata.org/prop/direct/P8068": ["https://topostext.org/place/404266UKre"], "begin": "-750"}, "geometry": {"type": "Point", "coordinates": [26.63261, 40.36042]}}]}