{"type": "FeatureCollection", "id": "http://www.wikidata.org/entity/Q499898", "name": "Portus Lemanis", "features": [{"type": "Feature", "id": "http://data.archaeology.link/data/ancientports/82", "name": "Stutfall Castle, near Lympne castle", "dateprops": ["begin"], "properties": {"http://purl.org/dc/elements/1.1/creator": ["http://data.archaeology.link/data/spphaefen/arthur_de_graauw"], "http://purl.org/dc/terms/isReferencedBy": ["https://historicengland.org.uk/listing/the-list/list-entry/1005179"], "http://purl.org/dc/terms/partOf": ["http://data.archaeology.link/data/ancientports/bib_deGrauw_2013_GeoDB"], "http://www.opengis.net/ont/geosparql#hasGeometry": ["http://data.archaeology.link/data/ancientports/82_geom"], "http://www.w3.org/1999/02/22-rdf-syntax-ns#type": ["http://www.ancientports.com/ont#Harbour"], "http://www.w3.org/2000/01/rdf-schema#label": ["Stutfall Castle, near Lympne castle"], "http://www.w3.org/2002/07/owl#sameAs": ["http://www.wikidata.org/entity/Q499898"], "http://www.w3.org/2004/02/skos/core#note": ["Wilmott (2018)"], "http://www.w3.org/2006/time#hasTime": ["http://data.archaeology.link/data/ancientports/82_foundation"], "http://www.wikidata.org/prop/direct/P1584": ["http://pleiades.stoa.org/places/79647"], "http://www.wikidata.org/prop/direct/P17": ["http://www.wikidata.org/entity/Q145"], "http://www.wikidata.org/prop/direct/P1936": ["http://imperium.ahlfeldt.se/places/18909"], "http://www.wikidata.org/prop/direct/P1958": ["https://www.trismegistos.org/place/14967"], "begin": "3001"}, "geometry": {"type": "Point", "coordinates": [1.0203, 51.0682]}}], "numberMatched": 1, "numberReturned": 1, "bbox": [1.0203, 51.0682, 1.0203, 51.0682], "crs": "http://www.opengis.net/def/crs/OGC/1.3/CRS84"}