{"type": "FeatureCollection", "id": "https://www.trismegistos.org/place/15788", "name": "15788", "features": [{"type": "Feature", "id": "http://data.archaeology.link/data/ancientports/1515", "label": "Lezhe, on R Drin", "properties": {"http://purl.org/dc/elements/1.1/created": ["2023"], "http://purl.org/dc/elements/1.1/creator": ["http://data.archaeology.link/data/spphaefen/arthur_de_graauw"], "http://www.ancientports.com/ont#date_min": ["-330"], "http://www.opengis.net/ont/geosparql#hasGeometry": ["http://data.archaeology.link/data/ancientports/1515_geom"], "http://www.w3.org/1999/02/22-rdf-syntax-ns#type": ["http://www.ancientports.com/ont#Harbour"], "http://www.w3.org/2000/01/rdf-schema#label": ["Lezhe, on R Drin"], "http://www.w3.org/2002/07/owl#sameAs": ["http://www.wikidata.org/entity/Q169160"], "http://www.wikidata.org/prop/direct/P1584": ["http://pleiades.stoa.org/places/481896"], "http://www.wikidata.org/prop/direct/P17": ["Albania"], "http://www.wikidata.org/prop/direct/P1958": ["https://www.trismegistos.org/place/15788"]}, "geometry": {"type": "Point", "coordinates": [19.643, 41.783]}}]}