{"type": "FeatureCollection", "id": "https://topostext.org/place/363277INar", "name": "363277INar", "features": [{"type": "Feature", "id": "http://data.archaeology.link/data/ancientports/2314_2", "label": "Isle of Sfyrna, near Rhodes", "dateprops": ["http://purl.org/dc/elements/1.1/created"], "properties": {"http://purl.org/dc/elements/1.1/created": ["2023"], "http://purl.org/dc/elements/1.1/creator": ["http://data.archaeology.link/data/spphaefen/arthur_de_graauw"], "http://www.opengis.net/ont/geosparql#hasGeometry": ["http://data.archaeology.link/data/ancientports/2314_2_geom"], "http://www.w3.org/1999/02/22-rdf-syntax-ns#type": ["http://www.ancientports.com/ont#Harbour"], "http://www.w3.org/2000/01/rdf-schema#label": ["Isle of Sfyrna, near Rhodes"], "http://www.wikidata.org/prop/direct/P1584": ["http://pleiades.stoa.org/places/589952"], "http://www.wikidata.org/prop/direct/P17": ["GR: Eastern Isl."], "http://www.wikidata.org/prop/direct/P1936": ["http://imperium.ahlfeldt.se/places/41164"], "http://www.wikidata.org/prop/direct/P8068": ["https://topostext.org/place/363277INar"]}, "geometry": {"type": "Point", "coordinates": [27.677, 36.264]}}]}