{"type": "FeatureCollection", "id": "http://www.wikidata.org/entity/Q182432", "name": "Lanzarote", "features": [{"type": "Feature", "id": "http://data.archaeology.link/data/ancientports/4341_2", "name": "Isla Lanzarote", "dateprops": ["begin"], "properties": {"http://purl.org/dc/elements/1.1/created": ["2023"], "http://purl.org/dc/elements/1.1/creator": ["http://data.archaeology.link/data/spphaefen/arthur_de_graauw"], "http://www.opengis.net/ont/geosparql#hasGeometry": ["http://data.archaeology.link/data/ancientports/4341_2_geom"], "http://www.w3.org/1999/02/22-rdf-syntax-ns#type": ["http://www.ancientports.com/ont#Harbour"], "http://www.w3.org/2000/01/rdf-schema#label": ["Isla Lanzarote"], "http://www.w3.org/2002/07/owl#sameAs": ["http://www.wikidata.org/entity/Q182432"], "http://www.w3.org/2006/time#hasTime": ["http://data.archaeology.link/data/ancientports/4341_2_foundation"], "http://www.wikidata.org/prop/direct/P17": ["http://www.wikidata.org/entity/Q29"], "begin": "-1100"}, "geometry": {"type": "Point", "coordinates": [-13.63, 29.02]}}]}