{"type": "FeatureCollection", "id": "https://topostext.org/place/397086UNea", "name": "397086UNea", "features": [{"type": "Feature", "id": "http://data.archaeology.link/data/ancientports/782", "name": "Santa Maria di Nabui, on R Pabillonis", "dateprops": [], "properties": {"http://purl.org/dc/elements/1.1/creator": ["http://data.archaeology.link/data/spphaefen/arthur_de_graauw"], "http://purl.org/dc/terms/partOf": ["http://data.archaeology.link/data/ancientports/bib_deGrauw_2013_GeoDB"], "http://www.opengis.net/ont/geosparql#hasGeometry": ["http://data.archaeology.link/data/ancientports/782_geom"], "http://www.w3.org/1999/02/22-rdf-syntax-ns#type": ["http://www.ancientports.com/ont#Quay"], "http://www.w3.org/2000/01/rdf-schema#label": ["Santa Maria di Nabui, on R Pabillonis"], "http://www.w3.org/2002/07/owl#sameAs": ["http://www.wikidata.org/entity/Q1137496"], "http://www.w3.org/2004/02/skos/core#note": ["Nervi (2014)"], "http://www.wikidata.org/prop/direct/P1584": ["http://pleiades.stoa.org/places/471977"], "http://www.wikidata.org/prop/direct/P17": ["http://www.wikidata.org/entity/Q38"], "http://www.wikidata.org/prop/direct/P1936": ["http://imperium.ahlfeldt.se/places/41635"], "http://www.wikidata.org/prop/direct/P1958": ["https://www.trismegistos.org/place/22118"], "http://www.wikidata.org/prop/direct/P8068": ["https://topostext.org/place/397086UNea"], "begin": ""}, "geometry": {"type": "Point", "coordinates": [8.5555, 39.68794]}}], "numberMatched": 1, "numberReturned": 1, "bbox": [8.5555, 39.68794, 8.5555, 39.68794], "crs": "http://www.opengis.net/def/crs/OGC/1.3/CRS84"}