{"type": "FeatureCollection", "id": "http://www.wikidata.org/entity/Q1362186", "name": "Molat", "features": [{"type": "Feature", "id": "http://data.archaeology.link/data/ancientports/1422", "name": "Prolaz Zapuntel, on Molat island", "dateprops": [], "properties": {"http://purl.org/dc/elements/1.1/creator": ["http://data.archaeology.link/data/spphaefen/arthur_de_graauw"], "http://purl.org/dc/terms/isReferencedBy": ["http://baza.iarh.hr/public/locality/detail/8025"], "http://purl.org/dc/terms/partOf": ["http://data.archaeology.link/data/ancientports/bib_deGrauw_2013_GeoDB"], "http://www.opengis.net/ont/geosparql#hasGeometry": ["http://data.archaeology.link/data/ancientports/1422_geom"], "http://www.w3.org/1999/02/22-rdf-syntax-ns#type": ["http://www.ancientports.com/ont#Harbour"], "http://www.w3.org/2000/01/rdf-schema#label": ["Prolaz Zapuntel, on Molat island"], "http://www.w3.org/2002/07/owl#sameAs": ["http://www.wikidata.org/entity/Q1362186"], "http://www.wikidata.org/prop/direct/P17": ["http://www.wikidata.org/entity/Q224"], "begin": ""}, "geometry": {"type": "Point", "coordinates": [14.79917, 44.25964]}}]}