{"type": "FeatureCollection", "id": "http://www.wikidata.org/entity/Q16010710", "name": "Q16010710", "features": [{"type": "Feature", "id": "http://data.archaeology.link/data/ancientports/946", "label": "Castello di San Gallo at Nettuno, on R Loricina", "properties": {"http://purl.org/dc/elements/1.1/created": ["2023"], "http://purl.org/dc/elements/1.1/creator": ["http://data.archaeology.link/data/spphaefen/arthur_de_graauw"], "http://www.ancientports.com/ont#date_min": ["-30"], "http://www.opengis.net/ont/geosparql#hasGeometry": ["http://data.archaeology.link/data/ancientports/946_geom"], "http://www.w3.org/1999/02/22-rdf-syntax-ns#type": ["http://www.ancientports.com/ont#Harbour"], "http://www.w3.org/2000/01/rdf-schema#label": ["Castello di San Gallo at Nettuno, on R Loricina"], "http://www.w3.org/2002/07/owl#sameAs": ["http://www.wikidata.org/entity/Q16010710"], "http://www.wikidata.org/prop/direct/P1584": ["http://pleiades.stoa.org/places/422985"], "http://www.wikidata.org/prop/direct/P17": ["Italy West"]}, "geometry": {"type": "Point", "coordinates": [12.66064, 41.45612]}}, {"type": "Feature", "id": "http://data.archaeology.link/data/ancientports/943", "label": "Anzio, with Nero's Roman villa and several others", "properties": {"http://purl.org/dc/elements/1.1/created": ["2023"], "http://purl.org/dc/elements/1.1/creator": ["http://data.archaeology.link/data/spphaefen/arthur_de_graauw"], "http://www.ancientports.com/ont#date_min": ["-750"], "http://www.opengis.net/ont/geosparql#hasGeometry": ["http://data.archaeology.link/data/ancientports/943_geom"], "http://www.w3.org/1999/02/22-rdf-syntax-ns#type": ["http://www.ancientports.com/ont#Harbour"], "http://www.w3.org/2000/01/rdf-schema#label": ["Anzio, with Nero's Roman villa and several others"], "http://www.w3.org/2002/07/owl#sameAs": ["http://www.wikidata.org/entity/Q16010710"], "http://www.wikidata.org/prop/direct/P1584": ["http://pleiades.stoa.org/places/422837"], "http://www.wikidata.org/prop/direct/P17": ["Italy West"], "http://www.wikidata.org/prop/direct/P1958": ["https://www.trismegistos.org/place/32374"]}, "geometry": {"type": "Point", "coordinates": [12.62839, 41.4427]}}]}