{"type": "FeatureCollection", "id": "http://imperium.ahlfeldt.se/places/29513", "name": "29513", "features": [{"type": "Feature", "id": "http://data.archaeology.link/data/ancientports/2266", "name": "Daskalopetra, on the isle of Chios", "dateprops": ["begin"], "properties": {"http://purl.org/dc/elements/1.1/creator": ["http://data.archaeology.link/data/spphaefen/arthur_de_graauw"], "http://purl.org/dc/terms/partOf": ["http://data.archaeology.link/data/ancientports/bib_deGrauw_2013_GeoDB"], "http://www.opengis.net/ont/geosparql#hasGeometry": ["http://data.archaeology.link/data/ancientports/2266_geom"], "http://www.w3.org/1999/02/22-rdf-syntax-ns#type": ["http://www.ancientports.com/ont#Harbour"], "http://www.w3.org/2000/01/rdf-schema#label": ["Daskalopetra, on the isle of Chios"], "http://www.w3.org/2002/07/owl#sameAs": ["http://www.wikidata.org/entity/Q65081497"], "http://www.w3.org/2006/time#hasTime": ["http://data.archaeology.link/data/ancientports/2266_foundation"], "http://www.wikidata.org/prop/direct/P1584": ["http://pleiades.stoa.org/places/550482"], "http://www.wikidata.org/prop/direct/P17": ["http://www.wikidata.org/entity/Q41"], "http://www.wikidata.org/prop/direct/P1936": ["http://imperium.ahlfeldt.se/places/29513"], "http://www.wikidata.org/prop/direct/P8068": ["https://topostext.org/place/384261UBab"], "begin": "-750"}, "geometry": {"type": "Point", "coordinates": [26.134, 38.4222]}}]}