{"type": "FeatureCollection", "id": "http://pleiades.stoa.org/places/462428", "name": "462428", "features": [{"type": "Feature", "id": "http://data.archaeology.link/data/ancientports/1180", "label": "Grotta del Genovese, on the isle of Levanzo, smallest of the Egadi islands", "dateprops": ["http://purl.org/dc/elements/1.1/created", "http://www.ancientports.com/ont#date_min"], "properties": {"http://purl.org/dc/elements/1.1/created": ["2023"], "http://purl.org/dc/elements/1.1/creator": ["http://data.archaeology.link/data/spphaefen/arthur_de_graauw"], "http://www.ancientports.com/ont#date_min": ["-30"], "http://www.opengis.net/ont/geosparql#hasGeometry": ["http://data.archaeology.link/data/ancientports/1180_geom"], "http://www.w3.org/1999/02/22-rdf-syntax-ns#type": ["http://www.ancientports.com/ont#Harbour"], "http://www.w3.org/2000/01/rdf-schema#label": ["Grotta del Genovese, on the isle of Levanzo, smallest of the Egadi islands"], "http://www.w3.org/2002/07/owl#sameAs": ["http://www.wikidata.org/entity/Q497357"], "http://www.wikidata.org/prop/direct/P1584": ["http://pleiades.stoa.org/places/462428"], "http://www.wikidata.org/prop/direct/P17": ["Italy Sicily"], "http://www.wikidata.org/prop/direct/P1936": ["http://imperium.ahlfeldt.se/places/22887"], "http://www.wikidata.org/prop/direct/P1958": ["https://www.trismegistos.org/place/22307"], "http://www.wikidata.org/prop/direct/P8068": ["https://topostext.org/place/380123IPho"]}, "geometry": {"type": "Point", "coordinates": [12.32163, 38.00168]}}]}