{"type": "FeatureCollection", "id": "https://www.trismegistos.org/place/60794", "name": "60794", "features": [{"type": "Feature", "id": "http://data.archaeology.link/data/ancientports/1626_1", "label": "Kinosoura", "properties": {"http://purl.org/dc/elements/1.1/created": ["2023"], "http://purl.org/dc/elements/1.1/creator": ["http://data.archaeology.link/data/spphaefen/arthur_de_graauw"], "http://www.opengis.net/ont/geosparql#hasGeometry": ["http://data.archaeology.link/data/ancientports/1626_1_geom"], "http://www.w3.org/1999/02/22-rdf-syntax-ns#type": ["http://www.ancientports.com/ont#Harbour"], "http://www.w3.org/2000/01/rdf-schema#label": ["Kinosoura"], "http://www.wikidata.org/prop/direct/P17": ["GR: Attica +"], "http://www.wikidata.org/prop/direct/P1958": ["https://www.trismegistos.org/place/60794"]}, "geometry": {"type": "Point", "coordinates": [23.557, 37.9457]}}]}