{"type": "FeatureCollection", "id": "http://imperium.ahlfeldt.se/places/36130", "name": "36130", "features": [{"type": "Feature", "id": "http://data.archaeology.link/data/ancientports/3719", "label": "Ras Hafun, Xaafuun, with bay of Khor Hordiyo, Hurdiyo? Other possible locations for Punt are Mundus, Mosylium and Adulis", "properties": {"http://purl.org/dc/elements/1.1/created": ["2023"], "http://purl.org/dc/elements/1.1/creator": ["http://data.archaeology.link/data/spphaefen/arthur_de_graauw"], "http://purl.org/dc/terms/isReferencedBy": ["https://pleiades.stoa.org/places/40352"], "http://www.ancientports.com/ont#date_min": ["-30"], "http://www.opengis.net/ont/geosparql#hasGeometry": ["http://data.archaeology.link/data/ancientports/3719_geom"], "http://www.w3.org/1999/02/22-rdf-syntax-ns#type": ["http://www.ancientports.com/ont#Harbour"], "http://www.w3.org/2000/01/rdf-schema#label": ["Ras Hafun, Xaafuun, with bay of Khor Hordiyo, Hurdiyo? Other possible locations for Punt are Mundus, Mosylium and Adulis"], "http://www.w3.org/2002/07/owl#sameAs": ["http://www.wikidata.org/entity/Q7098410"], "http://www.w3.org/2004/02/skos/core#note": ["Chittick (1976)", "Hussein (2014)"], "http://www.wikidata.org/prop/direct/P1584": ["http://pleiades.stoa.org/places/39403"], "http://www.wikidata.org/prop/direct/P17": ["http://www.wikidata.org/entity/Q1045"], "http://www.wikidata.org/prop/direct/P1936": ["http://imperium.ahlfeldt.se/places/36130"], "http://www.wikidata.org/prop/direct/P1958": ["https://www.trismegistos.org/place/11221"]}, "geometry": {"type": "Point", "coordinates": [51.2707, 10.4041]}}]}