{"type": "FeatureCollection", "id": "http://imperium.ahlfeldt.se/places/31539", "name": "31539", "features": [{"type": "Feature", "id": "http://data.archaeology.link/data/ancientports/1586_1", "label": "Kefalovriso", "properties": {"http://purl.org/dc/elements/1.1/created": ["2023"], "http://purl.org/dc/elements/1.1/creator": ["http://data.archaeology.link/data/spphaefen/arthur_de_graauw"], "http://www.ancientports.com/ont#date_min": ["-330"], "http://www.opengis.net/ont/geosparql#hasGeometry": ["http://data.archaeology.link/data/ancientports/1586_1_geom"], "http://www.w3.org/1999/02/22-rdf-syntax-ns#type": ["http://www.ancientports.com/ont#Harbour"], "http://www.w3.org/2000/01/rdf-schema#label": ["Kefalovriso"], "http://www.wikidata.org/prop/direct/P1584": ["http://pleiades.stoa.org/places/530857"], "http://www.wikidata.org/prop/direct/P17": ["GR: North-West"], "http://www.wikidata.org/prop/direct/P1936": ["http://imperium.ahlfeldt.se/places/31539"], "http://www.wikidata.org/prop/direct/P8068": ["https://topostext.org/place/385213UEla"]}, "geometry": {"type": "Point", "coordinates": [21.3214, 38.5087]}}]}