{"type": "FeatureCollection", "id": "http://www.wikidata.org/entity/Q4949619", "name": "Bouldnor Cliff", "features": [{"type": "Feature", "id": "http://data.archaeology.link/data/ancientports/95_1", "name": "Bouldnor Cliff, submerged Mesolithic settlement, on the isle of Wight", "dateprops": ["begin"], "properties": {"http://purl.org/dc/elements/1.1/creator": ["http://data.archaeology.link/data/spphaefen/arthur_de_graauw"], "http://purl.org/dc/terms/isReferencedBy": ["http://data.archaeology.link/data/ancientports/bib_Rich_2016_Mesolithic", "https://maritimearchaeologytrust.org/bouldnor"], "http://purl.org/dc/terms/partOf": ["http://data.archaeology.link/data/ancientports/bib_deGrauw_2013_GeoDB"], "http://www.opengis.net/ont/geosparql#hasGeometry": ["http://data.archaeology.link/data/ancientports/95_1_geom"], "http://www.w3.org/1999/02/22-rdf-syntax-ns#type": ["http://www.ancientports.com/ont#Harbour"], "http://www.w3.org/2000/01/rdf-schema#label": ["Bouldnor Cliff, submerged Mesolithic settlement, on the isle of Wight"], "http://www.w3.org/2002/07/owl#sameAs": ["http://www.wikidata.org/entity/Q4949619"], "http://www.w3.org/2006/time#hasTime": ["http://data.archaeology.link/data/ancientports/95_1_foundation"], "http://www.wikidata.org/prop/direct/P17": ["http://www.wikidata.org/entity/Q145"], "begin": "-6000"}, "geometry": {"type": "Point", "coordinates": [-1.4822, 50.7107]}}], "numberMatched": 1, "numberReturned": 1, "bbox": [-1.4822, 50.7107, -1.4822, 50.7107], "crs": "http://www.opengis.net/def/crs/EPSG/0/4326"}