{"type": "FeatureCollection", "id": "http://www.wikidata.org/entity/Q5580295", "name": "Q5580295", "features": [{"type": "Feature", "id": "http://data.archaeology.link/data/ancientports/52", "label": "possible lighthouse at Goldsborough ", "dateprops": [], "properties": {"http://purl.org/dc/elements/1.1/created": ["2023"], "http://purl.org/dc/elements/1.1/creator": ["http://data.archaeology.link/data/spphaefen/arthur_de_graauw"], "http://purl.org/dc/terms/isReferencedBy": ["https://historicengland.org.uk/listing/the-list/list-entry/1016537"], "http://www.opengis.net/ont/geosparql#hasGeometry": ["http://data.archaeology.link/data/ancientports/52_geom"], "http://www.w3.org/1999/02/22-rdf-syntax-ns#type": ["http://www.ancientports.com/ont#Harbour"], "http://www.w3.org/2000/01/rdf-schema#label": ["possible lighthouse at Goldsborough "], "http://www.w3.org/2002/07/owl#sameAs": ["http://www.wikidata.org/entity/Q5580295"], "http://www.w3.org/2006/time#hasTime": ["http://data.archaeology.link/data/ancientports/52_foundation"], "http://www.wikidata.org/prop/direct/P1584": ["http://pleiades.stoa.org/places/89194"], "http://www.wikidata.org/prop/direct/P17": ["http://www.wikidata.org/entity/Q145"], "http://www.wikidata.org/prop/direct/P1936": ["http://imperium.ahlfeldt.se/places/23716"]}, "geometry": {"type": "Point", "coordinates": [-0.7246, 54.53974]}}]}