{"type": "FeatureCollection", "id": "http://pleiades.stoa.org/places/550838", "name": "550838", "features": [{"type": "Feature", "id": "http://data.archaeology.link/data/ancientports/3147", "label": "Balikliova?", "dateprops": [], "properties": {"http://purl.org/dc/elements/1.1/created": ["2023"], "http://purl.org/dc/elements/1.1/creator": ["http://data.archaeology.link/data/spphaefen/arthur_de_graauw"], "http://www.opengis.net/ont/geosparql#hasGeometry": ["http://data.archaeology.link/data/ancientports/3147_geom"], "http://www.w3.org/1999/02/22-rdf-syntax-ns#type": ["http://www.ancientports.com/ont#Harbour"], "http://www.w3.org/2000/01/rdf-schema#label": ["Balikliova?"], "http://www.w3.org/2002/07/owl#sameAs": ["http://www.wikidata.org/entity/Q60791963"], "http://www.w3.org/2006/time#hasTime": ["http://data.archaeology.link/data/ancientports/3147_foundation"], "http://www.wikidata.org/prop/direct/P1584": ["http://pleiades.stoa.org/places/550838"], "http://www.wikidata.org/prop/direct/P17": ["TR: West"], "http://www.wikidata.org/prop/direct/P1936": ["http://imperium.ahlfeldt.se/places/27348"], "http://www.wikidata.org/prop/direct/P1958": ["https://www.trismegistos.org/place/60935"], "http://www.wikidata.org/prop/direct/P8068": ["https://topostext.org/place/384266UPol"]}, "geometry": {"type": "Point", "coordinates": [26.5772, 38.4291]}}]}