{"type": "FeatureCollection", "id": "http://www.wikidata.org/entity/Q898718", "name": "Q898718", "features": [{"type": "Feature", "id": "http://data.archaeology.link/data/ancientports/2310", "label": "Tilos, on the isle of Tilos", "dateprops": [], "properties": {"http://purl.org/dc/elements/1.1/created": ["2023"], "http://purl.org/dc/elements/1.1/creator": ["http://data.archaeology.link/data/spphaefen/arthur_de_graauw"], "http://purl.org/dc/terms/isReferencedBy": ["https://topostext.org/place/364274CCha"], "http://www.opengis.net/ont/geosparql#hasGeometry": ["http://data.archaeology.link/data/ancientports/2310_geom"], "http://www.w3.org/1999/02/22-rdf-syntax-ns#type": ["http://www.ancientports.com/ont#Harbour"], "http://www.w3.org/2000/01/rdf-schema#label": ["Tilos, on the isle of Tilos"], "http://www.w3.org/2002/07/owl#sameAs": ["http://www.wikidata.org/entity/Q898718"], "http://www.w3.org/2006/time#hasTime": ["http://data.archaeology.link/data/ancientports/2310_foundation"], "http://www.wikidata.org/prop/direct/P1584": ["http://pleiades.stoa.org/places/599960"], "http://www.wikidata.org/prop/direct/P17": ["http://www.wikidata.org/entity/Q41"], "http://www.wikidata.org/prop/direct/P1936": ["http://imperium.ahlfeldt.se/places/43446"], "http://www.wikidata.org/prop/direct/P1958": ["https://www.trismegistos.org/place/3637"], "http://www.wikidata.org/prop/direct/P8068": ["https://topostext.org/place/365273PTel"]}, "geometry": {"type": "Point", "coordinates": [27.347, 36.4555]}}]}