{"type": "FeatureCollection", "id": "http://www.wikidata.org/entity/Q31117838", "name": "Q31117838", "features": [{"type": "Feature", "id": "http://data.archaeology.link/data/ancientports/84_6", "label": "Hollingbury Castle oppidum, Brighton", "properties": {"http://purl.org/dc/elements/1.1/created": ["2023"], "http://purl.org/dc/elements/1.1/creator": ["http://data.archaeology.link/data/spphaefen/arthur_de_graauw"], "http://www.ancientports.com/ont#date_min": ["-500"], "http://www.opengis.net/ont/geosparql#hasGeometry": ["http://data.archaeology.link/data/ancientports/84_6_geom"], "http://www.w3.org/1999/02/22-rdf-syntax-ns#type": ["http://www.ancientports.com/ont#Harbour"], "http://www.w3.org/2000/01/rdf-schema#label": ["Hollingbury Castle oppidum, Brighton"], "http://www.w3.org/2002/07/owl#sameAs": ["http://www.wikidata.org/entity/Q31117838"], "http://www.wikidata.org/prop/direct/P17": ["UK"]}, "geometry": {"type": "Point", "coordinates": [-0.123, 50.8553]}}]}