{"type": "FeatureCollection", "id": "https://topostext.org/place/406143ICap", "name": "406143ICap", "features": [{"type": "Feature", "id": "http://data.archaeology.link/data/ancientports/1009", "label": "Bagni di Tiberio, near Marina Grande on the isle of Capri, with lighthouse at Roman villa Jovis", "properties": {"http://purl.org/dc/elements/1.1/created": ["2023"], "http://purl.org/dc/elements/1.1/creator": ["http://data.archaeology.link/data/spphaefen/arthur_de_graauw"], "http://www.ancientports.com/ont#date_min": ["-550"], "http://www.opengis.net/ont/geosparql#hasGeometry": ["http://data.archaeology.link/data/ancientports/1009_geom"], "http://www.w3.org/1999/02/22-rdf-syntax-ns#type": ["http://www.ancientports.com/ont#Pila", "http://www.ancientports.com/ont#Quay", "http://www.ancientports.com/ont#Lighthouse", "http://www.ancientports.com/ont#VillaMaritima"], "http://www.w3.org/2000/01/rdf-schema#label": ["Bagni di Tiberio, near Marina Grande on the isle of Capri, with lighthouse at Roman villa Jovis"], "http://www.w3.org/2002/07/owl#sameAs": ["http://www.wikidata.org/entity/Q6763830"], "http://www.wikidata.org/prop/direct/P1584": ["http://pleiades.stoa.org/places/432751"], "http://www.wikidata.org/prop/direct/P17": ["Italy West"], "http://www.wikidata.org/prop/direct/P1936": ["http://imperium.ahlfeldt.se/places/22631"], "http://www.wikidata.org/prop/direct/P1958": ["https://www.trismegistos.org/place/32415"], "http://www.wikidata.org/prop/direct/P8068": ["https://topostext.org/place/406143ICap"]}, "geometry": {"type": "Point", "coordinates": [14.23659, 40.55769]}}]}