{"type": "FeatureCollection", "id": "https://www.trismegistos.org/place/38107", "name": "38107", "features": [{"type": "Feature", "id": "http://data.archaeology.link/data/ancientports/1936", "label": "Modon", "dateprops": [], "properties": {"http://purl.org/dc/elements/1.1/created": ["2023"], "http://purl.org/dc/elements/1.1/creator": ["http://data.archaeology.link/data/spphaefen/arthur_de_graauw"], "http://purl.org/dc/terms/isReferencedBy": ["https://www2.rgzm.de/navis2/home/frames.htm"], "http://www.opengis.net/ont/geosparql#hasGeometry": ["http://data.archaeology.link/data/ancientports/1936_geom"], "http://www.w3.org/1999/02/22-rdf-syntax-ns#type": ["http://www.ancientports.com/ont#Harbour"], "http://www.w3.org/2000/01/rdf-schema#label": ["Modon"], "http://www.w3.org/2002/07/owl#sameAs": ["http://www.wikidata.org/entity/Q998805"], "http://www.w3.org/2006/time#hasTime": ["http://data.archaeology.link/data/ancientports/1936_foundation"], "http://www.wikidata.org/prop/direct/P1584": ["http://pleiades.stoa.org/places/570483"], "http://www.wikidata.org/prop/direct/P17": ["GR: Pelop"], "http://www.wikidata.org/prop/direct/P1936": ["http://imperium.ahlfeldt.se/places/21910"], "http://www.wikidata.org/prop/direct/P1958": ["https://www.trismegistos.org/place/38107"], "http://www.wikidata.org/prop/direct/P8068": ["https://topostext.org/place/368217UMot"]}, "geometry": {"type": "Point", "coordinates": [21.705, 36.817]}}]}