{"type": "FeatureCollection", "id": "https://www.trismegistos.org/place/8444", "name": "8444", "features": [{"type": "Feature", "id": "http://data.archaeology.link/data/ancientports/2797", "name": "Amasra", "dateprops": ["begin"], "properties": {"http://purl.org/dc/elements/1.1/creator": ["http://data.archaeology.link/data/spphaefen/arthur_de_graauw"], "http://purl.org/dc/terms/partOf": ["http://data.archaeology.link/data/ancientports/bib_deGrauw_2013_GeoDB"], "http://www.opengis.net/ont/geosparql#hasGeometry": ["http://data.archaeology.link/data/ancientports/2797_geom"], "http://www.w3.org/1999/02/22-rdf-syntax-ns#type": ["http://www.ancientports.com/ont#Harbour"], "http://www.w3.org/2000/01/rdf-schema#label": ["Amasra"], "http://www.w3.org/2002/07/owl#sameAs": ["http://www.wikidata.org/entity/Q455458"], "http://www.w3.org/2004/02/skos/core#note": ["Dan (2009)"], "http://www.w3.org/2006/time#hasTime": ["http://data.archaeology.link/data/ancientports/2797_foundation"], "http://www.wikidata.org/prop/direct/P1584": ["http://pleiades.stoa.org/places/844856"], "http://www.wikidata.org/prop/direct/P17": ["http://www.wikidata.org/entity/Q43"], "http://www.wikidata.org/prop/direct/P1936": ["http://imperium.ahlfeldt.se/places/21253"], "http://www.wikidata.org/prop/direct/P1958": ["https://www.trismegistos.org/place/8444"], "http://www.wikidata.org/prop/direct/P8068": ["https://topostext.org/place/417324UAma"], "begin": "-550"}, "geometry": {"type": "Point", "coordinates": [32.38602, 41.75489]}}], "numberMatched": 1, "numberReturned": 1, "bbox": [32.38602, 41.75489, 32.38602, 41.75489], "crs": "http://www.opengis.net/def/crs/OGC/1.3/CRS84"}