{"type": "FeatureCollection", "id": "https://www.trismegistos.org/place/22278", "name": "22278", "features": [{"type": "Feature", "id": "http://data.archaeology.link/data/ancientports/1184", "name": "Castellammare del Golfo, on R San Bartolomeo", "dateprops": ["begin"], "properties": {"http://purl.org/dc/elements/1.1/created": ["2023"], "http://purl.org/dc/elements/1.1/creator": ["http://data.archaeology.link/data/spphaefen/arthur_de_graauw"], "http://www.opengis.net/ont/geosparql#hasGeometry": ["http://data.archaeology.link/data/ancientports/1184_geom"], "http://www.w3.org/1999/02/22-rdf-syntax-ns#type": ["http://www.ancientports.com/ont#Harbour"], "http://www.w3.org/2000/01/rdf-schema#label": ["Castellammare del Golfo, on R San Bartolomeo"], "http://www.w3.org/2002/07/owl#sameAs": ["http://www.wikidata.org/entity/Q481642"], "http://www.w3.org/2006/time#hasTime": ["http://data.archaeology.link/data/ancientports/1184_foundation"], "http://www.wikidata.org/prop/direct/P1584": ["http://pleiades.stoa.org/places/462194"], "http://www.wikidata.org/prop/direct/P17": ["http://www.wikidata.org/entity/Q38"], "http://www.wikidata.org/prop/direct/P1936": ["http://imperium.ahlfeldt.se/places/31215"], "http://www.wikidata.org/prop/direct/P1958": ["https://www.trismegistos.org/place/22278"], "http://www.wikidata.org/prop/direct/P8068": ["https://topostext.org/place/380129UEmp"], "begin": "-330"}, "geometry": {"type": "Point", "coordinates": [12.88, 38.0295]}}]}