{"type": "FeatureCollection", "id": "http://www.wikidata.org/entity/Q312108", "name": "Q312108", "features": [{"type": "Feature", "id": "http://data.archaeology.link/data/ancientports/4217", "label": "el-Aouana and island Cavallo?", "dateprops": [], "properties": {"http://purl.org/dc/elements/1.1/created": ["2023"], "http://purl.org/dc/elements/1.1/creator": ["http://data.archaeology.link/data/spphaefen/arthur_de_graauw"], "http://www.opengis.net/ont/geosparql#hasGeometry": ["http://data.archaeology.link/data/ancientports/4217_geom"], "http://www.w3.org/1999/02/22-rdf-syntax-ns#type": ["http://www.ancientports.com/ont#Harbour"], "http://www.w3.org/2000/01/rdf-schema#label": ["el-Aouana and island Cavallo?"], "http://www.w3.org/2002/07/owl#sameAs": ["http://www.wikidata.org/entity/Q312108"], "http://www.w3.org/2004/02/skos/core#note": ["Elie de la Primaudaie (1860)"], "http://www.wikidata.org/prop/direct/P17": ["http://www.wikidata.org/entity/Q262"]}, "geometry": {"type": "Point", "coordinates": [5.60529, 36.78022]}}]}