{"type": "FeatureCollection", "id": "http://pleiades.stoa.org/places/590049", "name": "590049", "features": [{"type": "Feature", "id": "http://data.archaeology.link/data/ancientports/2075", "name": "Isle of Sifnos, Yavuzca", "dateprops": [], "properties": {"http://purl.org/dc/elements/1.1/creator": ["http://data.archaeology.link/data/spphaefen/arthur_de_graauw"], "http://purl.org/dc/terms/partOf": ["http://data.archaeology.link/data/ancientports/bib_deGrauw_2013_GeoDB"], "http://www.opengis.net/ont/geosparql#hasGeometry": ["http://data.archaeology.link/data/ancientports/2075_geom"], "http://www.w3.org/1999/02/22-rdf-syntax-ns#type": ["http://www.ancientports.com/ont#Harbour"], "http://www.w3.org/2000/01/rdf-schema#label": ["Isle of Sifnos, Yavuzca"], "http://www.w3.org/2002/07/owl#sameAs": ["http://www.wikidata.org/entity/Q212029"], "http://www.wikidata.org/prop/direct/P1584": ["http://pleiades.stoa.org/places/590049"], "http://www.wikidata.org/prop/direct/P17": ["http://www.wikidata.org/entity/Q41"], "begin": ""}, "geometry": {"type": "Point", "coordinates": [24.6991, 36.97672]}}]}