{"type": "FeatureCollection", "id": "http://imperium.ahlfeldt.se/places/40428", "name": "40428", "features": [{"type": "Feature", "id": "http://data.archaeology.link/data/ancientports/987", "label": "Lucrino, two concrete moles over 200 m long", "dateprops": ["http://purl.org/dc/elements/1.1/created"], "properties": {"http://purl.org/dc/elements/1.1/created": ["2023"], "http://purl.org/dc/elements/1.1/creator": ["http://data.archaeology.link/data/spphaefen/arthur_de_graauw"], "http://purl.org/dc/terms/isReferencedBy": ["https://www2.rgzm.de/navis2/home/frames.htm"], "http://www.opengis.net/ont/geosparql#hasGeometry": ["http://data.archaeology.link/data/ancientports/987_geom"], "http://www.w3.org/1999/02/22-rdf-syntax-ns#type": ["http://www.ancientports.com/ont#Pila"], "http://www.w3.org/2000/01/rdf-schema#label": ["Lucrino, two concrete moles over 200 m long"], "http://www.w3.org/2002/07/owl#sameAs": ["http://www.wikidata.org/entity/Q432545"], "http://www.w3.org/2004/02/skos/core#note": ["Brandon (2008)", "Pagano (2021)"], "http://www.wikidata.org/prop/direct/P1584": ["https://pleiades.stoa.org/places/432915?searchterm=lucrin"], "http://www.wikidata.org/prop/direct/P17": ["Italy West"], "http://www.wikidata.org/prop/direct/P1936": ["http://imperium.ahlfeldt.se/places/40428"], "http://www.wikidata.org/prop/direct/P1958": ["https://www.trismegistos.org/place/32454"], "http://www.wikidata.org/prop/direct/P8068": ["https://topostext.org/place/408141WLuc"]}, "geometry": {"type": "Point", "coordinates": [14.09471, 40.82648]}}]}