{"type": "FeatureCollection", "id": "http://imperium.ahlfeldt.se/places/12317", "name": "12317", "features": [{"type": "Feature", "id": "http://data.archaeology.link/data/ancientports/591", "label": "Roman villa at Le Grand Essart, on R Payre, near Jard sur Mer", "properties": {"http://purl.org/dc/elements/1.1/created": ["2023"], "http://purl.org/dc/elements/1.1/creator": ["http://data.archaeology.link/data/spphaefen/arthur_de_graauw"], "http://www.opengis.net/ont/geosparql#hasGeometry": ["http://data.archaeology.link/data/ancientports/591_geom"], "http://www.w3.org/1999/02/22-rdf-syntax-ns#type": ["http://www.ancientports.com/ont#Harbour"], "http://www.w3.org/2000/01/rdf-schema#label": ["Roman villa at Le Grand Essart, on R Payre, near Jard sur Mer"], "http://www.wikidata.org/prop/direct/P17": ["France West"], "http://www.wikidata.org/prop/direct/P1936": ["http://imperium.ahlfeldt.se/places/12317"]}, "geometry": {"type": "Point", "coordinates": [-1.57759, 46.42824]}}]}