{"type": "FeatureCollection", "id": "http://www.wikidata.org/entity/Q7230819", "name": "Q7230819", "features": [{"type": "Feature", "id": "http://data.archaeology.link/data/ancientports/106_1", "label": "Port Navas, near Gweek, on R Helford (export of tin?)", "properties": {"http://purl.org/dc/elements/1.1/created": ["2023"], "http://purl.org/dc/elements/1.1/creator": ["http://data.archaeology.link/data/spphaefen/arthur_de_graauw"], "http://purl.org/dc/terms/isReferencedBy": ["http://data.archaeology.link/data/ancientports/bib_Wilkes_2004_Iron"], "http://www.ancientports.com/ont#date_min": ["5001"], "http://www.opengis.net/ont/geosparql#hasGeometry": ["http://data.archaeology.link/data/ancientports/106_1_geom"], "http://www.w3.org/1999/02/22-rdf-syntax-ns#type": ["http://www.ancientports.com/ont#Harbour"], "http://www.w3.org/2000/01/rdf-schema#label": ["Port Navas, near Gweek, on R Helford (export of tin?)"], "http://www.w3.org/2002/07/owl#sameAs": ["http://www.wikidata.org/entity/Q7230819"], "http://www.w3.org/2004/02/skos/core#note": ["Wilkes (2004)"], "http://www.wikidata.org/prop/direct/P17": ["http://www.wikidata.org/entity/Q145"]}, "geometry": {"type": "Point", "coordinates": [-5.1408, 50.1055]}}]}