{"type": "FeatureCollection", "id": "https://www.trismegistos.org/place/19656", "name": "19656", "features": [{"type": "Feature", "id": "http://data.archaeology.link/data/ancientports/43_2", "name": "Roman camp near Saint Madoes, on Firth of Tay", "dateprops": ["begin"], "properties": {"http://purl.org/dc/elements/1.1/creator": ["http://data.archaeology.link/data/spphaefen/arthur_de_graauw"], "http://purl.org/dc/terms/isReferencedBy": ["https://ancientmonuments.uk/125651"], "http://purl.org/dc/terms/partOf": ["http://data.archaeology.link/data/ancientports/bib_deGrauw_2013_GeoDB"], "http://www.opengis.net/ont/geosparql#hasGeometry": ["http://data.archaeology.link/data/ancientports/43_2_geom"], "http://www.w3.org/1999/02/22-rdf-syntax-ns#type": ["http://www.ancientports.com/ont#Harbour"], "http://www.w3.org/2000/01/rdf-schema#label": ["Roman camp near Saint Madoes, on Firth of Tay"], "http://www.w3.org/2002/07/owl#sameAs": ["http://www.wikidata.org/entity/Q19719"], "http://www.w3.org/2006/time#hasTime": ["http://data.archaeology.link/data/ancientports/43_2_foundation"], "http://www.wikidata.org/prop/direct/P1584": ["https://pleiades.stoa.org/places/89299"], "http://www.wikidata.org/prop/direct/P17": ["http://www.wikidata.org/entity/Q145"], "http://www.wikidata.org/prop/direct/P1936": ["http://imperium.ahlfeldt.se/places/26288"], "http://www.wikidata.org/prop/direct/P1958": ["https://www.trismegistos.org/place/19656"], "begin": "1001"}, "geometry": {"type": "Point", "coordinates": [-3.2823, 56.3617]}}]}