{"type": "FeatureCollection", "id": "http://www.wikidata.org/entity/Q7228622", "name": "Poole Logboat", "features": [{"type": "Feature", "id": "http://data.archaeology.link/data/ancientports/98", "name": "Hamworthy, near Poole", "dateprops": ["begin"], "properties": {"http://purl.org/dc/elements/1.1/creator": ["http://data.archaeology.link/data/spphaefen/arthur_de_graauw"], "http://purl.org/dc/terms/isReferencedBy": ["http://www.poolemuseum.org.uk/collections/collection-highlights/poole-logboat/"], "http://purl.org/dc/terms/partOf": ["http://data.archaeology.link/data/ancientports/bib_deGrauw_2013_GeoDB"], "http://www.opengis.net/ont/geosparql#hasGeometry": ["http://data.archaeology.link/data/ancientports/98_geom"], "http://www.w3.org/1999/02/22-rdf-syntax-ns#type": ["http://www.ancientports.com/ont#Harbour"], "http://www.w3.org/2000/01/rdf-schema#label": ["Hamworthy, near Poole"], "http://www.w3.org/2002/07/owl#sameAs": ["http://www.wikidata.org/entity/Q7228622"], "http://www.w3.org/2006/time#hasTime": ["http://data.archaeology.link/data/ancientports/98_foundation"], "http://www.wikidata.org/prop/direct/P17": ["http://www.wikidata.org/entity/Q145"], "http://www.wikidata.org/prop/direct/P1936": ["http://imperium.ahlfeldt.se/places/25700"], "begin": "-300"}, "geometry": {"type": "Point", "coordinates": [-2.0014, 50.7095]}}], "numberMatched": 1, "numberReturned": 1, "bbox": [-2.0014, 50.7095, -2.0014, 50.7095], "crs": "http://www.opengis.net/def/crs/OGC/1.3/CRS84"}