{"type": "FeatureCollection", "id": "http://imperium.ahlfeldt.se/places/27524", "name": "27524", "features": [{"type": "Feature", "id": "http://data.archaeology.link/data/ancientports/2805", "label": "Iliksu K\u00f6y\u00fc, near Esenk\u00f6y", "properties": {"http://purl.org/dc/elements/1.1/created": ["2023"], "http://purl.org/dc/elements/1.1/creator": ["http://data.archaeology.link/data/spphaefen/arthur_de_graauw"], "http://www.ancientports.com/ont#date_min": ["-30"], "http://www.opengis.net/ont/geosparql#hasGeometry": ["http://data.archaeology.link/data/ancientports/2805_geom"], "http://www.w3.org/1999/02/22-rdf-syntax-ns#type": ["http://www.ancientports.com/ont#Harbour"], "http://www.w3.org/2000/01/rdf-schema#label": ["Iliksu K\u00f6y\u00fc, near Esenk\u00f6y"], "http://www.w3.org/2002/07/owl#sameAs": ["http://www.wikidata.org/entity/Q65046326"], "http://www.wikidata.org/prop/direct/P1584": ["http://pleiades.stoa.org/places/845030"], "http://www.wikidata.org/prop/direct/P17": ["TR: Black Sea"], "http://www.wikidata.org/prop/direct/P1936": ["http://imperium.ahlfeldt.se/places/27524"]}, "geometry": {"type": "Point", "coordinates": [31.68226, 41.41232]}}]}