{"type": "FeatureCollection", "id": "http://www.wikidata.org/entity/Q242784", "name": "Q242784", "features": [{"type": "Feature", "id": "http://data.archaeology.link/data/ancientports/908_1", "label": "Roman villa at Piazza degli Nereide, Ladispoli", "dateprops": ["http://purl.org/dc/elements/1.1/created"], "properties": {"http://purl.org/dc/elements/1.1/created": ["2023"], "http://purl.org/dc/elements/1.1/creator": ["http://data.archaeology.link/data/spphaefen/arthur_de_graauw"], "http://www.opengis.net/ont/geosparql#hasGeometry": ["http://data.archaeology.link/data/ancientports/908_1_geom"], "http://www.w3.org/1999/02/22-rdf-syntax-ns#type": ["http://www.ancientports.com/ont#VillaMaritima"], "http://www.w3.org/2000/01/rdf-schema#label": ["Roman villa at Piazza degli Nereide, Ladispoli"], "http://www.w3.org/2002/07/owl#sameAs": ["http://www.wikidata.org/entity/Q242784"], "http://www.w3.org/2006/time#hasTime": ["http://data.archaeology.link/data/ancientports/908_1_foundation"], "http://www.wikidata.org/prop/direct/P17": ["Italy West"]}, "geometry": {"type": "Point", "coordinates": [12.081, 41.942]}}]}