{"type": "FeatureCollection", "id": "http://www.wikidata.org/entity/Q1874", "name": "Q1874", "features": [{"type": "Feature", "id": "http://data.archaeology.link/data/ancientports/2541", "label": "Odessa, Prymorskyi Boulevard", "properties": {"http://purl.org/dc/elements/1.1/created": ["2023"], "http://purl.org/dc/elements/1.1/creator": ["http://data.archaeology.link/data/spphaefen/arthur_de_graauw"], "http://www.ancientports.com/ont#date_min": ["-550"], "http://www.opengis.net/ont/geosparql#hasGeometry": ["http://data.archaeology.link/data/ancientports/2541_geom"], "http://www.w3.org/1999/02/22-rdf-syntax-ns#type": ["http://www.ancientports.com/ont#Harbour"], "http://www.w3.org/2000/01/rdf-schema#label": ["Odessa, Prymorskyi Boulevard"], "http://www.w3.org/2002/07/owl#sameAs": ["http://www.wikidata.org/entity/Q1874"], "http://www.w3.org/2004/02/skos/core#note": ["Kozlovskaya (2017)"], "http://www.wikidata.org/prop/direct/P1584": ["http://pleiades.stoa.org/places/226634"], "http://www.wikidata.org/prop/direct/P17": ["Ukraine Black S."], "http://www.wikidata.org/prop/direct/P1936": ["http://imperium.ahlfeldt.se/places/27917"]}, "geometry": {"type": "Point", "coordinates": [30.741, 46.488]}}]}