{"type": "FeatureCollection", "id": "http://www.wikidata.org/entity/Q204439", "name": "El Alamein", "features": [{"type": "Feature", "id": "http://data.archaeology.link/data/ancientports/3948", "name": "", "dateprops": ["begin"], "properties": {"http://purl.org/dc/elements/1.1/creator": ["http://data.archaeology.link/data/spphaefen/arthur_de_graauw"], "http://purl.org/dc/terms/isReferencedBy": ["https://pcma.uw.edu.pl/en/2019/12/13/polish-egyptian-conservation-mission-marina-el-alamein/"], "http://purl.org/dc/terms/partOf": ["http://data.archaeology.link/data/ancientports/bib_deGrauw_2013_GeoDB"], "http://rdfs.org/ns/void#inDataset": ["http://data.archaeology.link/data/ancientports/dataset"], "http://www.opengis.net/ont/geosparql#hasGeometry": ["http://data.archaeology.link/data/ancientports/3948_geom"], "http://www.w3.org/1999/02/22-rdf-syntax-ns#type": ["http://www.ancientports.com/ont#Harbour"], "http://www.w3.org/2000/01/rdf-schema#label": ["Marina el-Alamein"], "http://www.w3.org/2002/07/owl#sameAs": ["http://www.wikidata.org/entity/Q204439"], "http://www.w3.org/2004/02/skos/core#note": ["Daszewski (2008)"], "http://www.w3.org/2006/time#hasTime": ["http://data.archaeology.link/data/ancientports/3948_foundation"], "http://www.wikidata.org/prop/direct/P1584": ["http://pleiades.stoa.org/places/716524"], "http://www.wikidata.org/prop/direct/P17": ["http://www.wikidata.org/entity/Q79"], "http://www.wikidata.org/prop/direct/P1936": ["http://imperium.ahlfeldt.se/places/21709"], "http://www.wikidata.org/prop/direct/P1958": ["https://www.trismegistos.org/place/8554"], "http://www.wikidata.org/prop/direct/P8068": ["https://topostext.org/place/308289UAnt"], "begin": "-330"}, "geometry": {"type": "Point", "coordinates": [29.0118, 30.8257]}}], "numberMatched": 1, "numberReturned": 1, "bbox": [29.0118, 30.8257, 29.0118, 30.8257], "crs": "http://www.opengis.net/def/crs/EPSG/0/4326"}