{"type": "FeatureCollection", "id": "http://www.wikidata.org/entity/Q589347", "name": "Posillipo#Imperial villa", "features": [{"type": "Feature", "id": "http://data.archaeology.link/data/ancientports/994_1", "name": "", "dateprops": [], "properties": {"http://purl.org/dc/elements/1.1/creator": ["http://data.archaeology.link/data/spphaefen/arthur_de_graauw"], "http://purl.org/dc/terms/isReferencedBy": ["http://data.archaeology.link/data/ancientports/bib_Aucelli_2017_Coastal"], "http://purl.org/dc/terms/partOf": ["http://data.archaeology.link/data/ancientports/bib_deGrauw_2013_GeoDB"], "http://rdfs.org/ns/void#inDataset": ["http://data.archaeology.link/data/ancientports/dataset"], "http://www.opengis.net/ont/geosparql#hasGeometry": ["http://data.archaeology.link/data/ancientports/994_1_geom"], "http://www.w3.org/1999/02/22-rdf-syntax-ns#type": ["http://www.ancientports.com/ont#Pila", "http://www.ancientports.com/ont#VillaMaritima"], "http://www.w3.org/2000/01/rdf-schema#label": ["Palazzo degli Spiriti, with pilae"], "http://www.w3.org/2002/07/owl#sameAs": ["http://www.wikidata.org/entity/Q589347"], "http://www.wikidata.org/prop/direct/P17": ["http://www.wikidata.org/entity/Q38"], "begin": ""}, "geometry": {"type": "Point", "coordinates": [14.1917, 40.7934]}}, {"type": "Feature", "id": "http://data.archaeology.link/data/ancientports/995", "name": "", "dateprops": [], "properties": {"http://purl.org/dc/elements/1.1/creator": ["http://data.archaeology.link/data/spphaefen/arthur_de_graauw"], "http://purl.org/dc/terms/isReferencedBy": ["http://data.archaeology.link/data/ancientports/bib_Aucelli_2017_Coastal"], "http://purl.org/dc/terms/partOf": ["http://data.archaeology.link/data/ancientports/bib_deGrauw_2013_GeoDB"], "http://rdfs.org/ns/void#inDataset": ["http://data.archaeology.link/data/ancientports/dataset"], "http://www.opengis.net/ont/geosparql#hasGeometry": ["http://data.archaeology.link/data/ancientports/995_geom"], "http://www.w3.org/1999/02/22-rdf-syntax-ns#type": ["http://www.ancientports.com/ont#Pila", "http://www.ancientports.com/ont#VillaMaritima"], "http://www.w3.org/2000/01/rdf-schema#label": ["Pollion's villa at Porto Marechiaro, with pilae"], "http://www.w3.org/2002/07/owl#sameAs": ["http://www.wikidata.org/entity/Q589347"], "http://www.wikidata.org/prop/direct/P17": ["http://www.wikidata.org/entity/Q38"], "http://www.wikidata.org/prop/direct/P1936": ["http://imperium.ahlfeldt.se/places/24883"], "begin": ""}, "geometry": {"type": "Point", "coordinates": [14.1919, 40.7947]}}, {"type": "Feature", "id": "http://data.archaeology.link/data/ancientports/994", "name": "", "dateprops": [], "properties": {"http://purl.org/dc/elements/1.1/creator": ["http://data.archaeology.link/data/spphaefen/arthur_de_graauw"], "http://purl.org/dc/terms/partOf": ["http://data.archaeology.link/data/ancientports/bib_deGrauw_2013_GeoDB"], "http://rdfs.org/ns/void#inDataset": ["http://data.archaeology.link/data/ancientports/dataset"], "http://www.opengis.net/ont/geosparql#hasGeometry": ["http://data.archaeology.link/data/ancientports/994_geom"], "http://www.w3.org/1999/02/22-rdf-syntax-ns#type": ["http://www.ancientports.com/ont#Pila", "http://www.ancientports.com/ont#Quay", "http://www.ancientports.com/ont#VillaMaritima"], "http://www.w3.org/2000/01/rdf-schema#label": ["Roman villa at Posillipo, protected by row of pilae"], "http://www.w3.org/2002/07/owl#sameAs": ["http://www.wikidata.org/entity/Q589347"], "http://www.wikidata.org/prop/direct/P17": ["http://www.wikidata.org/entity/Q38"], "http://www.wikidata.org/prop/direct/P1936": ["http://imperium.ahlfeldt.se/places/24883"], "begin": ""}, "geometry": {"type": "Point", "coordinates": [14.1883, 40.793]}}], "numberMatched": 3, "numberReturned": 3, "bbox": [14.1883, 40.793, 14.1919, 40.7947], "crs": "http://www.opengis.net/def/crs/EPSG/0/4326"}