{"type": "FeatureCollection", "id": "http://www.wikidata.org/entity/Q180294", "name": "Q180294", "features": [{"type": "Feature", "id": "http://data.archaeology.link/data/ancientports/3503", "label": "Jaffa, archaic port possibly on ancient outlet of R Ayalon, Roman port possibly further downstream due to sedimentation", "properties": {"http://purl.org/dc/elements/1.1/created": ["2023"], "http://purl.org/dc/elements/1.1/creator": ["http://data.archaeology.link/data/spphaefen/arthur_de_graauw"], "http://www.ancientports.com/ont#date_min": ["-1700"], "http://www.opengis.net/ont/geosparql#hasGeometry": ["http://data.archaeology.link/data/ancientports/3503_geom"], "http://www.w3.org/1999/02/22-rdf-syntax-ns#type": ["http://www.ancientports.com/ont#Harbour"], "http://www.w3.org/2000/01/rdf-schema#label": ["Jaffa, archaic port possibly on ancient outlet of R Ayalon, Roman port possibly further downstream due to sedimentation"], "http://www.w3.org/2002/07/owl#sameAs": ["http://www.wikidata.org/entity/Q180294"], "http://www.w3.org/2004/02/skos/core#note": ["Burke (2017)"], "http://www.wikidata.org/prop/direct/P1584": ["http://pleiades.stoa.org/places/687931"], "http://www.wikidata.org/prop/direct/P17": ["Israel"], "http://www.wikidata.org/prop/direct/P1958": ["https://www.trismegistos.org/place/905"]}, "geometry": {"type": "Point", "coordinates": [34.7615, 32.0516]}}]}