{"type": "FeatureCollection", "id": "http://www.wikidata.org/entity/Q21555533", "name": "Keri, Greece", "features": [{"type": "Feature", "id": "http://data.archaeology.link/data/ancientports/2024", "name": "Pitch quarry at Limni Keriou, on the Isle of Zakinthos", "dateprops": ["begin"], "properties": {"http://purl.org/dc/elements/1.1/creator": ["http://data.archaeology.link/data/spphaefen/arthur_de_graauw"], "http://purl.org/dc/terms/partOf": ["http://data.archaeology.link/data/ancientports/bib_deGrauw_2013_GeoDB"], "http://www.opengis.net/ont/geosparql#hasGeometry": ["http://data.archaeology.link/data/ancientports/2024_geom"], "http://www.w3.org/1999/02/22-rdf-syntax-ns#type": ["http://www.ancientports.com/ont#Harbour"], "http://www.w3.org/2000/01/rdf-schema#label": ["Pitch quarry at Limni Keriou, on the Isle of Zakinthos"], "http://www.w3.org/2002/07/owl#sameAs": ["http://www.wikidata.org/entity/Q21555533"], "http://www.w3.org/2006/time#hasTime": ["http://data.archaeology.link/data/ancientports/2024_foundation"], "http://www.wikidata.org/prop/direct/P1584": ["http://pleiades.stoa.org/places/530981"], "http://www.wikidata.org/prop/direct/P17": ["http://www.wikidata.org/entity/Q41"], "http://www.wikidata.org/prop/direct/P1936": ["http://imperium.ahlfeldt.se/places/38161"], "http://www.wikidata.org/prop/direct/P8068": ["https://topostext.org/place/377208QLim"], "begin": "-550"}, "geometry": {"type": "Point", "coordinates": [20.8344, 37.684]}}], "numberMatched": 1, "numberReturned": 1, "bbox": [20.8344, 37.684, 20.8344, 37.684], "crs": "http://www.opengis.net/def/crs/OGC/1.3/CRS84"}