{"type": "FeatureCollection", "id": "http://pleiades.stoa.org/places/197097", "name": "197097", "features": [{"type": "Feature", "id": "http://data.archaeology.link/data/ancientports/1508", "label": "Kotor, Cattaro", "dateprops": ["http://purl.org/dc/elements/1.1/created", "http://www.ancientports.com/ont#date_min"], "properties": {"http://purl.org/dc/elements/1.1/created": ["2023"], "http://purl.org/dc/elements/1.1/creator": ["http://data.archaeology.link/data/spphaefen/arthur_de_graauw"], "http://www.ancientports.com/ont#date_min": ["-330"], "http://www.opengis.net/ont/geosparql#hasGeometry": ["http://data.archaeology.link/data/ancientports/1508_geom"], "http://www.w3.org/1999/02/22-rdf-syntax-ns#type": ["http://www.ancientports.com/ont#Harbour"], "http://www.w3.org/2000/01/rdf-schema#label": ["Kotor, Cattaro"], "http://www.w3.org/2002/07/owl#sameAs": ["http://www.wikidata.org/entity/Q171080"], "http://www.wikidata.org/prop/direct/P1584": ["http://pleiades.stoa.org/places/197097"], "http://www.wikidata.org/prop/direct/P17": ["http://www.wikidata.org/entity/Q236"], "http://www.wikidata.org/prop/direct/P1936": ["http://imperium.ahlfeldt.se/places/21965"], "http://www.wikidata.org/prop/direct/P1958": ["https://www.trismegistos.org/place/29619"]}, "geometry": {"type": "Point", "coordinates": [18.7671, 42.4238]}}]}