{"type": "FeatureCollection", "id": "https://www.trismegistos.org/place/42515", "name": "42515", "features": [{"type": "Feature", "id": "http://data.archaeology.link/data/ancientports/1206", "label": "Porto Vulcano, on the isle of Vulcano", "dateprops": ["http://purl.org/dc/elements/1.1/created"], "properties": {"http://purl.org/dc/elements/1.1/created": ["2023"], "http://purl.org/dc/elements/1.1/creator": ["http://data.archaeology.link/data/spphaefen/arthur_de_graauw"], "http://www.opengis.net/ont/geosparql#hasGeometry": ["http://data.archaeology.link/data/ancientports/1206_geom"], "http://www.w3.org/1999/02/22-rdf-syntax-ns#type": ["http://www.ancientports.com/ont#Harbour"], "http://www.w3.org/2000/01/rdf-schema#label": ["Porto Vulcano, on the isle of Vulcano"], "http://www.w3.org/2002/07/owl#sameAs": ["http://www.wikidata.org/entity/Q207323"], "http://www.w3.org/2004/02/skos/core#note": ["ARCHEOLOGIA SUBACQUEA 2: Isole Eolie (Supplemento al n. 29", "ARCHEOLOGIA SUBACQUEA 2: Isole Eolie (Supplemento al n. 29, 1985)"], "http://www.w3.org/2006/time#hasTime": ["http://data.archaeology.link/data/ancientports/1206_foundation"], "http://www.wikidata.org/prop/direct/P1584": ["http://pleiades.stoa.org/places/462242"], "http://www.wikidata.org/prop/direct/P17": ["Italy Sicily"], "http://www.wikidata.org/prop/direct/P1936": ["http://imperium.ahlfeldt.se/places/41246"], "http://www.wikidata.org/prop/direct/P1958": ["https://www.trismegistos.org/place/42515"], "http://www.wikidata.org/prop/direct/P8068": ["https://topostext.org/place/384150IHie"]}, "geometry": {"type": "Point", "coordinates": [14.96645, 38.41636]}}]}