{"type": "FeatureCollection", "id": "https://pleiades.stoa.org/places/40218", "name": "40218", "features": [{"type": "Feature", "id": "http://data.archaeology.link/data/ancientports/3622", "label": "Howakil bay, Hauakil bay, near Ghelaelo, with Harena, Arena island", "properties": {"http://purl.org/dc/elements/1.1/created": ["2023"], "http://purl.org/dc/elements/1.1/creator": ["http://data.archaeology.link/data/spphaefen/arthur_de_graauw"], "http://www.opengis.net/ont/geosparql#hasGeometry": ["http://data.archaeology.link/data/ancientports/3622_geom"], "http://www.w3.org/1999/02/22-rdf-syntax-ns#type": ["http://www.ancientports.com/ont#Harbour"], "http://www.w3.org/2000/01/rdf-schema#label": ["Howakil bay, Hauakil bay, near Ghelaelo, with Harena, Arena island"], "http://www.wikidata.org/prop/direct/P1584": ["https://pleiades.stoa.org/places/40218"], "http://www.wikidata.org/prop/direct/P17": ["Eritrea"], "http://www.wikidata.org/prop/direct/P1958": ["https://www.trismegistos.org/place/5747"]}, "geometry": {"type": "Point", "coordinates": [40.065, 15.19]}}]}