{"type": "FeatureCollection", "id": "http://imperium.ahlfeldt.se/places/16737", "name": "16737", "features": [{"type": "Feature", "id": "http://data.archaeology.link/data/ancientports/1069", "name": "Locri", "dateprops": ["begin"], "properties": {"http://purl.org/dc/elements/1.1/creator": ["http://data.archaeology.link/data/spphaefen/arthur_de_graauw"], "http://purl.org/dc/terms/partOf": ["http://data.archaeology.link/data/ancientports/bib_deGrauw_2013_GeoDB"], "http://www.opengis.net/ont/geosparql#hasGeometry": ["http://data.archaeology.link/data/ancientports/1069_geom"], "http://www.w3.org/1999/02/22-rdf-syntax-ns#type": ["http://www.ancientports.com/ont#Harbour"], "http://www.w3.org/2000/01/rdf-schema#label": ["Locri"], "http://www.w3.org/2002/07/owl#sameAs": ["http://www.wikidata.org/entity/Q54619"], "http://www.w3.org/2006/time#hasTime": ["http://data.archaeology.link/data/ancientports/1069_foundation"], "http://www.wikidata.org/prop/direct/P1584": ["http://pleiades.stoa.org/places/452369"], "http://www.wikidata.org/prop/direct/P17": ["http://www.wikidata.org/entity/Q38"], "http://www.wikidata.org/prop/direct/P1936": ["http://imperium.ahlfeldt.se/places/16737"], "http://www.wikidata.org/prop/direct/P1958": ["https://www.trismegistos.org/place/33081"], "http://www.wikidata.org/prop/direct/P8068": ["https://topostext.org/place/382162PLoc"], "begin": "-750"}, "geometry": {"type": "Point", "coordinates": [16.2368, 38.2077]}}], "numberMatched": 1, "numberReturned": 1, "bbox": [16.2368, 38.2077, 16.2368, 38.2077], "crs": "http://www.opengis.net/def/crs/EPSG/0/4326"}