{"type": "FeatureCollection", "id": "http://imperium.ahlfeldt.se/places/26968", "name": "26968", "features": [{"type": "Feature", "id": "http://data.archaeology.link/data/ancientports/4298", "label": "el-Marsa, Ouadmarsa, Marsa Musa, fish processing factory", "properties": {"http://purl.org/dc/elements/1.1/created": ["2023"], "http://purl.org/dc/elements/1.1/creator": ["http://data.archaeology.link/data/spphaefen/arthur_de_graauw"], "http://www.ancientports.com/ont#date_min": ["-30"], "http://www.opengis.net/ont/geosparql#hasGeometry": ["http://data.archaeology.link/data/ancientports/4298_geom"], "http://www.w3.org/1999/02/22-rdf-syntax-ns#type": ["http://www.ancientports.com/ont#Harbour"], "http://www.w3.org/2000/01/rdf-schema#label": ["el-Marsa, Ouadmarsa, Marsa Musa, fish processing factory"], "http://www.w3.org/2004/02/skos/core#note": ["Erbati (2004)"], "http://www.wikidata.org/prop/direct/P1584": ["http://pleiades.stoa.org/places/275671"], "http://www.wikidata.org/prop/direct/P17": ["http://www.wikidata.org/entity/Q1028"], "http://www.wikidata.org/prop/direct/P1936": ["http://imperium.ahlfeldt.se/places/26968"]}, "geometry": {"type": "Point", "coordinates": [-5.44673, 35.90248]}}]}