{"type": "FeatureCollection", "id": "https://topostext.org/place/400237PAig", "name": "400237PAig", "features": [{"type": "Feature", "id": "http://data.archaeology.link/data/ancientports/1795", "label": "near Glarokavos", "dateprops": [], "properties": {"http://purl.org/dc/elements/1.1/created": ["2023"], "http://purl.org/dc/elements/1.1/creator": ["http://data.archaeology.link/data/spphaefen/arthur_de_graauw"], "http://www.opengis.net/ont/geosparql#hasGeometry": ["http://data.archaeology.link/data/ancientports/1795_geom"], "http://www.w3.org/1999/02/22-rdf-syntax-ns#type": ["http://www.ancientports.com/ont#Harbour"], "http://www.w3.org/2000/01/rdf-schema#label": ["near Glarokavos"], "http://www.w3.org/2002/07/owl#sameAs": ["http://www.wikidata.org/entity/Q16559458"], "http://www.w3.org/2006/time#hasTime": ["http://data.archaeology.link/data/ancientports/1795_foundation"], "http://www.wikidata.org/prop/direct/P1584": ["http://pleiades.stoa.org/places/501335"], "http://www.wikidata.org/prop/direct/P17": ["http://www.wikidata.org/entity/Q41"], "http://www.wikidata.org/prop/direct/P1936": ["http://imperium.ahlfeldt.se/places/32291"], "http://www.wikidata.org/prop/direct/P1958": ["https://www.trismegistos.org/place/8396"], "http://www.wikidata.org/prop/direct/P8068": ["https://topostext.org/place/400237PAig"]}, "geometry": {"type": "Point", "coordinates": [23.66229, 39.97967]}}]}