{"type": "FeatureCollection", "id": "http://pleiades.stoa.org/places/501637", "name": "501637", "features": [{"type": "Feature", "id": "http://data.archaeology.link/data/ancientports/1794", "label": "Chrusu, Chrousou, near Paliouri, in the gulf of Kassandra =  Toronic gulf", "dateprops": ["http://purl.org/dc/elements/1.1/created", "http://www.ancientports.com/ont#date_min"], "properties": {"http://purl.org/dc/elements/1.1/created": ["2023"], "http://purl.org/dc/elements/1.1/creator": ["http://data.archaeology.link/data/spphaefen/arthur_de_graauw"], "http://www.ancientports.com/ont#date_min": ["-550"], "http://www.opengis.net/ont/geosparql#hasGeometry": ["http://data.archaeology.link/data/ancientports/1794_geom"], "http://www.w3.org/1999/02/22-rdf-syntax-ns#type": ["http://www.ancientports.com/ont#Harbour"], "http://www.w3.org/2000/01/rdf-schema#label": ["Chrusu, Chrousou, near Paliouri, in the gulf of Kassandra =  Toronic gulf"], "http://www.w3.org/2002/07/owl#sameAs": ["http://www.wikidata.org/entity/Q54865144"], "http://www.wikidata.org/prop/direct/P1584": ["http://pleiades.stoa.org/places/501637"], "http://www.wikidata.org/prop/direct/P17": ["GR: North-East"], "http://www.wikidata.org/prop/direct/P1936": ["http://imperium.ahlfeldt.se/places/43689"], "http://www.wikidata.org/prop/direct/P8068": ["https://topostext.org/place/398238PThe"]}, "geometry": {"type": "Point", "coordinates": [23.6766, 39.9609]}}]}