{"type": "FeatureCollection", "id": "http://www.wikidata.org/entity/Q645041", "name": "Q645041", "features": [{"type": "Feature", "id": "http://data.archaeology.link/data/ancientports/996", "label": "Castell del'Ovo, at Pizzofalcone in Naples", "dateprops": [], "properties": {"http://purl.org/dc/elements/1.1/created": ["2023"], "http://purl.org/dc/elements/1.1/creator": ["http://data.archaeology.link/data/spphaefen/arthur_de_graauw"], "http://www.opengis.net/ont/geosparql#hasGeometry": ["http://data.archaeology.link/data/ancientports/996_geom"], "http://www.w3.org/1999/02/22-rdf-syntax-ns#type": ["http://www.ancientports.com/ont#VillaMaritima"], "http://www.w3.org/2000/01/rdf-schema#label": ["Castell del'Ovo, at Pizzofalcone in Naples"], "http://www.w3.org/2002/07/owl#sameAs": ["http://www.wikidata.org/entity/Q645041"], "http://www.w3.org/2004/02/skos/core#note": ["Donadio (2019)"], "http://www.wikidata.org/prop/direct/P17": ["http://www.wikidata.org/entity/Q38"]}, "geometry": {"type": "Point", "coordinates": [14.2481, 40.8271]}}]}