{"type": "FeatureCollection", "id": "https://topostext.org/place/375216XKle", "name": "375216XKle", "features": [{"type": "Feature", "id": "http://data.archaeology.link/data/ancientports/1946", "label": "Kleidhi, Klidi", "dateprops": ["http://purl.org/dc/elements/1.1/created", "http://www.ancientports.com/ont#date_min"], "properties": {"http://purl.org/dc/elements/1.1/created": ["2023"], "http://purl.org/dc/elements/1.1/creator": ["http://data.archaeology.link/data/spphaefen/arthur_de_graauw"], "http://www.ancientports.com/ont#date_min": ["-2500"], "http://www.opengis.net/ont/geosparql#hasGeometry": ["http://data.archaeology.link/data/ancientports/1946_geom"], "http://www.w3.org/1999/02/22-rdf-syntax-ns#type": ["http://www.ancientports.com/ont#Harbour"], "http://www.w3.org/2000/01/rdf-schema#label": ["Kleidhi, Klidi"], "http://www.w3.org/2004/02/skos/core#note": ["Kraft (2005)"], "http://www.wikidata.org/prop/direct/P17": ["GR: Pelop"], "http://www.wikidata.org/prop/direct/P8068": ["https://topostext.org/place/375216XKle"]}, "geometry": {"type": "Point", "coordinates": [21.5911, 37.5304]}}]}