{"type": "FeatureCollection", "id": "http://pleiades.stoa.org/places/472110", "name": "472110", "features": [{"type": "Feature", "id": "http://data.archaeology.link/data/ancientports/734", "label": "Bonifacio, Araguina-Sennola, Monte Leone", "dateprops": ["http://purl.org/dc/elements/1.1/created", "http://www.ancientports.com/ont#date_min"], "properties": {"http://purl.org/dc/elements/1.1/created": ["2023"], "http://purl.org/dc/elements/1.1/creator": ["http://data.archaeology.link/data/spphaefen/arthur_de_graauw"], "http://www.ancientports.com/ont#date_min": ["-30"], "http://www.opengis.net/ont/geosparql#hasGeometry": ["http://data.archaeology.link/data/ancientports/734_geom"], "http://www.w3.org/1999/02/22-rdf-syntax-ns#type": ["http://www.ancientports.com/ont#Harbour"], "http://www.w3.org/2000/01/rdf-schema#label": ["Bonifacio, Araguina-Sennola, Monte Leone"], "http://www.w3.org/2002/07/owl#sameAs": ["http://www.wikidata.org/entity/Q204051"], "http://www.wikidata.org/prop/direct/P1584": ["http://pleiades.stoa.org/places/472110"], "http://www.wikidata.org/prop/direct/P17": ["France Corsica"], "http://www.wikidata.org/prop/direct/P1936": ["http://imperium.ahlfeldt.se/places/31223"]}, "geometry": {"type": "Point", "coordinates": [9.16344, 41.38829]}}]}