{"type": "FeatureCollection", "id": "http://imperium.ahlfeldt.se/places/22664", "name": "22664", "features": [{"type": "Feature", "id": "http://data.archaeology.link/data/ancientports/3349", "label": "G\u00fcneysu K\u00f6y\u00fc, near Softa Kalesi", "dateprops": ["http://purl.org/dc/elements/1.1/created", "http://www.ancientports.com/ont#date_min"], "properties": {"http://purl.org/dc/elements/1.1/created": ["2023"], "http://purl.org/dc/elements/1.1/creator": ["http://data.archaeology.link/data/spphaefen/arthur_de_graauw"], "http://www.ancientports.com/ont#date_min": ["-330"], "http://www.opengis.net/ont/geosparql#hasGeometry": ["http://data.archaeology.link/data/ancientports/3349_geom"], "http://www.w3.org/1999/02/22-rdf-syntax-ns#type": ["http://www.ancientports.com/ont#Harbour"], "http://www.w3.org/2000/01/rdf-schema#label": ["G\u00fcneysu K\u00f6y\u00fc, near Softa Kalesi"], "http://www.w3.org/2002/07/owl#sameAs": ["http://www.wikidata.org/entity/Q4796558"], "http://www.wikidata.org/prop/direct/P1584": ["http://pleiades.stoa.org/places/648571"], "http://www.wikidata.org/prop/direct/P17": ["TR: South"], "http://www.wikidata.org/prop/direct/P1936": ["http://imperium.ahlfeldt.se/places/22664"], "http://www.wikidata.org/prop/direct/P1958": ["https://www.trismegistos.org/place/321"], "http://www.wikidata.org/prop/direct/P8068": ["https://topostext.org/place/361330UArs"]}, "geometry": {"type": "Point", "coordinates": [33.022, 36.093]}}]}