{"type": "FeatureCollection", "id": "https://www.trismegistos.org/place/29452", "name": "29452", "features": [{"type": "Feature", "id": "http://data.archaeology.link/data/ancientports/1408", "label": "Rab, on the isle of Rab", "properties": {"http://purl.org/dc/elements/1.1/created": ["2023"], "http://purl.org/dc/elements/1.1/creator": ["http://data.archaeology.link/data/spphaefen/arthur_de_graauw"], "http://www.ancientports.com/ont#date_min": ["-550"], "http://www.opengis.net/ont/geosparql#hasGeometry": ["http://data.archaeology.link/data/ancientports/1408_geom"], "http://www.w3.org/1999/02/22-rdf-syntax-ns#type": ["http://www.ancientports.com/ont#Harbour"], "http://www.w3.org/2000/01/rdf-schema#label": ["Rab, on the isle of Rab"], "http://www.w3.org/2002/07/owl#sameAs": ["http://www.wikidata.org/entity/Q13279"], "http://www.wikidata.org/prop/direct/P1584": ["http://pleiades.stoa.org/places/197134"], "http://www.wikidata.org/prop/direct/P17": ["http://www.wikidata.org/entity/Q224"], "http://www.wikidata.org/prop/direct/P1936": ["http://imperium.ahlfeldt.se/places/13856"], "http://www.wikidata.org/prop/direct/P1958": ["https://www.trismegistos.org/place/29452"]}, "geometry": {"type": "Point", "coordinates": [14.7619, 44.7568]}}]}