{"type": "FeatureCollection", "id": "https://www.trismegistos.org/place/1662", "name": "1662", "features": [{"type": "Feature", "id": "http://data.archaeology.link/data/ancientports/3872", "label": "Tell el-Farama", "dateprops": ["http://purl.org/dc/elements/1.1/created"], "properties": {"http://purl.org/dc/elements/1.1/created": ["2023"], "http://purl.org/dc/elements/1.1/creator": ["http://data.archaeology.link/data/spphaefen/arthur_de_graauw"], "http://purl.org/dc/terms/isReferencedBy": ["https://pcma.uw.edu.pl/en/2019/02/10/pelusium-tell-farama/"], "http://www.opengis.net/ont/geosparql#hasGeometry": ["http://data.archaeology.link/data/ancientports/3872_geom"], "http://www.w3.org/1999/02/22-rdf-syntax-ns#type": ["http://www.ancientports.com/ont#Harbour"], "http://www.w3.org/2000/01/rdf-schema#label": ["Tell el-Farama"], "http://www.w3.org/2002/07/owl#sameAs": ["http://www.wikidata.org/entity/Q1145715"], "http://www.w3.org/2004/02/skos/core#note": ["Chartier-Raymond (1993)", "Snape (2014:42)"], "http://www.w3.org/2006/time#hasTime": ["http://data.archaeology.link/data/ancientports/3872_foundation"], "http://www.wikidata.org/prop/direct/P1584": ["http://pleiades.stoa.org/places/727192"], "http://www.wikidata.org/prop/direct/P17": ["Egypt: Med Sea"], "http://www.wikidata.org/prop/direct/P1936": ["http://imperium.ahlfeldt.se/places/21695"], "http://www.wikidata.org/prop/direct/P1958": ["https://www.trismegistos.org/place/1662"], "http://www.wikidata.org/prop/direct/P8068": ["https://topostext.org/place/310325UPel"]}, "geometry": {"type": "Point", "coordinates": [32.5496, 31.0377]}}]}