{"type": "FeatureCollection", "id": "http://www.wikidata.org/entity/Q64825084", "name": "Q64825084", "features": [{"type": "Feature", "id": "http://data.archaeology.link/data/ancientports/3113_1", "label": "Roman villa between Altinoluk and Avcilar", "properties": {"http://purl.org/dc/elements/1.1/created": ["2023"], "http://purl.org/dc/elements/1.1/creator": ["http://data.archaeology.link/data/spphaefen/arthur_de_graauw"], "http://www.opengis.net/ont/geosparql#hasGeometry": ["http://data.archaeology.link/data/ancientports/3113_1_geom"], "http://www.w3.org/1999/02/22-rdf-syntax-ns#type": ["http://www.ancientports.com/ont#Harbour"], "http://www.w3.org/2000/01/rdf-schema#label": ["Roman villa between Altinoluk and Avcilar"], "http://www.w3.org/2002/07/owl#sameAs": ["http://www.wikidata.org/entity/Q64825084"], "http://www.wikidata.org/prop/direct/P1584": ["https://pleiades.stoa.org/places/550460"], "http://www.wikidata.org/prop/direct/P17": ["TR: West"], "http://www.wikidata.org/prop/direct/P1958": ["https://www.trismegistos.org/place/16242"]}, "geometry": {"type": "Point", "coordinates": [26.7862, 39.5716]}}]}