{"type": "FeatureCollection", "id": "http://imperium.ahlfeldt.se/places/31286", "name": "31286", "features": [{"type": "Feature", "id": "http://data.archaeology.link/data/ancientports/347", "name": "Tarifa", "dateprops": ["begin"], "properties": {"http://purl.org/dc/elements/1.1/created": ["2023"], "http://purl.org/dc/elements/1.1/creator": ["http://data.archaeology.link/data/spphaefen/arthur_de_graauw"], "http://www.opengis.net/ont/geosparql#hasGeometry": ["http://data.archaeology.link/data/ancientports/347_geom"], "http://www.w3.org/1999/02/22-rdf-syntax-ns#type": ["http://www.ancientports.com/ont#Harbour"], "http://www.w3.org/2000/01/rdf-schema#label": ["Tarifa"], "http://www.w3.org/2002/07/owl#sameAs": ["http://www.wikidata.org/entity/Q222702"], "http://www.w3.org/2006/time#hasTime": ["http://data.archaeology.link/data/ancientports/347_foundation"], "http://www.wikidata.org/prop/direct/P1584": ["http://pleiades.stoa.org/places/256293"], "http://www.wikidata.org/prop/direct/P17": ["http://www.wikidata.org/entity/Q29"], "http://www.wikidata.org/prop/direct/P1936": ["http://imperium.ahlfeldt.se/places/31286"], "http://www.wikidata.org/prop/direct/P1958": ["https://www.trismegistos.org/place/26602"], "begin": "-330"}, "geometry": {"type": "Point", "coordinates": [-5.60628, 36.0058]}}, {"type": "Feature", "id": "http://data.archaeology.link/data/ancientports/346", "name": "Valdevaqueros, uncertain location near the estuary of R Valle", "dateprops": ["begin"], "properties": {"http://purl.org/dc/elements/1.1/created": ["2023"], "http://purl.org/dc/elements/1.1/creator": ["http://data.archaeology.link/data/spphaefen/arthur_de_graauw"], "http://www.opengis.net/ont/geosparql#hasGeometry": ["http://data.archaeology.link/data/ancientports/346_geom"], "http://www.w3.org/1999/02/22-rdf-syntax-ns#type": ["http://www.ancientports.com/ont#Harbour"], "http://www.w3.org/2000/01/rdf-schema#label": ["Valdevaqueros, uncertain location near the estuary of R Valle"], "http://www.w3.org/2006/time#hasTime": ["http://data.archaeology.link/data/ancientports/346_foundation"], "http://www.wikidata.org/prop/direct/P1584": ["http://pleiades.stoa.org/places/256293"], "http://www.wikidata.org/prop/direct/P17": ["http://www.wikidata.org/entity/Q29"], "http://www.wikidata.org/prop/direct/P1936": ["http://imperium.ahlfeldt.se/places/31286"], "http://www.wikidata.org/prop/direct/P1958": ["https://www.trismegistos.org/place/26602"], "begin": "-330"}, "geometry": {"type": "Point", "coordinates": [-5.68985, 36.07074]}}]}