{"type": "FeatureCollection", "id": "https://topostext.org/place/373234XEpi", "name": "373234XEpi", "features": [{"type": "Feature", "id": "http://data.archaeology.link/data/ancientports/1875_1", "name": "Port of Episkopi, on the isle of Idra", "dateprops": ["begin"], "properties": {"http://purl.org/dc/elements/1.1/created": ["2023"], "http://purl.org/dc/elements/1.1/creator": ["http://data.archaeology.link/data/spphaefen/arthur_de_graauw"], "http://www.opengis.net/ont/geosparql#hasGeometry": ["http://data.archaeology.link/data/ancientports/1875_1_geom"], "http://www.w3.org/1999/02/22-rdf-syntax-ns#type": ["http://www.ancientports.com/ont#Harbour"], "http://www.w3.org/2000/01/rdf-schema#label": ["Port of Episkopi, on the isle of Idra"], "http://www.w3.org/2006/time#hasTime": ["http://data.archaeology.link/data/ancientports/1875_1_foundation"], "http://www.wikidata.org/prop/direct/P17": ["http://www.wikidata.org/entity/Q41"], "http://www.wikidata.org/prop/direct/P1958": ["https://www.trismegistos.org/place/37921"], "http://www.wikidata.org/prop/direct/P8068": ["https://topostext.org/place/373234XEpi"], "begin": "-3000"}, "geometry": {"type": "Point", "coordinates": [23.4393, 37.3117]}}]}