{"type": "FeatureCollection", "id": "http://www.wikidata.org/entity/Q106709661", "name": "Q106709661", "features": [{"type": "Feature", "id": "http://data.archaeology.link/data/ancientports/129_1", "label": "Pen Dinas, Dinas Maelor oppidum, Ceredigion, on R Ystwyth", "dateprops": ["http://purl.org/dc/elements/1.1/created", "http://www.ancientports.com/ont#date_min"], "properties": {"http://purl.org/dc/elements/1.1/created": ["2023"], "http://purl.org/dc/elements/1.1/creator": ["http://data.archaeology.link/data/spphaefen/arthur_de_graauw"], "http://purl.org/dc/terms/isReferencedBy": ["https://www.megalithic.co.uk/article.php?sid=5931"], "http://www.ancientports.com/ont#date_min": ["-500"], "http://www.opengis.net/ont/geosparql#hasGeometry": ["http://data.archaeology.link/data/ancientports/129_1_geom"], "http://www.w3.org/1999/02/22-rdf-syntax-ns#type": ["http://www.ancientports.com/ont#Harbour"], "http://www.w3.org/2000/01/rdf-schema#label": ["Pen Dinas, Dinas Maelor oppidum, Ceredigion, on R Ystwyth"], "http://www.w3.org/2002/07/owl#sameAs": ["http://www.wikidata.org/entity/Q106709661"], "http://www.wikidata.org/prop/direct/P17": ["http://www.wikidata.org/entity/Q145"]}, "geometry": {"type": "Point", "coordinates": [-4.082, 52.4018]}}]}