{"type": "FeatureCollection", "id": "http://www.wikidata.org/entity/Q2896085", "name": "Q2896085", "features": [{"type": "Feature", "id": "http://data.archaeology.link/data/ancientports/3483", "label": "Atlit-Yam, submerged Neolithic settlement at 12 m depth, in front of outlet of R Oren", "properties": {"http://purl.org/dc/elements/1.1/created": ["2023"], "http://purl.org/dc/elements/1.1/creator": ["http://data.archaeology.link/data/spphaefen/arthur_de_graauw"], "http://www.ancientports.com/ont#date_min": ["-6500"], "http://www.opengis.net/ont/geosparql#hasGeometry": ["http://data.archaeology.link/data/ancientports/3483_geom"], "http://www.w3.org/1999/02/22-rdf-syntax-ns#type": ["http://www.ancientports.com/ont#Harbour"], "http://www.w3.org/2000/01/rdf-schema#label": ["Atlit-Yam, submerged Neolithic settlement at 12 m depth, in front of outlet of R Oren"], "http://www.w3.org/2002/07/owl#sameAs": ["http://www.wikidata.org/entity/Q2896085"], "http://www.w3.org/2004/02/skos/core#note": ["Galili (2018)"], "http://www.wikidata.org/prop/direct/P17": ["Israel"]}, "geometry": {"type": "Point", "coordinates": [34.93515, 32.7108]}}]}