{"type": "FeatureCollection", "id": "http://pleiades.stoa.org/places/599738", "name": "599738", "features": [{"type": "Feature", "id": "http://data.archaeology.link/data/ancientports/3216", "label": "Akce K\u00f6y", "properties": {"http://purl.org/dc/elements/1.1/created": ["2023"], "http://purl.org/dc/elements/1.1/creator": ["http://data.archaeology.link/data/spphaefen/arthur_de_graauw"], "http://www.ancientports.com/ont#date_min": ["-30"], "http://www.opengis.net/ont/geosparql#hasGeometry": ["http://data.archaeology.link/data/ancientports/3216_geom"], "http://www.w3.org/1999/02/22-rdf-syntax-ns#type": ["http://www.ancientports.com/ont#Harbour"], "http://www.w3.org/2000/01/rdf-schema#label": ["Akce K\u00f6y"], "http://www.w3.org/2002/07/owl#sameAs": ["http://www.wikidata.org/entity/Q65065317"], "http://www.wikidata.org/prop/direct/P1584": ["http://pleiades.stoa.org/places/599738"], "http://www.wikidata.org/prop/direct/P17": ["TR: West"]}, "geometry": {"type": "Point", "coordinates": [27.2735, 37.0086]}}]}