{"type": "FeatureCollection", "id": "http://pleiades.stoa.org/places/462283", "name": "462283", "features": [{"type": "Feature", "id": "http://data.archaeology.link/data/ancientports/1205", "name": "Sottomonastero, on the isle of Lipari", "dateprops": ["begin"], "properties": {"http://purl.org/dc/elements/1.1/creator": ["http://data.archaeology.link/data/spphaefen/arthur_de_graauw"], "http://purl.org/dc/terms/isReferencedBy": ["http://www.aeolianislandsvacations.com/history-and-archaeology"], "http://purl.org/dc/terms/partOf": ["http://data.archaeology.link/data/ancientports/bib_deGrauw_2013_GeoDB"], "http://www.opengis.net/ont/geosparql#hasGeometry": ["http://data.archaeology.link/data/ancientports/1205_geom"], "http://www.w3.org/1999/02/22-rdf-syntax-ns#type": ["http://www.ancientports.com/ont#Harbour"], "http://www.w3.org/2000/01/rdf-schema#label": ["Sottomonastero, on the isle of Lipari"], "http://www.w3.org/2002/07/owl#sameAs": ["http://www.wikidata.org/entity/Q496389"], "http://www.w3.org/2004/02/skos/core#note": ["ARCHEOLOGIA SUBACQUEA 2: Isole Eolie (Supplemento al n. 29", "ARCHEOLOGIA SUBACQUEA 2: Isole Eolie (Supplemento al n. 29, 1985)", "La Rocca (2021)"], "http://www.w3.org/2006/time#hasTime": ["http://data.archaeology.link/data/ancientports/1205_foundation"], "http://www.wikidata.org/prop/direct/P1584": ["http://pleiades.stoa.org/places/462283"], "http://www.wikidata.org/prop/direct/P17": ["http://www.wikidata.org/entity/Q38"], "http://www.wikidata.org/prop/direct/P1936": ["http://imperium.ahlfeldt.se/places/16885"], "http://www.wikidata.org/prop/direct/P1958": ["https://www.trismegistos.org/place/22311"], "http://www.wikidata.org/prop/direct/P8068": ["https://topostext.org/place/385150PLip"], "begin": "-1500"}, "geometry": {"type": "Point", "coordinates": [14.9568, 38.4717]}}], "numberMatched": 1, "numberReturned": 1, "bbox": [14.9568, 38.4717, 14.9568, 38.4717], "crs": "http://www.opengis.net/def/crs/EPSG/0/4326"}