{"type": "FeatureCollection", "id": "http://www.wikidata.org/entity/Q117148037", "name": "Q117148037", "features": [{"type": "Feature", "id": "http://data.archaeology.link/data/ancientports/2776", "label": "Akliman", "properties": {"http://purl.org/dc/elements/1.1/created": ["2023"], "http://purl.org/dc/elements/1.1/creator": ["http://data.archaeology.link/data/spphaefen/arthur_de_graauw"], "http://www.ancientports.com/ont#date_min": ["-550"], "http://www.opengis.net/ont/geosparql#hasGeometry": ["http://data.archaeology.link/data/ancientports/2776_geom"], "http://www.w3.org/1999/02/22-rdf-syntax-ns#type": ["http://www.ancientports.com/ont#Harbour"], "http://www.w3.org/2000/01/rdf-schema#label": ["Akliman"], "http://www.w3.org/2002/07/owl#sameAs": ["http://www.wikidata.org/entity/Q117148037"], "http://www.w3.org/2004/02/skos/core#note": ["Dan (2009)"], "http://www.wikidata.org/prop/direct/P1584": ["http://pleiades.stoa.org/places/844865"], "http://www.wikidata.org/prop/direct/P17": ["TR: Black Sea"], "http://www.wikidata.org/prop/direct/P1958": ["https://www.trismegistos.org/place/61025"]}, "geometry": {"type": "Point", "coordinates": [35.05828, 42.05003]}}]}