{"type": "FeatureCollection", "id": "http://www.wikidata.org/entity/Q826118", "name": "Khor Rori", "features": [{"type": "Feature", "id": "http://data.archaeology.link/data/ancientports/3760", "name": "", "dateprops": ["begin"], "properties": {"http://purl.org/dc/elements/1.1/creator": ["http://data.archaeology.link/data/spphaefen/arthur_de_graauw"], "http://purl.org/dc/terms/isReferencedBy": ["http://data.archaeology.link/data/ancientports/bib_Avanzini_2014_Un", "http://whc.unesco.org/en/list/1010"], "http://purl.org/dc/terms/partOf": ["http://data.archaeology.link/data/ancientports/bib_deGrauw_2013_GeoDB"], "http://www.opengis.net/ont/geosparql#hasGeometry": ["http://data.archaeology.link/data/ancientports/3760_geom"], "http://www.w3.org/1999/02/22-rdf-syntax-ns#type": ["http://www.ancientports.com/ont#Harbour"], "http://www.w3.org/2000/01/rdf-schema#label": ["Khor Rori, at the outlet of wadi Darbat, near Taqah"], "http://www.w3.org/2002/07/owl#sameAs": ["http://www.wikidata.org/entity/Q826118"], "http://www.w3.org/2004/02/skos/core#note": ["Schiettecatte (2012)"], "http://www.w3.org/2006/time#hasTime": ["http://data.archaeology.link/data/ancientports/3760_foundation"], "http://www.wikidata.org/prop/direct/P1584": ["http://pleiades.stoa.org/places/40228"], "http://www.wikidata.org/prop/direct/P17": ["http://www.wikidata.org/entity/Q842"], "http://www.wikidata.org/prop/direct/P1936": ["http://imperium.ahlfeldt.se/places/27286"], "begin": "-200"}, "geometry": {"type": "Point", "coordinates": [54.43429, 17.03884]}}], "numberMatched": 1, "numberReturned": 1, "bbox": [54.43429, 17.03884, 54.43429, 17.03884], "crs": "http://www.opengis.net/def/crs/EPSG/0/4326"}