{"type": "FeatureCollection", "id": "http://pleiades.stoa.org/places/550403", "name": "550403", "features": [{"type": "Feature", "id": "http://data.archaeology.link/data/ancientports/3117", "label": "\u00d6ren Meydani, near Burhaniye Yat Limani, near R Karinca", "properties": {"http://purl.org/dc/elements/1.1/created": ["2023"], "http://purl.org/dc/elements/1.1/creator": ["http://data.archaeology.link/data/spphaefen/arthur_de_graauw"], "http://www.ancientports.com/ont#date_min": ["-750"], "http://www.opengis.net/ont/geosparql#hasGeometry": ["http://data.archaeology.link/data/ancientports/3117_geom"], "http://www.w3.org/1999/02/22-rdf-syntax-ns#type": ["http://www.ancientports.com/ont#Harbour"], "http://www.w3.org/2000/01/rdf-schema#label": ["\u00d6ren Meydani, near Burhaniye Yat Limani, near R Karinca"], "http://www.w3.org/2002/07/owl#sameAs": ["http://www.wikidata.org/entity/Q3605584"], "http://www.wikidata.org/prop/direct/P1584": ["http://pleiades.stoa.org/places/550403"], "http://www.wikidata.org/prop/direct/P17": ["TR: West"], "http://www.wikidata.org/prop/direct/P1958": ["https://www.trismegistos.org/place/48"]}, "geometry": {"type": "Point", "coordinates": [26.931, 39.5048]}}]}