{"type": "FeatureCollection", "id": "http://www.wikidata.org/entity/Q7861533", "name": "Tyritake", "features": [{"type": "Feature", "id": "http://data.archaeology.link/data/ancientports/2608", "name": "near Pryozerne industrial port", "dateprops": ["begin"], "properties": {"http://purl.org/dc/elements/1.1/created": ["2023"], "http://purl.org/dc/elements/1.1/creator": ["http://data.archaeology.link/data/spphaefen/arthur_de_graauw"], "http://www.opengis.net/ont/geosparql#hasGeometry": ["http://data.archaeology.link/data/ancientports/2608_geom"], "http://www.w3.org/1999/02/22-rdf-syntax-ns#type": ["http://www.ancientports.com/ont#Harbour"], "http://www.w3.org/2000/01/rdf-schema#label": ["near Pryozerne industrial port"], "http://www.w3.org/2002/07/owl#sameAs": ["http://www.wikidata.org/entity/Q7861533"], "http://www.w3.org/2004/02/skos/core#note": ["Hojte (2005)"], "http://www.w3.org/2006/time#hasTime": ["http://data.archaeology.link/data/ancientports/2608_foundation"], "http://www.wikidata.org/prop/direct/P1584": ["http://pleiades.stoa.org/places/854745"], "http://www.wikidata.org/prop/direct/P17": ["http://www.wikidata.org/entity/Q212"], "http://www.wikidata.org/prop/direct/P1936": ["http://imperium.ahlfeldt.se/places/22011"], "http://www.wikidata.org/prop/direct/P1958": ["https://www.trismegistos.org/place/38320"], "http://www.wikidata.org/prop/direct/P8068": ["https://topostext.org/place/453364UTyr"], "begin": "-550"}, "geometry": {"type": "Point", "coordinates": [36.4072, 45.27708]}}]}