{"type": "FeatureCollection", "id": "http://pleiades.stoa.org/places/217016", "name": "217016", "features": [{"type": "Feature", "id": "http://data.archaeology.link/data/ancientports/2481", "label": "Constantza", "properties": {"http://purl.org/dc/elements/1.1/created": ["2023"], "http://purl.org/dc/elements/1.1/creator": ["http://data.archaeology.link/data/spphaefen/arthur_de_graauw"], "http://www.ancientports.com/ont#date_min": ["-500"], "http://www.opengis.net/ont/geosparql#hasGeometry": ["http://data.archaeology.link/data/ancientports/2481_geom"], "http://www.w3.org/1999/02/22-rdf-syntax-ns#type": ["http://www.ancientports.com/ont#Harbour"], "http://www.w3.org/2000/01/rdf-schema#label": ["Constantza"], "http://www.w3.org/2002/07/owl#sameAs": ["http://www.wikidata.org/entity/Q79808"], "http://www.wikidata.org/prop/direct/P1584": ["http://pleiades.stoa.org/places/217016"], "http://www.wikidata.org/prop/direct/P17": ["Romania Black S."], "http://www.wikidata.org/prop/direct/P1958": ["https://www.trismegistos.org/place/11900"]}, "geometry": {"type": "Point", "coordinates": [28.659, 44.171]}}]}