{"type": "FeatureCollection", "id": "http://imperium.ahlfeldt.se/places/27515", "name": "27515", "features": [{"type": "Feature", "id": "http://data.archaeology.link/data/ancientports/2793", "label": "Gideros, near Kumluca", "dateprops": [], "properties": {"http://purl.org/dc/elements/1.1/created": ["2023"], "http://purl.org/dc/elements/1.1/creator": ["http://data.archaeology.link/data/spphaefen/arthur_de_graauw"], "http://www.opengis.net/ont/geosparql#hasGeometry": ["http://data.archaeology.link/data/ancientports/2793_geom"], "http://www.w3.org/1999/02/22-rdf-syntax-ns#type": ["http://www.ancientports.com/ont#Harbour"], "http://www.w3.org/2000/01/rdf-schema#label": ["Gideros, near Kumluca"], "http://www.w3.org/2002/07/owl#sameAs": ["http://www.wikidata.org/entity/Q5201382"], "http://www.w3.org/2004/02/skos/core#note": ["Dan (2009)"], "http://www.w3.org/2006/time#hasTime": ["http://data.archaeology.link/data/ancientports/2793_foundation"], "http://www.wikidata.org/prop/direct/P1584": ["http://pleiades.stoa.org/places/844997"], "http://www.wikidata.org/prop/direct/P17": ["TR: Black Sea"], "http://www.wikidata.org/prop/direct/P1936": ["http://imperium.ahlfeldt.se/places/27515"], "http://www.wikidata.org/prop/direct/P1958": ["https://www.trismegistos.org/place/16305"], "http://www.wikidata.org/prop/direct/P8068": ["https://topostext.org/place/419329UKyt"]}, "geometry": {"type": "Point", "coordinates": [32.85803, 41.85942]}}]}