{"type": "FeatureCollection", "id": "http://pleiades.stoa.org/places/930175", "name": "930175", "features": [{"type": "Feature", "id": "http://data.archaeology.link/data/ancientports/3812", "label": "Large river estuary south of Bandar Deylam", "dateprops": [], "properties": {"http://purl.org/dc/elements/1.1/created": ["2023"], "http://purl.org/dc/elements/1.1/creator": ["http://data.archaeology.link/data/spphaefen/arthur_de_graauw"], "http://www.opengis.net/ont/geosparql#hasGeometry": ["http://data.archaeology.link/data/ancientports/3812_geom"], "http://www.w3.org/1999/02/22-rdf-syntax-ns#type": ["http://www.ancientports.com/ont#Harbour"], "http://www.w3.org/2000/01/rdf-schema#label": ["Large river estuary south of Bandar Deylam"], "http://www.wikidata.org/prop/direct/P1584": ["http://pleiades.stoa.org/places/930175"], "http://www.wikidata.org/prop/direct/P17": ["Gulf"]}, "geometry": {"type": "Point", "coordinates": [50.12, 29.92]}}]}