{"type": "FeatureCollection", "id": "https://www.trismegistos.org/place/8384", "name": "8384", "features": [{"type": "Feature", "id": "http://data.archaeology.link/data/ancientports/3614", "name": "Dahlak Kebir village on the Dahlak islands, with many rock-cut cisterns on Dahlak Kebir", "dateprops": ["begin"], "properties": {"http://purl.org/dc/elements/1.1/creator": ["http://data.archaeology.link/data/spphaefen/arthur_de_graauw"], "http://purl.org/dc/terms/isReferencedBy": ["http://data.archaeology.link/data/ancientports/bib_Insoll_2001_Dahlak"], "http://purl.org/dc/terms/partOf": ["http://data.archaeology.link/data/ancientports/bib_deGrauw_2013_GeoDB"], "http://www.opengis.net/ont/geosparql#hasGeometry": ["http://data.archaeology.link/data/ancientports/3614_geom"], "http://www.w3.org/1999/02/22-rdf-syntax-ns#type": ["http://www.ancientports.com/ont#Harbour"], "http://www.w3.org/2000/01/rdf-schema#label": ["Dahlak Kebir village on the Dahlak islands, with many rock-cut cisterns on Dahlak Kebir"], "http://www.w3.org/2002/07/owl#sameAs": ["http://www.wikidata.org/entity/Q639648"], "http://www.w3.org/2006/time#hasTime": ["http://data.archaeology.link/data/ancientports/3614_foundation"], "http://www.wikidata.org/prop/direct/P1584": ["http://pleiades.stoa.org/places/39281"], "http://www.wikidata.org/prop/direct/P17": ["http://www.wikidata.org/entity/Q986"], "http://www.wikidata.org/prop/direct/P1936": ["http://imperium.ahlfeldt.se/places/41317"], "http://www.wikidata.org/prop/direct/P1958": ["https://www.trismegistos.org/place/8384"], "begin": "-30"}, "geometry": {"type": "Point", "coordinates": [40.013, 15.6122]}}], "numberMatched": 1, "numberReturned": 1, "bbox": [40.013, 15.6122, 40.013, 15.6122], "crs": "http://www.opengis.net/def/crs/EPSG/0/4326"}