{"type": "FeatureCollection", "id": "http://www.wikidata.org/entity/Q1540236", "name": "Q1540236", "features": [{"type": "Feature", "id": "http://data.archaeology.link/data/ancientports/2969", "label": "Gournia ", "dateprops": ["http://purl.org/dc/elements/1.1/created"], "properties": {"http://purl.org/dc/elements/1.1/created": ["2023"], "http://purl.org/dc/elements/1.1/creator": ["http://data.archaeology.link/data/spphaefen/arthur_de_graauw"], "http://www.opengis.net/ont/geosparql#hasGeometry": ["http://data.archaeology.link/data/ancientports/2969_geom"], "http://www.w3.org/1999/02/22-rdf-syntax-ns#type": ["http://www.ancientports.com/ont#Shipshed", "http://www.ancientports.com/ont#Slipway"], "http://www.w3.org/2000/01/rdf-schema#label": ["Gournia "], "http://www.w3.org/2002/07/owl#sameAs": ["http://www.wikidata.org/entity/Q1540236"], "http://www.w3.org/2004/02/skos/core#note": ["Watrous (2010)"], "http://www.w3.org/2006/time#hasTime": ["http://data.archaeology.link/data/ancientports/2969_foundation"], "http://www.wikidata.org/prop/direct/P1584": ["http://pleiades.stoa.org/places/771100776"], "http://www.wikidata.org/prop/direct/P17": ["GR: Crete North"], "http://www.wikidata.org/prop/direct/P1936": ["http://imperium.ahlfeldt.se/places/44585"], "http://www.wikidata.org/prop/direct/P8068": ["https://topostext.org/place/351258UGou"]}, "geometry": {"type": "Point", "coordinates": [25.7907, 35.1148]}}]}