{"type": "FeatureCollection", "id": "https://topostext.org/place/391262PPyr", "name": "391262PPyr", "features": [{"type": "Feature", "id": "http://data.archaeology.link/data/ancientports/2200", "label": "Pyrra WS of the isle of Lesbos, Lesvos", "dateprops": [], "properties": {"http://purl.org/dc/elements/1.1/created": ["2023"], "http://purl.org/dc/elements/1.1/creator": ["http://data.archaeology.link/data/spphaefen/arthur_de_graauw"], "http://www.ancientports.com/ont#date_min": ["-750"], "http://www.opengis.net/ont/geosparql#hasGeometry": ["http://data.archaeology.link/data/ancientports/2200_geom"], "http://www.w3.org/1999/02/22-rdf-syntax-ns#type": ["http://www.ancientports.com/ont#Harbour"], "http://www.w3.org/2000/01/rdf-schema#label": ["Pyrra WS of the isle of Lesbos, Lesvos"], "http://www.w3.org/2002/07/owl#sameAs": ["http://www.wikidata.org/entity/Q6076774"], "http://www.w3.org/2004/02/skos/core#note": ["Theodoulou (2008)"], "http://www.wikidata.org/prop/direct/P1584": ["http://pleiades.stoa.org/places/550851"], "http://www.wikidata.org/prop/direct/P17": ["GR: Eastern Isl."], "http://www.wikidata.org/prop/direct/P1936": ["http://imperium.ahlfeldt.se/places/27354"], "http://www.wikidata.org/prop/direct/P1958": ["https://www.trismegistos.org/place/34117"], "http://www.wikidata.org/prop/direct/P8068": ["https://topostext.org/place/391262PPyr"]}, "geometry": {"type": "Point", "coordinates": [26.2852, 39.1593]}}]}