{"type": "FeatureCollection", "id": "http://www.wikidata.org/entity/Q4119042", "name": "Q4119042", "features": [{"type": "Feature", "id": "http://data.archaeology.link/data/ancientports/3442", "label": "slipway at Ras al-Qalaat, Anfeh, Enfe", "dateprops": [], "properties": {"http://purl.org/dc/elements/1.1/created": ["2023"], "http://purl.org/dc/elements/1.1/creator": ["http://data.archaeology.link/data/spphaefen/arthur_de_graauw"], "http://purl.org/dc/terms/isReferencedBy": ["https://en.wikipedia.org/wiki/Amarna_letters", "https://honorfrostfoundation.org/2018/01/01/anfeh-lebanon/"], "http://www.ancientports.com/ont#date_min": ["-1500"], "http://www.opengis.net/ont/geosparql#hasGeometry": ["http://data.archaeology.link/data/ancientports/3442_geom"], "http://www.w3.org/1999/02/22-rdf-syntax-ns#type": ["http://www.ancientports.com/ont#Slipway"], "http://www.w3.org/2000/01/rdf-schema#label": ["slipway at Ras al-Qalaat, Anfeh, Enfe"], "http://www.w3.org/2002/07/owl#sameAs": ["http://www.wikidata.org/entity/Q4119042"], "http://www.w3.org/2004/02/skos/core#note": ["Pfaelzner (2012)"], "http://www.wikidata.org/prop/direct/P17": ["http://www.wikidata.org/entity/Q822"]}, "geometry": {"type": "Point", "coordinates": [35.72918, 34.36088]}}, {"type": "Feature", "id": "http://data.archaeology.link/data/ancientports/3443", "label": "slipway at Ras al-Qalaat, Anfeh, Enfe", "dateprops": [], "properties": {"http://purl.org/dc/elements/1.1/created": ["2023"], "http://purl.org/dc/elements/1.1/creator": ["http://data.archaeology.link/data/spphaefen/arthur_de_graauw"], "http://purl.org/dc/terms/isReferencedBy": ["https://honorfrostfoundation.org/2018/01/01/anfeh-lebanon/"], "http://www.opengis.net/ont/geosparql#hasGeometry": ["http://data.archaeology.link/data/ancientports/3443_geom"], "http://www.w3.org/1999/02/22-rdf-syntax-ns#type": ["http://www.ancientports.com/ont#Slipway"], "http://www.w3.org/2000/01/rdf-schema#label": ["slipway at Ras al-Qalaat, Anfeh, Enfe"], "http://www.w3.org/2002/07/owl#sameAs": ["http://www.wikidata.org/entity/Q4119042"], "http://www.w3.org/2004/02/skos/core#note": ["Carayon (2012)"], "http://www.wikidata.org/prop/direct/P17": ["http://www.wikidata.org/entity/Q822"]}, "geometry": {"type": "Point", "coordinates": [35.72547, 34.36146]}}, {"type": "Feature", "id": "http://data.archaeology.link/data/ancientports/3441_1", "label": "Deir el-Natour", "dateprops": [], "properties": {"http://purl.org/dc/elements/1.1/created": ["2023"], "http://purl.org/dc/elements/1.1/creator": ["http://data.archaeology.link/data/spphaefen/arthur_de_graauw"], "http://purl.org/dc/terms/isReferencedBy": ["https://honorfrostfoundation.org/2020/07/29/deir-el-natour-ongoing/"], "http://www.opengis.net/ont/geosparql#hasGeometry": ["http://data.archaeology.link/data/ancientports/3441_1_geom"], "http://www.w3.org/1999/02/22-rdf-syntax-ns#type": ["http://www.ancientports.com/ont#Harbour"], "http://www.w3.org/2000/01/rdf-schema#label": ["Deir el-Natour"], "http://www.w3.org/2002/07/owl#sameAs": ["http://www.wikidata.org/entity/Q4119042"], "http://www.wikidata.org/prop/direct/P17": ["http://www.wikidata.org/entity/Q822"]}, "geometry": {"type": "Point", "coordinates": [35.738, 34.3751]}}]}