{"type": "FeatureCollection", "id": "https://topostext.org/place/349248ULas", "name": "349248ULas", "features": [{"type": "Feature", "id": "http://data.archaeology.link/data/ancientports/2999", "name": "", "dateprops": ["begin"], "properties": {"http://purl.org/dc/elements/1.1/creator": ["http://data.archaeology.link/data/spphaefen/arthur_de_graauw"], "http://purl.org/dc/terms/partOf": ["http://data.archaeology.link/data/ancientports/bib_deGrauw_2013_GeoDB"], "http://rdfs.org/ns/void#inDataset": ["http://data.archaeology.link/data/ancientports/dataset"], "http://www.opengis.net/ont/geosparql#hasGeometry": ["http://data.archaeology.link/data/ancientports/2999_geom"], "http://www.w3.org/1999/02/22-rdf-syntax-ns#type": ["http://www.ancientports.com/ont#Harbour"], "http://www.w3.org/2000/01/rdf-schema#label": ["islet of Trafos at Chrysostomos 2 km east of Kaloi Limenes ; rubble mound breakwaters can be seen on Google Earth"], "http://www.w3.org/2002/07/owl#sameAs": ["http://www.wikidata.org/entity/Q7832593"], "http://www.w3.org/2004/02/skos/core#note": ["Kolaiti (2022)", "Uggeri (2003)", "de Graauw pictures (2022)"], "http://www.w3.org/2006/time#hasTime": ["http://data.archaeology.link/data/ancientports/2999_foundation"], "http://www.wikidata.org/prop/direct/P1584": ["http://pleiades.stoa.org/places/589897"], "http://www.wikidata.org/prop/direct/P17": ["http://www.wikidata.org/entity/Q41"], "http://www.wikidata.org/prop/direct/P1936": ["http://imperium.ahlfeldt.se/places/23383"], "http://www.wikidata.org/prop/direct/P1958": ["https://www.trismegistos.org/place/33285"], "http://www.wikidata.org/prop/direct/P8068": ["https://topostext.org/place/349248ULas"], "begin": "-3000"}, "geometry": {"type": "Point", "coordinates": [24.82495, 34.9376]}}], "numberMatched": 1, "numberReturned": 1, "bbox": [24.82495, 34.9376, 24.82495, 34.9376], "crs": "http://www.opengis.net/def/crs/EPSG/0/4326"}