{"type": "FeatureCollection", "id": "http://pleiades.stoa.org/places/157857", "name": "157857", "features": [{"type": "Feature", "id": "http://data.archaeology.link/data/ancientports/689", "name": "Pointe de La Galere (Porquerolles)", "dateprops": ["begin"], "properties": {"http://purl.org/dc/elements/1.1/created": ["2023"], "http://purl.org/dc/elements/1.1/creator": ["http://data.archaeology.link/data/spphaefen/arthur_de_graauw"], "http://www.opengis.net/ont/geosparql#hasGeometry": ["http://data.archaeology.link/data/ancientports/689_geom"], "http://www.w3.org/1999/02/22-rdf-syntax-ns#type": ["http://www.ancientports.com/ont#Harbour"], "http://www.w3.org/2000/01/rdf-schema#label": ["Pointe de La Galere (Porquerolles)"], "http://www.w3.org/2002/07/owl#sameAs": ["http://www.wikidata.org/entity/Q975080"], "http://www.w3.org/2004/02/skos/core#note": ["Brun (1992)"], "http://www.w3.org/2006/time#hasTime": ["http://data.archaeology.link/data/ancientports/689_foundation"], "http://www.wikidata.org/prop/direct/P1584": ["http://pleiades.stoa.org/places/157857"], "http://www.wikidata.org/prop/direct/P17": ["http://www.wikidata.org/entity/Q142"], "http://www.wikidata.org/prop/direct/P1936": ["http://imperium.ahlfeldt.se/places/17390"], "begin": "-100"}, "geometry": {"type": "Point", "coordinates": [6.25155, 43.00177]}}]}