{"type": "FeatureCollection", "id": "http://www.wikidata.org/entity/Q5297164", "name": "Q5297164", "features": [{"type": "Feature", "id": "http://data.archaeology.link/data/ancientports/171_06", "label": "An Duinin, Ballymore West, oppidum, near Ventry Harbour", "properties": {"http://purl.org/dc/elements/1.1/created": ["2023"], "http://purl.org/dc/elements/1.1/creator": ["http://data.archaeology.link/data/spphaefen/arthur_de_graauw"], "http://www.ancientports.com/ont#date_min": ["-500"], "http://www.opengis.net/ont/geosparql#hasGeometry": ["http://data.archaeology.link/data/ancientports/171_06_geom"], "http://www.w3.org/1999/02/22-rdf-syntax-ns#type": ["http://www.ancientports.com/ont#Harbour"], "http://www.w3.org/2000/01/rdf-schema#label": ["An Duinin, Ballymore West, oppidum, near Ventry Harbour"], "http://www.w3.org/2002/07/owl#sameAs": ["http://www.wikidata.org/entity/Q5297164"], "http://www.wikidata.org/prop/direct/P17": ["http://www.wikidata.org/entity/Q27"]}, "geometry": {"type": "Point", "coordinates": [-10.3357, 52.1216]}}]}