{"type": "FeatureCollection", "id": "http://pleiades.stoa.org/places/295279", "name": "295279", "features": [{"type": "Feature", "id": "http://data.archaeology.link/data/ancientports/4243", "label": "Cherchel, western basin", "dateprops": ["http://purl.org/dc/elements/1.1/created", "http://www.ancientports.com/ont#date_min"], "properties": {"http://purl.org/dc/elements/1.1/created": ["2023"], "http://purl.org/dc/elements/1.1/creator": ["http://data.archaeology.link/data/spphaefen/arthur_de_graauw"], "http://www.ancientports.com/ont#date_min": ["-550"], "http://www.opengis.net/ont/geosparql#hasGeometry": ["http://data.archaeology.link/data/ancientports/4243_geom"], "http://www.w3.org/1999/02/22-rdf-syntax-ns#type": ["http://www.ancientports.com/ont#Quay"], "http://www.w3.org/2000/01/rdf-schema#label": ["Cherchel, western basin"], "http://www.w3.org/2004/02/skos/core#note": ["Leveau (1984)", "Stone (2021)"], "http://www.wikidata.org/prop/direct/P1584": ["http://pleiades.stoa.org/places/295279"], "http://www.wikidata.org/prop/direct/P17": ["http://www.wikidata.org/entity/Q262"], "http://www.wikidata.org/prop/direct/P1936": ["http://imperium.ahlfeldt.se/places/21630"], "http://www.wikidata.org/prop/direct/P1958": ["https://www.trismegistos.org/place/3116"], "http://www.wikidata.org/prop/direct/P8068": ["https://topostext.org/place/366022UIol"]}, "geometry": {"type": "Point", "coordinates": [2.18758, 36.61011]}}, {"type": "Feature", "id": "http://data.archaeology.link/data/ancientports/4244", "label": "isle of Joinville in front of Cherchel, with ancient lighthouse", "dateprops": ["http://purl.org/dc/elements/1.1/created", "http://www.ancientports.com/ont#date_min"], "properties": {"http://purl.org/dc/elements/1.1/created": ["2023"], "http://purl.org/dc/elements/1.1/creator": ["http://data.archaeology.link/data/spphaefen/arthur_de_graauw"], "http://www.ancientports.com/ont#date_min": ["-550"], "http://www.opengis.net/ont/geosparql#hasGeometry": ["http://data.archaeology.link/data/ancientports/4244_geom"], "http://www.w3.org/1999/02/22-rdf-syntax-ns#type": ["http://www.ancientports.com/ont#Lighthouse", "http://www.ancientports.com/ont#Pila"], "http://www.w3.org/2000/01/rdf-schema#label": ["isle of Joinville in front of Cherchel, with ancient lighthouse"], "http://www.w3.org/2004/02/skos/core#note": ["Leveau (1984)", "Stone (2021)"], "http://www.wikidata.org/prop/direct/P1584": ["http://pleiades.stoa.org/places/295279"], "http://www.wikidata.org/prop/direct/P17": ["http://www.wikidata.org/entity/Q262"], "http://www.wikidata.org/prop/direct/P1936": ["http://imperium.ahlfeldt.se/places/21630"], "http://www.wikidata.org/prop/direct/P1958": ["https://www.trismegistos.org/place/3116"]}, "geometry": {"type": "Point", "coordinates": [2.18977, 36.61208]}}, {"type": "Feature", "id": "http://data.archaeology.link/data/ancientports/4242", "label": "Cherchel, eastern basin", "dateprops": ["http://purl.org/dc/elements/1.1/created", "http://www.ancientports.com/ont#date_min"], "properties": {"http://purl.org/dc/elements/1.1/created": ["2023"], "http://purl.org/dc/elements/1.1/creator": ["http://data.archaeology.link/data/spphaefen/arthur_de_graauw"], "http://www.ancientports.com/ont#date_min": ["-550"], "http://www.opengis.net/ont/geosparql#hasGeometry": ["http://data.archaeology.link/data/ancientports/4242_geom"], "http://www.w3.org/1999/02/22-rdf-syntax-ns#type": ["http://www.ancientports.com/ont#Harbour"], "http://www.w3.org/2000/01/rdf-schema#label": ["Cherchel, eastern basin"], "http://www.w3.org/2004/02/skos/core#note": ["Leveau (1984)", "Stone (2021)"], "http://www.wikidata.org/prop/direct/P1584": ["http://pleiades.stoa.org/places/295279"], "http://www.wikidata.org/prop/direct/P17": ["http://www.wikidata.org/entity/Q262"], "http://www.wikidata.org/prop/direct/P1936": ["http://imperium.ahlfeldt.se/places/21630"], "http://www.wikidata.org/prop/direct/P1958": ["https://www.trismegistos.org/place/3116"], "http://www.wikidata.org/prop/direct/P8068": ["https://topostext.org/place/366022UIol"]}, "geometry": {"type": "Point", "coordinates": [2.19034, 36.6099]}}]}