{"type": "FeatureCollection", "id": "https://www.trismegistos.org/place/20628", "name": "20628", "features": [{"type": "Feature", "id": "http://data.archaeology.link/data/ancientports/4270", "name": "Takembrit, river port on wadi Tafna", "dateprops": ["begin"], "properties": {"http://purl.org/dc/elements/1.1/created": ["2023"], "http://purl.org/dc/elements/1.1/creator": ["http://data.archaeology.link/data/spphaefen/arthur_de_graauw"], "http://www.opengis.net/ont/geosparql#hasGeometry": ["http://data.archaeology.link/data/ancientports/4270_geom"], "http://www.w3.org/1999/02/22-rdf-syntax-ns#type": ["http://www.ancientports.com/ont#Harbour"], "http://www.w3.org/2000/01/rdf-schema#label": ["Takembrit, river port on wadi Tafna"], "http://www.w3.org/2002/07/owl#sameAs": ["http://www.wikidata.org/entity/Q3483498"], "http://www.w3.org/2004/02/skos/core#note": ["Laporte (2004)"], "http://www.w3.org/2006/time#hasTime": ["http://data.archaeology.link/data/ancientports/4270_foundation"], "http://www.wikidata.org/prop/direct/P1584": ["http://pleiades.stoa.org/places/285521"], "http://www.wikidata.org/prop/direct/P17": ["http://www.wikidata.org/entity/Q262"], "http://www.wikidata.org/prop/direct/P1936": ["http://imperium.ahlfeldt.se/places/21632"], "http://www.wikidata.org/prop/direct/P1958": ["https://www.trismegistos.org/place/20628"], "begin": "-550"}, "geometry": {"type": "Point", "coordinates": [-1.4519, 35.26769]}}]}