{"type": "FeatureCollection", "id": "http://pleiades.stoa.org/places/315050", "name": "315050", "features": [{"type": "Feature", "id": "http://data.archaeology.link/data/ancientports/4158", "label": "Kerkouane ", "properties": {"http://purl.org/dc/elements/1.1/created": ["2023"], "http://purl.org/dc/elements/1.1/creator": ["http://data.archaeology.link/data/spphaefen/arthur_de_graauw"], "http://www.ancientports.com/ont#date_min": ["-330"], "http://www.opengis.net/ont/geosparql#hasGeometry": ["http://data.archaeology.link/data/ancientports/4158_geom"], "http://www.w3.org/1999/02/22-rdf-syntax-ns#type": ["http://www.ancientports.com/ont#Slipway"], "http://www.w3.org/2000/01/rdf-schema#label": ["Kerkouane "], "http://www.wikidata.org/prop/direct/P1584": ["http://pleiades.stoa.org/places/315050"], "http://www.wikidata.org/prop/direct/P17": ["http://www.wikidata.org/entity/Q948"], "http://www.wikidata.org/prop/direct/P1936": ["http://imperium.ahlfeldt.se/places/21607"]}, "geometry": {"type": "Point", "coordinates": [11.1005, 36.94425]}}]}