{"type": "FeatureCollection", "id": "http://www.wikidata.org/entity/Q396613", "name": "Q396613", "features": [{"type": "Feature", "id": "http://data.archaeology.link/data/ancientports/1412", "label": "Novalja, on the isle of Pag", "properties": {"http://purl.org/dc/elements/1.1/created": ["2023"], "http://purl.org/dc/elements/1.1/creator": ["http://data.archaeology.link/data/spphaefen/arthur_de_graauw"], "http://purl.org/dc/terms/isReferencedBy": ["http://baza.iarh.hr/public/locality/detail/2489"], "http://www.ancientports.com/ont#date_min": ["3001"], "http://www.opengis.net/ont/geosparql#hasGeometry": ["http://data.archaeology.link/data/ancientports/1412_geom"], "http://www.w3.org/1999/02/22-rdf-syntax-ns#type": ["http://www.ancientports.com/ont#Harbour"], "http://www.w3.org/2000/01/rdf-schema#label": ["Novalja, on the isle of Pag"], "http://www.w3.org/2002/07/owl#sameAs": ["http://www.wikidata.org/entity/Q396613"], "http://www.w3.org/2004/02/skos/core#note": ["Kurilic (2012)"], "http://www.wikidata.org/prop/direct/P17": ["http://www.wikidata.org/entity/Q224"], "http://www.wikidata.org/prop/direct/P1936": ["http://imperium.ahlfeldt.se/places/22378"]}, "geometry": {"type": "Point", "coordinates": [14.8818, 44.5569]}}]}