{"type": "FeatureCollection", "id": "http://www.wikidata.org/entity/Q2744509", "name": "Raversijde", "features": [{"type": "Feature", "id": "http://data.archaeology.link/data/ancientports/39_2", "name": "Roman dike at Raversijde, near Ostend", "dateprops": [], "properties": {"http://purl.org/dc/elements/1.1/creator": ["http://data.archaeology.link/data/spphaefen/arthur_de_graauw"], "http://purl.org/dc/terms/partOf": ["http://data.archaeology.link/data/ancientports/bib_deGrauw_2013_GeoDB"], "http://www.opengis.net/ont/geosparql#hasGeometry": ["http://data.archaeology.link/data/ancientports/39_2_geom"], "http://www.w3.org/1999/02/22-rdf-syntax-ns#type": ["http://www.ancientports.com/ont#Harbour"], "http://www.w3.org/2000/01/rdf-schema#label": ["Roman dike at Raversijde, near Ostend"], "http://www.w3.org/2002/07/owl#sameAs": ["http://www.wikidata.org/entity/Q2744509"], "http://www.w3.org/2004/02/skos/core#note": ["Missiaen (2017)"], "http://www.wikidata.org/prop/direct/P17": ["http://www.wikidata.org/entity/Q234"], "begin": ""}, "geometry": {"type": "Point", "coordinates": [2.8482, 51.19995]}}], "numberMatched": 1, "numberReturned": 1, "bbox": [2.8482, 51.19995, 2.8482, 51.19995], "crs": "http://www.opengis.net/def/crs/OGC/1.3/CRS84"}