{"type": "FeatureCollection", "id": "http://www.wikidata.org/entity/Q749180", "name": "Q749180", "features": [{"type": "Feature", "id": "http://data.archaeology.link/data/ancientports/285", "label": "Cerro da Rocha Branca, near Silves", "properties": {"http://purl.org/dc/elements/1.1/created": ["2023"], "http://purl.org/dc/elements/1.1/creator": ["http://data.archaeology.link/data/spphaefen/arthur_de_graauw"], "http://www.ancientports.com/ont#date_min": ["-30"], "http://www.opengis.net/ont/geosparql#hasGeometry": ["http://data.archaeology.link/data/ancientports/285_geom"], "http://www.w3.org/1999/02/22-rdf-syntax-ns#type": ["http://www.ancientports.com/ont#Harbour"], "http://www.w3.org/2000/01/rdf-schema#label": ["Cerro da Rocha Branca, near Silves"], "http://www.w3.org/2002/07/owl#sameAs": ["http://www.wikidata.org/entity/Q749180"], "http://www.wikidata.org/prop/direct/P1584": ["http://pleiades.stoa.org/places/256451"], "http://www.wikidata.org/prop/direct/P17": ["http://www.wikidata.org/entity/Q45"], "http://www.wikidata.org/prop/direct/P1936": ["http://imperium.ahlfeldt.se/places/38455"]}, "geometry": {"type": "Point", "coordinates": [-8.44246, 37.18241]}}]}