{"type": "FeatureCollection", "id": "http://www.wikidata.org/entity/Q1735340", "name": "Q1735340", "features": [{"type": "Feature", "id": "http://data.archaeology.link/data/ancientports/63", "label": "Brancaster", "properties": {"http://purl.org/dc/elements/1.1/created": ["2023"], "http://purl.org/dc/elements/1.1/creator": ["http://data.archaeology.link/data/spphaefen/arthur_de_graauw"], "http://purl.org/dc/terms/isReferencedBy": ["https://historicengland.org.uk/listing/the-list/list-entry/1003983"], "http://www.ancientports.com/ont#date_min": ["2001"], "http://www.opengis.net/ont/geosparql#hasGeometry": ["http://data.archaeology.link/data/ancientports/63_geom"], "http://www.w3.org/1999/02/22-rdf-syntax-ns#type": ["http://www.ancientports.com/ont#Harbour"], "http://www.w3.org/2000/01/rdf-schema#label": ["Brancaster"], "http://www.w3.org/2002/07/owl#sameAs": ["http://www.wikidata.org/entity/Q1735340"], "http://www.w3.org/2004/02/skos/core#note": ["Wilmott (2018)", "https://historicengland.org.uk/listing/the-list/list-entry/1003983"], "http://www.wikidata.org/prop/direct/P1584": ["http://pleiades.stoa.org/places/79346"], "http://www.wikidata.org/prop/direct/P17": ["http://www.wikidata.org/entity/Q145"], "http://www.wikidata.org/prop/direct/P1936": ["http://imperium.ahlfeldt.se/places/18916"], "http://www.wikidata.org/prop/direct/P1958": ["https://www.trismegistos.org/place/15419"]}, "geometry": {"type": "Point", "coordinates": [0.6523, 52.964]}}]}