{"type": "FeatureCollection", "id": "http://pleiades.stoa.org/places/98932", "name": "98932", "features": [{"type": "Feature", "id": "http://data.archaeology.link/data/ancientports/21", "label": "Bijlandse Waard, on R Rijn", "dateprops": [], "properties": {"http://purl.org/dc/elements/1.1/created": ["2023"], "http://purl.org/dc/elements/1.1/creator": ["http://data.archaeology.link/data/spphaefen/arthur_de_graauw"], "http://purl.org/dc/terms/isReferencedBy": ["https://vici.org/vici/68/", "https://arkeonews.net/archaeologists-discover-exceptional-ancient-roman-sanctuary-in-near-intact-condition-in-netherlands/"], "http://www.opengis.net/ont/geosparql#hasGeometry": ["http://data.archaeology.link/data/ancientports/21_geom"], "http://www.w3.org/1999/02/22-rdf-syntax-ns#type": ["http://www.ancientports.com/ont#Harbour"], "http://www.w3.org/2000/01/rdf-schema#label": ["Bijlandse Waard, on R Rijn"], "http://www.w3.org/2002/07/owl#sameAs": ["http://www.wikidata.org/entity/Q1265889"], "http://www.wikidata.org/prop/direct/P1584": ["http://pleiades.stoa.org/places/98932"], "http://www.wikidata.org/prop/direct/P17": ["http://www.wikidata.org/entity/Q55"]}, "geometry": {"type": "Point", "coordinates": [6.07908, 51.87279]}}]}