{"type": "FeatureCollection", "id": "http://imperium.ahlfeldt.se/places/29319", "name": "29319", "features": [{"type": "Feature", "id": "http://data.archaeology.link/data/ancientports/1668", "name": "near Agios Minas", "dateprops": ["begin"], "properties": {"http://purl.org/dc/elements/1.1/creator": ["http://data.archaeology.link/data/spphaefen/arthur_de_graauw"], "http://purl.org/dc/terms/partOf": ["http://data.archaeology.link/data/ancientports/bib_deGrauw_2013_GeoDB"], "http://www.opengis.net/ont/geosparql#hasGeometry": ["http://data.archaeology.link/data/ancientports/1668_geom"], "http://www.w3.org/1999/02/22-rdf-syntax-ns#type": ["http://www.ancientports.com/ont#Harbour"], "http://www.w3.org/2000/01/rdf-schema#label": ["near Agios Minas"], "http://www.w3.org/2006/time#hasTime": ["http://data.archaeology.link/data/ancientports/1668_foundation"], "http://www.wikidata.org/prop/direct/P1584": ["http://pleiades.stoa.org/places/540705"], "http://www.wikidata.org/prop/direct/P17": ["http://www.wikidata.org/entity/Q41"], "http://www.wikidata.org/prop/direct/P1936": ["http://imperium.ahlfeldt.se/places/29319"], "http://www.wikidata.org/prop/direct/P8068": ["https://topostext.org/place/385236UCha"], "begin": "-750"}, "geometry": {"type": "Point", "coordinates": [23.57612, 38.48578]}}]}