{"type": "FeatureCollection", "id": "https://www.trismegistos.org/place/727", "name": "727", "features": [{"type": "Feature", "id": "http://data.archaeology.link/data/ancientports/1916", "label": "Githio", "dateprops": ["http://purl.org/dc/elements/1.1/created", "http://www.ancientports.com/ont#date_min"], "properties": {"http://purl.org/dc/elements/1.1/created": ["2023"], "http://purl.org/dc/elements/1.1/creator": ["http://data.archaeology.link/data/spphaefen/arthur_de_graauw"], "http://purl.org/dc/terms/isReferencedBy": ["https://www2.rgzm.de/navis2/home/frames.htm"], "http://www.ancientports.com/ont#date_min": ["-1500"], "http://www.opengis.net/ont/geosparql#hasGeometry": ["http://data.archaeology.link/data/ancientports/1916_geom"], "http://www.w3.org/1999/02/22-rdf-syntax-ns#type": ["http://www.ancientports.com/ont#Shipyard"], "http://www.w3.org/2000/01/rdf-schema#label": ["Githio"], "http://www.w3.org/2002/07/owl#sameAs": ["http://www.wikidata.org/entity/Q992256"], "http://www.w3.org/2004/02/skos/core#note": ["Scoufopoulos (1985)"], "http://www.wikidata.org/prop/direct/P1584": ["http://pleiades.stoa.org/places/570268"], "http://www.wikidata.org/prop/direct/P17": ["GR: Pelop"], "http://www.wikidata.org/prop/direct/P1936": ["http://imperium.ahlfeldt.se/places/21912"], "http://www.wikidata.org/prop/direct/P1958": ["https://www.trismegistos.org/place/727"], "http://www.wikidata.org/prop/direct/P8068": ["https://topostext.org/place/368226PGyt"]}, "geometry": {"type": "Point", "coordinates": [22.5688, 36.7619]}}]}