{"type": "FeatureCollection", "id": "https://topostext.org/place/398198IPty", "name": "398198IPty", "features": [{"type": "Feature", "id": "http://data.archaeology.link/data/ancientports/1976", "label": "Isle of Ptichia, Vido", "dateprops": ["http://purl.org/dc/elements/1.1/created"], "properties": {"http://purl.org/dc/elements/1.1/created": ["2023"], "http://purl.org/dc/elements/1.1/creator": ["http://data.archaeology.link/data/spphaefen/arthur_de_graauw"], "http://www.opengis.net/ont/geosparql#hasGeometry": ["http://data.archaeology.link/data/ancientports/1976_geom"], "http://www.w3.org/1999/02/22-rdf-syntax-ns#type": ["http://www.ancientports.com/ont#Harbour"], "http://www.w3.org/2000/01/rdf-schema#label": ["Isle of Ptichia, Vido"], "http://www.w3.org/2002/07/owl#sameAs": ["http://www.wikidata.org/entity/Q68605"], "http://www.wikidata.org/prop/direct/P1584": ["https://pleiades.stoa.org/places/531078"], "http://www.wikidata.org/prop/direct/P17": ["GR: Ionian Isl."], "http://www.wikidata.org/prop/direct/P1936": ["http://imperium.ahlfeldt.se/places/44937"], "http://www.wikidata.org/prop/direct/P8068": ["https://topostext.org/place/398198IPty"]}, "geometry": {"type": "Point", "coordinates": [19.923, 39.637]}}]}