{"type": "FeatureCollection", "id": "http://pleiades.stoa.org/places/550846", "name": "550846", "features": [{"type": "Feature", "id": "http://data.archaeology.link/data/ancientports/2249", "label": "breakwater between the islet Daskalion and Arxontiki, on the isle of Psara", "dateprops": [], "properties": {"http://purl.org/dc/elements/1.1/created": ["2023"], "http://purl.org/dc/elements/1.1/creator": ["http://data.archaeology.link/data/spphaefen/arthur_de_graauw"], "http://www.opengis.net/ont/geosparql#hasGeometry": ["http://data.archaeology.link/data/ancientports/2249_geom"], "http://www.w3.org/1999/02/22-rdf-syntax-ns#type": ["http://www.ancientports.com/ont#Harbour"], "http://www.w3.org/2000/01/rdf-schema#label": ["breakwater between the islet Daskalion and Arxontiki, on the isle of Psara"], "http://www.wikidata.org/prop/direct/P1584": ["http://pleiades.stoa.org/places/550846"], "http://www.wikidata.org/prop/direct/P17": ["http://www.wikidata.org/entity/Q41"], "http://www.wikidata.org/prop/direct/P8068": ["https://topostext.org/place/386256XArc"]}, "geometry": {"type": "Point", "coordinates": [25.55814, 38.5668]}}]}