{"type": "FeatureCollection", "id": "https://topostext.org/place/387161PHip", "name": "387161PHip", "features": [{"type": "Feature", "id": "http://data.archaeology.link/data/ancientports/1047_1", "name": "", "dateprops": ["begin"], "properties": {"http://purl.org/dc/elements/1.1/creator": ["http://data.archaeology.link/data/spphaefen/arthur_de_graauw"], "http://purl.org/dc/terms/isReferencedBy": ["http://data.archaeology.link/data/ancientports/bib_Anzidei_2013_Evidence"], "http://purl.org/dc/terms/partOf": ["http://data.archaeology.link/data/ancientports/bib_deGrauw_2013_GeoDB"], "http://www.opengis.net/ont/geosparql#hasGeometry": ["http://data.archaeology.link/data/ancientports/1047_1_geom"], "http://www.w3.org/1999/02/22-rdf-syntax-ns#type": ["http://www.ancientports.com/ont#Harbour"], "http://www.w3.org/2000/01/rdf-schema#label": ["Outlet of R Trainiti, near Bivona"], "http://www.w3.org/2002/07/owl#sameAs": ["http://www.wikidata.org/entity/Q13625"], "http://www.w3.org/2006/time#hasTime": ["http://data.archaeology.link/data/ancientports/1047_1_foundation"], "http://www.wikidata.org/prop/direct/P1584": ["https://pleiades.stoa.org/places/452337"], "http://www.wikidata.org/prop/direct/P17": ["http://www.wikidata.org/entity/Q38"], "http://www.wikidata.org/prop/direct/P1936": ["http://imperium.ahlfeldt.se/places/16733"], "http://www.wikidata.org/prop/direct/P1958": ["https://www.trismegistos.org/place/33100"], "http://www.wikidata.org/prop/direct/P8068": ["https://topostext.org/place/387161PHip"], "begin": "-30"}, "geometry": {"type": "Point", "coordinates": [16.0723, 38.7222]}}], "numberMatched": 1, "numberReturned": 1, "bbox": [16.0723, 38.7222, 16.0723, 38.7222], "crs": "http://www.opengis.net/def/crs/EPSG/0/4326"}