{"type": "FeatureCollection", "id": "http://imperium.ahlfeldt.se/places/16721", "name": "16721", "features": [{"type": "Feature", "id": "http://data.archaeology.link/data/ancientports/991", "label": "Pozzuoli, Pouzzoles, Puteoles, in the Campi Flegrei volcano district, pilae of arched mole are under modern breakwater (Molo Caligoliano)", "properties": {"http://purl.org/dc/elements/1.1/created": ["2023"], "http://purl.org/dc/elements/1.1/creator": ["http://data.archaeology.link/data/spphaefen/arthur_de_graauw"], "http://www.ancientports.com/ont#date_min": ["-750"], "http://www.opengis.net/ont/geosparql#hasGeometry": ["http://data.archaeology.link/data/ancientports/991_geom"], "http://www.w3.org/1999/02/22-rdf-syntax-ns#type": ["http://www.ancientports.com/ont#Harbour"], "http://www.w3.org/2000/01/rdf-schema#label": ["Pozzuoli, Pouzzoles, Puteoles, in the Campi Flegrei volcano district, pilae of arched mole are under modern breakwater (Molo Caligoliano)"], "http://www.w3.org/2002/07/owl#sameAs": ["http://www.wikidata.org/entity/Q72425"], "http://www.w3.org/2004/02/skos/core#note": ["Amato (2013)"], "http://www.wikidata.org/prop/direct/P1584": ["http://pleiades.stoa.org/places/432815"], "http://www.wikidata.org/prop/direct/P17": ["Italy West"], "http://www.wikidata.org/prop/direct/P1936": ["http://imperium.ahlfeldt.se/places/16721"], "http://www.wikidata.org/prop/direct/P1958": ["https://www.trismegistos.org/place/3189"], "http://www.wikidata.org/prop/direct/P8068": ["https://topostext.org/place/408141PDik"]}, "geometry": {"type": "Point", "coordinates": [14.1154, 40.8216]}}]}