{"type": "FeatureCollection", "id": "https://www.trismegistos.org/place/29361", "name": "29361", "features": [{"type": "Feature", "id": "http://data.archaeology.link/data/ancientports/1456", "label": "Split", "properties": {"http://purl.org/dc/elements/1.1/created": ["2023"], "http://purl.org/dc/elements/1.1/creator": ["http://data.archaeology.link/data/spphaefen/arthur_de_graauw"], "http://www.ancientports.com/ont#date_min": ["3001"], "http://www.opengis.net/ont/geosparql#hasGeometry": ["http://data.archaeology.link/data/ancientports/1456_geom"], "http://www.w3.org/1999/02/22-rdf-syntax-ns#type": ["http://www.ancientports.com/ont#Harbour"], "http://www.w3.org/2000/01/rdf-schema#label": ["Split"], "http://www.w3.org/2002/07/owl#sameAs": ["http://www.wikidata.org/entity/Q1663"], "http://www.wikidata.org/prop/direct/P1584": ["http://pleiades.stoa.org/places/197524"], "http://www.wikidata.org/prop/direct/P17": ["http://www.wikidata.org/entity/Q224"], "http://www.wikidata.org/prop/direct/P1936": ["http://imperium.ahlfeldt.se/places/10938"], "http://www.wikidata.org/prop/direct/P1958": ["https://www.trismegistos.org/place/29361"], "http://www.wikidata.org/prop/direct/P8068": ["https://topostext.org/place/435164BDiP"]}, "geometry": {"type": "Point", "coordinates": [16.4374, 43.5073]}}]}