{"type": "FeatureCollection", "id": "https://topostext.org/place/590000IOrc", "name": "590000IOrc", "features": [{"type": "Feature", "id": "http://data.archaeology.link/data/ancientports/41", "label": "Orkney islands, North Scotland", "properties": {"http://purl.org/dc/elements/1.1/created": ["2023"], "http://purl.org/dc/elements/1.1/creator": ["http://data.archaeology.link/data/spphaefen/arthur_de_graauw"], "http://www.opengis.net/ont/geosparql#hasGeometry": ["http://data.archaeology.link/data/ancientports/41_geom"], "http://www.w3.org/1999/02/22-rdf-syntax-ns#type": ["http://www.ancientports.com/ont#Harbour"], "http://www.w3.org/2000/01/rdf-schema#label": ["Orkney islands, North Scotland"], "http://www.w3.org/2002/07/owl#sameAs": ["http://www.wikidata.org/entity/Q100166"], "http://www.wikidata.org/prop/direct/P1584": ["http://pleiades.stoa.org/places/89261"], "http://www.wikidata.org/prop/direct/P17": ["http://www.wikidata.org/entity/Q145"], "http://www.wikidata.org/prop/direct/P1936": ["http://imperium.ahlfeldt.se/places/41731"], "http://www.wikidata.org/prop/direct/P1958": ["https://www.trismegistos.org/place/19730"], "http://www.wikidata.org/prop/direct/P8068": ["https://topostext.org/place/590000IOrc"]}, "geometry": {"type": "Point", "coordinates": [-3.19681, 59.07437]}}]}