{"type": "FeatureCollection", "id": "http://pleiades.stoa.org/places/530965", "name": "530965", "features": [{"type": "Feature", "id": "http://data.archaeology.link/data/ancientports/1560", "label": "Paliavli hill, near Mpoukka", "dateprops": ["http://purl.org/dc/elements/1.1/created"], "properties": {"http://purl.org/dc/elements/1.1/created": ["2023"], "http://purl.org/dc/elements/1.1/creator": ["http://data.archaeology.link/data/spphaefen/arthur_de_graauw"], "http://www.opengis.net/ont/geosparql#hasGeometry": ["http://data.archaeology.link/data/ancientports/1560_geom"], "http://www.w3.org/1999/02/22-rdf-syntax-ns#type": ["http://www.ancientports.com/ont#Harbour"], "http://www.w3.org/2000/01/rdf-schema#label": ["Paliavli hill, near Mpoukka"], "http://www.w3.org/2002/07/owl#sameAs": ["http://www.wikidata.org/entity/Q60792197"], "http://www.w3.org/2006/time#hasTime": ["http://data.archaeology.link/data/ancientports/1560_foundation"], "http://www.wikidata.org/prop/direct/P1584": ["http://pleiades.stoa.org/places/530965"], "http://www.wikidata.org/prop/direct/P17": ["GR: North-West"], "http://www.wikidata.org/prop/direct/P1936": ["http://imperium.ahlfeldt.se/places/31590"], "http://www.wikidata.org/prop/direct/P8068": ["https://topostext.org/place/389212UKre"]}, "geometry": {"type": "Point", "coordinates": [21.1645, 38.9125]}}]}