{"type": "FeatureCollection", "id": "http://pleiades.stoa.org/places/403223", "name": "403223", "features": [{"type": "Feature", "id": "http://data.archaeology.link/data/ancientports/882", "label": "Porto San Stefano, on the peninsula of Argentario", "properties": {"http://purl.org/dc/elements/1.1/created": ["2023"], "http://purl.org/dc/elements/1.1/creator": ["http://data.archaeology.link/data/spphaefen/arthur_de_graauw"], "http://www.ancientports.com/ont#date_min": ["-30"], "http://www.opengis.net/ont/geosparql#hasGeometry": ["http://data.archaeology.link/data/ancientports/882_geom"], "http://www.w3.org/1999/02/22-rdf-syntax-ns#type": ["http://www.ancientports.com/ont#Harbour"], "http://www.w3.org/2000/01/rdf-schema#label": ["Porto San Stefano, on the peninsula of Argentario"], "http://www.w3.org/2002/07/owl#sameAs": ["http://www.wikidata.org/entity/Q1431610"], "http://www.wikidata.org/prop/direct/P1584": ["http://pleiades.stoa.org/places/403223"], "http://www.wikidata.org/prop/direct/P17": ["Italy West"]}, "geometry": {"type": "Point", "coordinates": [11.1166, 42.4396]}}]}