{"type": "FeatureCollection", "id": "http://imperium.ahlfeldt.se/places/36204", "name": "36204", "features": [{"type": "Feature", "id": "http://data.archaeology.link/data/ancientports/3987", "label": "wadi ed Sedd", "properties": {"http://purl.org/dc/elements/1.1/created": ["2023"], "http://purl.org/dc/elements/1.1/creator": ["http://data.archaeology.link/data/spphaefen/arthur_de_graauw"], "http://www.ancientports.com/ont#date_min": ["-750"], "http://www.opengis.net/ont/geosparql#hasGeometry": ["http://data.archaeology.link/data/ancientports/3987_geom"], "http://www.w3.org/1999/02/22-rdf-syntax-ns#type": ["http://www.ancientports.com/ont#Harbour"], "http://www.w3.org/2000/01/rdf-schema#label": ["wadi ed Sedd"], "http://www.wikidata.org/prop/direct/P1584": ["http://pleiades.stoa.org/places/716536"], "http://www.wikidata.org/prop/direct/P17": ["Libya"], "http://www.wikidata.org/prop/direct/P1936": ["http://imperium.ahlfeldt.se/places/36204"], "http://www.wikidata.org/prop/direct/P1958": ["https://www.trismegistos.org/place/3779"]}, "geometry": {"type": "Point", "coordinates": [23.30917, 32.17435]}}]}