{"type": "FeatureCollection", "id": "http://pleiades.stoa.org/places/305111", "name": "305111", "features": [{"type": "Feature", "id": "http://data.archaeology.link/data/ancientports/4219", "label": "Andriech, at Sidi Rehane, near Cape Aokas", "properties": {"http://purl.org/dc/elements/1.1/created": ["2023"], "http://purl.org/dc/elements/1.1/creator": ["http://data.archaeology.link/data/spphaefen/arthur_de_graauw"], "http://www.ancientports.com/ont#date_min": ["-330"], "http://www.opengis.net/ont/geosparql#hasGeometry": ["http://data.archaeology.link/data/ancientports/4219_geom"], "http://www.w3.org/1999/02/22-rdf-syntax-ns#type": ["http://www.ancientports.com/ont#Harbour"], "http://www.w3.org/2000/01/rdf-schema#label": ["Andriech, at Sidi Rehane, near Cape Aokas"], "http://www.wikidata.org/prop/direct/P1584": ["http://pleiades.stoa.org/places/305111"], "http://www.wikidata.org/prop/direct/P17": ["Algeria"]}, "geometry": {"type": "Point", "coordinates": [5.2616, 36.6298]}}]}