{"type": "FeatureCollection", "id": "https://topostext.org/place/377240IPat", "name": "377240IPat", "features": [{"type": "Feature", "id": "http://data.archaeology.link/data/ancientports/1641", "name": "Isle of Patroklos", "dateprops": [], "properties": {"http://purl.org/dc/elements/1.1/creator": ["http://data.archaeology.link/data/spphaefen/arthur_de_graauw"], "http://purl.org/dc/terms/partOf": ["http://data.archaeology.link/data/ancientports/bib_deGrauw_2013_GeoDB"], "http://www.opengis.net/ont/geosparql#hasGeometry": ["http://data.archaeology.link/data/ancientports/1641_geom"], "http://www.w3.org/1999/02/22-rdf-syntax-ns#type": ["http://www.ancientports.com/ont#Harbour"], "http://www.w3.org/2000/01/rdf-schema#label": ["Isle of Patroklos"], "http://www.w3.org/2002/07/owl#sameAs": ["http://www.wikidata.org/entity/Q1145107"], "http://www.wikidata.org/prop/direct/P1584": ["http://pleiades.stoa.org/places/580060"], "http://www.wikidata.org/prop/direct/P17": ["http://www.wikidata.org/entity/Q41"], "http://www.wikidata.org/prop/direct/P1936": ["http://imperium.ahlfeldt.se/places/46586"], "http://www.wikidata.org/prop/direct/P1958": ["https://www.trismegistos.org/place/60748"], "http://www.wikidata.org/prop/direct/P8068": ["https://topostext.org/place/377240IPat"], "begin": ""}, "geometry": {"type": "Point", "coordinates": [23.95004, 37.65222]}}], "numberMatched": 1, "numberReturned": 1, "bbox": [23.95004, 37.65222, 23.95004, 37.65222], "crs": "http://www.opengis.net/def/crs/OGC/1.3/CRS84"}