{"type": "FeatureCollection", "id": "http://imperium.ahlfeldt.se/places/32846", "name": "32846", "features": [{"type": "Feature", "id": "http://data.archaeology.link/data/ancientports/725", "label": "Etang de Diana", "dateprops": [], "properties": {"http://purl.org/dc/elements/1.1/created": ["2023"], "http://purl.org/dc/elements/1.1/creator": ["http://data.archaeology.link/data/spphaefen/arthur_de_graauw"], "http://purl.org/dc/terms/isReferencedBy": ["https://en.wikipedia.org/wiki/Al%C3%A9ria#Pre-Roman"], "http://www.ancientports.com/ont#date_min": ["-330"], "http://www.opengis.net/ont/geosparql#hasGeometry": ["http://data.archaeology.link/data/ancientports/725_geom"], "http://www.w3.org/1999/02/22-rdf-syntax-ns#type": ["http://www.ancientports.com/ont#Harbour"], "http://www.w3.org/2000/01/rdf-schema#label": ["Etang de Diana"], "http://www.w3.org/2002/07/owl#sameAs": ["http://www.wikidata.org/entity/Q3591687"], "http://www.wikidata.org/prop/direct/P1584": ["http://pleiades.stoa.org/places/472055"], "http://www.wikidata.org/prop/direct/P17": ["France Corsica"], "http://www.wikidata.org/prop/direct/P1936": ["http://imperium.ahlfeldt.se/places/32846"]}, "geometry": {"type": "Point", "coordinates": [9.54952, 42.13988]}}]}