{"type": "FeatureCollection", "id": "http://www.wikidata.org/entity/Q751086", "name": "Brownsea Island", "features": [{"type": "Feature", "id": "http://data.archaeology.link/data/ancientports/98_1", "name": "Oppidum at Cleavel Point, on Ower peninsula, in front of Green island", "dateprops": ["begin"], "properties": {"http://purl.org/dc/elements/1.1/creator": ["http://data.archaeology.link/data/spphaefen/arthur_de_graauw"], "http://purl.org/dc/terms/isReferencedBy": ["http://data.archaeology.link/data/ancientports/bib_Wilkes_2004_Iron"], "http://purl.org/dc/terms/partOf": ["http://data.archaeology.link/data/ancientports/bib_deGrauw_2013_GeoDB"], "http://www.opengis.net/ont/geosparql#hasGeometry": ["http://data.archaeology.link/data/ancientports/98_1_geom"], "http://www.w3.org/1999/02/22-rdf-syntax-ns#type": ["http://www.ancientports.com/ont#Quay"], "http://www.w3.org/2000/01/rdf-schema#label": ["Oppidum at Cleavel Point, on Ower peninsula, in front of Green island"], "http://www.w3.org/2002/07/owl#sameAs": ["http://www.wikidata.org/entity/Q751086"], "http://www.w3.org/2006/time#hasTime": ["http://data.archaeology.link/data/ancientports/98_1_foundation"], "http://www.wikidata.org/prop/direct/P17": ["http://www.wikidata.org/entity/Q145"], "begin": "-30"}, "geometry": {"type": "Point", "coordinates": [-1.999, 50.6738]}}]}