{"type": "FeatureCollection", "id": "http://www.wikidata.org/entity/Q2005211", "name": "Q2005211", "features": [{"type": "Feature", "id": "http://data.archaeology.link/data/ancientports/3743", "label": "PM: Marib, not to be confused with Shabwa located 182 km further east", "dateprops": [], "properties": {"http://purl.org/dc/elements/1.1/created": ["2023"], "http://purl.org/dc/elements/1.1/creator": ["http://data.archaeology.link/data/spphaefen/arthur_de_graauw"], "http://purl.org/dc/terms/isReferencedBy": ["https://en.wikipedia.org/wiki/Ma%27rib", "http://data.archaeology.link/data/ancientports/bib_Marcotte_2017_Ocean"], "http://www.opengis.net/ont/geosparql#hasGeometry": ["http://data.archaeology.link/data/ancientports/3743_geom"], "http://www.w3.org/1999/02/22-rdf-syntax-ns#type": ["http://www.ancientports.com/ont#Harbour"], "http://www.w3.org/2000/01/rdf-schema#label": ["PM: Marib, not to be confused with Shabwa located 182 km further east"], "http://www.w3.org/2002/07/owl#sameAs": ["http://www.wikidata.org/entity/Q2005211"], "http://www.wikidata.org/prop/direct/P1584": ["https://pleiades.stoa.org/places/39379"], "http://www.wikidata.org/prop/direct/P17": ["Yemen Ind Oc."]}, "geometry": {"type": "Point", "coordinates": [47.03, 15.37]}}]}