{"type": "FeatureCollection", "id": "https://www.trismegistos.org/place/42515", "name": "42515", "features": [{"type": "Feature", "id": "http://data.archaeology.link/data/ancientports/1206", "label": "Porto Vulcano, on the isle of Vulcano", "properties": {"http://purl.org/dc/elements/1.1/created": ["2023"], "http://purl.org/dc/elements/1.1/creator": ["http://data.archaeology.link/data/spphaefen/arthur_de_graauw"], "http://www.ancientports.com/ont#date_min": ["-550"], "http://www.opengis.net/ont/geosparql#hasGeometry": ["http://data.archaeology.link/data/ancientports/1206_geom"], "http://www.w3.org/1999/02/22-rdf-syntax-ns#type": ["http://www.ancientports.com/ont#Harbour"], "http://www.w3.org/2000/01/rdf-schema#label": ["Porto Vulcano, on the isle of Vulcano"], "http://www.w3.org/2002/07/owl#sameAs": ["http://www.wikidata.org/entity/Q207323"], "http://www.wikidata.org/prop/direct/P1584": ["http://pleiades.stoa.org/places/462242"], "http://www.wikidata.org/prop/direct/P17": ["Italy Sicily"], "http://www.wikidata.org/prop/direct/P1958": ["https://www.trismegistos.org/place/42515"]}, "geometry": {"type": "Point", "coordinates": [14.96645, 38.41636]}}]}