{"type": "FeatureCollection", "id": "http://www.wikidata.org/entity/Q584295", "name": "Q584295", "features": [{"type": "Feature", "id": "http://data.archaeology.link/data/ancientports/3863_93", "label": "Malpe, Udipi, on R Papanashini", "dateprops": ["http://purl.org/dc/elements/1.1/created"], "properties": {"http://purl.org/dc/elements/1.1/created": ["2023"], "http://purl.org/dc/elements/1.1/creator": ["http://data.archaeology.link/data/spphaefen/arthur_de_graauw"], "http://www.opengis.net/ont/geosparql#hasGeometry": ["http://data.archaeology.link/data/ancientports/3863_93_geom"], "http://www.w3.org/1999/02/22-rdf-syntax-ns#type": ["http://www.ancientports.com/ont#Harbour"], "http://www.w3.org/2000/01/rdf-schema#label": ["Malpe, Udipi, on R Papanashini"], "http://www.w3.org/2002/07/owl#sameAs": ["http://www.wikidata.org/entity/Q584295"], "http://www.wikidata.org/prop/direct/P1584": ["https://pleiades.stoa.org/places/50017"], "http://www.wikidata.org/prop/direct/P17": ["http://www.wikidata.org/entity/Q668"]}, "geometry": {"type": "Point", "coordinates": [74.688, 13.351]}}]}