{"type": "FeatureCollection", "id": "https://topostext.org/place/267339UPhi", "name": "267339UPhi", "features": [{"type": "Feature", "id": "http://data.archaeology.link/data/ancientports/3544", "name": "Marsa Gawasis, near wadi Jasus, 26 km south of Safaga port. Pliny speaks of Aennus. Modern authors seem to agree to locate this port at Marsa Gawasis near Safaga.", "dateprops": ["begin"], "properties": {"http://purl.org/dc/elements/1.1/creator": ["http://data.archaeology.link/data/spphaefen/arthur_de_graauw"], "http://purl.org/dc/terms/isReferencedBy": ["http://data.archaeology.link/data/ancientports/bib_Tallet_2015_Ports"], "http://purl.org/dc/terms/partOf": ["http://data.archaeology.link/data/ancientports/bib_deGrauw_2013_GeoDB"], "http://www.opengis.net/ont/geosparql#hasGeometry": ["http://data.archaeology.link/data/ancientports/3544_geom"], "http://www.w3.org/1999/02/22-rdf-syntax-ns#type": ["http://www.ancientports.com/ont#Harbour"], "http://www.w3.org/2000/01/rdf-schema#label": ["Marsa Gawasis, near wadi Jasus, 26 km south of Safaga port. Pliny speaks of Aennus. Modern authors seem to agree to locate this port at Marsa Gawasis near Safaga."], "http://www.w3.org/2002/07/owl#sameAs": ["http://www.wikidata.org/entity/Q1536350"], "http://www.w3.org/2004/02/skos/core#note": ["Bard & Fattovich (2007)"], "http://www.w3.org/2006/time#hasTime": ["http://data.archaeology.link/data/ancientports/3544_foundation"], "http://www.wikidata.org/prop/direct/P1584": ["http://pleiades.stoa.org/places/767851"], "http://www.wikidata.org/prop/direct/P17": ["http://www.wikidata.org/entity/Q79"], "http://www.wikidata.org/prop/direct/P1958": ["https://www.trismegistos.org/place/1777"], "http://www.wikidata.org/prop/direct/P8068": ["https://topostext.org/place/267339UPhi"], "begin": "-1940"}, "geometry": {"type": "Point", "coordinates": [34.0334, 26.5565]}}], "numberMatched": 1, "numberReturned": 1, "bbox": [34.0334, 26.5565, 34.0334, 26.5565], "crs": "http://www.opengis.net/def/crs/EPSG/0/4326"}