{"type": "FeatureCollection", "id": "http://pleiades.stoa.org/places/639002", "name": "639002", "features": [{"type": "Feature", "id": "http://data.archaeology.link/data/ancientports/3310", "label": "Sulu Adasi island", "dateprops": [], "properties": {"http://purl.org/dc/elements/1.1/created": ["2023"], "http://purl.org/dc/elements/1.1/creator": ["http://data.archaeology.link/data/spphaefen/arthur_de_graauw"], "http://www.opengis.net/ont/geosparql#hasGeometry": ["http://data.archaeology.link/data/ancientports/3310_geom"], "http://www.w3.org/1999/02/22-rdf-syntax-ns#type": ["http://www.ancientports.com/ont#Harbour"], "http://www.w3.org/2000/01/rdf-schema#label": ["Sulu Adasi island"], "http://www.w3.org/2002/07/owl#sameAs": ["http://www.wikidata.org/entity/Q30632464"], "http://www.w3.org/2006/time#hasTime": ["http://data.archaeology.link/data/ancientports/3310_foundation"], "http://www.wikidata.org/prop/direct/P1584": ["http://pleiades.stoa.org/places/639002"], "http://www.wikidata.org/prop/direct/P17": ["TR: South"], "http://www.wikidata.org/prop/direct/P1936": ["http://imperium.ahlfeldt.se/places/27779"]}, "geometry": {"type": "Point", "coordinates": [30.473, 36.238]}}]}