{"type": "FeatureCollection", "id": "https://www.trismegistos.org/place/24464", "name": "24464", "features": [{"type": "Feature", "id": "http://data.archaeology.link/data/ancientports/12", "name": "Alphen a/d Rijn, on R Oude Rijn", "dateprops": [], "properties": {"http://purl.org/dc/elements/1.1/creator": ["http://data.archaeology.link/data/spphaefen/arthur_de_graauw"], "http://purl.org/dc/terms/isReferencedBy": ["http://data.archaeology.link/data/ancientports/bib_Seinen_2014_Late", "https://vici.org/vici/61/"], "http://purl.org/dc/terms/partOf": ["http://data.archaeology.link/data/ancientports/bib_deGrauw_2013_GeoDB"], "http://www.opengis.net/ont/geosparql#hasGeometry": ["http://data.archaeology.link/data/ancientports/12_geom"], "http://www.w3.org/1999/02/22-rdf-syntax-ns#type": ["http://www.ancientports.com/ont#Quay"], "http://www.w3.org/2000/01/rdf-schema#label": ["Alphen a/d Rijn, on R Oude Rijn"], "http://www.w3.org/2002/07/owl#sameAs": ["http://www.wikidata.org/entity/Q1265889"], "http://www.wikidata.org/prop/direct/P1584": ["http://pleiades.stoa.org/places/98908"], "http://www.wikidata.org/prop/direct/P17": ["http://www.wikidata.org/entity/Q55"], "http://www.wikidata.org/prop/direct/P1936": ["http://imperium.ahlfeldt.se/places/4458"], "http://www.wikidata.org/prop/direct/P1958": ["https://www.trismegistos.org/place/24464"], "begin": ""}, "geometry": {"type": "Point", "coordinates": [4.66139, 52.12917]}}], "numberMatched": 1, "numberReturned": 1, "bbox": [4.66139, 52.12917, 4.66139, 52.12917], "crs": "http://www.opengis.net/def/crs/OGC/1.3/CRS84"}