{"type": "FeatureCollection", "id": "https://www.trismegistos.org/place/54711", "name": "54711", "features": [{"type": "Feature", "id": "http://data.archaeology.link/data/ancientports/3522_1", "name": "Bir Umm Reiga & Bir Aheimar", "dateprops": [], "properties": {"http://purl.org/dc/elements/1.1/creator": ["http://data.archaeology.link/data/spphaefen/arthur_de_graauw"], "http://purl.org/dc/terms/partOf": ["http://data.archaeology.link/data/ancientports/bib_deGrauw_2013_GeoDB"], "http://www.opengis.net/ont/geosparql#hasGeometry": ["http://data.archaeology.link/data/ancientports/3522_1_geom"], "http://www.w3.org/1999/02/22-rdf-syntax-ns#type": ["http://www.ancientports.com/ont#Harbour"], "http://www.w3.org/2000/01/rdf-schema#label": ["Bir Umm Reiga & Bir Aheimar"], "http://www.wikidata.org/prop/direct/P17": ["http://www.wikidata.org/entity/Q79"], "http://www.wikidata.org/prop/direct/P1958": ["https://www.trismegistos.org/place/54711"], "begin": ""}, "geometry": {"type": "Point", "coordinates": [32.393, 29.521]}}], "numberMatched": 1, "numberReturned": 1, "bbox": [32.393, 29.521, 32.393, 29.521], "crs": "http://www.opengis.net/def/crs/EPSG/0/4326"}