{"type": "FeatureCollection", "id": "http://www.wikidata.org/entity/Q4957784", "name": "Q4957784", "features": [{"type": "Feature", "id": "http://data.archaeology.link/data/ancientports/1895", "label": "Plaka Leonido", "dateprops": ["http://purl.org/dc/elements/1.1/created", "http://www.ancientports.com/ont#date_min"], "properties": {"http://purl.org/dc/elements/1.1/created": ["2023"], "http://purl.org/dc/elements/1.1/creator": ["http://data.archaeology.link/data/spphaefen/arthur_de_graauw"], "http://www.ancientports.com/ont#date_min": ["-750"], "http://www.opengis.net/ont/geosparql#hasGeometry": ["http://data.archaeology.link/data/ancientports/1895_geom"], "http://www.w3.org/1999/02/22-rdf-syntax-ns#type": ["http://www.ancientports.com/ont#Harbour"], "http://www.w3.org/2000/01/rdf-schema#label": ["Plaka Leonido"], "http://www.w3.org/2002/07/owl#sameAs": ["http://www.wikidata.org/entity/Q4957784"], "http://www.wikidata.org/prop/direct/P1584": ["http://pleiades.stoa.org/places/570629"], "http://www.wikidata.org/prop/direct/P17": ["GR: Pelop"], "http://www.wikidata.org/prop/direct/P1936": ["http://imperium.ahlfeldt.se/places/31055"], "http://www.wikidata.org/prop/direct/P1958": ["https://www.trismegistos.org/place/37802"], "http://www.wikidata.org/prop/direct/P8068": ["https://topostext.org/place/371229PPra"]}, "geometry": {"type": "Point", "coordinates": [22.896, 37.1559]}}]}