{"type": "FeatureCollection", "id": "http://pleiades.stoa.org/places/275716", "name": "275716", "features": [{"type": "Feature", "id": "http://data.archaeology.link/data/ancientports/4310", "name": "Roman villa at Sidi Kacem, possible fish processing factory", "dateprops": ["begin"], "properties": {"http://purl.org/dc/elements/1.1/creator": ["http://data.archaeology.link/data/spphaefen/arthur_de_graauw"], "http://purl.org/dc/terms/partOf": ["http://data.archaeology.link/data/ancientports/bib_deGrauw_2013_GeoDB"], "http://www.opengis.net/ont/geosparql#hasGeometry": ["http://data.archaeology.link/data/ancientports/4310_geom"], "http://www.w3.org/1999/02/22-rdf-syntax-ns#type": ["http://www.ancientports.com/ont#VillaMaritima"], "http://www.w3.org/2000/01/rdf-schema#label": ["Roman villa at Sidi Kacem, possible fish processing factory"], "http://www.w3.org/2006/time#hasTime": ["http://data.archaeology.link/data/ancientports/4310_foundation"], "http://www.wikidata.org/prop/direct/P1584": ["http://pleiades.stoa.org/places/275716"], "http://www.wikidata.org/prop/direct/P17": ["http://www.wikidata.org/entity/Q1028"], "http://www.wikidata.org/prop/direct/P1936": ["http://imperium.ahlfeldt.se/places/34979"], "begin": "1001"}, "geometry": {"type": "Point", "coordinates": [-5.94368, 35.7312]}}], "numberMatched": 1, "numberReturned": 1}