{"type": "FeatureCollection", "id": "https://topostext.org/place/366225SAig", "name": "366225SAig", "features": [{"type": "Feature", "id": "http://data.archaeology.link/data/ancientports/1920", "name": "Lalloudes?", "dateprops": ["begin"], "properties": {"http://purl.org/dc/elements/1.1/creator": ["http://data.archaeology.link/data/spphaefen/arthur_de_graauw"], "http://purl.org/dc/terms/partOf": ["http://data.archaeology.link/data/ancientports/bib_deGrauw_2013_GeoDB"], "http://www.opengis.net/ont/geosparql#hasGeometry": ["http://data.archaeology.link/data/ancientports/1920_geom"], "http://www.w3.org/1999/02/22-rdf-syntax-ns#type": ["http://www.ancientports.com/ont#Harbour"], "http://www.w3.org/2000/01/rdf-schema#label": ["Lalloudes?"], "http://www.w3.org/2002/07/owl#sameAs": ["http://www.wikidata.org/entity/Q60790908"], "http://www.w3.org/2006/time#hasTime": ["http://data.archaeology.link/data/ancientports/1920_foundation"], "http://www.wikidata.org/prop/direct/P1584": ["http://pleiades.stoa.org/places/570045"], "http://www.wikidata.org/prop/direct/P17": ["http://www.wikidata.org/entity/Q41"], "http://www.wikidata.org/prop/direct/P1936": ["http://imperium.ahlfeldt.se/places/27393"], "http://www.wikidata.org/prop/direct/P1958": ["https://www.trismegistos.org/place/37965"], "http://www.wikidata.org/prop/direct/P8068": ["https://topostext.org/place/366225SAig"], "begin": "-330"}, "geometry": {"type": "Point", "coordinates": [22.4791, 36.5476]}}], "numberMatched": 1, "numberReturned": 1, "bbox": [22.4791, 36.5476, 22.4791, 36.5476], "crs": "http://www.opengis.net/def/crs/OGC/1.3/CRS84"}