{"type": "FeatureCollection", "id": "http://pleiades.stoa.org/places/236612", "name": "236612", "features": [{"type": "Feature", "id": "http://data.archaeology.link/data/ancientports/183", "name": "San Vicente de la Barquera", "dateprops": ["begin"], "properties": {"http://purl.org/dc/elements/1.1/created": ["2023"], "http://purl.org/dc/elements/1.1/creator": ["http://data.archaeology.link/data/spphaefen/arthur_de_graauw"], "http://www.opengis.net/ont/geosparql#hasGeometry": ["http://data.archaeology.link/data/ancientports/183_geom"], "http://www.w3.org/1999/02/22-rdf-syntax-ns#type": ["http://www.ancientports.com/ont#VillaMaritima"], "http://www.w3.org/2000/01/rdf-schema#label": ["San Vicente de la Barquera"], "http://www.w3.org/2002/07/owl#sameAs": ["http://www.wikidata.org/entity/Q384817"], "http://www.w3.org/2006/time#hasTime": ["http://data.archaeology.link/data/ancientports/183_foundation"], "http://www.wikidata.org/prop/direct/P1584": ["http://pleiades.stoa.org/places/236612"], "http://www.wikidata.org/prop/direct/P17": ["http://www.wikidata.org/entity/Q29"], "http://www.wikidata.org/prop/direct/P1936": ["http://imperium.ahlfeldt.se/places/33680"], "begin": "-330"}, "geometry": {"type": "Point", "coordinates": [-4.38077, 43.39505]}}]}