{"type": "FeatureCollection", "id": "https://topostext.org/place/314265UCha", "name": "314265UCha", "features": [{"type": "Feature", "id": "http://data.archaeology.link/data/ancientports/3969", "label": "Ras Gargub, Marsa Jarjub", "dateprops": [], "properties": {"http://purl.org/dc/elements/1.1/created": ["2023"], "http://purl.org/dc/elements/1.1/creator": ["http://data.archaeology.link/data/spphaefen/arthur_de_graauw"], "http://www.opengis.net/ont/geosparql#hasGeometry": ["http://data.archaeology.link/data/ancientports/3969_geom"], "http://www.w3.org/1999/02/22-rdf-syntax-ns#type": ["http://www.ancientports.com/ont#Harbour"], "http://www.w3.org/2000/01/rdf-schema#label": ["Ras Gargub, Marsa Jarjub"], "http://www.w3.org/2006/time#hasTime": ["http://data.archaeology.link/data/ancientports/3969_foundation"], "http://www.wikidata.org/prop/direct/P1584": ["http://pleiades.stoa.org/places/716543"], "http://www.wikidata.org/prop/direct/P17": ["http://www.wikidata.org/entity/Q79"], "http://www.wikidata.org/prop/direct/P1936": ["http://imperium.ahlfeldt.se/places/36205"], "http://www.wikidata.org/prop/direct/P1958": ["https://www.trismegistos.org/place/8010"], "http://www.wikidata.org/prop/direct/P8068": ["https://topostext.org/place/314265UCha"]}, "geometry": {"type": "Point", "coordinates": [26.563, 31.5023]}}]}