{"type": "FeatureCollection", "id": "https://www.trismegistos.org/place/15617", "name": "15617", "features": [{"type": "Feature", "id": "http://data.archaeology.link/data/ancientports/4321", "name": "Tchemmich hill, 5 km east of Larache, very large Roman fish processing factory and possible salt production and amphora kilns on wadi Loukkos", "dateprops": ["begin"], "properties": {"http://purl.org/dc/elements/1.1/creator": ["http://data.archaeology.link/data/spphaefen/arthur_de_graauw"], "http://purl.org/dc/terms/partOf": ["http://data.archaeology.link/data/ancientports/bib_deGrauw_2013_GeoDB"], "http://www.opengis.net/ont/geosparql#hasGeometry": ["http://data.archaeology.link/data/ancientports/4321_geom"], "http://www.w3.org/1999/02/22-rdf-syntax-ns#type": ["http://www.ancientports.com/ont#Quay"], "http://www.w3.org/2000/01/rdf-schema#label": ["Tchemmich hill, 5 km east of Larache, very large Roman fish processing factory and possible salt production and amphora kilns on wadi Loukkos"], "http://www.w3.org/2002/07/owl#sameAs": ["http://www.wikidata.org/entity/Q923835"], "http://www.w3.org/2004/02/skos/core#note": ["Boscs (2021)"], "http://www.w3.org/2006/time#hasTime": ["http://data.archaeology.link/data/ancientports/4321_foundation"], "http://www.wikidata.org/prop/direct/P1584": ["http://pleiades.stoa.org/places/275666"], "http://www.wikidata.org/prop/direct/P17": ["http://www.wikidata.org/entity/Q1028"], "http://www.wikidata.org/prop/direct/P1936": ["http://imperium.ahlfeldt.se/places/21771"], "http://www.wikidata.org/prop/direct/P1958": ["https://www.trismegistos.org/place/15617"], "http://www.wikidata.org/prop/direct/P8068": ["https://topostext.org/place/352001ULix"], "begin": "-1180"}, "geometry": {"type": "Point", "coordinates": [-6.1086, 35.1967]}}], "numberMatched": 1, "numberReturned": 1}