{"type": "FeatureCollection", "id": "http://imperium.ahlfeldt.se/places/27516", "name": "27516", "features": [{"type": "Feature", "id": "http://data.archaeology.link/data/ancientports/2817", "name": "east of Akcakoca", "dateprops": ["begin"], "properties": {"http://purl.org/dc/elements/1.1/creator": ["http://data.archaeology.link/data/spphaefen/arthur_de_graauw"], "http://purl.org/dc/terms/partOf": ["http://data.archaeology.link/data/ancientports/bib_deGrauw_2013_GeoDB"], "http://www.opengis.net/ont/geosparql#hasGeometry": ["http://data.archaeology.link/data/ancientports/2817_geom"], "http://www.w3.org/1999/02/22-rdf-syntax-ns#type": ["http://www.ancientports.com/ont#Warehouse"], "http://www.w3.org/2000/01/rdf-schema#label": ["east of Akcakoca"], "http://www.w3.org/2002/07/owl#sameAs": ["http://www.wikidata.org/entity/Q65089817"], "http://www.w3.org/2006/time#hasTime": ["http://data.archaeology.link/data/ancientports/2817_foundation"], "http://www.wikidata.org/prop/direct/P1584": ["http://pleiades.stoa.org/places/845005"], "http://www.wikidata.org/prop/direct/P17": ["http://www.wikidata.org/entity/Q43"], "http://www.wikidata.org/prop/direct/P1936": ["http://imperium.ahlfeldt.se/places/27516"], "begin": "-30"}, "geometry": {"type": "Point", "coordinates": [31.186, 41.0967]}}], "numberMatched": 1, "numberReturned": 1, "bbox": [31.186, 41.0967, 31.186, 41.0967], "crs": "http://www.opengis.net/def/crs/EPSG/0/4326"}