{"type": "FeatureCollection", "id": "http://www.wikidata.org/entity/Q6730120", "name": "Q6730120", "features": [{"type": "Feature", "id": "http://data.archaeology.link/data/ancientports/3502", "label": "Tell Qudadi, Kudadi, Tell esh-Shuna, on R Yarkon", "dateprops": ["http://purl.org/dc/elements/1.1/created", "http://www.ancientports.com/ont#date_min"], "properties": {"http://purl.org/dc/elements/1.1/created": ["2023"], "http://purl.org/dc/elements/1.1/creator": ["http://data.archaeology.link/data/spphaefen/arthur_de_graauw"], "http://www.ancientports.com/ont#date_min": ["-750"], "http://www.opengis.net/ont/geosparql#hasGeometry": ["http://data.archaeology.link/data/ancientports/3502_geom"], "http://www.w3.org/1999/02/22-rdf-syntax-ns#type": ["http://www.ancientports.com/ont#Harbour"], "http://www.w3.org/2000/01/rdf-schema#label": ["Tell Qudadi, Kudadi, Tell esh-Shuna, on R Yarkon"], "http://www.w3.org/2002/07/owl#sameAs": ["http://www.wikidata.org/entity/Q6730120"], "http://www.w3.org/2004/02/skos/core#note": ["Fantalkin (2016)"], "http://www.wikidata.org/prop/direct/P17": ["http://www.wikidata.org/entity/Q801"]}, "geometry": {"type": "Point", "coordinates": [34.777, 32.10343]}}]}