{"type": "FeatureCollection", "id": "http://pleiades.stoa.org/places/285502", "name": "285502", "features": [{"type": "Feature", "id": "http://data.archaeology.link/data/ancientports/4260", "label": "Oran", "properties": {"http://purl.org/dc/elements/1.1/created": ["2023"], "http://purl.org/dc/elements/1.1/creator": ["http://data.archaeology.link/data/spphaefen/arthur_de_graauw"], "http://www.ancientports.com/ont#date_min": ["-30"], "http://www.opengis.net/ont/geosparql#hasGeometry": ["http://data.archaeology.link/data/ancientports/4260_geom"], "http://www.w3.org/1999/02/22-rdf-syntax-ns#type": ["http://www.ancientports.com/ont#Harbour"], "http://www.w3.org/2000/01/rdf-schema#label": ["Oran"], "http://www.w3.org/2002/07/owl#sameAs": ["http://www.wikidata.org/entity/Q31085"], "http://www.wikidata.org/prop/direct/P1584": ["http://pleiades.stoa.org/places/285502"], "http://www.wikidata.org/prop/direct/P17": ["Algeria"], "http://www.wikidata.org/prop/direct/P1936": ["http://imperium.ahlfeldt.se/places/27022"]}, "geometry": {"type": "Point", "coordinates": [-0.65101, 35.70994]}}]}