{"type": "FeatureCollection", "id": "https://www.trismegistos.org/place/33226", "name": "33226", "features": [{"type": "Feature", "id": "http://data.archaeology.link/data/ancientports/2348", "label": "Isle of Carpathos, Karpathos, Kerpe", "dateprops": ["http://purl.org/dc/elements/1.1/created"], "properties": {"http://purl.org/dc/elements/1.1/created": ["2023"], "http://purl.org/dc/elements/1.1/creator": ["http://data.archaeology.link/data/spphaefen/arthur_de_graauw"], "http://www.opengis.net/ont/geosparql#hasGeometry": ["http://data.archaeology.link/data/ancientports/2348_geom"], "http://www.w3.org/1999/02/22-rdf-syntax-ns#type": ["http://www.ancientports.com/ont#Harbour"], "http://www.w3.org/2000/01/rdf-schema#label": ["Isle of Carpathos, Karpathos, Kerpe"], "http://www.w3.org/2002/07/owl#sameAs": ["http://www.wikidata.org/entity/Q204757"], "http://www.wikidata.org/prop/direct/P1584": ["http://pleiades.stoa.org/places/589841"], "http://www.wikidata.org/prop/direct/P17": ["GR: Eastern Isl."], "http://www.wikidata.org/prop/direct/P1936": ["http://imperium.ahlfeldt.se/places/41463"], "http://www.wikidata.org/prop/direct/P1958": ["https://www.trismegistos.org/place/33226"], "http://www.wikidata.org/prop/direct/P8068": ["https://topostext.org/place/356271IKar"]}, "geometry": {"type": "Point", "coordinates": [27.12795, 35.58323]}}]}