{"type": "FeatureCollection", "id": "http://www.wikidata.org/entity/Q65048810", "name": "Q65048810", "features": [{"type": "Feature", "id": "http://data.archaeology.link/data/ancientports/2758", "label": "near Kurtulus at the airport of Samsun", "dateprops": ["http://purl.org/dc/elements/1.1/created"], "properties": {"http://purl.org/dc/elements/1.1/created": ["2023"], "http://purl.org/dc/elements/1.1/creator": ["http://data.archaeology.link/data/spphaefen/arthur_de_graauw"], "http://www.opengis.net/ont/geosparql#hasGeometry": ["http://data.archaeology.link/data/ancientports/2758_geom"], "http://www.w3.org/1999/02/22-rdf-syntax-ns#type": ["http://www.ancientports.com/ont#Harbour"], "http://www.w3.org/2000/01/rdf-schema#label": ["near Kurtulus at the airport of Samsun"], "http://www.w3.org/2002/07/owl#sameAs": ["http://www.wikidata.org/entity/Q65048810"], "http://www.w3.org/2006/time#hasTime": ["http://data.archaeology.link/data/ancientports/2758_foundation"], "http://www.wikidata.org/prop/direct/P1584": ["http://pleiades.stoa.org/places/857079"], "http://www.wikidata.org/prop/direct/P17": ["TR: Black Sea"], "http://www.wikidata.org/prop/direct/P1936": ["http://imperium.ahlfeldt.se/places/36256"]}, "geometry": {"type": "Point", "coordinates": [36.5626, 41.2924]}}]}