{"type": "FeatureCollection", "id": "http://www.wikidata.org/entity/Q3558915", "name": "Q3558915", "features": [{"type": "Feature", "id": "http://data.archaeology.link/data/ancientports/632", "label": "Roman villa at Loupian", "dateprops": [], "properties": {"http://purl.org/dc/elements/1.1/created": ["2023"], "http://purl.org/dc/elements/1.1/creator": ["http://data.archaeology.link/data/spphaefen/arthur_de_graauw"], "http://www.ancientports.com/ont#date_min": ["-600"], "http://www.opengis.net/ont/geosparql#hasGeometry": ["http://data.archaeology.link/data/ancientports/632_geom"], "http://www.w3.org/1999/02/22-rdf-syntax-ns#type": ["http://www.ancientports.com/ont#VillaMaritima"], "http://www.w3.org/2000/01/rdf-schema#label": ["Roman villa at Loupian"], "http://www.w3.org/2002/07/owl#sameAs": ["http://www.wikidata.org/entity/Q3558915"], "http://www.w3.org/2004/02/skos/core#note": ["Garcia (1995)"], "http://www.wikidata.org/prop/direct/P17": ["France South"]}, "geometry": {"type": "Point", "coordinates": [3.6143, 43.4401]}}]}