{"type": "FeatureCollection", "id": "http://www.wikidata.org/entity/Q3443623", "name": "Q3443623", "features": [{"type": "Feature", "id": "http://data.archaeology.link/data/ancientports/1411_2", "label": "Villa Maritima, on the isle of Petar", "dateprops": [], "properties": {"http://purl.org/dc/elements/1.1/created": ["2023"], "http://purl.org/dc/elements/1.1/creator": ["http://data.archaeology.link/data/spphaefen/arthur_de_graauw"], "http://www.ancientports.com/ont#date_min": ["3001"], "http://www.opengis.net/ont/geosparql#hasGeometry": ["http://data.archaeology.link/data/ancientports/1411_2_geom"], "http://www.w3.org/1999/02/22-rdf-syntax-ns#type": ["http://www.ancientports.com/ont#VillaMaritima"], "http://www.w3.org/2000/01/rdf-schema#label": ["Villa Maritima, on the isle of Petar"], "http://www.w3.org/2002/07/owl#sameAs": ["http://www.wikidata.org/entity/Q3443623"], "http://www.wikidata.org/prop/direct/P17": ["http://www.wikidata.org/entity/Q224"]}, "geometry": {"type": "Point", "coordinates": [14.5505, 44.4649]}}, {"type": "Feature", "id": "http://data.archaeology.link/data/ancientports/1411_1", "label": "Basilica, on the isle of Petar", "dateprops": [], "properties": {"http://purl.org/dc/elements/1.1/created": ["2023"], "http://purl.org/dc/elements/1.1/creator": ["http://data.archaeology.link/data/spphaefen/arthur_de_graauw"], "http://www.ancientports.com/ont#date_min": ["5001"], "http://www.opengis.net/ont/geosparql#hasGeometry": ["http://data.archaeology.link/data/ancientports/1411_1_geom"], "http://www.w3.org/1999/02/22-rdf-syntax-ns#type": ["http://www.ancientports.com/ont#Harbour"], "http://www.w3.org/2000/01/rdf-schema#label": ["Basilica, on the isle of Petar"], "http://www.w3.org/2002/07/owl#sameAs": ["http://www.wikidata.org/entity/Q3443623"], "http://www.wikidata.org/prop/direct/P17": ["http://www.wikidata.org/entity/Q224"]}, "geometry": {"type": "Point", "coordinates": [14.544, 44.468]}}]}