{"type": "FeatureCollection", "id": "https://www.trismegistos.org/place/971", "name": "971", "features": [{"type": "Feature", "id": "http://data.archaeology.link/data/ancientports/1873", "label": "Agios Nektarios, near Bay of Vagionia on the isle of Poros", "dateprops": [], "properties": {"http://purl.org/dc/elements/1.1/created": ["2023"], "http://purl.org/dc/elements/1.1/creator": ["http://data.archaeology.link/data/spphaefen/arthur_de_graauw"], "http://purl.org/dc/terms/isReferencedBy": ["http://www.kalaureia.org/"], "http://www.ancientports.com/ont#date_min": ["-750"], "http://www.opengis.net/ont/geosparql#hasGeometry": ["http://data.archaeology.link/data/ancientports/1873_geom"], "http://www.w3.org/1999/02/22-rdf-syntax-ns#type": ["http://www.ancientports.com/ont#Harbour"], "http://www.w3.org/2000/01/rdf-schema#label": ["Agios Nektarios, near Bay of Vagionia on the isle of Poros"], "http://www.w3.org/2002/07/owl#sameAs": ["http://www.wikidata.org/entity/Q1443132"], "http://www.w3.org/2004/02/skos/core#note": ["Kolaiti (2016)"], "http://www.wikidata.org/prop/direct/P1584": ["http://pleiades.stoa.org/places/570325"], "http://www.wikidata.org/prop/direct/P17": ["GR: Pelop"], "http://www.wikidata.org/prop/direct/P1936": ["http://imperium.ahlfeldt.se/places/41227"], "http://www.wikidata.org/prop/direct/P1958": ["https://www.trismegistos.org/place/971"], "http://www.wikidata.org/prop/direct/P8068": ["https://topostext.org/place/375235IKal"]}, "geometry": {"type": "Point", "coordinates": [23.48393, 37.53154]}}]}