{"type": "FeatureCollection", "id": "http://pleiades.stoa.org/places/501469", "name": "501469", "features": [{"type": "Feature", "id": "http://data.archaeology.link/data/ancientports/1819", "label": "Dhafni, Daphne", "dateprops": [], "properties": {"http://purl.org/dc/elements/1.1/created": ["2023"], "http://purl.org/dc/elements/1.1/creator": ["http://data.archaeology.link/data/spphaefen/arthur_de_graauw"], "http://www.ancientports.com/ont#date_min": ["-550"], "http://www.opengis.net/ont/geosparql#hasGeometry": ["http://data.archaeology.link/data/ancientports/1819_geom"], "http://www.w3.org/1999/02/22-rdf-syntax-ns#type": ["http://www.ancientports.com/ont#Harbour"], "http://www.w3.org/2000/01/rdf-schema#label": ["Dhafni, Daphne"], "http://www.w3.org/2002/07/owl#sameAs": ["http://www.wikidata.org/entity/Q17625411"], "http://www.wikidata.org/prop/direct/P1584": ["http://pleiades.stoa.org/places/501469"], "http://www.wikidata.org/prop/direct/P17": ["GR: North-East"], "http://www.wikidata.org/prop/direct/P1936": ["http://imperium.ahlfeldt.se/places/32343"], "http://www.wikidata.org/prop/direct/P8068": ["https://topostext.org/place/402242UKle"]}, "geometry": {"type": "Point", "coordinates": [24.222, 40.21391]}}]}