{"type": "FeatureCollection", "id": "http://imperium.ahlfeldt.se/places/43320", "name": "43320", "features": [{"type": "Feature", "id": "http://data.archaeology.link/data/ancientports/3293", "label": "Yaglica K\u00f6y\u00fc, refuge shelter before sailing west around cape Uluburun", "dateprops": [], "properties": {"http://purl.org/dc/elements/1.1/created": ["2023"], "http://purl.org/dc/elements/1.1/creator": ["http://data.archaeology.link/data/spphaefen/arthur_de_graauw"], "http://www.opengis.net/ont/geosparql#hasGeometry": ["http://data.archaeology.link/data/ancientports/3293_geom"], "http://www.w3.org/1999/02/22-rdf-syntax-ns#type": ["http://www.ancientports.com/ont#Harbour"], "http://www.w3.org/2000/01/rdf-schema#label": ["Yaglica K\u00f6y\u00fc, refuge shelter before sailing west around cape Uluburun"], "http://www.w3.org/2002/07/owl#sameAs": ["http://www.wikidata.org/entity/Q573852"], "http://www.w3.org/2004/02/skos/core#note": ["Arnaud (2008)"], "http://www.w3.org/2006/time#hasTime": ["http://data.archaeology.link/data/ancientports/3293_foundation"], "http://www.wikidata.org/prop/direct/P1584": ["http://pleiades.stoa.org/places/638737"], "http://www.wikidata.org/prop/direct/P17": ["TR: South"], "http://www.wikidata.org/prop/direct/P1936": ["http://imperium.ahlfeldt.se/places/43320"]}, "geometry": {"type": "Point", "coordinates": [29.695, 36.147]}}]}