{"type": "FeatureCollection", "id": "https://www.trismegistos.org/place/14550", "name": "14550", "features": [{"type": "Feature", "id": "http://data.archaeology.link/data/ancientports/127_9", "name": "Saint David's Head oppidum, near Porthmeigan beach", "dateprops": ["begin"], "properties": {"http://purl.org/dc/elements/1.1/creator": ["http://data.archaeology.link/data/spphaefen/arthur_de_graauw"], "http://purl.org/dc/terms/isReferencedBy": ["https://www.megalithic.co.uk/article.php?sid=5994"], "http://purl.org/dc/terms/partOf": ["http://data.archaeology.link/data/ancientports/bib_deGrauw_2013_GeoDB"], "http://www.opengis.net/ont/geosparql#hasGeometry": ["http://data.archaeology.link/data/ancientports/127_9_geom"], "http://www.w3.org/1999/02/22-rdf-syntax-ns#type": ["http://www.ancientports.com/ont#Harbour"], "http://www.w3.org/2000/01/rdf-schema#label": ["Saint David's Head oppidum, near Porthmeigan beach"], "http://www.w3.org/2006/time#hasTime": ["http://data.archaeology.link/data/ancientports/127_9_foundation"], "http://www.wikidata.org/prop/direct/P17": ["http://www.wikidata.org/entity/Q145"], "http://www.wikidata.org/prop/direct/P1958": ["https://www.trismegistos.org/place/14550"], "begin": "-500"}, "geometry": {"type": "Point", "coordinates": [-5.3114, 51.9029]}}], "numberMatched": 1, "numberReturned": 1}